Workbook
Name in_rate: Parameters!$B$4
Name in_poa: Parameters!$B$5
Name in_ppy: Parameters!$B$6
Name in_idc_method: Parameters!$B$7
Name in_timing: Parameters!$B$8
Name in_cost_dp: Parameters!$B$9
Name in_out_dp: Parameters!$B$10
Name calc_crf: Parameters!$B$11
Name out_status: 'Read me'!$B$10
Name out_changed: 'Read me'!$B$11
Name out_mismatch: 'Read me'!$B$12

Sheet Read me
A1: STAF demonstration: CE/ICA calculator
A2: Cost-effectiveness and incremental cost analysis, as live formulas.
A4: Study | B4: STAF demonstration
A5: Generated by | B5: CEICA 0.1.0 (engine 1)
A6: Project digest | B6: 5d6ded045e76
A7: Discount rate | B7: 3 percent
A8: Period of analysis | B8: 50 years
A10: Status | B10: =IF((SUMPRODUCT(1*(Parameters!B4:B10<>'snap Parameters'!B4:B10))+SUMPRODUCT(1*(Parameters!B14:G14<>'snap Parameters'!B14:G14))+SUMPRODUCT(1*('STAF scores'!F10:Y12<>'snap STAF scores'!F10:Y12))+SUMPRODUCT(1*('STAF scores'!E15:Y74<>'snap STAF scores'!E15:Y74))+SUMPRODUCT(1*(Costs!D6:G15<>'snap Costs'!D6:G15))+SUMPRODUCT(1*(Costs!L6:L15<>'snap Costs'!L6:L15))+SUMPRODUCT(1*(OMRRR!F5:M19<>'snap OMRRR'!F5:M19))+SUMPRODUCT(1*(Sites!C5:C7<>'snap Sites'!C5:C7))+SUMPRODUCT(1*('Watershed plans'!AA12:AA19<>'snap Watershed plans'!AA12:AA19))+SUMPRODUCT(1*('Watershed summary'!K50:L89<>'snap Watershed summary'!K50:L89))+SUMPRODUCT(1*('Watershed summary'!B93:B93<>'snap Watershed summary'!B93:B93)))=0,IF((SUMPRODUCT(1*(ABS(Summary!G5:G14-'snap Summary'!G5:G14)>1e-06))+SUMPRODUCT(1*(ABS(Summary!L5:L14-'snap Summary'!L5:L14)>0.0001))+SUMPRODUCT(1*('Site CE-ICA'!L6:L9<>'snap Site CE-ICA'!L6:L9))+SUMPRODUCT(1*('Site CE-ICA'!P6:P9<>'snap Site CE-ICA'!P6:P9))+SUMPRODUCT(1*('Site CE-ICA'!L12:L14<>'snap Site CE-ICA'!L12:L14))+SUMPRODUCT(1*('Site CE-ICA'!P12:P14<>'snap Site CE-ICA'!P12:P14))+SUMPRODUCT(1*('Site CE-ICA'!L17:L19<>'snap Site CE-ICA'!L17:L19))+SUMPRODUCT(1*('Site CE-ICA'!P17:P19<>'snap Site CE-ICA'!P17:P19))+SUMPRODUCT(1*('Watershed plans'!O12:O19<>'snap Watershed plans'!O12:O19))+SUMPRODUCT(1*('Watershed plans'!S12:S19<>'snap Watershed plans'!S12:S19)))=0,"Unchanged: matches the CEICA export","ERROR: results differ from the export although no input changed"),"Edited: "&(SUMPRODUCT(1*(Parameters!B4:B10<>'snap Parameters'!B4:B10))+SUMPRODUCT(1*(Parameters!B14:G14<>'snap Parameters'!B14:G14))+SUMPRODUCT(1*('STAF scores'!F10:Y12<>'snap STAF scores'!F10:Y12))+SUMPRODUCT(1*('STAF scores'!E15:Y74<>'snap STAF scores'!E15:Y74))+SUMPRODUCT(1*(Costs!D6:G15<>'snap Costs'!D6:G15))+SUMPRODUCT(1*(Costs!L6:L15<>'snap Costs'!L6:L15))+SUMPRODUCT(1*(OMRRR!F5:M19<>'snap OMRRR'!F5:M19))+SUMPRODUCT(1*(Sites!C5:C7<>'snap Sites'!C5:C7))+SUMPRODUCT(1*('Watershed plans'!AA12:AA19<>'snap Watershed plans'!AA12:AA19))+SUMPRODUCT(1*('Watershed summary'!K50:L89<>'snap Watershed summary'!K50:L89))+SUMPRODUCT(1*('Watershed summary'!B93:B93<>'snap Watershed summary'!B93:B93)))&" input cells changed since the export")
A11: Inputs changed | B11: =(SUMPRODUCT(1*(Parameters!B4:B10<>'snap Parameters'!B4:B10))+SUMPRODUCT(1*(Parameters!B14:G14<>'snap Parameters'!B14:G14))+SUMPRODUCT(1*('STAF scores'!F10:Y12<>'snap STAF scores'!F10:Y12))+SUMPRODUCT(1*('STAF scores'!E15:Y74<>'snap STAF scores'!E15:Y74))+SUMPRODUCT(1*(Costs!D6:G15<>'snap Costs'!D6:G15))+SUMPRODUCT(1*(Costs!L6:L15<>'snap Costs'!L6:L15))+SUMPRODUCT(1*(OMRRR!F5:M19<>'snap OMRRR'!F5:M19))+SUMPRODUCT(1*(Sites!C5:C7<>'snap Sites'!C5:C7))+SUMPRODUCT(1*('Watershed plans'!AA12:AA19<>'snap Watershed plans'!AA12:AA19))+SUMPRODUCT(1*('Watershed summary'!K50:L89<>'snap Watershed summary'!K50:L89))+SUMPRODUCT(1*('Watershed summary'!B93:B93<>'snap Watershed summary'!B93:B93)))
A12: Results that differ from the export | B12: =(SUMPRODUCT(1*(ABS(Summary!G5:G14-'snap Summary'!G5:G14)>1e-06))+SUMPRODUCT(1*(ABS(Summary!L5:L14-'snap Summary'!L5:L14)>0.0001))+SUMPRODUCT(1*('Site CE-ICA'!L6:L9<>'snap Site CE-ICA'!L6:L9))+SUMPRODUCT(1*('Site CE-ICA'!P6:P9<>'snap Site CE-ICA'!P6:P9))+SUMPRODUCT(1*('Site CE-ICA'!L12:L14<>'snap Site CE-ICA'!L12:L14))+SUMPRODUCT(1*('Site CE-ICA'!P12:P14<>'snap Site CE-ICA'!P12:P14))+SUMPRODUCT(1*('Site CE-ICA'!L17:L19<>'snap Site CE-ICA'!L17:L19))+SUMPRODUCT(1*('Site CE-ICA'!P17:P19<>'snap Site CE-ICA'!P17:P19))+SUMPRODUCT(1*('Watershed plans'!O12:O19<>'snap Watershed plans'!O12:O19))+SUMPRODUCT(1*('Watershed plans'!S12:S19<>'snap Watershed plans'!S12:S19)))
A14: How to use
A15: - Orange cells are inputs; grey cells are formulas. Sheets are protected (password 'ceica') only to prevent accidental edits.
A16: - Change any orange cell: annualization, site CE/ICA, the watershed plans and the summary update. Changed inputs turn yellow.
A17: - To add sites, alternatives or years, make the change in CEICA and export again.
A18: - Import this workbook in CEICA to bring your changes back into the project.
A20: Legend
A21: Input
A22: Formula
A23: Changed since export

Sheet Parameters
A1: Parameters
A2: Economics and conventions. Orange cells are inputs.
A3: Parameter | B3: Value
A4: Discount rate | B4: 0.03
A5: Period of analysis (years) | B5: 50
A6: Interest during construction: periods per year | B6: 12
A7: Interest during construction: spending in each period (END, MIDDLE or START) | B7: END
A8: OMRRR discounting (END_OF_YEAR or MID_YEAR) | B8: END_OF_YEAR
A9: Cost decimals kept for CE/ICA | B9: 2
A10: Output decimals kept for CE/ICA | B10: 3
A11: Capital recovery factor | B11: =IF(in_rate=0,1/in_poa,in_rate*(1+in_rate)^in_poa/((1+in_rate)^in_poa-1))
A13: Target years | B13: Year 1 | C13: Year 2 | D13: Year 3 | E13: Year 4 | F13: Year 5 | G13: Year 6
A14: Years (first to last) | B14: 0 | C14: 1 | D14: 5 | E14: 10 | F14: 25 | G14: 50

Sheet STAF scores
A1: STAF scores: function scores (0 to 15) at each target year
A2: Outcome mapping STAF documentation, EASI and DEEP (A): weight 1 for a direct effect, 0.1 for an indirect one. A function marked 0 under Assessed is left out of both sums at that site.
B4: Weights | F4: Catchment hydrology | G4: Surface water storage | H4: Reach inflow | I4: Streamflow regime | J4: Low flow and baseflow dynamics | K4: High flow dynamics | L4: Floodplain connectivity | M4: Hyporheic connectivity | N4: Channel evolution | O4: Channel and floodplain dynamics | P4: Sediment continuity | Q4: Bed composition and large wood | R4: Light & thermal regime | S4: Carbon processing | T4: Nutrient cycling | U4: Water & soil quality | V4: Habitat provision | W4: Population support | X4: Community dynamics | Y4: Watershed connectivity
B5: Physical | F5: 1 | G5: 1 | H5: 1 | I5: 1 | J5: 1 | K5: 1 | L5: 1 | M5: 1 | N5: 1 | O5: 1 | P5: 1 | Q5: 1 | R5: 0 | S5: 0 | T5: 0.1 | U5: 0.1 | V5: 0 | W5: 0.1 | X5: 0.1 | Y5: 0.1
B6: Chemical | F6: 0.1 | G6: 0.1 | H6: 0.1 | I6: 0.1 | J6: 0.1 | K6: 0.1 | L6: 0.1 | M6: 0.1 | N6: 0.1 | O6: 0.1 | P6: 0.1 | Q6: 0.1 | R6: 1 | S6: 1 | T6: 1 | U6: 1 | V6: 0 | W6: 0.1 | X6: 0.1 | Y6: 0
B7: Biological | F7: 0.1 | G7: 0.1 | H7: 0.1 | I7: 0.1 | J7: 0.1 | K7: 0.1 | L7: 0.1 | M7: 0.1 | N7: 0.1 | O7: 0.1 | P7: 0.1 | Q7: 0.1 | R7: 0.1 | S7: 0.1 | T7: 0.1 | U7: 0.1 | V7: 1 | W7: 1 | X7: 1 | Y7: 1
B9: Assessed (1) or not (0) | F9: Catchment hydrology | G9: Surface water storage | H9: Reach inflow | I9: Streamflow regime | J9: Low flow and baseflow dynamics | K9: High flow dynamics | L9: Floodplain connectivity | M9: Hyporheic connectivity | N9: Channel evolution | O9: Channel and floodplain dynamics | P9: Sediment continuity | Q9: Bed composition and large wood | R9: Light & thermal regime | S9: Carbon processing | T9: Nutrient cycling | U9: Water & soil quality | V9: Habitat provision | W9: Population support | X9: Community dynamics | Y9: Watershed connectivity
B10: R1 | F10: 1 | G10: 1 | H10: 1 | I10: 1 | J10: 1 | K10: 1 | L10: 1 | M10: 1 | N10: 1 | O10: 1 | P10: 1 | Q10: 1 | R10: 1 | S10: 1 | T10: 1 | U10: 1 | V10: 1 | W10: 1 | X10: 1 | Y10: 1
B11: R2 | F11: 1 | G11: 1 | H11: 1 | I11: 1 | J11: 1 | K11: 1 | L11: 1 | M11: 1 | N11: 1 | O11: 1 | P11: 1 | Q11: 1 | R11: 1 | S11: 1 | T11: 1 | U11: 1 | V11: 1 | W11: 1 | X11: 1 | Y11: 1
B12: R3 | F12: 1 | G12: 1 | H12: 1 | I12: 1 | J12: 1 | K12: 1 | L12: 1 | M12: 1 | N12: 1 | O12: 1 | P12: 1 | Q12: 1 | R12: 1 | S12: 1 | T12: 1 | U12: 1 | V12: 1 | W12: 1 | X12: 1 | Y12: 0
B14: Site | C14: Alternative | D14: Year | E14: Quantity (ft) | F14: Catchment hydrology | G14: Surface water storage | H14: Reach inflow | I14: Streamflow regime | J14: Low flow and baseflow dynamics | K14: High flow dynamics | L14: Floodplain connectivity | M14: Hyporheic connectivity | N14: Channel evolution | O14: Channel and floodplain dynamics | P14: Sediment continuity | Q14: Bed composition and large wood | R14: Light & thermal regime | S14: Carbon processing | T14: Nutrient cycling | U14: Water & soil quality | V14: Habitat provision | W14: Population support | X14: Community dynamics | Y14: Watershed connectivity
B15: R1 | C15: FWOP | D15: =Parameters!$B$14 | E15: 1000 | F15: 8 | G15: 15 | H15: 7 | I15: 12 | J15: 4 | K15: 11 | L15: 9 | M15: 13 | N15: 5 | O15: 10 | P15: 6 | Q15: 5 | R15: 12 | S15: 13 | T15: 13 | U15: 10 | V15: 2 | W15: 3 | X15: 4 | Y15: 1
B16: R1 | C16: FWOP | D16: =Parameters!$C$14 | E16: 1000 | F16: 8 | G16: 15 | H16: 7 | I16: 12 | J16: 4 | K16: 11 | L16: 9 | M16: 13 | N16: 5 | O16: 10 | P16: 6 | Q16: 5 | R16: 12 | S16: 13 | T16: 13 | U16: 10 | V16: 2 | W16: 3 | X16: 4 | Y16: 1
B17: R1 | C17: FWOP | D17: =Parameters!$D$14 | E17: 1000 | F17: 8 | G17: 15 | H17: 7 | I17: 12 | J17: 4 | K17: 11 | L17: 9 | M17: 13 | N17: 4.9 | O17: 10 | P17: 6 | Q17: 4.9 | R17: 12 | S17: 13 | T17: 13 | U17: 10 | V17: 2 | W17: 2.9 | X17: 3.9 | Y17: 1
B18: R1 | C18: FWOP | D18: =Parameters!$E$14 | E18: 1000 | F18: 8 | G18: 15 | H18: 7 | I18: 12 | J18: 4 | K18: 11 | L18: 9 | M18: 13 | N18: 4.8 | O18: 10 | P18: 6 | Q18: 4.8 | R18: 12 | S18: 13 | T18: 13 | U18: 10 | V18: 2 | W18: 2.8 | X18: 3.8 | Y18: 1
B19: R1 | C19: FWOP | D19: =Parameters!$F$14 | E19: 1000 | F19: 8 | G19: 15 | H19: 7 | I19: 12 | J19: 4 | K19: 11 | L19: 9 | M19: 13 | N19: 4.5 | O19: 10 | P19: 6 | Q19: 4.5 | R19: 12 | S19: 13 | T19: 13 | U19: 10 | V19: 2 | W19: 2.5 | X19: 3.5 | Y19: 1
B20: R1 | C20: FWOP | D20: =Parameters!$G$14 | E20: 1000 | F20: 8 | G20: 15 | H20: 7 | I20: 12 | J20: 4 | K20: 11 | L20: 9 | M20: 13 | N20: 4 | O20: 10 | P20: 6 | Q20: 4 | R20: 12 | S20: 13 | T20: 13 | U20: 10 | V20: 2 | W20: 2 | X20: 3 | Y20: 1
B21: R1 | C21: A1 | D21: =Parameters!$B$14 | E21: 1000 | F21: 8 | G21: 15 | H21: 7 | I21: 12 | J21: 4 | K21: 11 | L21: 9 | M21: 13 | N21: 5 | O21: 10 | P21: 6 | Q21: 5 | R21: 12 | S21: 13 | T21: 13 | U21: 10 | V21: 2 | W21: 3 | X21: 4 | Y21: 1
B22: R1 | C22: A1 | D22: =Parameters!$C$14 | E22: 1000 | F22: 8 | G22: 15 | H22: 7 | I22: 12 | J22: 4 | K22: 11 | L22: 9 | M22: 13 | N22: 5 | O22: 10 | P22: 6 | Q22: 5 | R22: 12.2 | S22: 13.1 | T22: 13.1 | U22: 10.2 | V22: 2 | W22: 3 | X22: 4 | Y22: 1
B23: R1 | C23: A1 | D23: =Parameters!$D$14 | E23: 1000 | F23: 8 | G23: 15 | H23: 7 | I23: 12 | J23: 4 | K23: 11 | L23: 9 | M23: 13 | N23: 4.9 | O23: 10 | P23: 6 | Q23: 4.9 | R23: 13 | S23: 13.5 | T23: 13.5 | U23: 11 | V23: 2.8 | W23: 3.4 | X23: 4.4 | Y23: 1
B24: R1 | C24: A1 | D24: =Parameters!$E$14 | E24: 1000 | F24: 8 | G24: 15 | H24: 7 | I24: 12 | J24: 4 | K24: 11 | L24: 9 | M24: 13 | N24: 4.8 | O24: 10 | P24: 6 | Q24: 4.8 | R24: 13.6 | S24: 13.8 | T24: 13.8 | U24: 11.6 | V24: 3.4 | W24: 3.7 | X24: 4.7 | Y24: 1
B25: R1 | C25: A1 | D25: =Parameters!$F$14 | E25: 1000 | F25: 8 | G25: 15 | H25: 7 | I25: 12 | J25: 4 | K25: 11 | L25: 9 | M25: 13 | N25: 4.5 | O25: 10 | P25: 6 | Q25: 4.5 | R25: 14 | S25: 14 | T25: 14 | U25: 12 | V25: 4 | W25: 4 | X25: 5 | Y25: 1
B26: R1 | C26: A1 | D26: =Parameters!$G$14 | E26: 1000 | F26: 8 | G26: 15 | H26: 7 | I26: 12 | J26: 4 | K26: 11 | L26: 9 | M26: 13 | N26: 4 | O26: 10 | P26: 6 | Q26: 4 | R26: 14 | S26: 14 | T26: 14 | U26: 12 | V26: 4 | W26: 4 | X26: 5 | Y26: 1
B27: R1 | C27: A2 | D27: =Parameters!$B$14 | E27: 1000 | F27: 8 | G27: 15 | H27: 7 | I27: 12 | J27: 4 | K27: 11 | L27: 9 | M27: 13 | N27: 5 | O27: 10 | P27: 6 | Q27: 5 | R27: 12 | S27: 13 | T27: 13 | U27: 10 | V27: 2 | W27: 3 | X27: 4 | Y27: 1
B28: R1 | C28: A2 | D28: =Parameters!$C$14 | E28: 1000 | F28: 8 | G28: 15 | H28: 7 | I28: 12 | J28: 4 | K28: 12.6 | L28: 12.2 | M28: 13.8 | N28: 5 | O28: 11.6 | P28: 6 | Q28: 5 | R28: 12.2 | S28: 13.1 | T28: 13.1 | U28: 10.2 | V28: 2 | W28: 3 | X28: 4 | Y28: 1
B29: R1 | C29: A2 | D29: =Parameters!$D$14 | E29: 1000 | F29: 8 | G29: 15 | H29: 7 | I29: 12 | J29: 4 | K29: 13 | L29: 13 | M29: 14 | N29: 5 | O29: 12 | P29: 6 | Q29: 5 | R29: 13 | S29: 13.5 | T29: 13.5 | U29: 11 | V29: 4 | W29: 4.2 | X29: 5.2 | Y29: 1
B30: R1 | C30: A2 | D30: =Parameters!$E$14 | E30: 1000 | F30: 8 | G30: 15 | H30: 7 | I30: 12 | J30: 4 | K30: 13 | L30: 13 | M30: 14 | N30: 5 | O30: 12 | P30: 6 | Q30: 5 | R30: 13.6 | S30: 13.8 | T30: 13.8 | U30: 11.6 | V30: 5.5 | W30: 5.1 | X30: 6.1 | Y30: 1
B31: R1 | C31: A2 | D31: =Parameters!$F$14 | E31: 1000 | F31: 8 | G31: 15 | H31: 7 | I31: 12 | J31: 4 | K31: 13 | L31: 13 | M31: 14 | N31: 5 | O31: 12 | P31: 6 | Q31: 5 | R31: 14 | S31: 14 | T31: 14 | U31: 12 | V31: 7 | W31: 6 | X31: 7 | Y31: 1
B32: R1 | C32: A2 | D32: =Parameters!$G$14 | E32: 1000 | F32: 8 | G32: 15 | H32: 7 | I32: 12 | J32: 4 | K32: 13 | L32: 13 | M32: 14 | N32: 5 | O32: 12 | P32: 6 | Q32: 5 | R32: 14 | S32: 14 | T32: 14 | U32: 12 | V32: 7 | W32: 6 | X32: 7 | Y32: 1
B33: R1 | C33: A3 | D33: =Parameters!$B$14 | E33: 1000 | F33: 8 | G33: 15 | H33: 7 | I33: 12 | J33: 4 | K33: 11 | L33: 9 | M33: 13 | N33: 5 | O33: 10 | P33: 6 | Q33: 5 | R33: 12 | S33: 13 | T33: 13 | U33: 10 | V33: 2 | W33: 3 | X33: 4 | Y33: 1
B34: R1 | C34: A3 | D34: =Parameters!$C$14 | E34: 1000 | F34: 8 | G34: 15 | H34: 7 | I34: 12 | J34: 6.4 | K34: 12.6 | L34: 12.2 | M34: 13.8 | N34: 5 | O34: 11.6 | P34: 7.6 | Q34: 9 | R34: 12.2 | S34: 13.1 | T34: 13.1 | U34: 10.2 | V34: 2 | W34: 3 | X34: 4 | Y34: 1
B35: R1 | C35: A3 | D35: =Parameters!$D$14 | E35: 1000 | F35: 8 | G35: 15 | H35: 7 | I35: 12 | J35: 7 | K35: 13 | L35: 13 | M35: 14 | N35: 5 | O35: 12 | P35: 8 | Q35: 10 | R35: 13 | S35: 13.5 | T35: 13.5 | U35: 11 | V35: 5.2 | W35: 5 | X35: 5.6 | Y35: 1
B36: R1 | C36: A3 | D36: =Parameters!$E$14 | E36: 1000 | F36: 8 | G36: 15 | H36: 7 | I36: 12 | J36: 7 | K36: 13 | L36: 13 | M36: 14 | N36: 5 | O36: 12 | P36: 8 | Q36: 10 | R36: 13.6 | S36: 13.8 | T36: 13.8 | U36: 11.6 | V36: 7.6 | W36: 6.5 | X36: 6.8 | Y36: 1
B37: R1 | C37: A3 | D37: =Parameters!$F$14 | E37: 1000 | F37: 8 | G37: 15 | H37: 7 | I37: 12 | J37: 7 | K37: 13 | L37: 13 | M37: 14 | N37: 5 | O37: 12 | P37: 8 | Q37: 10 | R37: 14 | S37: 14 | T37: 14 | U37: 12 | V37: 10 | W37: 8 | X37: 8 | Y37: 1
B38: R1 | C38: A3 | D38: =Parameters!$G$14 | E38: 1000 | F38: 8 | G38: 15 | H38: 7 | I38: 12 | J38: 7 | K38: 13 | L38: 13 | M38: 14 | N38: 5 | O38: 12 | P38: 8 | Q38: 10 | R38: 14 | S38: 14 | T38: 14 | U38: 12 | V38: 10 | W38: 8 | X38: 8 | Y38: 1
B39: R2 | C39: FWOP | D39: =Parameters!$B$14 | E39: 2400 | F39: 3 | G39: 4 | H39: 3 | I39: 4 | J39: 3 | K39: 3 | L39: 2 | M39: 4 | N39: 3 | O39: 3 | P39: 4 | Q39: 3 | R39: 5 | S39: 5 | T39: 6 | U39: 4 | V39: 2 | W39: 2 | X39: 2 | Y39: 3
B40: R2 | C40: FWOP | D40: =Parameters!$C$14 | E40: 2400 | F40: 3 | G40: 4 | H40: 3 | I40: 4 | J40: 3 | K40: 3 | L40: 2 | M40: 4 | N40: 3 | O40: 3 | P40: 4 | Q40: 3 | R40: 5 | S40: 5 | T40: 6 | U40: 4 | V40: 2 | W40: 2 | X40: 2 | Y40: 3
B41: R2 | C41: FWOP | D41: =Parameters!$D$14 | E41: 2400 | F41: 3 | G41: 4 | H41: 3 | I41: 4 | J41: 3 | K41: 3 | L41: 2 | M41: 4 | N41: 2.9 | O41: 2.9 | P41: 4 | Q41: 3 | R41: 5 | S41: 5 | T41: 6 | U41: 3.9 | V41: 2 | W41: 2 | X41: 2 | Y41: 3
B42: R2 | C42: FWOP | D42: =Parameters!$E$14 | E42: 2400 | F42: 3 | G42: 4 | H42: 3 | I42: 4 | J42: 3 | K42: 3 | L42: 2 | M42: 4 | N42: 2.8 | O42: 2.8 | P42: 4 | Q42: 3 | R42: 5 | S42: 5 | T42: 6 | U42: 3.8 | V42: 2 | W42: 2 | X42: 2 | Y42: 3
B43: R2 | C43: FWOP | D43: =Parameters!$F$14 | E43: 2400 | F43: 3 | G43: 4 | H43: 3 | I43: 4 | J43: 3 | K43: 3 | L43: 2 | M43: 4 | N43: 2.5 | O43: 2.5 | P43: 4 | Q43: 3 | R43: 5 | S43: 5 | T43: 6 | U43: 3.5 | V43: 2 | W43: 2 | X43: 2 | Y43: 3
B44: R2 | C44: FWOP | D44: =Parameters!$G$14 | E44: 2400 | F44: 3 | G44: 4 | H44: 3 | I44: 4 | J44: 3 | K44: 3 | L44: 2 | M44: 4 | N44: 2 | O44: 2 | P44: 4 | Q44: 3 | R44: 5 | S44: 5 | T44: 6 | U44: 3 | V44: 2 | W44: 2 | X44: 2 | Y44: 3
B45: R2 | C45: A1 | D45: =Parameters!$B$14 | E45: 2400 | F45: 12 | G45: 4 | H45: 3 | I45: 4 | J45: 3 | K45: 3 | L45: 2 | M45: 4 | N45: 3 | O45: 3 | P45: 4 | Q45: 3 | R45: 5 | S45: 5 | T45: 6 | U45: 4 | V45: 2 | W45: 2 | X45: 2 | Y45: 3
B46: R2 | C46: A1 | D46: =Parameters!$C$14 | E46: 2400 | F46: 3 | G46: 4 | H46: 3 | I46: 4 | J46: 3 | K46: 3 | L46: 2 | M46: 4 | N46: 3 | O46: 6.2 | P46: 5.6 | Q46: 3 | R46: 5.4 | S46: 5.3 | T46: 6.2 | U46: 4.2 | V46: 2 | W46: 2 | X46: 2 | Y46: 3
B47: R2 | C47: A1 | D47: =Parameters!$D$14 | E47: 2400 | F47: 3 | G47: 4 | H47: 3 | I47: 4 | J47: 3 | K47: 3 | L47: 2 | M47: 4 | N47: 2.9 | O47: 7 | P47: 6 | Q47: 3 | R47: 7 | S47: 6.5 | T47: 7 | U47: 5 | V47: 3.2 | W47: 2.4 | X47: 2.4 | Y47: 3
B48: R2 | C48: A1 | D48: =Parameters!$E$14 | E48: 2400 | F48: 3 | G48: 4 | H48: 3 | I48: 4 | J48: 3 | K48: 3 | L48: 2 | M48: 4 | N48: 2.8 | O48: 7 | P48: 6 | Q48: 3 | R48: 8.2 | S48: 7.4 | T48: 7.6 | U48: 5.6 | V48: 4.1 | W48: 2.7 | X48: 2.7 | Y48: 3
B49: R2 | C49: A1 | D49: =Parameters!$F$14 | E49: 2400 | F49: 3 | G49: 4 | H49: 3 | I49: 4 | J49: 3 | K49: 3 | L49: 2 | M49: 4 | N49: 2.5 | O49: 7 | P49: 6 | Q49: 3 | R49: 9 | S49: 8 | T49: 8 | U49: 6 | V49: 5 | W49: 3 | X49: 3 | Y49: 3
B50: R2 | C50: A1 | D50: =Parameters!$G$14 | E50: 2400 | F50: 3 | G50: 4 | H50: 3 | I50: 4 | J50: 3 | K50: 3 | L50: 2 | M50: 4 | N50: 2 | O50: 7 | P50: 6 | Q50: 3 | R50: 9 | S50: 8 | T50: 8 | U50: 6 | V50: 5 | W50: 3 | X50: 3 | Y50: 3
B51: R2 | C51: A2 | D51: =Parameters!$B$14 | E51: 2400 | F51: 3 | G51: 4 | H51: 3 | I51: 4 | J51: 3 | K51: 3 | L51: 2 | M51: 4 | N51: 3 | O51: 3 | P51: 4 | Q51: 3 | R51: 5 | S51: 5 | T51: 6 | U51: 4 | V51: 2 | W51: 2 | X51: 2 | Y51: 3
B52: R2 | C52: A2 | D52: =Parameters!$C$14 | E52: 2400 | F52: 3 | G52: 4 | H52: 3 | I52: 4 | J52: 5.4 | K52: 7 | L52: 8.4 | M52: 8 | N52: 7 | O52: 8.6 | P52: 7.2 | Q52: 7.8 | R52: 5.6 | S52: 5.5 | T52: 6.4 | U52: 4.4 | V52: 2 | W52: 2 | X52: 2 | Y52: 3
B53: R2 | C53: A2 | D53: =Parameters!$D$14 | E53: 2400 | F53: 3 | G53: 4 | H53: 3 | I53: 4 | J53: 6 | K53: 8 | L53: 10 | M53: 9 | N53: 8 | O53: 10 | P53: 8 | Q53: 9 | R53: 8 | S53: 7.5 | T53: 8 | U53: 6 | V53: 4.8 | W53: 3.6 | X53: 3.6 | Y53: 3.8
B54: R2 | C54: A2 | D54: =Parameters!$E$14 | E54: 2400 | F54: 3 | G54: 4 | H54: 3 | I54: 4 | J54: 6 | K54: 8 | L54: 10 | M54: 9 | N54: 8 | O54: 10 | P54: 8 | Q54: 9 | R54: 9.8 | S54: 9 | T54: 9.2 | U54: 7.2 | V54: 6.9 | W54: 4.8 | X54: 4.8 | Y54: 4.4
B55: R2 | C55: A2 | D55: =Parameters!$F$14 | E55: 2400 | F55: 3 | G55: 4 | H55: 3 | I55: 4 | J55: 6 | K55: 8 | L55: 10 | M55: 9 | N55: 8 | O55: 10 | P55: 8 | Q55: 9 | R55: 11 | S55: 10 | T55: 10 | U55: 8 | V55: 9 | W55: 6 | X55: 6 | Y55: 5
B56: R2 | C56: A2 | D56: =Parameters!$G$14 | E56: 2400 | F56: 3 | G56: 4 | H56: 3 | I56: 4 | J56: 6 | K56: 8 | L56: 10 | M56: 9 | N56: 8 | O56: 10 | P56: 8 | Q56: 9 | R56: 11 | S56: 10 | T56: 10 | U56: 8 | V56: 9 | W56: 6 | X56: 6 | Y56: 5
B57: R3 | C57: FWOP | D57: =Parameters!$B$14 | E57: 1600 | F57: 11 | G57: 12 | H57: 10 | I57: 11 | J57: 9 | K57: 10 | L57: 10 | M57: 11 | N57: 9 | O57: 8 | P57: 8 | Q57: 7 | R57: 10 | S57: 11 | T57: 10 | U57: 9 | V57: 6 | W57: 5 | X57: 6
B58: R3 | C58: FWOP | D58: =Parameters!$C$14 | E58: 1600 | F58: 11 | G58: 12 | H58: 10 | I58: 11 | J58: 9 | K58: 10 | L58: 10 | M58: 11 | N58: 9 | O58: 8 | P58: 8 | Q58: 7 | R58: 10 | S58: 11 | T58: 10 | U58: 9 | V58: 6 | W58: 5 | X58: 6
B59: R3 | C59: FWOP | D59: =Parameters!$D$14 | E59: 1600 | F59: 11 | G59: 12 | H59: 10 | I59: 11 | J59: 9 | K59: 10 | L59: 10 | M59: 11 | N59: 9 | O59: 8 | P59: 8 | Q59: 7 | R59: 10 | S59: 11 | T59: 10 | U59: 8.9 | V59: 5.9 | W59: 5 | X59: 6
B60: R3 | C60: FWOP | D60: =Parameters!$E$14 | E60: 1600 | F60: 11 | G60: 12 | H60: 10 | I60: 11 | J60: 9 | K60: 10 | L60: 10 | M60: 11 | N60: 9 | O60: 8 | P60: 8 | Q60: 7 | R60: 10 | S60: 11 | T60: 10 | U60: 8.8 | V60: 5.8 | W60: 5 | X60: 6
B61: R3 | C61: FWOP | D61: =Parameters!$F$14 | E61: 1600 | F61: 11 | G61: 12 | H61: 10 | I61: 11 | J61: 9 | K61: 10 | L61: 10 | M61: 11 | N61: 9 | O61: 8 | P61: 8 | Q61: 7 | R61: 10 | S61: 11 | T61: 10 | U61: 8.5 | V61: 5.5 | W61: 5 | X61: 6
B62: R3 | C62: FWOP | D62: =Parameters!$G$14 | E62: 1600 | F62: 11 | G62: 12 | H62: 10 | I62: 11 | J62: 9 | K62: 10 | L62: 10 | M62: 11 | N62: 9 | O62: 8 | P62: 8 | Q62: 7 | R62: 10 | S62: 11 | T62: 10 | U62: 8 | V62: 5 | W62: 5 | X62: 6
B63: R3 | C63: A1 | D63: =Parameters!$B$14 | E63: 1600 | F63: 11 | G63: 12 | H63: 10 | I63: 11 | J63: 9 | K63: 10 | L63: 10 | M63: 11 | N63: 9 | O63: 8 | P63: 8 | Q63: 7 | R63: 10 | S63: 11 | T63: 10 | U63: 9 | V63: 6 | W63: 5 | X63: 6
B64: R3 | C64: A1 | D64: =Parameters!$C$14 | E64: 1600 | F64: 11 | G64: 12 | H64: 10 | I64: 11 | J64: 9 | K64: 10 | L64: 10 | M64: 11 | N64: 9 | O64: 9.6 | P64: 9.6 | Q64: 7 | R64: 10.3 | S64: 11.1 | T64: 10.2 | U64: 9.3 | V64: 6 | W64: 5 | X64: 6
B65: R3 | C65: A1 | D65: =Parameters!$D$14 | E65: 1600 | F65: 11 | G65: 12 | H65: 10 | I65: 11 | J65: 9 | K65: 10 | L65: 10 | M65: 11 | N65: 9 | O65: 10 | P65: 10 | Q65: 7 | R65: 11.5 | S65: 11.5 | T65: 11 | U65: 10.5 | V65: 7.2 | W65: 5.8 | X65: 6.8
B66: R3 | C66: A1 | D66: =Parameters!$E$14 | E66: 1600 | F66: 11 | G66: 12 | H66: 10 | I66: 11 | J66: 9 | K66: 10 | L66: 10 | M66: 11 | N66: 9 | O66: 10 | P66: 10 | Q66: 7 | R66: 12.4 | S66: 11.8 | T66: 11.6 | U66: 11.4 | V66: 8.1 | W66: 6.4 | X66: 7.4
B67: R3 | C67: A1 | D67: =Parameters!$F$14 | E67: 1600 | F67: 11 | G67: 12 | H67: 10 | I67: 11 | J67: 9 | K67: 10 | L67: 10 | M67: 11 | N67: 9 | O67: 10 | P67: 10 | Q67: 7 | R67: 13 | S67: 12 | T67: 12 | U67: 12 | V67: 9 | W67: 7 | X67: 8
B68: R3 | C68: A1 | D68: =Parameters!$G$14 | E68: 1600 | F68: 11 | G68: 12 | H68: 10 | I68: 11 | J68: 9 | K68: 10 | L68: 10 | M68: 11 | N68: 9 | O68: 10 | P68: 10 | Q68: 7 | R68: 13 | S68: 12 | T68: 12 | U68: 12 | V68: 9 | W68: 7 | X68: 8
B69: R3 | C69: A2 | D69: =Parameters!$B$14 | E69: 1600 | F69: 11 | G69: 12 | H69: 10 | I69: 11 | J69: 9 | K69: 10 | L69: 10 | M69: 11 | N69: 9 | O69: 8 | P69: 8 | Q69: 7 | R69: 10 | S69: 11 | T69: 10 | U69: 9 | V69: 6 | W69: 5 | X69: 6
B70: R3 | C70: A2 | D70: =Parameters!$C$14 | E70: 1600 | F70: 11 | G70: 12 | H70: 10 | I70: 11 | J70: 9 | K70: 10 | L70: 10 | M70: 11 | N70: 9 | O70: 9.6 | P70: 11.2 | Q70: 9.4 | R70: 10.3 | S70: 11.1 | T70: 10.2 | U70: 9.3 | V70: 6 | W70: 5 | X70: 6
B71: R3 | C71: A2 | D71: =Parameters!$D$14 | E71: 1600 | F71: 11 | G71: 12 | H71: 10 | I71: 11 | J71: 9 | K71: 10 | L71: 10 | M71: 11 | N71: 9 | O71: 10 | P71: 12 | Q71: 10 | R71: 11.5 | S71: 11.5 | T71: 11 | U71: 10.5 | V71: 7.2 | W71: 6.6 | X71: 7.2
B72: R3 | C72: A2 | D72: =Parameters!$E$14 | E72: 1600 | F72: 11 | G72: 12 | H72: 10 | I72: 11 | J72: 9 | K72: 10 | L72: 10 | M72: 11 | N72: 9 | O72: 10 | P72: 12 | Q72: 10 | R72: 12.4 | S72: 11.8 | T72: 11.6 | U72: 11.4 | V72: 8.1 | W72: 7.8 | X72: 8.1
B73: R3 | C73: A2 | D73: =Parameters!$F$14 | E73: 1600 | F73: 11 | G73: 12 | H73: 10 | I73: 11 | J73: 9 | K73: 10 | L73: 10 | M73: 11 | N73: 9 | O73: 10 | P73: 12 | Q73: 10 | R73: 13 | S73: 12 | T73: 12 | U73: 12 | V73: 9 | W73: 9 | X73: 9
B74: R3 | C74: A2 | D74: =Parameters!$G$14 | E74: 1600 | F74: 11 | G74: 12 | H74: 10 | I74: 11 | J74: 9 | K74: 10 | L74: 10 | M74: 11 | N74: 9 | O74: 10 | P74: 12 | Q74: 10 | R74: 13 | S74: 12 | T74: 12 | U74: 12 | V74: 9 | W74: 9 | X74: 9

Sheet STAF roll-up
A1: STAF roll-up: sub-indices, Ecosystem Condition Index and condition units
A2: Each row matches the same row of STAF scores. Condition units = ECI x quantity; the Benefits sheet averages them over the period.
B4: Site | C4: Alternative | D4: Year | E4: Physical | F4: Chemical | G4: Biological | H4: Blank scores | I4: ECI | J4: Condition | K4: Quantity (ft) | L4: Condition units (CU)
B5: ='STAF scores'!B15 | C5: ='STAF scores'!C15 | D5: ='STAF scores'!D15 | E5: =IF(SUMPRODUCT('STAF scores'!$F$5:$Y$5,'STAF scores'!$F$10:$Y$10)>0,SUMPRODUCT('STAF scores'!F15:Y15,'STAF scores'!$F$5:$Y$5,'STAF scores'!$F$10:$Y$10)/(15*SUMPRODUCT('STAF scores'!$F$5:$Y$5,'STAF scores'!$F$10:$Y$10)),NA()) | F5: =IF(SUMPRODUCT('STAF scores'!$F$6:$Y$6,'STAF scores'!$F$10:$Y$10)>0,SUMPRODUCT('STAF scores'!F15:Y15,'STAF scores'!$F$6:$Y$6,'STAF scores'!$F$10:$Y$10)/(15*SUMPRODUCT('STAF scores'!$F$6:$Y$6,'STAF scores'!$F$10:$Y$10)),NA()) | G5: =IF(SUMPRODUCT('STAF scores'!$F$7:$Y$7,'STAF scores'!$F$10:$Y$10)>0,SUMPRODUCT('STAF scores'!F15:Y15,'STAF scores'!$F$7:$Y$7,'STAF scores'!$F$10:$Y$10)/(15*SUMPRODUCT('STAF scores'!$F$7:$Y$7,'STAF scores'!$F$10:$Y$10)),NA()) | H5: =SUMPRODUCT('STAF scores'!$F$10:$Y$10*(1-ISNUMBER('STAF scores'!F15:Y15))) | I5: =IF(H5>0,NA(),(E5+F5+G5)/3) | J5: =IF(ISNUMBER(I5),IF(ROUND(I5,2)<=0.39,"Non-Functioning",IF(ROUND(I5,2)<=0.69,"Functioning-at-Risk","Functioning")),"") | K5: =IF(ISNUMBER('STAF scores'!E15),'STAF scores'!E15,NA()) | L5: =I5*K5
B6: ='STAF scores'!B16 | C6: ='STAF scores'!C16 | D6: ='STAF scores'!D16 | E6: =IF(SUMPRODUCT('STAF scores'!$F$5:$Y$5,'STAF scores'!$F$10:$Y$10)>0,SUMPRODUCT('STAF scores'!F16:Y16,'STAF scores'!$F$5:$Y$5,'STAF scores'!$F$10:$Y$10)/(15*SUMPRODUCT('STAF scores'!$F$5:$Y$5,'STAF scores'!$F$10:$Y$10)),NA()) | F6: =IF(SUMPRODUCT('STAF scores'!$F$6:$Y$6,'STAF scores'!$F$10:$Y$10)>0,SUMPRODUCT('STAF scores'!F16:Y16,'STAF scores'!$F$6:$Y$6,'STAF scores'!$F$10:$Y$10)/(15*SUMPRODUCT('STAF scores'!$F$6:$Y$6,'STAF scores'!$F$10:$Y$10)),NA()) | G6: =IF(SUMPRODUCT('STAF scores'!$F$7:$Y$7,'STAF scores'!$F$10:$Y$10)>0,SUMPRODUCT('STAF scores'!F16:Y16,'STAF scores'!$F$7:$Y$7,'STAF scores'!$F$10:$Y$10)/(15*SUMPRODUCT('STAF scores'!$F$7:$Y$7,'STAF scores'!$F$10:$Y$10)),NA()) | H6: =SUMPRODUCT('STAF scores'!$F$10:$Y$10*(1-ISNUMBER('STAF scores'!F16:Y16))) | I6: =IF(H6>0,NA(),(E6+F6+G6)/3) | J6: =IF(ISNUMBER(I6),IF(ROUND(I6,2)<=0.39,"Non-Functioning",IF(ROUND(I6,2)<=0.69,"Functioning-at-Risk","Functioning")),"") | K6: =IF(ISNUMBER('STAF scores'!E16),'STAF scores'!E16,NA()) | L6: =I6*K6
B7: ='STAF scores'!B17 | C7: ='STAF scores'!C17 | D7: ='STAF scores'!D17 | E7: =IF(SUMPRODUCT('STAF scores'!$F$5:$Y$5,'STAF scores'!$F$10:$Y$10)>0,SUMPRODUCT('STAF scores'!F17:Y17,'STAF scores'!$F$5:$Y$5,'STAF scores'!$F$10:$Y$10)/(15*SUMPRODUCT('STAF scores'!$F$5:$Y$5,'STAF scores'!$F$10:$Y$10)),NA()) | F7: =IF(SUMPRODUCT('STAF scores'!$F$6:$Y$6,'STAF scores'!$F$10:$Y$10)>0,SUMPRODUCT('STAF scores'!F17:Y17,'STAF scores'!$F$6:$Y$6,'STAF scores'!$F$10:$Y$10)/(15*SUMPRODUCT('STAF scores'!$F$6:$Y$6,'STAF scores'!$F$10:$Y$10)),NA()) | G7: =IF(SUMPRODUCT('STAF scores'!$F$7:$Y$7,'STAF scores'!$F$10:$Y$10)>0,SUMPRODUCT('STAF scores'!F17:Y17,'STAF scores'!$F$7:$Y$7,'STAF scores'!$F$10:$Y$10)/(15*SUMPRODUCT('STAF scores'!$F$7:$Y$7,'STAF scores'!$F$10:$Y$10)),NA()) | H7: =SUMPRODUCT('STAF scores'!$F$10:$Y$10*(1-ISNUMBER('STAF scores'!F17:Y17))) | I7: =IF(H7>0,NA(),(E7+F7+G7)/3) | J7: =IF(ISNUMBER(I7),IF(ROUND(I7,2)<=0.39,"Non-Functioning",IF(ROUND(I7,2)<=0.69,"Functioning-at-Risk","Functioning")),"") | K7: =IF(ISNUMBER('STAF scores'!E17),'STAF scores'!E17,NA()) | L7: =I7*K7
B8: ='STAF scores'!B18 | C8: ='STAF scores'!C18 | D8: ='STAF scores'!D18 | E8: =IF(SUMPRODUCT('STAF scores'!$F$5:$Y$5,'STAF scores'!$F$10:$Y$10)>0,SUMPRODUCT('STAF scores'!F18:Y18,'STAF scores'!$F$5:$Y$5,'STAF scores'!$F$10:$Y$10)/(15*SUMPRODUCT('STAF scores'!$F$5:$Y$5,'STAF scores'!$F$10:$Y$10)),NA()) | F8: =IF(SUMPRODUCT('STAF scores'!$F$6:$Y$6,'STAF scores'!$F$10:$Y$10)>0,SUMPRODUCT('STAF scores'!F18:Y18,'STAF scores'!$F$6:$Y$6,'STAF scores'!$F$10:$Y$10)/(15*SUMPRODUCT('STAF scores'!$F$6:$Y$6,'STAF scores'!$F$10:$Y$10)),NA()) | G8: =IF(SUMPRODUCT('STAF scores'!$F$7:$Y$7,'STAF scores'!$F$10:$Y$10)>0,SUMPRODUCT('STAF scores'!F18:Y18,'STAF scores'!$F$7:$Y$7,'STAF scores'!$F$10:$Y$10)/(15*SUMPRODUCT('STAF scores'!$F$7:$Y$7,'STAF scores'!$F$10:$Y$10)),NA()) | H8: =SUMPRODUCT('STAF scores'!$F$10:$Y$10*(1-ISNUMBER('STAF scores'!F18:Y18))) | I8: =IF(H8>0,NA(),(E8+F8+G8)/3) | J8: =IF(ISNUMBER(I8),IF(ROUND(I8,2)<=0.39,"Non-Functioning",IF(ROUND(I8,2)<=0.69,"Functioning-at-Risk","Functioning")),"") | K8: =IF(ISNUMBER('STAF scores'!E18),'STAF scores'!E18,NA()) | L8: =I8*K8
B9: ='STAF scores'!B19 | C9: ='STAF scores'!C19 | D9: ='STAF scores'!D19 | E9: =IF(SUMPRODUCT('STAF scores'!$F$5:$Y$5,'STAF scores'!$F$10:$Y$10)>0,SUMPRODUCT('STAF scores'!F19:Y19,'STAF scores'!$F$5:$Y$5,'STAF scores'!$F$10:$Y$10)/(15*SUMPRODUCT('STAF scores'!$F$5:$Y$5,'STAF scores'!$F$10:$Y$10)),NA()) | F9: =IF(SUMPRODUCT('STAF scores'!$F$6:$Y$6,'STAF scores'!$F$10:$Y$10)>0,SUMPRODUCT('STAF scores'!F19:Y19,'STAF scores'!$F$6:$Y$6,'STAF scores'!$F$10:$Y$10)/(15*SUMPRODUCT('STAF scores'!$F$6:$Y$6,'STAF scores'!$F$10:$Y$10)),NA()) | G9: =IF(SUMPRODUCT('STAF scores'!$F$7:$Y$7,'STAF scores'!$F$10:$Y$10)>0,SUMPRODUCT('STAF scores'!F19:Y19,'STAF scores'!$F$7:$Y$7,'STAF scores'!$F$10:$Y$10)/(15*SUMPRODUCT('STAF scores'!$F$7:$Y$7,'STAF scores'!$F$10:$Y$10)),NA()) | H9: =SUMPRODUCT('STAF scores'!$F$10:$Y$10*(1-ISNUMBER('STAF scores'!F19:Y19))) | I9: =IF(H9>0,NA(),(E9+F9+G9)/3) | J9: =IF(ISNUMBER(I9),IF(ROUND(I9,2)<=0.39,"Non-Functioning",IF(ROUND(I9,2)<=0.69,"Functioning-at-Risk","Functioning")),"") | K9: =IF(ISNUMBER('STAF scores'!E19),'STAF scores'!E19,NA()) | L9: =I9*K9
B10: ='STAF scores'!B20 | C10: ='STAF scores'!C20 | D10: ='STAF scores'!D20 | E10: =IF(SUMPRODUCT('STAF scores'!$F$5:$Y$5,'STAF scores'!$F$10:$Y$10)>0,SUMPRODUCT('STAF scores'!F20:Y20,'STAF scores'!$F$5:$Y$5,'STAF scores'!$F$10:$Y$10)/(15*SUMPRODUCT('STAF scores'!$F$5:$Y$5,'STAF scores'!$F$10:$Y$10)),NA()) | F10: =IF(SUMPRODUCT('STAF scores'!$F$6:$Y$6,'STAF scores'!$F$10:$Y$10)>0,SUMPRODUCT('STAF scores'!F20:Y20,'STAF scores'!$F$6:$Y$6,'STAF scores'!$F$10:$Y$10)/(15*SUMPRODUCT('STAF scores'!$F$6:$Y$6,'STAF scores'!$F$10:$Y$10)),NA()) | G10: =IF(SUMPRODUCT('STAF scores'!$F$7:$Y$7,'STAF scores'!$F$10:$Y$10)>0,SUMPRODUCT('STAF scores'!F20:Y20,'STAF scores'!$F$7:$Y$7,'STAF scores'!$F$10:$Y$10)/(15*SUMPRODUCT('STAF scores'!$F$7:$Y$7,'STAF scores'!$F$10:$Y$10)),NA()) | H10: =SUMPRODUCT('STAF scores'!$F$10:$Y$10*(1-ISNUMBER('STAF scores'!F20:Y20))) | I10: =IF(H10>0,NA(),(E10+F10+G10)/3) | J10: =IF(ISNUMBER(I10),IF(ROUND(I10,2)<=0.39,"Non-Functioning",IF(ROUND(I10,2)<=0.69,"Functioning-at-Risk","Functioning")),"") | K10: =IF(ISNUMBER('STAF scores'!E20),'STAF scores'!E20,NA()) | L10: =I10*K10
B11: ='STAF scores'!B21 | C11: ='STAF scores'!C21 | D11: ='STAF scores'!D21 | E11: =IF(SUMPRODUCT('STAF scores'!$F$5:$Y$5,'STAF scores'!$F$10:$Y$10)>0,SUMPRODUCT('STAF scores'!F21:Y21,'STAF scores'!$F$5:$Y$5,'STAF scores'!$F$10:$Y$10)/(15*SUMPRODUCT('STAF scores'!$F$5:$Y$5,'STAF scores'!$F$10:$Y$10)),NA()) | F11: =IF(SUMPRODUCT('STAF scores'!$F$6:$Y$6,'STAF scores'!$F$10:$Y$10)>0,SUMPRODUCT('STAF scores'!F21:Y21,'STAF scores'!$F$6:$Y$6,'STAF scores'!$F$10:$Y$10)/(15*SUMPRODUCT('STAF scores'!$F$6:$Y$6,'STAF scores'!$F$10:$Y$10)),NA()) | G11: =IF(SUMPRODUCT('STAF scores'!$F$7:$Y$7,'STAF scores'!$F$10:$Y$10)>0,SUMPRODUCT('STAF scores'!F21:Y21,'STAF scores'!$F$7:$Y$7,'STAF scores'!$F$10:$Y$10)/(15*SUMPRODUCT('STAF scores'!$F$7:$Y$7,'STAF scores'!$F$10:$Y$10)),NA()) | H11: =SUMPRODUCT('STAF scores'!$F$10:$Y$10*(1-ISNUMBER('STAF scores'!F21:Y21))) | I11: =IF(H11>0,NA(),(E11+F11+G11)/3) | J11: =IF(ISNUMBER(I11),IF(ROUND(I11,2)<=0.39,"Non-Functioning",IF(ROUND(I11,2)<=0.69,"Functioning-at-Risk","Functioning")),"") | K11: =IF(ISNUMBER('STAF scores'!E21),'STAF scores'!E21,NA()) | L11: =I11*K11
B12: ='STAF scores'!B22 | C12: ='STAF scores'!C22 | D12: ='STAF scores'!D22 | E12: =IF(SUMPRODUCT('STAF scores'!$F$5:$Y$5,'STAF scores'!$F$10:$Y$10)>0,SUMPRODUCT('STAF scores'!F22:Y22,'STAF scores'!$F$5:$Y$5,'STAF scores'!$F$10:$Y$10)/(15*SUMPRODUCT('STAF scores'!$F$5:$Y$5,'STAF scores'!$F$10:$Y$10)),NA()) | F12: =IF(SUMPRODUCT('STAF scores'!$F$6:$Y$6,'STAF scores'!$F$10:$Y$10)>0,SUMPRODUCT('STAF scores'!F22:Y22,'STAF scores'!$F$6:$Y$6,'STAF scores'!$F$10:$Y$10)/(15*SUMPRODUCT('STAF scores'!$F$6:$Y$6,'STAF scores'!$F$10:$Y$10)),NA()) | G12: =IF(SUMPRODUCT('STAF scores'!$F$7:$Y$7,'STAF scores'!$F$10:$Y$10)>0,SUMPRODUCT('STAF scores'!F22:Y22,'STAF scores'!$F$7:$Y$7,'STAF scores'!$F$10:$Y$10)/(15*SUMPRODUCT('STAF scores'!$F$7:$Y$7,'STAF scores'!$F$10:$Y$10)),NA()) | H12: =SUMPRODUCT('STAF scores'!$F$10:$Y$10*(1-ISNUMBER('STAF scores'!F22:Y22))) | I12: =IF(H12>0,NA(),(E12+F12+G12)/3) | J12: =IF(ISNUMBER(I12),IF(ROUND(I12,2)<=0.39,"Non-Functioning",IF(ROUND(I12,2)<=0.69,"Functioning-at-Risk","Functioning")),"") | K12: =IF(ISNUMBER('STAF scores'!E22),'STAF scores'!E22,NA()) | L12: =I12*K12
B13: ='STAF scores'!B23 | C13: ='STAF scores'!C23 | D13: ='STAF scores'!D23 | E13: =IF(SUMPRODUCT('STAF scores'!$F$5:$Y$5,'STAF scores'!$F$10:$Y$10)>0,SUMPRODUCT('STAF scores'!F23:Y23,'STAF scores'!$F$5:$Y$5,'STAF scores'!$F$10:$Y$10)/(15*SUMPRODUCT('STAF scores'!$F$5:$Y$5,'STAF scores'!$F$10:$Y$10)),NA()) | F13: =IF(SUMPRODUCT('STAF scores'!$F$6:$Y$6,'STAF scores'!$F$10:$Y$10)>0,SUMPRODUCT('STAF scores'!F23:Y23,'STAF scores'!$F$6:$Y$6,'STAF scores'!$F$10:$Y$10)/(15*SUMPRODUCT('STAF scores'!$F$6:$Y$6,'STAF scores'!$F$10:$Y$10)),NA()) | G13: =IF(SUMPRODUCT('STAF scores'!$F$7:$Y$7,'STAF scores'!$F$10:$Y$10)>0,SUMPRODUCT('STAF scores'!F23:Y23,'STAF scores'!$F$7:$Y$7,'STAF scores'!$F$10:$Y$10)/(15*SUMPRODUCT('STAF scores'!$F$7:$Y$7,'STAF scores'!$F$10:$Y$10)),NA()) | H13: =SUMPRODUCT('STAF scores'!$F$10:$Y$10*(1-ISNUMBER('STAF scores'!F23:Y23))) | I13: =IF(H13>0,NA(),(E13+F13+G13)/3) | J13: =IF(ISNUMBER(I13),IF(ROUND(I13,2)<=0.39,"Non-Functioning",IF(ROUND(I13,2)<=0.69,"Functioning-at-Risk","Functioning")),"") | K13: =IF(ISNUMBER('STAF scores'!E23),'STAF scores'!E23,NA()) | L13: =I13*K13
B14: ='STAF scores'!B24 | C14: ='STAF scores'!C24 | D14: ='STAF scores'!D24 | E14: =IF(SUMPRODUCT('STAF scores'!$F$5:$Y$5,'STAF scores'!$F$10:$Y$10)>0,SUMPRODUCT('STAF scores'!F24:Y24,'STAF scores'!$F$5:$Y$5,'STAF scores'!$F$10:$Y$10)/(15*SUMPRODUCT('STAF scores'!$F$5:$Y$5,'STAF scores'!$F$10:$Y$10)),NA()) | F14: =IF(SUMPRODUCT('STAF scores'!$F$6:$Y$6,'STAF scores'!$F$10:$Y$10)>0,SUMPRODUCT('STAF scores'!F24:Y24,'STAF scores'!$F$6:$Y$6,'STAF scores'!$F$10:$Y$10)/(15*SUMPRODUCT('STAF scores'!$F$6:$Y$6,'STAF scores'!$F$10:$Y$10)),NA()) | G14: =IF(SUMPRODUCT('STAF scores'!$F$7:$Y$7,'STAF scores'!$F$10:$Y$10)>0,SUMPRODUCT('STAF scores'!F24:Y24,'STAF scores'!$F$7:$Y$7,'STAF scores'!$F$10:$Y$10)/(15*SUMPRODUCT('STAF scores'!$F$7:$Y$7,'STAF scores'!$F$10:$Y$10)),NA()) | H14: =SUMPRODUCT('STAF scores'!$F$10:$Y$10*(1-ISNUMBER('STAF scores'!F24:Y24))) | I14: =IF(H14>0,NA(),(E14+F14+G14)/3) | J14: =IF(ISNUMBER(I14),IF(ROUND(I14,2)<=0.39,"Non-Functioning",IF(ROUND(I14,2)<=0.69,"Functioning-at-Risk","Functioning")),"") | K14: =IF(ISNUMBER('STAF scores'!E24),'STAF scores'!E24,NA()) | L14: =I14*K14
B15: ='STAF scores'!B25 | C15: ='STAF scores'!C25 | D15: ='STAF scores'!D25 | E15: =IF(SUMPRODUCT('STAF scores'!$F$5:$Y$5,'STAF scores'!$F$10:$Y$10)>0,SUMPRODUCT('STAF scores'!F25:Y25,'STAF scores'!$F$5:$Y$5,'STAF scores'!$F$10:$Y$10)/(15*SUMPRODUCT('STAF scores'!$F$5:$Y$5,'STAF scores'!$F$10:$Y$10)),NA()) | F15: =IF(SUMPRODUCT('STAF scores'!$F$6:$Y$6,'STAF scores'!$F$10:$Y$10)>0,SUMPRODUCT('STAF scores'!F25:Y25,'STAF scores'!$F$6:$Y$6,'STAF scores'!$F$10:$Y$10)/(15*SUMPRODUCT('STAF scores'!$F$6:$Y$6,'STAF scores'!$F$10:$Y$10)),NA()) | G15: =IF(SUMPRODUCT('STAF scores'!$F$7:$Y$7,'STAF scores'!$F$10:$Y$10)>0,SUMPRODUCT('STAF scores'!F25:Y25,'STAF scores'!$F$7:$Y$7,'STAF scores'!$F$10:$Y$10)/(15*SUMPRODUCT('STAF scores'!$F$7:$Y$7,'STAF scores'!$F$10:$Y$10)),NA()) | H15: =SUMPRODUCT('STAF scores'!$F$10:$Y$10*(1-ISNUMBER('STAF scores'!F25:Y25))) | I15: =IF(H15>0,NA(),(E15+F15+G15)/3) | J15: =IF(ISNUMBER(I15),IF(ROUND(I15,2)<=0.39,"Non-Functioning",IF(ROUND(I15,2)<=0.69,"Functioning-at-Risk","Functioning")),"") | K15: =IF(ISNUMBER('STAF scores'!E25),'STAF scores'!E25,NA()) | L15: =I15*K15
B16: ='STAF scores'!B26 | C16: ='STAF scores'!C26 | D16: ='STAF scores'!D26 | E16: =IF(SUMPRODUCT('STAF scores'!$F$5:$Y$5,'STAF scores'!$F$10:$Y$10)>0,SUMPRODUCT('STAF scores'!F26:Y26,'STAF scores'!$F$5:$Y$5,'STAF scores'!$F$10:$Y$10)/(15*SUMPRODUCT('STAF scores'!$F$5:$Y$5,'STAF scores'!$F$10:$Y$10)),NA()) | F16: =IF(SUMPRODUCT('STAF scores'!$F$6:$Y$6,'STAF scores'!$F$10:$Y$10)>0,SUMPRODUCT('STAF scores'!F26:Y26,'STAF scores'!$F$6:$Y$6,'STAF scores'!$F$10:$Y$10)/(15*SUMPRODUCT('STAF scores'!$F$6:$Y$6,'STAF scores'!$F$10:$Y$10)),NA()) | G16: =IF(SUMPRODUCT('STAF scores'!$F$7:$Y$7,'STAF scores'!$F$10:$Y$10)>0,SUMPRODUCT('STAF scores'!F26:Y26,'STAF scores'!$F$7:$Y$7,'STAF scores'!$F$10:$Y$10)/(15*SUMPRODUCT('STAF scores'!$F$7:$Y$7,'STAF scores'!$F$10:$Y$10)),NA()) | H16: =SUMPRODUCT('STAF scores'!$F$10:$Y$10*(1-ISNUMBER('STAF scores'!F26:Y26))) | I16: =IF(H16>0,NA(),(E16+F16+G16)/3) | J16: =IF(ISNUMBER(I16),IF(ROUND(I16,2)<=0.39,"Non-Functioning",IF(ROUND(I16,2)<=0.69,"Functioning-at-Risk","Functioning")),"") | K16: =IF(ISNUMBER('STAF scores'!E26),'STAF scores'!E26,NA()) | L16: =I16*K16
... B28: ='STAF scores'!B38 | C28: ='STAF scores'!C38 | D28: ='STAF scores'!D38 | E28: =IF(SUMPRODUCT('STAF scores'!$F$5:$Y$5,'STAF scores'!$F$10:$Y$10)>0,SUMPRODUCT('STAF scores'!F38:Y38,'STAF scores'!$F$5:$Y$5,'STAF scores'!$F$10:$Y$10)/(15*SUMPRODUCT('STAF scores'!$F$5:$Y$5,'STAF scores'!$F$10:$Y$10)),NA()) | F28: =IF(SUMPRODUCT('STAF scores'!$F$6:$Y$6,'STAF scores'!$F$10:$Y$10)>0,SUMPRODUCT('STAF scores'!F38:Y38,'STAF scores'!$F$6:$Y$6,'STAF scores'!$F$10:$Y$10)/(15*SUMPRODUCT('STAF scores'!$F$6:$Y$6,'STAF scores'!$F$10:$Y$10)),NA()) | G28: =IF(SUMPRODUCT('STAF scores'!$F$7:$Y$7,'STAF scores'!$F$10:$Y$10)>0,SUMPRODUCT('STAF scores'!F38:Y38,'STAF scores'!$F$7:$Y$7,'STAF scores'!$F$10:$Y$10)/(15*SUMPRODUCT('STAF scores'!$F$7:$Y$7,'STAF scores'!$F$10:$Y$10)),NA()) | H28: =SUMPRODUCT('STAF scores'!$F$10:$Y$10*(1-ISNUMBER('STAF scores'!F38:Y38))) | I28: =IF(H28>0,NA(),(E28+F28+G28)/3) | J28: =IF(ISNUMBER(I28),IF(ROUND(I28,2)<=0.39,"Non-Functioning",IF(ROUND(I28,2)<=0.69,"Functioning-at-Risk","Functioning")),"") | K28: =IF(ISNUMBER('STAF scores'!E38),'STAF scores'!E38,NA()) | L28: =I28*K28
B29: ='STAF scores'!B39 | C29: ='STAF scores'!C39 | D29: ='STAF scores'!D39 | E29: =IF(SUMPRODUCT('STAF scores'!$F$5:$Y$5,'STAF scores'!$F$11:$Y$11)>0,SUMPRODUCT('STAF scores'!F39:Y39,'STAF scores'!$F$5:$Y$5,'STAF scores'!$F$11:$Y$11)/(15*SUMPRODUCT('STAF scores'!$F$5:$Y$5,'STAF scores'!$F$11:$Y$11)),NA()) | F29: =IF(SUMPRODUCT('STAF scores'!$F$6:$Y$6,'STAF scores'!$F$11:$Y$11)>0,SUMPRODUCT('STAF scores'!F39:Y39,'STAF scores'!$F$6:$Y$6,'STAF scores'!$F$11:$Y$11)/(15*SUMPRODUCT('STAF scores'!$F$6:$Y$6,'STAF scores'!$F$11:$Y$11)),NA()) | G29: =IF(SUMPRODUCT('STAF scores'!$F$7:$Y$7,'STAF scores'!$F$11:$Y$11)>0,SUMPRODUCT('STAF scores'!F39:Y39,'STAF scores'!$F$7:$Y$7,'STAF scores'!$F$11:$Y$11)/(15*SUMPRODUCT('STAF scores'!$F$7:$Y$7,'STAF scores'!$F$11:$Y$11)),NA()) | H29: =SUMPRODUCT('STAF scores'!$F$11:$Y$11*(1-ISNUMBER('STAF scores'!F39:Y39))) | I29: =IF(H29>0,NA(),(E29+F29+G29)/3) | J29: =IF(ISNUMBER(I29),IF(ROUND(I29,2)<=0.39,"Non-Functioning",IF(ROUND(I29,2)<=0.69,"Functioning-at-Risk","Functioning")),"") | K29: =IF(ISNUMBER('STAF scores'!E39),'STAF scores'!E39,NA()) | L29: =I29*K29
B30: ='STAF scores'!B40 | C30: ='STAF scores'!C40 | D30: ='STAF scores'!D40 | E30: =IF(SUMPRODUCT('STAF scores'!$F$5:$Y$5,'STAF scores'!$F$11:$Y$11)>0,SUMPRODUCT('STAF scores'!F40:Y40,'STAF scores'!$F$5:$Y$5,'STAF scores'!$F$11:$Y$11)/(15*SUMPRODUCT('STAF scores'!$F$5:$Y$5,'STAF scores'!$F$11:$Y$11)),NA()) | F30: =IF(SUMPRODUCT('STAF scores'!$F$6:$Y$6,'STAF scores'!$F$11:$Y$11)>0,SUMPRODUCT('STAF scores'!F40:Y40,'STAF scores'!$F$6:$Y$6,'STAF scores'!$F$11:$Y$11)/(15*SUMPRODUCT('STAF scores'!$F$6:$Y$6,'STAF scores'!$F$11:$Y$11)),NA()) | G30: =IF(SUMPRODUCT('STAF scores'!$F$7:$Y$7,'STAF scores'!$F$11:$Y$11)>0,SUMPRODUCT('STAF scores'!F40:Y40,'STAF scores'!$F$7:$Y$7,'STAF scores'!$F$11:$Y$11)/(15*SUMPRODUCT('STAF scores'!$F$7:$Y$7,'STAF scores'!$F$11:$Y$11)),NA()) | H30: =SUMPRODUCT('STAF scores'!$F$11:$Y$11*(1-ISNUMBER('STAF scores'!F40:Y40))) | I30: =IF(H30>0,NA(),(E30+F30+G30)/3) | J30: =IF(ISNUMBER(I30),IF(ROUND(I30,2)<=0.39,"Non-Functioning",IF(ROUND(I30,2)<=0.69,"Functioning-at-Risk","Functioning")),"") | K30: =IF(ISNUMBER('STAF scores'!E40),'STAF scores'!E40,NA()) | L30: =I30*K30
B31: ='STAF scores'!B41 | C31: ='STAF scores'!C41 | D31: ='STAF scores'!D41 | E31: =IF(SUMPRODUCT('STAF scores'!$F$5:$Y$5,'STAF scores'!$F$11:$Y$11)>0,SUMPRODUCT('STAF scores'!F41:Y41,'STAF scores'!$F$5:$Y$5,'STAF scores'!$F$11:$Y$11)/(15*SUMPRODUCT('STAF scores'!$F$5:$Y$5,'STAF scores'!$F$11:$Y$11)),NA()) | F31: =IF(SUMPRODUCT('STAF scores'!$F$6:$Y$6,'STAF scores'!$F$11:$Y$11)>0,SUMPRODUCT('STAF scores'!F41:Y41,'STAF scores'!$F$6:$Y$6,'STAF scores'!$F$11:$Y$11)/(15*SUMPRODUCT('STAF scores'!$F$6:$Y$6,'STAF scores'!$F$11:$Y$11)),NA()) | G31: =IF(SUMPRODUCT('STAF scores'!$F$7:$Y$7,'STAF scores'!$F$11:$Y$11)>0,SUMPRODUCT('STAF scores'!F41:Y41,'STAF scores'!$F$7:$Y$7,'STAF scores'!$F$11:$Y$11)/(15*SUMPRODUCT('STAF scores'!$F$7:$Y$7,'STAF scores'!$F$11:$Y$11)),NA()) | H31: =SUMPRODUCT('STAF scores'!$F$11:$Y$11*(1-ISNUMBER('STAF scores'!F41:Y41))) | I31: =IF(H31>0,NA(),(E31+F31+G31)/3) | J31: =IF(ISNUMBER(I31),IF(ROUND(I31,2)<=0.39,"Non-Functioning",IF(ROUND(I31,2)<=0.69,"Functioning-at-Risk","Functioning")),"") | K31: =IF(ISNUMBER('STAF scores'!E41),'STAF scores'!E41,NA()) | L31: =I31*K31
B32: ='STAF scores'!B42 | C32: ='STAF scores'!C42 | D32: ='STAF scores'!D42 | E32: =IF(SUMPRODUCT('STAF scores'!$F$5:$Y$5,'STAF scores'!$F$11:$Y$11)>0,SUMPRODUCT('STAF scores'!F42:Y42,'STAF scores'!$F$5:$Y$5,'STAF scores'!$F$11:$Y$11)/(15*SUMPRODUCT('STAF scores'!$F$5:$Y$5,'STAF scores'!$F$11:$Y$11)),NA()) | F32: =IF(SUMPRODUCT('STAF scores'!$F$6:$Y$6,'STAF scores'!$F$11:$Y$11)>0,SUMPRODUCT('STAF scores'!F42:Y42,'STAF scores'!$F$6:$Y$6,'STAF scores'!$F$11:$Y$11)/(15*SUMPRODUCT('STAF scores'!$F$6:$Y$6,'STAF scores'!$F$11:$Y$11)),NA()) | G32: =IF(SUMPRODUCT('STAF scores'!$F$7:$Y$7,'STAF scores'!$F$11:$Y$11)>0,SUMPRODUCT('STAF scores'!F42:Y42,'STAF scores'!$F$7:$Y$7,'STAF scores'!$F$11:$Y$11)/(15*SUMPRODUCT('STAF scores'!$F$7:$Y$7,'STAF scores'!$F$11:$Y$11)),NA()) | H32: =SUMPRODUCT('STAF scores'!$F$11:$Y$11*(1-ISNUMBER('STAF scores'!F42:Y42))) | I32: =IF(H32>0,NA(),(E32+F32+G32)/3) | J32: =IF(ISNUMBER(I32),IF(ROUND(I32,2)<=0.39,"Non-Functioning",IF(ROUND(I32,2)<=0.69,"Functioning-at-Risk","Functioning")),"") | K32: =IF(ISNUMBER('STAF scores'!E42),'STAF scores'!E42,NA()) | L32: =I32*K32
B33: ='STAF scores'!B43 | C33: ='STAF scores'!C43 | D33: ='STAF scores'!D43 | E33: =IF(SUMPRODUCT('STAF scores'!$F$5:$Y$5,'STAF scores'!$F$11:$Y$11)>0,SUMPRODUCT('STAF scores'!F43:Y43,'STAF scores'!$F$5:$Y$5,'STAF scores'!$F$11:$Y$11)/(15*SUMPRODUCT('STAF scores'!$F$5:$Y$5,'STAF scores'!$F$11:$Y$11)),NA()) | F33: =IF(SUMPRODUCT('STAF scores'!$F$6:$Y$6,'STAF scores'!$F$11:$Y$11)>0,SUMPRODUCT('STAF scores'!F43:Y43,'STAF scores'!$F$6:$Y$6,'STAF scores'!$F$11:$Y$11)/(15*SUMPRODUCT('STAF scores'!$F$6:$Y$6,'STAF scores'!$F$11:$Y$11)),NA()) | G33: =IF(SUMPRODUCT('STAF scores'!$F$7:$Y$7,'STAF scores'!$F$11:$Y$11)>0,SUMPRODUCT('STAF scores'!F43:Y43,'STAF scores'!$F$7:$Y$7,'STAF scores'!$F$11:$Y$11)/(15*SUMPRODUCT('STAF scores'!$F$7:$Y$7,'STAF scores'!$F$11:$Y$11)),NA()) | H33: =SUMPRODUCT('STAF scores'!$F$11:$Y$11*(1-ISNUMBER('STAF scores'!F43:Y43))) | I33: =IF(H33>0,NA(),(E33+F33+G33)/3) | J33: =IF(ISNUMBER(I33),IF(ROUND(I33,2)<=0.39,"Non-Functioning",IF(ROUND(I33,2)<=0.69,"Functioning-at-Risk","Functioning")),"") | K33: =IF(ISNUMBER('STAF scores'!E43),'STAF scores'!E43,NA()) | L33: =I33*K33
B34: ='STAF scores'!B44 | C34: ='STAF scores'!C44 | D34: ='STAF scores'!D44 | E34: =IF(SUMPRODUCT('STAF scores'!$F$5:$Y$5,'STAF scores'!$F$11:$Y$11)>0,SUMPRODUCT('STAF scores'!F44:Y44,'STAF scores'!$F$5:$Y$5,'STAF scores'!$F$11:$Y$11)/(15*SUMPRODUCT('STAF scores'!$F$5:$Y$5,'STAF scores'!$F$11:$Y$11)),NA()) | F34: =IF(SUMPRODUCT('STAF scores'!$F$6:$Y$6,'STAF scores'!$F$11:$Y$11)>0,SUMPRODUCT('STAF scores'!F44:Y44,'STAF scores'!$F$6:$Y$6,'STAF scores'!$F$11:$Y$11)/(15*SUMPRODUCT('STAF scores'!$F$6:$Y$6,'STAF scores'!$F$11:$Y$11)),NA()) | G34: =IF(SUMPRODUCT('STAF scores'!$F$7:$Y$7,'STAF scores'!$F$11:$Y$11)>0,SUMPRODUCT('STAF scores'!F44:Y44,'STAF scores'!$F$7:$Y$7,'STAF scores'!$F$11:$Y$11)/(15*SUMPRODUCT('STAF scores'!$F$7:$Y$7,'STAF scores'!$F$11:$Y$11)),NA()) | H34: =SUMPRODUCT('STAF scores'!$F$11:$Y$11*(1-ISNUMBER('STAF scores'!F44:Y44))) | I34: =IF(H34>0,NA(),(E34+F34+G34)/3) | J34: =IF(ISNUMBER(I34),IF(ROUND(I34,2)<=0.39,"Non-Functioning",IF(ROUND(I34,2)<=0.69,"Functioning-at-Risk","Functioning")),"") | K34: =IF(ISNUMBER('STAF scores'!E44),'STAF scores'!E44,NA()) | L34: =I34*K34
B35: ='STAF scores'!B45 | C35: ='STAF scores'!C45 | D35: ='STAF scores'!D45 | E35: =IF(SUMPRODUCT('STAF scores'!$F$5:$Y$5,'STAF scores'!$F$11:$Y$11)>0,SUMPRODUCT('STAF scores'!F45:Y45,'STAF scores'!$F$5:$Y$5,'STAF scores'!$F$11:$Y$11)/(15*SUMPRODUCT('STAF scores'!$F$5:$Y$5,'STAF scores'!$F$11:$Y$11)),NA()) | F35: =IF(SUMPRODUCT('STAF scores'!$F$6:$Y$6,'STAF scores'!$F$11:$Y$11)>0,SUMPRODUCT('STAF scores'!F45:Y45,'STAF scores'!$F$6:$Y$6,'STAF scores'!$F$11:$Y$11)/(15*SUMPRODUCT('STAF scores'!$F$6:$Y$6,'STAF scores'!$F$11:$Y$11)),NA()) | G35: =IF(SUMPRODUCT('STAF scores'!$F$7:$Y$7,'STAF scores'!$F$11:$Y$11)>0,SUMPRODUCT('STAF scores'!F45:Y45,'STAF scores'!$F$7:$Y$7,'STAF scores'!$F$11:$Y$11)/(15*SUMPRODUCT('STAF scores'!$F$7:$Y$7,'STAF scores'!$F$11:$Y$11)),NA()) | H35: =SUMPRODUCT('STAF scores'!$F$11:$Y$11*(1-ISNUMBER('STAF scores'!F45:Y45))) | I35: =IF(H35>0,NA(),(E35+F35+G35)/3) | J35: =IF(ISNUMBER(I35),IF(ROUND(I35,2)<=0.39,"Non-Functioning",IF(ROUND(I35,2)<=0.69,"Functioning-at-Risk","Functioning")),"") | K35: =IF(ISNUMBER('STAF scores'!E45),'STAF scores'!E45,NA()) | L35: =I35*K35
B36: ='STAF scores'!B46 | C36: ='STAF scores'!C46 | D36: ='STAF scores'!D46 | E36: =IF(SUMPRODUCT('STAF scores'!$F$5:$Y$5,'STAF scores'!$F$11:$Y$11)>0,SUMPRODUCT('STAF scores'!F46:Y46,'STAF scores'!$F$5:$Y$5,'STAF scores'!$F$11:$Y$11)/(15*SUMPRODUCT('STAF scores'!$F$5:$Y$5,'STAF scores'!$F$11:$Y$11)),NA()) | F36: =IF(SUMPRODUCT('STAF scores'!$F$6:$Y$6,'STAF scores'!$F$11:$Y$11)>0,SUMPRODUCT('STAF scores'!F46:Y46,'STAF scores'!$F$6:$Y$6,'STAF scores'!$F$11:$Y$11)/(15*SUMPRODUCT('STAF scores'!$F$6:$Y$6,'STAF scores'!$F$11:$Y$11)),NA()) | G36: =IF(SUMPRODUCT('STAF scores'!$F$7:$Y$7,'STAF scores'!$F$11:$Y$11)>0,SUMPRODUCT('STAF scores'!F46:Y46,'STAF scores'!$F$7:$Y$7,'STAF scores'!$F$11:$Y$11)/(15*SUMPRODUCT('STAF scores'!$F$7:$Y$7,'STAF scores'!$F$11:$Y$11)),NA()) | H36: =SUMPRODUCT('STAF scores'!$F$11:$Y$11*(1-ISNUMBER('STAF scores'!F46:Y46))) | I36: =IF(H36>0,NA(),(E36+F36+G36)/3) | J36: =IF(ISNUMBER(I36),IF(ROUND(I36,2)<=0.39,"Non-Functioning",IF(ROUND(I36,2)<=0.69,"Functioning-at-Risk","Functioning")),"") | K36: =IF(ISNUMBER('STAF scores'!E46),'STAF scores'!E46,NA()) | L36: =I36*K36
B37: ='STAF scores'!B47 | C37: ='STAF scores'!C47 | D37: ='STAF scores'!D47 | E37: =IF(SUMPRODUCT('STAF scores'!$F$5:$Y$5,'STAF scores'!$F$11:$Y$11)>0,SUMPRODUCT('STAF scores'!F47:Y47,'STAF scores'!$F$5:$Y$5,'STAF scores'!$F$11:$Y$11)/(15*SUMPRODUCT('STAF scores'!$F$5:$Y$5,'STAF scores'!$F$11:$Y$11)),NA()) | F37: =IF(SUMPRODUCT('STAF scores'!$F$6:$Y$6,'STAF scores'!$F$11:$Y$11)>0,SUMPRODUCT('STAF scores'!F47:Y47,'STAF scores'!$F$6:$Y$6,'STAF scores'!$F$11:$Y$11)/(15*SUMPRODUCT('STAF scores'!$F$6:$Y$6,'STAF scores'!$F$11:$Y$11)),NA()) | G37: =IF(SUMPRODUCT('STAF scores'!$F$7:$Y$7,'STAF scores'!$F$11:$Y$11)>0,SUMPRODUCT('STAF scores'!F47:Y47,'STAF scores'!$F$7:$Y$7,'STAF scores'!$F$11:$Y$11)/(15*SUMPRODUCT('STAF scores'!$F$7:$Y$7,'STAF scores'!$F$11:$Y$11)),NA()) | H37: =SUMPRODUCT('STAF scores'!$F$11:$Y$11*(1-ISNUMBER('STAF scores'!F47:Y47))) | I37: =IF(H37>0,NA(),(E37+F37+G37)/3) | J37: =IF(ISNUMBER(I37),IF(ROUND(I37,2)<=0.39,"Non-Functioning",IF(ROUND(I37,2)<=0.69,"Functioning-at-Risk","Functioning")),"") | K37: =IF(ISNUMBER('STAF scores'!E47),'STAF scores'!E47,NA()) | L37: =I37*K37
B38: ='STAF scores'!B48 | C38: ='STAF scores'!C48 | D38: ='STAF scores'!D48 | E38: =IF(SUMPRODUCT('STAF scores'!$F$5:$Y$5,'STAF scores'!$F$11:$Y$11)>0,SUMPRODUCT('STAF scores'!F48:Y48,'STAF scores'!$F$5:$Y$5,'STAF scores'!$F$11:$Y$11)/(15*SUMPRODUCT('STAF scores'!$F$5:$Y$5,'STAF scores'!$F$11:$Y$11)),NA()) | F38: =IF(SUMPRODUCT('STAF scores'!$F$6:$Y$6,'STAF scores'!$F$11:$Y$11)>0,SUMPRODUCT('STAF scores'!F48:Y48,'STAF scores'!$F$6:$Y$6,'STAF scores'!$F$11:$Y$11)/(15*SUMPRODUCT('STAF scores'!$F$6:$Y$6,'STAF scores'!$F$11:$Y$11)),NA()) | G38: =IF(SUMPRODUCT('STAF scores'!$F$7:$Y$7,'STAF scores'!$F$11:$Y$11)>0,SUMPRODUCT('STAF scores'!F48:Y48,'STAF scores'!$F$7:$Y$7,'STAF scores'!$F$11:$Y$11)/(15*SUMPRODUCT('STAF scores'!$F$7:$Y$7,'STAF scores'!$F$11:$Y$11)),NA()) | H38: =SUMPRODUCT('STAF scores'!$F$11:$Y$11*(1-ISNUMBER('STAF scores'!F48:Y48))) | I38: =IF(H38>0,NA(),(E38+F38+G38)/3) | J38: =IF(ISNUMBER(I38),IF(ROUND(I38,2)<=0.39,"Non-Functioning",IF(ROUND(I38,2)<=0.69,"Functioning-at-Risk","Functioning")),"") | K38: =IF(ISNUMBER('STAF scores'!E48),'STAF scores'!E48,NA()) | L38: =I38*K38
B39: ='STAF scores'!B49 | C39: ='STAF scores'!C49 | D39: ='STAF scores'!D49 | E39: =IF(SUMPRODUCT('STAF scores'!$F$5:$Y$5,'STAF scores'!$F$11:$Y$11)>0,SUMPRODUCT('STAF scores'!F49:Y49,'STAF scores'!$F$5:$Y$5,'STAF scores'!$F$11:$Y$11)/(15*SUMPRODUCT('STAF scores'!$F$5:$Y$5,'STAF scores'!$F$11:$Y$11)),NA()) | F39: =IF(SUMPRODUCT('STAF scores'!$F$6:$Y$6,'STAF scores'!$F$11:$Y$11)>0,SUMPRODUCT('STAF scores'!F49:Y49,'STAF scores'!$F$6:$Y$6,'STAF scores'!$F$11:$Y$11)/(15*SUMPRODUCT('STAF scores'!$F$6:$Y$6,'STAF scores'!$F$11:$Y$11)),NA()) | G39: =IF(SUMPRODUCT('STAF scores'!$F$7:$Y$7,'STAF scores'!$F$11:$Y$11)>0,SUMPRODUCT('STAF scores'!F49:Y49,'STAF scores'!$F$7:$Y$7,'STAF scores'!$F$11:$Y$11)/(15*SUMPRODUCT('STAF scores'!$F$7:$Y$7,'STAF scores'!$F$11:$Y$11)),NA()) | H39: =SUMPRODUCT('STAF scores'!$F$11:$Y$11*(1-ISNUMBER('STAF scores'!F49:Y49))) | I39: =IF(H39>0,NA(),(E39+F39+G39)/3) | J39: =IF(ISNUMBER(I39),IF(ROUND(I39,2)<=0.39,"Non-Functioning",IF(ROUND(I39,2)<=0.69,"Functioning-at-Risk","Functioning")),"") | K39: =IF(ISNUMBER('STAF scores'!E49),'STAF scores'!E49,NA()) | L39: =I39*K39
B40: ='STAF scores'!B50 | C40: ='STAF scores'!C50 | D40: ='STAF scores'!D50 | E40: =IF(SUMPRODUCT('STAF scores'!$F$5:$Y$5,'STAF scores'!$F$11:$Y$11)>0,SUMPRODUCT('STAF scores'!F50:Y50,'STAF scores'!$F$5:$Y$5,'STAF scores'!$F$11:$Y$11)/(15*SUMPRODUCT('STAF scores'!$F$5:$Y$5,'STAF scores'!$F$11:$Y$11)),NA()) | F40: =IF(SUMPRODUCT('STAF scores'!$F$6:$Y$6,'STAF scores'!$F$11:$Y$11)>0,SUMPRODUCT('STAF scores'!F50:Y50,'STAF scores'!$F$6:$Y$6,'STAF scores'!$F$11:$Y$11)/(15*SUMPRODUCT('STAF scores'!$F$6:$Y$6,'STAF scores'!$F$11:$Y$11)),NA()) | G40: =IF(SUMPRODUCT('STAF scores'!$F$7:$Y$7,'STAF scores'!$F$11:$Y$11)>0,SUMPRODUCT('STAF scores'!F50:Y50,'STAF scores'!$F$7:$Y$7,'STAF scores'!$F$11:$Y$11)/(15*SUMPRODUCT('STAF scores'!$F$7:$Y$7,'STAF scores'!$F$11:$Y$11)),NA()) | H40: =SUMPRODUCT('STAF scores'!$F$11:$Y$11*(1-ISNUMBER('STAF scores'!F50:Y50))) | I40: =IF(H40>0,NA(),(E40+F40+G40)/3) | J40: =IF(ISNUMBER(I40),IF(ROUND(I40,2)<=0.39,"Non-Functioning",IF(ROUND(I40,2)<=0.69,"Functioning-at-Risk","Functioning")),"") | K40: =IF(ISNUMBER('STAF scores'!E50),'STAF scores'!E50,NA()) | L40: =I40*K40
... B46: ='STAF scores'!B56 | C46: ='STAF scores'!C56 | D46: ='STAF scores'!D56 | E46: =IF(SUMPRODUCT('STAF scores'!$F$5:$Y$5,'STAF scores'!$F$11:$Y$11)>0,SUMPRODUCT('STAF scores'!F56:Y56,'STAF scores'!$F$5:$Y$5,'STAF scores'!$F$11:$Y$11)/(15*SUMPRODUCT('STAF scores'!$F$5:$Y$5,'STAF scores'!$F$11:$Y$11)),NA()) | F46: =IF(SUMPRODUCT('STAF scores'!$F$6:$Y$6,'STAF scores'!$F$11:$Y$11)>0,SUMPRODUCT('STAF scores'!F56:Y56,'STAF scores'!$F$6:$Y$6,'STAF scores'!$F$11:$Y$11)/(15*SUMPRODUCT('STAF scores'!$F$6:$Y$6,'STAF scores'!$F$11:$Y$11)),NA()) | G46: =IF(SUMPRODUCT('STAF scores'!$F$7:$Y$7,'STAF scores'!$F$11:$Y$11)>0,SUMPRODUCT('STAF scores'!F56:Y56,'STAF scores'!$F$7:$Y$7,'STAF scores'!$F$11:$Y$11)/(15*SUMPRODUCT('STAF scores'!$F$7:$Y$7,'STAF scores'!$F$11:$Y$11)),NA()) | H46: =SUMPRODUCT('STAF scores'!$F$11:$Y$11*(1-ISNUMBER('STAF scores'!F56:Y56))) | I46: =IF(H46>0,NA(),(E46+F46+G46)/3) | J46: =IF(ISNUMBER(I46),IF(ROUND(I46,2)<=0.39,"Non-Functioning",IF(ROUND(I46,2)<=0.69,"Functioning-at-Risk","Functioning")),"") | K46: =IF(ISNUMBER('STAF scores'!E56),'STAF scores'!E56,NA()) | L46: =I46*K46
B47: ='STAF scores'!B57 | C47: ='STAF scores'!C57 | D47: ='STAF scores'!D57 | E47: =IF(SUMPRODUCT('STAF scores'!$F$5:$Y$5,'STAF scores'!$F$12:$Y$12)>0,SUMPRODUCT('STAF scores'!F57:Y57,'STAF scores'!$F$5:$Y$5,'STAF scores'!$F$12:$Y$12)/(15*SUMPRODUCT('STAF scores'!$F$5:$Y$5,'STAF scores'!$F$12:$Y$12)),NA()) | F47: =IF(SUMPRODUCT('STAF scores'!$F$6:$Y$6,'STAF scores'!$F$12:$Y$12)>0,SUMPRODUCT('STAF scores'!F57:Y57,'STAF scores'!$F$6:$Y$6,'STAF scores'!$F$12:$Y$12)/(15*SUMPRODUCT('STAF scores'!$F$6:$Y$6,'STAF scores'!$F$12:$Y$12)),NA()) | G47: =IF(SUMPRODUCT('STAF scores'!$F$7:$Y$7,'STAF scores'!$F$12:$Y$12)>0,SUMPRODUCT('STAF scores'!F57:Y57,'STAF scores'!$F$7:$Y$7,'STAF scores'!$F$12:$Y$12)/(15*SUMPRODUCT('STAF scores'!$F$7:$Y$7,'STAF scores'!$F$12:$Y$12)),NA()) | H47: =SUMPRODUCT('STAF scores'!$F$12:$Y$12*(1-ISNUMBER('STAF scores'!F57:Y57))) | I47: =IF(H47>0,NA(),(E47+F47+G47)/3) | J47: =IF(ISNUMBER(I47),IF(ROUND(I47,2)<=0.39,"Non-Functioning",IF(ROUND(I47,2)<=0.69,"Functioning-at-Risk","Functioning")),"") | K47: =IF(ISNUMBER('STAF scores'!E57),'STAF scores'!E57,NA()) | L47: =I47*K47
B48: ='STAF scores'!B58 | C48: ='STAF scores'!C58 | D48: ='STAF scores'!D58 | E48: =IF(SUMPRODUCT('STAF scores'!$F$5:$Y$5,'STAF scores'!$F$12:$Y$12)>0,SUMPRODUCT('STAF scores'!F58:Y58,'STAF scores'!$F$5:$Y$5,'STAF scores'!$F$12:$Y$12)/(15*SUMPRODUCT('STAF scores'!$F$5:$Y$5,'STAF scores'!$F$12:$Y$12)),NA()) | F48: =IF(SUMPRODUCT('STAF scores'!$F$6:$Y$6,'STAF scores'!$F$12:$Y$12)>0,SUMPRODUCT('STAF scores'!F58:Y58,'STAF scores'!$F$6:$Y$6,'STAF scores'!$F$12:$Y$12)/(15*SUMPRODUCT('STAF scores'!$F$6:$Y$6,'STAF scores'!$F$12:$Y$12)),NA()) | G48: =IF(SUMPRODUCT('STAF scores'!$F$7:$Y$7,'STAF scores'!$F$12:$Y$12)>0,SUMPRODUCT('STAF scores'!F58:Y58,'STAF scores'!$F$7:$Y$7,'STAF scores'!$F$12:$Y$12)/(15*SUMPRODUCT('STAF scores'!$F$7:$Y$7,'STAF scores'!$F$12:$Y$12)),NA()) | H48: =SUMPRODUCT('STAF scores'!$F$12:$Y$12*(1-ISNUMBER('STAF scores'!F58:Y58))) | I48: =IF(H48>0,NA(),(E48+F48+G48)/3) | J48: =IF(ISNUMBER(I48),IF(ROUND(I48,2)<=0.39,"Non-Functioning",IF(ROUND(I48,2)<=0.69,"Functioning-at-Risk","Functioning")),"") | K48: =IF(ISNUMBER('STAF scores'!E58),'STAF scores'!E58,NA()) | L48: =I48*K48
B49: ='STAF scores'!B59 | C49: ='STAF scores'!C59 | D49: ='STAF scores'!D59 | E49: =IF(SUMPRODUCT('STAF scores'!$F$5:$Y$5,'STAF scores'!$F$12:$Y$12)>0,SUMPRODUCT('STAF scores'!F59:Y59,'STAF scores'!$F$5:$Y$5,'STAF scores'!$F$12:$Y$12)/(15*SUMPRODUCT('STAF scores'!$F$5:$Y$5,'STAF scores'!$F$12:$Y$12)),NA()) | F49: =IF(SUMPRODUCT('STAF scores'!$F$6:$Y$6,'STAF scores'!$F$12:$Y$12)>0,SUMPRODUCT('STAF scores'!F59:Y59,'STAF scores'!$F$6:$Y$6,'STAF scores'!$F$12:$Y$12)/(15*SUMPRODUCT('STAF scores'!$F$6:$Y$6,'STAF scores'!$F$12:$Y$12)),NA()) | G49: =IF(SUMPRODUCT('STAF scores'!$F$7:$Y$7,'STAF scores'!$F$12:$Y$12)>0,SUMPRODUCT('STAF scores'!F59:Y59,'STAF scores'!$F$7:$Y$7,'STAF scores'!$F$12:$Y$12)/(15*SUMPRODUCT('STAF scores'!$F$7:$Y$7,'STAF scores'!$F$12:$Y$12)),NA()) | H49: =SUMPRODUCT('STAF scores'!$F$12:$Y$12*(1-ISNUMBER('STAF scores'!F59:Y59))) | I49: =IF(H49>0,NA(),(E49+F49+G49)/3) | J49: =IF(ISNUMBER(I49),IF(ROUND(I49,2)<=0.39,"Non-Functioning",IF(ROUND(I49,2)<=0.69,"Functioning-at-Risk","Functioning")),"") | K49: =IF(ISNUMBER('STAF scores'!E59),'STAF scores'!E59,NA()) | L49: =I49*K49
B50: ='STAF scores'!B60 | C50: ='STAF scores'!C60 | D50: ='STAF scores'!D60 | E50: =IF(SUMPRODUCT('STAF scores'!$F$5:$Y$5,'STAF scores'!$F$12:$Y$12)>0,SUMPRODUCT('STAF scores'!F60:Y60,'STAF scores'!$F$5:$Y$5,'STAF scores'!$F$12:$Y$12)/(15*SUMPRODUCT('STAF scores'!$F$5:$Y$5,'STAF scores'!$F$12:$Y$12)),NA()) | F50: =IF(SUMPRODUCT('STAF scores'!$F$6:$Y$6,'STAF scores'!$F$12:$Y$12)>0,SUMPRODUCT('STAF scores'!F60:Y60,'STAF scores'!$F$6:$Y$6,'STAF scores'!$F$12:$Y$12)/(15*SUMPRODUCT('STAF scores'!$F$6:$Y$6,'STAF scores'!$F$12:$Y$12)),NA()) | G50: =IF(SUMPRODUCT('STAF scores'!$F$7:$Y$7,'STAF scores'!$F$12:$Y$12)>0,SUMPRODUCT('STAF scores'!F60:Y60,'STAF scores'!$F$7:$Y$7,'STAF scores'!$F$12:$Y$12)/(15*SUMPRODUCT('STAF scores'!$F$7:$Y$7,'STAF scores'!$F$12:$Y$12)),NA()) | H50: =SUMPRODUCT('STAF scores'!$F$12:$Y$12*(1-ISNUMBER('STAF scores'!F60:Y60))) | I50: =IF(H50>0,NA(),(E50+F50+G50)/3) | J50: =IF(ISNUMBER(I50),IF(ROUND(I50,2)<=0.39,"Non-Functioning",IF(ROUND(I50,2)<=0.69,"Functioning-at-Risk","Functioning")),"") | K50: =IF(ISNUMBER('STAF scores'!E60),'STAF scores'!E60,NA()) | L50: =I50*K50
B51: ='STAF scores'!B61 | C51: ='STAF scores'!C61 | D51: ='STAF scores'!D61 | E51: =IF(SUMPRODUCT('STAF scores'!$F$5:$Y$5,'STAF scores'!$F$12:$Y$12)>0,SUMPRODUCT('STAF scores'!F61:Y61,'STAF scores'!$F$5:$Y$5,'STAF scores'!$F$12:$Y$12)/(15*SUMPRODUCT('STAF scores'!$F$5:$Y$5,'STAF scores'!$F$12:$Y$12)),NA()) | F51: =IF(SUMPRODUCT('STAF scores'!$F$6:$Y$6,'STAF scores'!$F$12:$Y$12)>0,SUMPRODUCT('STAF scores'!F61:Y61,'STAF scores'!$F$6:$Y$6,'STAF scores'!$F$12:$Y$12)/(15*SUMPRODUCT('STAF scores'!$F$6:$Y$6,'STAF scores'!$F$12:$Y$12)),NA()) | G51: =IF(SUMPRODUCT('STAF scores'!$F$7:$Y$7,'STAF scores'!$F$12:$Y$12)>0,SUMPRODUCT('STAF scores'!F61:Y61,'STAF scores'!$F$7:$Y$7,'STAF scores'!$F$12:$Y$12)/(15*SUMPRODUCT('STAF scores'!$F$7:$Y$7,'STAF scores'!$F$12:$Y$12)),NA()) | H51: =SUMPRODUCT('STAF scores'!$F$12:$Y$12*(1-ISNUMBER('STAF scores'!F61:Y61))) | I51: =IF(H51>0,NA(),(E51+F51+G51)/3) | J51: =IF(ISNUMBER(I51),IF(ROUND(I51,2)<=0.39,"Non-Functioning",IF(ROUND(I51,2)<=0.69,"Functioning-at-Risk","Functioning")),"") | K51: =IF(ISNUMBER('STAF scores'!E61),'STAF scores'!E61,NA()) | L51: =I51*K51
B52: ='STAF scores'!B62 | C52: ='STAF scores'!C62 | D52: ='STAF scores'!D62 | E52: =IF(SUMPRODUCT('STAF scores'!$F$5:$Y$5,'STAF scores'!$F$12:$Y$12)>0,SUMPRODUCT('STAF scores'!F62:Y62,'STAF scores'!$F$5:$Y$5,'STAF scores'!$F$12:$Y$12)/(15*SUMPRODUCT('STAF scores'!$F$5:$Y$5,'STAF scores'!$F$12:$Y$12)),NA()) | F52: =IF(SUMPRODUCT('STAF scores'!$F$6:$Y$6,'STAF scores'!$F$12:$Y$12)>0,SUMPRODUCT('STAF scores'!F62:Y62,'STAF scores'!$F$6:$Y$6,'STAF scores'!$F$12:$Y$12)/(15*SUMPRODUCT('STAF scores'!$F$6:$Y$6,'STAF scores'!$F$12:$Y$12)),NA()) | G52: =IF(SUMPRODUCT('STAF scores'!$F$7:$Y$7,'STAF scores'!$F$12:$Y$12)>0,SUMPRODUCT('STAF scores'!F62:Y62,'STAF scores'!$F$7:$Y$7,'STAF scores'!$F$12:$Y$12)/(15*SUMPRODUCT('STAF scores'!$F$7:$Y$7,'STAF scores'!$F$12:$Y$12)),NA()) | H52: =SUMPRODUCT('STAF scores'!$F$12:$Y$12*(1-ISNUMBER('STAF scores'!F62:Y62))) | I52: =IF(H52>0,NA(),(E52+F52+G52)/3) | J52: =IF(ISNUMBER(I52),IF(ROUND(I52,2)<=0.39,"Non-Functioning",IF(ROUND(I52,2)<=0.69,"Functioning-at-Risk","Functioning")),"") | K52: =IF(ISNUMBER('STAF scores'!E62),'STAF scores'!E62,NA()) | L52: =I52*K52
B53: ='STAF scores'!B63 | C53: ='STAF scores'!C63 | D53: ='STAF scores'!D63 | E53: =IF(SUMPRODUCT('STAF scores'!$F$5:$Y$5,'STAF scores'!$F$12:$Y$12)>0,SUMPRODUCT('STAF scores'!F63:Y63,'STAF scores'!$F$5:$Y$5,'STAF scores'!$F$12:$Y$12)/(15*SUMPRODUCT('STAF scores'!$F$5:$Y$5,'STAF scores'!$F$12:$Y$12)),NA()) | F53: =IF(SUMPRODUCT('STAF scores'!$F$6:$Y$6,'STAF scores'!$F$12:$Y$12)>0,SUMPRODUCT('STAF scores'!F63:Y63,'STAF scores'!$F$6:$Y$6,'STAF scores'!$F$12:$Y$12)/(15*SUMPRODUCT('STAF scores'!$F$6:$Y$6,'STAF scores'!$F$12:$Y$12)),NA()) | G53: =IF(SUMPRODUCT('STAF scores'!$F$7:$Y$7,'STAF scores'!$F$12:$Y$12)>0,SUMPRODUCT('STAF scores'!F63:Y63,'STAF scores'!$F$7:$Y$7,'STAF scores'!$F$12:$Y$12)/(15*SUMPRODUCT('STAF scores'!$F$7:$Y$7,'STAF scores'!$F$12:$Y$12)),NA()) | H53: =SUMPRODUCT('STAF scores'!$F$12:$Y$12*(1-ISNUMBER('STAF scores'!F63:Y63))) | I53: =IF(H53>0,NA(),(E53+F53+G53)/3) | J53: =IF(ISNUMBER(I53),IF(ROUND(I53,2)<=0.39,"Non-Functioning",IF(ROUND(I53,2)<=0.69,"Functioning-at-Risk","Functioning")),"") | K53: =IF(ISNUMBER('STAF scores'!E63),'STAF scores'!E63,NA()) | L53: =I53*K53
B54: ='STAF scores'!B64 | C54: ='STAF scores'!C64 | D54: ='STAF scores'!D64 | E54: =IF(SUMPRODUCT('STAF scores'!$F$5:$Y$5,'STAF scores'!$F$12:$Y$12)>0,SUMPRODUCT('STAF scores'!F64:Y64,'STAF scores'!$F$5:$Y$5,'STAF scores'!$F$12:$Y$12)/(15*SUMPRODUCT('STAF scores'!$F$5:$Y$5,'STAF scores'!$F$12:$Y$12)),NA()) | F54: =IF(SUMPRODUCT('STAF scores'!$F$6:$Y$6,'STAF scores'!$F$12:$Y$12)>0,SUMPRODUCT('STAF scores'!F64:Y64,'STAF scores'!$F$6:$Y$6,'STAF scores'!$F$12:$Y$12)/(15*SUMPRODUCT('STAF scores'!$F$6:$Y$6,'STAF scores'!$F$12:$Y$12)),NA()) | G54: =IF(SUMPRODUCT('STAF scores'!$F$7:$Y$7,'STAF scores'!$F$12:$Y$12)>0,SUMPRODUCT('STAF scores'!F64:Y64,'STAF scores'!$F$7:$Y$7,'STAF scores'!$F$12:$Y$12)/(15*SUMPRODUCT('STAF scores'!$F$7:$Y$7,'STAF scores'!$F$12:$Y$12)),NA()) | H54: =SUMPRODUCT('STAF scores'!$F$12:$Y$12*(1-ISNUMBER('STAF scores'!F64:Y64))) | I54: =IF(H54>0,NA(),(E54+F54+G54)/3) | J54: =IF(ISNUMBER(I54),IF(ROUND(I54,2)<=0.39,"Non-Functioning",IF(ROUND(I54,2)<=0.69,"Functioning-at-Risk","Functioning")),"") | K54: =IF(ISNUMBER('STAF scores'!E64),'STAF scores'!E64,NA()) | L54: =I54*K54
B55: ='STAF scores'!B65 | C55: ='STAF scores'!C65 | D55: ='STAF scores'!D65 | E55: =IF(SUMPRODUCT('STAF scores'!$F$5:$Y$5,'STAF scores'!$F$12:$Y$12)>0,SUMPRODUCT('STAF scores'!F65:Y65,'STAF scores'!$F$5:$Y$5,'STAF scores'!$F$12:$Y$12)/(15*SUMPRODUCT('STAF scores'!$F$5:$Y$5,'STAF scores'!$F$12:$Y$12)),NA()) | F55: =IF(SUMPRODUCT('STAF scores'!$F$6:$Y$6,'STAF scores'!$F$12:$Y$12)>0,SUMPRODUCT('STAF scores'!F65:Y65,'STAF scores'!$F$6:$Y$6,'STAF scores'!$F$12:$Y$12)/(15*SUMPRODUCT('STAF scores'!$F$6:$Y$6,'STAF scores'!$F$12:$Y$12)),NA()) | G55: =IF(SUMPRODUCT('STAF scores'!$F$7:$Y$7,'STAF scores'!$F$12:$Y$12)>0,SUMPRODUCT('STAF scores'!F65:Y65,'STAF scores'!$F$7:$Y$7,'STAF scores'!$F$12:$Y$12)/(15*SUMPRODUCT('STAF scores'!$F$7:$Y$7,'STAF scores'!$F$12:$Y$12)),NA()) | H55: =SUMPRODUCT('STAF scores'!$F$12:$Y$12*(1-ISNUMBER('STAF scores'!F65:Y65))) | I55: =IF(H55>0,NA(),(E55+F55+G55)/3) | J55: =IF(ISNUMBER(I55),IF(ROUND(I55,2)<=0.39,"Non-Functioning",IF(ROUND(I55,2)<=0.69,"Functioning-at-Risk","Functioning")),"") | K55: =IF(ISNUMBER('STAF scores'!E65),'STAF scores'!E65,NA()) | L55: =I55*K55
B56: ='STAF scores'!B66 | C56: ='STAF scores'!C66 | D56: ='STAF scores'!D66 | E56: =IF(SUMPRODUCT('STAF scores'!$F$5:$Y$5,'STAF scores'!$F$12:$Y$12)>0,SUMPRODUCT('STAF scores'!F66:Y66,'STAF scores'!$F$5:$Y$5,'STAF scores'!$F$12:$Y$12)/(15*SUMPRODUCT('STAF scores'!$F$5:$Y$5,'STAF scores'!$F$12:$Y$12)),NA()) | F56: =IF(SUMPRODUCT('STAF scores'!$F$6:$Y$6,'STAF scores'!$F$12:$Y$12)>0,SUMPRODUCT('STAF scores'!F66:Y66,'STAF scores'!$F$6:$Y$6,'STAF scores'!$F$12:$Y$12)/(15*SUMPRODUCT('STAF scores'!$F$6:$Y$6,'STAF scores'!$F$12:$Y$12)),NA()) | G56: =IF(SUMPRODUCT('STAF scores'!$F$7:$Y$7,'STAF scores'!$F$12:$Y$12)>0,SUMPRODUCT('STAF scores'!F66:Y66,'STAF scores'!$F$7:$Y$7,'STAF scores'!$F$12:$Y$12)/(15*SUMPRODUCT('STAF scores'!$F$7:$Y$7,'STAF scores'!$F$12:$Y$12)),NA()) | H56: =SUMPRODUCT('STAF scores'!$F$12:$Y$12*(1-ISNUMBER('STAF scores'!F66:Y66))) | I56: =IF(H56>0,NA(),(E56+F56+G56)/3) | J56: =IF(ISNUMBER(I56),IF(ROUND(I56,2)<=0.39,"Non-Functioning",IF(ROUND(I56,2)<=0.69,"Functioning-at-Risk","Functioning")),"") | K56: =IF(ISNUMBER('STAF scores'!E66),'STAF scores'!E66,NA()) | L56: =I56*K56
B57: ='STAF scores'!B67 | C57: ='STAF scores'!C67 | D57: ='STAF scores'!D67 | E57: =IF(SUMPRODUCT('STAF scores'!$F$5:$Y$5,'STAF scores'!$F$12:$Y$12)>0,SUMPRODUCT('STAF scores'!F67:Y67,'STAF scores'!$F$5:$Y$5,'STAF scores'!$F$12:$Y$12)/(15*SUMPRODUCT('STAF scores'!$F$5:$Y$5,'STAF scores'!$F$12:$Y$12)),NA()) | F57: =IF(SUMPRODUCT('STAF scores'!$F$6:$Y$6,'STAF scores'!$F$12:$Y$12)>0,SUMPRODUCT('STAF scores'!F67:Y67,'STAF scores'!$F$6:$Y$6,'STAF scores'!$F$12:$Y$12)/(15*SUMPRODUCT('STAF scores'!$F$6:$Y$6,'STAF scores'!$F$12:$Y$12)),NA()) | G57: =IF(SUMPRODUCT('STAF scores'!$F$7:$Y$7,'STAF scores'!$F$12:$Y$12)>0,SUMPRODUCT('STAF scores'!F67:Y67,'STAF scores'!$F$7:$Y$7,'STAF scores'!$F$12:$Y$12)/(15*SUMPRODUCT('STAF scores'!$F$7:$Y$7,'STAF scores'!$F$12:$Y$12)),NA()) | H57: =SUMPRODUCT('STAF scores'!$F$12:$Y$12*(1-ISNUMBER('STAF scores'!F67:Y67))) | I57: =IF(H57>0,NA(),(E57+F57+G57)/3) | J57: =IF(ISNUMBER(I57),IF(ROUND(I57,2)<=0.39,"Non-Functioning",IF(ROUND(I57,2)<=0.69,"Functioning-at-Risk","Functioning")),"") | K57: =IF(ISNUMBER('STAF scores'!E67),'STAF scores'!E67,NA()) | L57: =I57*K57
B58: ='STAF scores'!B68 | C58: ='STAF scores'!C68 | D58: ='STAF scores'!D68 | E58: =IF(SUMPRODUCT('STAF scores'!$F$5:$Y$5,'STAF scores'!$F$12:$Y$12)>0,SUMPRODUCT('STAF scores'!F68:Y68,'STAF scores'!$F$5:$Y$5,'STAF scores'!$F$12:$Y$12)/(15*SUMPRODUCT('STAF scores'!$F$5:$Y$5,'STAF scores'!$F$12:$Y$12)),NA()) | F58: =IF(SUMPRODUCT('STAF scores'!$F$6:$Y$6,'STAF scores'!$F$12:$Y$12)>0,SUMPRODUCT('STAF scores'!F68:Y68,'STAF scores'!$F$6:$Y$6,'STAF scores'!$F$12:$Y$12)/(15*SUMPRODUCT('STAF scores'!$F$6:$Y$6,'STAF scores'!$F$12:$Y$12)),NA()) | G58: =IF(SUMPRODUCT('STAF scores'!$F$7:$Y$7,'STAF scores'!$F$12:$Y$12)>0,SUMPRODUCT('STAF scores'!F68:Y68,'STAF scores'!$F$7:$Y$7,'STAF scores'!$F$12:$Y$12)/(15*SUMPRODUCT('STAF scores'!$F$7:$Y$7,'STAF scores'!$F$12:$Y$12)),NA()) | H58: =SUMPRODUCT('STAF scores'!$F$12:$Y$12*(1-ISNUMBER('STAF scores'!F68:Y68))) | I58: =IF(H58>0,NA(),(E58+F58+G58)/3) | J58: =IF(ISNUMBER(I58),IF(ROUND(I58,2)<=0.39,"Non-Functioning",IF(ROUND(I58,2)<=0.69,"Functioning-at-Risk","Functioning")),"") | K58: =IF(ISNUMBER('STAF scores'!E68),'STAF scores'!E68,NA()) | L58: =I58*K58
... B64: ='STAF scores'!B74 | C64: ='STAF scores'!C74 | D64: ='STAF scores'!D74 | E64: =IF(SUMPRODUCT('STAF scores'!$F$5:$Y$5,'STAF scores'!$F$12:$Y$12)>0,SUMPRODUCT('STAF scores'!F74:Y74,'STAF scores'!$F$5:$Y$5,'STAF scores'!$F$12:$Y$12)/(15*SUMPRODUCT('STAF scores'!$F$5:$Y$5,'STAF scores'!$F$12:$Y$12)),NA()) | F64: =IF(SUMPRODUCT('STAF scores'!$F$6:$Y$6,'STAF scores'!$F$12:$Y$12)>0,SUMPRODUCT('STAF scores'!F74:Y74,'STAF scores'!$F$6:$Y$6,'STAF scores'!$F$12:$Y$12)/(15*SUMPRODUCT('STAF scores'!$F$6:$Y$6,'STAF scores'!$F$12:$Y$12)),NA()) | G64: =IF(SUMPRODUCT('STAF scores'!$F$7:$Y$7,'STAF scores'!$F$12:$Y$12)>0,SUMPRODUCT('STAF scores'!F74:Y74,'STAF scores'!$F$7:$Y$7,'STAF scores'!$F$12:$Y$12)/(15*SUMPRODUCT('STAF scores'!$F$7:$Y$7,'STAF scores'!$F$12:$Y$12)),NA()) | H64: =SUMPRODUCT('STAF scores'!$F$12:$Y$12*(1-ISNUMBER('STAF scores'!F74:Y74))) | I64: =IF(H64>0,NA(),(E64+F64+G64)/3) | J64: =IF(ISNUMBER(I64),IF(ROUND(I64,2)<=0.39,"Non-Functioning",IF(ROUND(I64,2)<=0.69,"Functioning-at-Risk","Functioning")),"") | K64: =IF(ISNUMBER('STAF scores'!E74),'STAF scores'!E74,NA()) | L64: =I64*K64

Sheet Benefits
A1: Benefits: condition units at each target year
A2: STAF mode: condition units (ECI x quantity) at each target year, from the STAF roll-up sheet.
A4: Key | B4: Site | C4: Alternative | D4: Component | E4: Condition units (CU) | K4: Average (AACU)
E5: =Parameters!$B$14 | F5: =Parameters!$C$14 | G5: =Parameters!$D$14 | H5: =Parameters!$E$14 | I5: =Parameters!$F$14 | J5: =Parameters!$G$14
A6: =B6&"|"&C6 | B6: R1 | C6: FWOP | D6: Condition units | E6: ='STAF roll-up'!L5 | F6: ='STAF roll-up'!L6 | G6: ='STAF roll-up'!L7 | H6: ='STAF roll-up'!L8 | I6: ='STAF roll-up'!L9 | J6: ='STAF roll-up'!L10 | K6: =SUMPRODUCT($F$5:$J$5-$E$5:$I$5,(F6:J6+E6:I6)/2)/($J$5-$E$5)
A7: =B7&"|"&C7 | B7: R1 | C7: A1 | D7: Condition units | E7: ='STAF roll-up'!L11 | F7: ='STAF roll-up'!L12 | G7: ='STAF roll-up'!L13 | H7: ='STAF roll-up'!L14 | I7: ='STAF roll-up'!L15 | J7: ='STAF roll-up'!L16 | K7: =SUMPRODUCT($F$5:$J$5-$E$5:$I$5,(F7:J7+E7:I7)/2)/($J$5-$E$5)
A8: =B8&"|"&C8 | B8: R1 | C8: A2 | D8: Condition units | E8: ='STAF roll-up'!L17 | F8: ='STAF roll-up'!L18 | G8: ='STAF roll-up'!L19 | H8: ='STAF roll-up'!L20 | I8: ='STAF roll-up'!L21 | J8: ='STAF roll-up'!L22 | K8: =SUMPRODUCT($F$5:$J$5-$E$5:$I$5,(F8:J8+E8:I8)/2)/($J$5-$E$5)
A9: =B9&"|"&C9 | B9: R1 | C9: A3 | D9: Condition units | E9: ='STAF roll-up'!L23 | F9: ='STAF roll-up'!L24 | G9: ='STAF roll-up'!L25 | H9: ='STAF roll-up'!L26 | I9: ='STAF roll-up'!L27 | J9: ='STAF roll-up'!L28 | K9: =SUMPRODUCT($F$5:$J$5-$E$5:$I$5,(F9:J9+E9:I9)/2)/($J$5-$E$5)
A10: =B10&"|"&C10 | B10: R2 | C10: FWOP | D10: Condition units | E10: ='STAF roll-up'!L29 | F10: ='STAF roll-up'!L30 | G10: ='STAF roll-up'!L31 | H10: ='STAF roll-up'!L32 | I10: ='STAF roll-up'!L33 | J10: ='STAF roll-up'!L34 | K10: =SUMPRODUCT($F$5:$J$5-$E$5:$I$5,(F10:J10+E10:I10)/2)/($J$5-$E$5)
A11: =B11&"|"&C11 | B11: R2 | C11: A1 | D11: Condition units | E11: ='STAF roll-up'!L35 | F11: ='STAF roll-up'!L36 | G11: ='STAF roll-up'!L37 | H11: ='STAF roll-up'!L38 | I11: ='STAF roll-up'!L39 | J11: ='STAF roll-up'!L40 | K11: =SUMPRODUCT($F$5:$J$5-$E$5:$I$5,(F11:J11+E11:I11)/2)/($J$5-$E$5)
A12: =B12&"|"&C12 | B12: R2 | C12: A2 | D12: Condition units | E12: ='STAF roll-up'!L41 | F12: ='STAF roll-up'!L42 | G12: ='STAF roll-up'!L43 | H12: ='STAF roll-up'!L44 | I12: ='STAF roll-up'!L45 | J12: ='STAF roll-up'!L46 | K12: =SUMPRODUCT($F$5:$J$5-$E$5:$I$5,(F12:J12+E12:I12)/2)/($J$5-$E$5)
A13: =B13&"|"&C13 | B13: R3 | C13: FWOP | D13: Condition units | E13: ='STAF roll-up'!L47 | F13: ='STAF roll-up'!L48 | G13: ='STAF roll-up'!L49 | H13: ='STAF roll-up'!L50 | I13: ='STAF roll-up'!L51 | J13: ='STAF roll-up'!L52 | K13: =SUMPRODUCT($F$5:$J$5-$E$5:$I$5,(F13:J13+E13:I13)/2)/($J$5-$E$5)
A14: =B14&"|"&C14 | B14: R3 | C14: A1 | D14: Condition units | E14: ='STAF roll-up'!L53 | F14: ='STAF roll-up'!L54 | G14: ='STAF roll-up'!L55 | H14: ='STAF roll-up'!L56 | I14: ='STAF roll-up'!L57 | J14: ='STAF roll-up'!L58 | K14: =SUMPRODUCT($F$5:$J$5-$E$5:$I$5,(F14:J14+E14:I14)/2)/($J$5-$E$5)
A15: =B15&"|"&C15 | B15: R3 | C15: A2 | D15: Condition units | E15: ='STAF roll-up'!L59 | F15: ='STAF roll-up'!L60 | G15: ='STAF roll-up'!L61 | H15: ='STAF roll-up'!L62 | I15: ='STAF roll-up'!L63 | J15: ='STAF roll-up'!L64 | K15: =SUMPRODUCT($F$5:$J$5-$E$5:$I$5,(F15:J15+E15:I15)/2)/($J$5-$E$5)

Sheet Costs
A1: Costs: first costs, interest during construction and OMRRR
A2: First costs are base-year lump sums. Interest during construction accrues on the categories marked *, spent evenly over the construction months.
N3: Average annual cost by part
A4: Key | B4: Site | C4: Alternative | D4: Construction * | E4: Monitoring | F4: Adaptive management | G4: Construction months | H4: IDC base | I4: Interest during construction | J4: OMRRR present value | K4: Total present value | L4: Average annual cost entered | M4: Average annual cost | N4: Construction | O4: Monitoring | P4: Adaptive management | Q4: Interest during construction | R4: OMRRR
D5: construction | E5: monitoring | F5: adaptive_management
A6: =B6&"|"&C6 | B6: R1 | C6: FWOP | G6: 0 | H6: =D6 | I6: =IF(OR(G6=0,in_rate=0,H6=0),0,H6/G6*(IF(in_idc_method="START",1+((1+in_rate)^(1/in_ppy)-1),IF(in_idc_method="MIDDLE",1+((1+in_rate)^(1/in_ppy)-1)/2,1))*((1+in_rate)^(G6/in_ppy)-1)/((1+in_rate)^(1/in_ppy)-1)-G6)) | J6: =SUMIFS(OMRRR!$S$5:$S$19,OMRRR!$A$5:$A$19,A6) | K6: =SUM(D6:F6)+I6+J6 | M6: =IF(ISNUMBER(L6),L6,calc_crf*K6) | N6: =calc_crf*D6 | O6: =calc_crf*E6 | P6: =calc_crf*F6 | Q6: =calc_crf*I6 | R6: =calc_crf*J6
A7: =B7&"|"&C7 | B7: R1 | C7: A1 | D7: 180000 | E7: 25000 | F7: 15000 | G7: 4 | H7: =D7 | I7: =IF(OR(G7=0,in_rate=0,H7=0),0,H7/G7*(IF(in_idc_method="START",1+((1+in_rate)^(1/in_ppy)-1),IF(in_idc_method="MIDDLE",1+((1+in_rate)^(1/in_ppy)-1)/2,1))*((1+in_rate)^(G7/in_ppy)-1)/((1+in_rate)^(1/in_ppy)-1)-G7)) | J7: =SUMIFS(OMRRR!$S$5:$S$19,OMRRR!$A$5:$A$19,A7) | K7: =SUM(D7:F7)+I7+J7 | M7: =IF(ISNUMBER(L7),L7,calc_crf*K7) | N7: =calc_crf*D7 | O7: =calc_crf*E7 | P7: =calc_crf*F7 | Q7: =calc_crf*I7 | R7: =calc_crf*J7
A8: =B8&"|"&C8 | B8: R1 | C8: A2 | D8: 620000 | E8: 40000 | F8: 60000 | G8: 8 | H8: =D8 | I8: =IF(OR(G8=0,in_rate=0,H8=0),0,H8/G8*(IF(in_idc_method="START",1+((1+in_rate)^(1/in_ppy)-1),IF(in_idc_method="MIDDLE",1+((1+in_rate)^(1/in_ppy)-1)/2,1))*((1+in_rate)^(G8/in_ppy)-1)/((1+in_rate)^(1/in_ppy)-1)-G8)) | J8: =SUMIFS(OMRRR!$S$5:$S$19,OMRRR!$A$5:$A$19,A8) | K8: =SUM(D8:F8)+I8+J8 | M8: =IF(ISNUMBER(L8),L8,calc_crf*K8) | N8: =calc_crf*D8 | O8: =calc_crf*E8 | P8: =calc_crf*F8 | Q8: =calc_crf*I8 | R8: =calc_crf*J8
A9: =B9&"|"&C9 | B9: R1 | C9: A3 | D9: 910000 | E9: 50000 | F9: 90000 | G9: 10 | H9: =D9 | I9: =IF(OR(G9=0,in_rate=0,H9=0),0,H9/G9*(IF(in_idc_method="START",1+((1+in_rate)^(1/in_ppy)-1),IF(in_idc_method="MIDDLE",1+((1+in_rate)^(1/in_ppy)-1)/2,1))*((1+in_rate)^(G9/in_ppy)-1)/((1+in_rate)^(1/in_ppy)-1)-G9)) | J9: =SUMIFS(OMRRR!$S$5:$S$19,OMRRR!$A$5:$A$19,A9) | K9: =SUM(D9:F9)+I9+J9 | M9: =IF(ISNUMBER(L9),L9,calc_crf*K9) | N9: =calc_crf*D9 | O9: =calc_crf*E9 | P9: =calc_crf*F9 | Q9: =calc_crf*I9 | R9: =calc_crf*J9
A10: =B10&"|"&C10 | B10: R2 | C10: FWOP | G10: 0 | H10: =D10 | I10: =IF(OR(G10=0,in_rate=0,H10=0),0,H10/G10*(IF(in_idc_method="START",1+((1+in_rate)^(1/in_ppy)-1),IF(in_idc_method="MIDDLE",1+((1+in_rate)^(1/in_ppy)-1)/2,1))*((1+in_rate)^(G10/in_ppy)-1)/((1+in_rate)^(1/in_ppy)-1)-G10)) | J10: =SUMIFS(OMRRR!$S$5:$S$19,OMRRR!$A$5:$A$19,A10) | K10: =SUM(D10:F10)+I10+J10 | M10: =IF(ISNUMBER(L10),L10,calc_crf*K10) | N10: =calc_crf*D10 | O10: =calc_crf*E10 | P10: =calc_crf*F10 | Q10: =calc_crf*I10 | R10: =calc_crf*J10
A11: =B11&"|"&C11 | B11: R2 | C11: A1 | D11: 850000 | E11: 45000 | F11: 85000 | G11: 9 | H11: =D11 | I11: =IF(OR(G11=0,in_rate=0,H11=0),0,H11/G11*(IF(in_idc_method="START",1+((1+in_rate)^(1/in_ppy)-1),IF(in_idc_method="MIDDLE",1+((1+in_rate)^(1/in_ppy)-1)/2,1))*((1+in_rate)^(G11/in_ppy)-1)/((1+in_rate)^(1/in_ppy)-1)-G11)) | J11: =SUMIFS(OMRRR!$S$5:$S$19,OMRRR!$A$5:$A$19,A11) | K11: =SUM(D11:F11)+I11+J11 | M11: =IF(ISNUMBER(L11),L11,calc_crf*K11) | N11: =calc_crf*D11 | O11: =calc_crf*E11 | P11: =calc_crf*F11 | Q11: =calc_crf*I11 | R11: =calc_crf*J11
A12: =B12&"|"&C12 | B12: R2 | C12: A2 | D12: 3400000 | E12: 90000 | F12: 340000 | G12: 18 | H12: =D12 | I12: =IF(OR(G12=0,in_rate=0,H12=0),0,H12/G12*(IF(in_idc_method="START",1+((1+in_rate)^(1/in_ppy)-1),IF(in_idc_method="MIDDLE",1+((1+in_rate)^(1/in_ppy)-1)/2,1))*((1+in_rate)^(G12/in_ppy)-1)/((1+in_rate)^(1/in_ppy)-1)-G12)) | J12: =SUMIFS(OMRRR!$S$5:$S$19,OMRRR!$A$5:$A$19,A12) | K12: =SUM(D12:F12)+I12+J12 | M12: =IF(ISNUMBER(L12),L12,calc_crf*K12) | N12: =calc_crf*D12 | O12: =calc_crf*E12 | P12: =calc_crf*F12 | Q12: =calc_crf*I12 | R12: =calc_crf*J12
A13: =B13&"|"&C13 | B13: R3 | C13: FWOP | G13: 0 | H13: =D13 | I13: =IF(OR(G13=0,in_rate=0,H13=0),0,H13/G13*(IF(in_idc_method="START",1+((1+in_rate)^(1/in_ppy)-1),IF(in_idc_method="MIDDLE",1+((1+in_rate)^(1/in_ppy)-1)/2,1))*((1+in_rate)^(G13/in_ppy)-1)/((1+in_rate)^(1/in_ppy)-1)-G13)) | J13: =SUMIFS(OMRRR!$S$5:$S$19,OMRRR!$A$5:$A$19,A13) | K13: =SUM(D13:F13)+I13+J13 | M13: =IF(ISNUMBER(L13),L13,calc_crf*K13) | N13: =calc_crf*D13 | O13: =calc_crf*E13 | P13: =calc_crf*F13 | Q13: =calc_crf*I13 | R13: =calc_crf*J13
A14: =B14&"|"&C14 | B14: R3 | C14: A1 | D14: 140000 | E14: 20000 | F14: 10000 | G14: 3 | H14: =D14 | I14: =IF(OR(G14=0,in_rate=0,H14=0),0,H14/G14*(IF(in_idc_method="START",1+((1+in_rate)^(1/in_ppy)-1),IF(in_idc_method="MIDDLE",1+((1+in_rate)^(1/in_ppy)-1)/2,1))*((1+in_rate)^(G14/in_ppy)-1)/((1+in_rate)^(1/in_ppy)-1)-G14)) | J14: =SUMIFS(OMRRR!$S$5:$S$19,OMRRR!$A$5:$A$19,A14) | K14: =SUM(D14:F14)+I14+J14 | M14: =IF(ISNUMBER(L14),L14,calc_crf*K14) | N14: =calc_crf*D14 | O14: =calc_crf*E14 | P14: =calc_crf*F14 | Q14: =calc_crf*I14 | R14: =calc_crf*J14
A15: =B15&"|"&C15 | B15: R3 | C15: A2 | D15: 520000 | E15: 30000 | F15: 40000 | G15: 6 | H15: =D15 | I15: =IF(OR(G15=0,in_rate=0,H15=0),0,H15/G15*(IF(in_idc_method="START",1+((1+in_rate)^(1/in_ppy)-1),IF(in_idc_method="MIDDLE",1+((1+in_rate)^(1/in_ppy)-1)/2,1))*((1+in_rate)^(G15/in_ppy)-1)/((1+in_rate)^(1/in_ppy)-1)-G15)) | J15: =SUMIFS(OMRRR!$S$5:$S$19,OMRRR!$A$5:$A$19,A15) | K15: =SUM(D15:F15)+I15+J15 | M15: =IF(ISNUMBER(L15),L15,calc_crf*K15) | N15: =calc_crf*D15 | O15: =calc_crf*E15 | P15: =calc_crf*F15 | Q15: =calc_crf*I15 | R15: =calc_crf*J15

Sheet OMRRR
A1: OMRRR: recurring operation, maintenance, repair, replacement and rehabilitation
A2: Each item costs the amount per occurrence every N years from the first year to the last (blank: every N years through the period of analysis). Basis: FIXED amount, PERCENT of a first-cost category, or RATE x quantity.
A4: Key | B4: Site | C4: Alternative | D4: Item | E4: Basis | F4: Amount | G4: Percent | H4: Category | I4: Unit rate | J4: Quantity | K4: Every N years | L4: First year | M4: Last year | N4: Amount per occurrence | O4: First | P4: Last | Q4: Occurrences | R4: Present value, end of year | S4: Present value
A5: =B5&"|"&C5 | B5: R1 | C5: A1 | D5: Annual maintenance | E5: FIXED | F5: 2500 | K5: 1 | N5: =IF(E5="FIXED",F5,IF(E5="PERCENT",G5*IFERROR(INDEX(Costs!$D$6:$F$15,MATCH(A5,Costs!$A$6:$A$15,0),MATCH(H5,Costs!$D$5:$F$5,0)),0),I5*J5)) | O5: =IF(ISNUMBER(L5),L5,K5) | P5: =IF(ISNUMBER(M5),MIN(M5,in_poa),in_poa) | Q5: =IF(P5<O5,0,INT((P5-O5)/K5)+1) | R5: =IF(Q5=0,0,IF(in_rate=0,N5*Q5,N5*(1+in_rate)^(-O5)*(1-(1+in_rate)^(-K5*Q5))/(1-(1+in_rate)^(-K5)))) | S5: =IF(in_timing="MID_YEAR",IF(O5=0,IF(Q5=0,0,N5+(R5-N5)*(1+in_rate)^0.5),R5*(1+in_rate)^0.5),R5)
A6: =B6&"|"&C6 | B6: R1 | C6: A1 | D6: Repair and replanting | E6: PERCENT | G6: 0.1 | H6: construction | K6: 10 | N6: =IF(E6="FIXED",F6,IF(E6="PERCENT",G6*IFERROR(INDEX(Costs!$D$6:$F$15,MATCH(A6,Costs!$A$6:$A$15,0),MATCH(H6,Costs!$D$5:$F$5,0)),0),I6*J6)) | O6: =IF(ISNUMBER(L6),L6,K6) | P6: =IF(ISNUMBER(M6),MIN(M6,in_poa),in_poa) | Q6: =IF(P6<O6,0,INT((P6-O6)/K6)+1) | R6: =IF(Q6=0,0,IF(in_rate=0,N6*Q6,N6*(1+in_rate)^(-O6)*(1-(1+in_rate)^(-K6*Q6))/(1-(1+in_rate)^(-K6)))) | S6: =IF(in_timing="MID_YEAR",IF(O6=0,IF(Q6=0,0,N6+(R6-N6)*(1+in_rate)^0.5),R6*(1+in_rate)^0.5),R6)
A7: =B7&"|"&C7 | B7: R1 | C7: A2 | D7: Annual maintenance | E7: FIXED | F7: 5000 | K7: 1 | N7: =IF(E7="FIXED",F7,IF(E7="PERCENT",G7*IFERROR(INDEX(Costs!$D$6:$F$15,MATCH(A7,Costs!$A$6:$A$15,0),MATCH(H7,Costs!$D$5:$F$5,0)),0),I7*J7)) | O7: =IF(ISNUMBER(L7),L7,K7) | P7: =IF(ISNUMBER(M7),MIN(M7,in_poa),in_poa) | Q7: =IF(P7<O7,0,INT((P7-O7)/K7)+1) | R7: =IF(Q7=0,0,IF(in_rate=0,N7*Q7,N7*(1+in_rate)^(-O7)*(1-(1+in_rate)^(-K7*Q7))/(1-(1+in_rate)^(-K7)))) | S7: =IF(in_timing="MID_YEAR",IF(O7=0,IF(Q7=0,0,N7+(R7-N7)*(1+in_rate)^0.5),R7*(1+in_rate)^0.5),R7)
A8: =B8&"|"&C8 | B8: R1 | C8: A2 | D8: Repair and replanting | E8: PERCENT | G8: 0.1 | H8: construction | K8: 25 | N8: =IF(E8="FIXED",F8,IF(E8="PERCENT",G8*IFERROR(INDEX(Costs!$D$6:$F$15,MATCH(A8,Costs!$A$6:$A$15,0),MATCH(H8,Costs!$D$5:$F$5,0)),0),I8*J8)) | O8: =IF(ISNUMBER(L8),L8,K8) | P8: =IF(ISNUMBER(M8),MIN(M8,in_poa),in_poa) | Q8: =IF(P8<O8,0,INT((P8-O8)/K8)+1) | R8: =IF(Q8=0,0,IF(in_rate=0,N8*Q8,N8*(1+in_rate)^(-O8)*(1-(1+in_rate)^(-K8*Q8))/(1-(1+in_rate)^(-K8)))) | S8: =IF(in_timing="MID_YEAR",IF(O8=0,IF(Q8=0,0,N8+(R8-N8)*(1+in_rate)^0.5),R8*(1+in_rate)^0.5),R8)
A9: =B9&"|"&C9 | B9: R1 | C9: A3 | D9: Annual maintenance | E9: FIXED | F9: 6000 | K9: 1 | N9: =IF(E9="FIXED",F9,IF(E9="PERCENT",G9*IFERROR(INDEX(Costs!$D$6:$F$15,MATCH(A9,Costs!$A$6:$A$15,0),MATCH(H9,Costs!$D$5:$F$5,0)),0),I9*J9)) | O9: =IF(ISNUMBER(L9),L9,K9) | P9: =IF(ISNUMBER(M9),MIN(M9,in_poa),in_poa) | Q9: =IF(P9<O9,0,INT((P9-O9)/K9)+1) | R9: =IF(Q9=0,0,IF(in_rate=0,N9*Q9,N9*(1+in_rate)^(-O9)*(1-(1+in_rate)^(-K9*Q9))/(1-(1+in_rate)^(-K9)))) | S9: =IF(in_timing="MID_YEAR",IF(O9=0,IF(Q9=0,0,N9+(R9-N9)*(1+in_rate)^0.5),R9*(1+in_rate)^0.5),R9)
A10: =B10&"|"&C10 | B10: R1 | C10: A3 | D10: Repair and replanting | E10: PERCENT | G10: 0.1 | H10: construction | K10: 25 | N10: =IF(E10="FIXED",F10,IF(E10="PERCENT",G10*IFERROR(INDEX(Costs!$D$6:$F$15,MATCH(A10,Costs!$A$6:$A$15,0),MATCH(H10,Costs!$D$5:$F$5,0)),0),I10*J10)) | O10: =IF(ISNUMBER(L10),L10,K10) | P10: =IF(ISNUMBER(M10),MIN(M10,in_poa),in_poa) | Q10: =IF(P10<O10,0,INT((P10-O10)/K10)+1) | R10: =IF(Q10=0,0,IF(in_rate=0,N10*Q10,N10*(1+in_rate)^(-O10)*(1-(1+in_rate)^(-K10*Q10))/(1-(1+in_rate)^(-K10)))) | S10: =IF(in_timing="MID_YEAR",IF(O10=0,IF(Q10=0,0,N10+(R10-N10)*(1+in_rate)^0.5),R10*(1+in_rate)^0.5),R10)
A11: =B11&"|"&C11 | B11: R1 | C11: A3 | D11: Structure inspection | E11: RATE | I11: 1.5 | J11: 1000 | K11: 5 | N11: =IF(E11="FIXED",F11,IF(E11="PERCENT",G11*IFERROR(INDEX(Costs!$D$6:$F$15,MATCH(A11,Costs!$A$6:$A$15,0),MATCH(H11,Costs!$D$5:$F$5,0)),0),I11*J11)) | O11: =IF(ISNUMBER(L11),L11,K11) | P11: =IF(ISNUMBER(M11),MIN(M11,in_poa),in_poa) | Q11: =IF(P11<O11,0,INT((P11-O11)/K11)+1) | R11: =IF(Q11=0,0,IF(in_rate=0,N11*Q11,N11*(1+in_rate)^(-O11)*(1-(1+in_rate)^(-K11*Q11))/(1-(1+in_rate)^(-K11)))) | S11: =IF(in_timing="MID_YEAR",IF(O11=0,IF(Q11=0,0,N11+(R11-N11)*(1+in_rate)^0.5),R11*(1+in_rate)^0.5),R11)
A12: =B12&"|"&C12 | B12: R2 | C12: A1 | D12: Annual maintenance | E12: FIXED | F12: 6000 | K12: 1 | N12: =IF(E12="FIXED",F12,IF(E12="PERCENT",G12*IFERROR(INDEX(Costs!$D$6:$F$15,MATCH(A12,Costs!$A$6:$A$15,0),MATCH(H12,Costs!$D$5:$F$5,0)),0),I12*J12)) | O12: =IF(ISNUMBER(L12),L12,K12) | P12: =IF(ISNUMBER(M12),MIN(M12,in_poa),in_poa) | Q12: =IF(P12<O12,0,INT((P12-O12)/K12)+1) | R12: =IF(Q12=0,0,IF(in_rate=0,N12*Q12,N12*(1+in_rate)^(-O12)*(1-(1+in_rate)^(-K12*Q12))/(1-(1+in_rate)^(-K12)))) | S12: =IF(in_timing="MID_YEAR",IF(O12=0,IF(Q12=0,0,N12+(R12-N12)*(1+in_rate)^0.5),R12*(1+in_rate)^0.5),R12)
A13: =B13&"|"&C13 | B13: R2 | C13: A1 | D13: Repair and replanting | E13: PERCENT | G13: 0.1 | H13: construction | K13: 25 | N13: =IF(E13="FIXED",F13,IF(E13="PERCENT",G13*IFERROR(INDEX(Costs!$D$6:$F$15,MATCH(A13,Costs!$A$6:$A$15,0),MATCH(H13,Costs!$D$5:$F$5,0)),0),I13*J13)) | O13: =IF(ISNUMBER(L13),L13,K13) | P13: =IF(ISNUMBER(M13),MIN(M13,in_poa),in_poa) | Q13: =IF(P13<O13,0,INT((P13-O13)/K13)+1) | R13: =IF(Q13=0,0,IF(in_rate=0,N13*Q13,N13*(1+in_rate)^(-O13)*(1-(1+in_rate)^(-K13*Q13))/(1-(1+in_rate)^(-K13)))) | S13: =IF(in_timing="MID_YEAR",IF(O13=0,IF(Q13=0,0,N13+(R13-N13)*(1+in_rate)^0.5),R13*(1+in_rate)^0.5),R13)
A14: =B14&"|"&C14 | B14: R2 | C14: A2 | D14: Annual maintenance | E14: FIXED | F14: 12000 | K14: 1 | N14: =IF(E14="FIXED",F14,IF(E14="PERCENT",G14*IFERROR(INDEX(Costs!$D$6:$F$15,MATCH(A14,Costs!$A$6:$A$15,0),MATCH(H14,Costs!$D$5:$F$5,0)),0),I14*J14)) | O14: =IF(ISNUMBER(L14),L14,K14) | P14: =IF(ISNUMBER(M14),MIN(M14,in_poa),in_poa) | Q14: =IF(P14<O14,0,INT((P14-O14)/K14)+1) | R14: =IF(Q14=0,0,IF(in_rate=0,N14*Q14,N14*(1+in_rate)^(-O14)*(1-(1+in_rate)^(-K14*Q14))/(1-(1+in_rate)^(-K14)))) | S14: =IF(in_timing="MID_YEAR",IF(O14=0,IF(Q14=0,0,N14+(R14-N14)*(1+in_rate)^0.5),R14*(1+in_rate)^0.5),R14)
A15: =B15&"|"&C15 | B15: R2 | C15: A2 | D15: Repair and replanting | E15: PERCENT | G15: 0.05 | H15: construction | K15: 10 | N15: =IF(E15="FIXED",F15,IF(E15="PERCENT",G15*IFERROR(INDEX(Costs!$D$6:$F$15,MATCH(A15,Costs!$A$6:$A$15,0),MATCH(H15,Costs!$D$5:$F$5,0)),0),I15*J15)) | O15: =IF(ISNUMBER(L15),L15,K15) | P15: =IF(ISNUMBER(M15),MIN(M15,in_poa),in_poa) | Q15: =IF(P15<O15,0,INT((P15-O15)/K15)+1) | R15: =IF(Q15=0,0,IF(in_rate=0,N15*Q15,N15*(1+in_rate)^(-O15)*(1-(1+in_rate)^(-K15*Q15))/(1-(1+in_rate)^(-K15)))) | S15: =IF(in_timing="MID_YEAR",IF(O15=0,IF(Q15=0,0,N15+(R15-N15)*(1+in_rate)^0.5),R15*(1+in_rate)^0.5),R15)
A16: =B16&"|"&C16 | B16: R3 | C16: A1 | D16: Annual maintenance | E16: FIXED | F16: 1500 | K16: 1 | N16: =IF(E16="FIXED",F16,IF(E16="PERCENT",G16*IFERROR(INDEX(Costs!$D$6:$F$15,MATCH(A16,Costs!$A$6:$A$15,0),MATCH(H16,Costs!$D$5:$F$5,0)),0),I16*J16)) | O16: =IF(ISNUMBER(L16),L16,K16) | P16: =IF(ISNUMBER(M16),MIN(M16,in_poa),in_poa) | Q16: =IF(P16<O16,0,INT((P16-O16)/K16)+1) | R16: =IF(Q16=0,0,IF(in_rate=0,N16*Q16,N16*(1+in_rate)^(-O16)*(1-(1+in_rate)^(-K16*Q16))/(1-(1+in_rate)^(-K16)))) | S16: =IF(in_timing="MID_YEAR",IF(O16=0,IF(Q16=0,0,N16+(R16-N16)*(1+in_rate)^0.5),R16*(1+in_rate)^0.5),R16)
A17: =B17&"|"&C17 | B17: R3 | C17: A1 | D17: Fence repair | E17: RATE | I17: 2 | J17: 3200 | K17: 10 | N17: =IF(E17="FIXED",F17,IF(E17="PERCENT",G17*IFERROR(INDEX(Costs!$D$6:$F$15,MATCH(A17,Costs!$A$6:$A$15,0),MATCH(H17,Costs!$D$5:$F$5,0)),0),I17*J17)) | O17: =IF(ISNUMBER(L17),L17,K17) | P17: =IF(ISNUMBER(M17),MIN(M17,in_poa),in_poa) | Q17: =IF(P17<O17,0,INT((P17-O17)/K17)+1) | R17: =IF(Q17=0,0,IF(in_rate=0,N17*Q17,N17*(1+in_rate)^(-O17)*(1-(1+in_rate)^(-K17*Q17))/(1-(1+in_rate)^(-K17)))) | S17: =IF(in_timing="MID_YEAR",IF(O17=0,IF(Q17=0,0,N17+(R17-N17)*(1+in_rate)^0.5),R17*(1+in_rate)^0.5),R17)
A18: =B18&"|"&C18 | B18: R3 | C18: A2 | D18: Annual maintenance | E18: FIXED | F18: 3000 | K18: 1 | N18: =IF(E18="FIXED",F18,IF(E18="PERCENT",G18*IFERROR(INDEX(Costs!$D$6:$F$15,MATCH(A18,Costs!$A$6:$A$15,0),MATCH(H18,Costs!$D$5:$F$5,0)),0),I18*J18)) | O18: =IF(ISNUMBER(L18),L18,K18) | P18: =IF(ISNUMBER(M18),MIN(M18,in_poa),in_poa) | Q18: =IF(P18<O18,0,INT((P18-O18)/K18)+1) | R18: =IF(Q18=0,0,IF(in_rate=0,N18*Q18,N18*(1+in_rate)^(-O18)*(1-(1+in_rate)^(-K18*Q18))/(1-(1+in_rate)^(-K18)))) | S18: =IF(in_timing="MID_YEAR",IF(O18=0,IF(Q18=0,0,N18+(R18-N18)*(1+in_rate)^0.5),R18*(1+in_rate)^0.5),R18)
A19: =B19&"|"&C19 | B19: R3 | C19: A2 | D19: Culvert inspection | E19: FIXED | F19: 2000 | K19: 5 | N19: =IF(E19="FIXED",F19,IF(E19="PERCENT",G19*IFERROR(INDEX(Costs!$D$6:$F$15,MATCH(A19,Costs!$A$6:$A$15,0),MATCH(H19,Costs!$D$5:$F$5,0)),0),I19*J19)) | O19: =IF(ISNUMBER(L19),L19,K19) | P19: =IF(ISNUMBER(M19),MIN(M19,in_poa),in_poa) | Q19: =IF(P19<O19,0,INT((P19-O19)/K19)+1) | R19: =IF(Q19=0,0,IF(in_rate=0,N19*Q19,N19*(1+in_rate)^(-O19)*(1-(1+in_rate)^(-K19*Q19))/(1-(1+in_rate)^(-K19)))) | S19: =IF(in_timing="MID_YEAR",IF(O19=0,IF(Q19=0,0,N19+(R19-N19)*(1+in_rate)^0.5),R19*(1+in_rate)^0.5),R19)

Sheet Summary
A1: Summary of inputs to CE/ICA
A2: Lift is each alternative's AACU above No Action; the CE/ICA cost is its average annual cost above No Action.
A4: Key | B4: Site | C4: Alternative | D4: Name | E4: No Action | F4: Outputs (AACU) | G4: Lift (AACU) | H4: Construction cost | I4: First costs | J4: Interest during construction | K4: OMRRR present value | L4: Average annual cost | M4: Cost above No Action | N4: Unit cost ($/AACU)
A5: =B5&"|"&C5 | B5: R1 | C5: FWOP | D5: No Action | E5: 1 | F5: =SUMIFS(Benefits!$K$6:$K$15,Benefits!$A$6:$A$15,A5) | G5: =F5-$F$5 | H5: =Costs!D6 | I5: =SUM(Costs!D6:F6) | J5: =Costs!I6 | K5: =Costs!J6 | L5: =Costs!M6 | M5: =L5-$L$5 | N5: =IF(G5>0,M5/G5,"n/a")
A6: =B6&"|"&C6 | B6: R1 | C6: A1 | D6: Riparian buffer | E6: 0 | F6: =SUMIFS(Benefits!$K$6:$K$15,Benefits!$A$6:$A$15,A6) | G6: =F6-$F$5 | H6: =Costs!D7 | I6: =SUM(Costs!D7:F7) | J6: =Costs!I7 | K6: =Costs!J7 | L6: =Costs!M7 | M6: =L6-$L$5 | N6: =IF(G6>0,M6/G6,"n/a")
A7: =B7&"|"&C7 | B7: R1 | C7: A2 | D7: Floodplain bench and buffer | E7: 0 | F7: =SUMIFS(Benefits!$K$6:$K$15,Benefits!$A$6:$A$15,A7) | G7: =F7-$F$5 | H7: =Costs!D8 | I7: =SUM(Costs!D8:F8) | J7: =Costs!I8 | K7: =Costs!J8 | L7: =Costs!M8 | M7: =L7-$L$5 | N7: =IF(G7>0,M7/G7,"n/a")
A8: =B8&"|"&C8 | B8: R1 | C8: A3 | D8: Bench, buffer and instream structure | E8: 0 | F8: =SUMIFS(Benefits!$K$6:$K$15,Benefits!$A$6:$A$15,A8) | G8: =F8-$F$5 | H8: =Costs!D9 | I8: =SUM(Costs!D9:F9) | J8: =Costs!I9 | K8: =Costs!J9 | L8: =Costs!M9 | M8: =L8-$L$5 | N8: =IF(G8>0,M8/G8,"n/a")
A9: =B9&"|"&C9 | B9: R2 | C9: FWOP | D9: No Action | E9: 1 | F9: =SUMIFS(Benefits!$K$6:$K$15,Benefits!$A$6:$A$15,A9) | G9: =F9-$F$9 | H9: =Costs!D10 | I9: =SUM(Costs!D10:F10) | J9: =Costs!I10 | K9: =Costs!J10 | L9: =Costs!M10 | M9: =L9-$L$9 | N9: =IF(G9>0,M9/G9,"n/a")
A10: =B10&"|"&C10 | B10: R2 | C10: A1 | D10: Bank regrading and planting | E10: 0 | F10: =SUMIFS(Benefits!$K$6:$K$15,Benefits!$A$6:$A$15,A10) | G10: =F10-$F$9 | H10: =Costs!D11 | I10: =SUM(Costs!D11:F11) | J10: =Costs!I11 | K10: =Costs!J11 | L10: =Costs!M11 | M10: =L10-$L$9 | N10: =IF(G10>0,M10/G10,"n/a")
A11: =B11&"|"&C11 | B11: R2 | C11: A2 | D11: Daylight and reconnect the floodplain | E11: 0 | F11: =SUMIFS(Benefits!$K$6:$K$15,Benefits!$A$6:$A$15,A11) | G11: =F11-$F$9 | H11: =Costs!D12 | I11: =SUM(Costs!D12:F12) | J11: =Costs!I12 | K11: =Costs!J12 | L11: =Costs!M12 | M11: =L11-$L$9 | N11: =IF(G11>0,M11/G11,"n/a")
A12: =B12&"|"&C12 | B12: R3 | C12: FWOP | D12: No Action | E12: 1 | F12: =SUMIFS(Benefits!$K$6:$K$15,Benefits!$A$6:$A$15,A12) | G12: =F12-$F$12 | H12: =Costs!D13 | I12: =SUM(Costs!D13:F13) | J12: =Costs!I13 | K12: =Costs!J13 | L12: =Costs!M13 | M12: =L12-$L$12 | N12: =IF(G12>0,M12/G12,"n/a")
A13: =B13&"|"&C13 | B13: R3 | C13: A1 | D13: Livestock exclusion | E13: 0 | F13: =SUMIFS(Benefits!$K$6:$K$15,Benefits!$A$6:$A$15,A13) | G13: =F13-$F$12 | H13: =Costs!D14 | I13: =SUM(Costs!D14:F14) | J13: =Costs!I14 | K13: =Costs!J14 | L13: =Costs!M14 | M13: =L13-$L$12 | N13: =IF(G13>0,M13/G13,"n/a")
A14: =B14&"|"&C14 | B14: R3 | C14: A2 | D14: Livestock exclusion and culvert replacement | E14: 0 | F14: =SUMIFS(Benefits!$K$6:$K$15,Benefits!$A$6:$A$15,A14) | G14: =F14-$F$12 | H14: =Costs!D15 | I14: =SUM(Costs!D15:F15) | J14: =Costs!I15 | K14: =Costs!J15 | L14: =Costs!M15 | M14: =L14-$L$12 | N14: =IF(G14>0,M14/G14,"n/a")

Sheet Site CE-ICA
A1: Site-by-site CE/ICA
A2: Cost-effective: no alternative gives the same output for less, or more output for no more. Best buy: on the lower hull from No Action (IWR Planning Suite II rules).
A4: Key | B4: Site | C4: Alternative | D4: Name | E4: No Action | F4: Ordinal | G4: Lift (AACU) | H4: Cost above No Action | I4: Lift (scaled) | J4: Cost (scaled) | K4: Dominated by | L4: Cost-effective | M4: Candidate | N4: Slope in (max) | O4: Slope out (min) | P4: Best buy | Q4: Best-buy step | R4: Previous lift (scaled) | S4: Previous cost (scaled) | T4: Incremental output | U4: Incremental cost | V4: Incremental cost per unit | W4: Unit cost | X4: Recommended
B5: R1 Example Reach
A6: =B6&"|"&C6 | B6: R1 | C6: FWOP | D6: No Action | E6: 1 | F6: 1 | G6: =Summary!G5 | H6: =Summary!M5 | I6: =ROUND(G6*10^in_out_dp,0) | J6: =ROUND(H6*10^in_cost_dp,0) | K6: =SUMPRODUCT(($I$6:$I$9=I6)*($J$6:$J$9<J6)+($I$6:$I$9>I6)*($J$6:$J$9<=J6)) | L6: =IF(OR(E6=1,K6=0),1,0) | M6: =IF(AND(L6=1,E6=0,I6>0),1,0) | N6: =IF(M6=1,MAX(J6/I6,SUMPRODUCT(MAX(((J6-$J$6:$J$9)*($M$6:$M$9*($I$6:$I$9<I6)))/((I6-$I$6:$I$9)*($M$6:$M$9*($I$6:$I$9<I6))+1-($M$6:$M$9*($I$6:$I$9<I6)))-(1-($M$6:$M$9*($I$6:$I$9<I6)))*1E+300))),0) | O6: =IF(M6=1,SUMPRODUCT(MIN(((($J$6:$J$9-J6)*($M$6:$M$9*($I$6:$I$9>I6)))/(($I$6:$I$9-I6)*($M$6:$M$9*($I$6:$I$9>I6))+1-($M$6:$M$9*($I$6:$I$9>I6)))+(1-($M$6:$M$9*($I$6:$I$9>I6)))*1E+300))),0) | P6: =IF(E6=1,1,IF(AND(M6=1,N6<=O6),1,0)) | Q6: =IF(P6=1,1+SUMPRODUCT($P$6:$P$9*(($I$6:$I$9<I6)+($I$6:$I$9=I6)*($F$6:$F$9<F6))),0) | R6: =IF(Q6<=1,0,SUMPRODUCT(($Q$6:$Q$9=Q6-1)*$I$6:$I$9)) | S6: =IF(Q6<=1,0,SUMPRODUCT(($Q$6:$Q$9=Q6-1)*$J$6:$J$9)) | T6: =IF(Q6=0,"",(I6-R6)/10^in_out_dp) | U6: =IF(Q6=0,"",(J6-S6)/10^in_cost_dp) | V6: =IF(Q6=0,"",IF(I6=R6,0,U6/T6)) | W6: =IF(I6>0,(J6/10^in_cost_dp)/(I6/10^in_out_dp),"n/a") | X6: =IF(Sites!$C$5=C6,1,0)
A7: =B7&"|"&C7 | B7: R1 | C7: A1 | D7: Riparian buffer | E7: 0 | F7: 2 | G7: =Summary!G6 | H7: =Summary!M6 | I7: =ROUND(G7*10^in_out_dp,0) | J7: =ROUND(H7*10^in_cost_dp,0) | K7: =SUMPRODUCT(($I$6:$I$9=I7)*($J$6:$J$9<J7)+($I$6:$I$9>I7)*($J$6:$J$9<=J7)) | L7: =IF(OR(E7=1,K7=0),1,0) | M7: =IF(AND(L7=1,E7=0,I7>0),1,0) | N7: =IF(M7=1,MAX(J7/I7,SUMPRODUCT(MAX(((J7-$J$6:$J$9)*($M$6:$M$9*($I$6:$I$9<I7)))/((I7-$I$6:$I$9)*($M$6:$M$9*($I$6:$I$9<I7))+1-($M$6:$M$9*($I$6:$I$9<I7)))-(1-($M$6:$M$9*($I$6:$I$9<I7)))*1E+300))),0) | O7: =IF(M7=1,SUMPRODUCT(MIN(((($J$6:$J$9-J7)*($M$6:$M$9*($I$6:$I$9>I7)))/(($I$6:$I$9-I7)*($M$6:$M$9*($I$6:$I$9>I7))+1-($M$6:$M$9*($I$6:$I$9>I7)))+(1-($M$6:$M$9*($I$6:$I$9>I7)))*1E+300))),0) | P7: =IF(E7=1,1,IF(AND(M7=1,N7<=O7),1,0)) | Q7: =IF(P7=1,1+SUMPRODUCT($P$6:$P$9*(($I$6:$I$9<I7)+($I$6:$I$9=I7)*($F$6:$F$9<F7))),0) | R7: =IF(Q7<=1,0,SUMPRODUCT(($Q$6:$Q$9=Q7-1)*$I$6:$I$9)) | S7: =IF(Q7<=1,0,SUMPRODUCT(($Q$6:$Q$9=Q7-1)*$J$6:$J$9)) | T7: =IF(Q7=0,"",(I7-R7)/10^in_out_dp) | U7: =IF(Q7=0,"",(J7-S7)/10^in_cost_dp) | V7: =IF(Q7=0,"",IF(I7=R7,0,U7/T7)) | W7: =IF(I7>0,(J7/10^in_cost_dp)/(I7/10^in_out_dp),"n/a") | X7: =IF(Sites!$C$5=C7,1,0)
A8: =B8&"|"&C8 | B8: R1 | C8: A2 | D8: Floodplain bench and buffer | E8: 0 | F8: 3 | G8: =Summary!G7 | H8: =Summary!M7 | I8: =ROUND(G8*10^in_out_dp,0) | J8: =ROUND(H8*10^in_cost_dp,0) | K8: =SUMPRODUCT(($I$6:$I$9=I8)*($J$6:$J$9<J8)+($I$6:$I$9>I8)*($J$6:$J$9<=J8)) | L8: =IF(OR(E8=1,K8=0),1,0) | M8: =IF(AND(L8=1,E8=0,I8>0),1,0) | N8: =IF(M8=1,MAX(J8/I8,SUMPRODUCT(MAX(((J8-$J$6:$J$9)*($M$6:$M$9*($I$6:$I$9<I8)))/((I8-$I$6:$I$9)*($M$6:$M$9*($I$6:$I$9<I8))+1-($M$6:$M$9*($I$6:$I$9<I8)))-(1-($M$6:$M$9*($I$6:$I$9<I8)))*1E+300))),0) | O8: =IF(M8=1,SUMPRODUCT(MIN(((($J$6:$J$9-J8)*($M$6:$M$9*($I$6:$I$9>I8)))/(($I$6:$I$9-I8)*($M$6:$M$9*($I$6:$I$9>I8))+1-($M$6:$M$9*($I$6:$I$9>I8)))+(1-($M$6:$M$9*($I$6:$I$9>I8)))*1E+300))),0) | P8: =IF(E8=1,1,IF(AND(M8=1,N8<=O8),1,0)) | Q8: =IF(P8=1,1+SUMPRODUCT($P$6:$P$9*(($I$6:$I$9<I8)+($I$6:$I$9=I8)*($F$6:$F$9<F8))),0) | R8: =IF(Q8<=1,0,SUMPRODUCT(($Q$6:$Q$9=Q8-1)*$I$6:$I$9)) | S8: =IF(Q8<=1,0,SUMPRODUCT(($Q$6:$Q$9=Q8-1)*$J$6:$J$9)) | T8: =IF(Q8=0,"",(I8-R8)/10^in_out_dp) | U8: =IF(Q8=0,"",(J8-S8)/10^in_cost_dp) | V8: =IF(Q8=0,"",IF(I8=R8,0,U8/T8)) | W8: =IF(I8>0,(J8/10^in_cost_dp)/(I8/10^in_out_dp),"n/a") | X8: =IF(Sites!$C$5=C8,1,0)
A9: =B9&"|"&C9 | B9: R1 | C9: A3 | D9: Bench, buffer and instream structure | E9: 0 | F9: 4 | G9: =Summary!G8 | H9: =Summary!M8 | I9: =ROUND(G9*10^in_out_dp,0) | J9: =ROUND(H9*10^in_cost_dp,0) | K9: =SUMPRODUCT(($I$6:$I$9=I9)*($J$6:$J$9<J9)+($I$6:$I$9>I9)*($J$6:$J$9<=J9)) | L9: =IF(OR(E9=1,K9=0),1,0) | M9: =IF(AND(L9=1,E9=0,I9>0),1,0) | N9: =IF(M9=1,MAX(J9/I9,SUMPRODUCT(MAX(((J9-$J$6:$J$9)*($M$6:$M$9*($I$6:$I$9<I9)))/((I9-$I$6:$I$9)*($M$6:$M$9*($I$6:$I$9<I9))+1-($M$6:$M$9*($I$6:$I$9<I9)))-(1-($M$6:$M$9*($I$6:$I$9<I9)))*1E+300))),0) | O9: =IF(M9=1,SUMPRODUCT(MIN(((($J$6:$J$9-J9)*($M$6:$M$9*($I$6:$I$9>I9)))/(($I$6:$I$9-I9)*($M$6:$M$9*($I$6:$I$9>I9))+1-($M$6:$M$9*($I$6:$I$9>I9)))+(1-($M$6:$M$9*($I$6:$I$9>I9)))*1E+300))),0) | P9: =IF(E9=1,1,IF(AND(M9=1,N9<=O9),1,0)) | Q9: =IF(P9=1,1+SUMPRODUCT($P$6:$P$9*(($I$6:$I$9<I9)+($I$6:$I$9=I9)*($F$6:$F$9<F9))),0) | R9: =IF(Q9<=1,0,SUMPRODUCT(($Q$6:$Q$9=Q9-1)*$I$6:$I$9)) | S9: =IF(Q9<=1,0,SUMPRODUCT(($Q$6:$Q$9=Q9-1)*$J$6:$J$9)) | T9: =IF(Q9=0,"",(I9-R9)/10^in_out_dp) | U9: =IF(Q9=0,"",(J9-S9)/10^in_cost_dp) | V9: =IF(Q9=0,"",IF(I9=R9,0,U9/T9)) | W9: =IF(I9>0,(J9/10^in_cost_dp)/(I9/10^in_out_dp),"n/a") | X9: =IF(Sites!$C$5=C9,1,0)
B11: R2 Urban tributary
A12: =B12&"|"&C12 | B12: R2 | C12: FWOP | D12: No Action | E12: 1 | F12: 1 | G12: =Summary!G9 | H12: =Summary!M9 | I12: =ROUND(G12*10^in_out_dp,0) | J12: =ROUND(H12*10^in_cost_dp,0) | K12: =SUMPRODUCT(($I$12:$I$14=I12)*($J$12:$J$14<J12)+($I$12:$I$14>I12)*($J$12:$J$14<=J12)) | L12: =IF(OR(E12=1,K12=0),1,0) | M12: =IF(AND(L12=1,E12=0,I12>0),1,0) | N12: =IF(M12=1,MAX(J12/I12,SUMPRODUCT(MAX(((J12-$J$12:$J$14)*($M$12:$M$14*($I$12:$I$14<I12)))/((I12-$I$12:$I$14)*($M$12:$M$14*($I$12:$I$14<I12))+1-($M$12:$M$14*($I$12:$I$14<I12)))-(1-($M$12:$M$14*($I$12:$I$14<I12)))*1E+300))),0) | O12: =IF(M12=1,SUMPRODUCT(MIN(((($J$12:$J$14-J12)*($M$12:$M$14*($I$12:$I$14>I12)))/(($I$12:$I$14-I12)*($M$12:$M$14*($I$12:$I$14>I12))+1-($M$12:$M$14*($I$12:$I$14>I12)))+(1-($M$12:$M$14*($I$12:$I$14>I12)))*1E+300))),0) | P12: =IF(E12=1,1,IF(AND(M12=1,N12<=O12),1,0)) | Q12: =IF(P12=1,1+SUMPRODUCT($P$12:$P$14*(($I$12:$I$14<I12)+($I$12:$I$14=I12)*($F$12:$F$14<F12))),0) | R12: =IF(Q12<=1,0,SUMPRODUCT(($Q$12:$Q$14=Q12-1)*$I$12:$I$14)) | S12: =IF(Q12<=1,0,SUMPRODUCT(($Q$12:$Q$14=Q12-1)*$J$12:$J$14)) | T12: =IF(Q12=0,"",(I12-R12)/10^in_out_dp) | U12: =IF(Q12=0,"",(J12-S12)/10^in_cost_dp) | V12: =IF(Q12=0,"",IF(I12=R12,0,U12/T12)) | W12: =IF(I12>0,(J12/10^in_cost_dp)/(I12/10^in_out_dp),"n/a") | X12: =IF(Sites!$C$6=C12,1,0)
A13: =B13&"|"&C13 | B13: R2 | C13: A1 | D13: Bank regrading and planting | E13: 0 | F13: 2 | G13: =Summary!G10 | H13: =Summary!M10 | I13: =ROUND(G13*10^in_out_dp,0) | J13: =ROUND(H13*10^in_cost_dp,0) | K13: =SUMPRODUCT(($I$12:$I$14=I13)*($J$12:$J$14<J13)+($I$12:$I$14>I13)*($J$12:$J$14<=J13)) | L13: =IF(OR(E13=1,K13=0),1,0) | M13: =IF(AND(L13=1,E13=0,I13>0),1,0) | N13: =IF(M13=1,MAX(J13/I13,SUMPRODUCT(MAX(((J13-$J$12:$J$14)*($M$12:$M$14*($I$12:$I$14<I13)))/((I13-$I$12:$I$14)*($M$12:$M$14*($I$12:$I$14<I13))+1-($M$12:$M$14*($I$12:$I$14<I13)))-(1-($M$12:$M$14*($I$12:$I$14<I13)))*1E+300))),0) | O13: =IF(M13=1,SUMPRODUCT(MIN(((($J$12:$J$14-J13)*($M$12:$M$14*($I$12:$I$14>I13)))/(($I$12:$I$14-I13)*($M$12:$M$14*($I$12:$I$14>I13))+1-($M$12:$M$14*($I$12:$I$14>I13)))+(1-($M$12:$M$14*($I$12:$I$14>I13)))*1E+300))),0) | P13: =IF(E13=1,1,IF(AND(M13=1,N13<=O13),1,0)) | Q13: =IF(P13=1,1+SUMPRODUCT($P$12:$P$14*(($I$12:$I$14<I13)+($I$12:$I$14=I13)*($F$12:$F$14<F13))),0) | R13: =IF(Q13<=1,0,SUMPRODUCT(($Q$12:$Q$14=Q13-1)*$I$12:$I$14)) | S13: =IF(Q13<=1,0,SUMPRODUCT(($Q$12:$Q$14=Q13-1)*$J$12:$J$14)) | T13: =IF(Q13=0,"",(I13-R13)/10^in_out_dp) | U13: =IF(Q13=0,"",(J13-S13)/10^in_cost_dp) | V13: =IF(Q13=0,"",IF(I13=R13,0,U13/T13)) | W13: =IF(I13>0,(J13/10^in_cost_dp)/(I13/10^in_out_dp),"n/a") | X13: =IF(Sites!$C$6=C13,1,0)
A14: =B14&"|"&C14 | B14: R2 | C14: A2 | D14: Daylight and reconnect the floodplain | E14: 0 | F14: 3 | G14: =Summary!G11 | H14: =Summary!M11 | I14: =ROUND(G14*10^in_out_dp,0) | J14: =ROUND(H14*10^in_cost_dp,0) | K14: =SUMPRODUCT(($I$12:$I$14=I14)*($J$12:$J$14<J14)+($I$12:$I$14>I14)*($J$12:$J$14<=J14)) | L14: =IF(OR(E14=1,K14=0),1,0) | M14: =IF(AND(L14=1,E14=0,I14>0),1,0) | N14: =IF(M14=1,MAX(J14/I14,SUMPRODUCT(MAX(((J14-$J$12:$J$14)*($M$12:$M$14*($I$12:$I$14<I14)))/((I14-$I$12:$I$14)*($M$12:$M$14*($I$12:$I$14<I14))+1-($M$12:$M$14*($I$12:$I$14<I14)))-(1-($M$12:$M$14*($I$12:$I$14<I14)))*1E+300))),0) | O14: =IF(M14=1,SUMPRODUCT(MIN(((($J$12:$J$14-J14)*($M$12:$M$14*($I$12:$I$14>I14)))/(($I$12:$I$14-I14)*($M$12:$M$14*($I$12:$I$14>I14))+1-($M$12:$M$14*($I$12:$I$14>I14)))+(1-($M$12:$M$14*($I$12:$I$14>I14)))*1E+300))),0) | P14: =IF(E14=1,1,IF(AND(M14=1,N14<=O14),1,0)) | Q14: =IF(P14=1,1+SUMPRODUCT($P$12:$P$14*(($I$12:$I$14<I14)+($I$12:$I$14=I14)*($F$12:$F$14<F14))),0) | R14: =IF(Q14<=1,0,SUMPRODUCT(($Q$12:$Q$14=Q14-1)*$I$12:$I$14)) | S14: =IF(Q14<=1,0,SUMPRODUCT(($Q$12:$Q$14=Q14-1)*$J$12:$J$14)) | T14: =IF(Q14=0,"",(I14-R14)/10^in_out_dp) | U14: =IF(Q14=0,"",(J14-S14)/10^in_cost_dp) | V14: =IF(Q14=0,"",IF(I14=R14,0,U14/T14)) | W14: =IF(I14>0,(J14/10^in_cost_dp)/(I14/10^in_out_dp),"n/a") | X14: =IF(Sites!$C$6=C14,1,0)
B16: R3 Rural headwater
A17: =B17&"|"&C17 | B17: R3 | C17: FWOP | D17: No Action | E17: 1 | F17: 1 | G17: =Summary!G12 | H17: =Summary!M12 | I17: =ROUND(G17*10^in_out_dp,0) | J17: =ROUND(H17*10^in_cost_dp,0) | K17: =SUMPRODUCT(($I$17:$I$19=I17)*($J$17:$J$19<J17)+($I$17:$I$19>I17)*($J$17:$J$19<=J17)) | L17: =IF(OR(E17=1,K17=0),1,0) | M17: =IF(AND(L17=1,E17=0,I17>0),1,0) | N17: =IF(M17=1,MAX(J17/I17,SUMPRODUCT(MAX(((J17-$J$17:$J$19)*($M$17:$M$19*($I$17:$I$19<I17)))/((I17-$I$17:$I$19)*($M$17:$M$19*($I$17:$I$19<I17))+1-($M$17:$M$19*($I$17:$I$19<I17)))-(1-($M$17:$M$19*($I$17:$I$19<I17)))*1E+300))),0) | O17: =IF(M17=1,SUMPRODUCT(MIN(((($J$17:$J$19-J17)*($M$17:$M$19*($I$17:$I$19>I17)))/(($I$17:$I$19-I17)*($M$17:$M$19*($I$17:$I$19>I17))+1-($M$17:$M$19*($I$17:$I$19>I17)))+(1-($M$17:$M$19*($I$17:$I$19>I17)))*1E+300))),0) | P17: =IF(E17=1,1,IF(AND(M17=1,N17<=O17),1,0)) | Q17: =IF(P17=1,1+SUMPRODUCT($P$17:$P$19*(($I$17:$I$19<I17)+($I$17:$I$19=I17)*($F$17:$F$19<F17))),0) | R17: =IF(Q17<=1,0,SUMPRODUCT(($Q$17:$Q$19=Q17-1)*$I$17:$I$19)) | S17: =IF(Q17<=1,0,SUMPRODUCT(($Q$17:$Q$19=Q17-1)*$J$17:$J$19)) | T17: =IF(Q17=0,"",(I17-R17)/10^in_out_dp) | U17: =IF(Q17=0,"",(J17-S17)/10^in_cost_dp) | V17: =IF(Q17=0,"",IF(I17=R17,0,U17/T17)) | W17: =IF(I17>0,(J17/10^in_cost_dp)/(I17/10^in_out_dp),"n/a") | X17: =IF(Sites!$C$7=C17,1,0)
A18: =B18&"|"&C18 | B18: R3 | C18: A1 | D18: Livestock exclusion | E18: 0 | F18: 2 | G18: =Summary!G13 | H18: =Summary!M13 | I18: =ROUND(G18*10^in_out_dp,0) | J18: =ROUND(H18*10^in_cost_dp,0) | K18: =SUMPRODUCT(($I$17:$I$19=I18)*($J$17:$J$19<J18)+($I$17:$I$19>I18)*($J$17:$J$19<=J18)) | L18: =IF(OR(E18=1,K18=0),1,0) | M18: =IF(AND(L18=1,E18=0,I18>0),1,0) | N18: =IF(M18=1,MAX(J18/I18,SUMPRODUCT(MAX(((J18-$J$17:$J$19)*($M$17:$M$19*($I$17:$I$19<I18)))/((I18-$I$17:$I$19)*($M$17:$M$19*($I$17:$I$19<I18))+1-($M$17:$M$19*($I$17:$I$19<I18)))-(1-($M$17:$M$19*($I$17:$I$19<I18)))*1E+300))),0) | O18: =IF(M18=1,SUMPRODUCT(MIN(((($J$17:$J$19-J18)*($M$17:$M$19*($I$17:$I$19>I18)))/(($I$17:$I$19-I18)*($M$17:$M$19*($I$17:$I$19>I18))+1-($M$17:$M$19*($I$17:$I$19>I18)))+(1-($M$17:$M$19*($I$17:$I$19>I18)))*1E+300))),0) | P18: =IF(E18=1,1,IF(AND(M18=1,N18<=O18),1,0)) | Q18: =IF(P18=1,1+SUMPRODUCT($P$17:$P$19*(($I$17:$I$19<I18)+($I$17:$I$19=I18)*($F$17:$F$19<F18))),0) | R18: =IF(Q18<=1,0,SUMPRODUCT(($Q$17:$Q$19=Q18-1)*$I$17:$I$19)) | S18: =IF(Q18<=1,0,SUMPRODUCT(($Q$17:$Q$19=Q18-1)*$J$17:$J$19)) | T18: =IF(Q18=0,"",(I18-R18)/10^in_out_dp) | U18: =IF(Q18=0,"",(J18-S18)/10^in_cost_dp) | V18: =IF(Q18=0,"",IF(I18=R18,0,U18/T18)) | W18: =IF(I18>0,(J18/10^in_cost_dp)/(I18/10^in_out_dp),"n/a") | X18: =IF(Sites!$C$7=C18,1,0)
A19: =B19&"|"&C19 | B19: R3 | C19: A2 | D19: Livestock exclusion and culvert replacement | E19: 0 | F19: 3 | G19: =Summary!G14 | H19: =Summary!M14 | I19: =ROUND(G19*10^in_out_dp,0) | J19: =ROUND(H19*10^in_cost_dp,0) | K19: =SUMPRODUCT(($I$17:$I$19=I19)*($J$17:$J$19<J19)+($I$17:$I$19>I19)*($J$17:$J$19<=J19)) | L19: =IF(OR(E19=1,K19=0),1,0) | M19: =IF(AND(L19=1,E19=0,I19>0),1,0) | N19: =IF(M19=1,MAX(J19/I19,SUMPRODUCT(MAX(((J19-$J$17:$J$19)*($M$17:$M$19*($I$17:$I$19<I19)))/((I19-$I$17:$I$19)*($M$17:$M$19*($I$17:$I$19<I19))+1-($M$17:$M$19*($I$17:$I$19<I19)))-(1-($M$17:$M$19*($I$17:$I$19<I19)))*1E+300))),0) | O19: =IF(M19=1,SUMPRODUCT(MIN(((($J$17:$J$19-J19)*($M$17:$M$19*($I$17:$I$19>I19)))/(($I$17:$I$19-I19)*($M$17:$M$19*($I$17:$I$19>I19))+1-($M$17:$M$19*($I$17:$I$19>I19)))+(1-($M$17:$M$19*($I$17:$I$19>I19)))*1E+300))),0) | P19: =IF(E19=1,1,IF(AND(M19=1,N19<=O19),1,0)) | Q19: =IF(P19=1,1+SUMPRODUCT($P$17:$P$19*(($I$17:$I$19<I19)+($I$17:$I$19=I19)*($F$17:$F$19<F19))),0) | R19: =IF(Q19<=1,0,SUMPRODUCT(($Q$17:$Q$19=Q19-1)*$I$17:$I$19)) | S19: =IF(Q19<=1,0,SUMPRODUCT(($Q$17:$Q$19=Q19-1)*$J$17:$J$19)) | T19: =IF(Q19=0,"",(I19-R19)/10^in_out_dp) | U19: =IF(Q19=0,"",(J19-S19)/10^in_cost_dp) | V19: =IF(Q19=0,"",IF(I19=R19,0,U19/T19)) | W19: =IF(I19>0,(J19/10^in_cost_dp)/(I19/10^in_out_dp),"n/a") | X19: =IF(Sites!$C$7=C19,1,0)

Sheet Sites
A1: Sites: the alternative carried to the watershed plans
A2: Choose each site's recommended alternative. No Action leaves the site out of every watershed plan.
A4: Site | B4: Name | C4: Recommended alternative | D4: No Action | E4: Carried | F4: Lift (AACU) | G4: Cost above No Action | H4: Construction cost | I4: Lift (scaled) | J4: Cost (scaled) | K4: Cost-effective | L4: Best buy | M4: Decided by
A5: R1 | B5: Example Reach | C5: A3 | D5: FWOP | E5: =IF(C5<>D5,1,0) | F5: =IFERROR(INDEX('Site CE-ICA'!$G$5:$G$19,MATCH(A5&"|"&C5,'Site CE-ICA'!$A$5:$A$19,0)),0) | G5: =IFERROR(INDEX('Site CE-ICA'!$H$5:$H$19,MATCH(A5&"|"&C5,'Site CE-ICA'!$A$5:$A$19,0)),0) | H5: =IFERROR(INDEX(Summary!$H$5:$H$8,MATCH(C5,Summary!$C$5:$C$8,0)),0) | I5: =IF(E5=1,IFERROR(INDEX('Site CE-ICA'!$I$5:$I$19,MATCH(A5&"|"&C5,'Site CE-ICA'!$A$5:$A$19,0)),0),0) | J5: =IF(E5=1,IFERROR(INDEX('Site CE-ICA'!$J$5:$J$19,MATCH(A5&"|"&C5,'Site CE-ICA'!$A$5:$A$19,0)),0),0) | K5: =IFERROR(INDEX('Site CE-ICA'!$L$5:$L$19,MATCH(A5&"|"&C5,'Site CE-ICA'!$A$5:$A$19,0)),0) | L5: =IFERROR(INDEX('Site CE-ICA'!$P$5:$P$19,MATCH(A5&"|"&C5,'Site CE-ICA'!$A$5:$A$19,0)),0) | M5: Suggested
A6: R2 | B6: Urban tributary | C6: A2 | D6: FWOP | E6: =IF(C6<>D6,1,0) | F6: =IFERROR(INDEX('Site CE-ICA'!$G$5:$G$19,MATCH(A6&"|"&C6,'Site CE-ICA'!$A$5:$A$19,0)),0) | G6: =IFERROR(INDEX('Site CE-ICA'!$H$5:$H$19,MATCH(A6&"|"&C6,'Site CE-ICA'!$A$5:$A$19,0)),0) | H6: =IFERROR(INDEX(Summary!$H$9:$H$11,MATCH(C6,Summary!$C$9:$C$11,0)),0) | I6: =IF(E6=1,IFERROR(INDEX('Site CE-ICA'!$I$5:$I$19,MATCH(A6&"|"&C6,'Site CE-ICA'!$A$5:$A$19,0)),0),0) | J6: =IF(E6=1,IFERROR(INDEX('Site CE-ICA'!$J$5:$J$19,MATCH(A6&"|"&C6,'Site CE-ICA'!$A$5:$A$19,0)),0),0) | K6: =IFERROR(INDEX('Site CE-ICA'!$L$5:$L$19,MATCH(A6&"|"&C6,'Site CE-ICA'!$A$5:$A$19,0)),0) | L6: =IFERROR(INDEX('Site CE-ICA'!$P$5:$P$19,MATCH(A6&"|"&C6,'Site CE-ICA'!$A$5:$A$19,0)),0) | M6: Suggested
A7: R3 | B7: Rural headwater | C7: A2 | D7: FWOP | E7: =IF(C7<>D7,1,0) | F7: =IFERROR(INDEX('Site CE-ICA'!$G$5:$G$19,MATCH(A7&"|"&C7,'Site CE-ICA'!$A$5:$A$19,0)),0) | G7: =IFERROR(INDEX('Site CE-ICA'!$H$5:$H$19,MATCH(A7&"|"&C7,'Site CE-ICA'!$A$5:$A$19,0)),0) | H7: =IFERROR(INDEX(Summary!$H$12:$H$14,MATCH(C7,Summary!$C$12:$C$14,0)),0) | I7: =IF(E7=1,IFERROR(INDEX('Site CE-ICA'!$I$5:$I$19,MATCH(A7&"|"&C7,'Site CE-ICA'!$A$5:$A$19,0)),0),0) | J7: =IF(E7=1,IFERROR(INDEX('Site CE-ICA'!$J$5:$J$19,MATCH(A7&"|"&C7,'Site CE-ICA'!$A$5:$A$19,0)),0),0) | K7: =IFERROR(INDEX('Site CE-ICA'!$L$5:$L$19,MATCH(A7&"|"&C7,'Site CE-ICA'!$A$5:$A$19,0)),0) | L7: =IFERROR(INDEX('Site CE-ICA'!$P$5:$P$19,MATCH(A7&"|"&C7,'Site CE-ICA'!$A$5:$A$19,0)),0) | M7: Suggested

Sheet Watershed plans
A1: Watershed plans: every combination of the recommended site actions
A2: 1 and 0 mark a site included or excluded. Rows that include a site whose recommendation is No Action are not valid plans.
C4: Site | D4: R1 | E4: R2 | F4: R3
C5: Carried | D5: =Sites!E5 | E5: =Sites!E6 | F5: =Sites!E7
C6: Lift (scaled) | D6: =Sites!I5 | E6: =Sites!I6 | F6: =Sites!I7
C7: Cost (scaled) | D7: =Sites!J5 | E7: =Sites!J6 | F7: =Sites!J7
C8: Construction cost | D8: =Sites!H5 | E8: =Sites!H6 | F8: =Sites!H7
C9: Weight | D9: =IF(D5=1,2^SUM(E5:$F$5),0) | E9: =IF(E5=1,2^SUM(F5:$F$5),0) | F9: =IF(F5=1,1,0)
A11: Row | B11: Plan | C11: Valid | D11: R1 | E11: R2 | F11: R3 | G11: Plan number | H11: Lift (scaled) | I11: Cost (scaled) | J11: Construction cost | K11: Lift (AACU) | L11: Average annual cost | M11: No Action | N11: Dominated by | O11: Cost-effective | P11: Candidate | Q11: Slope in (max) | R11: Slope out (min) | S11: Best buy | T11: Best-buy step | U11: Previous lift (scaled) | V11: Previous cost (scaled) | W11: Incremental output | X11: Incremental cost | Y11: Incremental cost per unit | Z11: Unit cost | AA11: Final array | AB11: Final array order
A12: 1 | B12: No Action | C12: =IF(SUMPRODUCT(D12:F12,1-$D$5:$F$5)=0,1,0) | D12: 0 | E12: 0 | F12: 0 | G12: =IF(C12=1,1+SUMPRODUCT(D12:F12,$D$9:$F$9),"") | H12: =SUMPRODUCT(D12:F12,$D$6:$F$6) | I12: =SUMPRODUCT(D12:F12,$D$7:$F$7) | J12: =SUMPRODUCT(D12:F12,$D$8:$F$8) | K12: =H12/10^in_out_dp | L12: =I12/10^in_cost_dp | M12: =IF(SUM(D12:F12)=0,1,0) | N12: =SUMPRODUCT($C$12:$C$19*(($H$12:$H$19=H12)*($I$12:$I$19<I12)+($H$12:$H$19>H12)*($I$12:$I$19<=I12))) | O12: =IF(C12=0,0,IF(OR(M12=1,N12=0),1,0)) | P12: =IF(AND(O12=1,M12=0,H12>0),1,0) | Q12: =IF(P12=1,MAX(I12/H12,SUMPRODUCT(MAX(((I12-$I$12:$I$19)*($P$12:$P$19*($H$12:$H$19<H12)))/((H12-$H$12:$H$19)*($P$12:$P$19*($H$12:$H$19<H12))+1-($P$12:$P$19*($H$12:$H$19<H12)))-(1-($P$12:$P$19*($H$12:$H$19<H12)))*1E+300))),0) | R12: =IF(P12=1,SUMPRODUCT(MIN(((($I$12:$I$19-I12)*($P$12:$P$19*($H$12:$H$19>H12)))/(($H$12:$H$19-H12)*($P$12:$P$19*($H$12:$H$19>H12))+1-($P$12:$P$19*($H$12:$H$19>H12)))+(1-($P$12:$P$19*($H$12:$H$19>H12)))*1E+300))),0) | S12: =IF(C12=0,0,IF(M12=1,1,IF(AND(P12=1,Q12<=R12),1,0))) | T12: =IF(S12=1,1+SUMPRODUCT($S$12:$S$19*(($H$12:$H$19<H12)+($H$12:$H$19=H12)*($A$12:$A$19<A12))),0) | U12: =IF(T12<=1,0,SUMPRODUCT(($T$12:$T$19=T12-1)*$H$12:$H$19)) | V12: =IF(T12<=1,0,SUMPRODUCT(($T$12:$T$19=T12-1)*$I$12:$I$19)) | W12: =IF(T12=0,"",(H12-U12)/10^in_out_dp) | X12: =IF(T12=0,"",(I12-V12)/10^in_cost_dp) | Y12: =IF(T12=0,"",IF(H12=U12,0,X12/W12)) | Z12: =IF(AND(C12=1,H12>0),L12/K12,"n/a") | AA12: 1 | AB12: =IF(AND(C12=1,AA12=1),1+SUMPRODUCT($C$12:$C$19*$AA$12:$AA$19*(($H$12:$H$19<H12)+($H$12:$H$19=H12)*($I$12:$I$19<I12)+($H$12:$H$19=H12)*($I$12:$I$19=I12)*($A$12:$A$19<A12))),0)
A13: 2 | B13: R3 | C13: =IF(SUMPRODUCT(D13:F13,1-$D$5:$F$5)=0,1,0) | D13: 0 | E13: 0 | F13: 1 | G13: =IF(C13=1,1+SUMPRODUCT(D13:F13,$D$9:$F$9),"") | H13: =SUMPRODUCT(D13:F13,$D$6:$F$6) | I13: =SUMPRODUCT(D13:F13,$D$7:$F$7) | J13: =SUMPRODUCT(D13:F13,$D$8:$F$8) | K13: =H13/10^in_out_dp | L13: =I13/10^in_cost_dp | M13: =IF(SUM(D13:F13)=0,1,0) | N13: =SUMPRODUCT($C$12:$C$19*(($H$12:$H$19=H13)*($I$12:$I$19<I13)+($H$12:$H$19>H13)*($I$12:$I$19<=I13))) | O13: =IF(C13=0,0,IF(OR(M13=1,N13=0),1,0)) | P13: =IF(AND(O13=1,M13=0,H13>0),1,0) | Q13: =IF(P13=1,MAX(I13/H13,SUMPRODUCT(MAX(((I13-$I$12:$I$19)*($P$12:$P$19*($H$12:$H$19<H13)))/((H13-$H$12:$H$19)*($P$12:$P$19*($H$12:$H$19<H13))+1-($P$12:$P$19*($H$12:$H$19<H13)))-(1-($P$12:$P$19*($H$12:$H$19<H13)))*1E+300))),0) | R13: =IF(P13=1,SUMPRODUCT(MIN(((($I$12:$I$19-I13)*($P$12:$P$19*($H$12:$H$19>H13)))/(($H$12:$H$19-H13)*($P$12:$P$19*($H$12:$H$19>H13))+1-($P$12:$P$19*($H$12:$H$19>H13)))+(1-($P$12:$P$19*($H$12:$H$19>H13)))*1E+300))),0) | S13: =IF(C13=0,0,IF(M13=1,1,IF(AND(P13=1,Q13<=R13),1,0))) | T13: =IF(S13=1,1+SUMPRODUCT($S$12:$S$19*(($H$12:$H$19<H13)+($H$12:$H$19=H13)*($A$12:$A$19<A13))),0) | U13: =IF(T13<=1,0,SUMPRODUCT(($T$12:$T$19=T13-1)*$H$12:$H$19)) | V13: =IF(T13<=1,0,SUMPRODUCT(($T$12:$T$19=T13-1)*$I$12:$I$19)) | W13: =IF(T13=0,"",(H13-U13)/10^in_out_dp) | X13: =IF(T13=0,"",(I13-V13)/10^in_cost_dp) | Y13: =IF(T13=0,"",IF(H13=U13,0,X13/W13)) | Z13: =IF(AND(C13=1,H13>0),L13/K13,"n/a") | AA13: 1 | AB13: =IF(AND(C13=1,AA13=1),1+SUMPRODUCT($C$12:$C$19*$AA$12:$AA$19*(($H$12:$H$19<H13)+($H$12:$H$19=H13)*($I$12:$I$19<I13)+($H$12:$H$19=H13)*($I$12:$I$19=I13)*($A$12:$A$19<A13))),0)
A14: 3 | B14: R2 | C14: =IF(SUMPRODUCT(D14:F14,1-$D$5:$F$5)=0,1,0) | D14: 0 | E14: 1 | F14: 0 | G14: =IF(C14=1,1+SUMPRODUCT(D14:F14,$D$9:$F$9),"") | H14: =SUMPRODUCT(D14:F14,$D$6:$F$6) | I14: =SUMPRODUCT(D14:F14,$D$7:$F$7) | J14: =SUMPRODUCT(D14:F14,$D$8:$F$8) | K14: =H14/10^in_out_dp | L14: =I14/10^in_cost_dp | M14: =IF(SUM(D14:F14)=0,1,0) | N14: =SUMPRODUCT($C$12:$C$19*(($H$12:$H$19=H14)*($I$12:$I$19<I14)+($H$12:$H$19>H14)*($I$12:$I$19<=I14))) | O14: =IF(C14=0,0,IF(OR(M14=1,N14=0),1,0)) | P14: =IF(AND(O14=1,M14=0,H14>0),1,0) | Q14: =IF(P14=1,MAX(I14/H14,SUMPRODUCT(MAX(((I14-$I$12:$I$19)*($P$12:$P$19*($H$12:$H$19<H14)))/((H14-$H$12:$H$19)*($P$12:$P$19*($H$12:$H$19<H14))+1-($P$12:$P$19*($H$12:$H$19<H14)))-(1-($P$12:$P$19*($H$12:$H$19<H14)))*1E+300))),0) | R14: =IF(P14=1,SUMPRODUCT(MIN(((($I$12:$I$19-I14)*($P$12:$P$19*($H$12:$H$19>H14)))/(($H$12:$H$19-H14)*($P$12:$P$19*($H$12:$H$19>H14))+1-($P$12:$P$19*($H$12:$H$19>H14)))+(1-($P$12:$P$19*($H$12:$H$19>H14)))*1E+300))),0) | S14: =IF(C14=0,0,IF(M14=1,1,IF(AND(P14=1,Q14<=R14),1,0))) | T14: =IF(S14=1,1+SUMPRODUCT($S$12:$S$19*(($H$12:$H$19<H14)+($H$12:$H$19=H14)*($A$12:$A$19<A14))),0) | U14: =IF(T14<=1,0,SUMPRODUCT(($T$12:$T$19=T14-1)*$H$12:$H$19)) | V14: =IF(T14<=1,0,SUMPRODUCT(($T$12:$T$19=T14-1)*$I$12:$I$19)) | W14: =IF(T14=0,"",(H14-U14)/10^in_out_dp) | X14: =IF(T14=0,"",(I14-V14)/10^in_cost_dp) | Y14: =IF(T14=0,"",IF(H14=U14,0,X14/W14)) | Z14: =IF(AND(C14=1,H14>0),L14/K14,"n/a") | AA14: 0 | AB14: =IF(AND(C14=1,AA14=1),1+SUMPRODUCT($C$12:$C$19*$AA$12:$AA$19*(($H$12:$H$19<H14)+($H$12:$H$19=H14)*($I$12:$I$19<I14)+($H$12:$H$19=H14)*($I$12:$I$19=I14)*($A$12:$A$19<A14))),0)
A15: 4 | B15: R2 + R3 | C15: =IF(SUMPRODUCT(D15:F15,1-$D$5:$F$5)=0,1,0) | D15: 0 | E15: 1 | F15: 1 | G15: =IF(C15=1,1+SUMPRODUCT(D15:F15,$D$9:$F$9),"") | H15: =SUMPRODUCT(D15:F15,$D$6:$F$6) | I15: =SUMPRODUCT(D15:F15,$D$7:$F$7) | J15: =SUMPRODUCT(D15:F15,$D$8:$F$8) | K15: =H15/10^in_out_dp | L15: =I15/10^in_cost_dp | M15: =IF(SUM(D15:F15)=0,1,0) | N15: =SUMPRODUCT($C$12:$C$19*(($H$12:$H$19=H15)*($I$12:$I$19<I15)+($H$12:$H$19>H15)*($I$12:$I$19<=I15))) | O15: =IF(C15=0,0,IF(OR(M15=1,N15=0),1,0)) | P15: =IF(AND(O15=1,M15=0,H15>0),1,0) | Q15: =IF(P15=1,MAX(I15/H15,SUMPRODUCT(MAX(((I15-$I$12:$I$19)*($P$12:$P$19*($H$12:$H$19<H15)))/((H15-$H$12:$H$19)*($P$12:$P$19*($H$12:$H$19<H15))+1-($P$12:$P$19*($H$12:$H$19<H15)))-(1-($P$12:$P$19*($H$12:$H$19<H15)))*1E+300))),0) | R15: =IF(P15=1,SUMPRODUCT(MIN(((($I$12:$I$19-I15)*($P$12:$P$19*($H$12:$H$19>H15)))/(($H$12:$H$19-H15)*($P$12:$P$19*($H$12:$H$19>H15))+1-($P$12:$P$19*($H$12:$H$19>H15)))+(1-($P$12:$P$19*($H$12:$H$19>H15)))*1E+300))),0) | S15: =IF(C15=0,0,IF(M15=1,1,IF(AND(P15=1,Q15<=R15),1,0))) | T15: =IF(S15=1,1+SUMPRODUCT($S$12:$S$19*(($H$12:$H$19<H15)+($H$12:$H$19=H15)*($A$12:$A$19<A15))),0) | U15: =IF(T15<=1,0,SUMPRODUCT(($T$12:$T$19=T15-1)*$H$12:$H$19)) | V15: =IF(T15<=1,0,SUMPRODUCT(($T$12:$T$19=T15-1)*$I$12:$I$19)) | W15: =IF(T15=0,"",(H15-U15)/10^in_out_dp) | X15: =IF(T15=0,"",(I15-V15)/10^in_cost_dp) | Y15: =IF(T15=0,"",IF(H15=U15,0,X15/W15)) | Z15: =IF(AND(C15=1,H15>0),L15/K15,"n/a") | AA15: 1 | AB15: =IF(AND(C15=1,AA15=1),1+SUMPRODUCT($C$12:$C$19*$AA$12:$AA$19*(($H$12:$H$19<H15)+($H$12:$H$19=H15)*($I$12:$I$19<I15)+($H$12:$H$19=H15)*($I$12:$I$19=I15)*($A$12:$A$19<A15))),0)
A16: 5 | B16: R1 | C16: =IF(SUMPRODUCT(D16:F16,1-$D$5:$F$5)=0,1,0) | D16: 1 | E16: 0 | F16: 0 | G16: =IF(C16=1,1+SUMPRODUCT(D16:F16,$D$9:$F$9),"") | H16: =SUMPRODUCT(D16:F16,$D$6:$F$6) | I16: =SUMPRODUCT(D16:F16,$D$7:$F$7) | J16: =SUMPRODUCT(D16:F16,$D$8:$F$8) | K16: =H16/10^in_out_dp | L16: =I16/10^in_cost_dp | M16: =IF(SUM(D16:F16)=0,1,0) | N16: =SUMPRODUCT($C$12:$C$19*(($H$12:$H$19=H16)*($I$12:$I$19<I16)+($H$12:$H$19>H16)*($I$12:$I$19<=I16))) | O16: =IF(C16=0,0,IF(OR(M16=1,N16=0),1,0)) | P16: =IF(AND(O16=1,M16=0,H16>0),1,0) | Q16: =IF(P16=1,MAX(I16/H16,SUMPRODUCT(MAX(((I16-$I$12:$I$19)*($P$12:$P$19*($H$12:$H$19<H16)))/((H16-$H$12:$H$19)*($P$12:$P$19*($H$12:$H$19<H16))+1-($P$12:$P$19*($H$12:$H$19<H16)))-(1-($P$12:$P$19*($H$12:$H$19<H16)))*1E+300))),0) | R16: =IF(P16=1,SUMPRODUCT(MIN(((($I$12:$I$19-I16)*($P$12:$P$19*($H$12:$H$19>H16)))/(($H$12:$H$19-H16)*($P$12:$P$19*($H$12:$H$19>H16))+1-($P$12:$P$19*($H$12:$H$19>H16)))+(1-($P$12:$P$19*($H$12:$H$19>H16)))*1E+300))),0) | S16: =IF(C16=0,0,IF(M16=1,1,IF(AND(P16=1,Q16<=R16),1,0))) | T16: =IF(S16=1,1+SUMPRODUCT($S$12:$S$19*(($H$12:$H$19<H16)+($H$12:$H$19=H16)*($A$12:$A$19<A16))),0) | U16: =IF(T16<=1,0,SUMPRODUCT(($T$12:$T$19=T16-1)*$H$12:$H$19)) | V16: =IF(T16<=1,0,SUMPRODUCT(($T$12:$T$19=T16-1)*$I$12:$I$19)) | W16: =IF(T16=0,"",(H16-U16)/10^in_out_dp) | X16: =IF(T16=0,"",(I16-V16)/10^in_cost_dp) | Y16: =IF(T16=0,"",IF(H16=U16,0,X16/W16)) | Z16: =IF(AND(C16=1,H16>0),L16/K16,"n/a") | AA16: 0 | AB16: =IF(AND(C16=1,AA16=1),1+SUMPRODUCT($C$12:$C$19*$AA$12:$AA$19*(($H$12:$H$19<H16)+($H$12:$H$19=H16)*($I$12:$I$19<I16)+($H$12:$H$19=H16)*($I$12:$I$19=I16)*($A$12:$A$19<A16))),0)
A17: 6 | B17: R1 + R3 | C17: =IF(SUMPRODUCT(D17:F17,1-$D$5:$F$5)=0,1,0) | D17: 1 | E17: 0 | F17: 1 | G17: =IF(C17=1,1+SUMPRODUCT(D17:F17,$D$9:$F$9),"") | H17: =SUMPRODUCT(D17:F17,$D$6:$F$6) | I17: =SUMPRODUCT(D17:F17,$D$7:$F$7) | J17: =SUMPRODUCT(D17:F17,$D$8:$F$8) | K17: =H17/10^in_out_dp | L17: =I17/10^in_cost_dp | M17: =IF(SUM(D17:F17)=0,1,0) | N17: =SUMPRODUCT($C$12:$C$19*(($H$12:$H$19=H17)*($I$12:$I$19<I17)+($H$12:$H$19>H17)*($I$12:$I$19<=I17))) | O17: =IF(C17=0,0,IF(OR(M17=1,N17=0),1,0)) | P17: =IF(AND(O17=1,M17=0,H17>0),1,0) | Q17: =IF(P17=1,MAX(I17/H17,SUMPRODUCT(MAX(((I17-$I$12:$I$19)*($P$12:$P$19*($H$12:$H$19<H17)))/((H17-$H$12:$H$19)*($P$12:$P$19*($H$12:$H$19<H17))+1-($P$12:$P$19*($H$12:$H$19<H17)))-(1-($P$12:$P$19*($H$12:$H$19<H17)))*1E+300))),0) | R17: =IF(P17=1,SUMPRODUCT(MIN(((($I$12:$I$19-I17)*($P$12:$P$19*($H$12:$H$19>H17)))/(($H$12:$H$19-H17)*($P$12:$P$19*($H$12:$H$19>H17))+1-($P$12:$P$19*($H$12:$H$19>H17)))+(1-($P$12:$P$19*($H$12:$H$19>H17)))*1E+300))),0) | S17: =IF(C17=0,0,IF(M17=1,1,IF(AND(P17=1,Q17<=R17),1,0))) | T17: =IF(S17=1,1+SUMPRODUCT($S$12:$S$19*(($H$12:$H$19<H17)+($H$12:$H$19=H17)*($A$12:$A$19<A17))),0) | U17: =IF(T17<=1,0,SUMPRODUCT(($T$12:$T$19=T17-1)*$H$12:$H$19)) | V17: =IF(T17<=1,0,SUMPRODUCT(($T$12:$T$19=T17-1)*$I$12:$I$19)) | W17: =IF(T17=0,"",(H17-U17)/10^in_out_dp) | X17: =IF(T17=0,"",(I17-V17)/10^in_cost_dp) | Y17: =IF(T17=0,"",IF(H17=U17,0,X17/W17)) | Z17: =IF(AND(C17=1,H17>0),L17/K17,"n/a") | AA17: 0 | AB17: =IF(AND(C17=1,AA17=1),1+SUMPRODUCT($C$12:$C$19*$AA$12:$AA$19*(($H$12:$H$19<H17)+($H$12:$H$19=H17)*($I$12:$I$19<I17)+($H$12:$H$19=H17)*($I$12:$I$19=I17)*($A$12:$A$19<A17))),0)
A18: 7 | B18: R1 + R2 | C18: =IF(SUMPRODUCT(D18:F18,1-$D$5:$F$5)=0,1,0) | D18: 1 | E18: 1 | F18: 0 | G18: =IF(C18=1,1+SUMPRODUCT(D18:F18,$D$9:$F$9),"") | H18: =SUMPRODUCT(D18:F18,$D$6:$F$6) | I18: =SUMPRODUCT(D18:F18,$D$7:$F$7) | J18: =SUMPRODUCT(D18:F18,$D$8:$F$8) | K18: =H18/10^in_out_dp | L18: =I18/10^in_cost_dp | M18: =IF(SUM(D18:F18)=0,1,0) | N18: =SUMPRODUCT($C$12:$C$19*(($H$12:$H$19=H18)*($I$12:$I$19<I18)+($H$12:$H$19>H18)*($I$12:$I$19<=I18))) | O18: =IF(C18=0,0,IF(OR(M18=1,N18=0),1,0)) | P18: =IF(AND(O18=1,M18=0,H18>0),1,0) | Q18: =IF(P18=1,MAX(I18/H18,SUMPRODUCT(MAX(((I18-$I$12:$I$19)*($P$12:$P$19*($H$12:$H$19<H18)))/((H18-$H$12:$H$19)*($P$12:$P$19*($H$12:$H$19<H18))+1-($P$12:$P$19*($H$12:$H$19<H18)))-(1-($P$12:$P$19*($H$12:$H$19<H18)))*1E+300))),0) | R18: =IF(P18=1,SUMPRODUCT(MIN(((($I$12:$I$19-I18)*($P$12:$P$19*($H$12:$H$19>H18)))/(($H$12:$H$19-H18)*($P$12:$P$19*($H$12:$H$19>H18))+1-($P$12:$P$19*($H$12:$H$19>H18)))+(1-($P$12:$P$19*($H$12:$H$19>H18)))*1E+300))),0) | S18: =IF(C18=0,0,IF(M18=1,1,IF(AND(P18=1,Q18<=R18),1,0))) | T18: =IF(S18=1,1+SUMPRODUCT($S$12:$S$19*(($H$12:$H$19<H18)+($H$12:$H$19=H18)*($A$12:$A$19<A18))),0) | U18: =IF(T18<=1,0,SUMPRODUCT(($T$12:$T$19=T18-1)*$H$12:$H$19)) | V18: =IF(T18<=1,0,SUMPRODUCT(($T$12:$T$19=T18-1)*$I$12:$I$19)) | W18: =IF(T18=0,"",(H18-U18)/10^in_out_dp) | X18: =IF(T18=0,"",(I18-V18)/10^in_cost_dp) | Y18: =IF(T18=0,"",IF(H18=U18,0,X18/W18)) | Z18: =IF(AND(C18=1,H18>0),L18/K18,"n/a") | AA18: 0 | AB18: =IF(AND(C18=1,AA18=1),1+SUMPRODUCT($C$12:$C$19*$AA$12:$AA$19*(($H$12:$H$19<H18)+($H$12:$H$19=H18)*($I$12:$I$19<I18)+($H$12:$H$19=H18)*($I$12:$I$19=I18)*($A$12:$A$19<A18))),0)
A19: 8 | B19: R1 + R2 + R3 | C19: =IF(SUMPRODUCT(D19:F19,1-$D$5:$F$5)=0,1,0) | D19: 1 | E19: 1 | F19: 1 | G19: =IF(C19=1,1+SUMPRODUCT(D19:F19,$D$9:$F$9),"") | H19: =SUMPRODUCT(D19:F19,$D$6:$F$6) | I19: =SUMPRODUCT(D19:F19,$D$7:$F$7) | J19: =SUMPRODUCT(D19:F19,$D$8:$F$8) | K19: =H19/10^in_out_dp | L19: =I19/10^in_cost_dp | M19: =IF(SUM(D19:F19)=0,1,0) | N19: =SUMPRODUCT($C$12:$C$19*(($H$12:$H$19=H19)*($I$12:$I$19<I19)+($H$12:$H$19>H19)*($I$12:$I$19<=I19))) | O19: =IF(C19=0,0,IF(OR(M19=1,N19=0),1,0)) | P19: =IF(AND(O19=1,M19=0,H19>0),1,0) | Q19: =IF(P19=1,MAX(I19/H19,SUMPRODUCT(MAX(((I19-$I$12:$I$19)*($P$12:$P$19*($H$12:$H$19<H19)))/((H19-$H$12:$H$19)*($P$12:$P$19*($H$12:$H$19<H19))+1-($P$12:$P$19*($H$12:$H$19<H19)))-(1-($P$12:$P$19*($H$12:$H$19<H19)))*1E+300))),0) | R19: =IF(P19=1,SUMPRODUCT(MIN(((($I$12:$I$19-I19)*($P$12:$P$19*($H$12:$H$19>H19)))/(($H$12:$H$19-H19)*($P$12:$P$19*($H$12:$H$19>H19))+1-($P$12:$P$19*($H$12:$H$19>H19)))+(1-($P$12:$P$19*($H$12:$H$19>H19)))*1E+300))),0) | S19: =IF(C19=0,0,IF(M19=1,1,IF(AND(P19=1,Q19<=R19),1,0))) | T19: =IF(S19=1,1+SUMPRODUCT($S$12:$S$19*(($H$12:$H$19<H19)+($H$12:$H$19=H19)*($A$12:$A$19<A19))),0) | U19: =IF(T19<=1,0,SUMPRODUCT(($T$12:$T$19=T19-1)*$H$12:$H$19)) | V19: =IF(T19<=1,0,SUMPRODUCT(($T$12:$T$19=T19-1)*$I$12:$I$19)) | W19: =IF(T19=0,"",(H19-U19)/10^in_out_dp) | X19: =IF(T19=0,"",(I19-V19)/10^in_cost_dp) | Y19: =IF(T19=0,"",IF(H19=U19,0,X19/W19)) | Z19: =IF(AND(C19=1,H19>0),L19/K19,"n/a") | AA19: 1 | AB19: =IF(AND(C19=1,AA19=1),1+SUMPRODUCT($C$12:$C$19*$AA$12:$AA$19*(($H$12:$H$19<H19)+($H$12:$H$19=H19)*($I$12:$I$19<I19)+($H$12:$H$19=H19)*($I$12:$I$19=I19)*($A$12:$A$19<A19))),0)

Sheet Watershed summary
A1: Watershed summary: best buys, final array and the tentatively selected plan
A2: Tables read the watershed plans sheet. Choose the TSP from the final array.
A4: Best buys
A5: Step | B5: Plan number | C5: Plan | D5: Lift (AACU) | E5: Average annual cost | F5: Construction cost | G5: Unit cost | H5: Incremental cost per unit
A6: 1 | B6: =IFERROR(INDEX('Watershed plans'!$G$12:$G$19,MATCH(1,'Watershed plans'!$T$12:$T$19,0)),"") | C6: =IFERROR(INDEX('Watershed plans'!$B$12:$B$19,MATCH(1,'Watershed plans'!$T$12:$T$19,0)),"") | D6: =IFERROR(INDEX('Watershed plans'!$K$12:$K$19,MATCH(1,'Watershed plans'!$T$12:$T$19,0)),"") | E6: =IFERROR(INDEX('Watershed plans'!$L$12:$L$19,MATCH(1,'Watershed plans'!$T$12:$T$19,0)),"") | F6: =IFERROR(INDEX('Watershed plans'!$J$12:$J$19,MATCH(1,'Watershed plans'!$T$12:$T$19,0)),"") | G6: =IFERROR(INDEX('Watershed plans'!$Z$12:$Z$19,MATCH(1,'Watershed plans'!$T$12:$T$19,0)),"") | H6: =IFERROR(INDEX('Watershed plans'!$Y$12:$Y$19,MATCH(1,'Watershed plans'!$T$12:$T$19,0)),"")
A7: 2 | B7: =IFERROR(INDEX('Watershed plans'!$G$12:$G$19,MATCH(2,'Watershed plans'!$T$12:$T$19,0)),"") | C7: =IFERROR(INDEX('Watershed plans'!$B$12:$B$19,MATCH(2,'Watershed plans'!$T$12:$T$19,0)),"") | D7: =IFERROR(INDEX('Watershed plans'!$K$12:$K$19,MATCH(2,'Watershed plans'!$T$12:$T$19,0)),"") | E7: =IFERROR(INDEX('Watershed plans'!$L$12:$L$19,MATCH(2,'Watershed plans'!$T$12:$T$19,0)),"") | F7: =IFERROR(INDEX('Watershed plans'!$J$12:$J$19,MATCH(2,'Watershed plans'!$T$12:$T$19,0)),"") | G7: =IFERROR(INDEX('Watershed plans'!$Z$12:$Z$19,MATCH(2,'Watershed plans'!$T$12:$T$19,0)),"") | H7: =IFERROR(INDEX('Watershed plans'!$Y$12:$Y$19,MATCH(2,'Watershed plans'!$T$12:$T$19,0)),"")
A8: 3 | B8: =IFERROR(INDEX('Watershed plans'!$G$12:$G$19,MATCH(3,'Watershed plans'!$T$12:$T$19,0)),"") | C8: =IFERROR(INDEX('Watershed plans'!$B$12:$B$19,MATCH(3,'Watershed plans'!$T$12:$T$19,0)),"") | D8: =IFERROR(INDEX('Watershed plans'!$K$12:$K$19,MATCH(3,'Watershed plans'!$T$12:$T$19,0)),"") | E8: =IFERROR(INDEX('Watershed plans'!$L$12:$L$19,MATCH(3,'Watershed plans'!$T$12:$T$19,0)),"") | F8: =IFERROR(INDEX('Watershed plans'!$J$12:$J$19,MATCH(3,'Watershed plans'!$T$12:$T$19,0)),"") | G8: =IFERROR(INDEX('Watershed plans'!$Z$12:$Z$19,MATCH(3,'Watershed plans'!$T$12:$T$19,0)),"") | H8: =IFERROR(INDEX('Watershed plans'!$Y$12:$Y$19,MATCH(3,'Watershed plans'!$T$12:$T$19,0)),"")
A9: 4 | B9: =IFERROR(INDEX('Watershed plans'!$G$12:$G$19,MATCH(4,'Watershed plans'!$T$12:$T$19,0)),"") | C9: =IFERROR(INDEX('Watershed plans'!$B$12:$B$19,MATCH(4,'Watershed plans'!$T$12:$T$19,0)),"") | D9: =IFERROR(INDEX('Watershed plans'!$K$12:$K$19,MATCH(4,'Watershed plans'!$T$12:$T$19,0)),"") | E9: =IFERROR(INDEX('Watershed plans'!$L$12:$L$19,MATCH(4,'Watershed plans'!$T$12:$T$19,0)),"") | F9: =IFERROR(INDEX('Watershed plans'!$J$12:$J$19,MATCH(4,'Watershed plans'!$T$12:$T$19,0)),"") | G9: =IFERROR(INDEX('Watershed plans'!$Z$12:$Z$19,MATCH(4,'Watershed plans'!$T$12:$T$19,0)),"") | H9: =IFERROR(INDEX('Watershed plans'!$Y$12:$Y$19,MATCH(4,'Watershed plans'!$T$12:$T$19,0)),"")
A10: 5 | B10: =IFERROR(INDEX('Watershed plans'!$G$12:$G$19,MATCH(5,'Watershed plans'!$T$12:$T$19,0)),"") | C10: =IFERROR(INDEX('Watershed plans'!$B$12:$B$19,MATCH(5,'Watershed plans'!$T$12:$T$19,0)),"") | D10: =IFERROR(INDEX('Watershed plans'!$K$12:$K$19,MATCH(5,'Watershed plans'!$T$12:$T$19,0)),"") | E10: =IFERROR(INDEX('Watershed plans'!$L$12:$L$19,MATCH(5,'Watershed plans'!$T$12:$T$19,0)),"") | F10: =IFERROR(INDEX('Watershed plans'!$J$12:$J$19,MATCH(5,'Watershed plans'!$T$12:$T$19,0)),"") | G10: =IFERROR(INDEX('Watershed plans'!$Z$12:$Z$19,MATCH(5,'Watershed plans'!$T$12:$T$19,0)),"") | H10: =IFERROR(INDEX('Watershed plans'!$Y$12:$Y$19,MATCH(5,'Watershed plans'!$T$12:$T$19,0)),"")
A11: 6 | B11: =IFERROR(INDEX('Watershed plans'!$G$12:$G$19,MATCH(6,'Watershed plans'!$T$12:$T$19,0)),"") | C11: =IFERROR(INDEX('Watershed plans'!$B$12:$B$19,MATCH(6,'Watershed plans'!$T$12:$T$19,0)),"") | D11: =IFERROR(INDEX('Watershed plans'!$K$12:$K$19,MATCH(6,'Watershed plans'!$T$12:$T$19,0)),"") | E11: =IFERROR(INDEX('Watershed plans'!$L$12:$L$19,MATCH(6,'Watershed plans'!$T$12:$T$19,0)),"") | F11: =IFERROR(INDEX('Watershed plans'!$J$12:$J$19,MATCH(6,'Watershed plans'!$T$12:$T$19,0)),"") | G11: =IFERROR(INDEX('Watershed plans'!$Z$12:$Z$19,MATCH(6,'Watershed plans'!$T$12:$T$19,0)),"") | H11: =IFERROR(INDEX('Watershed plans'!$Y$12:$Y$19,MATCH(6,'Watershed plans'!$T$12:$T$19,0)),"")
A12: 7 | B12: =IFERROR(INDEX('Watershed plans'!$G$12:$G$19,MATCH(7,'Watershed plans'!$T$12:$T$19,0)),"") | C12: =IFERROR(INDEX('Watershed plans'!$B$12:$B$19,MATCH(7,'Watershed plans'!$T$12:$T$19,0)),"") | D12: =IFERROR(INDEX('Watershed plans'!$K$12:$K$19,MATCH(7,'Watershed plans'!$T$12:$T$19,0)),"") | E12: =IFERROR(INDEX('Watershed plans'!$L$12:$L$19,MATCH(7,'Watershed plans'!$T$12:$T$19,0)),"") | F12: =IFERROR(INDEX('Watershed plans'!$J$12:$J$19,MATCH(7,'Watershed plans'!$T$12:$T$19,0)),"") | G12: =IFERROR(INDEX('Watershed plans'!$Z$12:$Z$19,MATCH(7,'Watershed plans'!$T$12:$T$19,0)),"") | H12: =IFERROR(INDEX('Watershed plans'!$Y$12:$Y$19,MATCH(7,'Watershed plans'!$T$12:$T$19,0)),"")
A13: 8 | B13: =IFERROR(INDEX('Watershed plans'!$G$12:$G$19,MATCH(8,'Watershed plans'!$T$12:$T$19,0)),"") | C13: =IFERROR(INDEX('Watershed plans'!$B$12:$B$19,MATCH(8,'Watershed plans'!$T$12:$T$19,0)),"") | D13: =IFERROR(INDEX('Watershed plans'!$K$12:$K$19,MATCH(8,'Watershed plans'!$T$12:$T$19,0)),"") | E13: =IFERROR(INDEX('Watershed plans'!$L$12:$L$19,MATCH(8,'Watershed plans'!$T$12:$T$19,0)),"") | F13: =IFERROR(INDEX('Watershed plans'!$J$12:$J$19,MATCH(8,'Watershed plans'!$T$12:$T$19,0)),"") | G13: =IFERROR(INDEX('Watershed plans'!$Z$12:$Z$19,MATCH(8,'Watershed plans'!$T$12:$T$19,0)),"") | H13: =IFERROR(INDEX('Watershed plans'!$Y$12:$Y$19,MATCH(8,'Watershed plans'!$T$12:$T$19,0)),"")
A14: 9 | B14: =IFERROR(INDEX('Watershed plans'!$G$12:$G$19,MATCH(9,'Watershed plans'!$T$12:$T$19,0)),"") | C14: =IFERROR(INDEX('Watershed plans'!$B$12:$B$19,MATCH(9,'Watershed plans'!$T$12:$T$19,0)),"") | D14: =IFERROR(INDEX('Watershed plans'!$K$12:$K$19,MATCH(9,'Watershed plans'!$T$12:$T$19,0)),"") | E14: =IFERROR(INDEX('Watershed plans'!$L$12:$L$19,MATCH(9,'Watershed plans'!$T$12:$T$19,0)),"") | F14: =IFERROR(INDEX('Watershed plans'!$J$12:$J$19,MATCH(9,'Watershed plans'!$T$12:$T$19,0)),"") | G14: =IFERROR(INDEX('Watershed plans'!$Z$12:$Z$19,MATCH(9,'Watershed plans'!$T$12:$T$19,0)),"") | H14: =IFERROR(INDEX('Watershed plans'!$Y$12:$Y$19,MATCH(9,'Watershed plans'!$T$12:$T$19,0)),"")
A15: 10 | B15: =IFERROR(INDEX('Watershed plans'!$G$12:$G$19,MATCH(10,'Watershed plans'!$T$12:$T$19,0)),"") | C15: =IFERROR(INDEX('Watershed plans'!$B$12:$B$19,MATCH(10,'Watershed plans'!$T$12:$T$19,0)),"") | D15: =IFERROR(INDEX('Watershed plans'!$K$12:$K$19,MATCH(10,'Watershed plans'!$T$12:$T$19,0)),"") | E15: =IFERROR(INDEX('Watershed plans'!$L$12:$L$19,MATCH(10,'Watershed plans'!$T$12:$T$19,0)),"") | F15: =IFERROR(INDEX('Watershed plans'!$J$12:$J$19,MATCH(10,'Watershed plans'!$T$12:$T$19,0)),"") | G15: =IFERROR(INDEX('Watershed plans'!$Z$12:$Z$19,MATCH(10,'Watershed plans'!$T$12:$T$19,0)),"") | H15: =IFERROR(INDEX('Watershed plans'!$Y$12:$Y$19,MATCH(10,'Watershed plans'!$T$12:$T$19,0)),"")
A16: 11 | B16: =IFERROR(INDEX('Watershed plans'!$G$12:$G$19,MATCH(11,'Watershed plans'!$T$12:$T$19,0)),"") | C16: =IFERROR(INDEX('Watershed plans'!$B$12:$B$19,MATCH(11,'Watershed plans'!$T$12:$T$19,0)),"") | D16: =IFERROR(INDEX('Watershed plans'!$K$12:$K$19,MATCH(11,'Watershed plans'!$T$12:$T$19,0)),"") | E16: =IFERROR(INDEX('Watershed plans'!$L$12:$L$19,MATCH(11,'Watershed plans'!$T$12:$T$19,0)),"") | F16: =IFERROR(INDEX('Watershed plans'!$J$12:$J$19,MATCH(11,'Watershed plans'!$T$12:$T$19,0)),"") | G16: =IFERROR(INDEX('Watershed plans'!$Z$12:$Z$19,MATCH(11,'Watershed plans'!$T$12:$T$19,0)),"") | H16: =IFERROR(INDEX('Watershed plans'!$Y$12:$Y$19,MATCH(11,'Watershed plans'!$T$12:$T$19,0)),"")
A17: 12 | B17: =IFERROR(INDEX('Watershed plans'!$G$12:$G$19,MATCH(12,'Watershed plans'!$T$12:$T$19,0)),"") | C17: =IFERROR(INDEX('Watershed plans'!$B$12:$B$19,MATCH(12,'Watershed plans'!$T$12:$T$19,0)),"") | D17: =IFERROR(INDEX('Watershed plans'!$K$12:$K$19,MATCH(12,'Watershed plans'!$T$12:$T$19,0)),"") | E17: =IFERROR(INDEX('Watershed plans'!$L$12:$L$19,MATCH(12,'Watershed plans'!$T$12:$T$19,0)),"") | F17: =IFERROR(INDEX('Watershed plans'!$J$12:$J$19,MATCH(12,'Watershed plans'!$T$12:$T$19,0)),"") | G17: =IFERROR(INDEX('Watershed plans'!$Z$12:$Z$19,MATCH(12,'Watershed plans'!$T$12:$T$19,0)),"") | H17: =IFERROR(INDEX('Watershed plans'!$Y$12:$Y$19,MATCH(12,'Watershed plans'!$T$12:$T$19,0)),"")
A18: 13 | B18: =IFERROR(INDEX('Watershed plans'!$G$12:$G$19,MATCH(13,'Watershed plans'!$T$12:$T$19,0)),"") | C18: =IFERROR(INDEX('Watershed plans'!$B$12:$B$19,MATCH(13,'Watershed plans'!$T$12:$T$19,0)),"") | D18: =IFERROR(INDEX('Watershed plans'!$K$12:$K$19,MATCH(13,'Watershed plans'!$T$12:$T$19,0)),"") | E18: =IFERROR(INDEX('Watershed plans'!$L$12:$L$19,MATCH(13,'Watershed plans'!$T$12:$T$19,0)),"") | F18: =IFERROR(INDEX('Watershed plans'!$J$12:$J$19,MATCH(13,'Watershed plans'!$T$12:$T$19,0)),"") | G18: =IFERROR(INDEX('Watershed plans'!$Z$12:$Z$19,MATCH(13,'Watershed plans'!$T$12:$T$19,0)),"") | H18: =IFERROR(INDEX('Watershed plans'!$Y$12:$Y$19,MATCH(13,'Watershed plans'!$T$12:$T$19,0)),"")
A19: 14 | B19: =IFERROR(INDEX('Watershed plans'!$G$12:$G$19,MATCH(14,'Watershed plans'!$T$12:$T$19,0)),"") | C19: =IFERROR(INDEX('Watershed plans'!$B$12:$B$19,MATCH(14,'Watershed plans'!$T$12:$T$19,0)),"") | D19: =IFERROR(INDEX('Watershed plans'!$K$12:$K$19,MATCH(14,'Watershed plans'!$T$12:$T$19,0)),"") | E19: =IFERROR(INDEX('Watershed plans'!$L$12:$L$19,MATCH(14,'Watershed plans'!$T$12:$T$19,0)),"") | F19: =IFERROR(INDEX('Watershed plans'!$J$12:$J$19,MATCH(14,'Watershed plans'!$T$12:$T$19,0)),"") | G19: =IFERROR(INDEX('Watershed plans'!$Z$12:$Z$19,MATCH(14,'Watershed plans'!$T$12:$T$19,0)),"") | H19: =IFERROR(INDEX('Watershed plans'!$Y$12:$Y$19,MATCH(14,'Watershed plans'!$T$12:$T$19,0)),"")
A20: 15 | B20: =IFERROR(INDEX('Watershed plans'!$G$12:$G$19,MATCH(15,'Watershed plans'!$T$12:$T$19,0)),"") | C20: =IFERROR(INDEX('Watershed plans'!$B$12:$B$19,MATCH(15,'Watershed plans'!$T$12:$T$19,0)),"") | D20: =IFERROR(INDEX('Watershed plans'!$K$12:$K$19,MATCH(15,'Watershed plans'!$T$12:$T$19,0)),"") | E20: =IFERROR(INDEX('Watershed plans'!$L$12:$L$19,MATCH(15,'Watershed plans'!$T$12:$T$19,0)),"") | F20: =IFERROR(INDEX('Watershed plans'!$J$12:$J$19,MATCH(15,'Watershed plans'!$T$12:$T$19,0)),"") | G20: =IFERROR(INDEX('Watershed plans'!$Z$12:$Z$19,MATCH(15,'Watershed plans'!$T$12:$T$19,0)),"") | H20: =IFERROR(INDEX('Watershed plans'!$Y$12:$Y$19,MATCH(15,'Watershed plans'!$T$12:$T$19,0)),"")
A21: 16 | B21: =IFERROR(INDEX('Watershed plans'!$G$12:$G$19,MATCH(16,'Watershed plans'!$T$12:$T$19,0)),"") | C21: =IFERROR(INDEX('Watershed plans'!$B$12:$B$19,MATCH(16,'Watershed plans'!$T$12:$T$19,0)),"") | D21: =IFERROR(INDEX('Watershed plans'!$K$12:$K$19,MATCH(16,'Watershed plans'!$T$12:$T$19,0)),"") | E21: =IFERROR(INDEX('Watershed plans'!$L$12:$L$19,MATCH(16,'Watershed plans'!$T$12:$T$19,0)),"") | F21: =IFERROR(INDEX('Watershed plans'!$J$12:$J$19,MATCH(16,'Watershed plans'!$T$12:$T$19,0)),"") | G21: =IFERROR(INDEX('Watershed plans'!$Z$12:$Z$19,MATCH(16,'Watershed plans'!$T$12:$T$19,0)),"") | H21: =IFERROR(INDEX('Watershed plans'!$Y$12:$Y$19,MATCH(16,'Watershed plans'!$T$12:$T$19,0)),"")
A22: 17 | B22: =IFERROR(INDEX('Watershed plans'!$G$12:$G$19,MATCH(17,'Watershed plans'!$T$12:$T$19,0)),"") | C22: =IFERROR(INDEX('Watershed plans'!$B$12:$B$19,MATCH(17,'Watershed plans'!$T$12:$T$19,0)),"") | D22: =IFERROR(INDEX('Watershed plans'!$K$12:$K$19,MATCH(17,'Watershed plans'!$T$12:$T$19,0)),"") | E22: =IFERROR(INDEX('Watershed plans'!$L$12:$L$19,MATCH(17,'Watershed plans'!$T$12:$T$19,0)),"") | F22: =IFERROR(INDEX('Watershed plans'!$J$12:$J$19,MATCH(17,'Watershed plans'!$T$12:$T$19,0)),"") | G22: =IFERROR(INDEX('Watershed plans'!$Z$12:$Z$19,MATCH(17,'Watershed plans'!$T$12:$T$19,0)),"") | H22: =IFERROR(INDEX('Watershed plans'!$Y$12:$Y$19,MATCH(17,'Watershed plans'!$T$12:$T$19,0)),"")
A23: 18 | B23: =IFERROR(INDEX('Watershed plans'!$G$12:$G$19,MATCH(18,'Watershed plans'!$T$12:$T$19,0)),"") | C23: =IFERROR(INDEX('Watershed plans'!$B$12:$B$19,MATCH(18,'Watershed plans'!$T$12:$T$19,0)),"") | D23: =IFERROR(INDEX('Watershed plans'!$K$12:$K$19,MATCH(18,'Watershed plans'!$T$12:$T$19,0)),"") | E23: =IFERROR(INDEX('Watershed plans'!$L$12:$L$19,MATCH(18,'Watershed plans'!$T$12:$T$19,0)),"") | F23: =IFERROR(INDEX('Watershed plans'!$J$12:$J$19,MATCH(18,'Watershed plans'!$T$12:$T$19,0)),"") | G23: =IFERROR(INDEX('Watershed plans'!$Z$12:$Z$19,MATCH(18,'Watershed plans'!$T$12:$T$19,0)),"") | H23: =IFERROR(INDEX('Watershed plans'!$Y$12:$Y$19,MATCH(18,'Watershed plans'!$T$12:$T$19,0)),"")
A24: 19 | B24: =IFERROR(INDEX('Watershed plans'!$G$12:$G$19,MATCH(19,'Watershed plans'!$T$12:$T$19,0)),"") | C24: =IFERROR(INDEX('Watershed plans'!$B$12:$B$19,MATCH(19,'Watershed plans'!$T$12:$T$19,0)),"") | D24: =IFERROR(INDEX('Watershed plans'!$K$12:$K$19,MATCH(19,'Watershed plans'!$T$12:$T$19,0)),"") | E24: =IFERROR(INDEX('Watershed plans'!$L$12:$L$19,MATCH(19,'Watershed plans'!$T$12:$T$19,0)),"") | F24: =IFERROR(INDEX('Watershed plans'!$J$12:$J$19,MATCH(19,'Watershed plans'!$T$12:$T$19,0)),"") | G24: =IFERROR(INDEX('Watershed plans'!$Z$12:$Z$19,MATCH(19,'Watershed plans'!$T$12:$T$19,0)),"") | H24: =IFERROR(INDEX('Watershed plans'!$Y$12:$Y$19,MATCH(19,'Watershed plans'!$T$12:$T$19,0)),"")
A25: 20 | B25: =IFERROR(INDEX('Watershed plans'!$G$12:$G$19,MATCH(20,'Watershed plans'!$T$12:$T$19,0)),"") | C25: =IFERROR(INDEX('Watershed plans'!$B$12:$B$19,MATCH(20,'Watershed plans'!$T$12:$T$19,0)),"") | D25: =IFERROR(INDEX('Watershed plans'!$K$12:$K$19,MATCH(20,'Watershed plans'!$T$12:$T$19,0)),"") | E25: =IFERROR(INDEX('Watershed plans'!$L$12:$L$19,MATCH(20,'Watershed plans'!$T$12:$T$19,0)),"") | F25: =IFERROR(INDEX('Watershed plans'!$J$12:$J$19,MATCH(20,'Watershed plans'!$T$12:$T$19,0)),"") | G25: =IFERROR(INDEX('Watershed plans'!$Z$12:$Z$19,MATCH(20,'Watershed plans'!$T$12:$T$19,0)),"") | H25: =IFERROR(INDEX('Watershed plans'!$Y$12:$Y$19,MATCH(20,'Watershed plans'!$T$12:$T$19,0)),"")
A26: 21 | B26: =IFERROR(INDEX('Watershed plans'!$G$12:$G$19,MATCH(21,'Watershed plans'!$T$12:$T$19,0)),"") | C26: =IFERROR(INDEX('Watershed plans'!$B$12:$B$19,MATCH(21,'Watershed plans'!$T$12:$T$19,0)),"") | D26: =IFERROR(INDEX('Watershed plans'!$K$12:$K$19,MATCH(21,'Watershed plans'!$T$12:$T$19,0)),"") | E26: =IFERROR(INDEX('Watershed plans'!$L$12:$L$19,MATCH(21,'Watershed plans'!$T$12:$T$19,0)),"") | F26: =IFERROR(INDEX('Watershed plans'!$J$12:$J$19,MATCH(21,'Watershed plans'!$T$12:$T$19,0)),"") | G26: =IFERROR(INDEX('Watershed plans'!$Z$12:$Z$19,MATCH(21,'Watershed plans'!$T$12:$T$19,0)),"") | H26: =IFERROR(INDEX('Watershed plans'!$Y$12:$Y$19,MATCH(21,'Watershed plans'!$T$12:$T$19,0)),"")
A27: 22 | B27: =IFERROR(INDEX('Watershed plans'!$G$12:$G$19,MATCH(22,'Watershed plans'!$T$12:$T$19,0)),"") | C27: =IFERROR(INDEX('Watershed plans'!$B$12:$B$19,MATCH(22,'Watershed plans'!$T$12:$T$19,0)),"") | D27: =IFERROR(INDEX('Watershed plans'!$K$12:$K$19,MATCH(22,'Watershed plans'!$T$12:$T$19,0)),"") | E27: =IFERROR(INDEX('Watershed plans'!$L$12:$L$19,MATCH(22,'Watershed plans'!$T$12:$T$19,0)),"") | F27: =IFERROR(INDEX('Watershed plans'!$J$12:$J$19,MATCH(22,'Watershed plans'!$T$12:$T$19,0)),"") | G27: =IFERROR(INDEX('Watershed plans'!$Z$12:$Z$19,MATCH(22,'Watershed plans'!$T$12:$T$19,0)),"") | H27: =IFERROR(INDEX('Watershed plans'!$Y$12:$Y$19,MATCH(22,'Watershed plans'!$T$12:$T$19,0)),"")
A28: 23 | B28: =IFERROR(INDEX('Watershed plans'!$G$12:$G$19,MATCH(23,'Watershed plans'!$T$12:$T$19,0)),"") | C28: =IFERROR(INDEX('Watershed plans'!$B$12:$B$19,MATCH(23,'Watershed plans'!$T$12:$T$19,0)),"") | D28: =IFERROR(INDEX('Watershed plans'!$K$12:$K$19,MATCH(23,'Watershed plans'!$T$12:$T$19,0)),"") | E28: =IFERROR(INDEX('Watershed plans'!$L$12:$L$19,MATCH(23,'Watershed plans'!$T$12:$T$19,0)),"") | F28: =IFERROR(INDEX('Watershed plans'!$J$12:$J$19,MATCH(23,'Watershed plans'!$T$12:$T$19,0)),"") | G28: =IFERROR(INDEX('Watershed plans'!$Z$12:$Z$19,MATCH(23,'Watershed plans'!$T$12:$T$19,0)),"") | H28: =IFERROR(INDEX('Watershed plans'!$Y$12:$Y$19,MATCH(23,'Watershed plans'!$T$12:$T$19,0)),"")
A29: 24 | B29: =IFERROR(INDEX('Watershed plans'!$G$12:$G$19,MATCH(24,'Watershed plans'!$T$12:$T$19,0)),"") | C29: =IFERROR(INDEX('Watershed plans'!$B$12:$B$19,MATCH(24,'Watershed plans'!$T$12:$T$19,0)),"") | D29: =IFERROR(INDEX('Watershed plans'!$K$12:$K$19,MATCH(24,'Watershed plans'!$T$12:$T$19,0)),"") | E29: =IFERROR(INDEX('Watershed plans'!$L$12:$L$19,MATCH(24,'Watershed plans'!$T$12:$T$19,0)),"") | F29: =IFERROR(INDEX('Watershed plans'!$J$12:$J$19,MATCH(24,'Watershed plans'!$T$12:$T$19,0)),"") | G29: =IFERROR(INDEX('Watershed plans'!$Z$12:$Z$19,MATCH(24,'Watershed plans'!$T$12:$T$19,0)),"") | H29: =IFERROR(INDEX('Watershed plans'!$Y$12:$Y$19,MATCH(24,'Watershed plans'!$T$12:$T$19,0)),"")
A30: 25 | B30: =IFERROR(INDEX('Watershed plans'!$G$12:$G$19,MATCH(25,'Watershed plans'!$T$12:$T$19,0)),"") | C30: =IFERROR(INDEX('Watershed plans'!$B$12:$B$19,MATCH(25,'Watershed plans'!$T$12:$T$19,0)),"") | D30: =IFERROR(INDEX('Watershed plans'!$K$12:$K$19,MATCH(25,'Watershed plans'!$T$12:$T$19,0)),"") | E30: =IFERROR(INDEX('Watershed plans'!$L$12:$L$19,MATCH(25,'Watershed plans'!$T$12:$T$19,0)),"") | F30: =IFERROR(INDEX('Watershed plans'!$J$12:$J$19,MATCH(25,'Watershed plans'!$T$12:$T$19,0)),"") | G30: =IFERROR(INDEX('Watershed plans'!$Z$12:$Z$19,MATCH(25,'Watershed plans'!$T$12:$T$19,0)),"") | H30: =IFERROR(INDEX('Watershed plans'!$Y$12:$Y$19,MATCH(25,'Watershed plans'!$T$12:$T$19,0)),"")
A31: 26 | B31: =IFERROR(INDEX('Watershed plans'!$G$12:$G$19,MATCH(26,'Watershed plans'!$T$12:$T$19,0)),"") | C31: =IFERROR(INDEX('Watershed plans'!$B$12:$B$19,MATCH(26,'Watershed plans'!$T$12:$T$19,0)),"") | D31: =IFERROR(INDEX('Watershed plans'!$K$12:$K$19,MATCH(26,'Watershed plans'!$T$12:$T$19,0)),"") | E31: =IFERROR(INDEX('Watershed plans'!$L$12:$L$19,MATCH(26,'Watershed plans'!$T$12:$T$19,0)),"") | F31: =IFERROR(INDEX('Watershed plans'!$J$12:$J$19,MATCH(26,'Watershed plans'!$T$12:$T$19,0)),"") | G31: =IFERROR(INDEX('Watershed plans'!$Z$12:$Z$19,MATCH(26,'Watershed plans'!$T$12:$T$19,0)),"") | H31: =IFERROR(INDEX('Watershed plans'!$Y$12:$Y$19,MATCH(26,'Watershed plans'!$T$12:$T$19,0)),"")
A32: 27 | B32: =IFERROR(INDEX('Watershed plans'!$G$12:$G$19,MATCH(27,'Watershed plans'!$T$12:$T$19,0)),"") | C32: =IFERROR(INDEX('Watershed plans'!$B$12:$B$19,MATCH(27,'Watershed plans'!$T$12:$T$19,0)),"") | D32: =IFERROR(INDEX('Watershed plans'!$K$12:$K$19,MATCH(27,'Watershed plans'!$T$12:$T$19,0)),"") | E32: =IFERROR(INDEX('Watershed plans'!$L$12:$L$19,MATCH(27,'Watershed plans'!$T$12:$T$19,0)),"") | F32: =IFERROR(INDEX('Watershed plans'!$J$12:$J$19,MATCH(27,'Watershed plans'!$T$12:$T$19,0)),"") | G32: =IFERROR(INDEX('Watershed plans'!$Z$12:$Z$19,MATCH(27,'Watershed plans'!$T$12:$T$19,0)),"") | H32: =IFERROR(INDEX('Watershed plans'!$Y$12:$Y$19,MATCH(27,'Watershed plans'!$T$12:$T$19,0)),"")
A33: 28 | B33: =IFERROR(INDEX('Watershed plans'!$G$12:$G$19,MATCH(28,'Watershed plans'!$T$12:$T$19,0)),"") | C33: =IFERROR(INDEX('Watershed plans'!$B$12:$B$19,MATCH(28,'Watershed plans'!$T$12:$T$19,0)),"") | D33: =IFERROR(INDEX('Watershed plans'!$K$12:$K$19,MATCH(28,'Watershed plans'!$T$12:$T$19,0)),"") | E33: =IFERROR(INDEX('Watershed plans'!$L$12:$L$19,MATCH(28,'Watershed plans'!$T$12:$T$19,0)),"") | F33: =IFERROR(INDEX('Watershed plans'!$J$12:$J$19,MATCH(28,'Watershed plans'!$T$12:$T$19,0)),"") | G33: =IFERROR(INDEX('Watershed plans'!$Z$12:$Z$19,MATCH(28,'Watershed plans'!$T$12:$T$19,0)),"") | H33: =IFERROR(INDEX('Watershed plans'!$Y$12:$Y$19,MATCH(28,'Watershed plans'!$T$12:$T$19,0)),"")
A34: 29 | B34: =IFERROR(INDEX('Watershed plans'!$G$12:$G$19,MATCH(29,'Watershed plans'!$T$12:$T$19,0)),"") | C34: =IFERROR(INDEX('Watershed plans'!$B$12:$B$19,MATCH(29,'Watershed plans'!$T$12:$T$19,0)),"") | D34: =IFERROR(INDEX('Watershed plans'!$K$12:$K$19,MATCH(29,'Watershed plans'!$T$12:$T$19,0)),"") | E34: =IFERROR(INDEX('Watershed plans'!$L$12:$L$19,MATCH(29,'Watershed plans'!$T$12:$T$19,0)),"") | F34: =IFERROR(INDEX('Watershed plans'!$J$12:$J$19,MATCH(29,'Watershed plans'!$T$12:$T$19,0)),"") | G34: =IFERROR(INDEX('Watershed plans'!$Z$12:$Z$19,MATCH(29,'Watershed plans'!$T$12:$T$19,0)),"") | H34: =IFERROR(INDEX('Watershed plans'!$Y$12:$Y$19,MATCH(29,'Watershed plans'!$T$12:$T$19,0)),"")
A35: 30 | B35: =IFERROR(INDEX('Watershed plans'!$G$12:$G$19,MATCH(30,'Watershed plans'!$T$12:$T$19,0)),"") | C35: =IFERROR(INDEX('Watershed plans'!$B$12:$B$19,MATCH(30,'Watershed plans'!$T$12:$T$19,0)),"") | D35: =IFERROR(INDEX('Watershed plans'!$K$12:$K$19,MATCH(30,'Watershed plans'!$T$12:$T$19,0)),"") | E35: =IFERROR(INDEX('Watershed plans'!$L$12:$L$19,MATCH(30,'Watershed plans'!$T$12:$T$19,0)),"") | F35: =IFERROR(INDEX('Watershed plans'!$J$12:$J$19,MATCH(30,'Watershed plans'!$T$12:$T$19,0)),"") | G35: =IFERROR(INDEX('Watershed plans'!$Z$12:$Z$19,MATCH(30,'Watershed plans'!$T$12:$T$19,0)),"") | H35: =IFERROR(INDEX('Watershed plans'!$Y$12:$Y$19,MATCH(30,'Watershed plans'!$T$12:$T$19,0)),"")
A36: 31 | B36: =IFERROR(INDEX('Watershed plans'!$G$12:$G$19,MATCH(31,'Watershed plans'!$T$12:$T$19,0)),"") | C36: =IFERROR(INDEX('Watershed plans'!$B$12:$B$19,MATCH(31,'Watershed plans'!$T$12:$T$19,0)),"") | D36: =IFERROR(INDEX('Watershed plans'!$K$12:$K$19,MATCH(31,'Watershed plans'!$T$12:$T$19,0)),"") | E36: =IFERROR(INDEX('Watershed plans'!$L$12:$L$19,MATCH(31,'Watershed plans'!$T$12:$T$19,0)),"") | F36: =IFERROR(INDEX('Watershed plans'!$J$12:$J$19,MATCH(31,'Watershed plans'!$T$12:$T$19,0)),"") | G36: =IFERROR(INDEX('Watershed plans'!$Z$12:$Z$19,MATCH(31,'Watershed plans'!$T$12:$T$19,0)),"") | H36: =IFERROR(INDEX('Watershed plans'!$Y$12:$Y$19,MATCH(31,'Watershed plans'!$T$12:$T$19,0)),"")
A37: 32 | B37: =IFERROR(INDEX('Watershed plans'!$G$12:$G$19,MATCH(32,'Watershed plans'!$T$12:$T$19,0)),"") | C37: =IFERROR(INDEX('Watershed plans'!$B$12:$B$19,MATCH(32,'Watershed plans'!$T$12:$T$19,0)),"") | D37: =IFERROR(INDEX('Watershed plans'!$K$12:$K$19,MATCH(32,'Watershed plans'!$T$12:$T$19,0)),"") | E37: =IFERROR(INDEX('Watershed plans'!$L$12:$L$19,MATCH(32,'Watershed plans'!$T$12:$T$19,0)),"") | F37: =IFERROR(INDEX('Watershed plans'!$J$12:$J$19,MATCH(32,'Watershed plans'!$T$12:$T$19,0)),"") | G37: =IFERROR(INDEX('Watershed plans'!$Z$12:$Z$19,MATCH(32,'Watershed plans'!$T$12:$T$19,0)),"") | H37: =IFERROR(INDEX('Watershed plans'!$Y$12:$Y$19,MATCH(32,'Watershed plans'!$T$12:$T$19,0)),"")
A38: 33 | B38: =IFERROR(INDEX('Watershed plans'!$G$12:$G$19,MATCH(33,'Watershed plans'!$T$12:$T$19,0)),"") | C38: =IFERROR(INDEX('Watershed plans'!$B$12:$B$19,MATCH(33,'Watershed plans'!$T$12:$T$19,0)),"") | D38: =IFERROR(INDEX('Watershed plans'!$K$12:$K$19,MATCH(33,'Watershed plans'!$T$12:$T$19,0)),"") | E38: =IFERROR(INDEX('Watershed plans'!$L$12:$L$19,MATCH(33,'Watershed plans'!$T$12:$T$19,0)),"") | F38: =IFERROR(INDEX('Watershed plans'!$J$12:$J$19,MATCH(33,'Watershed plans'!$T$12:$T$19,0)),"") | G38: =IFERROR(INDEX('Watershed plans'!$Z$12:$Z$19,MATCH(33,'Watershed plans'!$T$12:$T$19,0)),"") | H38: =IFERROR(INDEX('Watershed plans'!$Y$12:$Y$19,MATCH(33,'Watershed plans'!$T$12:$T$19,0)),"")
A39: 34 | B39: =IFERROR(INDEX('Watershed plans'!$G$12:$G$19,MATCH(34,'Watershed plans'!$T$12:$T$19,0)),"") | C39: =IFERROR(INDEX('Watershed plans'!$B$12:$B$19,MATCH(34,'Watershed plans'!$T$12:$T$19,0)),"") | D39: =IFERROR(INDEX('Watershed plans'!$K$12:$K$19,MATCH(34,'Watershed plans'!$T$12:$T$19,0)),"") | E39: =IFERROR(INDEX('Watershed plans'!$L$12:$L$19,MATCH(34,'Watershed plans'!$T$12:$T$19,0)),"") | F39: =IFERROR(INDEX('Watershed plans'!$J$12:$J$19,MATCH(34,'Watershed plans'!$T$12:$T$19,0)),"") | G39: =IFERROR(INDEX('Watershed plans'!$Z$12:$Z$19,MATCH(34,'Watershed plans'!$T$12:$T$19,0)),"") | H39: =IFERROR(INDEX('Watershed plans'!$Y$12:$Y$19,MATCH(34,'Watershed plans'!$T$12:$T$19,0)),"")
A40: 35 | B40: =IFERROR(INDEX('Watershed plans'!$G$12:$G$19,MATCH(35,'Watershed plans'!$T$12:$T$19,0)),"") | C40: =IFERROR(INDEX('Watershed plans'!$B$12:$B$19,MATCH(35,'Watershed plans'!$T$12:$T$19,0)),"") | D40: =IFERROR(INDEX('Watershed plans'!$K$12:$K$19,MATCH(35,'Watershed plans'!$T$12:$T$19,0)),"") | E40: =IFERROR(INDEX('Watershed plans'!$L$12:$L$19,MATCH(35,'Watershed plans'!$T$12:$T$19,0)),"") | F40: =IFERROR(INDEX('Watershed plans'!$J$12:$J$19,MATCH(35,'Watershed plans'!$T$12:$T$19,0)),"") | G40: =IFERROR(INDEX('Watershed plans'!$Z$12:$Z$19,MATCH(35,'Watershed plans'!$T$12:$T$19,0)),"") | H40: =IFERROR(INDEX('Watershed plans'!$Y$12:$Y$19,MATCH(35,'Watershed plans'!$T$12:$T$19,0)),"")
A41: 36 | B41: =IFERROR(INDEX('Watershed plans'!$G$12:$G$19,MATCH(36,'Watershed plans'!$T$12:$T$19,0)),"") | C41: =IFERROR(INDEX('Watershed plans'!$B$12:$B$19,MATCH(36,'Watershed plans'!$T$12:$T$19,0)),"") | D41: =IFERROR(INDEX('Watershed plans'!$K$12:$K$19,MATCH(36,'Watershed plans'!$T$12:$T$19,0)),"") | E41: =IFERROR(INDEX('Watershed plans'!$L$12:$L$19,MATCH(36,'Watershed plans'!$T$12:$T$19,0)),"") | F41: =IFERROR(INDEX('Watershed plans'!$J$12:$J$19,MATCH(36,'Watershed plans'!$T$12:$T$19,0)),"") | G41: =IFERROR(INDEX('Watershed plans'!$Z$12:$Z$19,MATCH(36,'Watershed plans'!$T$12:$T$19,0)),"") | H41: =IFERROR(INDEX('Watershed plans'!$Y$12:$Y$19,MATCH(36,'Watershed plans'!$T$12:$T$19,0)),"")
A42: 37 | B42: =IFERROR(INDEX('Watershed plans'!$G$12:$G$19,MATCH(37,'Watershed plans'!$T$12:$T$19,0)),"") | C42: =IFERROR(INDEX('Watershed plans'!$B$12:$B$19,MATCH(37,'Watershed plans'!$T$12:$T$19,0)),"") | D42: =IFERROR(INDEX('Watershed plans'!$K$12:$K$19,MATCH(37,'Watershed plans'!$T$12:$T$19,0)),"") | E42: =IFERROR(INDEX('Watershed plans'!$L$12:$L$19,MATCH(37,'Watershed plans'!$T$12:$T$19,0)),"") | F42: =IFERROR(INDEX('Watershed plans'!$J$12:$J$19,MATCH(37,'Watershed plans'!$T$12:$T$19,0)),"") | G42: =IFERROR(INDEX('Watershed plans'!$Z$12:$Z$19,MATCH(37,'Watershed plans'!$T$12:$T$19,0)),"") | H42: =IFERROR(INDEX('Watershed plans'!$Y$12:$Y$19,MATCH(37,'Watershed plans'!$T$12:$T$19,0)),"")
A43: 38 | B43: =IFERROR(INDEX('Watershed plans'!$G$12:$G$19,MATCH(38,'Watershed plans'!$T$12:$T$19,0)),"") | C43: =IFERROR(INDEX('Watershed plans'!$B$12:$B$19,MATCH(38,'Watershed plans'!$T$12:$T$19,0)),"") | D43: =IFERROR(INDEX('Watershed plans'!$K$12:$K$19,MATCH(38,'Watershed plans'!$T$12:$T$19,0)),"") | E43: =IFERROR(INDEX('Watershed plans'!$L$12:$L$19,MATCH(38,'Watershed plans'!$T$12:$T$19,0)),"") | F43: =IFERROR(INDEX('Watershed plans'!$J$12:$J$19,MATCH(38,'Watershed plans'!$T$12:$T$19,0)),"") | G43: =IFERROR(INDEX('Watershed plans'!$Z$12:$Z$19,MATCH(38,'Watershed plans'!$T$12:$T$19,0)),"") | H43: =IFERROR(INDEX('Watershed plans'!$Y$12:$Y$19,MATCH(38,'Watershed plans'!$T$12:$T$19,0)),"")
A44: 39 | B44: =IFERROR(INDEX('Watershed plans'!$G$12:$G$19,MATCH(39,'Watershed plans'!$T$12:$T$19,0)),"") | C44: =IFERROR(INDEX('Watershed plans'!$B$12:$B$19,MATCH(39,'Watershed plans'!$T$12:$T$19,0)),"") | D44: =IFERROR(INDEX('Watershed plans'!$K$12:$K$19,MATCH(39,'Watershed plans'!$T$12:$T$19,0)),"") | E44: =IFERROR(INDEX('Watershed plans'!$L$12:$L$19,MATCH(39,'Watershed plans'!$T$12:$T$19,0)),"") | F44: =IFERROR(INDEX('Watershed plans'!$J$12:$J$19,MATCH(39,'Watershed plans'!$T$12:$T$19,0)),"") | G44: =IFERROR(INDEX('Watershed plans'!$Z$12:$Z$19,MATCH(39,'Watershed plans'!$T$12:$T$19,0)),"") | H44: =IFERROR(INDEX('Watershed plans'!$Y$12:$Y$19,MATCH(39,'Watershed plans'!$T$12:$T$19,0)),"")
A45: 40 | B45: =IFERROR(INDEX('Watershed plans'!$G$12:$G$19,MATCH(40,'Watershed plans'!$T$12:$T$19,0)),"") | C45: =IFERROR(INDEX('Watershed plans'!$B$12:$B$19,MATCH(40,'Watershed plans'!$T$12:$T$19,0)),"") | D45: =IFERROR(INDEX('Watershed plans'!$K$12:$K$19,MATCH(40,'Watershed plans'!$T$12:$T$19,0)),"") | E45: =IFERROR(INDEX('Watershed plans'!$L$12:$L$19,MATCH(40,'Watershed plans'!$T$12:$T$19,0)),"") | F45: =IFERROR(INDEX('Watershed plans'!$J$12:$J$19,MATCH(40,'Watershed plans'!$T$12:$T$19,0)),"") | G45: =IFERROR(INDEX('Watershed plans'!$Z$12:$Z$19,MATCH(40,'Watershed plans'!$T$12:$T$19,0)),"") | H45: =IFERROR(INDEX('Watershed plans'!$Y$12:$Y$19,MATCH(40,'Watershed plans'!$T$12:$T$19,0)),"")
A48: Final array (in order of output) and 'Is it worth it?'
A49: Order | B49: Plan number | C49: Plan | D49: Lift (AACU) | E49: Average annual cost | F49: Construction cost | G49: Unit cost | H49: Added output | I49: Added cost | J49: Added cost per unit | K49: Worth it? | L49: Why
A50: 1 | B50: =IFERROR(INDEX('Watershed plans'!$G$12:$G$19,MATCH(1,'Watershed plans'!$AB$12:$AB$19,0)),"") | C50: =IFERROR(INDEX('Watershed plans'!$B$12:$B$19,MATCH(1,'Watershed plans'!$AB$12:$AB$19,0)),"") | D50: =IFERROR(INDEX('Watershed plans'!$K$12:$K$19,MATCH(1,'Watershed plans'!$AB$12:$AB$19,0)),"") | E50: =IFERROR(INDEX('Watershed plans'!$L$12:$L$19,MATCH(1,'Watershed plans'!$AB$12:$AB$19,0)),"") | F50: =IFERROR(INDEX('Watershed plans'!$J$12:$J$19,MATCH(1,'Watershed plans'!$AB$12:$AB$19,0)),"") | G50: =IFERROR(INDEX('Watershed plans'!$Z$12:$Z$19,MATCH(1,'Watershed plans'!$AB$12:$AB$19,0)),"")
A51: 2 | B51: =IFERROR(INDEX('Watershed plans'!$G$12:$G$19,MATCH(2,'Watershed plans'!$AB$12:$AB$19,0)),"") | C51: =IFERROR(INDEX('Watershed plans'!$B$12:$B$19,MATCH(2,'Watershed plans'!$AB$12:$AB$19,0)),"") | D51: =IFERROR(INDEX('Watershed plans'!$K$12:$K$19,MATCH(2,'Watershed plans'!$AB$12:$AB$19,0)),"") | E51: =IFERROR(INDEX('Watershed plans'!$L$12:$L$19,MATCH(2,'Watershed plans'!$AB$12:$AB$19,0)),"") | F51: =IFERROR(INDEX('Watershed plans'!$J$12:$J$19,MATCH(2,'Watershed plans'!$AB$12:$AB$19,0)),"") | G51: =IFERROR(INDEX('Watershed plans'!$Z$12:$Z$19,MATCH(2,'Watershed plans'!$AB$12:$AB$19,0)),"") | H51: =IF(ISNUMBER(D51),D51-D50,"") | I51: =IF(ISNUMBER(E51),E51-E50,"") | J51: =IF(AND(ISNUMBER(H51),H51<>0),I51/H51,"")
A52: 3 | B52: =IFERROR(INDEX('Watershed plans'!$G$12:$G$19,MATCH(3,'Watershed plans'!$AB$12:$AB$19,0)),"") | C52: =IFERROR(INDEX('Watershed plans'!$B$12:$B$19,MATCH(3,'Watershed plans'!$AB$12:$AB$19,0)),"") | D52: =IFERROR(INDEX('Watershed plans'!$K$12:$K$19,MATCH(3,'Watershed plans'!$AB$12:$AB$19,0)),"") | E52: =IFERROR(INDEX('Watershed plans'!$L$12:$L$19,MATCH(3,'Watershed plans'!$AB$12:$AB$19,0)),"") | F52: =IFERROR(INDEX('Watershed plans'!$J$12:$J$19,MATCH(3,'Watershed plans'!$AB$12:$AB$19,0)),"") | G52: =IFERROR(INDEX('Watershed plans'!$Z$12:$Z$19,MATCH(3,'Watershed plans'!$AB$12:$AB$19,0)),"") | H52: =IF(ISNUMBER(D52),D52-D51,"") | I52: =IF(ISNUMBER(E52),E52-E51,"") | J52: =IF(AND(ISNUMBER(H52),H52<>0),I52/H52,"")
A53: 4 | B53: =IFERROR(INDEX('Watershed plans'!$G$12:$G$19,MATCH(4,'Watershed plans'!$AB$12:$AB$19,0)),"") | C53: =IFERROR(INDEX('Watershed plans'!$B$12:$B$19,MATCH(4,'Watershed plans'!$AB$12:$AB$19,0)),"") | D53: =IFERROR(INDEX('Watershed plans'!$K$12:$K$19,MATCH(4,'Watershed plans'!$AB$12:$AB$19,0)),"") | E53: =IFERROR(INDEX('Watershed plans'!$L$12:$L$19,MATCH(4,'Watershed plans'!$AB$12:$AB$19,0)),"") | F53: =IFERROR(INDEX('Watershed plans'!$J$12:$J$19,MATCH(4,'Watershed plans'!$AB$12:$AB$19,0)),"") | G53: =IFERROR(INDEX('Watershed plans'!$Z$12:$Z$19,MATCH(4,'Watershed plans'!$AB$12:$AB$19,0)),"") | H53: =IF(ISNUMBER(D53),D53-D52,"") | I53: =IF(ISNUMBER(E53),E53-E52,"") | J53: =IF(AND(ISNUMBER(H53),H53<>0),I53/H53,"")
A54: 5 | B54: =IFERROR(INDEX('Watershed plans'!$G$12:$G$19,MATCH(5,'Watershed plans'!$AB$12:$AB$19,0)),"") | C54: =IFERROR(INDEX('Watershed plans'!$B$12:$B$19,MATCH(5,'Watershed plans'!$AB$12:$AB$19,0)),"") | D54: =IFERROR(INDEX('Watershed plans'!$K$12:$K$19,MATCH(5,'Watershed plans'!$AB$12:$AB$19,0)),"") | E54: =IFERROR(INDEX('Watershed plans'!$L$12:$L$19,MATCH(5,'Watershed plans'!$AB$12:$AB$19,0)),"") | F54: =IFERROR(INDEX('Watershed plans'!$J$12:$J$19,MATCH(5,'Watershed plans'!$AB$12:$AB$19,0)),"") | G54: =IFERROR(INDEX('Watershed plans'!$Z$12:$Z$19,MATCH(5,'Watershed plans'!$AB$12:$AB$19,0)),"") | H54: =IF(ISNUMBER(D54),D54-D53,"") | I54: =IF(ISNUMBER(E54),E54-E53,"") | J54: =IF(AND(ISNUMBER(H54),H54<>0),I54/H54,"")
A55: 6 | B55: =IFERROR(INDEX('Watershed plans'!$G$12:$G$19,MATCH(6,'Watershed plans'!$AB$12:$AB$19,0)),"") | C55: =IFERROR(INDEX('Watershed plans'!$B$12:$B$19,MATCH(6,'Watershed plans'!$AB$12:$AB$19,0)),"") | D55: =IFERROR(INDEX('Watershed plans'!$K$12:$K$19,MATCH(6,'Watershed plans'!$AB$12:$AB$19,0)),"") | E55: =IFERROR(INDEX('Watershed plans'!$L$12:$L$19,MATCH(6,'Watershed plans'!$AB$12:$AB$19,0)),"") | F55: =IFERROR(INDEX('Watershed plans'!$J$12:$J$19,MATCH(6,'Watershed plans'!$AB$12:$AB$19,0)),"") | G55: =IFERROR(INDEX('Watershed plans'!$Z$12:$Z$19,MATCH(6,'Watershed plans'!$AB$12:$AB$19,0)),"") | H55: =IF(ISNUMBER(D55),D55-D54,"") | I55: =IF(ISNUMBER(E55),E55-E54,"") | J55: =IF(AND(ISNUMBER(H55),H55<>0),I55/H55,"")
A56: 7 | B56: =IFERROR(INDEX('Watershed plans'!$G$12:$G$19,MATCH(7,'Watershed plans'!$AB$12:$AB$19,0)),"") | C56: =IFERROR(INDEX('Watershed plans'!$B$12:$B$19,MATCH(7,'Watershed plans'!$AB$12:$AB$19,0)),"") | D56: =IFERROR(INDEX('Watershed plans'!$K$12:$K$19,MATCH(7,'Watershed plans'!$AB$12:$AB$19,0)),"") | E56: =IFERROR(INDEX('Watershed plans'!$L$12:$L$19,MATCH(7,'Watershed plans'!$AB$12:$AB$19,0)),"") | F56: =IFERROR(INDEX('Watershed plans'!$J$12:$J$19,MATCH(7,'Watershed plans'!$AB$12:$AB$19,0)),"") | G56: =IFERROR(INDEX('Watershed plans'!$Z$12:$Z$19,MATCH(7,'Watershed plans'!$AB$12:$AB$19,0)),"") | H56: =IF(ISNUMBER(D56),D56-D55,"") | I56: =IF(ISNUMBER(E56),E56-E55,"") | J56: =IF(AND(ISNUMBER(H56),H56<>0),I56/H56,"")
A57: 8 | B57: =IFERROR(INDEX('Watershed plans'!$G$12:$G$19,MATCH(8,'Watershed plans'!$AB$12:$AB$19,0)),"") | C57: =IFERROR(INDEX('Watershed plans'!$B$12:$B$19,MATCH(8,'Watershed plans'!$AB$12:$AB$19,0)),"") | D57: =IFERROR(INDEX('Watershed plans'!$K$12:$K$19,MATCH(8,'Watershed plans'!$AB$12:$AB$19,0)),"") | E57: =IFERROR(INDEX('Watershed plans'!$L$12:$L$19,MATCH(8,'Watershed plans'!$AB$12:$AB$19,0)),"") | F57: =IFERROR(INDEX('Watershed plans'!$J$12:$J$19,MATCH(8,'Watershed plans'!$AB$12:$AB$19,0)),"") | G57: =IFERROR(INDEX('Watershed plans'!$Z$12:$Z$19,MATCH(8,'Watershed plans'!$AB$12:$AB$19,0)),"") | H57: =IF(ISNUMBER(D57),D57-D56,"") | I57: =IF(ISNUMBER(E57),E57-E56,"") | J57: =IF(AND(ISNUMBER(H57),H57<>0),I57/H57,"")
A58: 9 | B58: =IFERROR(INDEX('Watershed plans'!$G$12:$G$19,MATCH(9,'Watershed plans'!$AB$12:$AB$19,0)),"") | C58: =IFERROR(INDEX('Watershed plans'!$B$12:$B$19,MATCH(9,'Watershed plans'!$AB$12:$AB$19,0)),"") | D58: =IFERROR(INDEX('Watershed plans'!$K$12:$K$19,MATCH(9,'Watershed plans'!$AB$12:$AB$19,0)),"") | E58: =IFERROR(INDEX('Watershed plans'!$L$12:$L$19,MATCH(9,'Watershed plans'!$AB$12:$AB$19,0)),"") | F58: =IFERROR(INDEX('Watershed plans'!$J$12:$J$19,MATCH(9,'Watershed plans'!$AB$12:$AB$19,0)),"") | G58: =IFERROR(INDEX('Watershed plans'!$Z$12:$Z$19,MATCH(9,'Watershed plans'!$AB$12:$AB$19,0)),"") | H58: =IF(ISNUMBER(D58),D58-D57,"") | I58: =IF(ISNUMBER(E58),E58-E57,"") | J58: =IF(AND(ISNUMBER(H58),H58<>0),I58/H58,"")
A59: 10 | B59: =IFERROR(INDEX('Watershed plans'!$G$12:$G$19,MATCH(10,'Watershed plans'!$AB$12:$AB$19,0)),"") | C59: =IFERROR(INDEX('Watershed plans'!$B$12:$B$19,MATCH(10,'Watershed plans'!$AB$12:$AB$19,0)),"") | D59: =IFERROR(INDEX('Watershed plans'!$K$12:$K$19,MATCH(10,'Watershed plans'!$AB$12:$AB$19,0)),"") | E59: =IFERROR(INDEX('Watershed plans'!$L$12:$L$19,MATCH(10,'Watershed plans'!$AB$12:$AB$19,0)),"") | F59: =IFERROR(INDEX('Watershed plans'!$J$12:$J$19,MATCH(10,'Watershed plans'!$AB$12:$AB$19,0)),"") | G59: =IFERROR(INDEX('Watershed plans'!$Z$12:$Z$19,MATCH(10,'Watershed plans'!$AB$12:$AB$19,0)),"") | H59: =IF(ISNUMBER(D59),D59-D58,"") | I59: =IF(ISNUMBER(E59),E59-E58,"") | J59: =IF(AND(ISNUMBER(H59),H59<>0),I59/H59,"")
A60: 11 | B60: =IFERROR(INDEX('Watershed plans'!$G$12:$G$19,MATCH(11,'Watershed plans'!$AB$12:$AB$19,0)),"") | C60: =IFERROR(INDEX('Watershed plans'!$B$12:$B$19,MATCH(11,'Watershed plans'!$AB$12:$AB$19,0)),"") | D60: =IFERROR(INDEX('Watershed plans'!$K$12:$K$19,MATCH(11,'Watershed plans'!$AB$12:$AB$19,0)),"") | E60: =IFERROR(INDEX('Watershed plans'!$L$12:$L$19,MATCH(11,'Watershed plans'!$AB$12:$AB$19,0)),"") | F60: =IFERROR(INDEX('Watershed plans'!$J$12:$J$19,MATCH(11,'Watershed plans'!$AB$12:$AB$19,0)),"") | G60: =IFERROR(INDEX('Watershed plans'!$Z$12:$Z$19,MATCH(11,'Watershed plans'!$AB$12:$AB$19,0)),"") | H60: =IF(ISNUMBER(D60),D60-D59,"") | I60: =IF(ISNUMBER(E60),E60-E59,"") | J60: =IF(AND(ISNUMBER(H60),H60<>0),I60/H60,"")
A61: 12 | B61: =IFERROR(INDEX('Watershed plans'!$G$12:$G$19,MATCH(12,'Watershed plans'!$AB$12:$AB$19,0)),"") | C61: =IFERROR(INDEX('Watershed plans'!$B$12:$B$19,MATCH(12,'Watershed plans'!$AB$12:$AB$19,0)),"") | D61: =IFERROR(INDEX('Watershed plans'!$K$12:$K$19,MATCH(12,'Watershed plans'!$AB$12:$AB$19,0)),"") | E61: =IFERROR(INDEX('Watershed plans'!$L$12:$L$19,MATCH(12,'Watershed plans'!$AB$12:$AB$19,0)),"") | F61: =IFERROR(INDEX('Watershed plans'!$J$12:$J$19,MATCH(12,'Watershed plans'!$AB$12:$AB$19,0)),"") | G61: =IFERROR(INDEX('Watershed plans'!$Z$12:$Z$19,MATCH(12,'Watershed plans'!$AB$12:$AB$19,0)),"") | H61: =IF(ISNUMBER(D61),D61-D60,"") | I61: =IF(ISNUMBER(E61),E61-E60,"") | J61: =IF(AND(ISNUMBER(H61),H61<>0),I61/H61,"")
A62: 13 | B62: =IFERROR(INDEX('Watershed plans'!$G$12:$G$19,MATCH(13,'Watershed plans'!$AB$12:$AB$19,0)),"") | C62: =IFERROR(INDEX('Watershed plans'!$B$12:$B$19,MATCH(13,'Watershed plans'!$AB$12:$AB$19,0)),"") | D62: =IFERROR(INDEX('Watershed plans'!$K$12:$K$19,MATCH(13,'Watershed plans'!$AB$12:$AB$19,0)),"") | E62: =IFERROR(INDEX('Watershed plans'!$L$12:$L$19,MATCH(13,'Watershed plans'!$AB$12:$AB$19,0)),"") | F62: =IFERROR(INDEX('Watershed plans'!$J$12:$J$19,MATCH(13,'Watershed plans'!$AB$12:$AB$19,0)),"") | G62: =IFERROR(INDEX('Watershed plans'!$Z$12:$Z$19,MATCH(13,'Watershed plans'!$AB$12:$AB$19,0)),"") | H62: =IF(ISNUMBER(D62),D62-D61,"") | I62: =IF(ISNUMBER(E62),E62-E61,"") | J62: =IF(AND(ISNUMBER(H62),H62<>0),I62/H62,"")
A63: 14 | B63: =IFERROR(INDEX('Watershed plans'!$G$12:$G$19,MATCH(14,'Watershed plans'!$AB$12:$AB$19,0)),"") | C63: =IFERROR(INDEX('Watershed plans'!$B$12:$B$19,MATCH(14,'Watershed plans'!$AB$12:$AB$19,0)),"") | D63: =IFERROR(INDEX('Watershed plans'!$K$12:$K$19,MATCH(14,'Watershed plans'!$AB$12:$AB$19,0)),"") | E63: =IFERROR(INDEX('Watershed plans'!$L$12:$L$19,MATCH(14,'Watershed plans'!$AB$12:$AB$19,0)),"") | F63: =IFERROR(INDEX('Watershed plans'!$J$12:$J$19,MATCH(14,'Watershed plans'!$AB$12:$AB$19,0)),"") | G63: =IFERROR(INDEX('Watershed plans'!$Z$12:$Z$19,MATCH(14,'Watershed plans'!$AB$12:$AB$19,0)),"") | H63: =IF(ISNUMBER(D63),D63-D62,"") | I63: =IF(ISNUMBER(E63),E63-E62,"") | J63: =IF(AND(ISNUMBER(H63),H63<>0),I63/H63,"")
A64: 15 | B64: =IFERROR(INDEX('Watershed plans'!$G$12:$G$19,MATCH(15,'Watershed plans'!$AB$12:$AB$19,0)),"") | C64: =IFERROR(INDEX('Watershed plans'!$B$12:$B$19,MATCH(15,'Watershed plans'!$AB$12:$AB$19,0)),"") | D64: =IFERROR(INDEX('Watershed plans'!$K$12:$K$19,MATCH(15,'Watershed plans'!$AB$12:$AB$19,0)),"") | E64: =IFERROR(INDEX('Watershed plans'!$L$12:$L$19,MATCH(15,'Watershed plans'!$AB$12:$AB$19,0)),"") | F64: =IFERROR(INDEX('Watershed plans'!$J$12:$J$19,MATCH(15,'Watershed plans'!$AB$12:$AB$19,0)),"") | G64: =IFERROR(INDEX('Watershed plans'!$Z$12:$Z$19,MATCH(15,'Watershed plans'!$AB$12:$AB$19,0)),"") | H64: =IF(ISNUMBER(D64),D64-D63,"") | I64: =IF(ISNUMBER(E64),E64-E63,"") | J64: =IF(AND(ISNUMBER(H64),H64<>0),I64/H64,"")
A65: 16 | B65: =IFERROR(INDEX('Watershed plans'!$G$12:$G$19,MATCH(16,'Watershed plans'!$AB$12:$AB$19,0)),"") | C65: =IFERROR(INDEX('Watershed plans'!$B$12:$B$19,MATCH(16,'Watershed plans'!$AB$12:$AB$19,0)),"") | D65: =IFERROR(INDEX('Watershed plans'!$K$12:$K$19,MATCH(16,'Watershed plans'!$AB$12:$AB$19,0)),"") | E65: =IFERROR(INDEX('Watershed plans'!$L$12:$L$19,MATCH(16,'Watershed plans'!$AB$12:$AB$19,0)),"") | F65: =IFERROR(INDEX('Watershed plans'!$J$12:$J$19,MATCH(16,'Watershed plans'!$AB$12:$AB$19,0)),"") | G65: =IFERROR(INDEX('Watershed plans'!$Z$12:$Z$19,MATCH(16,'Watershed plans'!$AB$12:$AB$19,0)),"") | H65: =IF(ISNUMBER(D65),D65-D64,"") | I65: =IF(ISNUMBER(E65),E65-E64,"") | J65: =IF(AND(ISNUMBER(H65),H65<>0),I65/H65,"")
A66: 17 | B66: =IFERROR(INDEX('Watershed plans'!$G$12:$G$19,MATCH(17,'Watershed plans'!$AB$12:$AB$19,0)),"") | C66: =IFERROR(INDEX('Watershed plans'!$B$12:$B$19,MATCH(17,'Watershed plans'!$AB$12:$AB$19,0)),"") | D66: =IFERROR(INDEX('Watershed plans'!$K$12:$K$19,MATCH(17,'Watershed plans'!$AB$12:$AB$19,0)),"") | E66: =IFERROR(INDEX('Watershed plans'!$L$12:$L$19,MATCH(17,'Watershed plans'!$AB$12:$AB$19,0)),"") | F66: =IFERROR(INDEX('Watershed plans'!$J$12:$J$19,MATCH(17,'Watershed plans'!$AB$12:$AB$19,0)),"") | G66: =IFERROR(INDEX('Watershed plans'!$Z$12:$Z$19,MATCH(17,'Watershed plans'!$AB$12:$AB$19,0)),"") | H66: =IF(ISNUMBER(D66),D66-D65,"") | I66: =IF(ISNUMBER(E66),E66-E65,"") | J66: =IF(AND(ISNUMBER(H66),H66<>0),I66/H66,"")
A67: 18 | B67: =IFERROR(INDEX('Watershed plans'!$G$12:$G$19,MATCH(18,'Watershed plans'!$AB$12:$AB$19,0)),"") | C67: =IFERROR(INDEX('Watershed plans'!$B$12:$B$19,MATCH(18,'Watershed plans'!$AB$12:$AB$19,0)),"") | D67: =IFERROR(INDEX('Watershed plans'!$K$12:$K$19,MATCH(18,'Watershed plans'!$AB$12:$AB$19,0)),"") | E67: =IFERROR(INDEX('Watershed plans'!$L$12:$L$19,MATCH(18,'Watershed plans'!$AB$12:$AB$19,0)),"") | F67: =IFERROR(INDEX('Watershed plans'!$J$12:$J$19,MATCH(18,'Watershed plans'!$AB$12:$AB$19,0)),"") | G67: =IFERROR(INDEX('Watershed plans'!$Z$12:$Z$19,MATCH(18,'Watershed plans'!$AB$12:$AB$19,0)),"") | H67: =IF(ISNUMBER(D67),D67-D66,"") | I67: =IF(ISNUMBER(E67),E67-E66,"") | J67: =IF(AND(ISNUMBER(H67),H67<>0),I67/H67,"")
A68: 19 | B68: =IFERROR(INDEX('Watershed plans'!$G$12:$G$19,MATCH(19,'Watershed plans'!$AB$12:$AB$19,0)),"") | C68: =IFERROR(INDEX('Watershed plans'!$B$12:$B$19,MATCH(19,'Watershed plans'!$AB$12:$AB$19,0)),"") | D68: =IFERROR(INDEX('Watershed plans'!$K$12:$K$19,MATCH(19,'Watershed plans'!$AB$12:$AB$19,0)),"") | E68: =IFERROR(INDEX('Watershed plans'!$L$12:$L$19,MATCH(19,'Watershed plans'!$AB$12:$AB$19,0)),"") | F68: =IFERROR(INDEX('Watershed plans'!$J$12:$J$19,MATCH(19,'Watershed plans'!$AB$12:$AB$19,0)),"") | G68: =IFERROR(INDEX('Watershed plans'!$Z$12:$Z$19,MATCH(19,'Watershed plans'!$AB$12:$AB$19,0)),"") | H68: =IF(ISNUMBER(D68),D68-D67,"") | I68: =IF(ISNUMBER(E68),E68-E67,"") | J68: =IF(AND(ISNUMBER(H68),H68<>0),I68/H68,"")
A69: 20 | B69: =IFERROR(INDEX('Watershed plans'!$G$12:$G$19,MATCH(20,'Watershed plans'!$AB$12:$AB$19,0)),"") | C69: =IFERROR(INDEX('Watershed plans'!$B$12:$B$19,MATCH(20,'Watershed plans'!$AB$12:$AB$19,0)),"") | D69: =IFERROR(INDEX('Watershed plans'!$K$12:$K$19,MATCH(20,'Watershed plans'!$AB$12:$AB$19,0)),"") | E69: =IFERROR(INDEX('Watershed plans'!$L$12:$L$19,MATCH(20,'Watershed plans'!$AB$12:$AB$19,0)),"") | F69: =IFERROR(INDEX('Watershed plans'!$J$12:$J$19,MATCH(20,'Watershed plans'!$AB$12:$AB$19,0)),"") | G69: =IFERROR(INDEX('Watershed plans'!$Z$12:$Z$19,MATCH(20,'Watershed plans'!$AB$12:$AB$19,0)),"") | H69: =IF(ISNUMBER(D69),D69-D68,"") | I69: =IF(ISNUMBER(E69),E69-E68,"") | J69: =IF(AND(ISNUMBER(H69),H69<>0),I69/H69,"")
A70: 21 | B70: =IFERROR(INDEX('Watershed plans'!$G$12:$G$19,MATCH(21,'Watershed plans'!$AB$12:$AB$19,0)),"") | C70: =IFERROR(INDEX('Watershed plans'!$B$12:$B$19,MATCH(21,'Watershed plans'!$AB$12:$AB$19,0)),"") | D70: =IFERROR(INDEX('Watershed plans'!$K$12:$K$19,MATCH(21,'Watershed plans'!$AB$12:$AB$19,0)),"") | E70: =IFERROR(INDEX('Watershed plans'!$L$12:$L$19,MATCH(21,'Watershed plans'!$AB$12:$AB$19,0)),"") | F70: =IFERROR(INDEX('Watershed plans'!$J$12:$J$19,MATCH(21,'Watershed plans'!$AB$12:$AB$19,0)),"") | G70: =IFERROR(INDEX('Watershed plans'!$Z$12:$Z$19,MATCH(21,'Watershed plans'!$AB$12:$AB$19,0)),"") | H70: =IF(ISNUMBER(D70),D70-D69,"") | I70: =IF(ISNUMBER(E70),E70-E69,"") | J70: =IF(AND(ISNUMBER(H70),H70<>0),I70/H70,"")
A71: 22 | B71: =IFERROR(INDEX('Watershed plans'!$G$12:$G$19,MATCH(22,'Watershed plans'!$AB$12:$AB$19,0)),"") | C71: =IFERROR(INDEX('Watershed plans'!$B$12:$B$19,MATCH(22,'Watershed plans'!$AB$12:$AB$19,0)),"") | D71: =IFERROR(INDEX('Watershed plans'!$K$12:$K$19,MATCH(22,'Watershed plans'!$AB$12:$AB$19,0)),"") | E71: =IFERROR(INDEX('Watershed plans'!$L$12:$L$19,MATCH(22,'Watershed plans'!$AB$12:$AB$19,0)),"") | F71: =IFERROR(INDEX('Watershed plans'!$J$12:$J$19,MATCH(22,'Watershed plans'!$AB$12:$AB$19,0)),"") | G71: =IFERROR(INDEX('Watershed plans'!$Z$12:$Z$19,MATCH(22,'Watershed plans'!$AB$12:$AB$19,0)),"") | H71: =IF(ISNUMBER(D71),D71-D70,"") | I71: =IF(ISNUMBER(E71),E71-E70,"") | J71: =IF(AND(ISNUMBER(H71),H71<>0),I71/H71,"")
A72: 23 | B72: =IFERROR(INDEX('Watershed plans'!$G$12:$G$19,MATCH(23,'Watershed plans'!$AB$12:$AB$19,0)),"") | C72: =IFERROR(INDEX('Watershed plans'!$B$12:$B$19,MATCH(23,'Watershed plans'!$AB$12:$AB$19,0)),"") | D72: =IFERROR(INDEX('Watershed plans'!$K$12:$K$19,MATCH(23,'Watershed plans'!$AB$12:$AB$19,0)),"") | E72: =IFERROR(INDEX('Watershed plans'!$L$12:$L$19,MATCH(23,'Watershed plans'!$AB$12:$AB$19,0)),"") | F72: =IFERROR(INDEX('Watershed plans'!$J$12:$J$19,MATCH(23,'Watershed plans'!$AB$12:$AB$19,0)),"") | G72: =IFERROR(INDEX('Watershed plans'!$Z$12:$Z$19,MATCH(23,'Watershed plans'!$AB$12:$AB$19,0)),"") | H72: =IF(ISNUMBER(D72),D72-D71,"") | I72: =IF(ISNUMBER(E72),E72-E71,"") | J72: =IF(AND(ISNUMBER(H72),H72<>0),I72/H72,"")
A73: 24 | B73: =IFERROR(INDEX('Watershed plans'!$G$12:$G$19,MATCH(24,'Watershed plans'!$AB$12:$AB$19,0)),"") | C73: =IFERROR(INDEX('Watershed plans'!$B$12:$B$19,MATCH(24,'Watershed plans'!$AB$12:$AB$19,0)),"") | D73: =IFERROR(INDEX('Watershed plans'!$K$12:$K$19,MATCH(24,'Watershed plans'!$AB$12:$AB$19,0)),"") | E73: =IFERROR(INDEX('Watershed plans'!$L$12:$L$19,MATCH(24,'Watershed plans'!$AB$12:$AB$19,0)),"") | F73: =IFERROR(INDEX('Watershed plans'!$J$12:$J$19,MATCH(24,'Watershed plans'!$AB$12:$AB$19,0)),"") | G73: =IFERROR(INDEX('Watershed plans'!$Z$12:$Z$19,MATCH(24,'Watershed plans'!$AB$12:$AB$19,0)),"") | H73: =IF(ISNUMBER(D73),D73-D72,"") | I73: =IF(ISNUMBER(E73),E73-E72,"") | J73: =IF(AND(ISNUMBER(H73),H73<>0),I73/H73,"")
A74: 25 | B74: =IFERROR(INDEX('Watershed plans'!$G$12:$G$19,MATCH(25,'Watershed plans'!$AB$12:$AB$19,0)),"") | C74: =IFERROR(INDEX('Watershed plans'!$B$12:$B$19,MATCH(25,'Watershed plans'!$AB$12:$AB$19,0)),"") | D74: =IFERROR(INDEX('Watershed plans'!$K$12:$K$19,MATCH(25,'Watershed plans'!$AB$12:$AB$19,0)),"") | E74: =IFERROR(INDEX('Watershed plans'!$L$12:$L$19,MATCH(25,'Watershed plans'!$AB$12:$AB$19,0)),"") | F74: =IFERROR(INDEX('Watershed plans'!$J$12:$J$19,MATCH(25,'Watershed plans'!$AB$12:$AB$19,0)),"") | G74: =IFERROR(INDEX('Watershed plans'!$Z$12:$Z$19,MATCH(25,'Watershed plans'!$AB$12:$AB$19,0)),"") | H74: =IF(ISNUMBER(D74),D74-D73,"") | I74: =IF(ISNUMBER(E74),E74-E73,"") | J74: =IF(AND(ISNUMBER(H74),H74<>0),I74/H74,"")
A75: 26 | B75: =IFERROR(INDEX('Watershed plans'!$G$12:$G$19,MATCH(26,'Watershed plans'!$AB$12:$AB$19,0)),"") | C75: =IFERROR(INDEX('Watershed plans'!$B$12:$B$19,MATCH(26,'Watershed plans'!$AB$12:$AB$19,0)),"") | D75: =IFERROR(INDEX('Watershed plans'!$K$12:$K$19,MATCH(26,'Watershed plans'!$AB$12:$AB$19,0)),"") | E75: =IFERROR(INDEX('Watershed plans'!$L$12:$L$19,MATCH(26,'Watershed plans'!$AB$12:$AB$19,0)),"") | F75: =IFERROR(INDEX('Watershed plans'!$J$12:$J$19,MATCH(26,'Watershed plans'!$AB$12:$AB$19,0)),"") | G75: =IFERROR(INDEX('Watershed plans'!$Z$12:$Z$19,MATCH(26,'Watershed plans'!$AB$12:$AB$19,0)),"") | H75: =IF(ISNUMBER(D75),D75-D74,"") | I75: =IF(ISNUMBER(E75),E75-E74,"") | J75: =IF(AND(ISNUMBER(H75),H75<>0),I75/H75,"")
A76: 27 | B76: =IFERROR(INDEX('Watershed plans'!$G$12:$G$19,MATCH(27,'Watershed plans'!$AB$12:$AB$19,0)),"") | C76: =IFERROR(INDEX('Watershed plans'!$B$12:$B$19,MATCH(27,'Watershed plans'!$AB$12:$AB$19,0)),"") | D76: =IFERROR(INDEX('Watershed plans'!$K$12:$K$19,MATCH(27,'Watershed plans'!$AB$12:$AB$19,0)),"") | E76: =IFERROR(INDEX('Watershed plans'!$L$12:$L$19,MATCH(27,'Watershed plans'!$AB$12:$AB$19,0)),"") | F76: =IFERROR(INDEX('Watershed plans'!$J$12:$J$19,MATCH(27,'Watershed plans'!$AB$12:$AB$19,0)),"") | G76: =IFERROR(INDEX('Watershed plans'!$Z$12:$Z$19,MATCH(27,'Watershed plans'!$AB$12:$AB$19,0)),"") | H76: =IF(ISNUMBER(D76),D76-D75,"") | I76: =IF(ISNUMBER(E76),E76-E75,"") | J76: =IF(AND(ISNUMBER(H76),H76<>0),I76/H76,"")
A77: 28 | B77: =IFERROR(INDEX('Watershed plans'!$G$12:$G$19,MATCH(28,'Watershed plans'!$AB$12:$AB$19,0)),"") | C77: =IFERROR(INDEX('Watershed plans'!$B$12:$B$19,MATCH(28,'Watershed plans'!$AB$12:$AB$19,0)),"") | D77: =IFERROR(INDEX('Watershed plans'!$K$12:$K$19,MATCH(28,'Watershed plans'!$AB$12:$AB$19,0)),"") | E77: =IFERROR(INDEX('Watershed plans'!$L$12:$L$19,MATCH(28,'Watershed plans'!$AB$12:$AB$19,0)),"") | F77: =IFERROR(INDEX('Watershed plans'!$J$12:$J$19,MATCH(28,'Watershed plans'!$AB$12:$AB$19,0)),"") | G77: =IFERROR(INDEX('Watershed plans'!$Z$12:$Z$19,MATCH(28,'Watershed plans'!$AB$12:$AB$19,0)),"") | H77: =IF(ISNUMBER(D77),D77-D76,"") | I77: =IF(ISNUMBER(E77),E77-E76,"") | J77: =IF(AND(ISNUMBER(H77),H77<>0),I77/H77,"")
A78: 29 | B78: =IFERROR(INDEX('Watershed plans'!$G$12:$G$19,MATCH(29,'Watershed plans'!$AB$12:$AB$19,0)),"") | C78: =IFERROR(INDEX('Watershed plans'!$B$12:$B$19,MATCH(29,'Watershed plans'!$AB$12:$AB$19,0)),"") | D78: =IFERROR(INDEX('Watershed plans'!$K$12:$K$19,MATCH(29,'Watershed plans'!$AB$12:$AB$19,0)),"") | E78: =IFERROR(INDEX('Watershed plans'!$L$12:$L$19,MATCH(29,'Watershed plans'!$AB$12:$AB$19,0)),"") | F78: =IFERROR(INDEX('Watershed plans'!$J$12:$J$19,MATCH(29,'Watershed plans'!$AB$12:$AB$19,0)),"") | G78: =IFERROR(INDEX('Watershed plans'!$Z$12:$Z$19,MATCH(29,'Watershed plans'!$AB$12:$AB$19,0)),"") | H78: =IF(ISNUMBER(D78),D78-D77,"") | I78: =IF(ISNUMBER(E78),E78-E77,"") | J78: =IF(AND(ISNUMBER(H78),H78<>0),I78/H78,"")
A79: 30 | B79: =IFERROR(INDEX('Watershed plans'!$G$12:$G$19,MATCH(30,'Watershed plans'!$AB$12:$AB$19,0)),"") | C79: =IFERROR(INDEX('Watershed plans'!$B$12:$B$19,MATCH(30,'Watershed plans'!$AB$12:$AB$19,0)),"") | D79: =IFERROR(INDEX('Watershed plans'!$K$12:$K$19,MATCH(30,'Watershed plans'!$AB$12:$AB$19,0)),"") | E79: =IFERROR(INDEX('Watershed plans'!$L$12:$L$19,MATCH(30,'Watershed plans'!$AB$12:$AB$19,0)),"") | F79: =IFERROR(INDEX('Watershed plans'!$J$12:$J$19,MATCH(30,'Watershed plans'!$AB$12:$AB$19,0)),"") | G79: =IFERROR(INDEX('Watershed plans'!$Z$12:$Z$19,MATCH(30,'Watershed plans'!$AB$12:$AB$19,0)),"") | H79: =IF(ISNUMBER(D79),D79-D78,"") | I79: =IF(ISNUMBER(E79),E79-E78,"") | J79: =IF(AND(ISNUMBER(H79),H79<>0),I79/H79,"")
A80: 31 | B80: =IFERROR(INDEX('Watershed plans'!$G$12:$G$19,MATCH(31,'Watershed plans'!$AB$12:$AB$19,0)),"") | C80: =IFERROR(INDEX('Watershed plans'!$B$12:$B$19,MATCH(31,'Watershed plans'!$AB$12:$AB$19,0)),"") | D80: =IFERROR(INDEX('Watershed plans'!$K$12:$K$19,MATCH(31,'Watershed plans'!$AB$12:$AB$19,0)),"") | E80: =IFERROR(INDEX('Watershed plans'!$L$12:$L$19,MATCH(31,'Watershed plans'!$AB$12:$AB$19,0)),"") | F80: =IFERROR(INDEX('Watershed plans'!$J$12:$J$19,MATCH(31,'Watershed plans'!$AB$12:$AB$19,0)),"") | G80: =IFERROR(INDEX('Watershed plans'!$Z$12:$Z$19,MATCH(31,'Watershed plans'!$AB$12:$AB$19,0)),"") | H80: =IF(ISNUMBER(D80),D80-D79,"") | I80: =IF(ISNUMBER(E80),E80-E79,"") | J80: =IF(AND(ISNUMBER(H80),H80<>0),I80/H80,"")
A81: 32 | B81: =IFERROR(INDEX('Watershed plans'!$G$12:$G$19,MATCH(32,'Watershed plans'!$AB$12:$AB$19,0)),"") | C81: =IFERROR(INDEX('Watershed plans'!$B$12:$B$19,MATCH(32,'Watershed plans'!$AB$12:$AB$19,0)),"") | D81: =IFERROR(INDEX('Watershed plans'!$K$12:$K$19,MATCH(32,'Watershed plans'!$AB$12:$AB$19,0)),"") | E81: =IFERROR(INDEX('Watershed plans'!$L$12:$L$19,MATCH(32,'Watershed plans'!$AB$12:$AB$19,0)),"") | F81: =IFERROR(INDEX('Watershed plans'!$J$12:$J$19,MATCH(32,'Watershed plans'!$AB$12:$AB$19,0)),"") | G81: =IFERROR(INDEX('Watershed plans'!$Z$12:$Z$19,MATCH(32,'Watershed plans'!$AB$12:$AB$19,0)),"") | H81: =IF(ISNUMBER(D81),D81-D80,"") | I81: =IF(ISNUMBER(E81),E81-E80,"") | J81: =IF(AND(ISNUMBER(H81),H81<>0),I81/H81,"")
A82: 33 | B82: =IFERROR(INDEX('Watershed plans'!$G$12:$G$19,MATCH(33,'Watershed plans'!$AB$12:$AB$19,0)),"") | C82: =IFERROR(INDEX('Watershed plans'!$B$12:$B$19,MATCH(33,'Watershed plans'!$AB$12:$AB$19,0)),"") | D82: =IFERROR(INDEX('Watershed plans'!$K$12:$K$19,MATCH(33,'Watershed plans'!$AB$12:$AB$19,0)),"") | E82: =IFERROR(INDEX('Watershed plans'!$L$12:$L$19,MATCH(33,'Watershed plans'!$AB$12:$AB$19,0)),"") | F82: =IFERROR(INDEX('Watershed plans'!$J$12:$J$19,MATCH(33,'Watershed plans'!$AB$12:$AB$19,0)),"") | G82: =IFERROR(INDEX('Watershed plans'!$Z$12:$Z$19,MATCH(33,'Watershed plans'!$AB$12:$AB$19,0)),"") | H82: =IF(ISNUMBER(D82),D82-D81,"") | I82: =IF(ISNUMBER(E82),E82-E81,"") | J82: =IF(AND(ISNUMBER(H82),H82<>0),I82/H82,"")
A83: 34 | B83: =IFERROR(INDEX('Watershed plans'!$G$12:$G$19,MATCH(34,'Watershed plans'!$AB$12:$AB$19,0)),"") | C83: =IFERROR(INDEX('Watershed plans'!$B$12:$B$19,MATCH(34,'Watershed plans'!$AB$12:$AB$19,0)),"") | D83: =IFERROR(INDEX('Watershed plans'!$K$12:$K$19,MATCH(34,'Watershed plans'!$AB$12:$AB$19,0)),"") | E83: =IFERROR(INDEX('Watershed plans'!$L$12:$L$19,MATCH(34,'Watershed plans'!$AB$12:$AB$19,0)),"") | F83: =IFERROR(INDEX('Watershed plans'!$J$12:$J$19,MATCH(34,'Watershed plans'!$AB$12:$AB$19,0)),"") | G83: =IFERROR(INDEX('Watershed plans'!$Z$12:$Z$19,MATCH(34,'Watershed plans'!$AB$12:$AB$19,0)),"") | H83: =IF(ISNUMBER(D83),D83-D82,"") | I83: =IF(ISNUMBER(E83),E83-E82,"") | J83: =IF(AND(ISNUMBER(H83),H83<>0),I83/H83,"")
A84: 35 | B84: =IFERROR(INDEX('Watershed plans'!$G$12:$G$19,MATCH(35,'Watershed plans'!$AB$12:$AB$19,0)),"") | C84: =IFERROR(INDEX('Watershed plans'!$B$12:$B$19,MATCH(35,'Watershed plans'!$AB$12:$AB$19,0)),"") | D84: =IFERROR(INDEX('Watershed plans'!$K$12:$K$19,MATCH(35,'Watershed plans'!$AB$12:$AB$19,0)),"") | E84: =IFERROR(INDEX('Watershed plans'!$L$12:$L$19,MATCH(35,'Watershed plans'!$AB$12:$AB$19,0)),"") | F84: =IFERROR(INDEX('Watershed plans'!$J$12:$J$19,MATCH(35,'Watershed plans'!$AB$12:$AB$19,0)),"") | G84: =IFERROR(INDEX('Watershed plans'!$Z$12:$Z$19,MATCH(35,'Watershed plans'!$AB$12:$AB$19,0)),"") | H84: =IF(ISNUMBER(D84),D84-D83,"") | I84: =IF(ISNUMBER(E84),E84-E83,"") | J84: =IF(AND(ISNUMBER(H84),H84<>0),I84/H84,"")
A85: 36 | B85: =IFERROR(INDEX('Watershed plans'!$G$12:$G$19,MATCH(36,'Watershed plans'!$AB$12:$AB$19,0)),"") | C85: =IFERROR(INDEX('Watershed plans'!$B$12:$B$19,MATCH(36,'Watershed plans'!$AB$12:$AB$19,0)),"") | D85: =IFERROR(INDEX('Watershed plans'!$K$12:$K$19,MATCH(36,'Watershed plans'!$AB$12:$AB$19,0)),"") | E85: =IFERROR(INDEX('Watershed plans'!$L$12:$L$19,MATCH(36,'Watershed plans'!$AB$12:$AB$19,0)),"") | F85: =IFERROR(INDEX('Watershed plans'!$J$12:$J$19,MATCH(36,'Watershed plans'!$AB$12:$AB$19,0)),"") | G85: =IFERROR(INDEX('Watershed plans'!$Z$12:$Z$19,MATCH(36,'Watershed plans'!$AB$12:$AB$19,0)),"") | H85: =IF(ISNUMBER(D85),D85-D84,"") | I85: =IF(ISNUMBER(E85),E85-E84,"") | J85: =IF(AND(ISNUMBER(H85),H85<>0),I85/H85,"")
A86: 37 | B86: =IFERROR(INDEX('Watershed plans'!$G$12:$G$19,MATCH(37,'Watershed plans'!$AB$12:$AB$19,0)),"") | C86: =IFERROR(INDEX('Watershed plans'!$B$12:$B$19,MATCH(37,'Watershed plans'!$AB$12:$AB$19,0)),"") | D86: =IFERROR(INDEX('Watershed plans'!$K$12:$K$19,MATCH(37,'Watershed plans'!$AB$12:$AB$19,0)),"") | E86: =IFERROR(INDEX('Watershed plans'!$L$12:$L$19,MATCH(37,'Watershed plans'!$AB$12:$AB$19,0)),"") | F86: =IFERROR(INDEX('Watershed plans'!$J$12:$J$19,MATCH(37,'Watershed plans'!$AB$12:$AB$19,0)),"") | G86: =IFERROR(INDEX('Watershed plans'!$Z$12:$Z$19,MATCH(37,'Watershed plans'!$AB$12:$AB$19,0)),"") | H86: =IF(ISNUMBER(D86),D86-D85,"") | I86: =IF(ISNUMBER(E86),E86-E85,"") | J86: =IF(AND(ISNUMBER(H86),H86<>0),I86/H86,"")
A87: 38 | B87: =IFERROR(INDEX('Watershed plans'!$G$12:$G$19,MATCH(38,'Watershed plans'!$AB$12:$AB$19,0)),"") | C87: =IFERROR(INDEX('Watershed plans'!$B$12:$B$19,MATCH(38,'Watershed plans'!$AB$12:$AB$19,0)),"") | D87: =IFERROR(INDEX('Watershed plans'!$K$12:$K$19,MATCH(38,'Watershed plans'!$AB$12:$AB$19,0)),"") | E87: =IFERROR(INDEX('Watershed plans'!$L$12:$L$19,MATCH(38,'Watershed plans'!$AB$12:$AB$19,0)),"") | F87: =IFERROR(INDEX('Watershed plans'!$J$12:$J$19,MATCH(38,'Watershed plans'!$AB$12:$AB$19,0)),"") | G87: =IFERROR(INDEX('Watershed plans'!$Z$12:$Z$19,MATCH(38,'Watershed plans'!$AB$12:$AB$19,0)),"") | H87: =IF(ISNUMBER(D87),D87-D86,"") | I87: =IF(ISNUMBER(E87),E87-E86,"") | J87: =IF(AND(ISNUMBER(H87),H87<>0),I87/H87,"")
A88: 39 | B88: =IFERROR(INDEX('Watershed plans'!$G$12:$G$19,MATCH(39,'Watershed plans'!$AB$12:$AB$19,0)),"") | C88: =IFERROR(INDEX('Watershed plans'!$B$12:$B$19,MATCH(39,'Watershed plans'!$AB$12:$AB$19,0)),"") | D88: =IFERROR(INDEX('Watershed plans'!$K$12:$K$19,MATCH(39,'Watershed plans'!$AB$12:$AB$19,0)),"") | E88: =IFERROR(INDEX('Watershed plans'!$L$12:$L$19,MATCH(39,'Watershed plans'!$AB$12:$AB$19,0)),"") | F88: =IFERROR(INDEX('Watershed plans'!$J$12:$J$19,MATCH(39,'Watershed plans'!$AB$12:$AB$19,0)),"") | G88: =IFERROR(INDEX('Watershed plans'!$Z$12:$Z$19,MATCH(39,'Watershed plans'!$AB$12:$AB$19,0)),"") | H88: =IF(ISNUMBER(D88),D88-D87,"") | I88: =IF(ISNUMBER(E88),E88-E87,"") | J88: =IF(AND(ISNUMBER(H88),H88<>0),I88/H88,"")
A89: 40 | B89: =IFERROR(INDEX('Watershed plans'!$G$12:$G$19,MATCH(40,'Watershed plans'!$AB$12:$AB$19,0)),"") | C89: =IFERROR(INDEX('Watershed plans'!$B$12:$B$19,MATCH(40,'Watershed plans'!$AB$12:$AB$19,0)),"") | D89: =IFERROR(INDEX('Watershed plans'!$K$12:$K$19,MATCH(40,'Watershed plans'!$AB$12:$AB$19,0)),"") | E89: =IFERROR(INDEX('Watershed plans'!$L$12:$L$19,MATCH(40,'Watershed plans'!$AB$12:$AB$19,0)),"") | F89: =IFERROR(INDEX('Watershed plans'!$J$12:$J$19,MATCH(40,'Watershed plans'!$AB$12:$AB$19,0)),"") | G89: =IFERROR(INDEX('Watershed plans'!$Z$12:$Z$19,MATCH(40,'Watershed plans'!$AB$12:$AB$19,0)),"") | H89: =IF(ISNUMBER(D89),D89-D88,"") | I89: =IF(ISNUMBER(E89),E89-E88,"") | J89: =IF(AND(ISNUMBER(H89),H89<>0),I89/H89,"")
A92: Tentatively selected plan
A93: Plan number
A94: Plan | B94: =IFERROR(INDEX('Watershed plans'!$B$12:$B$19,MATCH($B$93,'Watershed plans'!$G$12:$G$19,0)),"n/a")
A95: Lift (AACU) | B95: =IFERROR(INDEX('Watershed plans'!$K$12:$K$19,MATCH($B$93,'Watershed plans'!$G$12:$G$19,0)),"n/a")
A96: Average annual cost | B96: =IFERROR(INDEX('Watershed plans'!$L$12:$L$19,MATCH($B$93,'Watershed plans'!$G$12:$G$19,0)),"n/a")
A97: Construction cost | B97: =IFERROR(INDEX('Watershed plans'!$J$12:$J$19,MATCH($B$93,'Watershed plans'!$G$12:$G$19,0)),"n/a")
A98: Unit cost | B98: =IFERROR(INDEX('Watershed plans'!$Z$12:$Z$19,MATCH($B$93,'Watershed plans'!$G$12:$G$19,0)),"n/a")
A99: In the final array | B99: =IFERROR(INDEX('Watershed plans'!$AA$12:$AA$19,MATCH($B$93,'Watershed plans'!$G$12:$G$19,0)),"n/a")

Sheet IWR input
A1: IWR Planning Suite II input
A2: Paste-ready plan, output and cost columns for an independent re-run in IWR Planning Suite II (user-entered planning set; No Action is the first plan).
A4: Site planning sets
A5: Site | B5: Plan | C5: Output (AACU above No Action) | D5: Cost (average annual, above No Action)
A6: R1 | B6: FWOP | C6: ='Site CE-ICA'!I6/10^in_out_dp | D6: ='Site CE-ICA'!J6/10^in_cost_dp
A7: R1 | B7: A1 | C7: ='Site CE-ICA'!I7/10^in_out_dp | D7: ='Site CE-ICA'!J7/10^in_cost_dp
A8: R1 | B8: A2 | C8: ='Site CE-ICA'!I8/10^in_out_dp | D8: ='Site CE-ICA'!J8/10^in_cost_dp
A9: R1 | B9: A3 | C9: ='Site CE-ICA'!I9/10^in_out_dp | D9: ='Site CE-ICA'!J9/10^in_cost_dp
A10: R2 | B10: FWOP | C10: ='Site CE-ICA'!I12/10^in_out_dp | D10: ='Site CE-ICA'!J12/10^in_cost_dp
A11: R2 | B11: A1 | C11: ='Site CE-ICA'!I13/10^in_out_dp | D11: ='Site CE-ICA'!J13/10^in_cost_dp
A12: R2 | B12: A2 | C12: ='Site CE-ICA'!I14/10^in_out_dp | D12: ='Site CE-ICA'!J14/10^in_cost_dp
A13: R3 | B13: FWOP | C13: ='Site CE-ICA'!I17/10^in_out_dp | D13: ='Site CE-ICA'!J17/10^in_cost_dp
A14: R3 | B14: A1 | C14: ='Site CE-ICA'!I18/10^in_out_dp | D14: ='Site CE-ICA'!J18/10^in_cost_dp
A15: R3 | B15: A2 | C15: ='Site CE-ICA'!I19/10^in_out_dp | D15: ='Site CE-ICA'!J19/10^in_cost_dp
A17: Watershed planning set (valid plans)
A18: Plan number | B18: Plan | C18: Output | D18: Cost
A19: ='Watershed plans'!G12 | B19: ='Watershed plans'!B12 | C19: =IF('Watershed plans'!C12=1,'Watershed plans'!K12,"") | D19: =IF('Watershed plans'!C12=1,'Watershed plans'!L12,"")
A20: ='Watershed plans'!G13 | B20: ='Watershed plans'!B13 | C20: =IF('Watershed plans'!C13=1,'Watershed plans'!K13,"") | D20: =IF('Watershed plans'!C13=1,'Watershed plans'!L13,"")
A21: ='Watershed plans'!G14 | B21: ='Watershed plans'!B14 | C21: =IF('Watershed plans'!C14=1,'Watershed plans'!K14,"") | D21: =IF('Watershed plans'!C14=1,'Watershed plans'!L14,"")
A22: ='Watershed plans'!G15 | B22: ='Watershed plans'!B15 | C22: =IF('Watershed plans'!C15=1,'Watershed plans'!K15,"") | D22: =IF('Watershed plans'!C15=1,'Watershed plans'!L15,"")
A23: ='Watershed plans'!G16 | B23: ='Watershed plans'!B16 | C23: =IF('Watershed plans'!C16=1,'Watershed plans'!K16,"") | D23: =IF('Watershed plans'!C16=1,'Watershed plans'!L16,"")
A24: ='Watershed plans'!G17 | B24: ='Watershed plans'!B17 | C24: =IF('Watershed plans'!C17=1,'Watershed plans'!K17,"") | D24: =IF('Watershed plans'!C17=1,'Watershed plans'!L17,"")
A25: ='Watershed plans'!G18 | B25: ='Watershed plans'!B18 | C25: =IF('Watershed plans'!C18=1,'Watershed plans'!K18,"") | D25: =IF('Watershed plans'!C18=1,'Watershed plans'!L18,"")
A26: ='Watershed plans'!G19 | B26: ='Watershed plans'!B19 | C26: =IF('Watershed plans'!C19=1,'Watershed plans'!K19,"") | D26: =IF('Watershed plans'!C19=1,'Watershed plans'!L19,"")

Sheet Charts
A1: Charts: watershed cost-effectiveness and incremental cost
A2: Built from the watershed plans sheet; they update with the inputs.
A30: All plans: lift | B30: All plans: cost | C30: Frontier: lift | D30: Frontier: cost | E30: Best buys: lift | F30: Best buys: cost | G30: Steps: output | H30: Steps: incremental cost | K30: (frontier order)
A31: =IF('Watershed plans'!C12=1,'Watershed plans'!K12,NA()) | B31: =IF('Watershed plans'!C12=1,'Watershed plans'!L12,NA()) | C31: =IFERROR(INDEX('Watershed plans'!$K$12:$K$19,MATCH(1,$K$31:$K$38,0)),NA()) | D31: =IFERROR(INDEX('Watershed plans'!$L$12:$L$19,MATCH(1,$K$31:$K$38,0)),NA()) | E31: =IFERROR(INDEX('Watershed plans'!$K$12:$K$19,MATCH(1,'Watershed plans'!$T$12:$T$19,0)),NA()) | F31: =IFERROR(INDEX('Watershed plans'!$L$12:$L$19,MATCH(1,'Watershed plans'!$T$12:$T$19,0)),NA()) | G31: =E31 | H31: =IFERROR(INDEX('Watershed plans'!$Y$12:$Y$19,MATCH(2,'Watershed plans'!$T$12:$T$19,0)),NA()) | K31: =IF('Watershed plans'!O12=1,1+SUMPRODUCT('Watershed plans'!$O$12:$O$19*(('Watershed plans'!$H$12:$H$19<'Watershed plans'!H12)+('Watershed plans'!$H$12:$H$19='Watershed plans'!H12)*('Watershed plans'!$A$12:$A$19<'Watershed plans'!A12))),0)
A32: =IF('Watershed plans'!C13=1,'Watershed plans'!K13,NA()) | B32: =IF('Watershed plans'!C13=1,'Watershed plans'!L13,NA()) | C32: =IFERROR(INDEX('Watershed plans'!$K$12:$K$19,MATCH(2,$K$31:$K$38,0)),NA()) | D32: =IFERROR(INDEX('Watershed plans'!$L$12:$L$19,MATCH(2,$K$31:$K$38,0)),NA()) | E32: =IFERROR(INDEX('Watershed plans'!$K$12:$K$19,MATCH(2,'Watershed plans'!$T$12:$T$19,0)),NA()) | F32: =IFERROR(INDEX('Watershed plans'!$L$12:$L$19,MATCH(2,'Watershed plans'!$T$12:$T$19,0)),NA()) | G32: =E32 | H32: =IFERROR(INDEX('Watershed plans'!$Y$12:$Y$19,MATCH(2,'Watershed plans'!$T$12:$T$19,0)),NA()) | K32: =IF('Watershed plans'!O13=1,1+SUMPRODUCT('Watershed plans'!$O$12:$O$19*(('Watershed plans'!$H$12:$H$19<'Watershed plans'!H13)+('Watershed plans'!$H$12:$H$19='Watershed plans'!H13)*('Watershed plans'!$A$12:$A$19<'Watershed plans'!A13))),0)
A33: =IF('Watershed plans'!C14=1,'Watershed plans'!K14,NA()) | B33: =IF('Watershed plans'!C14=1,'Watershed plans'!L14,NA()) | C33: =IFERROR(INDEX('Watershed plans'!$K$12:$K$19,MATCH(3,$K$31:$K$38,0)),NA()) | D33: =IFERROR(INDEX('Watershed plans'!$L$12:$L$19,MATCH(3,$K$31:$K$38,0)),NA()) | E33: =IFERROR(INDEX('Watershed plans'!$K$12:$K$19,MATCH(3,'Watershed plans'!$T$12:$T$19,0)),NA()) | F33: =IFERROR(INDEX('Watershed plans'!$L$12:$L$19,MATCH(3,'Watershed plans'!$T$12:$T$19,0)),NA()) | G33: =NA() | H33: =NA() | K33: =IF('Watershed plans'!O14=1,1+SUMPRODUCT('Watershed plans'!$O$12:$O$19*(('Watershed plans'!$H$12:$H$19<'Watershed plans'!H14)+('Watershed plans'!$H$12:$H$19='Watershed plans'!H14)*('Watershed plans'!$A$12:$A$19<'Watershed plans'!A14))),0)
A34: =IF('Watershed plans'!C15=1,'Watershed plans'!K15,NA()) | B34: =IF('Watershed plans'!C15=1,'Watershed plans'!L15,NA()) | C34: =IFERROR(INDEX('Watershed plans'!$K$12:$K$19,MATCH(4,$K$31:$K$38,0)),NA()) | D34: =IFERROR(INDEX('Watershed plans'!$L$12:$L$19,MATCH(4,$K$31:$K$38,0)),NA()) | E34: =IFERROR(INDEX('Watershed plans'!$K$12:$K$19,MATCH(4,'Watershed plans'!$T$12:$T$19,0)),NA()) | F34: =IFERROR(INDEX('Watershed plans'!$L$12:$L$19,MATCH(4,'Watershed plans'!$T$12:$T$19,0)),NA()) | G34: =E32 | H34: =IFERROR(INDEX('Watershed plans'!$Y$12:$Y$19,MATCH(3,'Watershed plans'!$T$12:$T$19,0)),NA()) | K34: =IF('Watershed plans'!O15=1,1+SUMPRODUCT('Watershed plans'!$O$12:$O$19*(('Watershed plans'!$H$12:$H$19<'Watershed plans'!H15)+('Watershed plans'!$H$12:$H$19='Watershed plans'!H15)*('Watershed plans'!$A$12:$A$19<'Watershed plans'!A15))),0)
A35: =IF('Watershed plans'!C16=1,'Watershed plans'!K16,NA()) | B35: =IF('Watershed plans'!C16=1,'Watershed plans'!L16,NA()) | C35: =IFERROR(INDEX('Watershed plans'!$K$12:$K$19,MATCH(5,$K$31:$K$38,0)),NA()) | D35: =IFERROR(INDEX('Watershed plans'!$L$12:$L$19,MATCH(5,$K$31:$K$38,0)),NA()) | E35: =IFERROR(INDEX('Watershed plans'!$K$12:$K$19,MATCH(5,'Watershed plans'!$T$12:$T$19,0)),NA()) | F35: =IFERROR(INDEX('Watershed plans'!$L$12:$L$19,MATCH(5,'Watershed plans'!$T$12:$T$19,0)),NA()) | G35: =E33 | H35: =IFERROR(INDEX('Watershed plans'!$Y$12:$Y$19,MATCH(3,'Watershed plans'!$T$12:$T$19,0)),NA()) | K35: =IF('Watershed plans'!O16=1,1+SUMPRODUCT('Watershed plans'!$O$12:$O$19*(('Watershed plans'!$H$12:$H$19<'Watershed plans'!H16)+('Watershed plans'!$H$12:$H$19='Watershed plans'!H16)*('Watershed plans'!$A$12:$A$19<'Watershed plans'!A16))),0)
A36: =IF('Watershed plans'!C17=1,'Watershed plans'!K17,NA()) | B36: =IF('Watershed plans'!C17=1,'Watershed plans'!L17,NA()) | C36: =IFERROR(INDEX('Watershed plans'!$K$12:$K$19,MATCH(6,$K$31:$K$38,0)),NA()) | D36: =IFERROR(INDEX('Watershed plans'!$L$12:$L$19,MATCH(6,$K$31:$K$38,0)),NA()) | E36: =IFERROR(INDEX('Watershed plans'!$K$12:$K$19,MATCH(6,'Watershed plans'!$T$12:$T$19,0)),NA()) | F36: =IFERROR(INDEX('Watershed plans'!$L$12:$L$19,MATCH(6,'Watershed plans'!$T$12:$T$19,0)),NA()) | G36: =NA() | H36: =NA() | K36: =IF('Watershed plans'!O17=1,1+SUMPRODUCT('Watershed plans'!$O$12:$O$19*(('Watershed plans'!$H$12:$H$19<'Watershed plans'!H17)+('Watershed plans'!$H$12:$H$19='Watershed plans'!H17)*('Watershed plans'!$A$12:$A$19<'Watershed plans'!A17))),0)
A37: =IF('Watershed plans'!C18=1,'Watershed plans'!K18,NA()) | B37: =IF('Watershed plans'!C18=1,'Watershed plans'!L18,NA()) | C37: =IFERROR(INDEX('Watershed plans'!$K$12:$K$19,MATCH(7,$K$31:$K$38,0)),NA()) | D37: =IFERROR(INDEX('Watershed plans'!$L$12:$L$19,MATCH(7,$K$31:$K$38,0)),NA()) | E37: =IFERROR(INDEX('Watershed plans'!$K$12:$K$19,MATCH(7,'Watershed plans'!$T$12:$T$19,0)),NA()) | F37: =IFERROR(INDEX('Watershed plans'!$L$12:$L$19,MATCH(7,'Watershed plans'!$T$12:$T$19,0)),NA()) | G37: =E33 | H37: =IFERROR(INDEX('Watershed plans'!$Y$12:$Y$19,MATCH(4,'Watershed plans'!$T$12:$T$19,0)),NA()) | K37: =IF('Watershed plans'!O18=1,1+SUMPRODUCT('Watershed plans'!$O$12:$O$19*(('Watershed plans'!$H$12:$H$19<'Watershed plans'!H18)+('Watershed plans'!$H$12:$H$19='Watershed plans'!H18)*('Watershed plans'!$A$12:$A$19<'Watershed plans'!A18))),0)
A38: =IF('Watershed plans'!C19=1,'Watershed plans'!K19,NA()) | B38: =IF('Watershed plans'!C19=1,'Watershed plans'!L19,NA()) | C38: =IFERROR(INDEX('Watershed plans'!$K$12:$K$19,MATCH(8,$K$31:$K$38,0)),NA()) | D38: =IFERROR(INDEX('Watershed plans'!$L$12:$L$19,MATCH(8,$K$31:$K$38,0)),NA()) | E38: =IFERROR(INDEX('Watershed plans'!$K$12:$K$19,MATCH(8,'Watershed plans'!$T$12:$T$19,0)),NA()) | F38: =IFERROR(INDEX('Watershed plans'!$L$12:$L$19,MATCH(8,'Watershed plans'!$T$12:$T$19,0)),NA()) | G38: =E34 | H38: =IFERROR(INDEX('Watershed plans'!$Y$12:$Y$19,MATCH(4,'Watershed plans'!$T$12:$T$19,0)),NA()) | K38: =IF('Watershed plans'!O19=1,1+SUMPRODUCT('Watershed plans'!$O$12:$O$19*(('Watershed plans'!$H$12:$H$19<'Watershed plans'!H19)+('Watershed plans'!$H$12:$H$19='Watershed plans'!H19)*('Watershed plans'!$A$12:$A$19<'Watershed plans'!A19))),0)
G39: =NA() | H39: =NA()
G40: =E34 | H40: =IFERROR(INDEX('Watershed plans'!$Y$12:$Y$19,MATCH(5,'Watershed plans'!$T$12:$T$19,0)),NA())
G41: =E35 | H41: =IFERROR(INDEX('Watershed plans'!$Y$12:$Y$19,MATCH(5,'Watershed plans'!$T$12:$T$19,0)),NA())
G42: =NA() | H42: =NA()
G43: =E35 | H43: =IFERROR(INDEX('Watershed plans'!$Y$12:$Y$19,MATCH(6,'Watershed plans'!$T$12:$T$19,0)),NA())
G44: =E36 | H44: =IFERROR(INDEX('Watershed plans'!$Y$12:$Y$19,MATCH(6,'Watershed plans'!$T$12:$T$19,0)),NA())
G45: =NA() | H45: =NA()
G46: =E36 | H46: =IFERROR(INDEX('Watershed plans'!$Y$12:$Y$19,MATCH(7,'Watershed plans'!$T$12:$T$19,0)),NA())
G47: =E37 | H47: =IFERROR(INDEX('Watershed plans'!$Y$12:$Y$19,MATCH(7,'Watershed plans'!$T$12:$T$19,0)),NA())
G48: =NA() | H48: =NA()
G49: =E37 | H49: =IFERROR(INDEX('Watershed plans'!$Y$12:$Y$19,MATCH(8,'Watershed plans'!$T$12:$T$19,0)),NA())
G50: =E38 | H50: =IFERROR(INDEX('Watershed plans'!$Y$12:$Y$19,MATCH(8,'Watershed plans'!$T$12:$T$19,0)),NA())
G51: =NA() | H51: =NA()

Sheet snap Parameters
B4: 0.03
B5: 50
B6: 12
B7: END
B8: END_OF_YEAR
B9: 2
B10: 3
B14: 0 | C14: 1 | D14: 5 | E14: 10 | F14: 25 | G14: 50

Sheet snap STAF scores
F10: 1 | G10: 1 | H10: 1 | I10: 1 | J10: 1 | K10: 1 | L10: 1 | M10: 1 | N10: 1 | O10: 1 | P10: 1 | Q10: 1 | R10: 1 | S10: 1 | T10: 1 | U10: 1 | V10: 1 | W10: 1 | X10: 1 | Y10: 1
F11: 1 | G11: 1 | H11: 1 | I11: 1 | J11: 1 | K11: 1 | L11: 1 | M11: 1 | N11: 1 | O11: 1 | P11: 1 | Q11: 1 | R11: 1 | S11: 1 | T11: 1 | U11: 1 | V11: 1 | W11: 1 | X11: 1 | Y11: 1
F12: 1 | G12: 1 | H12: 1 | I12: 1 | J12: 1 | K12: 1 | L12: 1 | M12: 1 | N12: 1 | O12: 1 | P12: 1 | Q12: 1 | R12: 1 | S12: 1 | T12: 1 | U12: 1 | V12: 1 | W12: 1 | X12: 1 | Y12: 0
E15: 1000 | F15: 8 | G15: 15 | H15: 7 | I15: 12 | J15: 4 | K15: 11 | L15: 9 | M15: 13 | N15: 5 | O15: 10 | P15: 6 | Q15: 5 | R15: 12 | S15: 13 | T15: 13 | U15: 10 | V15: 2 | W15: 3 | X15: 4 | Y15: 1
E16: 1000 | F16: 8 | G16: 15 | H16: 7 | I16: 12 | J16: 4 | K16: 11 | L16: 9 | M16: 13 | N16: 5 | O16: 10 | P16: 6 | Q16: 5 | R16: 12 | S16: 13 | T16: 13 | U16: 10 | V16: 2 | W16: 3 | X16: 4 | Y16: 1
E17: 1000 | F17: 8 | G17: 15 | H17: 7 | I17: 12 | J17: 4 | K17: 11 | L17: 9 | M17: 13 | N17: 4.9 | O17: 10 | P17: 6 | Q17: 4.9 | R17: 12 | S17: 13 | T17: 13 | U17: 10 | V17: 2 | W17: 2.9 | X17: 3.9 | Y17: 1
E18: 1000 | F18: 8 | G18: 15 | H18: 7 | I18: 12 | J18: 4 | K18: 11 | L18: 9 | M18: 13 | N18: 4.8 | O18: 10 | P18: 6 | Q18: 4.8 | R18: 12 | S18: 13 | T18: 13 | U18: 10 | V18: 2 | W18: 2.8 | X18: 3.8 | Y18: 1
E19: 1000 | F19: 8 | G19: 15 | H19: 7 | I19: 12 | J19: 4 | K19: 11 | L19: 9 | M19: 13 | N19: 4.5 | O19: 10 | P19: 6 | Q19: 4.5 | R19: 12 | S19: 13 | T19: 13 | U19: 10 | V19: 2 | W19: 2.5 | X19: 3.5 | Y19: 1
E20: 1000 | F20: 8 | G20: 15 | H20: 7 | I20: 12 | J20: 4 | K20: 11 | L20: 9 | M20: 13 | N20: 4 | O20: 10 | P20: 6 | Q20: 4 | R20: 12 | S20: 13 | T20: 13 | U20: 10 | V20: 2 | W20: 2 | X20: 3 | Y20: 1
E21: 1000 | F21: 8 | G21: 15 | H21: 7 | I21: 12 | J21: 4 | K21: 11 | L21: 9 | M21: 13 | N21: 5 | O21: 10 | P21: 6 | Q21: 5 | R21: 12 | S21: 13 | T21: 13 | U21: 10 | V21: 2 | W21: 3 | X21: 4 | Y21: 1
E22: 1000 | F22: 8 | G22: 15 | H22: 7 | I22: 12 | J22: 4 | K22: 11 | L22: 9 | M22: 13 | N22: 5 | O22: 10 | P22: 6 | Q22: 5 | R22: 12.2 | S22: 13.1 | T22: 13.1 | U22: 10.2 | V22: 2 | W22: 3 | X22: 4 | Y22: 1
E23: 1000 | F23: 8 | G23: 15 | H23: 7 | I23: 12 | J23: 4 | K23: 11 | L23: 9 | M23: 13 | N23: 4.9 | O23: 10 | P23: 6 | Q23: 4.9 | R23: 13 | S23: 13.5 | T23: 13.5 | U23: 11 | V23: 2.8 | W23: 3.4 | X23: 4.4 | Y23: 1
E24: 1000 | F24: 8 | G24: 15 | H24: 7 | I24: 12 | J24: 4 | K24: 11 | L24: 9 | M24: 13 | N24: 4.8 | O24: 10 | P24: 6 | Q24: 4.8 | R24: 13.6 | S24: 13.8 | T24: 13.8 | U24: 11.6 | V24: 3.4 | W24: 3.7 | X24: 4.7 | Y24: 1
E25: 1000 | F25: 8 | G25: 15 | H25: 7 | I25: 12 | J25: 4 | K25: 11 | L25: 9 | M25: 13 | N25: 4.5 | O25: 10 | P25: 6 | Q25: 4.5 | R25: 14 | S25: 14 | T25: 14 | U25: 12 | V25: 4 | W25: 4 | X25: 5 | Y25: 1
E26: 1000 | F26: 8 | G26: 15 | H26: 7 | I26: 12 | J26: 4 | K26: 11 | L26: 9 | M26: 13 | N26: 4 | O26: 10 | P26: 6 | Q26: 4 | R26: 14 | S26: 14 | T26: 14 | U26: 12 | V26: 4 | W26: 4 | X26: 5 | Y26: 1
... E56: 2400 | F56: 3 | G56: 4 | H56: 3 | I56: 4 | J56: 6 | K56: 8 | L56: 10 | M56: 9 | N56: 8 | O56: 10 | P56: 8 | Q56: 9 | R56: 11 | S56: 10 | T56: 10 | U56: 8 | V56: 9 | W56: 6 | X56: 6 | Y56: 5
E57: 1600 | F57: 11 | G57: 12 | H57: 10 | I57: 11 | J57: 9 | K57: 10 | L57: 10 | M57: 11 | N57: 9 | O57: 8 | P57: 8 | Q57: 7 | R57: 10 | S57: 11 | T57: 10 | U57: 9 | V57: 6 | W57: 5 | X57: 6
E58: 1600 | F58: 11 | G58: 12 | H58: 10 | I58: 11 | J58: 9 | K58: 10 | L58: 10 | M58: 11 | N58: 9 | O58: 8 | P58: 8 | Q58: 7 | R58: 10 | S58: 11 | T58: 10 | U58: 9 | V58: 6 | W58: 5 | X58: 6
E59: 1600 | F59: 11 | G59: 12 | H59: 10 | I59: 11 | J59: 9 | K59: 10 | L59: 10 | M59: 11 | N59: 9 | O59: 8 | P59: 8 | Q59: 7 | R59: 10 | S59: 11 | T59: 10 | U59: 8.9 | V59: 5.9 | W59: 5 | X59: 6
E60: 1600 | F60: 11 | G60: 12 | H60: 10 | I60: 11 | J60: 9 | K60: 10 | L60: 10 | M60: 11 | N60: 9 | O60: 8 | P60: 8 | Q60: 7 | R60: 10 | S60: 11 | T60: 10 | U60: 8.8 | V60: 5.8 | W60: 5 | X60: 6
E61: 1600 | F61: 11 | G61: 12 | H61: 10 | I61: 11 | J61: 9 | K61: 10 | L61: 10 | M61: 11 | N61: 9 | O61: 8 | P61: 8 | Q61: 7 | R61: 10 | S61: 11 | T61: 10 | U61: 8.5 | V61: 5.5 | W61: 5 | X61: 6
E62: 1600 | F62: 11 | G62: 12 | H62: 10 | I62: 11 | J62: 9 | K62: 10 | L62: 10 | M62: 11 | N62: 9 | O62: 8 | P62: 8 | Q62: 7 | R62: 10 | S62: 11 | T62: 10 | U62: 8 | V62: 5 | W62: 5 | X62: 6
E63: 1600 | F63: 11 | G63: 12 | H63: 10 | I63: 11 | J63: 9 | K63: 10 | L63: 10 | M63: 11 | N63: 9 | O63: 8 | P63: 8 | Q63: 7 | R63: 10 | S63: 11 | T63: 10 | U63: 9 | V63: 6 | W63: 5 | X63: 6
E64: 1600 | F64: 11 | G64: 12 | H64: 10 | I64: 11 | J64: 9 | K64: 10 | L64: 10 | M64: 11 | N64: 9 | O64: 9.6 | P64: 9.6 | Q64: 7 | R64: 10.3 | S64: 11.1 | T64: 10.2 | U64: 9.3 | V64: 6 | W64: 5 | X64: 6
E65: 1600 | F65: 11 | G65: 12 | H65: 10 | I65: 11 | J65: 9 | K65: 10 | L65: 10 | M65: 11 | N65: 9 | O65: 10 | P65: 10 | Q65: 7 | R65: 11.5 | S65: 11.5 | T65: 11 | U65: 10.5 | V65: 7.2 | W65: 5.8 | X65: 6.8
E66: 1600 | F66: 11 | G66: 12 | H66: 10 | I66: 11 | J66: 9 | K66: 10 | L66: 10 | M66: 11 | N66: 9 | O66: 10 | P66: 10 | Q66: 7 | R66: 12.4 | S66: 11.8 | T66: 11.6 | U66: 11.4 | V66: 8.1 | W66: 6.4 | X66: 7.4
E67: 1600 | F67: 11 | G67: 12 | H67: 10 | I67: 11 | J67: 9 | K67: 10 | L67: 10 | M67: 11 | N67: 9 | O67: 10 | P67: 10 | Q67: 7 | R67: 13 | S67: 12 | T67: 12 | U67: 12 | V67: 9 | W67: 7 | X67: 8
E68: 1600 | F68: 11 | G68: 12 | H68: 10 | I68: 11 | J68: 9 | K68: 10 | L68: 10 | M68: 11 | N68: 9 | O68: 10 | P68: 10 | Q68: 7 | R68: 13 | S68: 12 | T68: 12 | U68: 12 | V68: 9 | W68: 7 | X68: 8
... E74: 1600 | F74: 11 | G74: 12 | H74: 10 | I74: 11 | J74: 9 | K74: 10 | L74: 10 | M74: 11 | N74: 9 | O74: 10 | P74: 12 | Q74: 10 | R74: 13 | S74: 12 | T74: 12 | U74: 12 | V74: 9 | W74: 9 | X74: 9

Sheet snap Costs
G6: 0
D7: 180000 | E7: 25000 | F7: 15000 | G7: 4
D8: 620000 | E8: 40000 | F8: 60000 | G8: 8
D9: 910000 | E9: 50000 | F9: 90000 | G9: 10
G10: 0
D11: 850000 | E11: 45000 | F11: 85000 | G11: 9
D12: 3400000 | E12: 90000 | F12: 340000 | G12: 18
G13: 0
D14: 140000 | E14: 20000 | F14: 10000 | G14: 3
D15: 520000 | E15: 30000 | F15: 40000 | G15: 6

Sheet snap OMRRR
F5: 2500 | K5: 1
G6: 0.1 | H6: construction | K6: 10
F7: 5000 | K7: 1
G8: 0.1 | H8: construction | K8: 25
F9: 6000 | K9: 1
G10: 0.1 | H10: construction | K10: 25
I11: 1.5 | J11: 1000 | K11: 5
F12: 6000 | K12: 1
G13: 0.1 | H13: construction | K13: 25
F14: 12000 | K14: 1
G15: 0.05 | H15: construction | K15: 10
F16: 1500 | K16: 1
I17: 2 | J17: 3200 | K17: 10
F18: 3000 | K18: 1
F19: 2000 | K19: 5

Sheet snap Sites
C5: A3
C6: A2
C7: A2

Sheet snap Watershed plans
O12: 1 | S12: 1 | AA12: 1
O13: 1 | S13: 1 | AA13: 1
O14: 1 | S14: 0 | AA14: 0
O15: 1 | S15: 1 | AA15: 1
O16: 0 | S16: 0 | AA16: 0
O17: 1 | S17: 0 | AA17: 0
O18: 0 | S18: 0 | AA18: 0
O19: 1 | S19: 1 | AA19: 1

Sheet snap Watershed summary

Sheet snap Summary
G5: 0 | L5: 0
G6: 42.373928 | L6: 12646.481
G7: 92.656004 | L7: 34892.714
G8: 139.12699 | L8: 49982.347
G9: 0 | L9: 0
G10: 190.78824 | L10: 46747.335
G11: 597.02536 | L11: 178490.95
G12: 0 | L12: 0
G13: 130.51574 | L13: 8678.8397
G14: 173.07546 | L14: 26432.37

Sheet snap Site CE-ICA
L6: 1 | P6: 1
L7: 1 | P7: 1
L8: 1 | P8: 0
L9: 1 | P9: 1
L12: 1 | P12: 1
L13: 1 | P13: 1
L14: 1 | P14: 1
L17: 1 | P17: 1
L18: 1 | P18: 1
L19: 1 | P19: 1

Sheet manifest
A1: ceica-calculator | B1: 1
