Workbook
Name in_rate: Parameters!$B$4
Name in_poa: Parameters!$B$5
Name in_ppy: Parameters!$B$6
Name in_idc_method: Parameters!$B$7
Name in_timing: Parameters!$B$8
Name in_cost_dp: Parameters!$B$9
Name in_out_dp: Parameters!$B$10
Name calc_crf: Parameters!$B$11
Name out_status: 'Read me'!$B$10
Name out_changed: 'Read me'!$B$11
Name out_mismatch: 'Read me'!$B$12

Sheet Read me
A1: Utoy Creek Section 206: CE/ICA calculator
A2: Cost-effectiveness and incremental cost analysis, as live formulas.
A4: Study | B4: Utoy Creek Section 206
A5: Generated by | B5: CEICA 1.0.0 (engine 1)
A6: Project digest | B6: 082a32b302c7
A7: Discount rate | B7: 3 percent
A8: Period of analysis | B8: 50 years
A10: Status | B10: =IF(B11=0,IF(B12=0,"Unchanged: matches the CEICA export","ERROR: results differ from the export although no input changed"),"Edited: "&B11&" input cells changed since the export")
A11: Inputs changed | B11: =(SUMPRODUCT(1*(Parameters!B4:B10<>'snap Parameters'!B4:B10))+SUMPRODUCT(1*(Parameters!B14:E14<>'snap Parameters'!B14:E14))+SUMPRODUCT(1*(Benefits!F6:M36<>'snap Benefits'!F6:M36))+SUMPRODUCT(1*(Benefits!F37:M67<>'snap Benefits'!F37:M67))+SUMPRODUCT(1*(Benefits!F68:M98<>'snap Benefits'!F68:M98))+SUMPRODUCT(1*(Costs!D6:G36<>'snap Costs'!D6:G36))+SUMPRODUCT(1*(Costs!L6:L36<>'snap Costs'!L6:L36))+SUMPRODUCT(1*(OMRRR!F5:M96<>'snap OMRRR'!F5:M96))+SUMPRODUCT(1*(Sites!C5:C12<>'snap Sites'!C5:C12))+SUMPRODUCT(1*('Watershed plans'!AF12:AF267<>'snap Watershed plans'!AF12:AF267))+SUMPRODUCT(1*('Watershed summary'!K50:L89<>'snap Watershed summary'!K50:L89))+SUMPRODUCT(1*('Watershed summary'!B93:B93<>'snap Watershed summary'!B93:B93)))
A12: Results that differ from the export | B12: =(SUMPRODUCT(1*(ABS(Summary!G5:G35-'snap Summary'!G5:G35)>1e-06))+SUMPRODUCT(1*(ABS(Summary!L5:L35-'snap Summary'!L5:L35)>0.0001))+SUMPRODUCT(1*('Site CE-ICA'!L6:L9<>'snap Site CE-ICA'!L6:L9))+SUMPRODUCT(1*('Site CE-ICA'!P6:P9<>'snap Site CE-ICA'!P6:P9))+SUMPRODUCT(1*('Site CE-ICA'!L12:L15<>'snap Site CE-ICA'!L12:L15))+SUMPRODUCT(1*('Site CE-ICA'!P12:P15<>'snap Site CE-ICA'!P12:P15))+SUMPRODUCT(1*('Site CE-ICA'!L18:L21<>'snap Site CE-ICA'!L18:L21))+SUMPRODUCT(1*('Site CE-ICA'!P18:P21<>'snap Site CE-ICA'!P18:P21))+SUMPRODUCT(1*('Site CE-ICA'!L24:L27<>'snap Site CE-ICA'!L24:L27))+SUMPRODUCT(1*('Site CE-ICA'!P24:P27<>'snap Site CE-ICA'!P24:P27))+SUMPRODUCT(1*('Site CE-ICA'!L30:L33<>'snap Site CE-ICA'!L30:L33))+SUMPRODUCT(1*('Site CE-ICA'!P30:P33<>'snap Site CE-ICA'!P30:P33))+SUMPRODUCT(1*('Site CE-ICA'!L36:L39<>'snap Site CE-ICA'!L36:L39))+SUMPRODUCT(1*('Site CE-ICA'!P36:P39<>'snap Site CE-ICA'!P36:P39))+SUMPRODUCT(1*('Site CE-ICA'!L42:L45<>'snap Site CE-ICA'!L42:L45))+SUMPRODUCT(1*('Site CE-ICA'!P42:P45<>'snap Site CE-ICA'!P42:P45))+SUMPRODUCT(1*('Site CE-ICA'!L48:L50<>'snap Site CE-ICA'!L48:L50))+SUMPRODUCT(1*('Site CE-ICA'!P48:P50<>'snap Site CE-ICA'!P48:P50))+SUMPRODUCT(1*('Watershed plans'!T12:T267<>'snap Watershed plans'!T12:T267))+SUMPRODUCT(1*('Watershed plans'!X12:X267<>'snap Watershed plans'!X12:X267)))
A14: How to use
A15: - Orange cells are inputs; grey cells are formulas. Sheets are protected (password 'ceica') only to prevent accidental edits.
A16: - Change any orange cell: annualization, site CE/ICA, the watershed plans and the summary update. Changed inputs turn yellow.
A17: - To add sites, alternatives or years, make the change in CEICA and export again.
A18: - Import this workbook in CEICA to bring your changes back into the project.
A20: Legend
A21: Input
A22: Formula
A23: Changed since export

Sheet Parameters
A1: Parameters
A2: Economics and conventions. Orange cells are inputs.
A3: Parameter | B3: Value
A4: Discount rate | B4: 0.03
A5: Period of analysis (years) | B5: 50
A6: Interest during construction: periods per year | B6: 12
A7: Interest during construction: spending in each period (END, MIDDLE or START) | B7: END
A8: OMRRR discounting (END_OF_YEAR or MID_YEAR) | B8: END_OF_YEAR
A9: Cost decimals kept for CE/ICA | B9: 4
A10: Output decimals kept for CE/ICA | B10: 6
A11: Capital recovery factor | B11: =IF(in_rate=0,1/in_poa,in_rate*(1+in_rate)^in_poa/((1+in_rate)^in_poa-1))
A13: Target years | B13: Year 1 | C13: Year 2 | D13: Year 3 | E13: Year 4
A14: Years (first to last) | B14: 0 | C14: 2 | D14: 10 | E14: 50

Sheet Benefits
A1: Benefits: habitat units by module
A2: One row per module, site and alternative; the Summary adds the modules' averages. Riparian, left bank: index x quantity at each target year; Riparian, right bank: index x quantity at each target year; Instream: index x quantity at each target year. Averages are the area under straight lines between target years.
A4: Key | B4: Site | C4: Alternative | D4: Module | E4: Method | F4: Index (0 to 1) | J4: Quantity | N4: Habitat units (HU) | R4: Average (AAHU)
F5: =Parameters!$B$14 | G5: =Parameters!$C$14 | H5: =Parameters!$D$14 | I5: =Parameters!$E$14 | J5: =Parameters!$B$14 | K5: =Parameters!$C$14 | L5: =Parameters!$D$14 | M5: =Parameters!$E$14 | N5: =Parameters!$B$14 | O5: =Parameters!$C$14 | P5: =Parameters!$D$14 | Q5: =Parameters!$E$14
A6: =B6&"|"&C6 | B6: 17F2M | C6: FWOP | D6: Riparian, left bank | E6: Index x quantity | F6: 0.071111111 | G6: 0.071111111 | H6: 0.071111111 | I6: 0.071111111 | J6: 0 | K6: 0 | L6: 0 | M6: 0 | N6: =F6*J6 | O6: =G6*K6 | P6: =H6*L6 | Q6: =I6*M6 | R6: =SUMPRODUCT($O$5:$Q$5-$N$5:$P$5,(O6:Q6+N6:P6)/2)/($Q$5-$N$5)
A7: =B7&"|"&C7 | B7: 17F2M | C7: Alternative1 | D7: Riparian, left bank | E7: Index x quantity | F7: 0.071111111 | G7: 0.73333333 | H7: 0.79555556 | I7: 0.83555556 | J7: 0 | K7: 1.0806933 | L7: 1.0806933 | M7: 1.0806933 | N7: =F7*J7 | O7: =G7*K7 | P7: =H7*L7 | Q7: =I7*M7 | R7: =SUMPRODUCT($O$5:$Q$5-$N$5:$P$5,(O7:Q7+N7:P7)/2)/($Q$5-$N$5)
A8: =B8&"|"&C8 | B8: 17F2M | C8: Alternative2 | D8: Riparian, left bank | E8: Index x quantity | F8: 0.071111111 | G8: 0.66666667 | H8: 0.77777778 | I8: 0.77777778 | J8: 0 | K8: 0.38904959 | L8: 0.38904959 | M8: 0.38904959 | N8: =F8*J8 | O8: =G8*K8 | P8: =H8*L8 | Q8: =I8*M8 | R8: =SUMPRODUCT($O$5:$Q$5-$N$5:$P$5,(O8:Q8+N8:P8)/2)/($Q$5-$N$5)
A9: =B9&"|"&C9 | B9: 17F2M | C9: Alternative3 | D9: Riparian, left bank | E9: Index x quantity | F9: 0.071111111 | G9: 0.73333333 | H9: 0.79555556 | I9: 0.83555556 | J9: 0 | K9: 2.6723141 | L9: 2.6723141 | M9: 2.6723141 | N9: =F9*J9 | O9: =G9*K9 | P9: =H9*L9 | Q9: =I9*M9 | R9: =SUMPRODUCT($O$5:$Q$5-$N$5:$P$5,(O9:Q9+N9:P9)/2)/($Q$5-$N$5)
A10: =B10&"|"&C10 | B10: 17D2E | C10: FWOP | D10: Riparian, left bank | E10: Index x quantity | F10: 0.30222222 | G10: 0.30222222 | H10: 0.30222222 | I10: 0.30222222 | J10: 6.6331462 | K10: 6.6331462 | L10: 6.6331462 | M10: 6.6331462 | N10: =F10*J10 | O10: =G10*K10 | P10: =H10*L10 | Q10: =I10*M10 | R10: =SUMPRODUCT($O$5:$Q$5-$N$5:$P$5,(O10:Q10+N10:P10)/2)/($Q$5-$N$5)
A11: =B11&"|"&C11 | B11: 17D2E | C11: Alternative1 | D11: Riparian, left bank | E11: Index x quantity | F11: 0.30222222 | G11: 0.80888889 | H11: 0.90666667 | I11: 0.88 | J11: 6.6331462 | K11: 10.871323 | L11: 10.871323 | M11: 10.871323 | N11: =F11*J11 | O11: =G11*K11 | P11: =H11*L11 | Q11: =I11*M11 | R11: =SUMPRODUCT($O$5:$Q$5-$N$5:$P$5,(O11:Q11+N11:P11)/2)/($Q$5-$N$5)
A12: =B12&"|"&C12 | B12: 17D2E | C12: Alternative2 | D12: Riparian, left bank | E12: Index x quantity | F12: 0.30222222 | G12: 0.73777778 | H12: 0.80888889 | I12: 0.83111111 | J12: 6.6331462 | K12: 8.2401251 | L12: 8.2401251 | M12: 8.2401251 | N12: =F12*J12 | O12: =G12*K12 | P12: =H12*L12 | Q12: =I12*M12 | R12: =SUMPRODUCT($O$5:$Q$5-$N$5:$P$5,(O12:Q12+N12:P12)/2)/($Q$5-$N$5)
A13: =B13&"|"&C13 | B13: 17D2E | C13: Alternative3 | D13: Riparian, left bank | E13: Index x quantity | F13: 0.30222222 | G13: 0.61111111 | H13: 0.69111111 | I13: 0.69555556 | J13: 6.6331462 | K13: 6.6331462 | L13: 6.6331462 | M13: 6.6331462 | N13: =F13*J13 | O13: =G13*K13 | P13: =H13*L13 | Q13: =I13*M13 | R13: =SUMPRODUCT($O$5:$Q$5-$N$5:$P$5,(O13:Q13+N13:P13)/2)/($Q$5-$N$5)
A14: =B14&"|"&C14 | B14: 17B | C14: FWOP | D14: Riparian, left bank | E14: Index x quantity | F14: 0.72 | G14: 0.72 | H14: 0.72 | I14: 0.72 | J14: 74.757139 | K14: 74.757139 | L14: 74.757139 | M14: 74.757139 | N14: =F14*J14 | O14: =G14*K14 | P14: =H14*L14 | Q14: =I14*M14 | R14: =SUMPRODUCT($O$5:$Q$5-$N$5:$P$5,(O14:Q14+N14:P14)/2)/($Q$5-$N$5)
A15: =B15&"|"&C15 | B15: 17B | C15: Alternative1 | D15: Riparian, left bank | E15: Index x quantity | F15: 0.72 | G15: 0.80222222 | H15: 0.80666667 | I15: 0.80666667 | J15: 74.757139 | K15: 74.961879 | L15: 74.961879 | M15: 74.961879 | N15: =F15*J15 | O15: =G15*K15 | P15: =H15*L15 | Q15: =I15*M15 | R15: =SUMPRODUCT($O$5:$Q$5-$N$5:$P$5,(O15:Q15+N15:P15)/2)/($Q$5-$N$5)
A16: =B16&"|"&C16 | B16: 17B | C16: Alternative2 | D16: Riparian, left bank | E16: Index x quantity | F16: 0.72 | G16: 0.80222222 | H16: 0.82666667 | I16: 0.82666667 | J16: 74.757139 | K16: 74.961879 | L16: 74.961879 | M16: 74.961879 | N16: =F16*J16 | O16: =G16*K16 | P16: =H16*L16 | Q16: =I16*M16 | R16: =SUMPRODUCT($O$5:$Q$5-$N$5:$P$5,(O16:Q16+N16:P16)/2)/($Q$5-$N$5)
A17: =B17&"|"&C17 | B17: 17B | C17: Alternative3 | D17: Riparian, left bank | E17: Index x quantity | F17: 0.72 | G17: 0.72888889 | H17: 0.73333333 | I17: 0.73333333 | J17: 74.757139 | K17: 74.757139 | L17: 74.757139 | M17: 74.757139 | N17: =F17*J17 | O17: =G17*K17 | P17: =H17*L17 | Q17: =I17*M17 | R17: =SUMPRODUCT($O$5:$Q$5-$N$5:$P$5,(O17:Q17+N17:P17)/2)/($Q$5-$N$5)
... A98: =B98&"|"&C98 | B98: 19A | C98: Alternative3 | D98: Instream | E98: Index x quantity | F98: 0.57923284 | G98: 0.70839951 | H98: 0.70839951 | I98: 0.70839951 | J98: 5.6340055 | K98: 12.337803 | L98: 12.337803 | M98: 12.337803 | N98: =F98*J98 | O98: =G98*K98 | P98: =H98*L98 | Q98: =I98*M98 | R98: =SUMPRODUCT($O$5:$Q$5-$N$5:$P$5,(O98:Q98+N98:P98)/2)/($Q$5-$N$5)

Sheet Costs
A1: Costs: first costs, interest during construction and OMRRR
A2: First costs are base-year lump sums. Interest during construction accrues on the categories marked *, spent evenly over the construction months.
N3: Average annual cost by part
A4: Key | B4: Site | C4: Alternative | D4: Construction * | E4: Monitoring | F4: Adaptive management | G4: Construction months | H4: IDC base | I4: Interest during construction | J4: OMRRR present value | K4: Total present value | L4: Average annual cost entered | M4: Average annual cost | N4: Construction | O4: Monitoring | P4: Adaptive management | Q4: Interest during construction | R4: OMRRR
D5: construction | E5: monitoring | F5: adaptive_management
A6: =B6&"|"&C6 | B6: 17F2M | C6: FWOP | D6: 0 | E6: 0 | F6: 0 | G6: 0 | H6: =D6 | I6: =IF(OR(G6=0,in_rate=0,H6=0),0,H6/G6*(IF(in_idc_method="START",1+((1+in_rate)^(1/in_ppy)-1),IF(in_idc_method="MIDDLE",1+((1+in_rate)^(1/in_ppy)-1)/2,1))*((1+in_rate)^(G6/in_ppy)-1)/((1+in_rate)^(1/in_ppy)-1)-G6)) | J6: =SUMIFS(OMRRR!$S$5:$S$96,OMRRR!$A$5:$A$96,A6) | K6: =SUM(D6:F6)+I6+J6 | M6: =IF(ISNUMBER(L6),L6,calc_crf*K6) | N6: =calc_crf*D6 | O6: =calc_crf*E6 | P6: =calc_crf*F6 | Q6: =calc_crf*I6 | R6: =calc_crf*J6
A7: =B7&"|"&C7 | B7: 17F2M | C7: Alternative1 | D7: 776047 | E7: 60000 | F7: 77605 | G7: 10 | H7: =D7 | I7: =IF(OR(G7=0,in_rate=0,H7=0),0,H7/G7*(IF(in_idc_method="START",1+((1+in_rate)^(1/in_ppy)-1),IF(in_idc_method="MIDDLE",1+((1+in_rate)^(1/in_ppy)-1)/2,1))*((1+in_rate)^(G7/in_ppy)-1)/((1+in_rate)^(1/in_ppy)-1)-G7)) | J7: =SUMIFS(OMRRR!$S$5:$S$96,OMRRR!$A$5:$A$96,A7) | K7: =SUM(D7:F7)+I7+J7 | M7: =IF(ISNUMBER(L7),L7,calc_crf*K7) | N7: =calc_crf*D7 | O7: =calc_crf*E7 | P7: =calc_crf*F7 | Q7: =calc_crf*I7 | R7: =calc_crf*J7
A8: =B8&"|"&C8 | B8: 17F2M | C8: Alternative2 | D8: 691092 | E8: 56000 | F8: 69109 | G8: 9 | H8: =D8 | I8: =IF(OR(G8=0,in_rate=0,H8=0),0,H8/G8*(IF(in_idc_method="START",1+((1+in_rate)^(1/in_ppy)-1),IF(in_idc_method="MIDDLE",1+((1+in_rate)^(1/in_ppy)-1)/2,1))*((1+in_rate)^(G8/in_ppy)-1)/((1+in_rate)^(1/in_ppy)-1)-G8)) | J8: =SUMIFS(OMRRR!$S$5:$S$96,OMRRR!$A$5:$A$96,A8) | K8: =SUM(D8:F8)+I8+J8 | M8: =IF(ISNUMBER(L8),L8,calc_crf*K8) | N8: =calc_crf*D8 | O8: =calc_crf*E8 | P8: =calc_crf*F8 | Q8: =calc_crf*I8 | R8: =calc_crf*J8
A9: =B9&"|"&C9 | B9: 17F2M | C9: Alternative3 | D9: 798779 | E9: 48000 | F9: 79878 | G9: 11 | H9: =D9 | I9: =IF(OR(G9=0,in_rate=0,H9=0),0,H9/G9*(IF(in_idc_method="START",1+((1+in_rate)^(1/in_ppy)-1),IF(in_idc_method="MIDDLE",1+((1+in_rate)^(1/in_ppy)-1)/2,1))*((1+in_rate)^(G9/in_ppy)-1)/((1+in_rate)^(1/in_ppy)-1)-G9)) | J9: =SUMIFS(OMRRR!$S$5:$S$96,OMRRR!$A$5:$A$96,A9) | K9: =SUM(D9:F9)+I9+J9 | M9: =IF(ISNUMBER(L9),L9,calc_crf*K9) | N9: =calc_crf*D9 | O9: =calc_crf*E9 | P9: =calc_crf*F9 | Q9: =calc_crf*I9 | R9: =calc_crf*J9
A10: =B10&"|"&C10 | B10: 17D2E | C10: FWOP | D10: 0 | E10: 0 | F10: 0 | G10: 0 | H10: =D10 | I10: =IF(OR(G10=0,in_rate=0,H10=0),0,H10/G10*(IF(in_idc_method="START",1+((1+in_rate)^(1/in_ppy)-1),IF(in_idc_method="MIDDLE",1+((1+in_rate)^(1/in_ppy)-1)/2,1))*((1+in_rate)^(G10/in_ppy)-1)/((1+in_rate)^(1/in_ppy)-1)-G10)) | J10: =SUMIFS(OMRRR!$S$5:$S$96,OMRRR!$A$5:$A$96,A10) | K10: =SUM(D10:F10)+I10+J10 | M10: =IF(ISNUMBER(L10),L10,calc_crf*K10) | N10: =calc_crf*D10 | O10: =calc_crf*E10 | P10: =calc_crf*F10 | Q10: =calc_crf*I10 | R10: =calc_crf*J10
A11: =B11&"|"&C11 | B11: 17D2E | C11: Alternative1 | D11: 1070854 | E11: 48000 | F11: 160628 | G11: 14 | H11: =D11 | I11: =IF(OR(G11=0,in_rate=0,H11=0),0,H11/G11*(IF(in_idc_method="START",1+((1+in_rate)^(1/in_ppy)-1),IF(in_idc_method="MIDDLE",1+((1+in_rate)^(1/in_ppy)-1)/2,1))*((1+in_rate)^(G11/in_ppy)-1)/((1+in_rate)^(1/in_ppy)-1)-G11)) | J11: =SUMIFS(OMRRR!$S$5:$S$96,OMRRR!$A$5:$A$96,A11) | K11: =SUM(D11:F11)+I11+J11 | M11: =IF(ISNUMBER(L11),L11,calc_crf*K11) | N11: =calc_crf*D11 | O11: =calc_crf*E11 | P11: =calc_crf*F11 | Q11: =calc_crf*I11 | R11: =calc_crf*J11
A12: =B12&"|"&C12 | B12: 17D2E | C12: Alternative2 | D12: 1065670 | E12: 48000 | F12: 106567 | G12: 14 | H12: =D12 | I12: =IF(OR(G12=0,in_rate=0,H12=0),0,H12/G12*(IF(in_idc_method="START",1+((1+in_rate)^(1/in_ppy)-1),IF(in_idc_method="MIDDLE",1+((1+in_rate)^(1/in_ppy)-1)/2,1))*((1+in_rate)^(G12/in_ppy)-1)/((1+in_rate)^(1/in_ppy)-1)-G12)) | J12: =SUMIFS(OMRRR!$S$5:$S$96,OMRRR!$A$5:$A$96,A12) | K12: =SUM(D12:F12)+I12+J12 | M12: =IF(ISNUMBER(L12),L12,calc_crf*K12) | N12: =calc_crf*D12 | O12: =calc_crf*E12 | P12: =calc_crf*F12 | Q12: =calc_crf*I12 | R12: =calc_crf*J12
A13: =B13&"|"&C13 | B13: 17D2E | C13: Alternative3 | D13: 276233 | E13: 48000 | F13: 27623 | G13: 2 | H13: =D13 | I13: =IF(OR(G13=0,in_rate=0,H13=0),0,H13/G13*(IF(in_idc_method="START",1+((1+in_rate)^(1/in_ppy)-1),IF(in_idc_method="MIDDLE",1+((1+in_rate)^(1/in_ppy)-1)/2,1))*((1+in_rate)^(G13/in_ppy)-1)/((1+in_rate)^(1/in_ppy)-1)-G13)) | J13: =SUMIFS(OMRRR!$S$5:$S$96,OMRRR!$A$5:$A$96,A13) | K13: =SUM(D13:F13)+I13+J13 | M13: =IF(ISNUMBER(L13),L13,calc_crf*K13) | N13: =calc_crf*D13 | O13: =calc_crf*E13 | P13: =calc_crf*F13 | Q13: =calc_crf*I13 | R13: =calc_crf*J13
A14: =B14&"|"&C14 | B14: 17B | C14: FWOP | D14: 0 | E14: 0 | F14: 0 | G14: 0 | H14: =D14 | I14: =IF(OR(G14=0,in_rate=0,H14=0),0,H14/G14*(IF(in_idc_method="START",1+((1+in_rate)^(1/in_ppy)-1),IF(in_idc_method="MIDDLE",1+((1+in_rate)^(1/in_ppy)-1)/2,1))*((1+in_rate)^(G14/in_ppy)-1)/((1+in_rate)^(1/in_ppy)-1)-G14)) | J14: =SUMIFS(OMRRR!$S$5:$S$96,OMRRR!$A$5:$A$96,A14) | K14: =SUM(D14:F14)+I14+J14 | M14: =IF(ISNUMBER(L14),L14,calc_crf*K14) | N14: =calc_crf*D14 | O14: =calc_crf*E14 | P14: =calc_crf*F14 | Q14: =calc_crf*I14 | R14: =calc_crf*J14
A15: =B15&"|"&C15 | B15: 17B | C15: Alternative1 | D15: 1002697 | E15: 48000 | F15: 150405 | G15: 12 | H15: =D15 | I15: =IF(OR(G15=0,in_rate=0,H15=0),0,H15/G15*(IF(in_idc_method="START",1+((1+in_rate)^(1/in_ppy)-1),IF(in_idc_method="MIDDLE",1+((1+in_rate)^(1/in_ppy)-1)/2,1))*((1+in_rate)^(G15/in_ppy)-1)/((1+in_rate)^(1/in_ppy)-1)-G15)) | J15: =SUMIFS(OMRRR!$S$5:$S$96,OMRRR!$A$5:$A$96,A15) | K15: =SUM(D15:F15)+I15+J15 | M15: =IF(ISNUMBER(L15),L15,calc_crf*K15) | N15: =calc_crf*D15 | O15: =calc_crf*E15 | P15: =calc_crf*F15 | Q15: =calc_crf*I15 | R15: =calc_crf*J15
A16: =B16&"|"&C16 | B16: 17B | C16: Alternative2 | D16: 880983 | E16: 48000 | F16: 132147 | G16: 12 | H16: =D16 | I16: =IF(OR(G16=0,in_rate=0,H16=0),0,H16/G16*(IF(in_idc_method="START",1+((1+in_rate)^(1/in_ppy)-1),IF(in_idc_method="MIDDLE",1+((1+in_rate)^(1/in_ppy)-1)/2,1))*((1+in_rate)^(G16/in_ppy)-1)/((1+in_rate)^(1/in_ppy)-1)-G16)) | J16: =SUMIFS(OMRRR!$S$5:$S$96,OMRRR!$A$5:$A$96,A16) | K16: =SUM(D16:F16)+I16+J16 | M16: =IF(ISNUMBER(L16),L16,calc_crf*K16) | N16: =calc_crf*D16 | O16: =calc_crf*E16 | P16: =calc_crf*F16 | Q16: =calc_crf*I16 | R16: =calc_crf*J16
A17: =B17&"|"&C17 | B17: 17B | C17: Alternative3 | D17: 257611 | E17: 48000 | F17: 38642 | G17: 2 | H17: =D17 | I17: =IF(OR(G17=0,in_rate=0,H17=0),0,H17/G17*(IF(in_idc_method="START",1+((1+in_rate)^(1/in_ppy)-1),IF(in_idc_method="MIDDLE",1+((1+in_rate)^(1/in_ppy)-1)/2,1))*((1+in_rate)^(G17/in_ppy)-1)/((1+in_rate)^(1/in_ppy)-1)-G17)) | J17: =SUMIFS(OMRRR!$S$5:$S$96,OMRRR!$A$5:$A$96,A17) | K17: =SUM(D17:F17)+I17+J17 | M17: =IF(ISNUMBER(L17),L17,calc_crf*K17) | N17: =calc_crf*D17 | O17: =calc_crf*E17 | P17: =calc_crf*F17 | Q17: =calc_crf*I17 | R17: =calc_crf*J17
... A36: =B36&"|"&C36 | B36: 19A | C36: Alternative3 | D36: 228693 | E36: 48000 | F36: 45739 | G36: 3 | H36: =D36 | I36: =IF(OR(G36=0,in_rate=0,H36=0),0,H36/G36*(IF(in_idc_method="START",1+((1+in_rate)^(1/in_ppy)-1),IF(in_idc_method="MIDDLE",1+((1+in_rate)^(1/in_ppy)-1)/2,1))*((1+in_rate)^(G36/in_ppy)-1)/((1+in_rate)^(1/in_ppy)-1)-G36)) | J36: =SUMIFS(OMRRR!$S$5:$S$96,OMRRR!$A$5:$A$96,A36) | K36: =SUM(D36:F36)+I36+J36 | M36: =IF(ISNUMBER(L36),L36,calc_crf*K36) | N36: =calc_crf*D36 | O36: =calc_crf*E36 | P36: =calc_crf*F36 | Q36: =calc_crf*I36 | R36: =calc_crf*J36

Sheet OMRRR
A1: OMRRR: recurring operation, maintenance, repair, replacement and rehabilitation
A2: Each item costs the amount per occurrence every N years from the first year to the last (blank: every N years through the period of analysis). Basis: FIXED amount, PERCENT of a first-cost category, or RATE x quantity.
A4: Key | B4: Site | C4: Alternative | D4: Item | E4: Basis | F4: Amount | G4: Percent | H4: Category | I4: Unit rate | J4: Quantity | K4: Every N years | L4: First year | M4: Last year | N4: Amount per occurrence | O4: First | P4: Last | Q4: Occurrences | R4: Present value, end of year | S4: Present value
A5: =B5&"|"&C5 | B5: 17F2M | C5: Alternative1 | D5: General maintenance | E5: FIXED | F5: 10000 | K5: 1 | N5: =IF(E5="FIXED",F5,IF(E5="PERCENT",G5*IFERROR(INDEX(Costs!$D$6:$F$36,MATCH(A5,Costs!$A$6:$A$36,0),MATCH(H5,Costs!$D$5:$F$5,0)),0),I5*J5)) | O5: =IF(ISNUMBER(L5),L5,K5) | P5: =IF(ISNUMBER(M5),MIN(M5,in_poa),in_poa) | Q5: =IF(P5<O5,0,INT((P5-O5)/K5)+1) | R5: =IF(Q5=0,0,IF(in_rate=0,N5*Q5,N5*(1+in_rate)^(-O5)*(1-(1+in_rate)^(-K5*Q5))/(1-(1+in_rate)^(-K5)))) | S5: =IF(in_timing="MID_YEAR",IF(O5=0,IF(Q5=0,0,N5+(R5-N5)*(1+in_rate)^0.5),R5*(1+in_rate)^0.5),R5)
A6: =B6&"|"&C6 | B6: 17F2M | C6: Alternative1 | D6: Inspection and trash removal | E6: RATE | I6: 4 | J6: 2639.11 | K6: 2 | N6: =IF(E6="FIXED",F6,IF(E6="PERCENT",G6*IFERROR(INDEX(Costs!$D$6:$F$36,MATCH(A6,Costs!$A$6:$A$36,0),MATCH(H6,Costs!$D$5:$F$5,0)),0),I6*J6)) | O6: =IF(ISNUMBER(L6),L6,K6) | P6: =IF(ISNUMBER(M6),MIN(M6,in_poa),in_poa) | Q6: =IF(P6<O6,0,INT((P6-O6)/K6)+1) | R6: =IF(Q6=0,0,IF(in_rate=0,N6*Q6,N6*(1+in_rate)^(-O6)*(1-(1+in_rate)^(-K6*Q6))/(1-(1+in_rate)^(-K6)))) | S6: =IF(in_timing="MID_YEAR",IF(O6=0,IF(Q6=0,0,N6+(R6-N6)*(1+in_rate)^0.5),R6*(1+in_rate)^0.5),R6)
A7: =B7&"|"&C7 | B7: 17F2M | C7: Alternative1 | D7: Invasive species control | E7: FIXED | F7: 15000 | K7: 10 | N7: =IF(E7="FIXED",F7,IF(E7="PERCENT",G7*IFERROR(INDEX(Costs!$D$6:$F$36,MATCH(A7,Costs!$A$6:$A$36,0),MATCH(H7,Costs!$D$5:$F$5,0)),0),I7*J7)) | O7: =IF(ISNUMBER(L7),L7,K7) | P7: =IF(ISNUMBER(M7),MIN(M7,in_poa),in_poa) | Q7: =IF(P7<O7,0,INT((P7-O7)/K7)+1) | R7: =IF(Q7=0,0,IF(in_rate=0,N7*Q7,N7*(1+in_rate)^(-O7)*(1-(1+in_rate)^(-K7*Q7))/(1-(1+in_rate)^(-K7)))) | S7: =IF(in_timing="MID_YEAR",IF(O7=0,IF(Q7=0,0,N7+(R7-N7)*(1+in_rate)^0.5),R7*(1+in_rate)^0.5),R7)
A8: =B8&"|"&C8 | B8: 17F2M | C8: Alternative1 | D8: Wood, rock and earth repair | E8: PERCENT | G8: 0.1 | H8: construction | K8: 25 | N8: =IF(E8="FIXED",F8,IF(E8="PERCENT",G8*IFERROR(INDEX(Costs!$D$6:$F$36,MATCH(A8,Costs!$A$6:$A$36,0),MATCH(H8,Costs!$D$5:$F$5,0)),0),I8*J8)) | O8: =IF(ISNUMBER(L8),L8,K8) | P8: =IF(ISNUMBER(M8),MIN(M8,in_poa),in_poa) | Q8: =IF(P8<O8,0,INT((P8-O8)/K8)+1) | R8: =IF(Q8=0,0,IF(in_rate=0,N8*Q8,N8*(1+in_rate)^(-O8)*(1-(1+in_rate)^(-K8*Q8))/(1-(1+in_rate)^(-K8)))) | S8: =IF(in_timing="MID_YEAR",IF(O8=0,IF(Q8=0,0,N8+(R8-N8)*(1+in_rate)^0.5),R8*(1+in_rate)^0.5),R8)
A9: =B9&"|"&C9 | B9: 17F2M | C9: Alternative2 | D9: General maintenance | E9: FIXED | F9: 10000 | K9: 1 | N9: =IF(E9="FIXED",F9,IF(E9="PERCENT",G9*IFERROR(INDEX(Costs!$D$6:$F$36,MATCH(A9,Costs!$A$6:$A$36,0),MATCH(H9,Costs!$D$5:$F$5,0)),0),I9*J9)) | O9: =IF(ISNUMBER(L9),L9,K9) | P9: =IF(ISNUMBER(M9),MIN(M9,in_poa),in_poa) | Q9: =IF(P9<O9,0,INT((P9-O9)/K9)+1) | R9: =IF(Q9=0,0,IF(in_rate=0,N9*Q9,N9*(1+in_rate)^(-O9)*(1-(1+in_rate)^(-K9*Q9))/(1-(1+in_rate)^(-K9)))) | S9: =IF(in_timing="MID_YEAR",IF(O9=0,IF(Q9=0,0,N9+(R9-N9)*(1+in_rate)^0.5),R9*(1+in_rate)^0.5),R9)
A10: =B10&"|"&C10 | B10: 17F2M | C10: Alternative2 | D10: Inspection and trash removal | E10: RATE | I10: 4 | J10: 2378.1542 | K10: 2 | N10: =IF(E10="FIXED",F10,IF(E10="PERCENT",G10*IFERROR(INDEX(Costs!$D$6:$F$36,MATCH(A10,Costs!$A$6:$A$36,0),MATCH(H10,Costs!$D$5:$F$5,0)),0),I10*J10)) | O10: =IF(ISNUMBER(L10),L10,K10) | P10: =IF(ISNUMBER(M10),MIN(M10,in_poa),in_poa) | Q10: =IF(P10<O10,0,INT((P10-O10)/K10)+1) | R10: =IF(Q10=0,0,IF(in_rate=0,N10*Q10,N10*(1+in_rate)^(-O10)*(1-(1+in_rate)^(-K10*Q10))/(1-(1+in_rate)^(-K10)))) | S10: =IF(in_timing="MID_YEAR",IF(O10=0,IF(Q10=0,0,N10+(R10-N10)*(1+in_rate)^0.5),R10*(1+in_rate)^0.5),R10)
A11: =B11&"|"&C11 | B11: 17F2M | C11: Alternative2 | D11: Invasive species control | E11: FIXED | F11: 15000 | K11: 10 | N11: =IF(E11="FIXED",F11,IF(E11="PERCENT",G11*IFERROR(INDEX(Costs!$D$6:$F$36,MATCH(A11,Costs!$A$6:$A$36,0),MATCH(H11,Costs!$D$5:$F$5,0)),0),I11*J11)) | O11: =IF(ISNUMBER(L11),L11,K11) | P11: =IF(ISNUMBER(M11),MIN(M11,in_poa),in_poa) | Q11: =IF(P11<O11,0,INT((P11-O11)/K11)+1) | R11: =IF(Q11=0,0,IF(in_rate=0,N11*Q11,N11*(1+in_rate)^(-O11)*(1-(1+in_rate)^(-K11*Q11))/(1-(1+in_rate)^(-K11)))) | S11: =IF(in_timing="MID_YEAR",IF(O11=0,IF(Q11=0,0,N11+(R11-N11)*(1+in_rate)^0.5),R11*(1+in_rate)^0.5),R11)
A12: =B12&"|"&C12 | B12: 17F2M | C12: Alternative2 | D12: Wood, rock and earth repair | E12: PERCENT | G12: 0.1 | H12: construction | K12: 25 | N12: =IF(E12="FIXED",F12,IF(E12="PERCENT",G12*IFERROR(INDEX(Costs!$D$6:$F$36,MATCH(A12,Costs!$A$6:$A$36,0),MATCH(H12,Costs!$D$5:$F$5,0)),0),I12*J12)) | O12: =IF(ISNUMBER(L12),L12,K12) | P12: =IF(ISNUMBER(M12),MIN(M12,in_poa),in_poa) | Q12: =IF(P12<O12,0,INT((P12-O12)/K12)+1) | R12: =IF(Q12=0,0,IF(in_rate=0,N12*Q12,N12*(1+in_rate)^(-O12)*(1-(1+in_rate)^(-K12*Q12))/(1-(1+in_rate)^(-K12)))) | S12: =IF(in_timing="MID_YEAR",IF(O12=0,IF(Q12=0,0,N12+(R12-N12)*(1+in_rate)^0.5),R12*(1+in_rate)^0.5),R12)
A13: =B13&"|"&C13 | B13: 17F2M | C13: Alternative3 | D13: General maintenance | E13: FIXED | F13: 10000 | K13: 1 | N13: =IF(E13="FIXED",F13,IF(E13="PERCENT",G13*IFERROR(INDEX(Costs!$D$6:$F$36,MATCH(A13,Costs!$A$6:$A$36,0),MATCH(H13,Costs!$D$5:$F$5,0)),0),I13*J13)) | O13: =IF(ISNUMBER(L13),L13,K13) | P13: =IF(ISNUMBER(M13),MIN(M13,in_poa),in_poa) | Q13: =IF(P13<O13,0,INT((P13-O13)/K13)+1) | R13: =IF(Q13=0,0,IF(in_rate=0,N13*Q13,N13*(1+in_rate)^(-O13)*(1-(1+in_rate)^(-K13*Q13))/(1-(1+in_rate)^(-K13)))) | S13: =IF(in_timing="MID_YEAR",IF(O13=0,IF(Q13=0,0,N13+(R13-N13)*(1+in_rate)^0.5),R13*(1+in_rate)^0.5),R13)
A14: =B14&"|"&C14 | B14: 17F2M | C14: Alternative3 | D14: Inspection and trash removal | E14: RATE | I14: 4 | J14: 2639.11 | K14: 2 | N14: =IF(E14="FIXED",F14,IF(E14="PERCENT",G14*IFERROR(INDEX(Costs!$D$6:$F$36,MATCH(A14,Costs!$A$6:$A$36,0),MATCH(H14,Costs!$D$5:$F$5,0)),0),I14*J14)) | O14: =IF(ISNUMBER(L14),L14,K14) | P14: =IF(ISNUMBER(M14),MIN(M14,in_poa),in_poa) | Q14: =IF(P14<O14,0,INT((P14-O14)/K14)+1) | R14: =IF(Q14=0,0,IF(in_rate=0,N14*Q14,N14*(1+in_rate)^(-O14)*(1-(1+in_rate)^(-K14*Q14))/(1-(1+in_rate)^(-K14)))) | S14: =IF(in_timing="MID_YEAR",IF(O14=0,IF(Q14=0,0,N14+(R14-N14)*(1+in_rate)^0.5),R14*(1+in_rate)^0.5),R14)
A15: =B15&"|"&C15 | B15: 17F2M | C15: Alternative3 | D15: Invasive species control | E15: FIXED | F15: 15000 | K15: 10 | N15: =IF(E15="FIXED",F15,IF(E15="PERCENT",G15*IFERROR(INDEX(Costs!$D$6:$F$36,MATCH(A15,Costs!$A$6:$A$36,0),MATCH(H15,Costs!$D$5:$F$5,0)),0),I15*J15)) | O15: =IF(ISNUMBER(L15),L15,K15) | P15: =IF(ISNUMBER(M15),MIN(M15,in_poa),in_poa) | Q15: =IF(P15<O15,0,INT((P15-O15)/K15)+1) | R15: =IF(Q15=0,0,IF(in_rate=0,N15*Q15,N15*(1+in_rate)^(-O15)*(1-(1+in_rate)^(-K15*Q15))/(1-(1+in_rate)^(-K15)))) | S15: =IF(in_timing="MID_YEAR",IF(O15=0,IF(Q15=0,0,N15+(R15-N15)*(1+in_rate)^0.5),R15*(1+in_rate)^0.5),R15)
A16: =B16&"|"&C16 | B16: 17F2M | C16: Alternative3 | D16: Wood, rock and earth repair | E16: PERCENT | G16: 0.1 | H16: construction | K16: 25 | N16: =IF(E16="FIXED",F16,IF(E16="PERCENT",G16*IFERROR(INDEX(Costs!$D$6:$F$36,MATCH(A16,Costs!$A$6:$A$36,0),MATCH(H16,Costs!$D$5:$F$5,0)),0),I16*J16)) | O16: =IF(ISNUMBER(L16),L16,K16) | P16: =IF(ISNUMBER(M16),MIN(M16,in_poa),in_poa) | Q16: =IF(P16<O16,0,INT((P16-O16)/K16)+1) | R16: =IF(Q16=0,0,IF(in_rate=0,N16*Q16,N16*(1+in_rate)^(-O16)*(1-(1+in_rate)^(-K16*Q16))/(1-(1+in_rate)^(-K16)))) | S16: =IF(in_timing="MID_YEAR",IF(O16=0,IF(Q16=0,0,N16+(R16-N16)*(1+in_rate)^0.5),R16*(1+in_rate)^0.5),R16)
A17: =B17&"|"&C17 | B17: 17D2E | C17: Alternative1 | D17: General maintenance | E17: FIXED | F17: 10000 | K17: 1 | N17: =IF(E17="FIXED",F17,IF(E17="PERCENT",G17*IFERROR(INDEX(Costs!$D$6:$F$36,MATCH(A17,Costs!$A$6:$A$36,0),MATCH(H17,Costs!$D$5:$F$5,0)),0),I17*J17)) | O17: =IF(ISNUMBER(L17),L17,K17) | P17: =IF(ISNUMBER(M17),MIN(M17,in_poa),in_poa) | Q17: =IF(P17<O17,0,INT((P17-O17)/K17)+1) | R17: =IF(Q17=0,0,IF(in_rate=0,N17*Q17,N17*(1+in_rate)^(-O17)*(1-(1+in_rate)^(-K17*Q17))/(1-(1+in_rate)^(-K17)))) | S17: =IF(in_timing="MID_YEAR",IF(O17=0,IF(Q17=0,0,N17+(R17-N17)*(1+in_rate)^0.5),R17*(1+in_rate)^0.5),R17)
A18: =B18&"|"&C18 | B18: 17D2E | C18: Alternative1 | D18: Inspection and trash removal | E18: RATE | I18: 4 | J18: 3610.5749 | K18: 2 | N18: =IF(E18="FIXED",F18,IF(E18="PERCENT",G18*IFERROR(INDEX(Costs!$D$6:$F$36,MATCH(A18,Costs!$A$6:$A$36,0),MATCH(H18,Costs!$D$5:$F$5,0)),0),I18*J18)) | O18: =IF(ISNUMBER(L18),L18,K18) | P18: =IF(ISNUMBER(M18),MIN(M18,in_poa),in_poa) | Q18: =IF(P18<O18,0,INT((P18-O18)/K18)+1) | R18: =IF(Q18=0,0,IF(in_rate=0,N18*Q18,N18*(1+in_rate)^(-O18)*(1-(1+in_rate)^(-K18*Q18))/(1-(1+in_rate)^(-K18)))) | S18: =IF(in_timing="MID_YEAR",IF(O18=0,IF(Q18=0,0,N18+(R18-N18)*(1+in_rate)^0.5),R18*(1+in_rate)^0.5),R18)
A19: =B19&"|"&C19 | B19: 17D2E | C19: Alternative1 | D19: Invasive species control | E19: FIXED | F19: 15000 | K19: 10 | N19: =IF(E19="FIXED",F19,IF(E19="PERCENT",G19*IFERROR(INDEX(Costs!$D$6:$F$36,MATCH(A19,Costs!$A$6:$A$36,0),MATCH(H19,Costs!$D$5:$F$5,0)),0),I19*J19)) | O19: =IF(ISNUMBER(L19),L19,K19) | P19: =IF(ISNUMBER(M19),MIN(M19,in_poa),in_poa) | Q19: =IF(P19<O19,0,INT((P19-O19)/K19)+1) | R19: =IF(Q19=0,0,IF(in_rate=0,N19*Q19,N19*(1+in_rate)^(-O19)*(1-(1+in_rate)^(-K19*Q19))/(1-(1+in_rate)^(-K19)))) | S19: =IF(in_timing="MID_YEAR",IF(O19=0,IF(Q19=0,0,N19+(R19-N19)*(1+in_rate)^0.5),R19*(1+in_rate)^0.5),R19)
A20: =B20&"|"&C20 | B20: 17D2E | C20: Alternative1 | D20: Wood, rock and earth repair | E20: PERCENT | G20: 0.1 | H20: construction | K20: 25 | N20: =IF(E20="FIXED",F20,IF(E20="PERCENT",G20*IFERROR(INDEX(Costs!$D$6:$F$36,MATCH(A20,Costs!$A$6:$A$36,0),MATCH(H20,Costs!$D$5:$F$5,0)),0),I20*J20)) | O20: =IF(ISNUMBER(L20),L20,K20) | P20: =IF(ISNUMBER(M20),MIN(M20,in_poa),in_poa) | Q20: =IF(P20<O20,0,INT((P20-O20)/K20)+1) | R20: =IF(Q20=0,0,IF(in_rate=0,N20*Q20,N20*(1+in_rate)^(-O20)*(1-(1+in_rate)^(-K20*Q20))/(1-(1+in_rate)^(-K20)))) | S20: =IF(in_timing="MID_YEAR",IF(O20=0,IF(Q20=0,0,N20+(R20-N20)*(1+in_rate)^0.5),R20*(1+in_rate)^0.5),R20)
A21: =B21&"|"&C21 | B21: 17D2E | C21: Alternative2 | D21: General maintenance | E21: FIXED | F21: 10000 | K21: 1 | N21: =IF(E21="FIXED",F21,IF(E21="PERCENT",G21*IFERROR(INDEX(Costs!$D$6:$F$36,MATCH(A21,Costs!$A$6:$A$36,0),MATCH(H21,Costs!$D$5:$F$5,0)),0),I21*J21)) | O21: =IF(ISNUMBER(L21),L21,K21) | P21: =IF(ISNUMBER(M21),MIN(M21,in_poa),in_poa) | Q21: =IF(P21<O21,0,INT((P21-O21)/K21)+1) | R21: =IF(Q21=0,0,IF(in_rate=0,N21*Q21,N21*(1+in_rate)^(-O21)*(1-(1+in_rate)^(-K21*Q21))/(1-(1+in_rate)^(-K21)))) | S21: =IF(in_timing="MID_YEAR",IF(O21=0,IF(Q21=0,0,N21+(R21-N21)*(1+in_rate)^0.5),R21*(1+in_rate)^0.5),R21)
A22: =B22&"|"&C22 | B22: 17D2E | C22: Alternative2 | D22: Inspection and trash removal | E22: RATE | I22: 4 | J22: 3610.5749 | K22: 2 | N22: =IF(E22="FIXED",F22,IF(E22="PERCENT",G22*IFERROR(INDEX(Costs!$D$6:$F$36,MATCH(A22,Costs!$A$6:$A$36,0),MATCH(H22,Costs!$D$5:$F$5,0)),0),I22*J22)) | O22: =IF(ISNUMBER(L22),L22,K22) | P22: =IF(ISNUMBER(M22),MIN(M22,in_poa),in_poa) | Q22: =IF(P22<O22,0,INT((P22-O22)/K22)+1) | R22: =IF(Q22=0,0,IF(in_rate=0,N22*Q22,N22*(1+in_rate)^(-O22)*(1-(1+in_rate)^(-K22*Q22))/(1-(1+in_rate)^(-K22)))) | S22: =IF(in_timing="MID_YEAR",IF(O22=0,IF(Q22=0,0,N22+(R22-N22)*(1+in_rate)^0.5),R22*(1+in_rate)^0.5),R22)
A23: =B23&"|"&C23 | B23: 17D2E | C23: Alternative2 | D23: Invasive species control | E23: FIXED | F23: 15000 | K23: 10 | N23: =IF(E23="FIXED",F23,IF(E23="PERCENT",G23*IFERROR(INDEX(Costs!$D$6:$F$36,MATCH(A23,Costs!$A$6:$A$36,0),MATCH(H23,Costs!$D$5:$F$5,0)),0),I23*J23)) | O23: =IF(ISNUMBER(L23),L23,K23) | P23: =IF(ISNUMBER(M23),MIN(M23,in_poa),in_poa) | Q23: =IF(P23<O23,0,INT((P23-O23)/K23)+1) | R23: =IF(Q23=0,0,IF(in_rate=0,N23*Q23,N23*(1+in_rate)^(-O23)*(1-(1+in_rate)^(-K23*Q23))/(1-(1+in_rate)^(-K23)))) | S23: =IF(in_timing="MID_YEAR",IF(O23=0,IF(Q23=0,0,N23+(R23-N23)*(1+in_rate)^0.5),R23*(1+in_rate)^0.5),R23)
A24: =B24&"|"&C24 | B24: 17D2E | C24: Alternative2 | D24: Wood, rock and earth repair | E24: PERCENT | G24: 0.1 | H24: construction | K24: 25 | N24: =IF(E24="FIXED",F24,IF(E24="PERCENT",G24*IFERROR(INDEX(Costs!$D$6:$F$36,MATCH(A24,Costs!$A$6:$A$36,0),MATCH(H24,Costs!$D$5:$F$5,0)),0),I24*J24)) | O24: =IF(ISNUMBER(L24),L24,K24) | P24: =IF(ISNUMBER(M24),MIN(M24,in_poa),in_poa) | Q24: =IF(P24<O24,0,INT((P24-O24)/K24)+1) | R24: =IF(Q24=0,0,IF(in_rate=0,N24*Q24,N24*(1+in_rate)^(-O24)*(1-(1+in_rate)^(-K24*Q24))/(1-(1+in_rate)^(-K24)))) | S24: =IF(in_timing="MID_YEAR",IF(O24=0,IF(Q24=0,0,N24+(R24-N24)*(1+in_rate)^0.5),R24*(1+in_rate)^0.5),R24)
A25: =B25&"|"&C25 | B25: 17D2E | C25: Alternative3 | D25: General maintenance | E25: FIXED | F25: 10000 | K25: 1 | N25: =IF(E25="FIXED",F25,IF(E25="PERCENT",G25*IFERROR(INDEX(Costs!$D$6:$F$36,MATCH(A25,Costs!$A$6:$A$36,0),MATCH(H25,Costs!$D$5:$F$5,0)),0),I25*J25)) | O25: =IF(ISNUMBER(L25),L25,K25) | P25: =IF(ISNUMBER(M25),MIN(M25,in_poa),in_poa) | Q25: =IF(P25<O25,0,INT((P25-O25)/K25)+1) | R25: =IF(Q25=0,0,IF(in_rate=0,N25*Q25,N25*(1+in_rate)^(-O25)*(1-(1+in_rate)^(-K25*Q25))/(1-(1+in_rate)^(-K25)))) | S25: =IF(in_timing="MID_YEAR",IF(O25=0,IF(Q25=0,0,N25+(R25-N25)*(1+in_rate)^0.5),R25*(1+in_rate)^0.5),R25)
A26: =B26&"|"&C26 | B26: 17D2E | C26: Alternative3 | D26: Inspection and trash removal | E26: RATE | I26: 4 | J26: 3610.5749 | K26: 2 | N26: =IF(E26="FIXED",F26,IF(E26="PERCENT",G26*IFERROR(INDEX(Costs!$D$6:$F$36,MATCH(A26,Costs!$A$6:$A$36,0),MATCH(H26,Costs!$D$5:$F$5,0)),0),I26*J26)) | O26: =IF(ISNUMBER(L26),L26,K26) | P26: =IF(ISNUMBER(M26),MIN(M26,in_poa),in_poa) | Q26: =IF(P26<O26,0,INT((P26-O26)/K26)+1) | R26: =IF(Q26=0,0,IF(in_rate=0,N26*Q26,N26*(1+in_rate)^(-O26)*(1-(1+in_rate)^(-K26*Q26))/(1-(1+in_rate)^(-K26)))) | S26: =IF(in_timing="MID_YEAR",IF(O26=0,IF(Q26=0,0,N26+(R26-N26)*(1+in_rate)^0.5),R26*(1+in_rate)^0.5),R26)
A27: =B27&"|"&C27 | B27: 17D2E | C27: Alternative3 | D27: Invasive species control | E27: FIXED | F27: 15000 | K27: 10 | N27: =IF(E27="FIXED",F27,IF(E27="PERCENT",G27*IFERROR(INDEX(Costs!$D$6:$F$36,MATCH(A27,Costs!$A$6:$A$36,0),MATCH(H27,Costs!$D$5:$F$5,0)),0),I27*J27)) | O27: =IF(ISNUMBER(L27),L27,K27) | P27: =IF(ISNUMBER(M27),MIN(M27,in_poa),in_poa) | Q27: =IF(P27<O27,0,INT((P27-O27)/K27)+1) | R27: =IF(Q27=0,0,IF(in_rate=0,N27*Q27,N27*(1+in_rate)^(-O27)*(1-(1+in_rate)^(-K27*Q27))/(1-(1+in_rate)^(-K27)))) | S27: =IF(in_timing="MID_YEAR",IF(O27=0,IF(Q27=0,0,N27+(R27-N27)*(1+in_rate)^0.5),R27*(1+in_rate)^0.5),R27)
A28: =B28&"|"&C28 | B28: 17D2E | C28: Alternative3 | D28: Wood, rock and earth repair | E28: PERCENT | G28: 0.1 | H28: construction | K28: 25 | N28: =IF(E28="FIXED",F28,IF(E28="PERCENT",G28*IFERROR(INDEX(Costs!$D$6:$F$36,MATCH(A28,Costs!$A$6:$A$36,0),MATCH(H28,Costs!$D$5:$F$5,0)),0),I28*J28)) | O28: =IF(ISNUMBER(L28),L28,K28) | P28: =IF(ISNUMBER(M28),MIN(M28,in_poa),in_poa) | Q28: =IF(P28<O28,0,INT((P28-O28)/K28)+1) | R28: =IF(Q28=0,0,IF(in_rate=0,N28*Q28,N28*(1+in_rate)^(-O28)*(1-(1+in_rate)^(-K28*Q28))/(1-(1+in_rate)^(-K28)))) | S28: =IF(in_timing="MID_YEAR",IF(O28=0,IF(Q28=0,0,N28+(R28-N28)*(1+in_rate)^0.5),R28*(1+in_rate)^0.5),R28)
A29: =B29&"|"&C29 | B29: 17B | C29: Alternative1 | D29: General maintenance | E29: FIXED | F29: 10000 | K29: 1 | N29: =IF(E29="FIXED",F29,IF(E29="PERCENT",G29*IFERROR(INDEX(Costs!$D$6:$F$36,MATCH(A29,Costs!$A$6:$A$36,0),MATCH(H29,Costs!$D$5:$F$5,0)),0),I29*J29)) | O29: =IF(ISNUMBER(L29),L29,K29) | P29: =IF(ISNUMBER(M29),MIN(M29,in_poa),in_poa) | Q29: =IF(P29<O29,0,INT((P29-O29)/K29)+1) | R29: =IF(Q29=0,0,IF(in_rate=0,N29*Q29,N29*(1+in_rate)^(-O29)*(1-(1+in_rate)^(-K29*Q29))/(1-(1+in_rate)^(-K29)))) | S29: =IF(in_timing="MID_YEAR",IF(O29=0,IF(Q29=0,0,N29+(R29-N29)*(1+in_rate)^0.5),R29*(1+in_rate)^0.5),R29)
A30: =B30&"|"&C30 | B30: 17B | C30: Alternative1 | D30: Inspection and trash removal | E30: RATE | I30: 4 | J30: 6461.9861 | K30: 2 | N30: =IF(E30="FIXED",F30,IF(E30="PERCENT",G30*IFERROR(INDEX(Costs!$D$6:$F$36,MATCH(A30,Costs!$A$6:$A$36,0),MATCH(H30,Costs!$D$5:$F$5,0)),0),I30*J30)) | O30: =IF(ISNUMBER(L30),L30,K30) | P30: =IF(ISNUMBER(M30),MIN(M30,in_poa),in_poa) | Q30: =IF(P30<O30,0,INT((P30-O30)/K30)+1) | R30: =IF(Q30=0,0,IF(in_rate=0,N30*Q30,N30*(1+in_rate)^(-O30)*(1-(1+in_rate)^(-K30*Q30))/(1-(1+in_rate)^(-K30)))) | S30: =IF(in_timing="MID_YEAR",IF(O30=0,IF(Q30=0,0,N30+(R30-N30)*(1+in_rate)^0.5),R30*(1+in_rate)^0.5),R30)
A31: =B31&"|"&C31 | B31: 17B | C31: Alternative1 | D31: Invasive species control | E31: FIXED | F31: 15000 | K31: 10 | N31: =IF(E31="FIXED",F31,IF(E31="PERCENT",G31*IFERROR(INDEX(Costs!$D$6:$F$36,MATCH(A31,Costs!$A$6:$A$36,0),MATCH(H31,Costs!$D$5:$F$5,0)),0),I31*J31)) | O31: =IF(ISNUMBER(L31),L31,K31) | P31: =IF(ISNUMBER(M31),MIN(M31,in_poa),in_poa) | Q31: =IF(P31<O31,0,INT((P31-O31)/K31)+1) | R31: =IF(Q31=0,0,IF(in_rate=0,N31*Q31,N31*(1+in_rate)^(-O31)*(1-(1+in_rate)^(-K31*Q31))/(1-(1+in_rate)^(-K31)))) | S31: =IF(in_timing="MID_YEAR",IF(O31=0,IF(Q31=0,0,N31+(R31-N31)*(1+in_rate)^0.5),R31*(1+in_rate)^0.5),R31)
A32: =B32&"|"&C32 | B32: 17B | C32: Alternative1 | D32: Wood, rock and earth repair | E32: PERCENT | G32: 0.1 | H32: construction | K32: 25 | N32: =IF(E32="FIXED",F32,IF(E32="PERCENT",G32*IFERROR(INDEX(Costs!$D$6:$F$36,MATCH(A32,Costs!$A$6:$A$36,0),MATCH(H32,Costs!$D$5:$F$5,0)),0),I32*J32)) | O32: =IF(ISNUMBER(L32),L32,K32) | P32: =IF(ISNUMBER(M32),MIN(M32,in_poa),in_poa) | Q32: =IF(P32<O32,0,INT((P32-O32)/K32)+1) | R32: =IF(Q32=0,0,IF(in_rate=0,N32*Q32,N32*(1+in_rate)^(-O32)*(1-(1+in_rate)^(-K32*Q32))/(1-(1+in_rate)^(-K32)))) | S32: =IF(in_timing="MID_YEAR",IF(O32=0,IF(Q32=0,0,N32+(R32-N32)*(1+in_rate)^0.5),R32*(1+in_rate)^0.5),R32)
A33: =B33&"|"&C33 | B33: 17B | C33: Alternative2 | D33: General maintenance | E33: FIXED | F33: 10000 | K33: 1 | N33: =IF(E33="FIXED",F33,IF(E33="PERCENT",G33*IFERROR(INDEX(Costs!$D$6:$F$36,MATCH(A33,Costs!$A$6:$A$36,0),MATCH(H33,Costs!$D$5:$F$5,0)),0),I33*J33)) | O33: =IF(ISNUMBER(L33),L33,K33) | P33: =IF(ISNUMBER(M33),MIN(M33,in_poa),in_poa) | Q33: =IF(P33<O33,0,INT((P33-O33)/K33)+1) | R33: =IF(Q33=0,0,IF(in_rate=0,N33*Q33,N33*(1+in_rate)^(-O33)*(1-(1+in_rate)^(-K33*Q33))/(1-(1+in_rate)^(-K33)))) | S33: =IF(in_timing="MID_YEAR",IF(O33=0,IF(Q33=0,0,N33+(R33-N33)*(1+in_rate)^0.5),R33*(1+in_rate)^0.5),R33)
A34: =B34&"|"&C34 | B34: 17B | C34: Alternative2 | D34: Inspection and trash removal | E34: RATE | I34: 4 | J34: 6461.9861 | K34: 2 | N34: =IF(E34="FIXED",F34,IF(E34="PERCENT",G34*IFERROR(INDEX(Costs!$D$6:$F$36,MATCH(A34,Costs!$A$6:$A$36,0),MATCH(H34,Costs!$D$5:$F$5,0)),0),I34*J34)) | O34: =IF(ISNUMBER(L34),L34,K34) | P34: =IF(ISNUMBER(M34),MIN(M34,in_poa),in_poa) | Q34: =IF(P34<O34,0,INT((P34-O34)/K34)+1) | R34: =IF(Q34=0,0,IF(in_rate=0,N34*Q34,N34*(1+in_rate)^(-O34)*(1-(1+in_rate)^(-K34*Q34))/(1-(1+in_rate)^(-K34)))) | S34: =IF(in_timing="MID_YEAR",IF(O34=0,IF(Q34=0,0,N34+(R34-N34)*(1+in_rate)^0.5),R34*(1+in_rate)^0.5),R34)
A35: =B35&"|"&C35 | B35: 17B | C35: Alternative2 | D35: Invasive species control | E35: FIXED | F35: 15000 | K35: 10 | N35: =IF(E35="FIXED",F35,IF(E35="PERCENT",G35*IFERROR(INDEX(Costs!$D$6:$F$36,MATCH(A35,Costs!$A$6:$A$36,0),MATCH(H35,Costs!$D$5:$F$5,0)),0),I35*J35)) | O35: =IF(ISNUMBER(L35),L35,K35) | P35: =IF(ISNUMBER(M35),MIN(M35,in_poa),in_poa) | Q35: =IF(P35<O35,0,INT((P35-O35)/K35)+1) | R35: =IF(Q35=0,0,IF(in_rate=0,N35*Q35,N35*(1+in_rate)^(-O35)*(1-(1+in_rate)^(-K35*Q35))/(1-(1+in_rate)^(-K35)))) | S35: =IF(in_timing="MID_YEAR",IF(O35=0,IF(Q35=0,0,N35+(R35-N35)*(1+in_rate)^0.5),R35*(1+in_rate)^0.5),R35)
A36: =B36&"|"&C36 | B36: 17B | C36: Alternative2 | D36: Wood, rock and earth repair | E36: PERCENT | G36: 0.1 | H36: construction | K36: 25 | N36: =IF(E36="FIXED",F36,IF(E36="PERCENT",G36*IFERROR(INDEX(Costs!$D$6:$F$36,MATCH(A36,Costs!$A$6:$A$36,0),MATCH(H36,Costs!$D$5:$F$5,0)),0),I36*J36)) | O36: =IF(ISNUMBER(L36),L36,K36) | P36: =IF(ISNUMBER(M36),MIN(M36,in_poa),in_poa) | Q36: =IF(P36<O36,0,INT((P36-O36)/K36)+1) | R36: =IF(Q36=0,0,IF(in_rate=0,N36*Q36,N36*(1+in_rate)^(-O36)*(1-(1+in_rate)^(-K36*Q36))/(1-(1+in_rate)^(-K36)))) | S36: =IF(in_timing="MID_YEAR",IF(O36=0,IF(Q36=0,0,N36+(R36-N36)*(1+in_rate)^0.5),R36*(1+in_rate)^0.5),R36)
A37: =B37&"|"&C37 | B37: 17B | C37: Alternative3 | D37: General maintenance | E37: FIXED | F37: 10000 | K37: 1 | N37: =IF(E37="FIXED",F37,IF(E37="PERCENT",G37*IFERROR(INDEX(Costs!$D$6:$F$36,MATCH(A37,Costs!$A$6:$A$36,0),MATCH(H37,Costs!$D$5:$F$5,0)),0),I37*J37)) | O37: =IF(ISNUMBER(L37),L37,K37) | P37: =IF(ISNUMBER(M37),MIN(M37,in_poa),in_poa) | Q37: =IF(P37<O37,0,INT((P37-O37)/K37)+1) | R37: =IF(Q37=0,0,IF(in_rate=0,N37*Q37,N37*(1+in_rate)^(-O37)*(1-(1+in_rate)^(-K37*Q37))/(1-(1+in_rate)^(-K37)))) | S37: =IF(in_timing="MID_YEAR",IF(O37=0,IF(Q37=0,0,N37+(R37-N37)*(1+in_rate)^0.5),R37*(1+in_rate)^0.5),R37)
A38: =B38&"|"&C38 | B38: 17B | C38: Alternative3 | D38: Inspection and trash removal | E38: RATE | I38: 4 | J38: 6461.9861 | K38: 2 | N38: =IF(E38="FIXED",F38,IF(E38="PERCENT",G38*IFERROR(INDEX(Costs!$D$6:$F$36,MATCH(A38,Costs!$A$6:$A$36,0),MATCH(H38,Costs!$D$5:$F$5,0)),0),I38*J38)) | O38: =IF(ISNUMBER(L38),L38,K38) | P38: =IF(ISNUMBER(M38),MIN(M38,in_poa),in_poa) | Q38: =IF(P38<O38,0,INT((P38-O38)/K38)+1) | R38: =IF(Q38=0,0,IF(in_rate=0,N38*Q38,N38*(1+in_rate)^(-O38)*(1-(1+in_rate)^(-K38*Q38))/(1-(1+in_rate)^(-K38)))) | S38: =IF(in_timing="MID_YEAR",IF(O38=0,IF(Q38=0,0,N38+(R38-N38)*(1+in_rate)^0.5),R38*(1+in_rate)^0.5),R38)
A39: =B39&"|"&C39 | B39: 17B | C39: Alternative3 | D39: Invasive species control | E39: FIXED | F39: 15000 | K39: 10 | N39: =IF(E39="FIXED",F39,IF(E39="PERCENT",G39*IFERROR(INDEX(Costs!$D$6:$F$36,MATCH(A39,Costs!$A$6:$A$36,0),MATCH(H39,Costs!$D$5:$F$5,0)),0),I39*J39)) | O39: =IF(ISNUMBER(L39),L39,K39) | P39: =IF(ISNUMBER(M39),MIN(M39,in_poa),in_poa) | Q39: =IF(P39<O39,0,INT((P39-O39)/K39)+1) | R39: =IF(Q39=0,0,IF(in_rate=0,N39*Q39,N39*(1+in_rate)^(-O39)*(1-(1+in_rate)^(-K39*Q39))/(1-(1+in_rate)^(-K39)))) | S39: =IF(in_timing="MID_YEAR",IF(O39=0,IF(Q39=0,0,N39+(R39-N39)*(1+in_rate)^0.5),R39*(1+in_rate)^0.5),R39)
A40: =B40&"|"&C40 | B40: 17B | C40: Alternative3 | D40: Wood, rock and earth repair | E40: PERCENT | G40: 0.1 | H40: construction | K40: 25 | N40: =IF(E40="FIXED",F40,IF(E40="PERCENT",G40*IFERROR(INDEX(Costs!$D$6:$F$36,MATCH(A40,Costs!$A$6:$A$36,0),MATCH(H40,Costs!$D$5:$F$5,0)),0),I40*J40)) | O40: =IF(ISNUMBER(L40),L40,K40) | P40: =IF(ISNUMBER(M40),MIN(M40,in_poa),in_poa) | Q40: =IF(P40<O40,0,INT((P40-O40)/K40)+1) | R40: =IF(Q40=0,0,IF(in_rate=0,N40*Q40,N40*(1+in_rate)^(-O40)*(1-(1+in_rate)^(-K40*Q40))/(1-(1+in_rate)^(-K40)))) | S40: =IF(in_timing="MID_YEAR",IF(O40=0,IF(Q40=0,0,N40+(R40-N40)*(1+in_rate)^0.5),R40*(1+in_rate)^0.5),R40)
A41: =B41&"|"&C41 | B41: 2A | C41: Alternative1 | D41: General maintenance | E41: FIXED | F41: 10000 | K41: 1 | N41: =IF(E41="FIXED",F41,IF(E41="PERCENT",G41*IFERROR(INDEX(Costs!$D$6:$F$36,MATCH(A41,Costs!$A$6:$A$36,0),MATCH(H41,Costs!$D$5:$F$5,0)),0),I41*J41)) | O41: =IF(ISNUMBER(L41),L41,K41) | P41: =IF(ISNUMBER(M41),MIN(M41,in_poa),in_poa) | Q41: =IF(P41<O41,0,INT((P41-O41)/K41)+1) | R41: =IF(Q41=0,0,IF(in_rate=0,N41*Q41,N41*(1+in_rate)^(-O41)*(1-(1+in_rate)^(-K41*Q41))/(1-(1+in_rate)^(-K41)))) | S41: =IF(in_timing="MID_YEAR",IF(O41=0,IF(Q41=0,0,N41+(R41-N41)*(1+in_rate)^0.5),R41*(1+in_rate)^0.5),R41)
A42: =B42&"|"&C42 | B42: 2A | C42: Alternative1 | D42: Inspection and trash removal | E42: RATE | I42: 4 | J42: 3889 | K42: 2 | N42: =IF(E42="FIXED",F42,IF(E42="PERCENT",G42*IFERROR(INDEX(Costs!$D$6:$F$36,MATCH(A42,Costs!$A$6:$A$36,0),MATCH(H42,Costs!$D$5:$F$5,0)),0),I42*J42)) | O42: =IF(ISNUMBER(L42),L42,K42) | P42: =IF(ISNUMBER(M42),MIN(M42,in_poa),in_poa) | Q42: =IF(P42<O42,0,INT((P42-O42)/K42)+1) | R42: =IF(Q42=0,0,IF(in_rate=0,N42*Q42,N42*(1+in_rate)^(-O42)*(1-(1+in_rate)^(-K42*Q42))/(1-(1+in_rate)^(-K42)))) | S42: =IF(in_timing="MID_YEAR",IF(O42=0,IF(Q42=0,0,N42+(R42-N42)*(1+in_rate)^0.5),R42*(1+in_rate)^0.5),R42)
A43: =B43&"|"&C43 | B43: 2A | C43: Alternative1 | D43: Invasive species control | E43: FIXED | F43: 15000 | K43: 10 | N43: =IF(E43="FIXED",F43,IF(E43="PERCENT",G43*IFERROR(INDEX(Costs!$D$6:$F$36,MATCH(A43,Costs!$A$6:$A$36,0),MATCH(H43,Costs!$D$5:$F$5,0)),0),I43*J43)) | O43: =IF(ISNUMBER(L43),L43,K43) | P43: =IF(ISNUMBER(M43),MIN(M43,in_poa),in_poa) | Q43: =IF(P43<O43,0,INT((P43-O43)/K43)+1) | R43: =IF(Q43=0,0,IF(in_rate=0,N43*Q43,N43*(1+in_rate)^(-O43)*(1-(1+in_rate)^(-K43*Q43))/(1-(1+in_rate)^(-K43)))) | S43: =IF(in_timing="MID_YEAR",IF(O43=0,IF(Q43=0,0,N43+(R43-N43)*(1+in_rate)^0.5),R43*(1+in_rate)^0.5),R43)
A44: =B44&"|"&C44 | B44: 2A | C44: Alternative1 | D44: Wood, rock and earth repair | E44: PERCENT | G44: 0.1 | H44: construction | K44: 25 | N44: =IF(E44="FIXED",F44,IF(E44="PERCENT",G44*IFERROR(INDEX(Costs!$D$6:$F$36,MATCH(A44,Costs!$A$6:$A$36,0),MATCH(H44,Costs!$D$5:$F$5,0)),0),I44*J44)) | O44: =IF(ISNUMBER(L44),L44,K44) | P44: =IF(ISNUMBER(M44),MIN(M44,in_poa),in_poa) | Q44: =IF(P44<O44,0,INT((P44-O44)/K44)+1) | R44: =IF(Q44=0,0,IF(in_rate=0,N44*Q44,N44*(1+in_rate)^(-O44)*(1-(1+in_rate)^(-K44*Q44))/(1-(1+in_rate)^(-K44)))) | S44: =IF(in_timing="MID_YEAR",IF(O44=0,IF(Q44=0,0,N44+(R44-N44)*(1+in_rate)^0.5),R44*(1+in_rate)^0.5),R44)
A45: =B45&"|"&C45 | B45: 2A | C45: Alternative2 | D45: General maintenance | E45: FIXED | F45: 10000 | K45: 1 | N45: =IF(E45="FIXED",F45,IF(E45="PERCENT",G45*IFERROR(INDEX(Costs!$D$6:$F$36,MATCH(A45,Costs!$A$6:$A$36,0),MATCH(H45,Costs!$D$5:$F$5,0)),0),I45*J45)) | O45: =IF(ISNUMBER(L45),L45,K45) | P45: =IF(ISNUMBER(M45),MIN(M45,in_poa),in_poa) | Q45: =IF(P45<O45,0,INT((P45-O45)/K45)+1) | R45: =IF(Q45=0,0,IF(in_rate=0,N45*Q45,N45*(1+in_rate)^(-O45)*(1-(1+in_rate)^(-K45*Q45))/(1-(1+in_rate)^(-K45)))) | S45: =IF(in_timing="MID_YEAR",IF(O45=0,IF(Q45=0,0,N45+(R45-N45)*(1+in_rate)^0.5),R45*(1+in_rate)^0.5),R45)
A46: =B46&"|"&C46 | B46: 2A | C46: Alternative2 | D46: Inspection and trash removal | E46: RATE | I46: 4 | J46: 3739.6656 | K46: 2 | N46: =IF(E46="FIXED",F46,IF(E46="PERCENT",G46*IFERROR(INDEX(Costs!$D$6:$F$36,MATCH(A46,Costs!$A$6:$A$36,0),MATCH(H46,Costs!$D$5:$F$5,0)),0),I46*J46)) | O46: =IF(ISNUMBER(L46),L46,K46) | P46: =IF(ISNUMBER(M46),MIN(M46,in_poa),in_poa) | Q46: =IF(P46<O46,0,INT((P46-O46)/K46)+1) | R46: =IF(Q46=0,0,IF(in_rate=0,N46*Q46,N46*(1+in_rate)^(-O46)*(1-(1+in_rate)^(-K46*Q46))/(1-(1+in_rate)^(-K46)))) | S46: =IF(in_timing="MID_YEAR",IF(O46=0,IF(Q46=0,0,N46+(R46-N46)*(1+in_rate)^0.5),R46*(1+in_rate)^0.5),R46)
A47: =B47&"|"&C47 | B47: 2A | C47: Alternative2 | D47: Invasive species control | E47: FIXED | F47: 15000 | K47: 10 | N47: =IF(E47="FIXED",F47,IF(E47="PERCENT",G47*IFERROR(INDEX(Costs!$D$6:$F$36,MATCH(A47,Costs!$A$6:$A$36,0),MATCH(H47,Costs!$D$5:$F$5,0)),0),I47*J47)) | O47: =IF(ISNUMBER(L47),L47,K47) | P47: =IF(ISNUMBER(M47),MIN(M47,in_poa),in_poa) | Q47: =IF(P47<O47,0,INT((P47-O47)/K47)+1) | R47: =IF(Q47=0,0,IF(in_rate=0,N47*Q47,N47*(1+in_rate)^(-O47)*(1-(1+in_rate)^(-K47*Q47))/(1-(1+in_rate)^(-K47)))) | S47: =IF(in_timing="MID_YEAR",IF(O47=0,IF(Q47=0,0,N47+(R47-N47)*(1+in_rate)^0.5),R47*(1+in_rate)^0.5),R47)
A48: =B48&"|"&C48 | B48: 2A | C48: Alternative2 | D48: Wood, rock and earth repair | E48: PERCENT | G48: 0.1 | H48: construction | K48: 25 | N48: =IF(E48="FIXED",F48,IF(E48="PERCENT",G48*IFERROR(INDEX(Costs!$D$6:$F$36,MATCH(A48,Costs!$A$6:$A$36,0),MATCH(H48,Costs!$D$5:$F$5,0)),0),I48*J48)) | O48: =IF(ISNUMBER(L48),L48,K48) | P48: =IF(ISNUMBER(M48),MIN(M48,in_poa),in_poa) | Q48: =IF(P48<O48,0,INT((P48-O48)/K48)+1) | R48: =IF(Q48=0,0,IF(in_rate=0,N48*Q48,N48*(1+in_rate)^(-O48)*(1-(1+in_rate)^(-K48*Q48))/(1-(1+in_rate)^(-K48)))) | S48: =IF(in_timing="MID_YEAR",IF(O48=0,IF(Q48=0,0,N48+(R48-N48)*(1+in_rate)^0.5),R48*(1+in_rate)^0.5),R48)
A49: =B49&"|"&C49 | B49: 2A | C49: Alternative3 | D49: General maintenance | E49: FIXED | F49: 10000 | K49: 1 | N49: =IF(E49="FIXED",F49,IF(E49="PERCENT",G49*IFERROR(INDEX(Costs!$D$6:$F$36,MATCH(A49,Costs!$A$6:$A$36,0),MATCH(H49,Costs!$D$5:$F$5,0)),0),I49*J49)) | O49: =IF(ISNUMBER(L49),L49,K49) | P49: =IF(ISNUMBER(M49),MIN(M49,in_poa),in_poa) | Q49: =IF(P49<O49,0,INT((P49-O49)/K49)+1) | R49: =IF(Q49=0,0,IF(in_rate=0,N49*Q49,N49*(1+in_rate)^(-O49)*(1-(1+in_rate)^(-K49*Q49))/(1-(1+in_rate)^(-K49)))) | S49: =IF(in_timing="MID_YEAR",IF(O49=0,IF(Q49=0,0,N49+(R49-N49)*(1+in_rate)^0.5),R49*(1+in_rate)^0.5),R49)
A50: =B50&"|"&C50 | B50: 2A | C50: Alternative3 | D50: Inspection and trash removal | E50: RATE | I50: 4 | J50: 3739.6656 | K50: 2 | N50: =IF(E50="FIXED",F50,IF(E50="PERCENT",G50*IFERROR(INDEX(Costs!$D$6:$F$36,MATCH(A50,Costs!$A$6:$A$36,0),MATCH(H50,Costs!$D$5:$F$5,0)),0),I50*J50)) | O50: =IF(ISNUMBER(L50),L50,K50) | P50: =IF(ISNUMBER(M50),MIN(M50,in_poa),in_poa) | Q50: =IF(P50<O50,0,INT((P50-O50)/K50)+1) | R50: =IF(Q50=0,0,IF(in_rate=0,N50*Q50,N50*(1+in_rate)^(-O50)*(1-(1+in_rate)^(-K50*Q50))/(1-(1+in_rate)^(-K50)))) | S50: =IF(in_timing="MID_YEAR",IF(O50=0,IF(Q50=0,0,N50+(R50-N50)*(1+in_rate)^0.5),R50*(1+in_rate)^0.5),R50)
A51: =B51&"|"&C51 | B51: 2A | C51: Alternative3 | D51: Invasive species control | E51: FIXED | F51: 15000 | K51: 10 | N51: =IF(E51="FIXED",F51,IF(E51="PERCENT",G51*IFERROR(INDEX(Costs!$D$6:$F$36,MATCH(A51,Costs!$A$6:$A$36,0),MATCH(H51,Costs!$D$5:$F$5,0)),0),I51*J51)) | O51: =IF(ISNUMBER(L51),L51,K51) | P51: =IF(ISNUMBER(M51),MIN(M51,in_poa),in_poa) | Q51: =IF(P51<O51,0,INT((P51-O51)/K51)+1) | R51: =IF(Q51=0,0,IF(in_rate=0,N51*Q51,N51*(1+in_rate)^(-O51)*(1-(1+in_rate)^(-K51*Q51))/(1-(1+in_rate)^(-K51)))) | S51: =IF(in_timing="MID_YEAR",IF(O51=0,IF(Q51=0,0,N51+(R51-N51)*(1+in_rate)^0.5),R51*(1+in_rate)^0.5),R51)
A52: =B52&"|"&C52 | B52: 2A | C52: Alternative3 | D52: Wood, rock and earth repair | E52: PERCENT | G52: 0.1 | H52: construction | K52: 25 | N52: =IF(E52="FIXED",F52,IF(E52="PERCENT",G52*IFERROR(INDEX(Costs!$D$6:$F$36,MATCH(A52,Costs!$A$6:$A$36,0),MATCH(H52,Costs!$D$5:$F$5,0)),0),I52*J52)) | O52: =IF(ISNUMBER(L52),L52,K52) | P52: =IF(ISNUMBER(M52),MIN(M52,in_poa),in_poa) | Q52: =IF(P52<O52,0,INT((P52-O52)/K52)+1) | R52: =IF(Q52=0,0,IF(in_rate=0,N52*Q52,N52*(1+in_rate)^(-O52)*(1-(1+in_rate)^(-K52*Q52))/(1-(1+in_rate)^(-K52)))) | S52: =IF(in_timing="MID_YEAR",IF(O52=0,IF(Q52=0,0,N52+(R52-N52)*(1+in_rate)^0.5),R52*(1+in_rate)^0.5),R52)
A53: =B53&"|"&C53 | B53: 2B | C53: Alternative1 | D53: General maintenance | E53: FIXED | F53: 10000 | K53: 1 | N53: =IF(E53="FIXED",F53,IF(E53="PERCENT",G53*IFERROR(INDEX(Costs!$D$6:$F$36,MATCH(A53,Costs!$A$6:$A$36,0),MATCH(H53,Costs!$D$5:$F$5,0)),0),I53*J53)) | O53: =IF(ISNUMBER(L53),L53,K53) | P53: =IF(ISNUMBER(M53),MIN(M53,in_poa),in_poa) | Q53: =IF(P53<O53,0,INT((P53-O53)/K53)+1) | R53: =IF(Q53=0,0,IF(in_rate=0,N53*Q53,N53*(1+in_rate)^(-O53)*(1-(1+in_rate)^(-K53*Q53))/(1-(1+in_rate)^(-K53)))) | S53: =IF(in_timing="MID_YEAR",IF(O53=0,IF(Q53=0,0,N53+(R53-N53)*(1+in_rate)^0.5),R53*(1+in_rate)^0.5),R53)
A54: =B54&"|"&C54 | B54: 2B | C54: Alternative1 | D54: Inspection and trash removal | E54: RATE | I54: 4 | J54: 4504.9858 | K54: 2 | N54: =IF(E54="FIXED",F54,IF(E54="PERCENT",G54*IFERROR(INDEX(Costs!$D$6:$F$36,MATCH(A54,Costs!$A$6:$A$36,0),MATCH(H54,Costs!$D$5:$F$5,0)),0),I54*J54)) | O54: =IF(ISNUMBER(L54),L54,K54) | P54: =IF(ISNUMBER(M54),MIN(M54,in_poa),in_poa) | Q54: =IF(P54<O54,0,INT((P54-O54)/K54)+1) | R54: =IF(Q54=0,0,IF(in_rate=0,N54*Q54,N54*(1+in_rate)^(-O54)*(1-(1+in_rate)^(-K54*Q54))/(1-(1+in_rate)^(-K54)))) | S54: =IF(in_timing="MID_YEAR",IF(O54=0,IF(Q54=0,0,N54+(R54-N54)*(1+in_rate)^0.5),R54*(1+in_rate)^0.5),R54)
A55: =B55&"|"&C55 | B55: 2B | C55: Alternative1 | D55: Invasive species control | E55: FIXED | F55: 15000 | K55: 10 | N55: =IF(E55="FIXED",F55,IF(E55="PERCENT",G55*IFERROR(INDEX(Costs!$D$6:$F$36,MATCH(A55,Costs!$A$6:$A$36,0),MATCH(H55,Costs!$D$5:$F$5,0)),0),I55*J55)) | O55: =IF(ISNUMBER(L55),L55,K55) | P55: =IF(ISNUMBER(M55),MIN(M55,in_poa),in_poa) | Q55: =IF(P55<O55,0,INT((P55-O55)/K55)+1) | R55: =IF(Q55=0,0,IF(in_rate=0,N55*Q55,N55*(1+in_rate)^(-O55)*(1-(1+in_rate)^(-K55*Q55))/(1-(1+in_rate)^(-K55)))) | S55: =IF(in_timing="MID_YEAR",IF(O55=0,IF(Q55=0,0,N55+(R55-N55)*(1+in_rate)^0.5),R55*(1+in_rate)^0.5),R55)
A56: =B56&"|"&C56 | B56: 2B | C56: Alternative1 | D56: Wood, rock and earth repair | E56: PERCENT | G56: 0.1 | H56: construction | K56: 25 | N56: =IF(E56="FIXED",F56,IF(E56="PERCENT",G56*IFERROR(INDEX(Costs!$D$6:$F$36,MATCH(A56,Costs!$A$6:$A$36,0),MATCH(H56,Costs!$D$5:$F$5,0)),0),I56*J56)) | O56: =IF(ISNUMBER(L56),L56,K56) | P56: =IF(ISNUMBER(M56),MIN(M56,in_poa),in_poa) | Q56: =IF(P56<O56,0,INT((P56-O56)/K56)+1) | R56: =IF(Q56=0,0,IF(in_rate=0,N56*Q56,N56*(1+in_rate)^(-O56)*(1-(1+in_rate)^(-K56*Q56))/(1-(1+in_rate)^(-K56)))) | S56: =IF(in_timing="MID_YEAR",IF(O56=0,IF(Q56=0,0,N56+(R56-N56)*(1+in_rate)^0.5),R56*(1+in_rate)^0.5),R56)
A57: =B57&"|"&C57 | B57: 2B | C57: Alternative2 | D57: General maintenance | E57: FIXED | F57: 10000 | K57: 1 | N57: =IF(E57="FIXED",F57,IF(E57="PERCENT",G57*IFERROR(INDEX(Costs!$D$6:$F$36,MATCH(A57,Costs!$A$6:$A$36,0),MATCH(H57,Costs!$D$5:$F$5,0)),0),I57*J57)) | O57: =IF(ISNUMBER(L57),L57,K57) | P57: =IF(ISNUMBER(M57),MIN(M57,in_poa),in_poa) | Q57: =IF(P57<O57,0,INT((P57-O57)/K57)+1) | R57: =IF(Q57=0,0,IF(in_rate=0,N57*Q57,N57*(1+in_rate)^(-O57)*(1-(1+in_rate)^(-K57*Q57))/(1-(1+in_rate)^(-K57)))) | S57: =IF(in_timing="MID_YEAR",IF(O57=0,IF(Q57=0,0,N57+(R57-N57)*(1+in_rate)^0.5),R57*(1+in_rate)^0.5),R57)
A58: =B58&"|"&C58 | B58: 2B | C58: Alternative2 | D58: Inspection and trash removal | E58: RATE | I58: 4 | J58: 4504.9858 | K58: 2 | N58: =IF(E58="FIXED",F58,IF(E58="PERCENT",G58*IFERROR(INDEX(Costs!$D$6:$F$36,MATCH(A58,Costs!$A$6:$A$36,0),MATCH(H58,Costs!$D$5:$F$5,0)),0),I58*J58)) | O58: =IF(ISNUMBER(L58),L58,K58) | P58: =IF(ISNUMBER(M58),MIN(M58,in_poa),in_poa) | Q58: =IF(P58<O58,0,INT((P58-O58)/K58)+1) | R58: =IF(Q58=0,0,IF(in_rate=0,N58*Q58,N58*(1+in_rate)^(-O58)*(1-(1+in_rate)^(-K58*Q58))/(1-(1+in_rate)^(-K58)))) | S58: =IF(in_timing="MID_YEAR",IF(O58=0,IF(Q58=0,0,N58+(R58-N58)*(1+in_rate)^0.5),R58*(1+in_rate)^0.5),R58)
A59: =B59&"|"&C59 | B59: 2B | C59: Alternative2 | D59: Invasive species control | E59: FIXED | F59: 15000 | K59: 10 | N59: =IF(E59="FIXED",F59,IF(E59="PERCENT",G59*IFERROR(INDEX(Costs!$D$6:$F$36,MATCH(A59,Costs!$A$6:$A$36,0),MATCH(H59,Costs!$D$5:$F$5,0)),0),I59*J59)) | O59: =IF(ISNUMBER(L59),L59,K59) | P59: =IF(ISNUMBER(M59),MIN(M59,in_poa),in_poa) | Q59: =IF(P59<O59,0,INT((P59-O59)/K59)+1) | R59: =IF(Q59=0,0,IF(in_rate=0,N59*Q59,N59*(1+in_rate)^(-O59)*(1-(1+in_rate)^(-K59*Q59))/(1-(1+in_rate)^(-K59)))) | S59: =IF(in_timing="MID_YEAR",IF(O59=0,IF(Q59=0,0,N59+(R59-N59)*(1+in_rate)^0.5),R59*(1+in_rate)^0.5),R59)
A60: =B60&"|"&C60 | B60: 2B | C60: Alternative2 | D60: Wood, rock and earth repair | E60: PERCENT | G60: 0.1 | H60: construction | K60: 25 | N60: =IF(E60="FIXED",F60,IF(E60="PERCENT",G60*IFERROR(INDEX(Costs!$D$6:$F$36,MATCH(A60,Costs!$A$6:$A$36,0),MATCH(H60,Costs!$D$5:$F$5,0)),0),I60*J60)) | O60: =IF(ISNUMBER(L60),L60,K60) | P60: =IF(ISNUMBER(M60),MIN(M60,in_poa),in_poa) | Q60: =IF(P60<O60,0,INT((P60-O60)/K60)+1) | R60: =IF(Q60=0,0,IF(in_rate=0,N60*Q60,N60*(1+in_rate)^(-O60)*(1-(1+in_rate)^(-K60*Q60))/(1-(1+in_rate)^(-K60)))) | S60: =IF(in_timing="MID_YEAR",IF(O60=0,IF(Q60=0,0,N60+(R60-N60)*(1+in_rate)^0.5),R60*(1+in_rate)^0.5),R60)
A61: =B61&"|"&C61 | B61: 2B | C61: Alternative3 | D61: General maintenance | E61: FIXED | F61: 10000 | K61: 1 | N61: =IF(E61="FIXED",F61,IF(E61="PERCENT",G61*IFERROR(INDEX(Costs!$D$6:$F$36,MATCH(A61,Costs!$A$6:$A$36,0),MATCH(H61,Costs!$D$5:$F$5,0)),0),I61*J61)) | O61: =IF(ISNUMBER(L61),L61,K61) | P61: =IF(ISNUMBER(M61),MIN(M61,in_poa),in_poa) | Q61: =IF(P61<O61,0,INT((P61-O61)/K61)+1) | R61: =IF(Q61=0,0,IF(in_rate=0,N61*Q61,N61*(1+in_rate)^(-O61)*(1-(1+in_rate)^(-K61*Q61))/(1-(1+in_rate)^(-K61)))) | S61: =IF(in_timing="MID_YEAR",IF(O61=0,IF(Q61=0,0,N61+(R61-N61)*(1+in_rate)^0.5),R61*(1+in_rate)^0.5),R61)
A62: =B62&"|"&C62 | B62: 2B | C62: Alternative3 | D62: Inspection and trash removal | E62: RATE | I62: 4 | J62: 4504.9858 | K62: 2 | N62: =IF(E62="FIXED",F62,IF(E62="PERCENT",G62*IFERROR(INDEX(Costs!$D$6:$F$36,MATCH(A62,Costs!$A$6:$A$36,0),MATCH(H62,Costs!$D$5:$F$5,0)),0),I62*J62)) | O62: =IF(ISNUMBER(L62),L62,K62) | P62: =IF(ISNUMBER(M62),MIN(M62,in_poa),in_poa) | Q62: =IF(P62<O62,0,INT((P62-O62)/K62)+1) | R62: =IF(Q62=0,0,IF(in_rate=0,N62*Q62,N62*(1+in_rate)^(-O62)*(1-(1+in_rate)^(-K62*Q62))/(1-(1+in_rate)^(-K62)))) | S62: =IF(in_timing="MID_YEAR",IF(O62=0,IF(Q62=0,0,N62+(R62-N62)*(1+in_rate)^0.5),R62*(1+in_rate)^0.5),R62)
A63: =B63&"|"&C63 | B63: 2B | C63: Alternative3 | D63: Invasive species control | E63: FIXED | F63: 15000 | K63: 10 | N63: =IF(E63="FIXED",F63,IF(E63="PERCENT",G63*IFERROR(INDEX(Costs!$D$6:$F$36,MATCH(A63,Costs!$A$6:$A$36,0),MATCH(H63,Costs!$D$5:$F$5,0)),0),I63*J63)) | O63: =IF(ISNUMBER(L63),L63,K63) | P63: =IF(ISNUMBER(M63),MIN(M63,in_poa),in_poa) | Q63: =IF(P63<O63,0,INT((P63-O63)/K63)+1) | R63: =IF(Q63=0,0,IF(in_rate=0,N63*Q63,N63*(1+in_rate)^(-O63)*(1-(1+in_rate)^(-K63*Q63))/(1-(1+in_rate)^(-K63)))) | S63: =IF(in_timing="MID_YEAR",IF(O63=0,IF(Q63=0,0,N63+(R63-N63)*(1+in_rate)^0.5),R63*(1+in_rate)^0.5),R63)
A64: =B64&"|"&C64 | B64: 2B | C64: Alternative3 | D64: Wood, rock and earth repair | E64: PERCENT | G64: 0.1 | H64: construction | K64: 25 | N64: =IF(E64="FIXED",F64,IF(E64="PERCENT",G64*IFERROR(INDEX(Costs!$D$6:$F$36,MATCH(A64,Costs!$A$6:$A$36,0),MATCH(H64,Costs!$D$5:$F$5,0)),0),I64*J64)) | O64: =IF(ISNUMBER(L64),L64,K64) | P64: =IF(ISNUMBER(M64),MIN(M64,in_poa),in_poa) | Q64: =IF(P64<O64,0,INT((P64-O64)/K64)+1) | R64: =IF(Q64=0,0,IF(in_rate=0,N64*Q64,N64*(1+in_rate)^(-O64)*(1-(1+in_rate)^(-K64*Q64))/(1-(1+in_rate)^(-K64)))) | S64: =IF(in_timing="MID_YEAR",IF(O64=0,IF(Q64=0,0,N64+(R64-N64)*(1+in_rate)^0.5),R64*(1+in_rate)^0.5),R64)
A65: =B65&"|"&C65 | B65: 3E | C65: Alternative1 | D65: General maintenance | E65: FIXED | F65: 10000 | K65: 1 | N65: =IF(E65="FIXED",F65,IF(E65="PERCENT",G65*IFERROR(INDEX(Costs!$D$6:$F$36,MATCH(A65,Costs!$A$6:$A$36,0),MATCH(H65,Costs!$D$5:$F$5,0)),0),I65*J65)) | O65: =IF(ISNUMBER(L65),L65,K65) | P65: =IF(ISNUMBER(M65),MIN(M65,in_poa),in_poa) | Q65: =IF(P65<O65,0,INT((P65-O65)/K65)+1) | R65: =IF(Q65=0,0,IF(in_rate=0,N65*Q65,N65*(1+in_rate)^(-O65)*(1-(1+in_rate)^(-K65*Q65))/(1-(1+in_rate)^(-K65)))) | S65: =IF(in_timing="MID_YEAR",IF(O65=0,IF(Q65=0,0,N65+(R65-N65)*(1+in_rate)^0.5),R65*(1+in_rate)^0.5),R65)
A66: =B66&"|"&C66 | B66: 3E | C66: Alternative1 | D66: Inspection and trash removal | E66: RATE | I66: 4 | J66: 2494.045 | K66: 2 | N66: =IF(E66="FIXED",F66,IF(E66="PERCENT",G66*IFERROR(INDEX(Costs!$D$6:$F$36,MATCH(A66,Costs!$A$6:$A$36,0),MATCH(H66,Costs!$D$5:$F$5,0)),0),I66*J66)) | O66: =IF(ISNUMBER(L66),L66,K66) | P66: =IF(ISNUMBER(M66),MIN(M66,in_poa),in_poa) | Q66: =IF(P66<O66,0,INT((P66-O66)/K66)+1) | R66: =IF(Q66=0,0,IF(in_rate=0,N66*Q66,N66*(1+in_rate)^(-O66)*(1-(1+in_rate)^(-K66*Q66))/(1-(1+in_rate)^(-K66)))) | S66: =IF(in_timing="MID_YEAR",IF(O66=0,IF(Q66=0,0,N66+(R66-N66)*(1+in_rate)^0.5),R66*(1+in_rate)^0.5),R66)
A67: =B67&"|"&C67 | B67: 3E | C67: Alternative1 | D67: Invasive species control | E67: FIXED | F67: 15000 | K67: 10 | N67: =IF(E67="FIXED",F67,IF(E67="PERCENT",G67*IFERROR(INDEX(Costs!$D$6:$F$36,MATCH(A67,Costs!$A$6:$A$36,0),MATCH(H67,Costs!$D$5:$F$5,0)),0),I67*J67)) | O67: =IF(ISNUMBER(L67),L67,K67) | P67: =IF(ISNUMBER(M67),MIN(M67,in_poa),in_poa) | Q67: =IF(P67<O67,0,INT((P67-O67)/K67)+1) | R67: =IF(Q67=0,0,IF(in_rate=0,N67*Q67,N67*(1+in_rate)^(-O67)*(1-(1+in_rate)^(-K67*Q67))/(1-(1+in_rate)^(-K67)))) | S67: =IF(in_timing="MID_YEAR",IF(O67=0,IF(Q67=0,0,N67+(R67-N67)*(1+in_rate)^0.5),R67*(1+in_rate)^0.5),R67)
A68: =B68&"|"&C68 | B68: 3E | C68: Alternative1 | D68: Wood, rock and earth repair | E68: PERCENT | G68: 0.1 | H68: construction | K68: 25 | N68: =IF(E68="FIXED",F68,IF(E68="PERCENT",G68*IFERROR(INDEX(Costs!$D$6:$F$36,MATCH(A68,Costs!$A$6:$A$36,0),MATCH(H68,Costs!$D$5:$F$5,0)),0),I68*J68)) | O68: =IF(ISNUMBER(L68),L68,K68) | P68: =IF(ISNUMBER(M68),MIN(M68,in_poa),in_poa) | Q68: =IF(P68<O68,0,INT((P68-O68)/K68)+1) | R68: =IF(Q68=0,0,IF(in_rate=0,N68*Q68,N68*(1+in_rate)^(-O68)*(1-(1+in_rate)^(-K68*Q68))/(1-(1+in_rate)^(-K68)))) | S68: =IF(in_timing="MID_YEAR",IF(O68=0,IF(Q68=0,0,N68+(R68-N68)*(1+in_rate)^0.5),R68*(1+in_rate)^0.5),R68)
A69: =B69&"|"&C69 | B69: 3E | C69: Alternative2 | D69: General maintenance | E69: FIXED | F69: 10000 | K69: 1 | N69: =IF(E69="FIXED",F69,IF(E69="PERCENT",G69*IFERROR(INDEX(Costs!$D$6:$F$36,MATCH(A69,Costs!$A$6:$A$36,0),MATCH(H69,Costs!$D$5:$F$5,0)),0),I69*J69)) | O69: =IF(ISNUMBER(L69),L69,K69) | P69: =IF(ISNUMBER(M69),MIN(M69,in_poa),in_poa) | Q69: =IF(P69<O69,0,INT((P69-O69)/K69)+1) | R69: =IF(Q69=0,0,IF(in_rate=0,N69*Q69,N69*(1+in_rate)^(-O69)*(1-(1+in_rate)^(-K69*Q69))/(1-(1+in_rate)^(-K69)))) | S69: =IF(in_timing="MID_YEAR",IF(O69=0,IF(Q69=0,0,N69+(R69-N69)*(1+in_rate)^0.5),R69*(1+in_rate)^0.5),R69)
A70: =B70&"|"&C70 | B70: 3E | C70: Alternative2 | D70: Inspection and trash removal | E70: RATE | I70: 4 | J70: 2494.045 | K70: 2 | N70: =IF(E70="FIXED",F70,IF(E70="PERCENT",G70*IFERROR(INDEX(Costs!$D$6:$F$36,MATCH(A70,Costs!$A$6:$A$36,0),MATCH(H70,Costs!$D$5:$F$5,0)),0),I70*J70)) | O70: =IF(ISNUMBER(L70),L70,K70) | P70: =IF(ISNUMBER(M70),MIN(M70,in_poa),in_poa) | Q70: =IF(P70<O70,0,INT((P70-O70)/K70)+1) | R70: =IF(Q70=0,0,IF(in_rate=0,N70*Q70,N70*(1+in_rate)^(-O70)*(1-(1+in_rate)^(-K70*Q70))/(1-(1+in_rate)^(-K70)))) | S70: =IF(in_timing="MID_YEAR",IF(O70=0,IF(Q70=0,0,N70+(R70-N70)*(1+in_rate)^0.5),R70*(1+in_rate)^0.5),R70)
A71: =B71&"|"&C71 | B71: 3E | C71: Alternative2 | D71: Invasive species control | E71: FIXED | F71: 15000 | K71: 10 | N71: =IF(E71="FIXED",F71,IF(E71="PERCENT",G71*IFERROR(INDEX(Costs!$D$6:$F$36,MATCH(A71,Costs!$A$6:$A$36,0),MATCH(H71,Costs!$D$5:$F$5,0)),0),I71*J71)) | O71: =IF(ISNUMBER(L71),L71,K71) | P71: =IF(ISNUMBER(M71),MIN(M71,in_poa),in_poa) | Q71: =IF(P71<O71,0,INT((P71-O71)/K71)+1) | R71: =IF(Q71=0,0,IF(in_rate=0,N71*Q71,N71*(1+in_rate)^(-O71)*(1-(1+in_rate)^(-K71*Q71))/(1-(1+in_rate)^(-K71)))) | S71: =IF(in_timing="MID_YEAR",IF(O71=0,IF(Q71=0,0,N71+(R71-N71)*(1+in_rate)^0.5),R71*(1+in_rate)^0.5),R71)
A72: =B72&"|"&C72 | B72: 3E | C72: Alternative2 | D72: Wood, rock and earth repair | E72: PERCENT | G72: 0.1 | H72: construction | K72: 25 | N72: =IF(E72="FIXED",F72,IF(E72="PERCENT",G72*IFERROR(INDEX(Costs!$D$6:$F$36,MATCH(A72,Costs!$A$6:$A$36,0),MATCH(H72,Costs!$D$5:$F$5,0)),0),I72*J72)) | O72: =IF(ISNUMBER(L72),L72,K72) | P72: =IF(ISNUMBER(M72),MIN(M72,in_poa),in_poa) | Q72: =IF(P72<O72,0,INT((P72-O72)/K72)+1) | R72: =IF(Q72=0,0,IF(in_rate=0,N72*Q72,N72*(1+in_rate)^(-O72)*(1-(1+in_rate)^(-K72*Q72))/(1-(1+in_rate)^(-K72)))) | S72: =IF(in_timing="MID_YEAR",IF(O72=0,IF(Q72=0,0,N72+(R72-N72)*(1+in_rate)^0.5),R72*(1+in_rate)^0.5),R72)
A73: =B73&"|"&C73 | B73: 3E | C73: Alternative3 | D73: General maintenance | E73: FIXED | F73: 10000 | K73: 1 | N73: =IF(E73="FIXED",F73,IF(E73="PERCENT",G73*IFERROR(INDEX(Costs!$D$6:$F$36,MATCH(A73,Costs!$A$6:$A$36,0),MATCH(H73,Costs!$D$5:$F$5,0)),0),I73*J73)) | O73: =IF(ISNUMBER(L73),L73,K73) | P73: =IF(ISNUMBER(M73),MIN(M73,in_poa),in_poa) | Q73: =IF(P73<O73,0,INT((P73-O73)/K73)+1) | R73: =IF(Q73=0,0,IF(in_rate=0,N73*Q73,N73*(1+in_rate)^(-O73)*(1-(1+in_rate)^(-K73*Q73))/(1-(1+in_rate)^(-K73)))) | S73: =IF(in_timing="MID_YEAR",IF(O73=0,IF(Q73=0,0,N73+(R73-N73)*(1+in_rate)^0.5),R73*(1+in_rate)^0.5),R73)
A74: =B74&"|"&C74 | B74: 3E | C74: Alternative3 | D74: Inspection and trash removal | E74: RATE | I74: 4 | J74: 2494.045 | K74: 2 | N74: =IF(E74="FIXED",F74,IF(E74="PERCENT",G74*IFERROR(INDEX(Costs!$D$6:$F$36,MATCH(A74,Costs!$A$6:$A$36,0),MATCH(H74,Costs!$D$5:$F$5,0)),0),I74*J74)) | O74: =IF(ISNUMBER(L74),L74,K74) | P74: =IF(ISNUMBER(M74),MIN(M74,in_poa),in_poa) | Q74: =IF(P74<O74,0,INT((P74-O74)/K74)+1) | R74: =IF(Q74=0,0,IF(in_rate=0,N74*Q74,N74*(1+in_rate)^(-O74)*(1-(1+in_rate)^(-K74*Q74))/(1-(1+in_rate)^(-K74)))) | S74: =IF(in_timing="MID_YEAR",IF(O74=0,IF(Q74=0,0,N74+(R74-N74)*(1+in_rate)^0.5),R74*(1+in_rate)^0.5),R74)
A75: =B75&"|"&C75 | B75: 3E | C75: Alternative3 | D75: Invasive species control | E75: FIXED | F75: 15000 | K75: 10 | N75: =IF(E75="FIXED",F75,IF(E75="PERCENT",G75*IFERROR(INDEX(Costs!$D$6:$F$36,MATCH(A75,Costs!$A$6:$A$36,0),MATCH(H75,Costs!$D$5:$F$5,0)),0),I75*J75)) | O75: =IF(ISNUMBER(L75),L75,K75) | P75: =IF(ISNUMBER(M75),MIN(M75,in_poa),in_poa) | Q75: =IF(P75<O75,0,INT((P75-O75)/K75)+1) | R75: =IF(Q75=0,0,IF(in_rate=0,N75*Q75,N75*(1+in_rate)^(-O75)*(1-(1+in_rate)^(-K75*Q75))/(1-(1+in_rate)^(-K75)))) | S75: =IF(in_timing="MID_YEAR",IF(O75=0,IF(Q75=0,0,N75+(R75-N75)*(1+in_rate)^0.5),R75*(1+in_rate)^0.5),R75)
A76: =B76&"|"&C76 | B76: 3E | C76: Alternative3 | D76: Wood, rock and earth repair | E76: PERCENT | G76: 0.1 | H76: construction | K76: 25 | N76: =IF(E76="FIXED",F76,IF(E76="PERCENT",G76*IFERROR(INDEX(Costs!$D$6:$F$36,MATCH(A76,Costs!$A$6:$A$36,0),MATCH(H76,Costs!$D$5:$F$5,0)),0),I76*J76)) | O76: =IF(ISNUMBER(L76),L76,K76) | P76: =IF(ISNUMBER(M76),MIN(M76,in_poa),in_poa) | Q76: =IF(P76<O76,0,INT((P76-O76)/K76)+1) | R76: =IF(Q76=0,0,IF(in_rate=0,N76*Q76,N76*(1+in_rate)^(-O76)*(1-(1+in_rate)^(-K76*Q76))/(1-(1+in_rate)^(-K76)))) | S76: =IF(in_timing="MID_YEAR",IF(O76=0,IF(Q76=0,0,N76+(R76-N76)*(1+in_rate)^0.5),R76*(1+in_rate)^0.5),R76)
A77: =B77&"|"&C77 | B77: 3F | C77: Alternative1 | D77: General maintenance | E77: FIXED | F77: 10000 | K77: 1 | N77: =IF(E77="FIXED",F77,IF(E77="PERCENT",G77*IFERROR(INDEX(Costs!$D$6:$F$36,MATCH(A77,Costs!$A$6:$A$36,0),MATCH(H77,Costs!$D$5:$F$5,0)),0),I77*J77)) | O77: =IF(ISNUMBER(L77),L77,K77) | P77: =IF(ISNUMBER(M77),MIN(M77,in_poa),in_poa) | Q77: =IF(P77<O77,0,INT((P77-O77)/K77)+1) | R77: =IF(Q77=0,0,IF(in_rate=0,N77*Q77,N77*(1+in_rate)^(-O77)*(1-(1+in_rate)^(-K77*Q77))/(1-(1+in_rate)^(-K77)))) | S77: =IF(in_timing="MID_YEAR",IF(O77=0,IF(Q77=0,0,N77+(R77-N77)*(1+in_rate)^0.5),R77*(1+in_rate)^0.5),R77)
A78: =B78&"|"&C78 | B78: 3F | C78: Alternative1 | D78: Inspection and trash removal | E78: RATE | I78: 4 | J78: 4381.5974 | K78: 2 | N78: =IF(E78="FIXED",F78,IF(E78="PERCENT",G78*IFERROR(INDEX(Costs!$D$6:$F$36,MATCH(A78,Costs!$A$6:$A$36,0),MATCH(H78,Costs!$D$5:$F$5,0)),0),I78*J78)) | O78: =IF(ISNUMBER(L78),L78,K78) | P78: =IF(ISNUMBER(M78),MIN(M78,in_poa),in_poa) | Q78: =IF(P78<O78,0,INT((P78-O78)/K78)+1) | R78: =IF(Q78=0,0,IF(in_rate=0,N78*Q78,N78*(1+in_rate)^(-O78)*(1-(1+in_rate)^(-K78*Q78))/(1-(1+in_rate)^(-K78)))) | S78: =IF(in_timing="MID_YEAR",IF(O78=0,IF(Q78=0,0,N78+(R78-N78)*(1+in_rate)^0.5),R78*(1+in_rate)^0.5),R78)
A79: =B79&"|"&C79 | B79: 3F | C79: Alternative1 | D79: Invasive species control | E79: FIXED | F79: 15000 | K79: 10 | N79: =IF(E79="FIXED",F79,IF(E79="PERCENT",G79*IFERROR(INDEX(Costs!$D$6:$F$36,MATCH(A79,Costs!$A$6:$A$36,0),MATCH(H79,Costs!$D$5:$F$5,0)),0),I79*J79)) | O79: =IF(ISNUMBER(L79),L79,K79) | P79: =IF(ISNUMBER(M79),MIN(M79,in_poa),in_poa) | Q79: =IF(P79<O79,0,INT((P79-O79)/K79)+1) | R79: =IF(Q79=0,0,IF(in_rate=0,N79*Q79,N79*(1+in_rate)^(-O79)*(1-(1+in_rate)^(-K79*Q79))/(1-(1+in_rate)^(-K79)))) | S79: =IF(in_timing="MID_YEAR",IF(O79=0,IF(Q79=0,0,N79+(R79-N79)*(1+in_rate)^0.5),R79*(1+in_rate)^0.5),R79)
A80: =B80&"|"&C80 | B80: 3F | C80: Alternative1 | D80: Wood, rock and earth repair | E80: PERCENT | G80: 0.1 | H80: construction | K80: 25 | N80: =IF(E80="FIXED",F80,IF(E80="PERCENT",G80*IFERROR(INDEX(Costs!$D$6:$F$36,MATCH(A80,Costs!$A$6:$A$36,0),MATCH(H80,Costs!$D$5:$F$5,0)),0),I80*J80)) | O80: =IF(ISNUMBER(L80),L80,K80) | P80: =IF(ISNUMBER(M80),MIN(M80,in_poa),in_poa) | Q80: =IF(P80<O80,0,INT((P80-O80)/K80)+1) | R80: =IF(Q80=0,0,IF(in_rate=0,N80*Q80,N80*(1+in_rate)^(-O80)*(1-(1+in_rate)^(-K80*Q80))/(1-(1+in_rate)^(-K80)))) | S80: =IF(in_timing="MID_YEAR",IF(O80=0,IF(Q80=0,0,N80+(R80-N80)*(1+in_rate)^0.5),R80*(1+in_rate)^0.5),R80)
A81: =B81&"|"&C81 | B81: 3F | C81: Alternative2 | D81: General maintenance | E81: FIXED | F81: 10000 | K81: 1 | N81: =IF(E81="FIXED",F81,IF(E81="PERCENT",G81*IFERROR(INDEX(Costs!$D$6:$F$36,MATCH(A81,Costs!$A$6:$A$36,0),MATCH(H81,Costs!$D$5:$F$5,0)),0),I81*J81)) | O81: =IF(ISNUMBER(L81),L81,K81) | P81: =IF(ISNUMBER(M81),MIN(M81,in_poa),in_poa) | Q81: =IF(P81<O81,0,INT((P81-O81)/K81)+1) | R81: =IF(Q81=0,0,IF(in_rate=0,N81*Q81,N81*(1+in_rate)^(-O81)*(1-(1+in_rate)^(-K81*Q81))/(1-(1+in_rate)^(-K81)))) | S81: =IF(in_timing="MID_YEAR",IF(O81=0,IF(Q81=0,0,N81+(R81-N81)*(1+in_rate)^0.5),R81*(1+in_rate)^0.5),R81)
A82: =B82&"|"&C82 | B82: 3F | C82: Alternative2 | D82: Inspection and trash removal | E82: RATE | I82: 4 | J82: 4381.5974 | K82: 2 | N82: =IF(E82="FIXED",F82,IF(E82="PERCENT",G82*IFERROR(INDEX(Costs!$D$6:$F$36,MATCH(A82,Costs!$A$6:$A$36,0),MATCH(H82,Costs!$D$5:$F$5,0)),0),I82*J82)) | O82: =IF(ISNUMBER(L82),L82,K82) | P82: =IF(ISNUMBER(M82),MIN(M82,in_poa),in_poa) | Q82: =IF(P82<O82,0,INT((P82-O82)/K82)+1) | R82: =IF(Q82=0,0,IF(in_rate=0,N82*Q82,N82*(1+in_rate)^(-O82)*(1-(1+in_rate)^(-K82*Q82))/(1-(1+in_rate)^(-K82)))) | S82: =IF(in_timing="MID_YEAR",IF(O82=0,IF(Q82=0,0,N82+(R82-N82)*(1+in_rate)^0.5),R82*(1+in_rate)^0.5),R82)
A83: =B83&"|"&C83 | B83: 3F | C83: Alternative2 | D83: Invasive species control | E83: FIXED | F83: 15000 | K83: 10 | N83: =IF(E83="FIXED",F83,IF(E83="PERCENT",G83*IFERROR(INDEX(Costs!$D$6:$F$36,MATCH(A83,Costs!$A$6:$A$36,0),MATCH(H83,Costs!$D$5:$F$5,0)),0),I83*J83)) | O83: =IF(ISNUMBER(L83),L83,K83) | P83: =IF(ISNUMBER(M83),MIN(M83,in_poa),in_poa) | Q83: =IF(P83<O83,0,INT((P83-O83)/K83)+1) | R83: =IF(Q83=0,0,IF(in_rate=0,N83*Q83,N83*(1+in_rate)^(-O83)*(1-(1+in_rate)^(-K83*Q83))/(1-(1+in_rate)^(-K83)))) | S83: =IF(in_timing="MID_YEAR",IF(O83=0,IF(Q83=0,0,N83+(R83-N83)*(1+in_rate)^0.5),R83*(1+in_rate)^0.5),R83)
A84: =B84&"|"&C84 | B84: 3F | C84: Alternative2 | D84: Wood, rock and earth repair | E84: PERCENT | G84: 0.1 | H84: construction | K84: 25 | N84: =IF(E84="FIXED",F84,IF(E84="PERCENT",G84*IFERROR(INDEX(Costs!$D$6:$F$36,MATCH(A84,Costs!$A$6:$A$36,0),MATCH(H84,Costs!$D$5:$F$5,0)),0),I84*J84)) | O84: =IF(ISNUMBER(L84),L84,K84) | P84: =IF(ISNUMBER(M84),MIN(M84,in_poa),in_poa) | Q84: =IF(P84<O84,0,INT((P84-O84)/K84)+1) | R84: =IF(Q84=0,0,IF(in_rate=0,N84*Q84,N84*(1+in_rate)^(-O84)*(1-(1+in_rate)^(-K84*Q84))/(1-(1+in_rate)^(-K84)))) | S84: =IF(in_timing="MID_YEAR",IF(O84=0,IF(Q84=0,0,N84+(R84-N84)*(1+in_rate)^0.5),R84*(1+in_rate)^0.5),R84)
A85: =B85&"|"&C85 | B85: 3F | C85: Alternative3 | D85: General maintenance | E85: FIXED | F85: 10000 | K85: 1 | N85: =IF(E85="FIXED",F85,IF(E85="PERCENT",G85*IFERROR(INDEX(Costs!$D$6:$F$36,MATCH(A85,Costs!$A$6:$A$36,0),MATCH(H85,Costs!$D$5:$F$5,0)),0),I85*J85)) | O85: =IF(ISNUMBER(L85),L85,K85) | P85: =IF(ISNUMBER(M85),MIN(M85,in_poa),in_poa) | Q85: =IF(P85<O85,0,INT((P85-O85)/K85)+1) | R85: =IF(Q85=0,0,IF(in_rate=0,N85*Q85,N85*(1+in_rate)^(-O85)*(1-(1+in_rate)^(-K85*Q85))/(1-(1+in_rate)^(-K85)))) | S85: =IF(in_timing="MID_YEAR",IF(O85=0,IF(Q85=0,0,N85+(R85-N85)*(1+in_rate)^0.5),R85*(1+in_rate)^0.5),R85)
A86: =B86&"|"&C86 | B86: 3F | C86: Alternative3 | D86: Inspection and trash removal | E86: RATE | I86: 4 | J86: 4381.5974 | K86: 2 | N86: =IF(E86="FIXED",F86,IF(E86="PERCENT",G86*IFERROR(INDEX(Costs!$D$6:$F$36,MATCH(A86,Costs!$A$6:$A$36,0),MATCH(H86,Costs!$D$5:$F$5,0)),0),I86*J86)) | O86: =IF(ISNUMBER(L86),L86,K86) | P86: =IF(ISNUMBER(M86),MIN(M86,in_poa),in_poa) | Q86: =IF(P86<O86,0,INT((P86-O86)/K86)+1) | R86: =IF(Q86=0,0,IF(in_rate=0,N86*Q86,N86*(1+in_rate)^(-O86)*(1-(1+in_rate)^(-K86*Q86))/(1-(1+in_rate)^(-K86)))) | S86: =IF(in_timing="MID_YEAR",IF(O86=0,IF(Q86=0,0,N86+(R86-N86)*(1+in_rate)^0.5),R86*(1+in_rate)^0.5),R86)
A87: =B87&"|"&C87 | B87: 3F | C87: Alternative3 | D87: Invasive species control | E87: FIXED | F87: 15000 | K87: 10 | N87: =IF(E87="FIXED",F87,IF(E87="PERCENT",G87*IFERROR(INDEX(Costs!$D$6:$F$36,MATCH(A87,Costs!$A$6:$A$36,0),MATCH(H87,Costs!$D$5:$F$5,0)),0),I87*J87)) | O87: =IF(ISNUMBER(L87),L87,K87) | P87: =IF(ISNUMBER(M87),MIN(M87,in_poa),in_poa) | Q87: =IF(P87<O87,0,INT((P87-O87)/K87)+1) | R87: =IF(Q87=0,0,IF(in_rate=0,N87*Q87,N87*(1+in_rate)^(-O87)*(1-(1+in_rate)^(-K87*Q87))/(1-(1+in_rate)^(-K87)))) | S87: =IF(in_timing="MID_YEAR",IF(O87=0,IF(Q87=0,0,N87+(R87-N87)*(1+in_rate)^0.5),R87*(1+in_rate)^0.5),R87)
A88: =B88&"|"&C88 | B88: 3F | C88: Alternative3 | D88: Wood, rock and earth repair | E88: PERCENT | G88: 0.1 | H88: construction | K88: 25 | N88: =IF(E88="FIXED",F88,IF(E88="PERCENT",G88*IFERROR(INDEX(Costs!$D$6:$F$36,MATCH(A88,Costs!$A$6:$A$36,0),MATCH(H88,Costs!$D$5:$F$5,0)),0),I88*J88)) | O88: =IF(ISNUMBER(L88),L88,K88) | P88: =IF(ISNUMBER(M88),MIN(M88,in_poa),in_poa) | Q88: =IF(P88<O88,0,INT((P88-O88)/K88)+1) | R88: =IF(Q88=0,0,IF(in_rate=0,N88*Q88,N88*(1+in_rate)^(-O88)*(1-(1+in_rate)^(-K88*Q88))/(1-(1+in_rate)^(-K88)))) | S88: =IF(in_timing="MID_YEAR",IF(O88=0,IF(Q88=0,0,N88+(R88-N88)*(1+in_rate)^0.5),R88*(1+in_rate)^0.5),R88)
A89: =B89&"|"&C89 | B89: 19A | C89: Alternative2 | D89: General maintenance | E89: FIXED | F89: 10000 | K89: 1 | N89: =IF(E89="FIXED",F89,IF(E89="PERCENT",G89*IFERROR(INDEX(Costs!$D$6:$F$36,MATCH(A89,Costs!$A$6:$A$36,0),MATCH(H89,Costs!$D$5:$F$5,0)),0),I89*J89)) | O89: =IF(ISNUMBER(L89),L89,K89) | P89: =IF(ISNUMBER(M89),MIN(M89,in_poa),in_poa) | Q89: =IF(P89<O89,0,INT((P89-O89)/K89)+1) | R89: =IF(Q89=0,0,IF(in_rate=0,N89*Q89,N89*(1+in_rate)^(-O89)*(1-(1+in_rate)^(-K89*Q89))/(1-(1+in_rate)^(-K89)))) | S89: =IF(in_timing="MID_YEAR",IF(O89=0,IF(Q89=0,0,N89+(R89-N89)*(1+in_rate)^0.5),R89*(1+in_rate)^0.5),R89)
A90: =B90&"|"&C90 | B90: 19A | C90: Alternative2 | D90: Inspection and trash removal | E90: RATE | I90: 4 | J90: 5026.9824 | K90: 2 | N90: =IF(E90="FIXED",F90,IF(E90="PERCENT",G90*IFERROR(INDEX(Costs!$D$6:$F$36,MATCH(A90,Costs!$A$6:$A$36,0),MATCH(H90,Costs!$D$5:$F$5,0)),0),I90*J90)) | O90: =IF(ISNUMBER(L90),L90,K90) | P90: =IF(ISNUMBER(M90),MIN(M90,in_poa),in_poa) | Q90: =IF(P90<O90,0,INT((P90-O90)/K90)+1) | R90: =IF(Q90=0,0,IF(in_rate=0,N90*Q90,N90*(1+in_rate)^(-O90)*(1-(1+in_rate)^(-K90*Q90))/(1-(1+in_rate)^(-K90)))) | S90: =IF(in_timing="MID_YEAR",IF(O90=0,IF(Q90=0,0,N90+(R90-N90)*(1+in_rate)^0.5),R90*(1+in_rate)^0.5),R90)
A91: =B91&"|"&C91 | B91: 19A | C91: Alternative2 | D91: Invasive species control | E91: FIXED | F91: 15000 | K91: 10 | N91: =IF(E91="FIXED",F91,IF(E91="PERCENT",G91*IFERROR(INDEX(Costs!$D$6:$F$36,MATCH(A91,Costs!$A$6:$A$36,0),MATCH(H91,Costs!$D$5:$F$5,0)),0),I91*J91)) | O91: =IF(ISNUMBER(L91),L91,K91) | P91: =IF(ISNUMBER(M91),MIN(M91,in_poa),in_poa) | Q91: =IF(P91<O91,0,INT((P91-O91)/K91)+1) | R91: =IF(Q91=0,0,IF(in_rate=0,N91*Q91,N91*(1+in_rate)^(-O91)*(1-(1+in_rate)^(-K91*Q91))/(1-(1+in_rate)^(-K91)))) | S91: =IF(in_timing="MID_YEAR",IF(O91=0,IF(Q91=0,0,N91+(R91-N91)*(1+in_rate)^0.5),R91*(1+in_rate)^0.5),R91)
A92: =B92&"|"&C92 | B92: 19A | C92: Alternative2 | D92: Wood, rock and earth repair | E92: PERCENT | G92: 0.1 | H92: construction | K92: 25 | N92: =IF(E92="FIXED",F92,IF(E92="PERCENT",G92*IFERROR(INDEX(Costs!$D$6:$F$36,MATCH(A92,Costs!$A$6:$A$36,0),MATCH(H92,Costs!$D$5:$F$5,0)),0),I92*J92)) | O92: =IF(ISNUMBER(L92),L92,K92) | P92: =IF(ISNUMBER(M92),MIN(M92,in_poa),in_poa) | Q92: =IF(P92<O92,0,INT((P92-O92)/K92)+1) | R92: =IF(Q92=0,0,IF(in_rate=0,N92*Q92,N92*(1+in_rate)^(-O92)*(1-(1+in_rate)^(-K92*Q92))/(1-(1+in_rate)^(-K92)))) | S92: =IF(in_timing="MID_YEAR",IF(O92=0,IF(Q92=0,0,N92+(R92-N92)*(1+in_rate)^0.5),R92*(1+in_rate)^0.5),R92)
A93: =B93&"|"&C93 | B93: 19A | C93: Alternative3 | D93: General maintenance | E93: FIXED | F93: 10000 | K93: 1 | N93: =IF(E93="FIXED",F93,IF(E93="PERCENT",G93*IFERROR(INDEX(Costs!$D$6:$F$36,MATCH(A93,Costs!$A$6:$A$36,0),MATCH(H93,Costs!$D$5:$F$5,0)),0),I93*J93)) | O93: =IF(ISNUMBER(L93),L93,K93) | P93: =IF(ISNUMBER(M93),MIN(M93,in_poa),in_poa) | Q93: =IF(P93<O93,0,INT((P93-O93)/K93)+1) | R93: =IF(Q93=0,0,IF(in_rate=0,N93*Q93,N93*(1+in_rate)^(-O93)*(1-(1+in_rate)^(-K93*Q93))/(1-(1+in_rate)^(-K93)))) | S93: =IF(in_timing="MID_YEAR",IF(O93=0,IF(Q93=0,0,N93+(R93-N93)*(1+in_rate)^0.5),R93*(1+in_rate)^0.5),R93)
A94: =B94&"|"&C94 | B94: 19A | C94: Alternative3 | D94: Inspection and trash removal | E94: RATE | I94: 4 | J94: 5026.9824 | K94: 2 | N94: =IF(E94="FIXED",F94,IF(E94="PERCENT",G94*IFERROR(INDEX(Costs!$D$6:$F$36,MATCH(A94,Costs!$A$6:$A$36,0),MATCH(H94,Costs!$D$5:$F$5,0)),0),I94*J94)) | O94: =IF(ISNUMBER(L94),L94,K94) | P94: =IF(ISNUMBER(M94),MIN(M94,in_poa),in_poa) | Q94: =IF(P94<O94,0,INT((P94-O94)/K94)+1) | R94: =IF(Q94=0,0,IF(in_rate=0,N94*Q94,N94*(1+in_rate)^(-O94)*(1-(1+in_rate)^(-K94*Q94))/(1-(1+in_rate)^(-K94)))) | S94: =IF(in_timing="MID_YEAR",IF(O94=0,IF(Q94=0,0,N94+(R94-N94)*(1+in_rate)^0.5),R94*(1+in_rate)^0.5),R94)
A95: =B95&"|"&C95 | B95: 19A | C95: Alternative3 | D95: Invasive species control | E95: FIXED | F95: 15000 | K95: 10 | N95: =IF(E95="FIXED",F95,IF(E95="PERCENT",G95*IFERROR(INDEX(Costs!$D$6:$F$36,MATCH(A95,Costs!$A$6:$A$36,0),MATCH(H95,Costs!$D$5:$F$5,0)),0),I95*J95)) | O95: =IF(ISNUMBER(L95),L95,K95) | P95: =IF(ISNUMBER(M95),MIN(M95,in_poa),in_poa) | Q95: =IF(P95<O95,0,INT((P95-O95)/K95)+1) | R95: =IF(Q95=0,0,IF(in_rate=0,N95*Q95,N95*(1+in_rate)^(-O95)*(1-(1+in_rate)^(-K95*Q95))/(1-(1+in_rate)^(-K95)))) | S95: =IF(in_timing="MID_YEAR",IF(O95=0,IF(Q95=0,0,N95+(R95-N95)*(1+in_rate)^0.5),R95*(1+in_rate)^0.5),R95)
A96: =B96&"|"&C96 | B96: 19A | C96: Alternative3 | D96: Wood, rock and earth repair | E96: PERCENT | G96: 0.1 | H96: construction | K96: 25 | N96: =IF(E96="FIXED",F96,IF(E96="PERCENT",G96*IFERROR(INDEX(Costs!$D$6:$F$36,MATCH(A96,Costs!$A$6:$A$36,0),MATCH(H96,Costs!$D$5:$F$5,0)),0),I96*J96)) | O96: =IF(ISNUMBER(L96),L96,K96) | P96: =IF(ISNUMBER(M96),MIN(M96,in_poa),in_poa) | Q96: =IF(P96<O96,0,INT((P96-O96)/K96)+1) | R96: =IF(Q96=0,0,IF(in_rate=0,N96*Q96,N96*(1+in_rate)^(-O96)*(1-(1+in_rate)^(-K96*Q96))/(1-(1+in_rate)^(-K96)))) | S96: =IF(in_timing="MID_YEAR",IF(O96=0,IF(Q96=0,0,N96+(R96-N96)*(1+in_rate)^0.5),R96*(1+in_rate)^0.5),R96)

Sheet Summary
A1: Summary of inputs to CE/ICA
A2: Lift is each alternative's AAHU above No Action; the CE/ICA cost is its average annual cost above No Action.
A4: Key | B4: Site | C4: Alternative | D4: Name | E4: No Action | F4: Outputs (AAHU) | G4: Lift (AAHU) | H4: Construction cost | I4: First costs | J4: Interest during construction | K4: OMRRR present value | L4: Average annual cost | M4: Cost above No Action | N4: Unit cost ($/AAHU)
A5: =B5&"|"&C5 | B5: 17F2M | C5: FWOP | D5: No Action | E5: 1 | F5: =SUMIFS(Benefits!$R$6:$R$98,Benefits!$A$6:$A$98,A5) | G5: =F5-$F$5 | H5: =Costs!D6 | I5: =SUM(Costs!D6:F6) | J5: =Costs!I6 | K5: =Costs!J6 | L5: =Costs!M6 | M5: =L5-$L$5 | N5: =IF(G5>0,M5/G5,"n/a")
A6: =B6&"|"&C6 | B6: 17F2M | C6: Alternative1 | D6: Alternative 1 | E6: 0 | F6: =SUMIFS(Benefits!$R$6:$R$98,Benefits!$A$6:$A$98,A6) | G6: =F6-$F$5 | H6: =Costs!D7 | I6: =SUM(Costs!D7:F7) | J6: =Costs!I7 | K6: =Costs!J7 | L6: =Costs!M7 | M6: =L6-$L$5 | N6: =IF(G6>0,M6/G6,"n/a")
A7: =B7&"|"&C7 | B7: 17F2M | C7: Alternative2 | D7: Alternative 2 | E7: 0 | F7: =SUMIFS(Benefits!$R$6:$R$98,Benefits!$A$6:$A$98,A7) | G7: =F7-$F$5 | H7: =Costs!D8 | I7: =SUM(Costs!D8:F8) | J7: =Costs!I8 | K7: =Costs!J8 | L7: =Costs!M8 | M7: =L7-$L$5 | N7: =IF(G7>0,M7/G7,"n/a")
A8: =B8&"|"&C8 | B8: 17F2M | C8: Alternative3 | D8: Alternative 3 | E8: 0 | F8: =SUMIFS(Benefits!$R$6:$R$98,Benefits!$A$6:$A$98,A8) | G8: =F8-$F$5 | H8: =Costs!D9 | I8: =SUM(Costs!D9:F9) | J8: =Costs!I9 | K8: =Costs!J9 | L8: =Costs!M9 | M8: =L8-$L$5 | N8: =IF(G8>0,M8/G8,"n/a")
A9: =B9&"|"&C9 | B9: 17D2E | C9: FWOP | D9: No Action | E9: 1 | F9: =SUMIFS(Benefits!$R$6:$R$98,Benefits!$A$6:$A$98,A9) | G9: =F9-$F$9 | H9: =Costs!D10 | I9: =SUM(Costs!D10:F10) | J9: =Costs!I10 | K9: =Costs!J10 | L9: =Costs!M10 | M9: =L9-$L$9 | N9: =IF(G9>0,M9/G9,"n/a")
A10: =B10&"|"&C10 | B10: 17D2E | C10: Alternative1 | D10: Alternative 1 | E10: 0 | F10: =SUMIFS(Benefits!$R$6:$R$98,Benefits!$A$6:$A$98,A10) | G10: =F10-$F$9 | H10: =Costs!D11 | I10: =SUM(Costs!D11:F11) | J10: =Costs!I11 | K10: =Costs!J11 | L10: =Costs!M11 | M10: =L10-$L$9 | N10: =IF(G10>0,M10/G10,"n/a")
A11: =B11&"|"&C11 | B11: 17D2E | C11: Alternative2 | D11: Alternative 2 | E11: 0 | F11: =SUMIFS(Benefits!$R$6:$R$98,Benefits!$A$6:$A$98,A11) | G11: =F11-$F$9 | H11: =Costs!D12 | I11: =SUM(Costs!D12:F12) | J11: =Costs!I12 | K11: =Costs!J12 | L11: =Costs!M12 | M11: =L11-$L$9 | N11: =IF(G11>0,M11/G11,"n/a")
A12: =B12&"|"&C12 | B12: 17D2E | C12: Alternative3 | D12: Alternative 3 | E12: 0 | F12: =SUMIFS(Benefits!$R$6:$R$98,Benefits!$A$6:$A$98,A12) | G12: =F12-$F$9 | H12: =Costs!D13 | I12: =SUM(Costs!D13:F13) | J12: =Costs!I13 | K12: =Costs!J13 | L12: =Costs!M13 | M12: =L12-$L$9 | N12: =IF(G12>0,M12/G12,"n/a")
A13: =B13&"|"&C13 | B13: 17B | C13: FWOP | D13: No Action | E13: 1 | F13: =SUMIFS(Benefits!$R$6:$R$98,Benefits!$A$6:$A$98,A13) | G13: =F13-$F$13 | H13: =Costs!D14 | I13: =SUM(Costs!D14:F14) | J13: =Costs!I14 | K13: =Costs!J14 | L13: =Costs!M14 | M13: =L13-$L$13 | N13: =IF(G13>0,M13/G13,"n/a")
A14: =B14&"|"&C14 | B14: 17B | C14: Alternative1 | D14: Alternative 1 | E14: 0 | F14: =SUMIFS(Benefits!$R$6:$R$98,Benefits!$A$6:$A$98,A14) | G14: =F14-$F$13 | H14: =Costs!D15 | I14: =SUM(Costs!D15:F15) | J14: =Costs!I15 | K14: =Costs!J15 | L14: =Costs!M15 | M14: =L14-$L$13 | N14: =IF(G14>0,M14/G14,"n/a")
A15: =B15&"|"&C15 | B15: 17B | C15: Alternative2 | D15: Alternative 2 | E15: 0 | F15: =SUMIFS(Benefits!$R$6:$R$98,Benefits!$A$6:$A$98,A15) | G15: =F15-$F$13 | H15: =Costs!D16 | I15: =SUM(Costs!D16:F16) | J15: =Costs!I16 | K15: =Costs!J16 | L15: =Costs!M16 | M15: =L15-$L$13 | N15: =IF(G15>0,M15/G15,"n/a")
A16: =B16&"|"&C16 | B16: 17B | C16: Alternative3 | D16: Alternative 3 | E16: 0 | F16: =SUMIFS(Benefits!$R$6:$R$98,Benefits!$A$6:$A$98,A16) | G16: =F16-$F$13 | H16: =Costs!D17 | I16: =SUM(Costs!D17:F17) | J16: =Costs!I17 | K16: =Costs!J17 | L16: =Costs!M17 | M16: =L16-$L$13 | N16: =IF(G16>0,M16/G16,"n/a")
A17: =B17&"|"&C17 | B17: 2A | C17: FWOP | D17: No Action | E17: 1 | F17: =SUMIFS(Benefits!$R$6:$R$98,Benefits!$A$6:$A$98,A17) | G17: =F17-$F$17 | H17: =Costs!D18 | I17: =SUM(Costs!D18:F18) | J17: =Costs!I18 | K17: =Costs!J18 | L17: =Costs!M18 | M17: =L17-$L$17 | N17: =IF(G17>0,M17/G17,"n/a")
A18: =B18&"|"&C18 | B18: 2A | C18: Alternative1 | D18: Alternative 1 | E18: 0 | F18: =SUMIFS(Benefits!$R$6:$R$98,Benefits!$A$6:$A$98,A18) | G18: =F18-$F$17 | H18: =Costs!D19 | I18: =SUM(Costs!D19:F19) | J18: =Costs!I19 | K18: =Costs!J19 | L18: =Costs!M19 | M18: =L18-$L$17 | N18: =IF(G18>0,M18/G18,"n/a")
A19: =B19&"|"&C19 | B19: 2A | C19: Alternative2 | D19: Alternative 2 | E19: 0 | F19: =SUMIFS(Benefits!$R$6:$R$98,Benefits!$A$6:$A$98,A19) | G19: =F19-$F$17 | H19: =Costs!D20 | I19: =SUM(Costs!D20:F20) | J19: =Costs!I20 | K19: =Costs!J20 | L19: =Costs!M20 | M19: =L19-$L$17 | N19: =IF(G19>0,M19/G19,"n/a")
A20: =B20&"|"&C20 | B20: 2A | C20: Alternative3 | D20: Alternative 3 | E20: 0 | F20: =SUMIFS(Benefits!$R$6:$R$98,Benefits!$A$6:$A$98,A20) | G20: =F20-$F$17 | H20: =Costs!D21 | I20: =SUM(Costs!D21:F21) | J20: =Costs!I21 | K20: =Costs!J21 | L20: =Costs!M21 | M20: =L20-$L$17 | N20: =IF(G20>0,M20/G20,"n/a")
A21: =B21&"|"&C21 | B21: 2B | C21: FWOP | D21: No Action | E21: 1 | F21: =SUMIFS(Benefits!$R$6:$R$98,Benefits!$A$6:$A$98,A21) | G21: =F21-$F$21 | H21: =Costs!D22 | I21: =SUM(Costs!D22:F22) | J21: =Costs!I22 | K21: =Costs!J22 | L21: =Costs!M22 | M21: =L21-$L$21 | N21: =IF(G21>0,M21/G21,"n/a")
A22: =B22&"|"&C22 | B22: 2B | C22: Alternative1 | D22: Alternative 1 | E22: 0 | F22: =SUMIFS(Benefits!$R$6:$R$98,Benefits!$A$6:$A$98,A22) | G22: =F22-$F$21 | H22: =Costs!D23 | I22: =SUM(Costs!D23:F23) | J22: =Costs!I23 | K22: =Costs!J23 | L22: =Costs!M23 | M22: =L22-$L$21 | N22: =IF(G22>0,M22/G22,"n/a")
A23: =B23&"|"&C23 | B23: 2B | C23: Alternative2 | D23: Alternative 2 | E23: 0 | F23: =SUMIFS(Benefits!$R$6:$R$98,Benefits!$A$6:$A$98,A23) | G23: =F23-$F$21 | H23: =Costs!D24 | I23: =SUM(Costs!D24:F24) | J23: =Costs!I24 | K23: =Costs!J24 | L23: =Costs!M24 | M23: =L23-$L$21 | N23: =IF(G23>0,M23/G23,"n/a")
A24: =B24&"|"&C24 | B24: 2B | C24: Alternative3 | D24: Alternative 3 | E24: 0 | F24: =SUMIFS(Benefits!$R$6:$R$98,Benefits!$A$6:$A$98,A24) | G24: =F24-$F$21 | H24: =Costs!D25 | I24: =SUM(Costs!D25:F25) | J24: =Costs!I25 | K24: =Costs!J25 | L24: =Costs!M25 | M24: =L24-$L$21 | N24: =IF(G24>0,M24/G24,"n/a")
A25: =B25&"|"&C25 | B25: 3E | C25: FWOP | D25: No Action | E25: 1 | F25: =SUMIFS(Benefits!$R$6:$R$98,Benefits!$A$6:$A$98,A25) | G25: =F25-$F$25 | H25: =Costs!D26 | I25: =SUM(Costs!D26:F26) | J25: =Costs!I26 | K25: =Costs!J26 | L25: =Costs!M26 | M25: =L25-$L$25 | N25: =IF(G25>0,M25/G25,"n/a")
A26: =B26&"|"&C26 | B26: 3E | C26: Alternative1 | D26: Alternative 1 | E26: 0 | F26: =SUMIFS(Benefits!$R$6:$R$98,Benefits!$A$6:$A$98,A26) | G26: =F26-$F$25 | H26: =Costs!D27 | I26: =SUM(Costs!D27:F27) | J26: =Costs!I27 | K26: =Costs!J27 | L26: =Costs!M27 | M26: =L26-$L$25 | N26: =IF(G26>0,M26/G26,"n/a")
A27: =B27&"|"&C27 | B27: 3E | C27: Alternative2 | D27: Alternative 2 | E27: 0 | F27: =SUMIFS(Benefits!$R$6:$R$98,Benefits!$A$6:$A$98,A27) | G27: =F27-$F$25 | H27: =Costs!D28 | I27: =SUM(Costs!D28:F28) | J27: =Costs!I28 | K27: =Costs!J28 | L27: =Costs!M28 | M27: =L27-$L$25 | N27: =IF(G27>0,M27/G27,"n/a")
A28: =B28&"|"&C28 | B28: 3E | C28: Alternative3 | D28: Alternative 3 | E28: 0 | F28: =SUMIFS(Benefits!$R$6:$R$98,Benefits!$A$6:$A$98,A28) | G28: =F28-$F$25 | H28: =Costs!D29 | I28: =SUM(Costs!D29:F29) | J28: =Costs!I29 | K28: =Costs!J29 | L28: =Costs!M29 | M28: =L28-$L$25 | N28: =IF(G28>0,M28/G28,"n/a")
A29: =B29&"|"&C29 | B29: 3F | C29: FWOP | D29: No Action | E29: 1 | F29: =SUMIFS(Benefits!$R$6:$R$98,Benefits!$A$6:$A$98,A29) | G29: =F29-$F$29 | H29: =Costs!D30 | I29: =SUM(Costs!D30:F30) | J29: =Costs!I30 | K29: =Costs!J30 | L29: =Costs!M30 | M29: =L29-$L$29 | N29: =IF(G29>0,M29/G29,"n/a")
A30: =B30&"|"&C30 | B30: 3F | C30: Alternative1 | D30: Alternative 1 | E30: 0 | F30: =SUMIFS(Benefits!$R$6:$R$98,Benefits!$A$6:$A$98,A30) | G30: =F30-$F$29 | H30: =Costs!D31 | I30: =SUM(Costs!D31:F31) | J30: =Costs!I31 | K30: =Costs!J31 | L30: =Costs!M31 | M30: =L30-$L$29 | N30: =IF(G30>0,M30/G30,"n/a")
A31: =B31&"|"&C31 | B31: 3F | C31: Alternative2 | D31: Alternative 2 | E31: 0 | F31: =SUMIFS(Benefits!$R$6:$R$98,Benefits!$A$6:$A$98,A31) | G31: =F31-$F$29 | H31: =Costs!D32 | I31: =SUM(Costs!D32:F32) | J31: =Costs!I32 | K31: =Costs!J32 | L31: =Costs!M32 | M31: =L31-$L$29 | N31: =IF(G31>0,M31/G31,"n/a")
A32: =B32&"|"&C32 | B32: 3F | C32: Alternative3 | D32: Alternative 3 | E32: 0 | F32: =SUMIFS(Benefits!$R$6:$R$98,Benefits!$A$6:$A$98,A32) | G32: =F32-$F$29 | H32: =Costs!D33 | I32: =SUM(Costs!D33:F33) | J32: =Costs!I33 | K32: =Costs!J33 | L32: =Costs!M33 | M32: =L32-$L$29 | N32: =IF(G32>0,M32/G32,"n/a")
A33: =B33&"|"&C33 | B33: 19A | C33: FWOP | D33: No Action | E33: 1 | F33: =SUMIFS(Benefits!$R$6:$R$98,Benefits!$A$6:$A$98,A33) | G33: =F33-$F$33 | H33: =Costs!D34 | I33: =SUM(Costs!D34:F34) | J33: =Costs!I34 | K33: =Costs!J34 | L33: =Costs!M34 | M33: =L33-$L$33 | N33: =IF(G33>0,M33/G33,"n/a")
A34: =B34&"|"&C34 | B34: 19A | C34: Alternative2 | D34: Alternative 2 | E34: 0 | F34: =SUMIFS(Benefits!$R$6:$R$98,Benefits!$A$6:$A$98,A34) | G34: =F34-$F$33 | H34: =Costs!D35 | I34: =SUM(Costs!D35:F35) | J34: =Costs!I35 | K34: =Costs!J35 | L34: =Costs!M35 | M34: =L34-$L$33 | N34: =IF(G34>0,M34/G34,"n/a")
A35: =B35&"|"&C35 | B35: 19A | C35: Alternative3 | D35: Alternative 3 | E35: 0 | F35: =SUMIFS(Benefits!$R$6:$R$98,Benefits!$A$6:$A$98,A35) | G35: =F35-$F$33 | H35: =Costs!D36 | I35: =SUM(Costs!D36:F36) | J35: =Costs!I36 | K35: =Costs!J36 | L35: =Costs!M36 | M35: =L35-$L$33 | N35: =IF(G35>0,M35/G35,"n/a")

Sheet Site CE-ICA
A1: Site-by-site CE/ICA
A2: Cost-effective: no alternative gives the same output for less, or more output for no more. Best buy: on the lower hull from No Action (IWR Planning Suite II rules).
A4: Key | B4: Site | C4: Alternative | D4: Name | E4: No Action | F4: Ordinal | G4: Lift (AAHU) | H4: Cost above No Action | I4: Lift (scaled) | J4: Cost (scaled) | K4: Dominated by | L4: Cost-effective | M4: Candidate | N4: Slope in (max) | O4: Slope out (min) | P4: Best buy | Q4: Best-buy step | R4: Previous lift (scaled) | S4: Previous cost (scaled) | T4: Incremental output | U4: Incremental cost | V4: Incremental cost per unit | W4: Unit cost | X4: Recommended
B5: 17F2M Golf course concrete channel
A6: =B6&"|"&C6 | B6: 17F2M | C6: FWOP | D6: No Action | E6: 1 | F6: 1 | G6: =Summary!G5 | H6: =Summary!M5 | I6: =ROUND(G6*10^in_out_dp,0) | J6: =ROUND(H6*10^in_cost_dp,0) | K6: =SUMPRODUCT(($I$6:$I$9=I6)*($J$6:$J$9<J6)+($I$6:$I$9>I6)*($J$6:$J$9<=J6)) | L6: =IF(OR(E6=1,K6=0),1,0) | M6: =IF(AND(L6=1,E6=0,I6>0),1,0) | N6: =IF(M6=1,MAX(J6/I6,SUMPRODUCT(MAX(((J6-$J$6:$J$9)*($M$6:$M$9*($I$6:$I$9<I6)))/((I6-$I$6:$I$9)*($M$6:$M$9*($I$6:$I$9<I6))+1-($M$6:$M$9*($I$6:$I$9<I6)))-(1-($M$6:$M$9*($I$6:$I$9<I6)))*1E+300))),0) | O6: =IF(M6=1,SUMPRODUCT(MIN(((($J$6:$J$9-J6)*($M$6:$M$9*($I$6:$I$9>I6)))/(($I$6:$I$9-I6)*($M$6:$M$9*($I$6:$I$9>I6))+1-($M$6:$M$9*($I$6:$I$9>I6)))+(1-($M$6:$M$9*($I$6:$I$9>I6)))*1E+300))),0) | P6: =IF(E6=1,1,IF(AND(M6=1,N6<=O6),1,0)) | Q6: =IF(P6=1,1+SUMPRODUCT($P$6:$P$9*(($I$6:$I$9<I6)+($I$6:$I$9=I6)*($F$6:$F$9<F6))),0) | R6: =IF(Q6<=1,0,SUMPRODUCT(($Q$6:$Q$9=Q6-1)*$I$6:$I$9)) | S6: =IF(Q6<=1,0,SUMPRODUCT(($Q$6:$Q$9=Q6-1)*$J$6:$J$9)) | T6: =IF(Q6=0,"",(I6-R6)/10^in_out_dp) | U6: =IF(Q6=0,"",(J6-S6)/10^in_cost_dp) | V6: =IF(Q6=0,"",IF(I6=R6,0,U6/T6)) | W6: =IF(I6>0,(J6/10^in_cost_dp)/(I6/10^in_out_dp),"n/a") | X6: =IF(Sites!$C$5=C6,1,0)
A7: =B7&"|"&C7 | B7: 17F2M | C7: Alternative1 | D7: Alternative 1 | E7: 0 | F7: 2 | G7: =Summary!G6 | H7: =Summary!M6 | I7: =ROUND(G7*10^in_out_dp,0) | J7: =ROUND(H7*10^in_cost_dp,0) | K7: =SUMPRODUCT(($I$6:$I$9=I7)*($J$6:$J$9<J7)+($I$6:$I$9>I7)*($J$6:$J$9<=J7)) | L7: =IF(OR(E7=1,K7=0),1,0) | M7: =IF(AND(L7=1,E7=0,I7>0),1,0) | N7: =IF(M7=1,MAX(J7/I7,SUMPRODUCT(MAX(((J7-$J$6:$J$9)*($M$6:$M$9*($I$6:$I$9<I7)))/((I7-$I$6:$I$9)*($M$6:$M$9*($I$6:$I$9<I7))+1-($M$6:$M$9*($I$6:$I$9<I7)))-(1-($M$6:$M$9*($I$6:$I$9<I7)))*1E+300))),0) | O7: =IF(M7=1,SUMPRODUCT(MIN(((($J$6:$J$9-J7)*($M$6:$M$9*($I$6:$I$9>I7)))/(($I$6:$I$9-I7)*($M$6:$M$9*($I$6:$I$9>I7))+1-($M$6:$M$9*($I$6:$I$9>I7)))+(1-($M$6:$M$9*($I$6:$I$9>I7)))*1E+300))),0) | P7: =IF(E7=1,1,IF(AND(M7=1,N7<=O7),1,0)) | Q7: =IF(P7=1,1+SUMPRODUCT($P$6:$P$9*(($I$6:$I$9<I7)+($I$6:$I$9=I7)*($F$6:$F$9<F7))),0) | R7: =IF(Q7<=1,0,SUMPRODUCT(($Q$6:$Q$9=Q7-1)*$I$6:$I$9)) | S7: =IF(Q7<=1,0,SUMPRODUCT(($Q$6:$Q$9=Q7-1)*$J$6:$J$9)) | T7: =IF(Q7=0,"",(I7-R7)/10^in_out_dp) | U7: =IF(Q7=0,"",(J7-S7)/10^in_cost_dp) | V7: =IF(Q7=0,"",IF(I7=R7,0,U7/T7)) | W7: =IF(I7>0,(J7/10^in_cost_dp)/(I7/10^in_out_dp),"n/a") | X7: =IF(Sites!$C$5=C7,1,0)
A8: =B8&"|"&C8 | B8: 17F2M | C8: Alternative2 | D8: Alternative 2 | E8: 0 | F8: 3 | G8: =Summary!G7 | H8: =Summary!M7 | I8: =ROUND(G8*10^in_out_dp,0) | J8: =ROUND(H8*10^in_cost_dp,0) | K8: =SUMPRODUCT(($I$6:$I$9=I8)*($J$6:$J$9<J8)+($I$6:$I$9>I8)*($J$6:$J$9<=J8)) | L8: =IF(OR(E8=1,K8=0),1,0) | M8: =IF(AND(L8=1,E8=0,I8>0),1,0) | N8: =IF(M8=1,MAX(J8/I8,SUMPRODUCT(MAX(((J8-$J$6:$J$9)*($M$6:$M$9*($I$6:$I$9<I8)))/((I8-$I$6:$I$9)*($M$6:$M$9*($I$6:$I$9<I8))+1-($M$6:$M$9*($I$6:$I$9<I8)))-(1-($M$6:$M$9*($I$6:$I$9<I8)))*1E+300))),0) | O8: =IF(M8=1,SUMPRODUCT(MIN(((($J$6:$J$9-J8)*($M$6:$M$9*($I$6:$I$9>I8)))/(($I$6:$I$9-I8)*($M$6:$M$9*($I$6:$I$9>I8))+1-($M$6:$M$9*($I$6:$I$9>I8)))+(1-($M$6:$M$9*($I$6:$I$9>I8)))*1E+300))),0) | P8: =IF(E8=1,1,IF(AND(M8=1,N8<=O8),1,0)) | Q8: =IF(P8=1,1+SUMPRODUCT($P$6:$P$9*(($I$6:$I$9<I8)+($I$6:$I$9=I8)*($F$6:$F$9<F8))),0) | R8: =IF(Q8<=1,0,SUMPRODUCT(($Q$6:$Q$9=Q8-1)*$I$6:$I$9)) | S8: =IF(Q8<=1,0,SUMPRODUCT(($Q$6:$Q$9=Q8-1)*$J$6:$J$9)) | T8: =IF(Q8=0,"",(I8-R8)/10^in_out_dp) | U8: =IF(Q8=0,"",(J8-S8)/10^in_cost_dp) | V8: =IF(Q8=0,"",IF(I8=R8,0,U8/T8)) | W8: =IF(I8>0,(J8/10^in_cost_dp)/(I8/10^in_out_dp),"n/a") | X8: =IF(Sites!$C$5=C8,1,0)
A9: =B9&"|"&C9 | B9: 17F2M | C9: Alternative3 | D9: Alternative 3 | E9: 0 | F9: 4 | G9: =Summary!G8 | H9: =Summary!M8 | I9: =ROUND(G9*10^in_out_dp,0) | J9: =ROUND(H9*10^in_cost_dp,0) | K9: =SUMPRODUCT(($I$6:$I$9=I9)*($J$6:$J$9<J9)+($I$6:$I$9>I9)*($J$6:$J$9<=J9)) | L9: =IF(OR(E9=1,K9=0),1,0) | M9: =IF(AND(L9=1,E9=0,I9>0),1,0) | N9: =IF(M9=1,MAX(J9/I9,SUMPRODUCT(MAX(((J9-$J$6:$J$9)*($M$6:$M$9*($I$6:$I$9<I9)))/((I9-$I$6:$I$9)*($M$6:$M$9*($I$6:$I$9<I9))+1-($M$6:$M$9*($I$6:$I$9<I9)))-(1-($M$6:$M$9*($I$6:$I$9<I9)))*1E+300))),0) | O9: =IF(M9=1,SUMPRODUCT(MIN(((($J$6:$J$9-J9)*($M$6:$M$9*($I$6:$I$9>I9)))/(($I$6:$I$9-I9)*($M$6:$M$9*($I$6:$I$9>I9))+1-($M$6:$M$9*($I$6:$I$9>I9)))+(1-($M$6:$M$9*($I$6:$I$9>I9)))*1E+300))),0) | P9: =IF(E9=1,1,IF(AND(M9=1,N9<=O9),1,0)) | Q9: =IF(P9=1,1+SUMPRODUCT($P$6:$P$9*(($I$6:$I$9<I9)+($I$6:$I$9=I9)*($F$6:$F$9<F9))),0) | R9: =IF(Q9<=1,0,SUMPRODUCT(($Q$6:$Q$9=Q9-1)*$I$6:$I$9)) | S9: =IF(Q9<=1,0,SUMPRODUCT(($Q$6:$Q$9=Q9-1)*$J$6:$J$9)) | T9: =IF(Q9=0,"",(I9-R9)/10^in_out_dp) | U9: =IF(Q9=0,"",(J9-S9)/10^in_cost_dp) | V9: =IF(Q9=0,"",IF(I9=R9,0,U9/T9)) | W9: =IF(I9>0,(J9/10^in_cost_dp)/(I9/10^in_out_dp),"n/a") | X9: =IF(Sites!$C$5=C9,1,0)
B11: 17D2E Concrete channel to Beecher Road
A12: =B12&"|"&C12 | B12: 17D2E | C12: FWOP | D12: No Action | E12: 1 | F12: 1 | G12: =Summary!G9 | H12: =Summary!M9 | I12: =ROUND(G12*10^in_out_dp,0) | J12: =ROUND(H12*10^in_cost_dp,0) | K12: =SUMPRODUCT(($I$12:$I$15=I12)*($J$12:$J$15<J12)+($I$12:$I$15>I12)*($J$12:$J$15<=J12)) | L12: =IF(OR(E12=1,K12=0),1,0) | M12: =IF(AND(L12=1,E12=0,I12>0),1,0) | N12: =IF(M12=1,MAX(J12/I12,SUMPRODUCT(MAX(((J12-$J$12:$J$15)*($M$12:$M$15*($I$12:$I$15<I12)))/((I12-$I$12:$I$15)*($M$12:$M$15*($I$12:$I$15<I12))+1-($M$12:$M$15*($I$12:$I$15<I12)))-(1-($M$12:$M$15*($I$12:$I$15<I12)))*1E+300))),0) | O12: =IF(M12=1,SUMPRODUCT(MIN(((($J$12:$J$15-J12)*($M$12:$M$15*($I$12:$I$15>I12)))/(($I$12:$I$15-I12)*($M$12:$M$15*($I$12:$I$15>I12))+1-($M$12:$M$15*($I$12:$I$15>I12)))+(1-($M$12:$M$15*($I$12:$I$15>I12)))*1E+300))),0) | P12: =IF(E12=1,1,IF(AND(M12=1,N12<=O12),1,0)) | Q12: =IF(P12=1,1+SUMPRODUCT($P$12:$P$15*(($I$12:$I$15<I12)+($I$12:$I$15=I12)*($F$12:$F$15<F12))),0) | R12: =IF(Q12<=1,0,SUMPRODUCT(($Q$12:$Q$15=Q12-1)*$I$12:$I$15)) | S12: =IF(Q12<=1,0,SUMPRODUCT(($Q$12:$Q$15=Q12-1)*$J$12:$J$15)) | T12: =IF(Q12=0,"",(I12-R12)/10^in_out_dp) | U12: =IF(Q12=0,"",(J12-S12)/10^in_cost_dp) | V12: =IF(Q12=0,"",IF(I12=R12,0,U12/T12)) | W12: =IF(I12>0,(J12/10^in_cost_dp)/(I12/10^in_out_dp),"n/a") | X12: =IF(Sites!$C$6=C12,1,0)
A13: =B13&"|"&C13 | B13: 17D2E | C13: Alternative1 | D13: Alternative 1 | E13: 0 | F13: 2 | G13: =Summary!G10 | H13: =Summary!M10 | I13: =ROUND(G13*10^in_out_dp,0) | J13: =ROUND(H13*10^in_cost_dp,0) | K13: =SUMPRODUCT(($I$12:$I$15=I13)*($J$12:$J$15<J13)+($I$12:$I$15>I13)*($J$12:$J$15<=J13)) | L13: =IF(OR(E13=1,K13=0),1,0) | M13: =IF(AND(L13=1,E13=0,I13>0),1,0) | N13: =IF(M13=1,MAX(J13/I13,SUMPRODUCT(MAX(((J13-$J$12:$J$15)*($M$12:$M$15*($I$12:$I$15<I13)))/((I13-$I$12:$I$15)*($M$12:$M$15*($I$12:$I$15<I13))+1-($M$12:$M$15*($I$12:$I$15<I13)))-(1-($M$12:$M$15*($I$12:$I$15<I13)))*1E+300))),0) | O13: =IF(M13=1,SUMPRODUCT(MIN(((($J$12:$J$15-J13)*($M$12:$M$15*($I$12:$I$15>I13)))/(($I$12:$I$15-I13)*($M$12:$M$15*($I$12:$I$15>I13))+1-($M$12:$M$15*($I$12:$I$15>I13)))+(1-($M$12:$M$15*($I$12:$I$15>I13)))*1E+300))),0) | P13: =IF(E13=1,1,IF(AND(M13=1,N13<=O13),1,0)) | Q13: =IF(P13=1,1+SUMPRODUCT($P$12:$P$15*(($I$12:$I$15<I13)+($I$12:$I$15=I13)*($F$12:$F$15<F13))),0) | R13: =IF(Q13<=1,0,SUMPRODUCT(($Q$12:$Q$15=Q13-1)*$I$12:$I$15)) | S13: =IF(Q13<=1,0,SUMPRODUCT(($Q$12:$Q$15=Q13-1)*$J$12:$J$15)) | T13: =IF(Q13=0,"",(I13-R13)/10^in_out_dp) | U13: =IF(Q13=0,"",(J13-S13)/10^in_cost_dp) | V13: =IF(Q13=0,"",IF(I13=R13,0,U13/T13)) | W13: =IF(I13>0,(J13/10^in_cost_dp)/(I13/10^in_out_dp),"n/a") | X13: =IF(Sites!$C$6=C13,1,0)
A14: =B14&"|"&C14 | B14: 17D2E | C14: Alternative2 | D14: Alternative 2 | E14: 0 | F14: 3 | G14: =Summary!G11 | H14: =Summary!M11 | I14: =ROUND(G14*10^in_out_dp,0) | J14: =ROUND(H14*10^in_cost_dp,0) | K14: =SUMPRODUCT(($I$12:$I$15=I14)*($J$12:$J$15<J14)+($I$12:$I$15>I14)*($J$12:$J$15<=J14)) | L14: =IF(OR(E14=1,K14=0),1,0) | M14: =IF(AND(L14=1,E14=0,I14>0),1,0) | N14: =IF(M14=1,MAX(J14/I14,SUMPRODUCT(MAX(((J14-$J$12:$J$15)*($M$12:$M$15*($I$12:$I$15<I14)))/((I14-$I$12:$I$15)*($M$12:$M$15*($I$12:$I$15<I14))+1-($M$12:$M$15*($I$12:$I$15<I14)))-(1-($M$12:$M$15*($I$12:$I$15<I14)))*1E+300))),0) | O14: =IF(M14=1,SUMPRODUCT(MIN(((($J$12:$J$15-J14)*($M$12:$M$15*($I$12:$I$15>I14)))/(($I$12:$I$15-I14)*($M$12:$M$15*($I$12:$I$15>I14))+1-($M$12:$M$15*($I$12:$I$15>I14)))+(1-($M$12:$M$15*($I$12:$I$15>I14)))*1E+300))),0) | P14: =IF(E14=1,1,IF(AND(M14=1,N14<=O14),1,0)) | Q14: =IF(P14=1,1+SUMPRODUCT($P$12:$P$15*(($I$12:$I$15<I14)+($I$12:$I$15=I14)*($F$12:$F$15<F14))),0) | R14: =IF(Q14<=1,0,SUMPRODUCT(($Q$12:$Q$15=Q14-1)*$I$12:$I$15)) | S14: =IF(Q14<=1,0,SUMPRODUCT(($Q$12:$Q$15=Q14-1)*$J$12:$J$15)) | T14: =IF(Q14=0,"",(I14-R14)/10^in_out_dp) | U14: =IF(Q14=0,"",(J14-S14)/10^in_cost_dp) | V14: =IF(Q14=0,"",IF(I14=R14,0,U14/T14)) | W14: =IF(I14>0,(J14/10^in_cost_dp)/(I14/10^in_out_dp),"n/a") | X14: =IF(Sites!$C$6=C14,1,0)
A15: =B15&"|"&C15 | B15: 17D2E | C15: Alternative3 | D15: Alternative 3 | E15: 0 | F15: 4 | G15: =Summary!G12 | H15: =Summary!M12 | I15: =ROUND(G15*10^in_out_dp,0) | J15: =ROUND(H15*10^in_cost_dp,0) | K15: =SUMPRODUCT(($I$12:$I$15=I15)*($J$12:$J$15<J15)+($I$12:$I$15>I15)*($J$12:$J$15<=J15)) | L15: =IF(OR(E15=1,K15=0),1,0) | M15: =IF(AND(L15=1,E15=0,I15>0),1,0) | N15: =IF(M15=1,MAX(J15/I15,SUMPRODUCT(MAX(((J15-$J$12:$J$15)*($M$12:$M$15*($I$12:$I$15<I15)))/((I15-$I$12:$I$15)*($M$12:$M$15*($I$12:$I$15<I15))+1-($M$12:$M$15*($I$12:$I$15<I15)))-(1-($M$12:$M$15*($I$12:$I$15<I15)))*1E+300))),0) | O15: =IF(M15=1,SUMPRODUCT(MIN(((($J$12:$J$15-J15)*($M$12:$M$15*($I$12:$I$15>I15)))/(($I$12:$I$15-I15)*($M$12:$M$15*($I$12:$I$15>I15))+1-($M$12:$M$15*($I$12:$I$15>I15)))+(1-($M$12:$M$15*($I$12:$I$15>I15)))*1E+300))),0) | P15: =IF(E15=1,1,IF(AND(M15=1,N15<=O15),1,0)) | Q15: =IF(P15=1,1+SUMPRODUCT($P$12:$P$15*(($I$12:$I$15<I15)+($I$12:$I$15=I15)*($F$12:$F$15<F15))),0) | R15: =IF(Q15<=1,0,SUMPRODUCT(($Q$12:$Q$15=Q15-1)*$I$12:$I$15)) | S15: =IF(Q15<=1,0,SUMPRODUCT(($Q$12:$Q$15=Q15-1)*$J$12:$J$15)) | T15: =IF(Q15=0,"",(I15-R15)/10^in_out_dp) | U15: =IF(Q15=0,"",(J15-S15)/10^in_cost_dp) | V15: =IF(Q15=0,"",IF(I15=R15,0,U15/T15)) | W15: =IF(I15>0,(J15/10^in_cost_dp)/(I15/10^in_out_dp),"n/a") | X15: =IF(Sites!$C$6=C15,1,0)
B17: 17B Southwest Connector Trail reach
A18: =B18&"|"&C18 | B18: 17B | C18: FWOP | D18: No Action | E18: 1 | F18: 1 | G18: =Summary!G13 | H18: =Summary!M13 | I18: =ROUND(G18*10^in_out_dp,0) | J18: =ROUND(H18*10^in_cost_dp,0) | K18: =SUMPRODUCT(($I$18:$I$21=I18)*($J$18:$J$21<J18)+($I$18:$I$21>I18)*($J$18:$J$21<=J18)) | L18: =IF(OR(E18=1,K18=0),1,0) | M18: =IF(AND(L18=1,E18=0,I18>0),1,0) | N18: =IF(M18=1,MAX(J18/I18,SUMPRODUCT(MAX(((J18-$J$18:$J$21)*($M$18:$M$21*($I$18:$I$21<I18)))/((I18-$I$18:$I$21)*($M$18:$M$21*($I$18:$I$21<I18))+1-($M$18:$M$21*($I$18:$I$21<I18)))-(1-($M$18:$M$21*($I$18:$I$21<I18)))*1E+300))),0) | O18: =IF(M18=1,SUMPRODUCT(MIN(((($J$18:$J$21-J18)*($M$18:$M$21*($I$18:$I$21>I18)))/(($I$18:$I$21-I18)*($M$18:$M$21*($I$18:$I$21>I18))+1-($M$18:$M$21*($I$18:$I$21>I18)))+(1-($M$18:$M$21*($I$18:$I$21>I18)))*1E+300))),0) | P18: =IF(E18=1,1,IF(AND(M18=1,N18<=O18),1,0)) | Q18: =IF(P18=1,1+SUMPRODUCT($P$18:$P$21*(($I$18:$I$21<I18)+($I$18:$I$21=I18)*($F$18:$F$21<F18))),0) | R18: =IF(Q18<=1,0,SUMPRODUCT(($Q$18:$Q$21=Q18-1)*$I$18:$I$21)) | S18: =IF(Q18<=1,0,SUMPRODUCT(($Q$18:$Q$21=Q18-1)*$J$18:$J$21)) | T18: =IF(Q18=0,"",(I18-R18)/10^in_out_dp) | U18: =IF(Q18=0,"",(J18-S18)/10^in_cost_dp) | V18: =IF(Q18=0,"",IF(I18=R18,0,U18/T18)) | W18: =IF(I18>0,(J18/10^in_cost_dp)/(I18/10^in_out_dp),"n/a") | X18: =IF(Sites!$C$7=C18,1,0)
A19: =B19&"|"&C19 | B19: 17B | C19: Alternative1 | D19: Alternative 1 | E19: 0 | F19: 2 | G19: =Summary!G14 | H19: =Summary!M14 | I19: =ROUND(G19*10^in_out_dp,0) | J19: =ROUND(H19*10^in_cost_dp,0) | K19: =SUMPRODUCT(($I$18:$I$21=I19)*($J$18:$J$21<J19)+($I$18:$I$21>I19)*($J$18:$J$21<=J19)) | L19: =IF(OR(E19=1,K19=0),1,0) | M19: =IF(AND(L19=1,E19=0,I19>0),1,0) | N19: =IF(M19=1,MAX(J19/I19,SUMPRODUCT(MAX(((J19-$J$18:$J$21)*($M$18:$M$21*($I$18:$I$21<I19)))/((I19-$I$18:$I$21)*($M$18:$M$21*($I$18:$I$21<I19))+1-($M$18:$M$21*($I$18:$I$21<I19)))-(1-($M$18:$M$21*($I$18:$I$21<I19)))*1E+300))),0) | O19: =IF(M19=1,SUMPRODUCT(MIN(((($J$18:$J$21-J19)*($M$18:$M$21*($I$18:$I$21>I19)))/(($I$18:$I$21-I19)*($M$18:$M$21*($I$18:$I$21>I19))+1-($M$18:$M$21*($I$18:$I$21>I19)))+(1-($M$18:$M$21*($I$18:$I$21>I19)))*1E+300))),0) | P19: =IF(E19=1,1,IF(AND(M19=1,N19<=O19),1,0)) | Q19: =IF(P19=1,1+SUMPRODUCT($P$18:$P$21*(($I$18:$I$21<I19)+($I$18:$I$21=I19)*($F$18:$F$21<F19))),0) | R19: =IF(Q19<=1,0,SUMPRODUCT(($Q$18:$Q$21=Q19-1)*$I$18:$I$21)) | S19: =IF(Q19<=1,0,SUMPRODUCT(($Q$18:$Q$21=Q19-1)*$J$18:$J$21)) | T19: =IF(Q19=0,"",(I19-R19)/10^in_out_dp) | U19: =IF(Q19=0,"",(J19-S19)/10^in_cost_dp) | V19: =IF(Q19=0,"",IF(I19=R19,0,U19/T19)) | W19: =IF(I19>0,(J19/10^in_cost_dp)/(I19/10^in_out_dp),"n/a") | X19: =IF(Sites!$C$7=C19,1,0)
A20: =B20&"|"&C20 | B20: 17B | C20: Alternative2 | D20: Alternative 2 | E20: 0 | F20: 3 | G20: =Summary!G15 | H20: =Summary!M15 | I20: =ROUND(G20*10^in_out_dp,0) | J20: =ROUND(H20*10^in_cost_dp,0) | K20: =SUMPRODUCT(($I$18:$I$21=I20)*($J$18:$J$21<J20)+($I$18:$I$21>I20)*($J$18:$J$21<=J20)) | L20: =IF(OR(E20=1,K20=0),1,0) | M20: =IF(AND(L20=1,E20=0,I20>0),1,0) | N20: =IF(M20=1,MAX(J20/I20,SUMPRODUCT(MAX(((J20-$J$18:$J$21)*($M$18:$M$21*($I$18:$I$21<I20)))/((I20-$I$18:$I$21)*($M$18:$M$21*($I$18:$I$21<I20))+1-($M$18:$M$21*($I$18:$I$21<I20)))-(1-($M$18:$M$21*($I$18:$I$21<I20)))*1E+300))),0) | O20: =IF(M20=1,SUMPRODUCT(MIN(((($J$18:$J$21-J20)*($M$18:$M$21*($I$18:$I$21>I20)))/(($I$18:$I$21-I20)*($M$18:$M$21*($I$18:$I$21>I20))+1-($M$18:$M$21*($I$18:$I$21>I20)))+(1-($M$18:$M$21*($I$18:$I$21>I20)))*1E+300))),0) | P20: =IF(E20=1,1,IF(AND(M20=1,N20<=O20),1,0)) | Q20: =IF(P20=1,1+SUMPRODUCT($P$18:$P$21*(($I$18:$I$21<I20)+($I$18:$I$21=I20)*($F$18:$F$21<F20))),0) | R20: =IF(Q20<=1,0,SUMPRODUCT(($Q$18:$Q$21=Q20-1)*$I$18:$I$21)) | S20: =IF(Q20<=1,0,SUMPRODUCT(($Q$18:$Q$21=Q20-1)*$J$18:$J$21)) | T20: =IF(Q20=0,"",(I20-R20)/10^in_out_dp) | U20: =IF(Q20=0,"",(J20-S20)/10^in_cost_dp) | V20: =IF(Q20=0,"",IF(I20=R20,0,U20/T20)) | W20: =IF(I20>0,(J20/10^in_cost_dp)/(I20/10^in_out_dp),"n/a") | X20: =IF(Sites!$C$7=C20,1,0)
A21: =B21&"|"&C21 | B21: 17B | C21: Alternative3 | D21: Alternative 3 | E21: 0 | F21: 4 | G21: =Summary!G16 | H21: =Summary!M16 | I21: =ROUND(G21*10^in_out_dp,0) | J21: =ROUND(H21*10^in_cost_dp,0) | K21: =SUMPRODUCT(($I$18:$I$21=I21)*($J$18:$J$21<J21)+($I$18:$I$21>I21)*($J$18:$J$21<=J21)) | L21: =IF(OR(E21=1,K21=0),1,0) | M21: =IF(AND(L21=1,E21=0,I21>0),1,0) | N21: =IF(M21=1,MAX(J21/I21,SUMPRODUCT(MAX(((J21-$J$18:$J$21)*($M$18:$M$21*($I$18:$I$21<I21)))/((I21-$I$18:$I$21)*($M$18:$M$21*($I$18:$I$21<I21))+1-($M$18:$M$21*($I$18:$I$21<I21)))-(1-($M$18:$M$21*($I$18:$I$21<I21)))*1E+300))),0) | O21: =IF(M21=1,SUMPRODUCT(MIN(((($J$18:$J$21-J21)*($M$18:$M$21*($I$18:$I$21>I21)))/(($I$18:$I$21-I21)*($M$18:$M$21*($I$18:$I$21>I21))+1-($M$18:$M$21*($I$18:$I$21>I21)))+(1-($M$18:$M$21*($I$18:$I$21>I21)))*1E+300))),0) | P21: =IF(E21=1,1,IF(AND(M21=1,N21<=O21),1,0)) | Q21: =IF(P21=1,1+SUMPRODUCT($P$18:$P$21*(($I$18:$I$21<I21)+($I$18:$I$21=I21)*($F$18:$F$21<F21))),0) | R21: =IF(Q21<=1,0,SUMPRODUCT(($Q$18:$Q$21=Q21-1)*$I$18:$I$21)) | S21: =IF(Q21<=1,0,SUMPRODUCT(($Q$18:$Q$21=Q21-1)*$J$18:$J$21)) | T21: =IF(Q21=0,"",(I21-R21)/10^in_out_dp) | U21: =IF(Q21=0,"",(J21-S21)/10^in_cost_dp) | V21: =IF(Q21=0,"",IF(I21=R21,0,U21/T21)) | W21: =IF(I21>0,(J21/10^in_cost_dp)/(I21/10^in_out_dp),"n/a") | X21: =IF(Sites!$C$7=C21,1,0)
B23: 2A Lower North Utoy powerline reach
A24: =B24&"|"&C24 | B24: 2A | C24: FWOP | D24: No Action | E24: 1 | F24: 1 | G24: =Summary!G17 | H24: =Summary!M17 | I24: =ROUND(G24*10^in_out_dp,0) | J24: =ROUND(H24*10^in_cost_dp,0) | K24: =SUMPRODUCT(($I$24:$I$27=I24)*($J$24:$J$27<J24)+($I$24:$I$27>I24)*($J$24:$J$27<=J24)) | L24: =IF(OR(E24=1,K24=0),1,0) | M24: =IF(AND(L24=1,E24=0,I24>0),1,0) | N24: =IF(M24=1,MAX(J24/I24,SUMPRODUCT(MAX(((J24-$J$24:$J$27)*($M$24:$M$27*($I$24:$I$27<I24)))/((I24-$I$24:$I$27)*($M$24:$M$27*($I$24:$I$27<I24))+1-($M$24:$M$27*($I$24:$I$27<I24)))-(1-($M$24:$M$27*($I$24:$I$27<I24)))*1E+300))),0) | O24: =IF(M24=1,SUMPRODUCT(MIN(((($J$24:$J$27-J24)*($M$24:$M$27*($I$24:$I$27>I24)))/(($I$24:$I$27-I24)*($M$24:$M$27*($I$24:$I$27>I24))+1-($M$24:$M$27*($I$24:$I$27>I24)))+(1-($M$24:$M$27*($I$24:$I$27>I24)))*1E+300))),0) | P24: =IF(E24=1,1,IF(AND(M24=1,N24<=O24),1,0)) | Q24: =IF(P24=1,1+SUMPRODUCT($P$24:$P$27*(($I$24:$I$27<I24)+($I$24:$I$27=I24)*($F$24:$F$27<F24))),0) | R24: =IF(Q24<=1,0,SUMPRODUCT(($Q$24:$Q$27=Q24-1)*$I$24:$I$27)) | S24: =IF(Q24<=1,0,SUMPRODUCT(($Q$24:$Q$27=Q24-1)*$J$24:$J$27)) | T24: =IF(Q24=0,"",(I24-R24)/10^in_out_dp) | U24: =IF(Q24=0,"",(J24-S24)/10^in_cost_dp) | V24: =IF(Q24=0,"",IF(I24=R24,0,U24/T24)) | W24: =IF(I24>0,(J24/10^in_cost_dp)/(I24/10^in_out_dp),"n/a") | X24: =IF(Sites!$C$8=C24,1,0)
A25: =B25&"|"&C25 | B25: 2A | C25: Alternative1 | D25: Alternative 1 | E25: 0 | F25: 2 | G25: =Summary!G18 | H25: =Summary!M18 | I25: =ROUND(G25*10^in_out_dp,0) | J25: =ROUND(H25*10^in_cost_dp,0) | K25: =SUMPRODUCT(($I$24:$I$27=I25)*($J$24:$J$27<J25)+($I$24:$I$27>I25)*($J$24:$J$27<=J25)) | L25: =IF(OR(E25=1,K25=0),1,0) | M25: =IF(AND(L25=1,E25=0,I25>0),1,0) | N25: =IF(M25=1,MAX(J25/I25,SUMPRODUCT(MAX(((J25-$J$24:$J$27)*($M$24:$M$27*($I$24:$I$27<I25)))/((I25-$I$24:$I$27)*($M$24:$M$27*($I$24:$I$27<I25))+1-($M$24:$M$27*($I$24:$I$27<I25)))-(1-($M$24:$M$27*($I$24:$I$27<I25)))*1E+300))),0) | O25: =IF(M25=1,SUMPRODUCT(MIN(((($J$24:$J$27-J25)*($M$24:$M$27*($I$24:$I$27>I25)))/(($I$24:$I$27-I25)*($M$24:$M$27*($I$24:$I$27>I25))+1-($M$24:$M$27*($I$24:$I$27>I25)))+(1-($M$24:$M$27*($I$24:$I$27>I25)))*1E+300))),0) | P25: =IF(E25=1,1,IF(AND(M25=1,N25<=O25),1,0)) | Q25: =IF(P25=1,1+SUMPRODUCT($P$24:$P$27*(($I$24:$I$27<I25)+($I$24:$I$27=I25)*($F$24:$F$27<F25))),0) | R25: =IF(Q25<=1,0,SUMPRODUCT(($Q$24:$Q$27=Q25-1)*$I$24:$I$27)) | S25: =IF(Q25<=1,0,SUMPRODUCT(($Q$24:$Q$27=Q25-1)*$J$24:$J$27)) | T25: =IF(Q25=0,"",(I25-R25)/10^in_out_dp) | U25: =IF(Q25=0,"",(J25-S25)/10^in_cost_dp) | V25: =IF(Q25=0,"",IF(I25=R25,0,U25/T25)) | W25: =IF(I25>0,(J25/10^in_cost_dp)/(I25/10^in_out_dp),"n/a") | X25: =IF(Sites!$C$8=C25,1,0)
A26: =B26&"|"&C26 | B26: 2A | C26: Alternative2 | D26: Alternative 2 | E26: 0 | F26: 3 | G26: =Summary!G19 | H26: =Summary!M19 | I26: =ROUND(G26*10^in_out_dp,0) | J26: =ROUND(H26*10^in_cost_dp,0) | K26: =SUMPRODUCT(($I$24:$I$27=I26)*($J$24:$J$27<J26)+($I$24:$I$27>I26)*($J$24:$J$27<=J26)) | L26: =IF(OR(E26=1,K26=0),1,0) | M26: =IF(AND(L26=1,E26=0,I26>0),1,0) | N26: =IF(M26=1,MAX(J26/I26,SUMPRODUCT(MAX(((J26-$J$24:$J$27)*($M$24:$M$27*($I$24:$I$27<I26)))/((I26-$I$24:$I$27)*($M$24:$M$27*($I$24:$I$27<I26))+1-($M$24:$M$27*($I$24:$I$27<I26)))-(1-($M$24:$M$27*($I$24:$I$27<I26)))*1E+300))),0) | O26: =IF(M26=1,SUMPRODUCT(MIN(((($J$24:$J$27-J26)*($M$24:$M$27*($I$24:$I$27>I26)))/(($I$24:$I$27-I26)*($M$24:$M$27*($I$24:$I$27>I26))+1-($M$24:$M$27*($I$24:$I$27>I26)))+(1-($M$24:$M$27*($I$24:$I$27>I26)))*1E+300))),0) | P26: =IF(E26=1,1,IF(AND(M26=1,N26<=O26),1,0)) | Q26: =IF(P26=1,1+SUMPRODUCT($P$24:$P$27*(($I$24:$I$27<I26)+($I$24:$I$27=I26)*($F$24:$F$27<F26))),0) | R26: =IF(Q26<=1,0,SUMPRODUCT(($Q$24:$Q$27=Q26-1)*$I$24:$I$27)) | S26: =IF(Q26<=1,0,SUMPRODUCT(($Q$24:$Q$27=Q26-1)*$J$24:$J$27)) | T26: =IF(Q26=0,"",(I26-R26)/10^in_out_dp) | U26: =IF(Q26=0,"",(J26-S26)/10^in_cost_dp) | V26: =IF(Q26=0,"",IF(I26=R26,0,U26/T26)) | W26: =IF(I26>0,(J26/10^in_cost_dp)/(I26/10^in_out_dp),"n/a") | X26: =IF(Sites!$C$8=C26,1,0)
A27: =B27&"|"&C27 | B27: 2A | C27: Alternative3 | D27: Alternative 3 | E27: 0 | F27: 4 | G27: =Summary!G20 | H27: =Summary!M20 | I27: =ROUND(G27*10^in_out_dp,0) | J27: =ROUND(H27*10^in_cost_dp,0) | K27: =SUMPRODUCT(($I$24:$I$27=I27)*($J$24:$J$27<J27)+($I$24:$I$27>I27)*($J$24:$J$27<=J27)) | L27: =IF(OR(E27=1,K27=0),1,0) | M27: =IF(AND(L27=1,E27=0,I27>0),1,0) | N27: =IF(M27=1,MAX(J27/I27,SUMPRODUCT(MAX(((J27-$J$24:$J$27)*($M$24:$M$27*($I$24:$I$27<I27)))/((I27-$I$24:$I$27)*($M$24:$M$27*($I$24:$I$27<I27))+1-($M$24:$M$27*($I$24:$I$27<I27)))-(1-($M$24:$M$27*($I$24:$I$27<I27)))*1E+300))),0) | O27: =IF(M27=1,SUMPRODUCT(MIN(((($J$24:$J$27-J27)*($M$24:$M$27*($I$24:$I$27>I27)))/(($I$24:$I$27-I27)*($M$24:$M$27*($I$24:$I$27>I27))+1-($M$24:$M$27*($I$24:$I$27>I27)))+(1-($M$24:$M$27*($I$24:$I$27>I27)))*1E+300))),0) | P27: =IF(E27=1,1,IF(AND(M27=1,N27<=O27),1,0)) | Q27: =IF(P27=1,1+SUMPRODUCT($P$24:$P$27*(($I$24:$I$27<I27)+($I$24:$I$27=I27)*($F$24:$F$27<F27))),0) | R27: =IF(Q27<=1,0,SUMPRODUCT(($Q$24:$Q$27=Q27-1)*$I$24:$I$27)) | S27: =IF(Q27<=1,0,SUMPRODUCT(($Q$24:$Q$27=Q27-1)*$J$24:$J$27)) | T27: =IF(Q27=0,"",(I27-R27)/10^in_out_dp) | U27: =IF(Q27=0,"",(J27-S27)/10^in_cost_dp) | V27: =IF(Q27=0,"",IF(I27=R27,0,U27/T27)) | W27: =IF(I27>0,(J27/10^in_cost_dp)/(I27/10^in_out_dp),"n/a") | X27: =IF(Sites!$C$8=C27,1,0)
B29: 2B North Utoy powerline reach
A30: =B30&"|"&C30 | B30: 2B | C30: FWOP | D30: No Action | E30: 1 | F30: 1 | G30: =Summary!G21 | H30: =Summary!M21 | I30: =ROUND(G30*10^in_out_dp,0) | J30: =ROUND(H30*10^in_cost_dp,0) | K30: =SUMPRODUCT(($I$30:$I$33=I30)*($J$30:$J$33<J30)+($I$30:$I$33>I30)*($J$30:$J$33<=J30)) | L30: =IF(OR(E30=1,K30=0),1,0) | M30: =IF(AND(L30=1,E30=0,I30>0),1,0) | N30: =IF(M30=1,MAX(J30/I30,SUMPRODUCT(MAX(((J30-$J$30:$J$33)*($M$30:$M$33*($I$30:$I$33<I30)))/((I30-$I$30:$I$33)*($M$30:$M$33*($I$30:$I$33<I30))+1-($M$30:$M$33*($I$30:$I$33<I30)))-(1-($M$30:$M$33*($I$30:$I$33<I30)))*1E+300))),0) | O30: =IF(M30=1,SUMPRODUCT(MIN(((($J$30:$J$33-J30)*($M$30:$M$33*($I$30:$I$33>I30)))/(($I$30:$I$33-I30)*($M$30:$M$33*($I$30:$I$33>I30))+1-($M$30:$M$33*($I$30:$I$33>I30)))+(1-($M$30:$M$33*($I$30:$I$33>I30)))*1E+300))),0) | P30: =IF(E30=1,1,IF(AND(M30=1,N30<=O30),1,0)) | Q30: =IF(P30=1,1+SUMPRODUCT($P$30:$P$33*(($I$30:$I$33<I30)+($I$30:$I$33=I30)*($F$30:$F$33<F30))),0) | R30: =IF(Q30<=1,0,SUMPRODUCT(($Q$30:$Q$33=Q30-1)*$I$30:$I$33)) | S30: =IF(Q30<=1,0,SUMPRODUCT(($Q$30:$Q$33=Q30-1)*$J$30:$J$33)) | T30: =IF(Q30=0,"",(I30-R30)/10^in_out_dp) | U30: =IF(Q30=0,"",(J30-S30)/10^in_cost_dp) | V30: =IF(Q30=0,"",IF(I30=R30,0,U30/T30)) | W30: =IF(I30>0,(J30/10^in_cost_dp)/(I30/10^in_out_dp),"n/a") | X30: =IF(Sites!$C$9=C30,1,0)
A31: =B31&"|"&C31 | B31: 2B | C31: Alternative1 | D31: Alternative 1 | E31: 0 | F31: 2 | G31: =Summary!G22 | H31: =Summary!M22 | I31: =ROUND(G31*10^in_out_dp,0) | J31: =ROUND(H31*10^in_cost_dp,0) | K31: =SUMPRODUCT(($I$30:$I$33=I31)*($J$30:$J$33<J31)+($I$30:$I$33>I31)*($J$30:$J$33<=J31)) | L31: =IF(OR(E31=1,K31=0),1,0) | M31: =IF(AND(L31=1,E31=0,I31>0),1,0) | N31: =IF(M31=1,MAX(J31/I31,SUMPRODUCT(MAX(((J31-$J$30:$J$33)*($M$30:$M$33*($I$30:$I$33<I31)))/((I31-$I$30:$I$33)*($M$30:$M$33*($I$30:$I$33<I31))+1-($M$30:$M$33*($I$30:$I$33<I31)))-(1-($M$30:$M$33*($I$30:$I$33<I31)))*1E+300))),0) | O31: =IF(M31=1,SUMPRODUCT(MIN(((($J$30:$J$33-J31)*($M$30:$M$33*($I$30:$I$33>I31)))/(($I$30:$I$33-I31)*($M$30:$M$33*($I$30:$I$33>I31))+1-($M$30:$M$33*($I$30:$I$33>I31)))+(1-($M$30:$M$33*($I$30:$I$33>I31)))*1E+300))),0) | P31: =IF(E31=1,1,IF(AND(M31=1,N31<=O31),1,0)) | Q31: =IF(P31=1,1+SUMPRODUCT($P$30:$P$33*(($I$30:$I$33<I31)+($I$30:$I$33=I31)*($F$30:$F$33<F31))),0) | R31: =IF(Q31<=1,0,SUMPRODUCT(($Q$30:$Q$33=Q31-1)*$I$30:$I$33)) | S31: =IF(Q31<=1,0,SUMPRODUCT(($Q$30:$Q$33=Q31-1)*$J$30:$J$33)) | T31: =IF(Q31=0,"",(I31-R31)/10^in_out_dp) | U31: =IF(Q31=0,"",(J31-S31)/10^in_cost_dp) | V31: =IF(Q31=0,"",IF(I31=R31,0,U31/T31)) | W31: =IF(I31>0,(J31/10^in_cost_dp)/(I31/10^in_out_dp),"n/a") | X31: =IF(Sites!$C$9=C31,1,0)
A32: =B32&"|"&C32 | B32: 2B | C32: Alternative2 | D32: Alternative 2 | E32: 0 | F32: 3 | G32: =Summary!G23 | H32: =Summary!M23 | I32: =ROUND(G32*10^in_out_dp,0) | J32: =ROUND(H32*10^in_cost_dp,0) | K32: =SUMPRODUCT(($I$30:$I$33=I32)*($J$30:$J$33<J32)+($I$30:$I$33>I32)*($J$30:$J$33<=J32)) | L32: =IF(OR(E32=1,K32=0),1,0) | M32: =IF(AND(L32=1,E32=0,I32>0),1,0) | N32: =IF(M32=1,MAX(J32/I32,SUMPRODUCT(MAX(((J32-$J$30:$J$33)*($M$30:$M$33*($I$30:$I$33<I32)))/((I32-$I$30:$I$33)*($M$30:$M$33*($I$30:$I$33<I32))+1-($M$30:$M$33*($I$30:$I$33<I32)))-(1-($M$30:$M$33*($I$30:$I$33<I32)))*1E+300))),0) | O32: =IF(M32=1,SUMPRODUCT(MIN(((($J$30:$J$33-J32)*($M$30:$M$33*($I$30:$I$33>I32)))/(($I$30:$I$33-I32)*($M$30:$M$33*($I$30:$I$33>I32))+1-($M$30:$M$33*($I$30:$I$33>I32)))+(1-($M$30:$M$33*($I$30:$I$33>I32)))*1E+300))),0) | P32: =IF(E32=1,1,IF(AND(M32=1,N32<=O32),1,0)) | Q32: =IF(P32=1,1+SUMPRODUCT($P$30:$P$33*(($I$30:$I$33<I32)+($I$30:$I$33=I32)*($F$30:$F$33<F32))),0) | R32: =IF(Q32<=1,0,SUMPRODUCT(($Q$30:$Q$33=Q32-1)*$I$30:$I$33)) | S32: =IF(Q32<=1,0,SUMPRODUCT(($Q$30:$Q$33=Q32-1)*$J$30:$J$33)) | T32: =IF(Q32=0,"",(I32-R32)/10^in_out_dp) | U32: =IF(Q32=0,"",(J32-S32)/10^in_cost_dp) | V32: =IF(Q32=0,"",IF(I32=R32,0,U32/T32)) | W32: =IF(I32>0,(J32/10^in_cost_dp)/(I32/10^in_out_dp),"n/a") | X32: =IF(Sites!$C$9=C32,1,0)
A33: =B33&"|"&C33 | B33: 2B | C33: Alternative3 | D33: Alternative 3 | E33: 0 | F33: 4 | G33: =Summary!G24 | H33: =Summary!M24 | I33: =ROUND(G33*10^in_out_dp,0) | J33: =ROUND(H33*10^in_cost_dp,0) | K33: =SUMPRODUCT(($I$30:$I$33=I33)*($J$30:$J$33<J33)+($I$30:$I$33>I33)*($J$30:$J$33<=J33)) | L33: =IF(OR(E33=1,K33=0),1,0) | M33: =IF(AND(L33=1,E33=0,I33>0),1,0) | N33: =IF(M33=1,MAX(J33/I33,SUMPRODUCT(MAX(((J33-$J$30:$J$33)*($M$30:$M$33*($I$30:$I$33<I33)))/((I33-$I$30:$I$33)*($M$30:$M$33*($I$30:$I$33<I33))+1-($M$30:$M$33*($I$30:$I$33<I33)))-(1-($M$30:$M$33*($I$30:$I$33<I33)))*1E+300))),0) | O33: =IF(M33=1,SUMPRODUCT(MIN(((($J$30:$J$33-J33)*($M$30:$M$33*($I$30:$I$33>I33)))/(($I$30:$I$33-I33)*($M$30:$M$33*($I$30:$I$33>I33))+1-($M$30:$M$33*($I$30:$I$33>I33)))+(1-($M$30:$M$33*($I$30:$I$33>I33)))*1E+300))),0) | P33: =IF(E33=1,1,IF(AND(M33=1,N33<=O33),1,0)) | Q33: =IF(P33=1,1+SUMPRODUCT($P$30:$P$33*(($I$30:$I$33<I33)+($I$30:$I$33=I33)*($F$30:$F$33<F33))),0) | R33: =IF(Q33<=1,0,SUMPRODUCT(($Q$30:$Q$33=Q33-1)*$I$30:$I$33)) | S33: =IF(Q33<=1,0,SUMPRODUCT(($Q$30:$Q$33=Q33-1)*$J$30:$J$33)) | T33: =IF(Q33=0,"",(I33-R33)/10^in_out_dp) | U33: =IF(Q33=0,"",(J33-S33)/10^in_cost_dp) | V33: =IF(Q33=0,"",IF(I33=R33,0,U33/T33)) | W33: =IF(I33>0,(J33/10^in_cost_dp)/(I33/10^in_out_dp),"n/a") | X33: =IF(Sites!$C$9=C33,1,0)
B35: 3E Cascade Springs road crossings
A36: =B36&"|"&C36 | B36: 3E | C36: FWOP | D36: No Action | E36: 1 | F36: 1 | G36: =Summary!G25 | H36: =Summary!M25 | I36: =ROUND(G36*10^in_out_dp,0) | J36: =ROUND(H36*10^in_cost_dp,0) | K36: =SUMPRODUCT(($I$36:$I$39=I36)*($J$36:$J$39<J36)+($I$36:$I$39>I36)*($J$36:$J$39<=J36)) | L36: =IF(OR(E36=1,K36=0),1,0) | M36: =IF(AND(L36=1,E36=0,I36>0),1,0) | N36: =IF(M36=1,MAX(J36/I36,SUMPRODUCT(MAX(((J36-$J$36:$J$39)*($M$36:$M$39*($I$36:$I$39<I36)))/((I36-$I$36:$I$39)*($M$36:$M$39*($I$36:$I$39<I36))+1-($M$36:$M$39*($I$36:$I$39<I36)))-(1-($M$36:$M$39*($I$36:$I$39<I36)))*1E+300))),0) | O36: =IF(M36=1,SUMPRODUCT(MIN(((($J$36:$J$39-J36)*($M$36:$M$39*($I$36:$I$39>I36)))/(($I$36:$I$39-I36)*($M$36:$M$39*($I$36:$I$39>I36))+1-($M$36:$M$39*($I$36:$I$39>I36)))+(1-($M$36:$M$39*($I$36:$I$39>I36)))*1E+300))),0) | P36: =IF(E36=1,1,IF(AND(M36=1,N36<=O36),1,0)) | Q36: =IF(P36=1,1+SUMPRODUCT($P$36:$P$39*(($I$36:$I$39<I36)+($I$36:$I$39=I36)*($F$36:$F$39<F36))),0) | R36: =IF(Q36<=1,0,SUMPRODUCT(($Q$36:$Q$39=Q36-1)*$I$36:$I$39)) | S36: =IF(Q36<=1,0,SUMPRODUCT(($Q$36:$Q$39=Q36-1)*$J$36:$J$39)) | T36: =IF(Q36=0,"",(I36-R36)/10^in_out_dp) | U36: =IF(Q36=0,"",(J36-S36)/10^in_cost_dp) | V36: =IF(Q36=0,"",IF(I36=R36,0,U36/T36)) | W36: =IF(I36>0,(J36/10^in_cost_dp)/(I36/10^in_out_dp),"n/a") | X36: =IF(Sites!$C$10=C36,1,0)
A37: =B37&"|"&C37 | B37: 3E | C37: Alternative1 | D37: Alternative 1 | E37: 0 | F37: 2 | G37: =Summary!G26 | H37: =Summary!M26 | I37: =ROUND(G37*10^in_out_dp,0) | J37: =ROUND(H37*10^in_cost_dp,0) | K37: =SUMPRODUCT(($I$36:$I$39=I37)*($J$36:$J$39<J37)+($I$36:$I$39>I37)*($J$36:$J$39<=J37)) | L37: =IF(OR(E37=1,K37=0),1,0) | M37: =IF(AND(L37=1,E37=0,I37>0),1,0) | N37: =IF(M37=1,MAX(J37/I37,SUMPRODUCT(MAX(((J37-$J$36:$J$39)*($M$36:$M$39*($I$36:$I$39<I37)))/((I37-$I$36:$I$39)*($M$36:$M$39*($I$36:$I$39<I37))+1-($M$36:$M$39*($I$36:$I$39<I37)))-(1-($M$36:$M$39*($I$36:$I$39<I37)))*1E+300))),0) | O37: =IF(M37=1,SUMPRODUCT(MIN(((($J$36:$J$39-J37)*($M$36:$M$39*($I$36:$I$39>I37)))/(($I$36:$I$39-I37)*($M$36:$M$39*($I$36:$I$39>I37))+1-($M$36:$M$39*($I$36:$I$39>I37)))+(1-($M$36:$M$39*($I$36:$I$39>I37)))*1E+300))),0) | P37: =IF(E37=1,1,IF(AND(M37=1,N37<=O37),1,0)) | Q37: =IF(P37=1,1+SUMPRODUCT($P$36:$P$39*(($I$36:$I$39<I37)+($I$36:$I$39=I37)*($F$36:$F$39<F37))),0) | R37: =IF(Q37<=1,0,SUMPRODUCT(($Q$36:$Q$39=Q37-1)*$I$36:$I$39)) | S37: =IF(Q37<=1,0,SUMPRODUCT(($Q$36:$Q$39=Q37-1)*$J$36:$J$39)) | T37: =IF(Q37=0,"",(I37-R37)/10^in_out_dp) | U37: =IF(Q37=0,"",(J37-S37)/10^in_cost_dp) | V37: =IF(Q37=0,"",IF(I37=R37,0,U37/T37)) | W37: =IF(I37>0,(J37/10^in_cost_dp)/(I37/10^in_out_dp),"n/a") | X37: =IF(Sites!$C$10=C37,1,0)
A38: =B38&"|"&C38 | B38: 3E | C38: Alternative2 | D38: Alternative 2 | E38: 0 | F38: 3 | G38: =Summary!G27 | H38: =Summary!M27 | I38: =ROUND(G38*10^in_out_dp,0) | J38: =ROUND(H38*10^in_cost_dp,0) | K38: =SUMPRODUCT(($I$36:$I$39=I38)*($J$36:$J$39<J38)+($I$36:$I$39>I38)*($J$36:$J$39<=J38)) | L38: =IF(OR(E38=1,K38=0),1,0) | M38: =IF(AND(L38=1,E38=0,I38>0),1,0) | N38: =IF(M38=1,MAX(J38/I38,SUMPRODUCT(MAX(((J38-$J$36:$J$39)*($M$36:$M$39*($I$36:$I$39<I38)))/((I38-$I$36:$I$39)*($M$36:$M$39*($I$36:$I$39<I38))+1-($M$36:$M$39*($I$36:$I$39<I38)))-(1-($M$36:$M$39*($I$36:$I$39<I38)))*1E+300))),0) | O38: =IF(M38=1,SUMPRODUCT(MIN(((($J$36:$J$39-J38)*($M$36:$M$39*($I$36:$I$39>I38)))/(($I$36:$I$39-I38)*($M$36:$M$39*($I$36:$I$39>I38))+1-($M$36:$M$39*($I$36:$I$39>I38)))+(1-($M$36:$M$39*($I$36:$I$39>I38)))*1E+300))),0) | P38: =IF(E38=1,1,IF(AND(M38=1,N38<=O38),1,0)) | Q38: =IF(P38=1,1+SUMPRODUCT($P$36:$P$39*(($I$36:$I$39<I38)+($I$36:$I$39=I38)*($F$36:$F$39<F38))),0) | R38: =IF(Q38<=1,0,SUMPRODUCT(($Q$36:$Q$39=Q38-1)*$I$36:$I$39)) | S38: =IF(Q38<=1,0,SUMPRODUCT(($Q$36:$Q$39=Q38-1)*$J$36:$J$39)) | T38: =IF(Q38=0,"",(I38-R38)/10^in_out_dp) | U38: =IF(Q38=0,"",(J38-S38)/10^in_cost_dp) | V38: =IF(Q38=0,"",IF(I38=R38,0,U38/T38)) | W38: =IF(I38>0,(J38/10^in_cost_dp)/(I38/10^in_out_dp),"n/a") | X38: =IF(Sites!$C$10=C38,1,0)
A39: =B39&"|"&C39 | B39: 3E | C39: Alternative3 | D39: Alternative 3 | E39: 0 | F39: 4 | G39: =Summary!G28 | H39: =Summary!M28 | I39: =ROUND(G39*10^in_out_dp,0) | J39: =ROUND(H39*10^in_cost_dp,0) | K39: =SUMPRODUCT(($I$36:$I$39=I39)*($J$36:$J$39<J39)+($I$36:$I$39>I39)*($J$36:$J$39<=J39)) | L39: =IF(OR(E39=1,K39=0),1,0) | M39: =IF(AND(L39=1,E39=0,I39>0),1,0) | N39: =IF(M39=1,MAX(J39/I39,SUMPRODUCT(MAX(((J39-$J$36:$J$39)*($M$36:$M$39*($I$36:$I$39<I39)))/((I39-$I$36:$I$39)*($M$36:$M$39*($I$36:$I$39<I39))+1-($M$36:$M$39*($I$36:$I$39<I39)))-(1-($M$36:$M$39*($I$36:$I$39<I39)))*1E+300))),0) | O39: =IF(M39=1,SUMPRODUCT(MIN(((($J$36:$J$39-J39)*($M$36:$M$39*($I$36:$I$39>I39)))/(($I$36:$I$39-I39)*($M$36:$M$39*($I$36:$I$39>I39))+1-($M$36:$M$39*($I$36:$I$39>I39)))+(1-($M$36:$M$39*($I$36:$I$39>I39)))*1E+300))),0) | P39: =IF(E39=1,1,IF(AND(M39=1,N39<=O39),1,0)) | Q39: =IF(P39=1,1+SUMPRODUCT($P$36:$P$39*(($I$36:$I$39<I39)+($I$36:$I$39=I39)*($F$36:$F$39<F39))),0) | R39: =IF(Q39<=1,0,SUMPRODUCT(($Q$36:$Q$39=Q39-1)*$I$36:$I$39)) | S39: =IF(Q39<=1,0,SUMPRODUCT(($Q$36:$Q$39=Q39-1)*$J$36:$J$39)) | T39: =IF(Q39=0,"",(I39-R39)/10^in_out_dp) | U39: =IF(Q39=0,"",(J39-S39)/10^in_cost_dp) | V39: =IF(Q39=0,"",IF(I39=R39,0,U39/T39)) | W39: =IF(I39>0,(J39/10^in_cost_dp)/(I39/10^in_out_dp),"n/a") | X39: =IF(Sites!$C$10=C39,1,0)
B41: 3F Dodson Drive to Harbin Road
A42: =B42&"|"&C42 | B42: 3F | C42: FWOP | D42: No Action | E42: 1 | F42: 1 | G42: =Summary!G29 | H42: =Summary!M29 | I42: =ROUND(G42*10^in_out_dp,0) | J42: =ROUND(H42*10^in_cost_dp,0) | K42: =SUMPRODUCT(($I$42:$I$45=I42)*($J$42:$J$45<J42)+($I$42:$I$45>I42)*($J$42:$J$45<=J42)) | L42: =IF(OR(E42=1,K42=0),1,0) | M42: =IF(AND(L42=1,E42=0,I42>0),1,0) | N42: =IF(M42=1,MAX(J42/I42,SUMPRODUCT(MAX(((J42-$J$42:$J$45)*($M$42:$M$45*($I$42:$I$45<I42)))/((I42-$I$42:$I$45)*($M$42:$M$45*($I$42:$I$45<I42))+1-($M$42:$M$45*($I$42:$I$45<I42)))-(1-($M$42:$M$45*($I$42:$I$45<I42)))*1E+300))),0) | O42: =IF(M42=1,SUMPRODUCT(MIN(((($J$42:$J$45-J42)*($M$42:$M$45*($I$42:$I$45>I42)))/(($I$42:$I$45-I42)*($M$42:$M$45*($I$42:$I$45>I42))+1-($M$42:$M$45*($I$42:$I$45>I42)))+(1-($M$42:$M$45*($I$42:$I$45>I42)))*1E+300))),0) | P42: =IF(E42=1,1,IF(AND(M42=1,N42<=O42),1,0)) | Q42: =IF(P42=1,1+SUMPRODUCT($P$42:$P$45*(($I$42:$I$45<I42)+($I$42:$I$45=I42)*($F$42:$F$45<F42))),0) | R42: =IF(Q42<=1,0,SUMPRODUCT(($Q$42:$Q$45=Q42-1)*$I$42:$I$45)) | S42: =IF(Q42<=1,0,SUMPRODUCT(($Q$42:$Q$45=Q42-1)*$J$42:$J$45)) | T42: =IF(Q42=0,"",(I42-R42)/10^in_out_dp) | U42: =IF(Q42=0,"",(J42-S42)/10^in_cost_dp) | V42: =IF(Q42=0,"",IF(I42=R42,0,U42/T42)) | W42: =IF(I42>0,(J42/10^in_cost_dp)/(I42/10^in_out_dp),"n/a") | X42: =IF(Sites!$C$11=C42,1,0)
A43: =B43&"|"&C43 | B43: 3F | C43: Alternative1 | D43: Alternative 1 | E43: 0 | F43: 2 | G43: =Summary!G30 | H43: =Summary!M30 | I43: =ROUND(G43*10^in_out_dp,0) | J43: =ROUND(H43*10^in_cost_dp,0) | K43: =SUMPRODUCT(($I$42:$I$45=I43)*($J$42:$J$45<J43)+($I$42:$I$45>I43)*($J$42:$J$45<=J43)) | L43: =IF(OR(E43=1,K43=0),1,0) | M43: =IF(AND(L43=1,E43=0,I43>0),1,0) | N43: =IF(M43=1,MAX(J43/I43,SUMPRODUCT(MAX(((J43-$J$42:$J$45)*($M$42:$M$45*($I$42:$I$45<I43)))/((I43-$I$42:$I$45)*($M$42:$M$45*($I$42:$I$45<I43))+1-($M$42:$M$45*($I$42:$I$45<I43)))-(1-($M$42:$M$45*($I$42:$I$45<I43)))*1E+300))),0) | O43: =IF(M43=1,SUMPRODUCT(MIN(((($J$42:$J$45-J43)*($M$42:$M$45*($I$42:$I$45>I43)))/(($I$42:$I$45-I43)*($M$42:$M$45*($I$42:$I$45>I43))+1-($M$42:$M$45*($I$42:$I$45>I43)))+(1-($M$42:$M$45*($I$42:$I$45>I43)))*1E+300))),0) | P43: =IF(E43=1,1,IF(AND(M43=1,N43<=O43),1,0)) | Q43: =IF(P43=1,1+SUMPRODUCT($P$42:$P$45*(($I$42:$I$45<I43)+($I$42:$I$45=I43)*($F$42:$F$45<F43))),0) | R43: =IF(Q43<=1,0,SUMPRODUCT(($Q$42:$Q$45=Q43-1)*$I$42:$I$45)) | S43: =IF(Q43<=1,0,SUMPRODUCT(($Q$42:$Q$45=Q43-1)*$J$42:$J$45)) | T43: =IF(Q43=0,"",(I43-R43)/10^in_out_dp) | U43: =IF(Q43=0,"",(J43-S43)/10^in_cost_dp) | V43: =IF(Q43=0,"",IF(I43=R43,0,U43/T43)) | W43: =IF(I43>0,(J43/10^in_cost_dp)/(I43/10^in_out_dp),"n/a") | X43: =IF(Sites!$C$11=C43,1,0)
A44: =B44&"|"&C44 | B44: 3F | C44: Alternative2 | D44: Alternative 2 | E44: 0 | F44: 3 | G44: =Summary!G31 | H44: =Summary!M31 | I44: =ROUND(G44*10^in_out_dp,0) | J44: =ROUND(H44*10^in_cost_dp,0) | K44: =SUMPRODUCT(($I$42:$I$45=I44)*($J$42:$J$45<J44)+($I$42:$I$45>I44)*($J$42:$J$45<=J44)) | L44: =IF(OR(E44=1,K44=0),1,0) | M44: =IF(AND(L44=1,E44=0,I44>0),1,0) | N44: =IF(M44=1,MAX(J44/I44,SUMPRODUCT(MAX(((J44-$J$42:$J$45)*($M$42:$M$45*($I$42:$I$45<I44)))/((I44-$I$42:$I$45)*($M$42:$M$45*($I$42:$I$45<I44))+1-($M$42:$M$45*($I$42:$I$45<I44)))-(1-($M$42:$M$45*($I$42:$I$45<I44)))*1E+300))),0) | O44: =IF(M44=1,SUMPRODUCT(MIN(((($J$42:$J$45-J44)*($M$42:$M$45*($I$42:$I$45>I44)))/(($I$42:$I$45-I44)*($M$42:$M$45*($I$42:$I$45>I44))+1-($M$42:$M$45*($I$42:$I$45>I44)))+(1-($M$42:$M$45*($I$42:$I$45>I44)))*1E+300))),0) | P44: =IF(E44=1,1,IF(AND(M44=1,N44<=O44),1,0)) | Q44: =IF(P44=1,1+SUMPRODUCT($P$42:$P$45*(($I$42:$I$45<I44)+($I$42:$I$45=I44)*($F$42:$F$45<F44))),0) | R44: =IF(Q44<=1,0,SUMPRODUCT(($Q$42:$Q$45=Q44-1)*$I$42:$I$45)) | S44: =IF(Q44<=1,0,SUMPRODUCT(($Q$42:$Q$45=Q44-1)*$J$42:$J$45)) | T44: =IF(Q44=0,"",(I44-R44)/10^in_out_dp) | U44: =IF(Q44=0,"",(J44-S44)/10^in_cost_dp) | V44: =IF(Q44=0,"",IF(I44=R44,0,U44/T44)) | W44: =IF(I44>0,(J44/10^in_cost_dp)/(I44/10^in_out_dp),"n/a") | X44: =IF(Sites!$C$11=C44,1,0)
A45: =B45&"|"&C45 | B45: 3F | C45: Alternative3 | D45: Alternative 3 | E45: 0 | F45: 4 | G45: =Summary!G32 | H45: =Summary!M32 | I45: =ROUND(G45*10^in_out_dp,0) | J45: =ROUND(H45*10^in_cost_dp,0) | K45: =SUMPRODUCT(($I$42:$I$45=I45)*($J$42:$J$45<J45)+($I$42:$I$45>I45)*($J$42:$J$45<=J45)) | L45: =IF(OR(E45=1,K45=0),1,0) | M45: =IF(AND(L45=1,E45=0,I45>0),1,0) | N45: =IF(M45=1,MAX(J45/I45,SUMPRODUCT(MAX(((J45-$J$42:$J$45)*($M$42:$M$45*($I$42:$I$45<I45)))/((I45-$I$42:$I$45)*($M$42:$M$45*($I$42:$I$45<I45))+1-($M$42:$M$45*($I$42:$I$45<I45)))-(1-($M$42:$M$45*($I$42:$I$45<I45)))*1E+300))),0) | O45: =IF(M45=1,SUMPRODUCT(MIN(((($J$42:$J$45-J45)*($M$42:$M$45*($I$42:$I$45>I45)))/(($I$42:$I$45-I45)*($M$42:$M$45*($I$42:$I$45>I45))+1-($M$42:$M$45*($I$42:$I$45>I45)))+(1-($M$42:$M$45*($I$42:$I$45>I45)))*1E+300))),0) | P45: =IF(E45=1,1,IF(AND(M45=1,N45<=O45),1,0)) | Q45: =IF(P45=1,1+SUMPRODUCT($P$42:$P$45*(($I$42:$I$45<I45)+($I$42:$I$45=I45)*($F$42:$F$45<F45))),0) | R45: =IF(Q45<=1,0,SUMPRODUCT(($Q$42:$Q$45=Q45-1)*$I$42:$I$45)) | S45: =IF(Q45<=1,0,SUMPRODUCT(($Q$42:$Q$45=Q45-1)*$J$42:$J$45)) | T45: =IF(Q45=0,"",(I45-R45)/10^in_out_dp) | U45: =IF(Q45=0,"",(J45-S45)/10^in_cost_dp) | V45: =IF(Q45=0,"",IF(I45=R45,0,U45/T45)) | W45: =IF(I45>0,(J45/10^in_cost_dp)/(I45/10^in_out_dp),"n/a") | X45: =IF(Sites!$C$11=C45,1,0)
B47: 19A I-285 and Glenview Drive reach
A48: =B48&"|"&C48 | B48: 19A | C48: FWOP | D48: No Action | E48: 1 | F48: 1 | G48: =Summary!G33 | H48: =Summary!M33 | I48: =ROUND(G48*10^in_out_dp,0) | J48: =ROUND(H48*10^in_cost_dp,0) | K48: =SUMPRODUCT(($I$48:$I$50=I48)*($J$48:$J$50<J48)+($I$48:$I$50>I48)*($J$48:$J$50<=J48)) | L48: =IF(OR(E48=1,K48=0),1,0) | M48: =IF(AND(L48=1,E48=0,I48>0),1,0) | N48: =IF(M48=1,MAX(J48/I48,SUMPRODUCT(MAX(((J48-$J$48:$J$50)*($M$48:$M$50*($I$48:$I$50<I48)))/((I48-$I$48:$I$50)*($M$48:$M$50*($I$48:$I$50<I48))+1-($M$48:$M$50*($I$48:$I$50<I48)))-(1-($M$48:$M$50*($I$48:$I$50<I48)))*1E+300))),0) | O48: =IF(M48=1,SUMPRODUCT(MIN(((($J$48:$J$50-J48)*($M$48:$M$50*($I$48:$I$50>I48)))/(($I$48:$I$50-I48)*($M$48:$M$50*($I$48:$I$50>I48))+1-($M$48:$M$50*($I$48:$I$50>I48)))+(1-($M$48:$M$50*($I$48:$I$50>I48)))*1E+300))),0) | P48: =IF(E48=1,1,IF(AND(M48=1,N48<=O48),1,0)) | Q48: =IF(P48=1,1+SUMPRODUCT($P$48:$P$50*(($I$48:$I$50<I48)+($I$48:$I$50=I48)*($F$48:$F$50<F48))),0) | R48: =IF(Q48<=1,0,SUMPRODUCT(($Q$48:$Q$50=Q48-1)*$I$48:$I$50)) | S48: =IF(Q48<=1,0,SUMPRODUCT(($Q$48:$Q$50=Q48-1)*$J$48:$J$50)) | T48: =IF(Q48=0,"",(I48-R48)/10^in_out_dp) | U48: =IF(Q48=0,"",(J48-S48)/10^in_cost_dp) | V48: =IF(Q48=0,"",IF(I48=R48,0,U48/T48)) | W48: =IF(I48>0,(J48/10^in_cost_dp)/(I48/10^in_out_dp),"n/a") | X48: =IF(Sites!$C$12=C48,1,0)
A49: =B49&"|"&C49 | B49: 19A | C49: Alternative2 | D49: Alternative 2 | E49: 0 | F49: 2 | G49: =Summary!G34 | H49: =Summary!M34 | I49: =ROUND(G49*10^in_out_dp,0) | J49: =ROUND(H49*10^in_cost_dp,0) | K49: =SUMPRODUCT(($I$48:$I$50=I49)*($J$48:$J$50<J49)+($I$48:$I$50>I49)*($J$48:$J$50<=J49)) | L49: =IF(OR(E49=1,K49=0),1,0) | M49: =IF(AND(L49=1,E49=0,I49>0),1,0) | N49: =IF(M49=1,MAX(J49/I49,SUMPRODUCT(MAX(((J49-$J$48:$J$50)*($M$48:$M$50*($I$48:$I$50<I49)))/((I49-$I$48:$I$50)*($M$48:$M$50*($I$48:$I$50<I49))+1-($M$48:$M$50*($I$48:$I$50<I49)))-(1-($M$48:$M$50*($I$48:$I$50<I49)))*1E+300))),0) | O49: =IF(M49=1,SUMPRODUCT(MIN(((($J$48:$J$50-J49)*($M$48:$M$50*($I$48:$I$50>I49)))/(($I$48:$I$50-I49)*($M$48:$M$50*($I$48:$I$50>I49))+1-($M$48:$M$50*($I$48:$I$50>I49)))+(1-($M$48:$M$50*($I$48:$I$50>I49)))*1E+300))),0) | P49: =IF(E49=1,1,IF(AND(M49=1,N49<=O49),1,0)) | Q49: =IF(P49=1,1+SUMPRODUCT($P$48:$P$50*(($I$48:$I$50<I49)+($I$48:$I$50=I49)*($F$48:$F$50<F49))),0) | R49: =IF(Q49<=1,0,SUMPRODUCT(($Q$48:$Q$50=Q49-1)*$I$48:$I$50)) | S49: =IF(Q49<=1,0,SUMPRODUCT(($Q$48:$Q$50=Q49-1)*$J$48:$J$50)) | T49: =IF(Q49=0,"",(I49-R49)/10^in_out_dp) | U49: =IF(Q49=0,"",(J49-S49)/10^in_cost_dp) | V49: =IF(Q49=0,"",IF(I49=R49,0,U49/T49)) | W49: =IF(I49>0,(J49/10^in_cost_dp)/(I49/10^in_out_dp),"n/a") | X49: =IF(Sites!$C$12=C49,1,0)
A50: =B50&"|"&C50 | B50: 19A | C50: Alternative3 | D50: Alternative 3 | E50: 0 | F50: 3 | G50: =Summary!G35 | H50: =Summary!M35 | I50: =ROUND(G50*10^in_out_dp,0) | J50: =ROUND(H50*10^in_cost_dp,0) | K50: =SUMPRODUCT(($I$48:$I$50=I50)*($J$48:$J$50<J50)+($I$48:$I$50>I50)*($J$48:$J$50<=J50)) | L50: =IF(OR(E50=1,K50=0),1,0) | M50: =IF(AND(L50=1,E50=0,I50>0),1,0) | N50: =IF(M50=1,MAX(J50/I50,SUMPRODUCT(MAX(((J50-$J$48:$J$50)*($M$48:$M$50*($I$48:$I$50<I50)))/((I50-$I$48:$I$50)*($M$48:$M$50*($I$48:$I$50<I50))+1-($M$48:$M$50*($I$48:$I$50<I50)))-(1-($M$48:$M$50*($I$48:$I$50<I50)))*1E+300))),0) | O50: =IF(M50=1,SUMPRODUCT(MIN(((($J$48:$J$50-J50)*($M$48:$M$50*($I$48:$I$50>I50)))/(($I$48:$I$50-I50)*($M$48:$M$50*($I$48:$I$50>I50))+1-($M$48:$M$50*($I$48:$I$50>I50)))+(1-($M$48:$M$50*($I$48:$I$50>I50)))*1E+300))),0) | P50: =IF(E50=1,1,IF(AND(M50=1,N50<=O50),1,0)) | Q50: =IF(P50=1,1+SUMPRODUCT($P$48:$P$50*(($I$48:$I$50<I50)+($I$48:$I$50=I50)*($F$48:$F$50<F50))),0) | R50: =IF(Q50<=1,0,SUMPRODUCT(($Q$48:$Q$50=Q50-1)*$I$48:$I$50)) | S50: =IF(Q50<=1,0,SUMPRODUCT(($Q$48:$Q$50=Q50-1)*$J$48:$J$50)) | T50: =IF(Q50=0,"",(I50-R50)/10^in_out_dp) | U50: =IF(Q50=0,"",(J50-S50)/10^in_cost_dp) | V50: =IF(Q50=0,"",IF(I50=R50,0,U50/T50)) | W50: =IF(I50>0,(J50/10^in_cost_dp)/(I50/10^in_out_dp),"n/a") | X50: =IF(Sites!$C$12=C50,1,0)

Sheet Sites
A1: Sites: the alternative carried to the watershed plans
A2: Choose each site's recommended alternative. No Action leaves the site out of every watershed plan.
A4: Site | B4: Name | C4: Recommended alternative | D4: No Action | E4: Carried | F4: Lift (AAHU) | G4: Cost above No Action | H4: Construction cost | I4: Lift (scaled) | J4: Cost (scaled) | K4: Cost-effective | L4: Best buy | M4: Decided by
A5: 17F2M | B5: Golf course concrete channel | C5: Alternative3 | D5: FWOP | E5: =IF(C5<>D5,1,0) | F5: =IFERROR(INDEX('Site CE-ICA'!$G$5:$G$50,MATCH(A5&"|"&C5,'Site CE-ICA'!$A$5:$A$50,0)),0) | G5: =IFERROR(INDEX('Site CE-ICA'!$H$5:$H$50,MATCH(A5&"|"&C5,'Site CE-ICA'!$A$5:$A$50,0)),0) | H5: =IFERROR(INDEX(Summary!$H$5:$H$8,MATCH(C5,Summary!$C$5:$C$8,0)),0) | I5: =IF(E5=1,IFERROR(INDEX('Site CE-ICA'!$I$5:$I$50,MATCH(A5&"|"&C5,'Site CE-ICA'!$A$5:$A$50,0)),0),0) | J5: =IF(E5=1,IFERROR(INDEX('Site CE-ICA'!$J$5:$J$50,MATCH(A5&"|"&C5,'Site CE-ICA'!$A$5:$A$50,0)),0),0) | K5: =IFERROR(INDEX('Site CE-ICA'!$L$5:$L$50,MATCH(A5&"|"&C5,'Site CE-ICA'!$A$5:$A$50,0)),0) | L5: =IFERROR(INDEX('Site CE-ICA'!$P$5:$P$50,MATCH(A5&"|"&C5,'Site CE-ICA'!$A$5:$A$50,0)),0) | M5: Team
A6: 17D2E | B6: Concrete channel to Beecher Road | C6: Alternative1 | D6: FWOP | E6: =IF(C6<>D6,1,0) | F6: =IFERROR(INDEX('Site CE-ICA'!$G$5:$G$50,MATCH(A6&"|"&C6,'Site CE-ICA'!$A$5:$A$50,0)),0) | G6: =IFERROR(INDEX('Site CE-ICA'!$H$5:$H$50,MATCH(A6&"|"&C6,'Site CE-ICA'!$A$5:$A$50,0)),0) | H6: =IFERROR(INDEX(Summary!$H$9:$H$12,MATCH(C6,Summary!$C$9:$C$12,0)),0) | I6: =IF(E6=1,IFERROR(INDEX('Site CE-ICA'!$I$5:$I$50,MATCH(A6&"|"&C6,'Site CE-ICA'!$A$5:$A$50,0)),0),0) | J6: =IF(E6=1,IFERROR(INDEX('Site CE-ICA'!$J$5:$J$50,MATCH(A6&"|"&C6,'Site CE-ICA'!$A$5:$A$50,0)),0),0) | K6: =IFERROR(INDEX('Site CE-ICA'!$L$5:$L$50,MATCH(A6&"|"&C6,'Site CE-ICA'!$A$5:$A$50,0)),0) | L6: =IFERROR(INDEX('Site CE-ICA'!$P$5:$P$50,MATCH(A6&"|"&C6,'Site CE-ICA'!$A$5:$A$50,0)),0) | M6: Team
A7: 17B | B7: Southwest Connector Trail reach | C7: Alternative2 | D7: FWOP | E7: =IF(C7<>D7,1,0) | F7: =IFERROR(INDEX('Site CE-ICA'!$G$5:$G$50,MATCH(A7&"|"&C7,'Site CE-ICA'!$A$5:$A$50,0)),0) | G7: =IFERROR(INDEX('Site CE-ICA'!$H$5:$H$50,MATCH(A7&"|"&C7,'Site CE-ICA'!$A$5:$A$50,0)),0) | H7: =IFERROR(INDEX(Summary!$H$13:$H$16,MATCH(C7,Summary!$C$13:$C$16,0)),0) | I7: =IF(E7=1,IFERROR(INDEX('Site CE-ICA'!$I$5:$I$50,MATCH(A7&"|"&C7,'Site CE-ICA'!$A$5:$A$50,0)),0),0) | J7: =IF(E7=1,IFERROR(INDEX('Site CE-ICA'!$J$5:$J$50,MATCH(A7&"|"&C7,'Site CE-ICA'!$A$5:$A$50,0)),0),0) | K7: =IFERROR(INDEX('Site CE-ICA'!$L$5:$L$50,MATCH(A7&"|"&C7,'Site CE-ICA'!$A$5:$A$50,0)),0) | L7: =IFERROR(INDEX('Site CE-ICA'!$P$5:$P$50,MATCH(A7&"|"&C7,'Site CE-ICA'!$A$5:$A$50,0)),0) | M7: Team
A8: 2A | B8: Lower North Utoy powerline reach | C8: Alternative1 | D8: FWOP | E8: =IF(C8<>D8,1,0) | F8: =IFERROR(INDEX('Site CE-ICA'!$G$5:$G$50,MATCH(A8&"|"&C8,'Site CE-ICA'!$A$5:$A$50,0)),0) | G8: =IFERROR(INDEX('Site CE-ICA'!$H$5:$H$50,MATCH(A8&"|"&C8,'Site CE-ICA'!$A$5:$A$50,0)),0) | H8: =IFERROR(INDEX(Summary!$H$17:$H$20,MATCH(C8,Summary!$C$17:$C$20,0)),0) | I8: =IF(E8=1,IFERROR(INDEX('Site CE-ICA'!$I$5:$I$50,MATCH(A8&"|"&C8,'Site CE-ICA'!$A$5:$A$50,0)),0),0) | J8: =IF(E8=1,IFERROR(INDEX('Site CE-ICA'!$J$5:$J$50,MATCH(A8&"|"&C8,'Site CE-ICA'!$A$5:$A$50,0)),0),0) | K8: =IFERROR(INDEX('Site CE-ICA'!$L$5:$L$50,MATCH(A8&"|"&C8,'Site CE-ICA'!$A$5:$A$50,0)),0) | L8: =IFERROR(INDEX('Site CE-ICA'!$P$5:$P$50,MATCH(A8&"|"&C8,'Site CE-ICA'!$A$5:$A$50,0)),0) | M8: Team
A9: 2B | B9: North Utoy powerline reach | C9: Alternative1 | D9: FWOP | E9: =IF(C9<>D9,1,0) | F9: =IFERROR(INDEX('Site CE-ICA'!$G$5:$G$50,MATCH(A9&"|"&C9,'Site CE-ICA'!$A$5:$A$50,0)),0) | G9: =IFERROR(INDEX('Site CE-ICA'!$H$5:$H$50,MATCH(A9&"|"&C9,'Site CE-ICA'!$A$5:$A$50,0)),0) | H9: =IFERROR(INDEX(Summary!$H$21:$H$24,MATCH(C9,Summary!$C$21:$C$24,0)),0) | I9: =IF(E9=1,IFERROR(INDEX('Site CE-ICA'!$I$5:$I$50,MATCH(A9&"|"&C9,'Site CE-ICA'!$A$5:$A$50,0)),0),0) | J9: =IF(E9=1,IFERROR(INDEX('Site CE-ICA'!$J$5:$J$50,MATCH(A9&"|"&C9,'Site CE-ICA'!$A$5:$A$50,0)),0),0) | K9: =IFERROR(INDEX('Site CE-ICA'!$L$5:$L$50,MATCH(A9&"|"&C9,'Site CE-ICA'!$A$5:$A$50,0)),0) | L9: =IFERROR(INDEX('Site CE-ICA'!$P$5:$P$50,MATCH(A9&"|"&C9,'Site CE-ICA'!$A$5:$A$50,0)),0) | M9: Team
A10: 3E | B10: Cascade Springs road crossings | C10: FWOP | D10: FWOP | E10: =IF(C10<>D10,1,0) | F10: =IFERROR(INDEX('Site CE-ICA'!$G$5:$G$50,MATCH(A10&"|"&C10,'Site CE-ICA'!$A$5:$A$50,0)),0) | G10: =IFERROR(INDEX('Site CE-ICA'!$H$5:$H$50,MATCH(A10&"|"&C10,'Site CE-ICA'!$A$5:$A$50,0)),0) | H10: =IFERROR(INDEX(Summary!$H$25:$H$28,MATCH(C10,Summary!$C$25:$C$28,0)),0) | I10: =IF(E10=1,IFERROR(INDEX('Site CE-ICA'!$I$5:$I$50,MATCH(A10&"|"&C10,'Site CE-ICA'!$A$5:$A$50,0)),0),0) | J10: =IF(E10=1,IFERROR(INDEX('Site CE-ICA'!$J$5:$J$50,MATCH(A10&"|"&C10,'Site CE-ICA'!$A$5:$A$50,0)),0),0) | K10: =IFERROR(INDEX('Site CE-ICA'!$L$5:$L$50,MATCH(A10&"|"&C10,'Site CE-ICA'!$A$5:$A$50,0)),0) | L10: =IFERROR(INDEX('Site CE-ICA'!$P$5:$P$50,MATCH(A10&"|"&C10,'Site CE-ICA'!$A$5:$A$50,0)),0) | M10: Team
A11: 3F | B11: Dodson Drive to Harbin Road | C11: Alternative1 | D11: FWOP | E11: =IF(C11<>D11,1,0) | F11: =IFERROR(INDEX('Site CE-ICA'!$G$5:$G$50,MATCH(A11&"|"&C11,'Site CE-ICA'!$A$5:$A$50,0)),0) | G11: =IFERROR(INDEX('Site CE-ICA'!$H$5:$H$50,MATCH(A11&"|"&C11,'Site CE-ICA'!$A$5:$A$50,0)),0) | H11: =IFERROR(INDEX(Summary!$H$29:$H$32,MATCH(C11,Summary!$C$29:$C$32,0)),0) | I11: =IF(E11=1,IFERROR(INDEX('Site CE-ICA'!$I$5:$I$50,MATCH(A11&"|"&C11,'Site CE-ICA'!$A$5:$A$50,0)),0),0) | J11: =IF(E11=1,IFERROR(INDEX('Site CE-ICA'!$J$5:$J$50,MATCH(A11&"|"&C11,'Site CE-ICA'!$A$5:$A$50,0)),0),0) | K11: =IFERROR(INDEX('Site CE-ICA'!$L$5:$L$50,MATCH(A11&"|"&C11,'Site CE-ICA'!$A$5:$A$50,0)),0) | L11: =IFERROR(INDEX('Site CE-ICA'!$P$5:$P$50,MATCH(A11&"|"&C11,'Site CE-ICA'!$A$5:$A$50,0)),0) | M11: Team
A12: 19A | B12: I-285 and Glenview Drive reach | C12: Alternative2 | D12: FWOP | E12: =IF(C12<>D12,1,0) | F12: =IFERROR(INDEX('Site CE-ICA'!$G$5:$G$50,MATCH(A12&"|"&C12,'Site CE-ICA'!$A$5:$A$50,0)),0) | G12: =IFERROR(INDEX('Site CE-ICA'!$H$5:$H$50,MATCH(A12&"|"&C12,'Site CE-ICA'!$A$5:$A$50,0)),0) | H12: =IFERROR(INDEX(Summary!$H$33:$H$35,MATCH(C12,Summary!$C$33:$C$35,0)),0) | I12: =IF(E12=1,IFERROR(INDEX('Site CE-ICA'!$I$5:$I$50,MATCH(A12&"|"&C12,'Site CE-ICA'!$A$5:$A$50,0)),0),0) | J12: =IF(E12=1,IFERROR(INDEX('Site CE-ICA'!$J$5:$J$50,MATCH(A12&"|"&C12,'Site CE-ICA'!$A$5:$A$50,0)),0),0) | K12: =IFERROR(INDEX('Site CE-ICA'!$L$5:$L$50,MATCH(A12&"|"&C12,'Site CE-ICA'!$A$5:$A$50,0)),0) | L12: =IFERROR(INDEX('Site CE-ICA'!$P$5:$P$50,MATCH(A12&"|"&C12,'Site CE-ICA'!$A$5:$A$50,0)),0) | M12: Team

Sheet Watershed plans
A1: Watershed plans: every combination of the recommended site actions
A2: 1 and 0 mark a site included or excluded. Rows that include a site whose recommendation is No Action are not valid plans.
C4: Site | D4: 17F2M | E4: 17D2E | F4: 17B | G4: 2A | H4: 2B | I4: 3E | J4: 3F | K4: 19A
C5: Carried | D5: =Sites!E5 | E5: =Sites!E6 | F5: =Sites!E7 | G5: =Sites!E8 | H5: =Sites!E9 | I5: =Sites!E10 | J5: =Sites!E11 | K5: =Sites!E12
C6: Lift (scaled) | D6: =Sites!I5 | E6: =Sites!I6 | F6: =Sites!I7 | G6: =Sites!I8 | H6: =Sites!I9 | I6: =Sites!I10 | J6: =Sites!I11 | K6: =Sites!I12
C7: Cost (scaled) | D7: =Sites!J5 | E7: =Sites!J6 | F7: =Sites!J7 | G7: =Sites!J8 | H7: =Sites!J9 | I7: =Sites!J10 | J7: =Sites!J11 | K7: =Sites!J12
C8: Construction cost | D8: =Sites!H5 | E8: =Sites!H6 | F8: =Sites!H7 | G8: =Sites!H8 | H8: =Sites!H9 | I8: =Sites!H10 | J8: =Sites!H11 | K8: =Sites!H12
C9: Weight | D9: =IF(D5=1,2^SUM(E5:$K$5),0) | E9: =IF(E5=1,2^SUM(F5:$K$5),0) | F9: =IF(F5=1,2^SUM(G5:$K$5),0) | G9: =IF(G5=1,2^SUM(H5:$K$5),0) | H9: =IF(H5=1,2^SUM(I5:$K$5),0) | I9: =IF(I5=1,2^SUM(J5:$K$5),0) | J9: =IF(J5=1,2^SUM(K5:$K$5),0) | K9: =IF(K5=1,1,0)
A11: Row | B11: Plan | C11: Valid | D11: 17F2M | E11: 17D2E | F11: 17B | G11: 2A | H11: 2B | I11: 3E | J11: 3F | K11: 19A | L11: Plan number | M11: Lift (scaled) | N11: Cost (scaled) | O11: Construction cost | P11: Lift (AAHU) | Q11: Average annual cost | R11: No Action | S11: Dominated by | T11: Cost-effective | U11: Candidate | V11: Slope in (max) | W11: Slope out (min) | X11: Best buy | Y11: Best-buy step | Z11: Previous lift (scaled) | AA11: Previous cost (scaled) | AB11: Incremental output | AC11: Incremental cost | AD11: Incremental cost per unit | AE11: Unit cost | AF11: Final array | AG11: Final array order
A12: 1 | B12: No Action | C12: =IF(SUMPRODUCT(D12:K12,1-$D$5:$K$5)=0,1,0) | D12: 0 | E12: 0 | F12: 0 | G12: 0 | H12: 0 | I12: 0 | J12: 0 | K12: 0 | L12: =IF(C12=1,1+SUMPRODUCT(D12:K12,$D$9:$K$9),"") | M12: =SUMPRODUCT(D12:K12,$D$6:$K$6) | N12: =SUMPRODUCT(D12:K12,$D$7:$K$7) | O12: =SUMPRODUCT(D12:K12,$D$8:$K$8) | P12: =M12/10^in_out_dp | Q12: =N12/10^in_cost_dp | R12: =IF(SUM(D12:K12)=0,1,0) | S12: =SUMPRODUCT($C$12:$C$267*(($M$12:$M$267=M12)*($N$12:$N$267<N12)+($M$12:$M$267>M12)*($N$12:$N$267<=N12))) | T12: =IF(C12=0,0,IF(OR(R12=1,S12=0),1,0)) | U12: =IF(AND(T12=1,R12=0,M12>0),1,0) | V12: =IF(U12=1,MAX(N12/M12,SUMPRODUCT(MAX(((N12-$N$12:$N$267)*($U$12:$U$267*($M$12:$M$267<M12)))/((M12-$M$12:$M$267)*($U$12:$U$267*($M$12:$M$267<M12))+1-($U$12:$U$267*($M$12:$M$267<M12)))-(1-($U$12:$U$267*($M$12:$M$267<M12)))*1E+300))),0) | W12: =IF(U12=1,SUMPRODUCT(MIN(((($N$12:$N$267-N12)*($U$12:$U$267*($M$12:$M$267>M12)))/(($M$12:$M$267-M12)*($U$12:$U$267*($M$12:$M$267>M12))+1-($U$12:$U$267*($M$12:$M$267>M12)))+(1-($U$12:$U$267*($M$12:$M$267>M12)))*1E+300))),0) | X12: =IF(C12=0,0,IF(R12=1,1,IF(AND(U12=1,V12<=W12),1,0))) | Y12: =IF(X12=1,1+SUMPRODUCT($X$12:$X$267*(($M$12:$M$267<M12)+($M$12:$M$267=M12)*($A$12:$A$267<A12))),0) | Z12: =IF(Y12<=1,0,SUMPRODUCT(($Y$12:$Y$267=Y12-1)*$M$12:$M$267)) | AA12: =IF(Y12<=1,0,SUMPRODUCT(($Y$12:$Y$267=Y12-1)*$N$12:$N$267)) | AB12: =IF(Y12=0,"",(M12-Z12)/10^in_out_dp) | AC12: =IF(Y12=0,"",(N12-AA12)/10^in_cost_dp) | AD12: =IF(Y12=0,"",IF(M12=Z12,0,AC12/AB12)) | AE12: =IF(AND(C12=1,M12>0),Q12/P12,"n/a") | AF12: 1 | AG12: =IF(AND(C12=1,AF12=1),1+SUMPRODUCT($C$12:$C$267*$AF$12:$AF$267*(($M$12:$M$267<M12)+($M$12:$M$267=M12)*($N$12:$N$267<N12)+($M$12:$M$267=M12)*($N$12:$N$267=N12)*($A$12:$A$267<A12))),0)
A13: 2 | B13: 19A | C13: =IF(SUMPRODUCT(D13:K13,1-$D$5:$K$5)=0,1,0) | D13: 0 | E13: 0 | F13: 0 | G13: 0 | H13: 0 | I13: 0 | J13: 0 | K13: 1 | L13: =IF(C13=1,1+SUMPRODUCT(D13:K13,$D$9:$K$9),"") | M13: =SUMPRODUCT(D13:K13,$D$6:$K$6) | N13: =SUMPRODUCT(D13:K13,$D$7:$K$7) | O13: =SUMPRODUCT(D13:K13,$D$8:$K$8) | P13: =M13/10^in_out_dp | Q13: =N13/10^in_cost_dp | R13: =IF(SUM(D13:K13)=0,1,0) | S13: =SUMPRODUCT($C$12:$C$267*(($M$12:$M$267=M13)*($N$12:$N$267<N13)+($M$12:$M$267>M13)*($N$12:$N$267<=N13))) | T13: =IF(C13=0,0,IF(OR(R13=1,S13=0),1,0)) | U13: =IF(AND(T13=1,R13=0,M13>0),1,0) | V13: =IF(U13=1,MAX(N13/M13,SUMPRODUCT(MAX(((N13-$N$12:$N$267)*($U$12:$U$267*($M$12:$M$267<M13)))/((M13-$M$12:$M$267)*($U$12:$U$267*($M$12:$M$267<M13))+1-($U$12:$U$267*($M$12:$M$267<M13)))-(1-($U$12:$U$267*($M$12:$M$267<M13)))*1E+300))),0) | W13: =IF(U13=1,SUMPRODUCT(MIN(((($N$12:$N$267-N13)*($U$12:$U$267*($M$12:$M$267>M13)))/(($M$12:$M$267-M13)*($U$12:$U$267*($M$12:$M$267>M13))+1-($U$12:$U$267*($M$12:$M$267>M13)))+(1-($U$12:$U$267*($M$12:$M$267>M13)))*1E+300))),0) | X13: =IF(C13=0,0,IF(R13=1,1,IF(AND(U13=1,V13<=W13),1,0))) | Y13: =IF(X13=1,1+SUMPRODUCT($X$12:$X$267*(($M$12:$M$267<M13)+($M$12:$M$267=M13)*($A$12:$A$267<A13))),0) | Z13: =IF(Y13<=1,0,SUMPRODUCT(($Y$12:$Y$267=Y13-1)*$M$12:$M$267)) | AA13: =IF(Y13<=1,0,SUMPRODUCT(($Y$12:$Y$267=Y13-1)*$N$12:$N$267)) | AB13: =IF(Y13=0,"",(M13-Z13)/10^in_out_dp) | AC13: =IF(Y13=0,"",(N13-AA13)/10^in_cost_dp) | AD13: =IF(Y13=0,"",IF(M13=Z13,0,AC13/AB13)) | AE13: =IF(AND(C13=1,M13>0),Q13/P13,"n/a") | AF13: 1 | AG13: =IF(AND(C13=1,AF13=1),1+SUMPRODUCT($C$12:$C$267*$AF$12:$AF$267*(($M$12:$M$267<M13)+($M$12:$M$267=M13)*($N$12:$N$267<N13)+($M$12:$M$267=M13)*($N$12:$N$267=N13)*($A$12:$A$267<A13))),0)
A14: 3 | B14: 3F | C14: =IF(SUMPRODUCT(D14:K14,1-$D$5:$K$5)=0,1,0) | D14: 0 | E14: 0 | F14: 0 | G14: 0 | H14: 0 | I14: 0 | J14: 1 | K14: 0 | L14: =IF(C14=1,1+SUMPRODUCT(D14:K14,$D$9:$K$9),"") | M14: =SUMPRODUCT(D14:K14,$D$6:$K$6) | N14: =SUMPRODUCT(D14:K14,$D$7:$K$7) | O14: =SUMPRODUCT(D14:K14,$D$8:$K$8) | P14: =M14/10^in_out_dp | Q14: =N14/10^in_cost_dp | R14: =IF(SUM(D14:K14)=0,1,0) | S14: =SUMPRODUCT($C$12:$C$267*(($M$12:$M$267=M14)*($N$12:$N$267<N14)+($M$12:$M$267>M14)*($N$12:$N$267<=N14))) | T14: =IF(C14=0,0,IF(OR(R14=1,S14=0),1,0)) | U14: =IF(AND(T14=1,R14=0,M14>0),1,0) | V14: =IF(U14=1,MAX(N14/M14,SUMPRODUCT(MAX(((N14-$N$12:$N$267)*($U$12:$U$267*($M$12:$M$267<M14)))/((M14-$M$12:$M$267)*($U$12:$U$267*($M$12:$M$267<M14))+1-($U$12:$U$267*($M$12:$M$267<M14)))-(1-($U$12:$U$267*($M$12:$M$267<M14)))*1E+300))),0) | W14: =IF(U14=1,SUMPRODUCT(MIN(((($N$12:$N$267-N14)*($U$12:$U$267*($M$12:$M$267>M14)))/(($M$12:$M$267-M14)*($U$12:$U$267*($M$12:$M$267>M14))+1-($U$12:$U$267*($M$12:$M$267>M14)))+(1-($U$12:$U$267*($M$12:$M$267>M14)))*1E+300))),0) | X14: =IF(C14=0,0,IF(R14=1,1,IF(AND(U14=1,V14<=W14),1,0))) | Y14: =IF(X14=1,1+SUMPRODUCT($X$12:$X$267*(($M$12:$M$267<M14)+($M$12:$M$267=M14)*($A$12:$A$267<A14))),0) | Z14: =IF(Y14<=1,0,SUMPRODUCT(($Y$12:$Y$267=Y14-1)*$M$12:$M$267)) | AA14: =IF(Y14<=1,0,SUMPRODUCT(($Y$12:$Y$267=Y14-1)*$N$12:$N$267)) | AB14: =IF(Y14=0,"",(M14-Z14)/10^in_out_dp) | AC14: =IF(Y14=0,"",(N14-AA14)/10^in_cost_dp) | AD14: =IF(Y14=0,"",IF(M14=Z14,0,AC14/AB14)) | AE14: =IF(AND(C14=1,M14>0),Q14/P14,"n/a") | AF14: 0 | AG14: =IF(AND(C14=1,AF14=1),1+SUMPRODUCT($C$12:$C$267*$AF$12:$AF$267*(($M$12:$M$267<M14)+($M$12:$M$267=M14)*($N$12:$N$267<N14)+($M$12:$M$267=M14)*($N$12:$N$267=N14)*($A$12:$A$267<A14))),0)
A15: 4 | B15: 3F + 19A | C15: =IF(SUMPRODUCT(D15:K15,1-$D$5:$K$5)=0,1,0) | D15: 0 | E15: 0 | F15: 0 | G15: 0 | H15: 0 | I15: 0 | J15: 1 | K15: 1 | L15: =IF(C15=1,1+SUMPRODUCT(D15:K15,$D$9:$K$9),"") | M15: =SUMPRODUCT(D15:K15,$D$6:$K$6) | N15: =SUMPRODUCT(D15:K15,$D$7:$K$7) | O15: =SUMPRODUCT(D15:K15,$D$8:$K$8) | P15: =M15/10^in_out_dp | Q15: =N15/10^in_cost_dp | R15: =IF(SUM(D15:K15)=0,1,0) | S15: =SUMPRODUCT($C$12:$C$267*(($M$12:$M$267=M15)*($N$12:$N$267<N15)+($M$12:$M$267>M15)*($N$12:$N$267<=N15))) | T15: =IF(C15=0,0,IF(OR(R15=1,S15=0),1,0)) | U15: =IF(AND(T15=1,R15=0,M15>0),1,0) | V15: =IF(U15=1,MAX(N15/M15,SUMPRODUCT(MAX(((N15-$N$12:$N$267)*($U$12:$U$267*($M$12:$M$267<M15)))/((M15-$M$12:$M$267)*($U$12:$U$267*($M$12:$M$267<M15))+1-($U$12:$U$267*($M$12:$M$267<M15)))-(1-($U$12:$U$267*($M$12:$M$267<M15)))*1E+300))),0) | W15: =IF(U15=1,SUMPRODUCT(MIN(((($N$12:$N$267-N15)*($U$12:$U$267*($M$12:$M$267>M15)))/(($M$12:$M$267-M15)*($U$12:$U$267*($M$12:$M$267>M15))+1-($U$12:$U$267*($M$12:$M$267>M15)))+(1-($U$12:$U$267*($M$12:$M$267>M15)))*1E+300))),0) | X15: =IF(C15=0,0,IF(R15=1,1,IF(AND(U15=1,V15<=W15),1,0))) | Y15: =IF(X15=1,1+SUMPRODUCT($X$12:$X$267*(($M$12:$M$267<M15)+($M$12:$M$267=M15)*($A$12:$A$267<A15))),0) | Z15: =IF(Y15<=1,0,SUMPRODUCT(($Y$12:$Y$267=Y15-1)*$M$12:$M$267)) | AA15: =IF(Y15<=1,0,SUMPRODUCT(($Y$12:$Y$267=Y15-1)*$N$12:$N$267)) | AB15: =IF(Y15=0,"",(M15-Z15)/10^in_out_dp) | AC15: =IF(Y15=0,"",(N15-AA15)/10^in_cost_dp) | AD15: =IF(Y15=0,"",IF(M15=Z15,0,AC15/AB15)) | AE15: =IF(AND(C15=1,M15>0),Q15/P15,"n/a") | AF15: 0 | AG15: =IF(AND(C15=1,AF15=1),1+SUMPRODUCT($C$12:$C$267*$AF$12:$AF$267*(($M$12:$M$267<M15)+($M$12:$M$267=M15)*($N$12:$N$267<N15)+($M$12:$M$267=M15)*($N$12:$N$267=N15)*($A$12:$A$267<A15))),0)
A16: 5 | B16: 3E | C16: =IF(SUMPRODUCT(D16:K16,1-$D$5:$K$5)=0,1,0) | D16: 0 | E16: 0 | F16: 0 | G16: 0 | H16: 0 | I16: 1 | J16: 0 | K16: 0 | L16: =IF(C16=1,1+SUMPRODUCT(D16:K16,$D$9:$K$9),"") | M16: =SUMPRODUCT(D16:K16,$D$6:$K$6) | N16: =SUMPRODUCT(D16:K16,$D$7:$K$7) | O16: =SUMPRODUCT(D16:K16,$D$8:$K$8) | P16: =M16/10^in_out_dp | Q16: =N16/10^in_cost_dp | R16: =IF(SUM(D16:K16)=0,1,0) | S16: =SUMPRODUCT($C$12:$C$267*(($M$12:$M$267=M16)*($N$12:$N$267<N16)+($M$12:$M$267>M16)*($N$12:$N$267<=N16))) | T16: =IF(C16=0,0,IF(OR(R16=1,S16=0),1,0)) | U16: =IF(AND(T16=1,R16=0,M16>0),1,0) | V16: =IF(U16=1,MAX(N16/M16,SUMPRODUCT(MAX(((N16-$N$12:$N$267)*($U$12:$U$267*($M$12:$M$267<M16)))/((M16-$M$12:$M$267)*($U$12:$U$267*($M$12:$M$267<M16))+1-($U$12:$U$267*($M$12:$M$267<M16)))-(1-($U$12:$U$267*($M$12:$M$267<M16)))*1E+300))),0) | W16: =IF(U16=1,SUMPRODUCT(MIN(((($N$12:$N$267-N16)*($U$12:$U$267*($M$12:$M$267>M16)))/(($M$12:$M$267-M16)*($U$12:$U$267*($M$12:$M$267>M16))+1-($U$12:$U$267*($M$12:$M$267>M16)))+(1-($U$12:$U$267*($M$12:$M$267>M16)))*1E+300))),0) | X16: =IF(C16=0,0,IF(R16=1,1,IF(AND(U16=1,V16<=W16),1,0))) | Y16: =IF(X16=1,1+SUMPRODUCT($X$12:$X$267*(($M$12:$M$267<M16)+($M$12:$M$267=M16)*($A$12:$A$267<A16))),0) | Z16: =IF(Y16<=1,0,SUMPRODUCT(($Y$12:$Y$267=Y16-1)*$M$12:$M$267)) | AA16: =IF(Y16<=1,0,SUMPRODUCT(($Y$12:$Y$267=Y16-1)*$N$12:$N$267)) | AB16: =IF(Y16=0,"",(M16-Z16)/10^in_out_dp) | AC16: =IF(Y16=0,"",(N16-AA16)/10^in_cost_dp) | AD16: =IF(Y16=0,"",IF(M16=Z16,0,AC16/AB16)) | AE16: =IF(AND(C16=1,M16>0),Q16/P16,"n/a") | AF16: 1 | AG16: =IF(AND(C16=1,AF16=1),1+SUMPRODUCT($C$12:$C$267*$AF$12:$AF$267*(($M$12:$M$267<M16)+($M$12:$M$267=M16)*($N$12:$N$267<N16)+($M$12:$M$267=M16)*($N$12:$N$267=N16)*($A$12:$A$267<A16))),0)
A17: 6 | B17: 3E + 19A | C17: =IF(SUMPRODUCT(D17:K17,1-$D$5:$K$5)=0,1,0) | D17: 0 | E17: 0 | F17: 0 | G17: 0 | H17: 0 | I17: 1 | J17: 0 | K17: 1 | L17: =IF(C17=1,1+SUMPRODUCT(D17:K17,$D$9:$K$9),"") | M17: =SUMPRODUCT(D17:K17,$D$6:$K$6) | N17: =SUMPRODUCT(D17:K17,$D$7:$K$7) | O17: =SUMPRODUCT(D17:K17,$D$8:$K$8) | P17: =M17/10^in_out_dp | Q17: =N17/10^in_cost_dp | R17: =IF(SUM(D17:K17)=0,1,0) | S17: =SUMPRODUCT($C$12:$C$267*(($M$12:$M$267=M17)*($N$12:$N$267<N17)+($M$12:$M$267>M17)*($N$12:$N$267<=N17))) | T17: =IF(C17=0,0,IF(OR(R17=1,S17=0),1,0)) | U17: =IF(AND(T17=1,R17=0,M17>0),1,0) | V17: =IF(U17=1,MAX(N17/M17,SUMPRODUCT(MAX(((N17-$N$12:$N$267)*($U$12:$U$267*($M$12:$M$267<M17)))/((M17-$M$12:$M$267)*($U$12:$U$267*($M$12:$M$267<M17))+1-($U$12:$U$267*($M$12:$M$267<M17)))-(1-($U$12:$U$267*($M$12:$M$267<M17)))*1E+300))),0) | W17: =IF(U17=1,SUMPRODUCT(MIN(((($N$12:$N$267-N17)*($U$12:$U$267*($M$12:$M$267>M17)))/(($M$12:$M$267-M17)*($U$12:$U$267*($M$12:$M$267>M17))+1-($U$12:$U$267*($M$12:$M$267>M17)))+(1-($U$12:$U$267*($M$12:$M$267>M17)))*1E+300))),0) | X17: =IF(C17=0,0,IF(R17=1,1,IF(AND(U17=1,V17<=W17),1,0))) | Y17: =IF(X17=1,1+SUMPRODUCT($X$12:$X$267*(($M$12:$M$267<M17)+($M$12:$M$267=M17)*($A$12:$A$267<A17))),0) | Z17: =IF(Y17<=1,0,SUMPRODUCT(($Y$12:$Y$267=Y17-1)*$M$12:$M$267)) | AA17: =IF(Y17<=1,0,SUMPRODUCT(($Y$12:$Y$267=Y17-1)*$N$12:$N$267)) | AB17: =IF(Y17=0,"",(M17-Z17)/10^in_out_dp) | AC17: =IF(Y17=0,"",(N17-AA17)/10^in_cost_dp) | AD17: =IF(Y17=0,"",IF(M17=Z17,0,AC17/AB17)) | AE17: =IF(AND(C17=1,M17>0),Q17/P17,"n/a") | AF17: 0 | AG17: =IF(AND(C17=1,AF17=1),1+SUMPRODUCT($C$12:$C$267*$AF$12:$AF$267*(($M$12:$M$267<M17)+($M$12:$M$267=M17)*($N$12:$N$267<N17)+($M$12:$M$267=M17)*($N$12:$N$267=N17)*($A$12:$A$267<A17))),0)
A18: 7 | B18: 3E + 3F | C18: =IF(SUMPRODUCT(D18:K18,1-$D$5:$K$5)=0,1,0) | D18: 0 | E18: 0 | F18: 0 | G18: 0 | H18: 0 | I18: 1 | J18: 1 | K18: 0 | L18: =IF(C18=1,1+SUMPRODUCT(D18:K18,$D$9:$K$9),"") | M18: =SUMPRODUCT(D18:K18,$D$6:$K$6) | N18: =SUMPRODUCT(D18:K18,$D$7:$K$7) | O18: =SUMPRODUCT(D18:K18,$D$8:$K$8) | P18: =M18/10^in_out_dp | Q18: =N18/10^in_cost_dp | R18: =IF(SUM(D18:K18)=0,1,0) | S18: =SUMPRODUCT($C$12:$C$267*(($M$12:$M$267=M18)*($N$12:$N$267<N18)+($M$12:$M$267>M18)*($N$12:$N$267<=N18))) | T18: =IF(C18=0,0,IF(OR(R18=1,S18=0),1,0)) | U18: =IF(AND(T18=1,R18=0,M18>0),1,0) | V18: =IF(U18=1,MAX(N18/M18,SUMPRODUCT(MAX(((N18-$N$12:$N$267)*($U$12:$U$267*($M$12:$M$267<M18)))/((M18-$M$12:$M$267)*($U$12:$U$267*($M$12:$M$267<M18))+1-($U$12:$U$267*($M$12:$M$267<M18)))-(1-($U$12:$U$267*($M$12:$M$267<M18)))*1E+300))),0) | W18: =IF(U18=1,SUMPRODUCT(MIN(((($N$12:$N$267-N18)*($U$12:$U$267*($M$12:$M$267>M18)))/(($M$12:$M$267-M18)*($U$12:$U$267*($M$12:$M$267>M18))+1-($U$12:$U$267*($M$12:$M$267>M18)))+(1-($U$12:$U$267*($M$12:$M$267>M18)))*1E+300))),0) | X18: =IF(C18=0,0,IF(R18=1,1,IF(AND(U18=1,V18<=W18),1,0))) | Y18: =IF(X18=1,1+SUMPRODUCT($X$12:$X$267*(($M$12:$M$267<M18)+($M$12:$M$267=M18)*($A$12:$A$267<A18))),0) | Z18: =IF(Y18<=1,0,SUMPRODUCT(($Y$12:$Y$267=Y18-1)*$M$12:$M$267)) | AA18: =IF(Y18<=1,0,SUMPRODUCT(($Y$12:$Y$267=Y18-1)*$N$12:$N$267)) | AB18: =IF(Y18=0,"",(M18-Z18)/10^in_out_dp) | AC18: =IF(Y18=0,"",(N18-AA18)/10^in_cost_dp) | AD18: =IF(Y18=0,"",IF(M18=Z18,0,AC18/AB18)) | AE18: =IF(AND(C18=1,M18>0),Q18/P18,"n/a") | AF18: 0 | AG18: =IF(AND(C18=1,AF18=1),1+SUMPRODUCT($C$12:$C$267*$AF$12:$AF$267*(($M$12:$M$267<M18)+($M$12:$M$267=M18)*($N$12:$N$267<N18)+($M$12:$M$267=M18)*($N$12:$N$267=N18)*($A$12:$A$267<A18))),0)
A19: 8 | B19: 3E + 3F + 19A | C19: =IF(SUMPRODUCT(D19:K19,1-$D$5:$K$5)=0,1,0) | D19: 0 | E19: 0 | F19: 0 | G19: 0 | H19: 0 | I19: 1 | J19: 1 | K19: 1 | L19: =IF(C19=1,1+SUMPRODUCT(D19:K19,$D$9:$K$9),"") | M19: =SUMPRODUCT(D19:K19,$D$6:$K$6) | N19: =SUMPRODUCT(D19:K19,$D$7:$K$7) | O19: =SUMPRODUCT(D19:K19,$D$8:$K$8) | P19: =M19/10^in_out_dp | Q19: =N19/10^in_cost_dp | R19: =IF(SUM(D19:K19)=0,1,0) | S19: =SUMPRODUCT($C$12:$C$267*(($M$12:$M$267=M19)*($N$12:$N$267<N19)+($M$12:$M$267>M19)*($N$12:$N$267<=N19))) | T19: =IF(C19=0,0,IF(OR(R19=1,S19=0),1,0)) | U19: =IF(AND(T19=1,R19=0,M19>0),1,0) | V19: =IF(U19=1,MAX(N19/M19,SUMPRODUCT(MAX(((N19-$N$12:$N$267)*($U$12:$U$267*($M$12:$M$267<M19)))/((M19-$M$12:$M$267)*($U$12:$U$267*($M$12:$M$267<M19))+1-($U$12:$U$267*($M$12:$M$267<M19)))-(1-($U$12:$U$267*($M$12:$M$267<M19)))*1E+300))),0) | W19: =IF(U19=1,SUMPRODUCT(MIN(((($N$12:$N$267-N19)*($U$12:$U$267*($M$12:$M$267>M19)))/(($M$12:$M$267-M19)*($U$12:$U$267*($M$12:$M$267>M19))+1-($U$12:$U$267*($M$12:$M$267>M19)))+(1-($U$12:$U$267*($M$12:$M$267>M19)))*1E+300))),0) | X19: =IF(C19=0,0,IF(R19=1,1,IF(AND(U19=1,V19<=W19),1,0))) | Y19: =IF(X19=1,1+SUMPRODUCT($X$12:$X$267*(($M$12:$M$267<M19)+($M$12:$M$267=M19)*($A$12:$A$267<A19))),0) | Z19: =IF(Y19<=1,0,SUMPRODUCT(($Y$12:$Y$267=Y19-1)*$M$12:$M$267)) | AA19: =IF(Y19<=1,0,SUMPRODUCT(($Y$12:$Y$267=Y19-1)*$N$12:$N$267)) | AB19: =IF(Y19=0,"",(M19-Z19)/10^in_out_dp) | AC19: =IF(Y19=0,"",(N19-AA19)/10^in_cost_dp) | AD19: =IF(Y19=0,"",IF(M19=Z19,0,AC19/AB19)) | AE19: =IF(AND(C19=1,M19>0),Q19/P19,"n/a") | AF19: 0 | AG19: =IF(AND(C19=1,AF19=1),1+SUMPRODUCT($C$12:$C$267*$AF$12:$AF$267*(($M$12:$M$267<M19)+($M$12:$M$267=M19)*($N$12:$N$267<N19)+($M$12:$M$267=M19)*($N$12:$N$267=N19)*($A$12:$A$267<A19))),0)
A20: 9 | B20: 2B | C20: =IF(SUMPRODUCT(D20:K20,1-$D$5:$K$5)=0,1,0) | D20: 0 | E20: 0 | F20: 0 | G20: 0 | H20: 1 | I20: 0 | J20: 0 | K20: 0 | L20: =IF(C20=1,1+SUMPRODUCT(D20:K20,$D$9:$K$9),"") | M20: =SUMPRODUCT(D20:K20,$D$6:$K$6) | N20: =SUMPRODUCT(D20:K20,$D$7:$K$7) | O20: =SUMPRODUCT(D20:K20,$D$8:$K$8) | P20: =M20/10^in_out_dp | Q20: =N20/10^in_cost_dp | R20: =IF(SUM(D20:K20)=0,1,0) | S20: =SUMPRODUCT($C$12:$C$267*(($M$12:$M$267=M20)*($N$12:$N$267<N20)+($M$12:$M$267>M20)*($N$12:$N$267<=N20))) | T20: =IF(C20=0,0,IF(OR(R20=1,S20=0),1,0)) | U20: =IF(AND(T20=1,R20=0,M20>0),1,0) | V20: =IF(U20=1,MAX(N20/M20,SUMPRODUCT(MAX(((N20-$N$12:$N$267)*($U$12:$U$267*($M$12:$M$267<M20)))/((M20-$M$12:$M$267)*($U$12:$U$267*($M$12:$M$267<M20))+1-($U$12:$U$267*($M$12:$M$267<M20)))-(1-($U$12:$U$267*($M$12:$M$267<M20)))*1E+300))),0) | W20: =IF(U20=1,SUMPRODUCT(MIN(((($N$12:$N$267-N20)*($U$12:$U$267*($M$12:$M$267>M20)))/(($M$12:$M$267-M20)*($U$12:$U$267*($M$12:$M$267>M20))+1-($U$12:$U$267*($M$12:$M$267>M20)))+(1-($U$12:$U$267*($M$12:$M$267>M20)))*1E+300))),0) | X20: =IF(C20=0,0,IF(R20=1,1,IF(AND(U20=1,V20<=W20),1,0))) | Y20: =IF(X20=1,1+SUMPRODUCT($X$12:$X$267*(($M$12:$M$267<M20)+($M$12:$M$267=M20)*($A$12:$A$267<A20))),0) | Z20: =IF(Y20<=1,0,SUMPRODUCT(($Y$12:$Y$267=Y20-1)*$M$12:$M$267)) | AA20: =IF(Y20<=1,0,SUMPRODUCT(($Y$12:$Y$267=Y20-1)*$N$12:$N$267)) | AB20: =IF(Y20=0,"",(M20-Z20)/10^in_out_dp) | AC20: =IF(Y20=0,"",(N20-AA20)/10^in_cost_dp) | AD20: =IF(Y20=0,"",IF(M20=Z20,0,AC20/AB20)) | AE20: =IF(AND(C20=1,M20>0),Q20/P20,"n/a") | AF20: 0 | AG20: =IF(AND(C20=1,AF20=1),1+SUMPRODUCT($C$12:$C$267*$AF$12:$AF$267*(($M$12:$M$267<M20)+($M$12:$M$267=M20)*($N$12:$N$267<N20)+($M$12:$M$267=M20)*($N$12:$N$267=N20)*($A$12:$A$267<A20))),0)
A21: 10 | B21: 2B + 19A | C21: =IF(SUMPRODUCT(D21:K21,1-$D$5:$K$5)=0,1,0) | D21: 0 | E21: 0 | F21: 0 | G21: 0 | H21: 1 | I21: 0 | J21: 0 | K21: 1 | L21: =IF(C21=1,1+SUMPRODUCT(D21:K21,$D$9:$K$9),"") | M21: =SUMPRODUCT(D21:K21,$D$6:$K$6) | N21: =SUMPRODUCT(D21:K21,$D$7:$K$7) | O21: =SUMPRODUCT(D21:K21,$D$8:$K$8) | P21: =M21/10^in_out_dp | Q21: =N21/10^in_cost_dp | R21: =IF(SUM(D21:K21)=0,1,0) | S21: =SUMPRODUCT($C$12:$C$267*(($M$12:$M$267=M21)*($N$12:$N$267<N21)+($M$12:$M$267>M21)*($N$12:$N$267<=N21))) | T21: =IF(C21=0,0,IF(OR(R21=1,S21=0),1,0)) | U21: =IF(AND(T21=1,R21=0,M21>0),1,0) | V21: =IF(U21=1,MAX(N21/M21,SUMPRODUCT(MAX(((N21-$N$12:$N$267)*($U$12:$U$267*($M$12:$M$267<M21)))/((M21-$M$12:$M$267)*($U$12:$U$267*($M$12:$M$267<M21))+1-($U$12:$U$267*($M$12:$M$267<M21)))-(1-($U$12:$U$267*($M$12:$M$267<M21)))*1E+300))),0) | W21: =IF(U21=1,SUMPRODUCT(MIN(((($N$12:$N$267-N21)*($U$12:$U$267*($M$12:$M$267>M21)))/(($M$12:$M$267-M21)*($U$12:$U$267*($M$12:$M$267>M21))+1-($U$12:$U$267*($M$12:$M$267>M21)))+(1-($U$12:$U$267*($M$12:$M$267>M21)))*1E+300))),0) | X21: =IF(C21=0,0,IF(R21=1,1,IF(AND(U21=1,V21<=W21),1,0))) | Y21: =IF(X21=1,1+SUMPRODUCT($X$12:$X$267*(($M$12:$M$267<M21)+($M$12:$M$267=M21)*($A$12:$A$267<A21))),0) | Z21: =IF(Y21<=1,0,SUMPRODUCT(($Y$12:$Y$267=Y21-1)*$M$12:$M$267)) | AA21: =IF(Y21<=1,0,SUMPRODUCT(($Y$12:$Y$267=Y21-1)*$N$12:$N$267)) | AB21: =IF(Y21=0,"",(M21-Z21)/10^in_out_dp) | AC21: =IF(Y21=0,"",(N21-AA21)/10^in_cost_dp) | AD21: =IF(Y21=0,"",IF(M21=Z21,0,AC21/AB21)) | AE21: =IF(AND(C21=1,M21>0),Q21/P21,"n/a") | AF21: 0 | AG21: =IF(AND(C21=1,AF21=1),1+SUMPRODUCT($C$12:$C$267*$AF$12:$AF$267*(($M$12:$M$267<M21)+($M$12:$M$267=M21)*($N$12:$N$267<N21)+($M$12:$M$267=M21)*($N$12:$N$267=N21)*($A$12:$A$267<A21))),0)
A22: 11 | B22: 2B + 3F | C22: =IF(SUMPRODUCT(D22:K22,1-$D$5:$K$5)=0,1,0) | D22: 0 | E22: 0 | F22: 0 | G22: 0 | H22: 1 | I22: 0 | J22: 1 | K22: 0 | L22: =IF(C22=1,1+SUMPRODUCT(D22:K22,$D$9:$K$9),"") | M22: =SUMPRODUCT(D22:K22,$D$6:$K$6) | N22: =SUMPRODUCT(D22:K22,$D$7:$K$7) | O22: =SUMPRODUCT(D22:K22,$D$8:$K$8) | P22: =M22/10^in_out_dp | Q22: =N22/10^in_cost_dp | R22: =IF(SUM(D22:K22)=0,1,0) | S22: =SUMPRODUCT($C$12:$C$267*(($M$12:$M$267=M22)*($N$12:$N$267<N22)+($M$12:$M$267>M22)*($N$12:$N$267<=N22))) | T22: =IF(C22=0,0,IF(OR(R22=1,S22=0),1,0)) | U22: =IF(AND(T22=1,R22=0,M22>0),1,0) | V22: =IF(U22=1,MAX(N22/M22,SUMPRODUCT(MAX(((N22-$N$12:$N$267)*($U$12:$U$267*($M$12:$M$267<M22)))/((M22-$M$12:$M$267)*($U$12:$U$267*($M$12:$M$267<M22))+1-($U$12:$U$267*($M$12:$M$267<M22)))-(1-($U$12:$U$267*($M$12:$M$267<M22)))*1E+300))),0) | W22: =IF(U22=1,SUMPRODUCT(MIN(((($N$12:$N$267-N22)*($U$12:$U$267*($M$12:$M$267>M22)))/(($M$12:$M$267-M22)*($U$12:$U$267*($M$12:$M$267>M22))+1-($U$12:$U$267*($M$12:$M$267>M22)))+(1-($U$12:$U$267*($M$12:$M$267>M22)))*1E+300))),0) | X22: =IF(C22=0,0,IF(R22=1,1,IF(AND(U22=1,V22<=W22),1,0))) | Y22: =IF(X22=1,1+SUMPRODUCT($X$12:$X$267*(($M$12:$M$267<M22)+($M$12:$M$267=M22)*($A$12:$A$267<A22))),0) | Z22: =IF(Y22<=1,0,SUMPRODUCT(($Y$12:$Y$267=Y22-1)*$M$12:$M$267)) | AA22: =IF(Y22<=1,0,SUMPRODUCT(($Y$12:$Y$267=Y22-1)*$N$12:$N$267)) | AB22: =IF(Y22=0,"",(M22-Z22)/10^in_out_dp) | AC22: =IF(Y22=0,"",(N22-AA22)/10^in_cost_dp) | AD22: =IF(Y22=0,"",IF(M22=Z22,0,AC22/AB22)) | AE22: =IF(AND(C22=1,M22>0),Q22/P22,"n/a") | AF22: 0 | AG22: =IF(AND(C22=1,AF22=1),1+SUMPRODUCT($C$12:$C$267*$AF$12:$AF$267*(($M$12:$M$267<M22)+($M$12:$M$267=M22)*($N$12:$N$267<N22)+($M$12:$M$267=M22)*($N$12:$N$267=N22)*($A$12:$A$267<A22))),0)
A23: 12 | B23: 2B + 3F + 19A | C23: =IF(SUMPRODUCT(D23:K23,1-$D$5:$K$5)=0,1,0) | D23: 0 | E23: 0 | F23: 0 | G23: 0 | H23: 1 | I23: 0 | J23: 1 | K23: 1 | L23: =IF(C23=1,1+SUMPRODUCT(D23:K23,$D$9:$K$9),"") | M23: =SUMPRODUCT(D23:K23,$D$6:$K$6) | N23: =SUMPRODUCT(D23:K23,$D$7:$K$7) | O23: =SUMPRODUCT(D23:K23,$D$8:$K$8) | P23: =M23/10^in_out_dp | Q23: =N23/10^in_cost_dp | R23: =IF(SUM(D23:K23)=0,1,0) | S23: =SUMPRODUCT($C$12:$C$267*(($M$12:$M$267=M23)*($N$12:$N$267<N23)+($M$12:$M$267>M23)*($N$12:$N$267<=N23))) | T23: =IF(C23=0,0,IF(OR(R23=1,S23=0),1,0)) | U23: =IF(AND(T23=1,R23=0,M23>0),1,0) | V23: =IF(U23=1,MAX(N23/M23,SUMPRODUCT(MAX(((N23-$N$12:$N$267)*($U$12:$U$267*($M$12:$M$267<M23)))/((M23-$M$12:$M$267)*($U$12:$U$267*($M$12:$M$267<M23))+1-($U$12:$U$267*($M$12:$M$267<M23)))-(1-($U$12:$U$267*($M$12:$M$267<M23)))*1E+300))),0) | W23: =IF(U23=1,SUMPRODUCT(MIN(((($N$12:$N$267-N23)*($U$12:$U$267*($M$12:$M$267>M23)))/(($M$12:$M$267-M23)*($U$12:$U$267*($M$12:$M$267>M23))+1-($U$12:$U$267*($M$12:$M$267>M23)))+(1-($U$12:$U$267*($M$12:$M$267>M23)))*1E+300))),0) | X23: =IF(C23=0,0,IF(R23=1,1,IF(AND(U23=1,V23<=W23),1,0))) | Y23: =IF(X23=1,1+SUMPRODUCT($X$12:$X$267*(($M$12:$M$267<M23)+($M$12:$M$267=M23)*($A$12:$A$267<A23))),0) | Z23: =IF(Y23<=1,0,SUMPRODUCT(($Y$12:$Y$267=Y23-1)*$M$12:$M$267)) | AA23: =IF(Y23<=1,0,SUMPRODUCT(($Y$12:$Y$267=Y23-1)*$N$12:$N$267)) | AB23: =IF(Y23=0,"",(M23-Z23)/10^in_out_dp) | AC23: =IF(Y23=0,"",(N23-AA23)/10^in_cost_dp) | AD23: =IF(Y23=0,"",IF(M23=Z23,0,AC23/AB23)) | AE23: =IF(AND(C23=1,M23>0),Q23/P23,"n/a") | AF23: 0 | AG23: =IF(AND(C23=1,AF23=1),1+SUMPRODUCT($C$12:$C$267*$AF$12:$AF$267*(($M$12:$M$267<M23)+($M$12:$M$267=M23)*($N$12:$N$267<N23)+($M$12:$M$267=M23)*($N$12:$N$267=N23)*($A$12:$A$267<A23))),0)
... A267: 256 | B267: 17F2M + 17D2E + 17B + 2A + 2B + 3E + 3F + 19A | C267: =IF(SUMPRODUCT(D267:K267,1-$D$5:$K$5)=0,1,0) | D267: 1 | E267: 1 | F267: 1 | G267: 1 | H267: 1 | I267: 1 | J267: 1 | K267: 1 | L267: =IF(C267=1,1+SUMPRODUCT(D267:K267,$D$9:$K$9),"") | M267: =SUMPRODUCT(D267:K267,$D$6:$K$6) | N267: =SUMPRODUCT(D267:K267,$D$7:$K$7) | O267: =SUMPRODUCT(D267:K267,$D$8:$K$8) | P267: =M267/10^in_out_dp | Q267: =N267/10^in_cost_dp | R267: =IF(SUM(D267:K267)=0,1,0) | S267: =SUMPRODUCT($C$12:$C$267*(($M$12:$M$267=M267)*($N$12:$N$267<N267)+($M$12:$M$267>M267)*($N$12:$N$267<=N267))) | T267: =IF(C267=0,0,IF(OR(R267=1,S267=0),1,0)) | U267: =IF(AND(T267=1,R267=0,M267>0),1,0) | V267: =IF(U267=1,MAX(N267/M267,SUMPRODUCT(MAX(((N267-$N$12:$N$267)*($U$12:$U$267*($M$12:$M$267<M267)))/((M267-$M$12:$M$267)*($U$12:$U$267*($M$12:$M$267<M267))+1-($U$12:$U$267*($M$12:$M$267<M267)))-(1-($U$12:$U$267*($M$12:$M$267<M267)))*1E+300))),0) | W267: =IF(U267=1,SUMPRODUCT(MIN(((($N$12:$N$267-N267)*($U$12:$U$267*($M$12:$M$267>M267)))/(($M$12:$M$267-M267)*($U$12:$U$267*($M$12:$M$267>M267))+1-($U$12:$U$267*($M$12:$M$267>M267)))+(1-($U$12:$U$267*($M$12:$M$267>M267)))*1E+300))),0) | X267: =IF(C267=0,0,IF(R267=1,1,IF(AND(U267=1,V267<=W267),1,0))) | Y267: =IF(X267=1,1+SUMPRODUCT($X$12:$X$267*(($M$12:$M$267<M267)+($M$12:$M$267=M267)*($A$12:$A$267<A267))),0) | Z267: =IF(Y267<=1,0,SUMPRODUCT(($Y$12:$Y$267=Y267-1)*$M$12:$M$267)) | AA267: =IF(Y267<=1,0,SUMPRODUCT(($Y$12:$Y$267=Y267-1)*$N$12:$N$267)) | AB267: =IF(Y267=0,"",(M267-Z267)/10^in_out_dp) | AC267: =IF(Y267=0,"",(N267-AA267)/10^in_cost_dp) | AD267: =IF(Y267=0,"",IF(M267=Z267,0,AC267/AB267)) | AE267: =IF(AND(C267=1,M267>0),Q267/P267,"n/a") | AF267: 0 | AG267: =IF(AND(C267=1,AF267=1),1+SUMPRODUCT($C$12:$C$267*$AF$12:$AF$267*(($M$12:$M$267<M267)+($M$12:$M$267=M267)*($N$12:$N$267<N267)+($M$12:$M$267=M267)*($N$12:$N$267=N267)*($A$12:$A$267<A267))),0)

Sheet Watershed summary
A1: Watershed summary: best buys, final array and the tentatively selected plan
A2: Tables read the watershed plans sheet. Choose the TSP from the final array.
A4: Best buys
A5: Step | B5: Plan number | C5: Plan | D5: Lift (AAHU) | E5: Average annual cost | F5: Construction cost | G5: Unit cost | H5: Incremental cost per unit
A6: 1 | B6: =IFERROR(INDEX('Watershed plans'!$L$12:$L$267,MATCH(1,'Watershed plans'!$Y$12:$Y$267,0)),"") | C6: =IFERROR(INDEX('Watershed plans'!$B$12:$B$267,MATCH(1,'Watershed plans'!$Y$12:$Y$267,0)),"") | D6: =IFERROR(INDEX('Watershed plans'!$P$12:$P$267,MATCH(1,'Watershed plans'!$Y$12:$Y$267,0)),"") | E6: =IFERROR(INDEX('Watershed plans'!$Q$12:$Q$267,MATCH(1,'Watershed plans'!$Y$12:$Y$267,0)),"") | F6: =IFERROR(INDEX('Watershed plans'!$O$12:$O$267,MATCH(1,'Watershed plans'!$Y$12:$Y$267,0)),"") | G6: =IFERROR(INDEX('Watershed plans'!$AE$12:$AE$267,MATCH(1,'Watershed plans'!$Y$12:$Y$267,0)),"") | H6: =IFERROR(INDEX('Watershed plans'!$AD$12:$AD$267,MATCH(1,'Watershed plans'!$Y$12:$Y$267,0)),"")
A7: 2 | B7: =IFERROR(INDEX('Watershed plans'!$L$12:$L$267,MATCH(2,'Watershed plans'!$Y$12:$Y$267,0)),"") | C7: =IFERROR(INDEX('Watershed plans'!$B$12:$B$267,MATCH(2,'Watershed plans'!$Y$12:$Y$267,0)),"") | D7: =IFERROR(INDEX('Watershed plans'!$P$12:$P$267,MATCH(2,'Watershed plans'!$Y$12:$Y$267,0)),"") | E7: =IFERROR(INDEX('Watershed plans'!$Q$12:$Q$267,MATCH(2,'Watershed plans'!$Y$12:$Y$267,0)),"") | F7: =IFERROR(INDEX('Watershed plans'!$O$12:$O$267,MATCH(2,'Watershed plans'!$Y$12:$Y$267,0)),"") | G7: =IFERROR(INDEX('Watershed plans'!$AE$12:$AE$267,MATCH(2,'Watershed plans'!$Y$12:$Y$267,0)),"") | H7: =IFERROR(INDEX('Watershed plans'!$AD$12:$AD$267,MATCH(2,'Watershed plans'!$Y$12:$Y$267,0)),"")
A8: 3 | B8: =IFERROR(INDEX('Watershed plans'!$L$12:$L$267,MATCH(3,'Watershed plans'!$Y$12:$Y$267,0)),"") | C8: =IFERROR(INDEX('Watershed plans'!$B$12:$B$267,MATCH(3,'Watershed plans'!$Y$12:$Y$267,0)),"") | D8: =IFERROR(INDEX('Watershed plans'!$P$12:$P$267,MATCH(3,'Watershed plans'!$Y$12:$Y$267,0)),"") | E8: =IFERROR(INDEX('Watershed plans'!$Q$12:$Q$267,MATCH(3,'Watershed plans'!$Y$12:$Y$267,0)),"") | F8: =IFERROR(INDEX('Watershed plans'!$O$12:$O$267,MATCH(3,'Watershed plans'!$Y$12:$Y$267,0)),"") | G8: =IFERROR(INDEX('Watershed plans'!$AE$12:$AE$267,MATCH(3,'Watershed plans'!$Y$12:$Y$267,0)),"") | H8: =IFERROR(INDEX('Watershed plans'!$AD$12:$AD$267,MATCH(3,'Watershed plans'!$Y$12:$Y$267,0)),"")
A9: 4 | B9: =IFERROR(INDEX('Watershed plans'!$L$12:$L$267,MATCH(4,'Watershed plans'!$Y$12:$Y$267,0)),"") | C9: =IFERROR(INDEX('Watershed plans'!$B$12:$B$267,MATCH(4,'Watershed plans'!$Y$12:$Y$267,0)),"") | D9: =IFERROR(INDEX('Watershed plans'!$P$12:$P$267,MATCH(4,'Watershed plans'!$Y$12:$Y$267,0)),"") | E9: =IFERROR(INDEX('Watershed plans'!$Q$12:$Q$267,MATCH(4,'Watershed plans'!$Y$12:$Y$267,0)),"") | F9: =IFERROR(INDEX('Watershed plans'!$O$12:$O$267,MATCH(4,'Watershed plans'!$Y$12:$Y$267,0)),"") | G9: =IFERROR(INDEX('Watershed plans'!$AE$12:$AE$267,MATCH(4,'Watershed plans'!$Y$12:$Y$267,0)),"") | H9: =IFERROR(INDEX('Watershed plans'!$AD$12:$AD$267,MATCH(4,'Watershed plans'!$Y$12:$Y$267,0)),"")
A10: 5 | B10: =IFERROR(INDEX('Watershed plans'!$L$12:$L$267,MATCH(5,'Watershed plans'!$Y$12:$Y$267,0)),"") | C10: =IFERROR(INDEX('Watershed plans'!$B$12:$B$267,MATCH(5,'Watershed plans'!$Y$12:$Y$267,0)),"") | D10: =IFERROR(INDEX('Watershed plans'!$P$12:$P$267,MATCH(5,'Watershed plans'!$Y$12:$Y$267,0)),"") | E10: =IFERROR(INDEX('Watershed plans'!$Q$12:$Q$267,MATCH(5,'Watershed plans'!$Y$12:$Y$267,0)),"") | F10: =IFERROR(INDEX('Watershed plans'!$O$12:$O$267,MATCH(5,'Watershed plans'!$Y$12:$Y$267,0)),"") | G10: =IFERROR(INDEX('Watershed plans'!$AE$12:$AE$267,MATCH(5,'Watershed plans'!$Y$12:$Y$267,0)),"") | H10: =IFERROR(INDEX('Watershed plans'!$AD$12:$AD$267,MATCH(5,'Watershed plans'!$Y$12:$Y$267,0)),"")
A11: 6 | B11: =IFERROR(INDEX('Watershed plans'!$L$12:$L$267,MATCH(6,'Watershed plans'!$Y$12:$Y$267,0)),"") | C11: =IFERROR(INDEX('Watershed plans'!$B$12:$B$267,MATCH(6,'Watershed plans'!$Y$12:$Y$267,0)),"") | D11: =IFERROR(INDEX('Watershed plans'!$P$12:$P$267,MATCH(6,'Watershed plans'!$Y$12:$Y$267,0)),"") | E11: =IFERROR(INDEX('Watershed plans'!$Q$12:$Q$267,MATCH(6,'Watershed plans'!$Y$12:$Y$267,0)),"") | F11: =IFERROR(INDEX('Watershed plans'!$O$12:$O$267,MATCH(6,'Watershed plans'!$Y$12:$Y$267,0)),"") | G11: =IFERROR(INDEX('Watershed plans'!$AE$12:$AE$267,MATCH(6,'Watershed plans'!$Y$12:$Y$267,0)),"") | H11: =IFERROR(INDEX('Watershed plans'!$AD$12:$AD$267,MATCH(6,'Watershed plans'!$Y$12:$Y$267,0)),"")
A12: 7 | B12: =IFERROR(INDEX('Watershed plans'!$L$12:$L$267,MATCH(7,'Watershed plans'!$Y$12:$Y$267,0)),"") | C12: =IFERROR(INDEX('Watershed plans'!$B$12:$B$267,MATCH(7,'Watershed plans'!$Y$12:$Y$267,0)),"") | D12: =IFERROR(INDEX('Watershed plans'!$P$12:$P$267,MATCH(7,'Watershed plans'!$Y$12:$Y$267,0)),"") | E12: =IFERROR(INDEX('Watershed plans'!$Q$12:$Q$267,MATCH(7,'Watershed plans'!$Y$12:$Y$267,0)),"") | F12: =IFERROR(INDEX('Watershed plans'!$O$12:$O$267,MATCH(7,'Watershed plans'!$Y$12:$Y$267,0)),"") | G12: =IFERROR(INDEX('Watershed plans'!$AE$12:$AE$267,MATCH(7,'Watershed plans'!$Y$12:$Y$267,0)),"") | H12: =IFERROR(INDEX('Watershed plans'!$AD$12:$AD$267,MATCH(7,'Watershed plans'!$Y$12:$Y$267,0)),"")
A13: 8 | B13: =IFERROR(INDEX('Watershed plans'!$L$12:$L$267,MATCH(8,'Watershed plans'!$Y$12:$Y$267,0)),"") | C13: =IFERROR(INDEX('Watershed plans'!$B$12:$B$267,MATCH(8,'Watershed plans'!$Y$12:$Y$267,0)),"") | D13: =IFERROR(INDEX('Watershed plans'!$P$12:$P$267,MATCH(8,'Watershed plans'!$Y$12:$Y$267,0)),"") | E13: =IFERROR(INDEX('Watershed plans'!$Q$12:$Q$267,MATCH(8,'Watershed plans'!$Y$12:$Y$267,0)),"") | F13: =IFERROR(INDEX('Watershed plans'!$O$12:$O$267,MATCH(8,'Watershed plans'!$Y$12:$Y$267,0)),"") | G13: =IFERROR(INDEX('Watershed plans'!$AE$12:$AE$267,MATCH(8,'Watershed plans'!$Y$12:$Y$267,0)),"") | H13: =IFERROR(INDEX('Watershed plans'!$AD$12:$AD$267,MATCH(8,'Watershed plans'!$Y$12:$Y$267,0)),"")
A14: 9 | B14: =IFERROR(INDEX('Watershed plans'!$L$12:$L$267,MATCH(9,'Watershed plans'!$Y$12:$Y$267,0)),"") | C14: =IFERROR(INDEX('Watershed plans'!$B$12:$B$267,MATCH(9,'Watershed plans'!$Y$12:$Y$267,0)),"") | D14: =IFERROR(INDEX('Watershed plans'!$P$12:$P$267,MATCH(9,'Watershed plans'!$Y$12:$Y$267,0)),"") | E14: =IFERROR(INDEX('Watershed plans'!$Q$12:$Q$267,MATCH(9,'Watershed plans'!$Y$12:$Y$267,0)),"") | F14: =IFERROR(INDEX('Watershed plans'!$O$12:$O$267,MATCH(9,'Watershed plans'!$Y$12:$Y$267,0)),"") | G14: =IFERROR(INDEX('Watershed plans'!$AE$12:$AE$267,MATCH(9,'Watershed plans'!$Y$12:$Y$267,0)),"") | H14: =IFERROR(INDEX('Watershed plans'!$AD$12:$AD$267,MATCH(9,'Watershed plans'!$Y$12:$Y$267,0)),"")
A15: 10 | B15: =IFERROR(INDEX('Watershed plans'!$L$12:$L$267,MATCH(10,'Watershed plans'!$Y$12:$Y$267,0)),"") | C15: =IFERROR(INDEX('Watershed plans'!$B$12:$B$267,MATCH(10,'Watershed plans'!$Y$12:$Y$267,0)),"") | D15: =IFERROR(INDEX('Watershed plans'!$P$12:$P$267,MATCH(10,'Watershed plans'!$Y$12:$Y$267,0)),"") | E15: =IFERROR(INDEX('Watershed plans'!$Q$12:$Q$267,MATCH(10,'Watershed plans'!$Y$12:$Y$267,0)),"") | F15: =IFERROR(INDEX('Watershed plans'!$O$12:$O$267,MATCH(10,'Watershed plans'!$Y$12:$Y$267,0)),"") | G15: =IFERROR(INDEX('Watershed plans'!$AE$12:$AE$267,MATCH(10,'Watershed plans'!$Y$12:$Y$267,0)),"") | H15: =IFERROR(INDEX('Watershed plans'!$AD$12:$AD$267,MATCH(10,'Watershed plans'!$Y$12:$Y$267,0)),"")
A16: 11 | B16: =IFERROR(INDEX('Watershed plans'!$L$12:$L$267,MATCH(11,'Watershed plans'!$Y$12:$Y$267,0)),"") | C16: =IFERROR(INDEX('Watershed plans'!$B$12:$B$267,MATCH(11,'Watershed plans'!$Y$12:$Y$267,0)),"") | D16: =IFERROR(INDEX('Watershed plans'!$P$12:$P$267,MATCH(11,'Watershed plans'!$Y$12:$Y$267,0)),"") | E16: =IFERROR(INDEX('Watershed plans'!$Q$12:$Q$267,MATCH(11,'Watershed plans'!$Y$12:$Y$267,0)),"") | F16: =IFERROR(INDEX('Watershed plans'!$O$12:$O$267,MATCH(11,'Watershed plans'!$Y$12:$Y$267,0)),"") | G16: =IFERROR(INDEX('Watershed plans'!$AE$12:$AE$267,MATCH(11,'Watershed plans'!$Y$12:$Y$267,0)),"") | H16: =IFERROR(INDEX('Watershed plans'!$AD$12:$AD$267,MATCH(11,'Watershed plans'!$Y$12:$Y$267,0)),"")
A17: 12 | B17: =IFERROR(INDEX('Watershed plans'!$L$12:$L$267,MATCH(12,'Watershed plans'!$Y$12:$Y$267,0)),"") | C17: =IFERROR(INDEX('Watershed plans'!$B$12:$B$267,MATCH(12,'Watershed plans'!$Y$12:$Y$267,0)),"") | D17: =IFERROR(INDEX('Watershed plans'!$P$12:$P$267,MATCH(12,'Watershed plans'!$Y$12:$Y$267,0)),"") | E17: =IFERROR(INDEX('Watershed plans'!$Q$12:$Q$267,MATCH(12,'Watershed plans'!$Y$12:$Y$267,0)),"") | F17: =IFERROR(INDEX('Watershed plans'!$O$12:$O$267,MATCH(12,'Watershed plans'!$Y$12:$Y$267,0)),"") | G17: =IFERROR(INDEX('Watershed plans'!$AE$12:$AE$267,MATCH(12,'Watershed plans'!$Y$12:$Y$267,0)),"") | H17: =IFERROR(INDEX('Watershed plans'!$AD$12:$AD$267,MATCH(12,'Watershed plans'!$Y$12:$Y$267,0)),"")
A18: 13 | B18: =IFERROR(INDEX('Watershed plans'!$L$12:$L$267,MATCH(13,'Watershed plans'!$Y$12:$Y$267,0)),"") | C18: =IFERROR(INDEX('Watershed plans'!$B$12:$B$267,MATCH(13,'Watershed plans'!$Y$12:$Y$267,0)),"") | D18: =IFERROR(INDEX('Watershed plans'!$P$12:$P$267,MATCH(13,'Watershed plans'!$Y$12:$Y$267,0)),"") | E18: =IFERROR(INDEX('Watershed plans'!$Q$12:$Q$267,MATCH(13,'Watershed plans'!$Y$12:$Y$267,0)),"") | F18: =IFERROR(INDEX('Watershed plans'!$O$12:$O$267,MATCH(13,'Watershed plans'!$Y$12:$Y$267,0)),"") | G18: =IFERROR(INDEX('Watershed plans'!$AE$12:$AE$267,MATCH(13,'Watershed plans'!$Y$12:$Y$267,0)),"") | H18: =IFERROR(INDEX('Watershed plans'!$AD$12:$AD$267,MATCH(13,'Watershed plans'!$Y$12:$Y$267,0)),"")
A19: 14 | B19: =IFERROR(INDEX('Watershed plans'!$L$12:$L$267,MATCH(14,'Watershed plans'!$Y$12:$Y$267,0)),"") | C19: =IFERROR(INDEX('Watershed plans'!$B$12:$B$267,MATCH(14,'Watershed plans'!$Y$12:$Y$267,0)),"") | D19: =IFERROR(INDEX('Watershed plans'!$P$12:$P$267,MATCH(14,'Watershed plans'!$Y$12:$Y$267,0)),"") | E19: =IFERROR(INDEX('Watershed plans'!$Q$12:$Q$267,MATCH(14,'Watershed plans'!$Y$12:$Y$267,0)),"") | F19: =IFERROR(INDEX('Watershed plans'!$O$12:$O$267,MATCH(14,'Watershed plans'!$Y$12:$Y$267,0)),"") | G19: =IFERROR(INDEX('Watershed plans'!$AE$12:$AE$267,MATCH(14,'Watershed plans'!$Y$12:$Y$267,0)),"") | H19: =IFERROR(INDEX('Watershed plans'!$AD$12:$AD$267,MATCH(14,'Watershed plans'!$Y$12:$Y$267,0)),"")
A20: 15 | B20: =IFERROR(INDEX('Watershed plans'!$L$12:$L$267,MATCH(15,'Watershed plans'!$Y$12:$Y$267,0)),"") | C20: =IFERROR(INDEX('Watershed plans'!$B$12:$B$267,MATCH(15,'Watershed plans'!$Y$12:$Y$267,0)),"") | D20: =IFERROR(INDEX('Watershed plans'!$P$12:$P$267,MATCH(15,'Watershed plans'!$Y$12:$Y$267,0)),"") | E20: =IFERROR(INDEX('Watershed plans'!$Q$12:$Q$267,MATCH(15,'Watershed plans'!$Y$12:$Y$267,0)),"") | F20: =IFERROR(INDEX('Watershed plans'!$O$12:$O$267,MATCH(15,'Watershed plans'!$Y$12:$Y$267,0)),"") | G20: =IFERROR(INDEX('Watershed plans'!$AE$12:$AE$267,MATCH(15,'Watershed plans'!$Y$12:$Y$267,0)),"") | H20: =IFERROR(INDEX('Watershed plans'!$AD$12:$AD$267,MATCH(15,'Watershed plans'!$Y$12:$Y$267,0)),"")
A21: 16 | B21: =IFERROR(INDEX('Watershed plans'!$L$12:$L$267,MATCH(16,'Watershed plans'!$Y$12:$Y$267,0)),"") | C21: =IFERROR(INDEX('Watershed plans'!$B$12:$B$267,MATCH(16,'Watershed plans'!$Y$12:$Y$267,0)),"") | D21: =IFERROR(INDEX('Watershed plans'!$P$12:$P$267,MATCH(16,'Watershed plans'!$Y$12:$Y$267,0)),"") | E21: =IFERROR(INDEX('Watershed plans'!$Q$12:$Q$267,MATCH(16,'Watershed plans'!$Y$12:$Y$267,0)),"") | F21: =IFERROR(INDEX('Watershed plans'!$O$12:$O$267,MATCH(16,'Watershed plans'!$Y$12:$Y$267,0)),"") | G21: =IFERROR(INDEX('Watershed plans'!$AE$12:$AE$267,MATCH(16,'Watershed plans'!$Y$12:$Y$267,0)),"") | H21: =IFERROR(INDEX('Watershed plans'!$AD$12:$AD$267,MATCH(16,'Watershed plans'!$Y$12:$Y$267,0)),"")
A22: 17 | B22: =IFERROR(INDEX('Watershed plans'!$L$12:$L$267,MATCH(17,'Watershed plans'!$Y$12:$Y$267,0)),"") | C22: =IFERROR(INDEX('Watershed plans'!$B$12:$B$267,MATCH(17,'Watershed plans'!$Y$12:$Y$267,0)),"") | D22: =IFERROR(INDEX('Watershed plans'!$P$12:$P$267,MATCH(17,'Watershed plans'!$Y$12:$Y$267,0)),"") | E22: =IFERROR(INDEX('Watershed plans'!$Q$12:$Q$267,MATCH(17,'Watershed plans'!$Y$12:$Y$267,0)),"") | F22: =IFERROR(INDEX('Watershed plans'!$O$12:$O$267,MATCH(17,'Watershed plans'!$Y$12:$Y$267,0)),"") | G22: =IFERROR(INDEX('Watershed plans'!$AE$12:$AE$267,MATCH(17,'Watershed plans'!$Y$12:$Y$267,0)),"") | H22: =IFERROR(INDEX('Watershed plans'!$AD$12:$AD$267,MATCH(17,'Watershed plans'!$Y$12:$Y$267,0)),"")
A23: 18 | B23: =IFERROR(INDEX('Watershed plans'!$L$12:$L$267,MATCH(18,'Watershed plans'!$Y$12:$Y$267,0)),"") | C23: =IFERROR(INDEX('Watershed plans'!$B$12:$B$267,MATCH(18,'Watershed plans'!$Y$12:$Y$267,0)),"") | D23: =IFERROR(INDEX('Watershed plans'!$P$12:$P$267,MATCH(18,'Watershed plans'!$Y$12:$Y$267,0)),"") | E23: =IFERROR(INDEX('Watershed plans'!$Q$12:$Q$267,MATCH(18,'Watershed plans'!$Y$12:$Y$267,0)),"") | F23: =IFERROR(INDEX('Watershed plans'!$O$12:$O$267,MATCH(18,'Watershed plans'!$Y$12:$Y$267,0)),"") | G23: =IFERROR(INDEX('Watershed plans'!$AE$12:$AE$267,MATCH(18,'Watershed plans'!$Y$12:$Y$267,0)),"") | H23: =IFERROR(INDEX('Watershed plans'!$AD$12:$AD$267,MATCH(18,'Watershed plans'!$Y$12:$Y$267,0)),"")
A24: 19 | B24: =IFERROR(INDEX('Watershed plans'!$L$12:$L$267,MATCH(19,'Watershed plans'!$Y$12:$Y$267,0)),"") | C24: =IFERROR(INDEX('Watershed plans'!$B$12:$B$267,MATCH(19,'Watershed plans'!$Y$12:$Y$267,0)),"") | D24: =IFERROR(INDEX('Watershed plans'!$P$12:$P$267,MATCH(19,'Watershed plans'!$Y$12:$Y$267,0)),"") | E24: =IFERROR(INDEX('Watershed plans'!$Q$12:$Q$267,MATCH(19,'Watershed plans'!$Y$12:$Y$267,0)),"") | F24: =IFERROR(INDEX('Watershed plans'!$O$12:$O$267,MATCH(19,'Watershed plans'!$Y$12:$Y$267,0)),"") | G24: =IFERROR(INDEX('Watershed plans'!$AE$12:$AE$267,MATCH(19,'Watershed plans'!$Y$12:$Y$267,0)),"") | H24: =IFERROR(INDEX('Watershed plans'!$AD$12:$AD$267,MATCH(19,'Watershed plans'!$Y$12:$Y$267,0)),"")
A25: 20 | B25: =IFERROR(INDEX('Watershed plans'!$L$12:$L$267,MATCH(20,'Watershed plans'!$Y$12:$Y$267,0)),"") | C25: =IFERROR(INDEX('Watershed plans'!$B$12:$B$267,MATCH(20,'Watershed plans'!$Y$12:$Y$267,0)),"") | D25: =IFERROR(INDEX('Watershed plans'!$P$12:$P$267,MATCH(20,'Watershed plans'!$Y$12:$Y$267,0)),"") | E25: =IFERROR(INDEX('Watershed plans'!$Q$12:$Q$267,MATCH(20,'Watershed plans'!$Y$12:$Y$267,0)),"") | F25: =IFERROR(INDEX('Watershed plans'!$O$12:$O$267,MATCH(20,'Watershed plans'!$Y$12:$Y$267,0)),"") | G25: =IFERROR(INDEX('Watershed plans'!$AE$12:$AE$267,MATCH(20,'Watershed plans'!$Y$12:$Y$267,0)),"") | H25: =IFERROR(INDEX('Watershed plans'!$AD$12:$AD$267,MATCH(20,'Watershed plans'!$Y$12:$Y$267,0)),"")
A26: 21 | B26: =IFERROR(INDEX('Watershed plans'!$L$12:$L$267,MATCH(21,'Watershed plans'!$Y$12:$Y$267,0)),"") | C26: =IFERROR(INDEX('Watershed plans'!$B$12:$B$267,MATCH(21,'Watershed plans'!$Y$12:$Y$267,0)),"") | D26: =IFERROR(INDEX('Watershed plans'!$P$12:$P$267,MATCH(21,'Watershed plans'!$Y$12:$Y$267,0)),"") | E26: =IFERROR(INDEX('Watershed plans'!$Q$12:$Q$267,MATCH(21,'Watershed plans'!$Y$12:$Y$267,0)),"") | F26: =IFERROR(INDEX('Watershed plans'!$O$12:$O$267,MATCH(21,'Watershed plans'!$Y$12:$Y$267,0)),"") | G26: =IFERROR(INDEX('Watershed plans'!$AE$12:$AE$267,MATCH(21,'Watershed plans'!$Y$12:$Y$267,0)),"") | H26: =IFERROR(INDEX('Watershed plans'!$AD$12:$AD$267,MATCH(21,'Watershed plans'!$Y$12:$Y$267,0)),"")
A27: 22 | B27: =IFERROR(INDEX('Watershed plans'!$L$12:$L$267,MATCH(22,'Watershed plans'!$Y$12:$Y$267,0)),"") | C27: =IFERROR(INDEX('Watershed plans'!$B$12:$B$267,MATCH(22,'Watershed plans'!$Y$12:$Y$267,0)),"") | D27: =IFERROR(INDEX('Watershed plans'!$P$12:$P$267,MATCH(22,'Watershed plans'!$Y$12:$Y$267,0)),"") | E27: =IFERROR(INDEX('Watershed plans'!$Q$12:$Q$267,MATCH(22,'Watershed plans'!$Y$12:$Y$267,0)),"") | F27: =IFERROR(INDEX('Watershed plans'!$O$12:$O$267,MATCH(22,'Watershed plans'!$Y$12:$Y$267,0)),"") | G27: =IFERROR(INDEX('Watershed plans'!$AE$12:$AE$267,MATCH(22,'Watershed plans'!$Y$12:$Y$267,0)),"") | H27: =IFERROR(INDEX('Watershed plans'!$AD$12:$AD$267,MATCH(22,'Watershed plans'!$Y$12:$Y$267,0)),"")
A28: 23 | B28: =IFERROR(INDEX('Watershed plans'!$L$12:$L$267,MATCH(23,'Watershed plans'!$Y$12:$Y$267,0)),"") | C28: =IFERROR(INDEX('Watershed plans'!$B$12:$B$267,MATCH(23,'Watershed plans'!$Y$12:$Y$267,0)),"") | D28: =IFERROR(INDEX('Watershed plans'!$P$12:$P$267,MATCH(23,'Watershed plans'!$Y$12:$Y$267,0)),"") | E28: =IFERROR(INDEX('Watershed plans'!$Q$12:$Q$267,MATCH(23,'Watershed plans'!$Y$12:$Y$267,0)),"") | F28: =IFERROR(INDEX('Watershed plans'!$O$12:$O$267,MATCH(23,'Watershed plans'!$Y$12:$Y$267,0)),"") | G28: =IFERROR(INDEX('Watershed plans'!$AE$12:$AE$267,MATCH(23,'Watershed plans'!$Y$12:$Y$267,0)),"") | H28: =IFERROR(INDEX('Watershed plans'!$AD$12:$AD$267,MATCH(23,'Watershed plans'!$Y$12:$Y$267,0)),"")
A29: 24 | B29: =IFERROR(INDEX('Watershed plans'!$L$12:$L$267,MATCH(24,'Watershed plans'!$Y$12:$Y$267,0)),"") | C29: =IFERROR(INDEX('Watershed plans'!$B$12:$B$267,MATCH(24,'Watershed plans'!$Y$12:$Y$267,0)),"") | D29: =IFERROR(INDEX('Watershed plans'!$P$12:$P$267,MATCH(24,'Watershed plans'!$Y$12:$Y$267,0)),"") | E29: =IFERROR(INDEX('Watershed plans'!$Q$12:$Q$267,MATCH(24,'Watershed plans'!$Y$12:$Y$267,0)),"") | F29: =IFERROR(INDEX('Watershed plans'!$O$12:$O$267,MATCH(24,'Watershed plans'!$Y$12:$Y$267,0)),"") | G29: =IFERROR(INDEX('Watershed plans'!$AE$12:$AE$267,MATCH(24,'Watershed plans'!$Y$12:$Y$267,0)),"") | H29: =IFERROR(INDEX('Watershed plans'!$AD$12:$AD$267,MATCH(24,'Watershed plans'!$Y$12:$Y$267,0)),"")
A30: 25 | B30: =IFERROR(INDEX('Watershed plans'!$L$12:$L$267,MATCH(25,'Watershed plans'!$Y$12:$Y$267,0)),"") | C30: =IFERROR(INDEX('Watershed plans'!$B$12:$B$267,MATCH(25,'Watershed plans'!$Y$12:$Y$267,0)),"") | D30: =IFERROR(INDEX('Watershed plans'!$P$12:$P$267,MATCH(25,'Watershed plans'!$Y$12:$Y$267,0)),"") | E30: =IFERROR(INDEX('Watershed plans'!$Q$12:$Q$267,MATCH(25,'Watershed plans'!$Y$12:$Y$267,0)),"") | F30: =IFERROR(INDEX('Watershed plans'!$O$12:$O$267,MATCH(25,'Watershed plans'!$Y$12:$Y$267,0)),"") | G30: =IFERROR(INDEX('Watershed plans'!$AE$12:$AE$267,MATCH(25,'Watershed plans'!$Y$12:$Y$267,0)),"") | H30: =IFERROR(INDEX('Watershed plans'!$AD$12:$AD$267,MATCH(25,'Watershed plans'!$Y$12:$Y$267,0)),"")
A31: 26 | B31: =IFERROR(INDEX('Watershed plans'!$L$12:$L$267,MATCH(26,'Watershed plans'!$Y$12:$Y$267,0)),"") | C31: =IFERROR(INDEX('Watershed plans'!$B$12:$B$267,MATCH(26,'Watershed plans'!$Y$12:$Y$267,0)),"") | D31: =IFERROR(INDEX('Watershed plans'!$P$12:$P$267,MATCH(26,'Watershed plans'!$Y$12:$Y$267,0)),"") | E31: =IFERROR(INDEX('Watershed plans'!$Q$12:$Q$267,MATCH(26,'Watershed plans'!$Y$12:$Y$267,0)),"") | F31: =IFERROR(INDEX('Watershed plans'!$O$12:$O$267,MATCH(26,'Watershed plans'!$Y$12:$Y$267,0)),"") | G31: =IFERROR(INDEX('Watershed plans'!$AE$12:$AE$267,MATCH(26,'Watershed plans'!$Y$12:$Y$267,0)),"") | H31: =IFERROR(INDEX('Watershed plans'!$AD$12:$AD$267,MATCH(26,'Watershed plans'!$Y$12:$Y$267,0)),"")
A32: 27 | B32: =IFERROR(INDEX('Watershed plans'!$L$12:$L$267,MATCH(27,'Watershed plans'!$Y$12:$Y$267,0)),"") | C32: =IFERROR(INDEX('Watershed plans'!$B$12:$B$267,MATCH(27,'Watershed plans'!$Y$12:$Y$267,0)),"") | D32: =IFERROR(INDEX('Watershed plans'!$P$12:$P$267,MATCH(27,'Watershed plans'!$Y$12:$Y$267,0)),"") | E32: =IFERROR(INDEX('Watershed plans'!$Q$12:$Q$267,MATCH(27,'Watershed plans'!$Y$12:$Y$267,0)),"") | F32: =IFERROR(INDEX('Watershed plans'!$O$12:$O$267,MATCH(27,'Watershed plans'!$Y$12:$Y$267,0)),"") | G32: =IFERROR(INDEX('Watershed plans'!$AE$12:$AE$267,MATCH(27,'Watershed plans'!$Y$12:$Y$267,0)),"") | H32: =IFERROR(INDEX('Watershed plans'!$AD$12:$AD$267,MATCH(27,'Watershed plans'!$Y$12:$Y$267,0)),"")
A33: 28 | B33: =IFERROR(INDEX('Watershed plans'!$L$12:$L$267,MATCH(28,'Watershed plans'!$Y$12:$Y$267,0)),"") | C33: =IFERROR(INDEX('Watershed plans'!$B$12:$B$267,MATCH(28,'Watershed plans'!$Y$12:$Y$267,0)),"") | D33: =IFERROR(INDEX('Watershed plans'!$P$12:$P$267,MATCH(28,'Watershed plans'!$Y$12:$Y$267,0)),"") | E33: =IFERROR(INDEX('Watershed plans'!$Q$12:$Q$267,MATCH(28,'Watershed plans'!$Y$12:$Y$267,0)),"") | F33: =IFERROR(INDEX('Watershed plans'!$O$12:$O$267,MATCH(28,'Watershed plans'!$Y$12:$Y$267,0)),"") | G33: =IFERROR(INDEX('Watershed plans'!$AE$12:$AE$267,MATCH(28,'Watershed plans'!$Y$12:$Y$267,0)),"") | H33: =IFERROR(INDEX('Watershed plans'!$AD$12:$AD$267,MATCH(28,'Watershed plans'!$Y$12:$Y$267,0)),"")
A34: 29 | B34: =IFERROR(INDEX('Watershed plans'!$L$12:$L$267,MATCH(29,'Watershed plans'!$Y$12:$Y$267,0)),"") | C34: =IFERROR(INDEX('Watershed plans'!$B$12:$B$267,MATCH(29,'Watershed plans'!$Y$12:$Y$267,0)),"") | D34: =IFERROR(INDEX('Watershed plans'!$P$12:$P$267,MATCH(29,'Watershed plans'!$Y$12:$Y$267,0)),"") | E34: =IFERROR(INDEX('Watershed plans'!$Q$12:$Q$267,MATCH(29,'Watershed plans'!$Y$12:$Y$267,0)),"") | F34: =IFERROR(INDEX('Watershed plans'!$O$12:$O$267,MATCH(29,'Watershed plans'!$Y$12:$Y$267,0)),"") | G34: =IFERROR(INDEX('Watershed plans'!$AE$12:$AE$267,MATCH(29,'Watershed plans'!$Y$12:$Y$267,0)),"") | H34: =IFERROR(INDEX('Watershed plans'!$AD$12:$AD$267,MATCH(29,'Watershed plans'!$Y$12:$Y$267,0)),"")
A35: 30 | B35: =IFERROR(INDEX('Watershed plans'!$L$12:$L$267,MATCH(30,'Watershed plans'!$Y$12:$Y$267,0)),"") | C35: =IFERROR(INDEX('Watershed plans'!$B$12:$B$267,MATCH(30,'Watershed plans'!$Y$12:$Y$267,0)),"") | D35: =IFERROR(INDEX('Watershed plans'!$P$12:$P$267,MATCH(30,'Watershed plans'!$Y$12:$Y$267,0)),"") | E35: =IFERROR(INDEX('Watershed plans'!$Q$12:$Q$267,MATCH(30,'Watershed plans'!$Y$12:$Y$267,0)),"") | F35: =IFERROR(INDEX('Watershed plans'!$O$12:$O$267,MATCH(30,'Watershed plans'!$Y$12:$Y$267,0)),"") | G35: =IFERROR(INDEX('Watershed plans'!$AE$12:$AE$267,MATCH(30,'Watershed plans'!$Y$12:$Y$267,0)),"") | H35: =IFERROR(INDEX('Watershed plans'!$AD$12:$AD$267,MATCH(30,'Watershed plans'!$Y$12:$Y$267,0)),"")
A36: 31 | B36: =IFERROR(INDEX('Watershed plans'!$L$12:$L$267,MATCH(31,'Watershed plans'!$Y$12:$Y$267,0)),"") | C36: =IFERROR(INDEX('Watershed plans'!$B$12:$B$267,MATCH(31,'Watershed plans'!$Y$12:$Y$267,0)),"") | D36: =IFERROR(INDEX('Watershed plans'!$P$12:$P$267,MATCH(31,'Watershed plans'!$Y$12:$Y$267,0)),"") | E36: =IFERROR(INDEX('Watershed plans'!$Q$12:$Q$267,MATCH(31,'Watershed plans'!$Y$12:$Y$267,0)),"") | F36: =IFERROR(INDEX('Watershed plans'!$O$12:$O$267,MATCH(31,'Watershed plans'!$Y$12:$Y$267,0)),"") | G36: =IFERROR(INDEX('Watershed plans'!$AE$12:$AE$267,MATCH(31,'Watershed plans'!$Y$12:$Y$267,0)),"") | H36: =IFERROR(INDEX('Watershed plans'!$AD$12:$AD$267,MATCH(31,'Watershed plans'!$Y$12:$Y$267,0)),"")
A37: 32 | B37: =IFERROR(INDEX('Watershed plans'!$L$12:$L$267,MATCH(32,'Watershed plans'!$Y$12:$Y$267,0)),"") | C37: =IFERROR(INDEX('Watershed plans'!$B$12:$B$267,MATCH(32,'Watershed plans'!$Y$12:$Y$267,0)),"") | D37: =IFERROR(INDEX('Watershed plans'!$P$12:$P$267,MATCH(32,'Watershed plans'!$Y$12:$Y$267,0)),"") | E37: =IFERROR(INDEX('Watershed plans'!$Q$12:$Q$267,MATCH(32,'Watershed plans'!$Y$12:$Y$267,0)),"") | F37: =IFERROR(INDEX('Watershed plans'!$O$12:$O$267,MATCH(32,'Watershed plans'!$Y$12:$Y$267,0)),"") | G37: =IFERROR(INDEX('Watershed plans'!$AE$12:$AE$267,MATCH(32,'Watershed plans'!$Y$12:$Y$267,0)),"") | H37: =IFERROR(INDEX('Watershed plans'!$AD$12:$AD$267,MATCH(32,'Watershed plans'!$Y$12:$Y$267,0)),"")
A38: 33 | B38: =IFERROR(INDEX('Watershed plans'!$L$12:$L$267,MATCH(33,'Watershed plans'!$Y$12:$Y$267,0)),"") | C38: =IFERROR(INDEX('Watershed plans'!$B$12:$B$267,MATCH(33,'Watershed plans'!$Y$12:$Y$267,0)),"") | D38: =IFERROR(INDEX('Watershed plans'!$P$12:$P$267,MATCH(33,'Watershed plans'!$Y$12:$Y$267,0)),"") | E38: =IFERROR(INDEX('Watershed plans'!$Q$12:$Q$267,MATCH(33,'Watershed plans'!$Y$12:$Y$267,0)),"") | F38: =IFERROR(INDEX('Watershed plans'!$O$12:$O$267,MATCH(33,'Watershed plans'!$Y$12:$Y$267,0)),"") | G38: =IFERROR(INDEX('Watershed plans'!$AE$12:$AE$267,MATCH(33,'Watershed plans'!$Y$12:$Y$267,0)),"") | H38: =IFERROR(INDEX('Watershed plans'!$AD$12:$AD$267,MATCH(33,'Watershed plans'!$Y$12:$Y$267,0)),"")
A39: 34 | B39: =IFERROR(INDEX('Watershed plans'!$L$12:$L$267,MATCH(34,'Watershed plans'!$Y$12:$Y$267,0)),"") | C39: =IFERROR(INDEX('Watershed plans'!$B$12:$B$267,MATCH(34,'Watershed plans'!$Y$12:$Y$267,0)),"") | D39: =IFERROR(INDEX('Watershed plans'!$P$12:$P$267,MATCH(34,'Watershed plans'!$Y$12:$Y$267,0)),"") | E39: =IFERROR(INDEX('Watershed plans'!$Q$12:$Q$267,MATCH(34,'Watershed plans'!$Y$12:$Y$267,0)),"") | F39: =IFERROR(INDEX('Watershed plans'!$O$12:$O$267,MATCH(34,'Watershed plans'!$Y$12:$Y$267,0)),"") | G39: =IFERROR(INDEX('Watershed plans'!$AE$12:$AE$267,MATCH(34,'Watershed plans'!$Y$12:$Y$267,0)),"") | H39: =IFERROR(INDEX('Watershed plans'!$AD$12:$AD$267,MATCH(34,'Watershed plans'!$Y$12:$Y$267,0)),"")
A40: 35 | B40: =IFERROR(INDEX('Watershed plans'!$L$12:$L$267,MATCH(35,'Watershed plans'!$Y$12:$Y$267,0)),"") | C40: =IFERROR(INDEX('Watershed plans'!$B$12:$B$267,MATCH(35,'Watershed plans'!$Y$12:$Y$267,0)),"") | D40: =IFERROR(INDEX('Watershed plans'!$P$12:$P$267,MATCH(35,'Watershed plans'!$Y$12:$Y$267,0)),"") | E40: =IFERROR(INDEX('Watershed plans'!$Q$12:$Q$267,MATCH(35,'Watershed plans'!$Y$12:$Y$267,0)),"") | F40: =IFERROR(INDEX('Watershed plans'!$O$12:$O$267,MATCH(35,'Watershed plans'!$Y$12:$Y$267,0)),"") | G40: =IFERROR(INDEX('Watershed plans'!$AE$12:$AE$267,MATCH(35,'Watershed plans'!$Y$12:$Y$267,0)),"") | H40: =IFERROR(INDEX('Watershed plans'!$AD$12:$AD$267,MATCH(35,'Watershed plans'!$Y$12:$Y$267,0)),"")
A41: 36 | B41: =IFERROR(INDEX('Watershed plans'!$L$12:$L$267,MATCH(36,'Watershed plans'!$Y$12:$Y$267,0)),"") | C41: =IFERROR(INDEX('Watershed plans'!$B$12:$B$267,MATCH(36,'Watershed plans'!$Y$12:$Y$267,0)),"") | D41: =IFERROR(INDEX('Watershed plans'!$P$12:$P$267,MATCH(36,'Watershed plans'!$Y$12:$Y$267,0)),"") | E41: =IFERROR(INDEX('Watershed plans'!$Q$12:$Q$267,MATCH(36,'Watershed plans'!$Y$12:$Y$267,0)),"") | F41: =IFERROR(INDEX('Watershed plans'!$O$12:$O$267,MATCH(36,'Watershed plans'!$Y$12:$Y$267,0)),"") | G41: =IFERROR(INDEX('Watershed plans'!$AE$12:$AE$267,MATCH(36,'Watershed plans'!$Y$12:$Y$267,0)),"") | H41: =IFERROR(INDEX('Watershed plans'!$AD$12:$AD$267,MATCH(36,'Watershed plans'!$Y$12:$Y$267,0)),"")
A42: 37 | B42: =IFERROR(INDEX('Watershed plans'!$L$12:$L$267,MATCH(37,'Watershed plans'!$Y$12:$Y$267,0)),"") | C42: =IFERROR(INDEX('Watershed plans'!$B$12:$B$267,MATCH(37,'Watershed plans'!$Y$12:$Y$267,0)),"") | D42: =IFERROR(INDEX('Watershed plans'!$P$12:$P$267,MATCH(37,'Watershed plans'!$Y$12:$Y$267,0)),"") | E42: =IFERROR(INDEX('Watershed plans'!$Q$12:$Q$267,MATCH(37,'Watershed plans'!$Y$12:$Y$267,0)),"") | F42: =IFERROR(INDEX('Watershed plans'!$O$12:$O$267,MATCH(37,'Watershed plans'!$Y$12:$Y$267,0)),"") | G42: =IFERROR(INDEX('Watershed plans'!$AE$12:$AE$267,MATCH(37,'Watershed plans'!$Y$12:$Y$267,0)),"") | H42: =IFERROR(INDEX('Watershed plans'!$AD$12:$AD$267,MATCH(37,'Watershed plans'!$Y$12:$Y$267,0)),"")
A43: 38 | B43: =IFERROR(INDEX('Watershed plans'!$L$12:$L$267,MATCH(38,'Watershed plans'!$Y$12:$Y$267,0)),"") | C43: =IFERROR(INDEX('Watershed plans'!$B$12:$B$267,MATCH(38,'Watershed plans'!$Y$12:$Y$267,0)),"") | D43: =IFERROR(INDEX('Watershed plans'!$P$12:$P$267,MATCH(38,'Watershed plans'!$Y$12:$Y$267,0)),"") | E43: =IFERROR(INDEX('Watershed plans'!$Q$12:$Q$267,MATCH(38,'Watershed plans'!$Y$12:$Y$267,0)),"") | F43: =IFERROR(INDEX('Watershed plans'!$O$12:$O$267,MATCH(38,'Watershed plans'!$Y$12:$Y$267,0)),"") | G43: =IFERROR(INDEX('Watershed plans'!$AE$12:$AE$267,MATCH(38,'Watershed plans'!$Y$12:$Y$267,0)),"") | H43: =IFERROR(INDEX('Watershed plans'!$AD$12:$AD$267,MATCH(38,'Watershed plans'!$Y$12:$Y$267,0)),"")
A44: 39 | B44: =IFERROR(INDEX('Watershed plans'!$L$12:$L$267,MATCH(39,'Watershed plans'!$Y$12:$Y$267,0)),"") | C44: =IFERROR(INDEX('Watershed plans'!$B$12:$B$267,MATCH(39,'Watershed plans'!$Y$12:$Y$267,0)),"") | D44: =IFERROR(INDEX('Watershed plans'!$P$12:$P$267,MATCH(39,'Watershed plans'!$Y$12:$Y$267,0)),"") | E44: =IFERROR(INDEX('Watershed plans'!$Q$12:$Q$267,MATCH(39,'Watershed plans'!$Y$12:$Y$267,0)),"") | F44: =IFERROR(INDEX('Watershed plans'!$O$12:$O$267,MATCH(39,'Watershed plans'!$Y$12:$Y$267,0)),"") | G44: =IFERROR(INDEX('Watershed plans'!$AE$12:$AE$267,MATCH(39,'Watershed plans'!$Y$12:$Y$267,0)),"") | H44: =IFERROR(INDEX('Watershed plans'!$AD$12:$AD$267,MATCH(39,'Watershed plans'!$Y$12:$Y$267,0)),"")
A45: 40 | B45: =IFERROR(INDEX('Watershed plans'!$L$12:$L$267,MATCH(40,'Watershed plans'!$Y$12:$Y$267,0)),"") | C45: =IFERROR(INDEX('Watershed plans'!$B$12:$B$267,MATCH(40,'Watershed plans'!$Y$12:$Y$267,0)),"") | D45: =IFERROR(INDEX('Watershed plans'!$P$12:$P$267,MATCH(40,'Watershed plans'!$Y$12:$Y$267,0)),"") | E45: =IFERROR(INDEX('Watershed plans'!$Q$12:$Q$267,MATCH(40,'Watershed plans'!$Y$12:$Y$267,0)),"") | F45: =IFERROR(INDEX('Watershed plans'!$O$12:$O$267,MATCH(40,'Watershed plans'!$Y$12:$Y$267,0)),"") | G45: =IFERROR(INDEX('Watershed plans'!$AE$12:$AE$267,MATCH(40,'Watershed plans'!$Y$12:$Y$267,0)),"") | H45: =IFERROR(INDEX('Watershed plans'!$AD$12:$AD$267,MATCH(40,'Watershed plans'!$Y$12:$Y$267,0)),"")
A48: Final array (in order of output) and 'Is it worth it?'
A49: Order | B49: Plan number | C49: Plan | D49: Lift (AAHU) | E49: Average annual cost | F49: Construction cost | G49: Unit cost | H49: Added output | I49: Added cost | J49: Added cost per unit | K49: Worth it? | L49: Why
A50: 1 | B50: =IFERROR(INDEX('Watershed plans'!$L$12:$L$267,MATCH(1,'Watershed plans'!$AG$12:$AG$267,0)),"") | C50: =IFERROR(INDEX('Watershed plans'!$B$12:$B$267,MATCH(1,'Watershed plans'!$AG$12:$AG$267,0)),"") | D50: =IFERROR(INDEX('Watershed plans'!$P$12:$P$267,MATCH(1,'Watershed plans'!$AG$12:$AG$267,0)),"") | E50: =IFERROR(INDEX('Watershed plans'!$Q$12:$Q$267,MATCH(1,'Watershed plans'!$AG$12:$AG$267,0)),"") | F50: =IFERROR(INDEX('Watershed plans'!$O$12:$O$267,MATCH(1,'Watershed plans'!$AG$12:$AG$267,0)),"") | G50: =IFERROR(INDEX('Watershed plans'!$AE$12:$AE$267,MATCH(1,'Watershed plans'!$AG$12:$AG$267,0)),"")
A51: 2 | B51: =IFERROR(INDEX('Watershed plans'!$L$12:$L$267,MATCH(2,'Watershed plans'!$AG$12:$AG$267,0)),"") | C51: =IFERROR(INDEX('Watershed plans'!$B$12:$B$267,MATCH(2,'Watershed plans'!$AG$12:$AG$267,0)),"") | D51: =IFERROR(INDEX('Watershed plans'!$P$12:$P$267,MATCH(2,'Watershed plans'!$AG$12:$AG$267,0)),"") | E51: =IFERROR(INDEX('Watershed plans'!$Q$12:$Q$267,MATCH(2,'Watershed plans'!$AG$12:$AG$267,0)),"") | F51: =IFERROR(INDEX('Watershed plans'!$O$12:$O$267,MATCH(2,'Watershed plans'!$AG$12:$AG$267,0)),"") | G51: =IFERROR(INDEX('Watershed plans'!$AE$12:$AE$267,MATCH(2,'Watershed plans'!$AG$12:$AG$267,0)),"") | H51: =IF(ISNUMBER(D51),D51-D50,"") | I51: =IF(ISNUMBER(E51),E51-E50,"") | J51: =IF(AND(ISNUMBER(H51),H51<>0),I51/H51,"") | K51: No | L51: Too costly for the added lift
A52: 3 | B52: =IFERROR(INDEX('Watershed plans'!$L$12:$L$267,MATCH(3,'Watershed plans'!$AG$12:$AG$267,0)),"") | C52: =IFERROR(INDEX('Watershed plans'!$B$12:$B$267,MATCH(3,'Watershed plans'!$AG$12:$AG$267,0)),"") | D52: =IFERROR(INDEX('Watershed plans'!$P$12:$P$267,MATCH(3,'Watershed plans'!$AG$12:$AG$267,0)),"") | E52: =IFERROR(INDEX('Watershed plans'!$Q$12:$Q$267,MATCH(3,'Watershed plans'!$AG$12:$AG$267,0)),"") | F52: =IFERROR(INDEX('Watershed plans'!$O$12:$O$267,MATCH(3,'Watershed plans'!$AG$12:$AG$267,0)),"") | G52: =IFERROR(INDEX('Watershed plans'!$AE$12:$AE$267,MATCH(3,'Watershed plans'!$AG$12:$AG$267,0)),"") | H52: =IF(ISNUMBER(D52),D52-D51,"") | I52: =IF(ISNUMBER(E52),E52-E51,"") | J52: =IF(AND(ISNUMBER(H52),H52<>0),I52/H52,"") | K52: Yes | L52: Site 3F adds high benefit at low cost and demonstrates innovative methods for the region.
A53: 4 | B53: =IFERROR(INDEX('Watershed plans'!$L$12:$L$267,MATCH(4,'Watershed plans'!$AG$12:$AG$267,0)),"") | C53: =IFERROR(INDEX('Watershed plans'!$B$12:$B$267,MATCH(4,'Watershed plans'!$AG$12:$AG$267,0)),"") | D53: =IFERROR(INDEX('Watershed plans'!$P$12:$P$267,MATCH(4,'Watershed plans'!$AG$12:$AG$267,0)),"") | E53: =IFERROR(INDEX('Watershed plans'!$Q$12:$Q$267,MATCH(4,'Watershed plans'!$AG$12:$AG$267,0)),"") | F53: =IFERROR(INDEX('Watershed plans'!$O$12:$O$267,MATCH(4,'Watershed plans'!$AG$12:$AG$267,0)),"") | G53: =IFERROR(INDEX('Watershed plans'!$AE$12:$AE$267,MATCH(4,'Watershed plans'!$AG$12:$AG$267,0)),"") | H53: =IF(ISNUMBER(D53),D53-D52,"") | I53: =IF(ISNUMBER(E53),E53-E52,"") | J53: =IF(AND(ISNUMBER(H53),H53<>0),I53/H53,"") | K53: Yes | L53: Site 17B extends actions upstream and cuts sediment delivered to Sites 2A and 2B.
A54: 5 | B54: =IFERROR(INDEX('Watershed plans'!$L$12:$L$267,MATCH(5,'Watershed plans'!$AG$12:$AG$267,0)),"") | C54: =IFERROR(INDEX('Watershed plans'!$B$12:$B$267,MATCH(5,'Watershed plans'!$AG$12:$AG$267,0)),"") | D54: =IFERROR(INDEX('Watershed plans'!$P$12:$P$267,MATCH(5,'Watershed plans'!$AG$12:$AG$267,0)),"") | E54: =IFERROR(INDEX('Watershed plans'!$Q$12:$Q$267,MATCH(5,'Watershed plans'!$AG$12:$AG$267,0)),"") | F54: =IFERROR(INDEX('Watershed plans'!$O$12:$O$267,MATCH(5,'Watershed plans'!$AG$12:$AG$267,0)),"") | G54: =IFERROR(INDEX('Watershed plans'!$AE$12:$AE$267,MATCH(5,'Watershed plans'!$AG$12:$AG$267,0)),"") | H54: =IF(ISNUMBER(D54),D54-D53,"") | I54: =IF(ISNUMBER(E54),E54-E53,"") | J54: =IF(AND(ISNUMBER(H54),H54<>0),I54/H54,"") | K54: Yes | L54: Site 17D2E begins to address the concrete channel, a major cause of degradation.
A55: 6 | B55: =IFERROR(INDEX('Watershed plans'!$L$12:$L$267,MATCH(6,'Watershed plans'!$AG$12:$AG$267,0)),"") | C55: =IFERROR(INDEX('Watershed plans'!$B$12:$B$267,MATCH(6,'Watershed plans'!$AG$12:$AG$267,0)),"") | D55: =IFERROR(INDEX('Watershed plans'!$P$12:$P$267,MATCH(6,'Watershed plans'!$AG$12:$AG$267,0)),"") | E55: =IFERROR(INDEX('Watershed plans'!$Q$12:$Q$267,MATCH(6,'Watershed plans'!$AG$12:$AG$267,0)),"") | F55: =IFERROR(INDEX('Watershed plans'!$O$12:$O$267,MATCH(6,'Watershed plans'!$AG$12:$AG$267,0)),"") | G55: =IFERROR(INDEX('Watershed plans'!$AE$12:$AE$267,MATCH(6,'Watershed plans'!$AG$12:$AG$267,0)),"") | H55: =IF(ISNUMBER(D55),D55-D54,"") | I55: =IF(ISNUMBER(E55),E55-E54,"") | J55: =IF(AND(ISNUMBER(H55),H55<>0),I55/H55,"") | K55: Yes | L55: Site 17F2M addresses the largest extent of concrete channel; working with 17D2E should cut mobilization costs, and the plan has the widest coverage.
A56: 7 | B56: =IFERROR(INDEX('Watershed plans'!$L$12:$L$267,MATCH(7,'Watershed plans'!$AG$12:$AG$267,0)),"") | C56: =IFERROR(INDEX('Watershed plans'!$B$12:$B$267,MATCH(7,'Watershed plans'!$AG$12:$AG$267,0)),"") | D56: =IFERROR(INDEX('Watershed plans'!$P$12:$P$267,MATCH(7,'Watershed plans'!$AG$12:$AG$267,0)),"") | E56: =IFERROR(INDEX('Watershed plans'!$Q$12:$Q$267,MATCH(7,'Watershed plans'!$AG$12:$AG$267,0)),"") | F56: =IFERROR(INDEX('Watershed plans'!$O$12:$O$267,MATCH(7,'Watershed plans'!$AG$12:$AG$267,0)),"") | G56: =IFERROR(INDEX('Watershed plans'!$AE$12:$AE$267,MATCH(7,'Watershed plans'!$AG$12:$AG$267,0)),"") | H56: =IF(ISNUMBER(D56),D56-D55,"") | I56: =IF(ISNUMBER(E56),E56-E55,"") | J56: =IF(AND(ISNUMBER(H56),H56<>0),I56/H56,"")
A57: 8 | B57: =IFERROR(INDEX('Watershed plans'!$L$12:$L$267,MATCH(8,'Watershed plans'!$AG$12:$AG$267,0)),"") | C57: =IFERROR(INDEX('Watershed plans'!$B$12:$B$267,MATCH(8,'Watershed plans'!$AG$12:$AG$267,0)),"") | D57: =IFERROR(INDEX('Watershed plans'!$P$12:$P$267,MATCH(8,'Watershed plans'!$AG$12:$AG$267,0)),"") | E57: =IFERROR(INDEX('Watershed plans'!$Q$12:$Q$267,MATCH(8,'Watershed plans'!$AG$12:$AG$267,0)),"") | F57: =IFERROR(INDEX('Watershed plans'!$O$12:$O$267,MATCH(8,'Watershed plans'!$AG$12:$AG$267,0)),"") | G57: =IFERROR(INDEX('Watershed plans'!$AE$12:$AE$267,MATCH(8,'Watershed plans'!$AG$12:$AG$267,0)),"") | H57: =IF(ISNUMBER(D57),D57-D56,"") | I57: =IF(ISNUMBER(E57),E57-E56,"") | J57: =IF(AND(ISNUMBER(H57),H57<>0),I57/H57,"")
A58: 9 | B58: =IFERROR(INDEX('Watershed plans'!$L$12:$L$267,MATCH(9,'Watershed plans'!$AG$12:$AG$267,0)),"") | C58: =IFERROR(INDEX('Watershed plans'!$B$12:$B$267,MATCH(9,'Watershed plans'!$AG$12:$AG$267,0)),"") | D58: =IFERROR(INDEX('Watershed plans'!$P$12:$P$267,MATCH(9,'Watershed plans'!$AG$12:$AG$267,0)),"") | E58: =IFERROR(INDEX('Watershed plans'!$Q$12:$Q$267,MATCH(9,'Watershed plans'!$AG$12:$AG$267,0)),"") | F58: =IFERROR(INDEX('Watershed plans'!$O$12:$O$267,MATCH(9,'Watershed plans'!$AG$12:$AG$267,0)),"") | G58: =IFERROR(INDEX('Watershed plans'!$AE$12:$AE$267,MATCH(9,'Watershed plans'!$AG$12:$AG$267,0)),"") | H58: =IF(ISNUMBER(D58),D58-D57,"") | I58: =IF(ISNUMBER(E58),E58-E57,"") | J58: =IF(AND(ISNUMBER(H58),H58<>0),I58/H58,"")
A59: 10 | B59: =IFERROR(INDEX('Watershed plans'!$L$12:$L$267,MATCH(10,'Watershed plans'!$AG$12:$AG$267,0)),"") | C59: =IFERROR(INDEX('Watershed plans'!$B$12:$B$267,MATCH(10,'Watershed plans'!$AG$12:$AG$267,0)),"") | D59: =IFERROR(INDEX('Watershed plans'!$P$12:$P$267,MATCH(10,'Watershed plans'!$AG$12:$AG$267,0)),"") | E59: =IFERROR(INDEX('Watershed plans'!$Q$12:$Q$267,MATCH(10,'Watershed plans'!$AG$12:$AG$267,0)),"") | F59: =IFERROR(INDEX('Watershed plans'!$O$12:$O$267,MATCH(10,'Watershed plans'!$AG$12:$AG$267,0)),"") | G59: =IFERROR(INDEX('Watershed plans'!$AE$12:$AE$267,MATCH(10,'Watershed plans'!$AG$12:$AG$267,0)),"") | H59: =IF(ISNUMBER(D59),D59-D58,"") | I59: =IF(ISNUMBER(E59),E59-E58,"") | J59: =IF(AND(ISNUMBER(H59),H59<>0),I59/H59,"")
A60: 11 | B60: =IFERROR(INDEX('Watershed plans'!$L$12:$L$267,MATCH(11,'Watershed plans'!$AG$12:$AG$267,0)),"") | C60: =IFERROR(INDEX('Watershed plans'!$B$12:$B$267,MATCH(11,'Watershed plans'!$AG$12:$AG$267,0)),"") | D60: =IFERROR(INDEX('Watershed plans'!$P$12:$P$267,MATCH(11,'Watershed plans'!$AG$12:$AG$267,0)),"") | E60: =IFERROR(INDEX('Watershed plans'!$Q$12:$Q$267,MATCH(11,'Watershed plans'!$AG$12:$AG$267,0)),"") | F60: =IFERROR(INDEX('Watershed plans'!$O$12:$O$267,MATCH(11,'Watershed plans'!$AG$12:$AG$267,0)),"") | G60: =IFERROR(INDEX('Watershed plans'!$AE$12:$AE$267,MATCH(11,'Watershed plans'!$AG$12:$AG$267,0)),"") | H60: =IF(ISNUMBER(D60),D60-D59,"") | I60: =IF(ISNUMBER(E60),E60-E59,"") | J60: =IF(AND(ISNUMBER(H60),H60<>0),I60/H60,"")
A61: 12 | B61: =IFERROR(INDEX('Watershed plans'!$L$12:$L$267,MATCH(12,'Watershed plans'!$AG$12:$AG$267,0)),"") | C61: =IFERROR(INDEX('Watershed plans'!$B$12:$B$267,MATCH(12,'Watershed plans'!$AG$12:$AG$267,0)),"") | D61: =IFERROR(INDEX('Watershed plans'!$P$12:$P$267,MATCH(12,'Watershed plans'!$AG$12:$AG$267,0)),"") | E61: =IFERROR(INDEX('Watershed plans'!$Q$12:$Q$267,MATCH(12,'Watershed plans'!$AG$12:$AG$267,0)),"") | F61: =IFERROR(INDEX('Watershed plans'!$O$12:$O$267,MATCH(12,'Watershed plans'!$AG$12:$AG$267,0)),"") | G61: =IFERROR(INDEX('Watershed plans'!$AE$12:$AE$267,MATCH(12,'Watershed plans'!$AG$12:$AG$267,0)),"") | H61: =IF(ISNUMBER(D61),D61-D60,"") | I61: =IF(ISNUMBER(E61),E61-E60,"") | J61: =IF(AND(ISNUMBER(H61),H61<>0),I61/H61,"")
A62: 13 | B62: =IFERROR(INDEX('Watershed plans'!$L$12:$L$267,MATCH(13,'Watershed plans'!$AG$12:$AG$267,0)),"") | C62: =IFERROR(INDEX('Watershed plans'!$B$12:$B$267,MATCH(13,'Watershed plans'!$AG$12:$AG$267,0)),"") | D62: =IFERROR(INDEX('Watershed plans'!$P$12:$P$267,MATCH(13,'Watershed plans'!$AG$12:$AG$267,0)),"") | E62: =IFERROR(INDEX('Watershed plans'!$Q$12:$Q$267,MATCH(13,'Watershed plans'!$AG$12:$AG$267,0)),"") | F62: =IFERROR(INDEX('Watershed plans'!$O$12:$O$267,MATCH(13,'Watershed plans'!$AG$12:$AG$267,0)),"") | G62: =IFERROR(INDEX('Watershed plans'!$AE$12:$AE$267,MATCH(13,'Watershed plans'!$AG$12:$AG$267,0)),"") | H62: =IF(ISNUMBER(D62),D62-D61,"") | I62: =IF(ISNUMBER(E62),E62-E61,"") | J62: =IF(AND(ISNUMBER(H62),H62<>0),I62/H62,"")
A63: 14 | B63: =IFERROR(INDEX('Watershed plans'!$L$12:$L$267,MATCH(14,'Watershed plans'!$AG$12:$AG$267,0)),"") | C63: =IFERROR(INDEX('Watershed plans'!$B$12:$B$267,MATCH(14,'Watershed plans'!$AG$12:$AG$267,0)),"") | D63: =IFERROR(INDEX('Watershed plans'!$P$12:$P$267,MATCH(14,'Watershed plans'!$AG$12:$AG$267,0)),"") | E63: =IFERROR(INDEX('Watershed plans'!$Q$12:$Q$267,MATCH(14,'Watershed plans'!$AG$12:$AG$267,0)),"") | F63: =IFERROR(INDEX('Watershed plans'!$O$12:$O$267,MATCH(14,'Watershed plans'!$AG$12:$AG$267,0)),"") | G63: =IFERROR(INDEX('Watershed plans'!$AE$12:$AE$267,MATCH(14,'Watershed plans'!$AG$12:$AG$267,0)),"") | H63: =IF(ISNUMBER(D63),D63-D62,"") | I63: =IF(ISNUMBER(E63),E63-E62,"") | J63: =IF(AND(ISNUMBER(H63),H63<>0),I63/H63,"")
A64: 15 | B64: =IFERROR(INDEX('Watershed plans'!$L$12:$L$267,MATCH(15,'Watershed plans'!$AG$12:$AG$267,0)),"") | C64: =IFERROR(INDEX('Watershed plans'!$B$12:$B$267,MATCH(15,'Watershed plans'!$AG$12:$AG$267,0)),"") | D64: =IFERROR(INDEX('Watershed plans'!$P$12:$P$267,MATCH(15,'Watershed plans'!$AG$12:$AG$267,0)),"") | E64: =IFERROR(INDEX('Watershed plans'!$Q$12:$Q$267,MATCH(15,'Watershed plans'!$AG$12:$AG$267,0)),"") | F64: =IFERROR(INDEX('Watershed plans'!$O$12:$O$267,MATCH(15,'Watershed plans'!$AG$12:$AG$267,0)),"") | G64: =IFERROR(INDEX('Watershed plans'!$AE$12:$AE$267,MATCH(15,'Watershed plans'!$AG$12:$AG$267,0)),"") | H64: =IF(ISNUMBER(D64),D64-D63,"") | I64: =IF(ISNUMBER(E64),E64-E63,"") | J64: =IF(AND(ISNUMBER(H64),H64<>0),I64/H64,"")
A65: 16 | B65: =IFERROR(INDEX('Watershed plans'!$L$12:$L$267,MATCH(16,'Watershed plans'!$AG$12:$AG$267,0)),"") | C65: =IFERROR(INDEX('Watershed plans'!$B$12:$B$267,MATCH(16,'Watershed plans'!$AG$12:$AG$267,0)),"") | D65: =IFERROR(INDEX('Watershed plans'!$P$12:$P$267,MATCH(16,'Watershed plans'!$AG$12:$AG$267,0)),"") | E65: =IFERROR(INDEX('Watershed plans'!$Q$12:$Q$267,MATCH(16,'Watershed plans'!$AG$12:$AG$267,0)),"") | F65: =IFERROR(INDEX('Watershed plans'!$O$12:$O$267,MATCH(16,'Watershed plans'!$AG$12:$AG$267,0)),"") | G65: =IFERROR(INDEX('Watershed plans'!$AE$12:$AE$267,MATCH(16,'Watershed plans'!$AG$12:$AG$267,0)),"") | H65: =IF(ISNUMBER(D65),D65-D64,"") | I65: =IF(ISNUMBER(E65),E65-E64,"") | J65: =IF(AND(ISNUMBER(H65),H65<>0),I65/H65,"")
