Workbook
Name calc_crf: Parameters!$B$11
Name in_cost_dp: Parameters!$B$9
Name in_idc_method: Parameters!$B$7
Name in_out_dp: Parameters!$B$10
Name in_poa: Parameters!$B$5
Name in_ppy: Parameters!$B$6
Name in_rate: Parameters!$B$4
Name in_timing: Parameters!$B$8
Name out_changed: 'Read me'!$B$11
Name out_mismatch: 'Read me'!$B$12
Name out_status: 'Read me'!$B$10

Sheet Read me
A1: Mixed test: CE/ICA calculator
A2: Cost-effectiveness and incremental cost analysis, as live formulas.
A4: Study | B4: Mixed test
A5: Generated by | B5: CEICA 0.1.0 (engine 1)
A6: Project digest | B6: 8030b2b0f57f
A7: Discount rate | B7: 3 percent
A8: Period of analysis | B8: 50 years
A10: Status | B10: =IF(B11=0,IF(B12=0,"Unchanged: matches the CEICA export","ERROR: results differ from the export although no input changed"),"Edited: "&B11&" input cells changed since the export") -> Edited: 3 input cells changed since the export
A11: Inputs changed | B11: =(SUMPRODUCT(1*(Parameters!B4:B10<>'snap Parameters'!B4:B10))+SUMPRODUCT(1*(Parameters!B14:D14<>'snap Parameters'!B14:D14))+SUMPRODUCT(1*(Benefits!L6:N10<>'snap Benefits'!L6:N10))+SUMPRODUCT(1*(Benefits!F11:K15<>'snap Benefits'!F11:K15))+SUMPRODUCT(1*(Benefits!O16:O20<>'snap Benefits'!O16:O20))+SUMPRODUCT(1*(Costs!D6:G10<>'snap Costs'!D6:G10))+SUMPRODUCT(1*(Costs!L6:L10<>'snap Costs'!L6:L10))+SUMPRODUCT(1*(Sites!C5:C6<>'snap Sites'!C5:C6))+SUMPRODUCT(1*('Watershed plans'!Z12:Z15<>'snap Watershed plans'!Z12:Z15))+SUMPRODUCT(1*('Watershed summary'!K50:L89<>'snap Watershed summary'!K50:L89))+SUMPRODUCT(1*('Watershed summary'!B93:B93<>'snap Watershed summary'!B93:B93))) -> 3
A12: Results that differ from the export | B12: =(SUMPRODUCT(1*(ABS(Summary!G5:G9-'snap Summary'!G5:G9)>0.000001))+SUMPRODUCT(1*(ABS(Summary!L5:L9-'snap Summary'!L5:L9)>0.0001))+SUMPRODUCT(1*('Site CE-ICA'!L6:L8<>'snap Site CE-ICA'!L6:L8))+SUMPRODUCT(1*('Site CE-ICA'!P6:P8<>'snap Site CE-ICA'!P6:P8))+SUMPRODUCT(1*('Site CE-ICA'!L11:L12<>'snap Site CE-ICA'!L11:L12))+SUMPRODUCT(1*('Site CE-ICA'!P11:P12<>'snap Site CE-ICA'!P11:P12))+SUMPRODUCT(1*('Watershed plans'!N12:N15<>'snap Watershed plans'!N12:N15))+SUMPRODUCT(1*('Watershed plans'!R12:R15<>'snap Watershed plans'!R12:R15))) -> 6
A14: How to use
A15: - Orange cells are inputs; grey cells are formulas. Sheets are protected (password 'ceica') only to prevent accidental edits.
A16: - Change any orange cell: annualization, site CE/ICA, the watershed plans and the summary update. Changed inputs turn yellow.
A17: - To add sites, alternatives or years, make the change in CEICA and export again.
A18: - Import this workbook in CEICA to bring your changes back into the project.
A20: Legend
A21: Input
A22: Formula
A23: Changed since export

Sheet Parameters
A1: Parameters
A2: Economics and conventions. Orange cells are inputs.
A3: Parameter | B3: Value
A4: Discount rate | B4: 0.04
A5: Period of analysis (years) | B5: 50
A6: Interest during construction: periods per year | B6: 12
A7: Interest during construction: spending in each period (END, MIDDLE or START) | B7: END
A8: OMRRR discounting (END_OF_YEAR or MID_YEAR) | B8: END_OF_YEAR
A9: Cost decimals kept for CE/ICA | B9: 2
A10: Output decimals kept for CE/ICA | B10: 3
A11: Capital recovery factor | B11: =IF(in_rate=0,1/in_poa,in_rate*(1+in_rate)^in_poa/((1+in_rate)^in_poa-1)) -> 0.0465502
A13: Target years | B13: Year 1 | C13: Year 2 | D13: Year 3
A14: Years (first to last) | B14: 0 | C14: 5 | D14: 50

Sheet Benefits
A1: Benefits: habitat units by module
A2: One row per module, site and alternative; the Summary adds the modules' averages. Habitat: habitat units entered at each target year; Riparian: index x quantity at each target year; Wetland: the average entered directly. Averages are the area under straight lines between target years.
A4: Key | B4: Site | C4: Alternative | D4: Module | E4: Method | F4: Index (0 to 1) | I4: Quantity | L4: Habitat units (HU) | O4: Average (AAHU)
F5: =Parameters!$B$14 -> 0 | G5: =Parameters!$C$14 -> 5 | H5: =Parameters!$D$14 -> 50 | I5: =Parameters!$B$14 -> 0 | J5: =Parameters!$C$14 -> 5 | K5: =Parameters!$D$14 -> 50 | L5: =Parameters!$B$14 -> 0 | M5: =Parameters!$C$14 -> 5 | N5: =Parameters!$D$14 -> 50
A6: =B6&"|"&C6 -> A|NA | B6: A | C6: NA | D6: Habitat | E6: Habitat units | L6: 1 | M6: 1 | N6: 1 | O6: =SUMPRODUCT($M$5:$N$5-$L$5:$M$5,(M6:N6+L6:M6)/2)/($N$5-$L$5) -> 1
A7: =B7&"|"&C7 -> A|A1 | B7: A | C7: A1 | D7: Habitat | E7: Habitat units | L7: 1 | M7: 4 | N7: 5 | O7: =SUMPRODUCT($M$5:$N$5-$L$5:$M$5,(M7:N7+L7:M7)/2)/($N$5-$L$5) -> 4.3
A8: =B8&"|"&C8 -> A|A2 | B8: A | C8: A2 | D8: Habitat | E8: Habitat units | L8: 1 | M8: 2 | N8: 2.5 | O8: =SUMPRODUCT($M$5:$N$5-$L$5:$M$5,(M8:N8+L8:M8)/2)/($N$5-$L$5) -> 2.175
A9: =B9&"|"&C9 -> B|NA | B9: B | C9: NA | D9: Habitat | E9: Habitat units | L9: 2 | M9: 2 | N9: 2 | O9: =SUMPRODUCT($M$5:$N$5-$L$5:$M$5,(M9:N9+L9:M9)/2)/($N$5-$L$5) -> 2
A10: =B10&"|"&C10 -> B|B1 | B10: B | C10: B1 | D10: Habitat | E10: Habitat units | L10: 2 | M10: 5 | N10: 6 | O10: =SUMPRODUCT($M$5:$N$5-$L$5:$M$5,(M10:N10+L10:M10)/2)/($N$5-$L$5) -> 5.3
A11: =B11&"|"&C11 -> A|NA | B11: A | C11: NA | D11: Riparian | E11: Index x quantity | F11: 0.2 | G11: 0.2 | H11: 0.2 | I11: 3 | J11: 3 | K11: 3 | L11: =F11*I11 -> 0.6 | M11: =G11*J11 -> 0.6 | N11: =H11*K11 -> 0.6 | O11: =SUMPRODUCT($M$5:$N$5-$L$5:$M$5,(M11:N11+L11:M11)/2)/($N$5-$L$5) -> 0.6
A12: =B12&"|"&C12 -> A|A1 | B12: A | C12: A1 | D12: Riparian | E12: Index x quantity | F12: 0.2 | G12: 0.5 | H12: 0.7 | I12: 3 | J12: 3.5 | K12: 3.5 | L12: =F12*I12 -> 0.6 | M12: =G12*J12 -> 1.75 | N12: =H12*K12 -> 2.45 | O12: =SUMPRODUCT($M$5:$N$5-$L$5:$M$5,(M12:N12+L12:M12)/2)/($N$5-$L$5) -> 2.0075
A13: =B13&"|"&C13 -> A|A2 | B13: A | C13: A2 | D13: Riparian | E13: Index x quantity | F13: 0.2 | G13: 0.6 | H13: 0.8 | I13: 3 | J13: 3 | K13: 3 | L13: =F13*I13 -> 0.6 | M13: =G13*J13 -> 1.8 | N13: =H13*K13 -> 2.4 | O13: =SUMPRODUCT($M$5:$N$5-$L$5:$M$5,(M13:N13+L13:M13)/2)/($N$5-$L$5) -> 2.01
A14: =B14&"|"&C14 -> B|NA | B14: B | C14: NA | D14: Riparian | E14: Index x quantity | F14: 0.4 | G14: 0.4 | H14: 0.4 | I14: 1 | J14: 1 | K14: 1 | L14: =F14*I14 -> 0.4 | M14: =G14*J14 -> 0.4 | N14: =H14*K14 -> 0.4 | O14: =SUMPRODUCT($M$5:$N$5-$L$5:$M$5,(M14:N14+L14:M14)/2)/($N$5-$L$5) -> 0.4
A15: =B15&"|"&C15 -> B|B1 | B15: B | C15: B1 | D15: Riparian | E15: Index x quantity | F15: 0.4 | G15: 0.4 | H15: 0.9 | I15: 1 | J15: 1 | K15: 2 | L15: =F15*I15 -> 0.4 | M15: =G15*J15 -> 0.4 | N15: =H15*K15 -> 1.8 | O15: =SUMPRODUCT($M$5:$N$5-$L$5:$M$5,(M15:N15+L15:M15)/2)/($N$5-$L$5) -> 1.03
A16: =B16&"|"&C16 -> A|NA | B16: A | C16: NA | D16: Wetland | E16: Average annual value | O16: 0
A17: =B17&"|"&C17 -> A|A1 | B17: A | C17: A1 | D17: Wetland | E17: Average annual value | O17: 1.5
A18: =B18&"|"&C18 -> A|A2 | B18: A | C18: A2 | D18: Wetland | E18: Average annual value | O18: 0.5
A19: =B19&"|"&C19 -> B|NA | B19: B | C19: NA | D19: Wetland | E19: Average annual value | O19: 0
A20: =B20&"|"&C20 -> B|B1 | B20: B | C20: B1 | D20: Wetland | E20: Average annual value | O20: 2

Sheet Costs
A1: Costs: first costs, interest during construction and OMRRR
A2: First costs are base-year lump sums. Interest during construction accrues on the categories marked *, spent evenly over the construction months.
N3: Average annual cost by part
A4: Key | B4: Site | C4: Alternative | D4: Construction * | E4: Monitoring | F4: Adaptive management | G4: Construction months | H4: IDC base | I4: Interest during construction | J4: OMRRR present value | K4: Total present value | L4: Average annual cost entered | M4: Average annual cost | N4: Construction | O4: Monitoring | P4: Adaptive management | Q4: Interest during construction | R4: OMRRR
D5: construction | E5: monitoring | F5: adaptive_management
A6: =B6&"|"&C6 -> A|NA | B6: A | C6: NA | D6: 0 | G6: 4 | H6: =D6 -> 0 | I6: =IF(OR(G6=0,in_rate=0,H6=0),0,H6/G6*(IF(in_idc_method="START",1+((1+in_rate)^(1/in_ppy)-1),IF(in_idc_method="MIDDLE",1+((1+in_rate)^(1/in_ppy)-1)/2,1))*((1+in_rate)^(G6/in_ppy)-1)/((1+in_rate)^(1/in_ppy)-1)-G6)) -> 0 | J6: =SUMIFS(OMRRR!$S$5:$S$5,OMRRR!$A$5:$A$5,A6) -> 0 | K6: =SUM(D6:F6)+I6+J6 -> 0 | M6: =IF(ISNUMBER(L6),L6,calc_crf*K6) -> 0 | N6: =calc_crf*D6 -> 0 | O6: =calc_crf*E6 -> 0 | P6: =calc_crf*F6 -> 0 | Q6: =calc_crf*I6 -> 0 | R6: =calc_crf*J6 -> 0
A7: =B7&"|"&C7 -> A|A1 | B7: A | C7: A1 | D7: 400000 | G7: 4 | H7: =D7 -> 400000 | I7: =IF(OR(G7=0,in_rate=0,H7=0),0,H7/G7*(IF(in_idc_method="START",1+((1+in_rate)^(1/in_ppy)-1),IF(in_idc_method="MIDDLE",1+((1+in_rate)^(1/in_ppy)-1)/2,1))*((1+in_rate)^(G7/in_ppy)-1)/((1+in_rate)^(1/in_ppy)-1)-G7)) -> 1968.5343 | J7: =SUMIFS(OMRRR!$S$5:$S$5,OMRRR!$A$5:$A$5,A7) -> 0 | K7: =SUM(D7:F7)+I7+J7 -> 401968.53 | M7: =IF(ISNUMBER(L7),L7,calc_crf*K7) -> 18711.716 | N7: =calc_crf*D7 -> 18620.08 | O7: =calc_crf*E7 -> 0 | P7: =calc_crf*F7 -> 0 | Q7: =calc_crf*I7 -> 91.635668 | R7: =calc_crf*J7 -> 0
A8: =B8&"|"&C8 -> A|A2 | B8: A | C8: A2 | D8: 180000 | G8: 4 | H8: =D8 -> 180000 | I8: =IF(OR(G8=0,in_rate=0,H8=0),0,H8/G8*(IF(in_idc_method="START",1+((1+in_rate)^(1/in_ppy)-1),IF(in_idc_method="MIDDLE",1+((1+in_rate)^(1/in_ppy)-1)/2,1))*((1+in_rate)^(G8/in_ppy)-1)/((1+in_rate)^(1/in_ppy)-1)-G8)) -> 885.84045 | J8: =SUMIFS(OMRRR!$S$5:$S$5,OMRRR!$A$5:$A$5,A8) -> 0 | K8: =SUM(D8:F8)+I8+J8 -> 180885.84 | M8: =IF(ISNUMBER(L8),L8,calc_crf*K8) -> 8420.2721 | N8: =calc_crf*D8 -> 8379.0361 | O8: =calc_crf*E8 -> 0 | P8: =calc_crf*F8 -> 0 | Q8: =calc_crf*I8 -> 41.23605 | R8: =calc_crf*J8 -> 0
A9: =B9&"|"&C9 -> B|NA | B9: B | C9: NA | D9: 0 | G9: 4 | H9: =D9 -> 0 | I9: =IF(OR(G9=0,in_rate=0,H9=0),0,H9/G9*(IF(in_idc_method="START",1+((1+in_rate)^(1/in_ppy)-1),IF(in_idc_method="MIDDLE",1+((1+in_rate)^(1/in_ppy)-1)/2,1))*((1+in_rate)^(G9/in_ppy)-1)/((1+in_rate)^(1/in_ppy)-1)-G9)) -> 0 | J9: =SUMIFS(OMRRR!$S$5:$S$5,OMRRR!$A$5:$A$5,A9) -> 0 | K9: =SUM(D9:F9)+I9+J9 -> 0 | M9: =IF(ISNUMBER(L9),L9,calc_crf*K9) -> 0 | N9: =calc_crf*D9 -> 0 | O9: =calc_crf*E9 -> 0 | P9: =calc_crf*F9 -> 0 | Q9: =calc_crf*I9 -> 0 | R9: =calc_crf*J9 -> 0
A10: =B10&"|"&C10 -> B|B1 | B10: B | C10: B1 | D10: 300000 | G10: 4 | H10: =D10 -> 300000 | I10: =IF(OR(G10=0,in_rate=0,H10=0),0,H10/G10*(IF(in_idc_method="START",1+((1+in_rate)^(1/in_ppy)-1),IF(in_idc_method="MIDDLE",1+((1+in_rate)^(1/in_ppy)-1)/2,1))*((1+in_rate)^(G10/in_ppy)-1)/((1+in_rate)^(1/in_ppy)-1)-G10)) -> 1476.4007 | J10: =SUMIFS(OMRRR!$S$5:$S$5,OMRRR!$A$5:$A$5,A10) -> 0 | K10: =SUM(D10:F10)+I10+J10 -> 301476.4 | M10: =IF(ISNUMBER(L10),L10,calc_crf*K10) -> 14033.787 | N10: =calc_crf*D10 -> 13965.06 | O10: =calc_crf*E10 -> 0 | P10: =calc_crf*F10 -> 0 | Q10: =calc_crf*I10 -> 68.726751 | R10: =calc_crf*J10 -> 0

Sheet OMRRR
A1: OMRRR: recurring operation, maintenance, repair, replacement and rehabilitation
A2: Each item costs the amount per occurrence every N years from the first year to the last (blank: every N years through the period of analysis). Basis: FIXED amount, PERCENT of a first-cost category, or RATE x quantity.
A4: Key | B4: Site | C4: Alternative | D4: Item | E4: Basis | F4: Amount | G4: Percent | H4: Category | I4: Unit rate | J4: Quantity | K4: Every N years | L4: First year | M4: Last year | N4: Amount per occurrence | O4: First | P4: Last | Q4: Occurrences | R4: Present value, end of year | S4: Present value

Sheet Summary
A1: Summary of inputs to CE/ICA
A2: Lift is each alternative's AAHU above No Action; the CE/ICA cost is its average annual cost above No Action.
A4: Key | B4: Site | C4: Alternative | D4: Name | E4: No Action | F4: Outputs (AAHU) | G4: Lift (AAHU) | H4: Construction cost | I4: First costs | J4: Interest during construction | K4: OMRRR present value | L4: Average annual cost | M4: Cost above No Action | N4: Unit cost ($/AAHU)
A5: =B5&"|"&C5 -> A|NA | B5: A | C5: NA | D5: NA | E5: 1 | F5: =SUMIFS(Benefits!$O$6:$O$20,Benefits!$A$6:$A$20,A5) -> 1.6 | G5: =F5-$F$5 -> 0 | H5: =Costs!D6 -> 0 | I5: =SUM(Costs!D6:F6) -> 0 | J5: =Costs!I6 -> 0 | K5: =Costs!J6 -> 0 | L5: =Costs!M6 -> 0 | M5: =L5-$L$5 -> 0 | N5: =IF(G5>0,M5/G5,"n/a") -> n/a
A6: =B6&"|"&C6 -> A|A1 | B6: A | C6: A1 | D6: A1 | E6: 0 | F6: =SUMIFS(Benefits!$O$6:$O$20,Benefits!$A$6:$A$20,A6) -> 7.8075 | G6: =F6-$F$5 -> 6.2075 | H6: =Costs!D7 -> 400000 | I6: =SUM(Costs!D7:F7) -> 400000 | J6: =Costs!I7 -> 1968.5343 | K6: =Costs!J7 -> 0 | L6: =Costs!M7 -> 18711.716 | M6: =L6-$L$5 -> 18711.716 | N6: =IF(G6>0,M6/G6,"n/a") -> 3014.3723
A7: =B7&"|"&C7 -> A|A2 | B7: A | C7: A2 | D7: A2 | E7: 0 | F7: =SUMIFS(Benefits!$O$6:$O$20,Benefits!$A$6:$A$20,A7) -> 4.685 | G7: =F7-$F$5 -> 3.085 | H7: =Costs!D8 -> 180000 | I7: =SUM(Costs!D8:F8) -> 180000 | J7: =Costs!I8 -> 885.84045 | K7: =Costs!J8 -> 0 | L7: =Costs!M8 -> 8420.2721 | M7: =L7-$L$5 -> 8420.2721 | N7: =IF(G7>0,M7/G7,"n/a") -> 2729.4237
A8: =B8&"|"&C8 -> B|NA | B8: B | C8: NA | D8: NA | E8: 1 | F8: =SUMIFS(Benefits!$O$6:$O$20,Benefits!$A$6:$A$20,A8) -> 2.4 | G8: =F8-$F$8 -> 0 | H8: =Costs!D9 -> 0 | I8: =SUM(Costs!D9:F9) -> 0 | J8: =Costs!I9 -> 0 | K8: =Costs!J9 -> 0 | L8: =Costs!M9 -> 0 | M8: =L8-$L$8 -> 0 | N8: =IF(G8>0,M8/G8,"n/a") -> n/a
A9: =B9&"|"&C9 -> B|B1 | B9: B | C9: B1 | D9: B1 | E9: 0 | F9: =SUMIFS(Benefits!$O$6:$O$20,Benefits!$A$6:$A$20,A9) -> 8.33 | G9: =F9-$F$8 -> 5.93 | H9: =Costs!D10 -> 300000 | I9: =SUM(Costs!D10:F10) -> 300000 | J9: =Costs!I10 -> 1476.4007 | K9: =Costs!J10 -> 0 | L9: =Costs!M10 -> 14033.787 | M9: =L9-$L$8 -> 14033.787 | N9: =IF(G9>0,M9/G9,"n/a") -> 2366.5745

Sheet Site CE-ICA
A1: Site-by-site CE/ICA
A2: Cost-effective: no alternative gives the same output for less, or more output for no more. Best buy: on the lower hull from No Action (IWR Planning Suite II rules).
A4: Key | B4: Site | C4: Alternative | D4: Name | E4: No Action | F4: Ordinal | G4: Lift (AAHU) | H4: Cost above No Action | I4: Lift (scaled) | J4: Cost (scaled) | K4: Dominated by | L4: Cost-effective | M4: Candidate | N4: Slope in (max) | O4: Slope out (min) | P4: Best buy | Q4: Best-buy step | R4: Previous lift (scaled) | S4: Previous cost (scaled) | T4: Incremental output | U4: Incremental cost | V4: Incremental cost per unit | W4: Unit cost | X4: Recommended
B5: A
A6: =B6&"|"&C6 -> A|NA | B6: A | C6: NA | D6: NA | E6: 1 | F6: 1 | G6: =Summary!G5 -> 0 | H6: =Summary!M5 -> 0 | I6: =ROUND(G6*10^in_out_dp,0) -> 0 | J6: =ROUND(H6*10^in_cost_dp,0) -> 0 | K6: =SUMPRODUCT(($I$6:$I$8=I6)*($J$6:$J$8<J6)+($I$6:$I$8>I6)*($J$6:$J$8<=J6)) -> 0 | L6: =IF(OR(E6=1,K6=0),1,0) -> 1 | M6: =IF(AND(L6=1,E6=0,I6>0),1,0) -> 0 | N6: =IF(M6=1,MAX(J6/I6,SUMPRODUCT(MAX(((J6-$J$6:$J$8)*($M$6:$M$8*($I$6:$I$8<I6)))/((I6-$I$6:$I$8)*($M$6:$M$8*($I$6:$I$8<I6))+1-($M$6:$M$8*($I$6:$I$8<I6)))-(1-($M$6:$M$8*($I$6:$I$8<I6)))*1E+300))),0) -> 0 | O6: =IF(M6=1,SUMPRODUCT(MIN(((($J$6:$J$8-J6)*($M$6:$M$8*($I$6:$I$8>I6)))/(($I$6:$I$8-I6)*($M$6:$M$8*($I$6:$I$8>I6))+1-($M$6:$M$8*($I$6:$I$8>I6)))+(1-($M$6:$M$8*($I$6:$I$8>I6)))*1E+300))),0) -> 0 | P6: =IF(E6=1,1,IF(AND(M6=1,N6<=O6),1,0)) -> 1 | Q6: =IF(P6=1,1+SUMPRODUCT($P$6:$P$8*(($I$6:$I$8<I6)+($I$6:$I$8=I6)*($F$6:$F$8<F6))),0) -> 1 | R6: =IF(Q6<=1,0,SUMPRODUCT(($Q$6:$Q$8=Q6-1)*$I$6:$I$8)) -> 0 | S6: =IF(Q6<=1,0,SUMPRODUCT(($Q$6:$Q$8=Q6-1)*$J$6:$J$8)) -> 0 | T6: =IF(Q6=0,"",(I6-R6)/10^in_out_dp) -> 0 | U6: =IF(Q6=0,"",(J6-S6)/10^in_cost_dp) -> 0 | V6: =IF(Q6=0,"",IF(I6=R6,0,U6/T6)) -> 0 | W6: =IF(I6>0,(J6/10^in_cost_dp)/(I6/10^in_out_dp),"n/a") -> n/a | X6: =IF(Sites!$C$5=C6,1,0) -> 0
A7: =B7&"|"&C7 -> A|A1 | B7: A | C7: A1 | D7: A1 | E7: 0 | F7: 2 | G7: =Summary!G6 -> 6.2075 | H7: =Summary!M6 -> 18711.716 | I7: =ROUND(G7*10^in_out_dp,0) -> 6208 | J7: =ROUND(H7*10^in_cost_dp,0) -> 1871172 | K7: =SUMPRODUCT(($I$6:$I$8=I7)*($J$6:$J$8<J7)+($I$6:$I$8>I7)*($J$6:$J$8<=J7)) -> 0 | L7: =IF(OR(E7=1,K7=0),1,0) -> 1 | M7: =IF(AND(L7=1,E7=0,I7>0),1,0) -> 1 | N7: =IF(M7=1,MAX(J7/I7,SUMPRODUCT(MAX(((J7-$J$6:$J$8)*($M$6:$M$8*($I$6:$I$8<I7)))/((I7-$I$6:$I$8)*($M$6:$M$8*($I$6:$I$8<I7))+1-($M$6:$M$8*($I$6:$I$8<I7)))-(1-($M$6:$M$8*($I$6:$I$8<I7)))*1E+300))),0) -> 329.5373 | O7: =IF(M7=1,SUMPRODUCT(MIN(((($J$6:$J$8-J7)*($M$6:$M$8*($I$6:$I$8>I7)))/(($I$6:$I$8-I7)*($M$6:$M$8*($I$6:$I$8>I7))+1-($M$6:$M$8*($I$6:$I$8>I7)))+(1-($M$6:$M$8*($I$6:$I$8>I7)))*1E+300))),0) -> 1e+300 | P7: =IF(E7=1,1,IF(AND(M7=1,N7<=O7),1,0)) -> 1 | Q7: =IF(P7=1,1+SUMPRODUCT($P$6:$P$8*(($I$6:$I$8<I7)+($I$6:$I$8=I7)*($F$6:$F$8<F7))),0) -> 3 | R7: =IF(Q7<=1,0,SUMPRODUCT(($Q$6:$Q$8=Q7-1)*$I$6:$I$8)) -> 3085 | S7: =IF(Q7<=1,0,SUMPRODUCT(($Q$6:$Q$8=Q7-1)*$J$6:$J$8)) -> 842027 | T7: =IF(Q7=0,"",(I7-R7)/10^in_out_dp) -> 3.123 | U7: =IF(Q7=0,"",(J7-S7)/10^in_cost_dp) -> 10291.45 | V7: =IF(Q7=0,"",IF(I7=R7,0,U7/T7)) -> 3295.373 | W7: =IF(I7>0,(J7/10^in_cost_dp)/(I7/10^in_out_dp),"n/a") -> 3014.1302 | X7: =IF(Sites!$C$5=C7,1,0) -> 1
A8: =B8&"|"&C8 -> A|A2 | B8: A | C8: A2 | D8: A2 | E8: 0 | F8: 3 | G8: =Summary!G7 -> 3.085 | H8: =Summary!M7 -> 8420.2721 | I8: =ROUND(G8*10^in_out_dp,0) -> 3085 | J8: =ROUND(H8*10^in_cost_dp,0) -> 842027 | K8: =SUMPRODUCT(($I$6:$I$8=I8)*($J$6:$J$8<J8)+($I$6:$I$8>I8)*($J$6:$J$8<=J8)) -> 0 | L8: =IF(OR(E8=1,K8=0),1,0) -> 1 | M8: =IF(AND(L8=1,E8=0,I8>0),1,0) -> 1 | N8: =IF(M8=1,MAX(J8/I8,SUMPRODUCT(MAX(((J8-$J$6:$J$8)*($M$6:$M$8*($I$6:$I$8<I8)))/((I8-$I$6:$I$8)*($M$6:$M$8*($I$6:$I$8<I8))+1-($M$6:$M$8*($I$6:$I$8<I8)))-(1-($M$6:$M$8*($I$6:$I$8<I8)))*1E+300))),0) -> 272.9423 | O8: =IF(M8=1,SUMPRODUCT(MIN(((($J$6:$J$8-J8)*($M$6:$M$8*($I$6:$I$8>I8)))/(($I$6:$I$8-I8)*($M$6:$M$8*($I$6:$I$8>I8))+1-($M$6:$M$8*($I$6:$I$8>I8)))+(1-($M$6:$M$8*($I$6:$I$8>I8)))*1E+300))),0) -> 329.5373 | P8: =IF(E8=1,1,IF(AND(M8=1,N8<=O8),1,0)) -> 1 | Q8: =IF(P8=1,1+SUMPRODUCT($P$6:$P$8*(($I$6:$I$8<I8)+($I$6:$I$8=I8)*($F$6:$F$8<F8))),0) -> 2 | R8: =IF(Q8<=1,0,SUMPRODUCT(($Q$6:$Q$8=Q8-1)*$I$6:$I$8)) -> 0 | S8: =IF(Q8<=1,0,SUMPRODUCT(($Q$6:$Q$8=Q8-1)*$J$6:$J$8)) -> 0 | T8: =IF(Q8=0,"",(I8-R8)/10^in_out_dp) -> 3.085 | U8: =IF(Q8=0,"",(J8-S8)/10^in_cost_dp) -> 8420.27 | V8: =IF(Q8=0,"",IF(I8=R8,0,U8/T8)) -> 2729.423 | W8: =IF(I8>0,(J8/10^in_cost_dp)/(I8/10^in_out_dp),"n/a") -> 2729.423 | X8: =IF(Sites!$C$5=C8,1,0) -> 0
B10: B
A11: =B11&"|"&C11 -> B|NA | B11: B | C11: NA | D11: NA | E11: 1 | F11: 1 | G11: =Summary!G8 -> 0 | H11: =Summary!M8 -> 0 | I11: =ROUND(G11*10^in_out_dp,0) -> 0 | J11: =ROUND(H11*10^in_cost_dp,0) -> 0 | K11: =SUMPRODUCT(($I$11:$I$12=I11)*($J$11:$J$12<J11)+($I$11:$I$12>I11)*($J$11:$J$12<=J11)) -> 0 | L11: =IF(OR(E11=1,K11=0),1,0) -> 1 | M11: =IF(AND(L11=1,E11=0,I11>0),1,0) -> 0 | N11: =IF(M11=1,MAX(J11/I11,SUMPRODUCT(MAX(((J11-$J$11:$J$12)*($M$11:$M$12*($I$11:$I$12<I11)))/((I11-$I$11:$I$12)*($M$11:$M$12*($I$11:$I$12<I11))+1-($M$11:$M$12*($I$11:$I$12<I11)))-(1-($M$11:$M$12*($I$11:$I$12<I11)))*1E+300))),0) -> 0 | O11: =IF(M11=1,SUMPRODUCT(MIN(((($J$11:$J$12-J11)*($M$11:$M$12*($I$11:$I$12>I11)))/(($I$11:$I$12-I11)*($M$11:$M$12*($I$11:$I$12>I11))+1-($M$11:$M$12*($I$11:$I$12>I11)))+(1-($M$11:$M$12*($I$11:$I$12>I11)))*1E+300))),0) -> 0 | P11: =IF(E11=1,1,IF(AND(M11=1,N11<=O11),1,0)) -> 1 | Q11: =IF(P11=1,1+SUMPRODUCT($P$11:$P$12*(($I$11:$I$12<I11)+($I$11:$I$12=I11)*($F$11:$F$12<F11))),0) -> 1 | R11: =IF(Q11<=1,0,SUMPRODUCT(($Q$11:$Q$12=Q11-1)*$I$11:$I$12)) -> 0 | S11: =IF(Q11<=1,0,SUMPRODUCT(($Q$11:$Q$12=Q11-1)*$J$11:$J$12)) -> 0 | T11: =IF(Q11=0,"",(I11-R11)/10^in_out_dp) -> 0 | U11: =IF(Q11=0,"",(J11-S11)/10^in_cost_dp) -> 0 | V11: =IF(Q11=0,"",IF(I11=R11,0,U11/T11)) -> 0 | W11: =IF(I11>0,(J11/10^in_cost_dp)/(I11/10^in_out_dp),"n/a") -> n/a | X11: =IF(Sites!$C$6=C11,1,0) -> 1
A12: =B12&"|"&C12 -> B|B1 | B12: B | C12: B1 | D12: B1 | E12: 0 | F12: 2 | G12: =Summary!G9 -> 5.93 | H12: =Summary!M9 -> 14033.787 | I12: =ROUND(G12*10^in_out_dp,0) -> 5930 | J12: =ROUND(H12*10^in_cost_dp,0) -> 1403379 | K12: =SUMPRODUCT(($I$11:$I$12=I12)*($J$11:$J$12<J12)+($I$11:$I$12>I12)*($J$11:$J$12<=J12)) -> 0 | L12: =IF(OR(E12=1,K12=0),1,0) -> 1 | M12: =IF(AND(L12=1,E12=0,I12>0),1,0) -> 1 | N12: =IF(M12=1,MAX(J12/I12,SUMPRODUCT(MAX(((J12-$J$11:$J$12)*($M$11:$M$12*($I$11:$I$12<I12)))/((I12-$I$11:$I$12)*($M$11:$M$12*($I$11:$I$12<I12))+1-($M$11:$M$12*($I$11:$I$12<I12)))-(1-($M$11:$M$12*($I$11:$I$12<I12)))*1E+300))),0) -> 236.6575 | O12: =IF(M12=1,SUMPRODUCT(MIN(((($J$11:$J$12-J12)*($M$11:$M$12*($I$11:$I$12>I12)))/(($I$11:$I$12-I12)*($M$11:$M$12*($I$11:$I$12>I12))+1-($M$11:$M$12*($I$11:$I$12>I12)))+(1-($M$11:$M$12*($I$11:$I$12>I12)))*1E+300))),0) -> 1e+300 | P12: =IF(E12=1,1,IF(AND(M12=1,N12<=O12),1,0)) -> 1 | Q12: =IF(P12=1,1+SUMPRODUCT($P$11:$P$12*(($I$11:$I$12<I12)+($I$11:$I$12=I12)*($F$11:$F$12<F12))),0) -> 2 | R12: =IF(Q12<=1,0,SUMPRODUCT(($Q$11:$Q$12=Q12-1)*$I$11:$I$12)) -> 0 | S12: =IF(Q12<=1,0,SUMPRODUCT(($Q$11:$Q$12=Q12-1)*$J$11:$J$12)) -> 0 | T12: =IF(Q12=0,"",(I12-R12)/10^in_out_dp) -> 5.93 | U12: =IF(Q12=0,"",(J12-S12)/10^in_cost_dp) -> 14033.79 | V12: =IF(Q12=0,"",IF(I12=R12,0,U12/T12)) -> 2366.575 | W12: =IF(I12>0,(J12/10^in_cost_dp)/(I12/10^in_out_dp),"n/a") -> 2366.575 | X12: =IF(Sites!$C$6=C12,1,0) -> 0

Sheet Sites
A1: Sites: the alternative carried to the watershed plans
A2: Choose each site's recommended alternative. No Action leaves the site out of every watershed plan.
A4: Site | B4: Name | C4: Recommended alternative | D4: No Action | E4: Carried | F4: Lift (AAHU) | G4: Cost above No Action | H4: Construction cost | I4: Lift (scaled) | J4: Cost (scaled) | K4: Cost-effective | L4: Best buy | M4: Decided by
A5: A | C5: A1 | D5: NA | E5: =IF(C5<>D5,1,0) -> 1 | F5: =IFERROR(INDEX('Site CE-ICA'!$G$5:$G$12,MATCH(A5&"|"&C5,'Site CE-ICA'!$A$5:$A$12,0)),0) -> 6.2075 | G5: =IFERROR(INDEX('Site CE-ICA'!$H$5:$H$12,MATCH(A5&"|"&C5,'Site CE-ICA'!$A$5:$A$12,0)),0) -> 18711.716 | H5: =IFERROR(INDEX(Summary!$H$5:$H$7,MATCH(C5,Summary!$C$5:$C$7,0)),0) -> 400000 | I5: =IF(E5=1,IFERROR(INDEX('Site CE-ICA'!$I$5:$I$12,MATCH(A5&"|"&C5,'Site CE-ICA'!$A$5:$A$12,0)),0),0) -> 6208 | J5: =IF(E5=1,IFERROR(INDEX('Site CE-ICA'!$J$5:$J$12,MATCH(A5&"|"&C5,'Site CE-ICA'!$A$5:$A$12,0)),0),0) -> 1871172 | K5: =IFERROR(INDEX('Site CE-ICA'!$L$5:$L$12,MATCH(A5&"|"&C5,'Site CE-ICA'!$A$5:$A$12,0)),0) -> 1 | L5: =IFERROR(INDEX('Site CE-ICA'!$P$5:$P$12,MATCH(A5&"|"&C5,'Site CE-ICA'!$A$5:$A$12,0)),0) -> 1 | M5: Suggested
A6: B | C6: NA | D6: NA | E6: =IF(C6<>D6,1,0) -> 0 | F6: =IFERROR(INDEX('Site CE-ICA'!$G$5:$G$12,MATCH(A6&"|"&C6,'Site CE-ICA'!$A$5:$A$12,0)),0) -> 0 | G6: =IFERROR(INDEX('Site CE-ICA'!$H$5:$H$12,MATCH(A6&"|"&C6,'Site CE-ICA'!$A$5:$A$12,0)),0) -> 0 | H6: =IFERROR(INDEX(Summary!$H$8:$H$9,MATCH(C6,Summary!$C$8:$C$9,0)),0) -> 0 | I6: =IF(E6=1,IFERROR(INDEX('Site CE-ICA'!$I$5:$I$12,MATCH(A6&"|"&C6,'Site CE-ICA'!$A$5:$A$12,0)),0),0) -> 0 | J6: =IF(E6=1,IFERROR(INDEX('Site CE-ICA'!$J$5:$J$12,MATCH(A6&"|"&C6,'Site CE-ICA'!$A$5:$A$12,0)),0),0) -> 0 | K6: =IFERROR(INDEX('Site CE-ICA'!$L$5:$L$12,MATCH(A6&"|"&C6,'Site CE-ICA'!$A$5:$A$12,0)),0) -> 1 | L6: =IFERROR(INDEX('Site CE-ICA'!$P$5:$P$12,MATCH(A6&"|"&C6,'Site CE-ICA'!$A$5:$A$12,0)),0) -> 1 | M6: Suggested

Sheet Watershed plans
A1: Watershed plans: every combination of the recommended site actions
A2: 1 and 0 mark a site included or excluded. Rows that include a site whose recommendation is No Action are not valid plans.
C4: Site | D4: A | E4: B
C5: Carried | D5: =Sites!E5 -> 1 | E5: =Sites!E6 -> 0
C6: Lift (scaled) | D6: =Sites!I5 -> 6208 | E6: =Sites!I6 -> 0
C7: Cost (scaled) | D7: =Sites!J5 -> 1871172 | E7: =Sites!J6 -> 0
C8: Construction cost | D8: =Sites!H5 -> 400000 | E8: =Sites!H6 -> 0
C9: Weight | D9: =IF(D5=1,2^SUM(E5:$E$5),0) -> 1 | E9: =IF(E5=1,1,0) -> 0
A11: Row | B11: Plan | C11: Valid | D11: A | E11: B | F11: Plan number | G11: Lift (scaled) | H11: Cost (scaled) | I11: Construction cost | J11: Lift (AAHU) | K11: Average annual cost | L11: No Action | M11: Dominated by | N11: Cost-effective | O11: Candidate | P11: Slope in (max) | Q11: Slope out (min) | R11: Best buy | S11: Best-buy step | T11: Previous lift (scaled) | U11: Previous cost (scaled) | V11: Incremental output | W11: Incremental cost | X11: Incremental cost per unit | Y11: Unit cost | Z11: Final array | AA11: Final array order
A12: 1 | B12: No Action | C12: =IF(SUMPRODUCT(D12:E12,1-$D$5:$E$5)=0,1,0) -> 1 | D12: 0 | E12: 0 | F12: =IF(C12=1,1+SUMPRODUCT(D12:E12,$D$9:$E$9),"") -> 1 | G12: =SUMPRODUCT(D12:E12,$D$6:$E$6) -> 0 | H12: =SUMPRODUCT(D12:E12,$D$7:$E$7) -> 0 | I12: =SUMPRODUCT(D12:E12,$D$8:$E$8) -> 0 | J12: =G12/10^in_out_dp -> 0 | K12: =H12/10^in_cost_dp -> 0 | L12: =IF(SUM(D12:E12)=0,1,0) -> 1 | M12: =SUMPRODUCT($C$12:$C$15*(($G$12:$G$15=G12)*($H$12:$H$15<H12)+($G$12:$G$15>G12)*($H$12:$H$15<=H12))) -> 0 | N12: =IF(C12=0,0,IF(OR(L12=1,M12=0),1,0)) -> 1 | O12: =IF(AND(N12=1,L12=0,G12>0),1,0) -> 0 | P12: =IF(O12=1,MAX(H12/G12,SUMPRODUCT(MAX(((H12-$H$12:$H$15)*($O$12:$O$15*($G$12:$G$15<G12)))/((G12-$G$12:$G$15)*($O$12:$O$15*($G$12:$G$15<G12))+1-($O$12:$O$15*($G$12:$G$15<G12)))-(1-($O$12:$O$15*($G$12:$G$15<G12)))*1E+300))),0) -> 0 | Q12: =IF(O12=1,SUMPRODUCT(MIN(((($H$12:$H$15-H12)*($O$12:$O$15*($G$12:$G$15>G12)))/(($G$12:$G$15-G12)*($O$12:$O$15*($G$12:$G$15>G12))+1-($O$12:$O$15*($G$12:$G$15>G12)))+(1-($O$12:$O$15*($G$12:$G$15>G12)))*1E+300))),0) -> 0 | R12: =IF(C12=0,0,IF(L12=1,1,IF(AND(O12=1,P12<=Q12),1,0))) -> 1 | S12: =IF(R12=1,1+SUMPRODUCT($R$12:$R$15*(($G$12:$G$15<G12)+($G$12:$G$15=G12)*($A$12:$A$15<A12))),0) -> 1 | T12: =IF(S12<=1,0,SUMPRODUCT(($S$12:$S$15=S12-1)*$G$12:$G$15)) -> 0 | U12: =IF(S12<=1,0,SUMPRODUCT(($S$12:$S$15=S12-1)*$H$12:$H$15)) -> 0 | V12: =IF(S12=0,"",(G12-T12)/10^in_out_dp) -> 0 | W12: =IF(S12=0,"",(H12-U12)/10^in_cost_dp) -> 0 | X12: =IF(S12=0,"",IF(G12=T12,0,W12/V12)) -> 0 | Y12: =IF(AND(C12=1,G12>0),K12/J12,"n/a") -> n/a | Z12: 1 | AA12: =IF(AND(C12=1,Z12=1),1+SUMPRODUCT($C$12:$C$15*$Z$12:$Z$15*(($G$12:$G$15<G12)+($G$12:$G$15=G12)*($H$12:$H$15<H12)+($G$12:$G$15=G12)*($H$12:$H$15=H12)*($A$12:$A$15<A12))),0) -> 1
A13: 2 | B13: B | C13: =IF(SUMPRODUCT(D13:E13,1-$D$5:$E$5)=0,1,0) -> 0 | D13: 0 | E13: 1 | F13: =IF(C13=1,1+SUMPRODUCT(D13:E13,$D$9:$E$9),"") | G13: =SUMPRODUCT(D13:E13,$D$6:$E$6) -> 0 | H13: =SUMPRODUCT(D13:E13,$D$7:$E$7) -> 0 | I13: =SUMPRODUCT(D13:E13,$D$8:$E$8) -> 0 | J13: =G13/10^in_out_dp -> 0 | K13: =H13/10^in_cost_dp -> 0 | L13: =IF(SUM(D13:E13)=0,1,0) -> 0 | M13: =SUMPRODUCT($C$12:$C$15*(($G$12:$G$15=G13)*($H$12:$H$15<H13)+($G$12:$G$15>G13)*($H$12:$H$15<=H13))) -> 0 | N13: =IF(C13=0,0,IF(OR(L13=1,M13=0),1,0)) -> 0 | O13: =IF(AND(N13=1,L13=0,G13>0),1,0) -> 0 | P13: =IF(O13=1,MAX(H13/G13,SUMPRODUCT(MAX(((H13-$H$12:$H$15)*($O$12:$O$15*($G$12:$G$15<G13)))/((G13-$G$12:$G$15)*($O$12:$O$15*($G$12:$G$15<G13))+1-($O$12:$O$15*($G$12:$G$15<G13)))-(1-($O$12:$O$15*($G$12:$G$15<G13)))*1E+300))),0) -> 0 | Q13: =IF(O13=1,SUMPRODUCT(MIN(((($H$12:$H$15-H13)*($O$12:$O$15*($G$12:$G$15>G13)))/(($G$12:$G$15-G13)*($O$12:$O$15*($G$12:$G$15>G13))+1-($O$12:$O$15*($G$12:$G$15>G13)))+(1-($O$12:$O$15*($G$12:$G$15>G13)))*1E+300))),0) -> 0 | R13: =IF(C13=0,0,IF(L13=1,1,IF(AND(O13=1,P13<=Q13),1,0))) -> 0 | S13: =IF(R13=1,1+SUMPRODUCT($R$12:$R$15*(($G$12:$G$15<G13)+($G$12:$G$15=G13)*($A$12:$A$15<A13))),0) -> 0 | T13: =IF(S13<=1,0,SUMPRODUCT(($S$12:$S$15=S13-1)*$G$12:$G$15)) -> 0 | U13: =IF(S13<=1,0,SUMPRODUCT(($S$12:$S$15=S13-1)*$H$12:$H$15)) -> 0 | V13: =IF(S13=0,"",(G13-T13)/10^in_out_dp) | W13: =IF(S13=0,"",(H13-U13)/10^in_cost_dp) | X13: =IF(S13=0,"",IF(G13=T13,0,W13/V13)) | Y13: =IF(AND(C13=1,G13>0),K13/J13,"n/a") -> n/a | Z13: 0 | AA13: =IF(AND(C13=1,Z13=1),1+SUMPRODUCT($C$12:$C$15*$Z$12:$Z$15*(($G$12:$G$15<G13)+($G$12:$G$15=G13)*($H$12:$H$15<H13)+($G$12:$G$15=G13)*($H$12:$H$15=H13)*($A$12:$A$15<A13))),0) -> 0
A14: 3 | B14: A | C14: =IF(SUMPRODUCT(D14:E14,1-$D$5:$E$5)=0,1,0) -> 1 | D14: 1 | E14: 0 | F14: =IF(C14=1,1+SUMPRODUCT(D14:E14,$D$9:$E$9),"") -> 2 | G14: =SUMPRODUCT(D14:E14,$D$6:$E$6) -> 6208 | H14: =SUMPRODUCT(D14:E14,$D$7:$E$7) -> 1871172 | I14: =SUMPRODUCT(D14:E14,$D$8:$E$8) -> 400000 | J14: =G14/10^in_out_dp -> 6.208 | K14: =H14/10^in_cost_dp -> 18711.72 | L14: =IF(SUM(D14:E14)=0,1,0) -> 0 | M14: =SUMPRODUCT($C$12:$C$15*(($G$12:$G$15=G14)*($H$12:$H$15<H14)+($G$12:$G$15>G14)*($H$12:$H$15<=H14))) -> 0 | N14: =IF(C14=0,0,IF(OR(L14=1,M14=0),1,0)) -> 1 | O14: =IF(AND(N14=1,L14=0,G14>0),1,0) -> 1 | P14: =IF(O14=1,MAX(H14/G14,SUMPRODUCT(MAX(((H14-$H$12:$H$15)*($O$12:$O$15*($G$12:$G$15<G14)))/((G14-$G$12:$G$15)*($O$12:$O$15*($G$12:$G$15<G14))+1-($O$12:$O$15*($G$12:$G$15<G14)))-(1-($O$12:$O$15*($G$12:$G$15<G14)))*1E+300))),0) -> 301.41302 | Q14: =IF(O14=1,SUMPRODUCT(MIN(((($H$12:$H$15-H14)*($O$12:$O$15*($G$12:$G$15>G14)))/(($G$12:$G$15-G14)*($O$12:$O$15*($G$12:$G$15>G14))+1-($O$12:$O$15*($G$12:$G$15>G14)))+(1-($O$12:$O$15*($G$12:$G$15>G14)))*1E+300))),0) -> 1e+300 | R14: =IF(C14=0,0,IF(L14=1,1,IF(AND(O14=1,P14<=Q14),1,0))) -> 1 | S14: =IF(R14=1,1+SUMPRODUCT($R$12:$R$15*(($G$12:$G$15<G14)+($G$12:$G$15=G14)*($A$12:$A$15<A14))),0) -> 2 | T14: =IF(S14<=1,0,SUMPRODUCT(($S$12:$S$15=S14-1)*$G$12:$G$15)) -> 0 | U14: =IF(S14<=1,0,SUMPRODUCT(($S$12:$S$15=S14-1)*$H$12:$H$15)) -> 0 | V14: =IF(S14=0,"",(G14-T14)/10^in_out_dp) -> 6.208 | W14: =IF(S14=0,"",(H14-U14)/10^in_cost_dp) -> 18711.72 | X14: =IF(S14=0,"",IF(G14=T14,0,W14/V14)) -> 3014.1302 | Y14: =IF(AND(C14=1,G14>0),K14/J14,"n/a") -> 3014.1302 | Z14: 1 | AA14: =IF(AND(C14=1,Z14=1),1+SUMPRODUCT($C$12:$C$15*$Z$12:$Z$15*(($G$12:$G$15<G14)+($G$12:$G$15=G14)*($H$12:$H$15<H14)+($G$12:$G$15=G14)*($H$12:$H$15=H14)*($A$12:$A$15<A14))),0) -> 2
A15: 4 | B15: A + B | C15: =IF(SUMPRODUCT(D15:E15,1-$D$5:$E$5)=0,1,0) -> 0 | D15: 1 | E15: 1 | F15: =IF(C15=1,1+SUMPRODUCT(D15:E15,$D$9:$E$9),"") | G15: =SUMPRODUCT(D15:E15,$D$6:$E$6) -> 6208 | H15: =SUMPRODUCT(D15:E15,$D$7:$E$7) -> 1871172 | I15: =SUMPRODUCT(D15:E15,$D$8:$E$8) -> 400000 | J15: =G15/10^in_out_dp -> 6.208 | K15: =H15/10^in_cost_dp -> 18711.72 | L15: =IF(SUM(D15:E15)=0,1,0) -> 0 | M15: =SUMPRODUCT($C$12:$C$15*(($G$12:$G$15=G15)*($H$12:$H$15<H15)+($G$12:$G$15>G15)*($H$12:$H$15<=H15))) -> 0 | N15: =IF(C15=0,0,IF(OR(L15=1,M15=0),1,0)) -> 0 | O15: =IF(AND(N15=1,L15=0,G15>0),1,0) -> 0 | P15: =IF(O15=1,MAX(H15/G15,SUMPRODUCT(MAX(((H15-$H$12:$H$15)*($O$12:$O$15*($G$12:$G$15<G15)))/((G15-$G$12:$G$15)*($O$12:$O$15*($G$12:$G$15<G15))+1-($O$12:$O$15*($G$12:$G$15<G15)))-(1-($O$12:$O$15*($G$12:$G$15<G15)))*1E+300))),0) -> 0 | Q15: =IF(O15=1,SUMPRODUCT(MIN(((($H$12:$H$15-H15)*($O$12:$O$15*($G$12:$G$15>G15)))/(($G$12:$G$15-G15)*($O$12:$O$15*($G$12:$G$15>G15))+1-($O$12:$O$15*($G$12:$G$15>G15)))+(1-($O$12:$O$15*($G$12:$G$15>G15)))*1E+300))),0) -> 0 | R15: =IF(C15=0,0,IF(L15=1,1,IF(AND(O15=1,P15<=Q15),1,0))) -> 0 | S15: =IF(R15=1,1+SUMPRODUCT($R$12:$R$15*(($G$12:$G$15<G15)+($G$12:$G$15=G15)*($A$12:$A$15<A15))),0) -> 0 | T15: =IF(S15<=1,0,SUMPRODUCT(($S$12:$S$15=S15-1)*$G$12:$G$15)) -> 0 | U15: =IF(S15<=1,0,SUMPRODUCT(($S$12:$S$15=S15-1)*$H$12:$H$15)) -> 0 | V15: =IF(S15=0,"",(G15-T15)/10^in_out_dp) | W15: =IF(S15=0,"",(H15-U15)/10^in_cost_dp) | X15: =IF(S15=0,"",IF(G15=T15,0,W15/V15)) | Y15: =IF(AND(C15=1,G15>0),K15/J15,"n/a") -> n/a | Z15: 1 | AA15: =IF(AND(C15=1,Z15=1),1+SUMPRODUCT($C$12:$C$15*$Z$12:$Z$15*(($G$12:$G$15<G15)+($G$12:$G$15=G15)*($H$12:$H$15<H15)+($G$12:$G$15=G15)*($H$12:$H$15=H15)*($A$12:$A$15<A15))),0) -> 0

Sheet Watershed summary
A1: Watershed summary: best buys, final array and the tentatively selected plan
A2: Tables read the watershed plans sheet. Choose the TSP from the final array.
A4: Best buys
A5: Step | B5: Plan number | C5: Plan | D5: Lift (AAHU) | E5: Average annual cost | F5: Construction cost | G5: Unit cost | H5: Incremental cost per unit
A6: 1 | B6: =IFERROR(INDEX('Watershed plans'!$F$12:$F$15,MATCH(1,'Watershed plans'!$S$12:$S$15,0)),"") -> 1 | C6: =IFERROR(INDEX('Watershed plans'!$B$12:$B$15,MATCH(1,'Watershed plans'!$S$12:$S$15,0)),"") -> No Action | D6: =IFERROR(INDEX('Watershed plans'!$J$12:$J$15,MATCH(1,'Watershed plans'!$S$12:$S$15,0)),"") -> 0 | E6: =IFERROR(INDEX('Watershed plans'!$K$12:$K$15,MATCH(1,'Watershed plans'!$S$12:$S$15,0)),"") -> 0 | F6: =IFERROR(INDEX('Watershed plans'!$I$12:$I$15,MATCH(1,'Watershed plans'!$S$12:$S$15,0)),"") -> 0 | G6: =IFERROR(INDEX('Watershed plans'!$Y$12:$Y$15,MATCH(1,'Watershed plans'!$S$12:$S$15,0)),"") -> n/a | H6: =IFERROR(INDEX('Watershed plans'!$X$12:$X$15,MATCH(1,'Watershed plans'!$S$12:$S$15,0)),"") -> 0
A7: 2 | B7: =IFERROR(INDEX('Watershed plans'!$F$12:$F$15,MATCH(2,'Watershed plans'!$S$12:$S$15,0)),"") -> 2 | C7: =IFERROR(INDEX('Watershed plans'!$B$12:$B$15,MATCH(2,'Watershed plans'!$S$12:$S$15,0)),"") -> A | D7: =IFERROR(INDEX('Watershed plans'!$J$12:$J$15,MATCH(2,'Watershed plans'!$S$12:$S$15,0)),"") -> 6.208 | E7: =IFERROR(INDEX('Watershed plans'!$K$12:$K$15,MATCH(2,'Watershed plans'!$S$12:$S$15,0)),"") -> 18711.72 | F7: =IFERROR(INDEX('Watershed plans'!$I$12:$I$15,MATCH(2,'Watershed plans'!$S$12:$S$15,0)),"") -> 400000 | G7: =IFERROR(INDEX('Watershed plans'!$Y$12:$Y$15,MATCH(2,'Watershed plans'!$S$12:$S$15,0)),"") -> 3014.1302 | H7: =IFERROR(INDEX('Watershed plans'!$X$12:$X$15,MATCH(2,'Watershed plans'!$S$12:$S$15,0)),"") -> 3014.1302
A8: 3 | B8: =IFERROR(INDEX('Watershed plans'!$F$12:$F$15,MATCH(3,'Watershed plans'!$S$12:$S$15,0)),"") | C8: =IFERROR(INDEX('Watershed plans'!$B$12:$B$15,MATCH(3,'Watershed plans'!$S$12:$S$15,0)),"") | D8: =IFERROR(INDEX('Watershed plans'!$J$12:$J$15,MATCH(3,'Watershed plans'!$S$12:$S$15,0)),"") | E8: =IFERROR(INDEX('Watershed plans'!$K$12:$K$15,MATCH(3,'Watershed plans'!$S$12:$S$15,0)),"") | F8: =IFERROR(INDEX('Watershed plans'!$I$12:$I$15,MATCH(3,'Watershed plans'!$S$12:$S$15,0)),"") | G8: =IFERROR(INDEX('Watershed plans'!$Y$12:$Y$15,MATCH(3,'Watershed plans'!$S$12:$S$15,0)),"") | H8: =IFERROR(INDEX('Watershed plans'!$X$12:$X$15,MATCH(3,'Watershed plans'!$S$12:$S$15,0)),"")
A9: 4 | B9: =IFERROR(INDEX('Watershed plans'!$F$12:$F$15,MATCH(4,'Watershed plans'!$S$12:$S$15,0)),"") | C9: =IFERROR(INDEX('Watershed plans'!$B$12:$B$15,MATCH(4,'Watershed plans'!$S$12:$S$15,0)),"") | D9: =IFERROR(INDEX('Watershed plans'!$J$12:$J$15,MATCH(4,'Watershed plans'!$S$12:$S$15,0)),"") | E9: =IFERROR(INDEX('Watershed plans'!$K$12:$K$15,MATCH(4,'Watershed plans'!$S$12:$S$15,0)),"") | F9: =IFERROR(INDEX('Watershed plans'!$I$12:$I$15,MATCH(4,'Watershed plans'!$S$12:$S$15,0)),"") | G9: =IFERROR(INDEX('Watershed plans'!$Y$12:$Y$15,MATCH(4,'Watershed plans'!$S$12:$S$15,0)),"") | H9: =IFERROR(INDEX('Watershed plans'!$X$12:$X$15,MATCH(4,'Watershed plans'!$S$12:$S$15,0)),"")
A10: 5 | B10: =IFERROR(INDEX('Watershed plans'!$F$12:$F$15,MATCH(5,'Watershed plans'!$S$12:$S$15,0)),"") | C10: =IFERROR(INDEX('Watershed plans'!$B$12:$B$15,MATCH(5,'Watershed plans'!$S$12:$S$15,0)),"") | D10: =IFERROR(INDEX('Watershed plans'!$J$12:$J$15,MATCH(5,'Watershed plans'!$S$12:$S$15,0)),"") | E10: =IFERROR(INDEX('Watershed plans'!$K$12:$K$15,MATCH(5,'Watershed plans'!$S$12:$S$15,0)),"") | F10: =IFERROR(INDEX('Watershed plans'!$I$12:$I$15,MATCH(5,'Watershed plans'!$S$12:$S$15,0)),"") | G10: =IFERROR(INDEX('Watershed plans'!$Y$12:$Y$15,MATCH(5,'Watershed plans'!$S$12:$S$15,0)),"") | H10: =IFERROR(INDEX('Watershed plans'!$X$12:$X$15,MATCH(5,'Watershed plans'!$S$12:$S$15,0)),"")
A11: 6 | B11: =IFERROR(INDEX('Watershed plans'!$F$12:$F$15,MATCH(6,'Watershed plans'!$S$12:$S$15,0)),"") | C11: =IFERROR(INDEX('Watershed plans'!$B$12:$B$15,MATCH(6,'Watershed plans'!$S$12:$S$15,0)),"") | D11: =IFERROR(INDEX('Watershed plans'!$J$12:$J$15,MATCH(6,'Watershed plans'!$S$12:$S$15,0)),"") | E11: =IFERROR(INDEX('Watershed plans'!$K$12:$K$15,MATCH(6,'Watershed plans'!$S$12:$S$15,0)),"") | F11: =IFERROR(INDEX('Watershed plans'!$I$12:$I$15,MATCH(6,'Watershed plans'!$S$12:$S$15,0)),"") | G11: =IFERROR(INDEX('Watershed plans'!$Y$12:$Y$15,MATCH(6,'Watershed plans'!$S$12:$S$15,0)),"") | H11: =IFERROR(INDEX('Watershed plans'!$X$12:$X$15,MATCH(6,'Watershed plans'!$S$12:$S$15,0)),"")
A12: 7 | B12: =IFERROR(INDEX('Watershed plans'!$F$12:$F$15,MATCH(7,'Watershed plans'!$S$12:$S$15,0)),"") | C12: =IFERROR(INDEX('Watershed plans'!$B$12:$B$15,MATCH(7,'Watershed plans'!$S$12:$S$15,0)),"") | D12: =IFERROR(INDEX('Watershed plans'!$J$12:$J$15,MATCH(7,'Watershed plans'!$S$12:$S$15,0)),"") | E12: =IFERROR(INDEX('Watershed plans'!$K$12:$K$15,MATCH(7,'Watershed plans'!$S$12:$S$15,0)),"") | F12: =IFERROR(INDEX('Watershed plans'!$I$12:$I$15,MATCH(7,'Watershed plans'!$S$12:$S$15,0)),"") | G12: =IFERROR(INDEX('Watershed plans'!$Y$12:$Y$15,MATCH(7,'Watershed plans'!$S$12:$S$15,0)),"") | H12: =IFERROR(INDEX('Watershed plans'!$X$12:$X$15,MATCH(7,'Watershed plans'!$S$12:$S$15,0)),"")
A13: 8 | B13: =IFERROR(INDEX('Watershed plans'!$F$12:$F$15,MATCH(8,'Watershed plans'!$S$12:$S$15,0)),"") | C13: =IFERROR(INDEX('Watershed plans'!$B$12:$B$15,MATCH(8,'Watershed plans'!$S$12:$S$15,0)),"") | D13: =IFERROR(INDEX('Watershed plans'!$J$12:$J$15,MATCH(8,'Watershed plans'!$S$12:$S$15,0)),"") | E13: =IFERROR(INDEX('Watershed plans'!$K$12:$K$15,MATCH(8,'Watershed plans'!$S$12:$S$15,0)),"") | F13: =IFERROR(INDEX('Watershed plans'!$I$12:$I$15,MATCH(8,'Watershed plans'!$S$12:$S$15,0)),"") | G13: =IFERROR(INDEX('Watershed plans'!$Y$12:$Y$15,MATCH(8,'Watershed plans'!$S$12:$S$15,0)),"") | H13: =IFERROR(INDEX('Watershed plans'!$X$12:$X$15,MATCH(8,'Watershed plans'!$S$12:$S$15,0)),"")
A14: 9 | B14: =IFERROR(INDEX('Watershed plans'!$F$12:$F$15,MATCH(9,'Watershed plans'!$S$12:$S$15,0)),"") | C14: =IFERROR(INDEX('Watershed plans'!$B$12:$B$15,MATCH(9,'Watershed plans'!$S$12:$S$15,0)),"") | D14: =IFERROR(INDEX('Watershed plans'!$J$12:$J$15,MATCH(9,'Watershed plans'!$S$12:$S$15,0)),"") | E14: =IFERROR(INDEX('Watershed plans'!$K$12:$K$15,MATCH(9,'Watershed plans'!$S$12:$S$15,0)),"") | F14: =IFERROR(INDEX('Watershed plans'!$I$12:$I$15,MATCH(9,'Watershed plans'!$S$12:$S$15,0)),"") | G14: =IFERROR(INDEX('Watershed plans'!$Y$12:$Y$15,MATCH(9,'Watershed plans'!$S$12:$S$15,0)),"") | H14: =IFERROR(INDEX('Watershed plans'!$X$12:$X$15,MATCH(9,'Watershed plans'!$S$12:$S$15,0)),"")
A15: 10 | B15: =IFERROR(INDEX('Watershed plans'!$F$12:$F$15,MATCH(10,'Watershed plans'!$S$12:$S$15,0)),"") | C15: =IFERROR(INDEX('Watershed plans'!$B$12:$B$15,MATCH(10,'Watershed plans'!$S$12:$S$15,0)),"") | D15: =IFERROR(INDEX('Watershed plans'!$J$12:$J$15,MATCH(10,'Watershed plans'!$S$12:$S$15,0)),"") | E15: =IFERROR(INDEX('Watershed plans'!$K$12:$K$15,MATCH(10,'Watershed plans'!$S$12:$S$15,0)),"") | F15: =IFERROR(INDEX('Watershed plans'!$I$12:$I$15,MATCH(10,'Watershed plans'!$S$12:$S$15,0)),"") | G15: =IFERROR(INDEX('Watershed plans'!$Y$12:$Y$15,MATCH(10,'Watershed plans'!$S$12:$S$15,0)),"") | H15: =IFERROR(INDEX('Watershed plans'!$X$12:$X$15,MATCH(10,'Watershed plans'!$S$12:$S$15,0)),"")
A16: 11 | B16: =IFERROR(INDEX('Watershed plans'!$F$12:$F$15,MATCH(11,'Watershed plans'!$S$12:$S$15,0)),"") | C16: =IFERROR(INDEX('Watershed plans'!$B$12:$B$15,MATCH(11,'Watershed plans'!$S$12:$S$15,0)),"") | D16: =IFERROR(INDEX('Watershed plans'!$J$12:$J$15,MATCH(11,'Watershed plans'!$S$12:$S$15,0)),"") | E16: =IFERROR(INDEX('Watershed plans'!$K$12:$K$15,MATCH(11,'Watershed plans'!$S$12:$S$15,0)),"") | F16: =IFERROR(INDEX('Watershed plans'!$I$12:$I$15,MATCH(11,'Watershed plans'!$S$12:$S$15,0)),"") | G16: =IFERROR(INDEX('Watershed plans'!$Y$12:$Y$15,MATCH(11,'Watershed plans'!$S$12:$S$15,0)),"") | H16: =IFERROR(INDEX('Watershed plans'!$X$12:$X$15,MATCH(11,'Watershed plans'!$S$12:$S$15,0)),"")
A17: 12 | B17: =IFERROR(INDEX('Watershed plans'!$F$12:$F$15,MATCH(12,'Watershed plans'!$S$12:$S$15,0)),"") | C17: =IFERROR(INDEX('Watershed plans'!$B$12:$B$15,MATCH(12,'Watershed plans'!$S$12:$S$15,0)),"") | D17: =IFERROR(INDEX('Watershed plans'!$J$12:$J$15,MATCH(12,'Watershed plans'!$S$12:$S$15,0)),"") | E17: =IFERROR(INDEX('Watershed plans'!$K$12:$K$15,MATCH(12,'Watershed plans'!$S$12:$S$15,0)),"") | F17: =IFERROR(INDEX('Watershed plans'!$I$12:$I$15,MATCH(12,'Watershed plans'!$S$12:$S$15,0)),"") | G17: =IFERROR(INDEX('Watershed plans'!$Y$12:$Y$15,MATCH(12,'Watershed plans'!$S$12:$S$15,0)),"") | H17: =IFERROR(INDEX('Watershed plans'!$X$12:$X$15,MATCH(12,'Watershed plans'!$S$12:$S$15,0)),"")
A18: 13 | B18: =IFERROR(INDEX('Watershed plans'!$F$12:$F$15,MATCH(13,'Watershed plans'!$S$12:$S$15,0)),"") | C18: =IFERROR(INDEX('Watershed plans'!$B$12:$B$15,MATCH(13,'Watershed plans'!$S$12:$S$15,0)),"") | D18: =IFERROR(INDEX('Watershed plans'!$J$12:$J$15,MATCH(13,'Watershed plans'!$S$12:$S$15,0)),"") | E18: =IFERROR(INDEX('Watershed plans'!$K$12:$K$15,MATCH(13,'Watershed plans'!$S$12:$S$15,0)),"") | F18: =IFERROR(INDEX('Watershed plans'!$I$12:$I$15,MATCH(13,'Watershed plans'!$S$12:$S$15,0)),"") | G18: =IFERROR(INDEX('Watershed plans'!$Y$12:$Y$15,MATCH(13,'Watershed plans'!$S$12:$S$15,0)),"") | H18: =IFERROR(INDEX('Watershed plans'!$X$12:$X$15,MATCH(13,'Watershed plans'!$S$12:$S$15,0)),"")
A19: 14 | B19: =IFERROR(INDEX('Watershed plans'!$F$12:$F$15,MATCH(14,'Watershed plans'!$S$12:$S$15,0)),"") | C19: =IFERROR(INDEX('Watershed plans'!$B$12:$B$15,MATCH(14,'Watershed plans'!$S$12:$S$15,0)),"") | D19: =IFERROR(INDEX('Watershed plans'!$J$12:$J$15,MATCH(14,'Watershed plans'!$S$12:$S$15,0)),"") | E19: =IFERROR(INDEX('Watershed plans'!$K$12:$K$15,MATCH(14,'Watershed plans'!$S$12:$S$15,0)),"") | F19: =IFERROR(INDEX('Watershed plans'!$I$12:$I$15,MATCH(14,'Watershed plans'!$S$12:$S$15,0)),"") | G19: =IFERROR(INDEX('Watershed plans'!$Y$12:$Y$15,MATCH(14,'Watershed plans'!$S$12:$S$15,0)),"") | H19: =IFERROR(INDEX('Watershed plans'!$X$12:$X$15,MATCH(14,'Watershed plans'!$S$12:$S$15,0)),"")
A20: 15 | B20: =IFERROR(INDEX('Watershed plans'!$F$12:$F$15,MATCH(15,'Watershed plans'!$S$12:$S$15,0)),"") | C20: =IFERROR(INDEX('Watershed plans'!$B$12:$B$15,MATCH(15,'Watershed plans'!$S$12:$S$15,0)),"") | D20: =IFERROR(INDEX('Watershed plans'!$J$12:$J$15,MATCH(15,'Watershed plans'!$S$12:$S$15,0)),"") | E20: =IFERROR(INDEX('Watershed plans'!$K$12:$K$15,MATCH(15,'Watershed plans'!$S$12:$S$15,0)),"") | F20: =IFERROR(INDEX('Watershed plans'!$I$12:$I$15,MATCH(15,'Watershed plans'!$S$12:$S$15,0)),"") | G20: =IFERROR(INDEX('Watershed plans'!$Y$12:$Y$15,MATCH(15,'Watershed plans'!$S$12:$S$15,0)),"") | H20: =IFERROR(INDEX('Watershed plans'!$X$12:$X$15,MATCH(15,'Watershed plans'!$S$12:$S$15,0)),"")
A21: 16 | B21: =IFERROR(INDEX('Watershed plans'!$F$12:$F$15,MATCH(16,'Watershed plans'!$S$12:$S$15,0)),"") | C21: =IFERROR(INDEX('Watershed plans'!$B$12:$B$15,MATCH(16,'Watershed plans'!$S$12:$S$15,0)),"") | D21: =IFERROR(INDEX('Watershed plans'!$J$12:$J$15,MATCH(16,'Watershed plans'!$S$12:$S$15,0)),"") | E21: =IFERROR(INDEX('Watershed plans'!$K$12:$K$15,MATCH(16,'Watershed plans'!$S$12:$S$15,0)),"") | F21: =IFERROR(INDEX('Watershed plans'!$I$12:$I$15,MATCH(16,'Watershed plans'!$S$12:$S$15,0)),"") | G21: =IFERROR(INDEX('Watershed plans'!$Y$12:$Y$15,MATCH(16,'Watershed plans'!$S$12:$S$15,0)),"") | H21: =IFERROR(INDEX('Watershed plans'!$X$12:$X$15,MATCH(16,'Watershed plans'!$S$12:$S$15,0)),"")
A22: 17 | B22: =IFERROR(INDEX('Watershed plans'!$F$12:$F$15,MATCH(17,'Watershed plans'!$S$12:$S$15,0)),"") | C22: =IFERROR(INDEX('Watershed plans'!$B$12:$B$15,MATCH(17,'Watershed plans'!$S$12:$S$15,0)),"") | D22: =IFERROR(INDEX('Watershed plans'!$J$12:$J$15,MATCH(17,'Watershed plans'!$S$12:$S$15,0)),"") | E22: =IFERROR(INDEX('Watershed plans'!$K$12:$K$15,MATCH(17,'Watershed plans'!$S$12:$S$15,0)),"") | F22: =IFERROR(INDEX('Watershed plans'!$I$12:$I$15,MATCH(17,'Watershed plans'!$S$12:$S$15,0)),"") | G22: =IFERROR(INDEX('Watershed plans'!$Y$12:$Y$15,MATCH(17,'Watershed plans'!$S$12:$S$15,0)),"") | H22: =IFERROR(INDEX('Watershed plans'!$X$12:$X$15,MATCH(17,'Watershed plans'!$S$12:$S$15,0)),"")
A23: 18 | B23: =IFERROR(INDEX('Watershed plans'!$F$12:$F$15,MATCH(18,'Watershed plans'!$S$12:$S$15,0)),"") | C23: =IFERROR(INDEX('Watershed plans'!$B$12:$B$15,MATCH(18,'Watershed plans'!$S$12:$S$15,0)),"") | D23: =IFERROR(INDEX('Watershed plans'!$J$12:$J$15,MATCH(18,'Watershed plans'!$S$12:$S$15,0)),"") | E23: =IFERROR(INDEX('Watershed plans'!$K$12:$K$15,MATCH(18,'Watershed plans'!$S$12:$S$15,0)),"") | F23: =IFERROR(INDEX('Watershed plans'!$I$12:$I$15,MATCH(18,'Watershed plans'!$S$12:$S$15,0)),"") | G23: =IFERROR(INDEX('Watershed plans'!$Y$12:$Y$15,MATCH(18,'Watershed plans'!$S$12:$S$15,0)),"") | H23: =IFERROR(INDEX('Watershed plans'!$X$12:$X$15,MATCH(18,'Watershed plans'!$S$12:$S$15,0)),"")
A24: 19 | B24: =IFERROR(INDEX('Watershed plans'!$F$12:$F$15,MATCH(19,'Watershed plans'!$S$12:$S$15,0)),"") | C24: =IFERROR(INDEX('Watershed plans'!$B$12:$B$15,MATCH(19,'Watershed plans'!$S$12:$S$15,0)),"") | D24: =IFERROR(INDEX('Watershed plans'!$J$12:$J$15,MATCH(19,'Watershed plans'!$S$12:$S$15,0)),"") | E24: =IFERROR(INDEX('Watershed plans'!$K$12:$K$15,MATCH(19,'Watershed plans'!$S$12:$S$15,0)),"") | F24: =IFERROR(INDEX('Watershed plans'!$I$12:$I$15,MATCH(19,'Watershed plans'!$S$12:$S$15,0)),"") | G24: =IFERROR(INDEX('Watershed plans'!$Y$12:$Y$15,MATCH(19,'Watershed plans'!$S$12:$S$15,0)),"") | H24: =IFERROR(INDEX('Watershed plans'!$X$12:$X$15,MATCH(19,'Watershed plans'!$S$12:$S$15,0)),"")
A25: 20 | B25: =IFERROR(INDEX('Watershed plans'!$F$12:$F$15,MATCH(20,'Watershed plans'!$S$12:$S$15,0)),"") | C25: =IFERROR(INDEX('Watershed plans'!$B$12:$B$15,MATCH(20,'Watershed plans'!$S$12:$S$15,0)),"") | D25: =IFERROR(INDEX('Watershed plans'!$J$12:$J$15,MATCH(20,'Watershed plans'!$S$12:$S$15,0)),"") | E25: =IFERROR(INDEX('Watershed plans'!$K$12:$K$15,MATCH(20,'Watershed plans'!$S$12:$S$15,0)),"") | F25: =IFERROR(INDEX('Watershed plans'!$I$12:$I$15,MATCH(20,'Watershed plans'!$S$12:$S$15,0)),"") | G25: =IFERROR(INDEX('Watershed plans'!$Y$12:$Y$15,MATCH(20,'Watershed plans'!$S$12:$S$15,0)),"") | H25: =IFERROR(INDEX('Watershed plans'!$X$12:$X$15,MATCH(20,'Watershed plans'!$S$12:$S$15,0)),"")
A26: 21 | B26: =IFERROR(INDEX('Watershed plans'!$F$12:$F$15,MATCH(21,'Watershed plans'!$S$12:$S$15,0)),"") | C26: =IFERROR(INDEX('Watershed plans'!$B$12:$B$15,MATCH(21,'Watershed plans'!$S$12:$S$15,0)),"") | D26: =IFERROR(INDEX('Watershed plans'!$J$12:$J$15,MATCH(21,'Watershed plans'!$S$12:$S$15,0)),"") | E26: =IFERROR(INDEX('Watershed plans'!$K$12:$K$15,MATCH(21,'Watershed plans'!$S$12:$S$15,0)),"") | F26: =IFERROR(INDEX('Watershed plans'!$I$12:$I$15,MATCH(21,'Watershed plans'!$S$12:$S$15,0)),"") | G26: =IFERROR(INDEX('Watershed plans'!$Y$12:$Y$15,MATCH(21,'Watershed plans'!$S$12:$S$15,0)),"") | H26: =IFERROR(INDEX('Watershed plans'!$X$12:$X$15,MATCH(21,'Watershed plans'!$S$12:$S$15,0)),"")
A27: 22 | B27: =IFERROR(INDEX('Watershed plans'!$F$12:$F$15,MATCH(22,'Watershed plans'!$S$12:$S$15,0)),"") | C27: =IFERROR(INDEX('Watershed plans'!$B$12:$B$15,MATCH(22,'Watershed plans'!$S$12:$S$15,0)),"") | D27: =IFERROR(INDEX('Watershed plans'!$J$12:$J$15,MATCH(22,'Watershed plans'!$S$12:$S$15,0)),"") | E27: =IFERROR(INDEX('Watershed plans'!$K$12:$K$15,MATCH(22,'Watershed plans'!$S$12:$S$15,0)),"") | F27: =IFERROR(INDEX('Watershed plans'!$I$12:$I$15,MATCH(22,'Watershed plans'!$S$12:$S$15,0)),"") | G27: =IFERROR(INDEX('Watershed plans'!$Y$12:$Y$15,MATCH(22,'Watershed plans'!$S$12:$S$15,0)),"") | H27: =IFERROR(INDEX('Watershed plans'!$X$12:$X$15,MATCH(22,'Watershed plans'!$S$12:$S$15,0)),"")
A28: 23 | B28: =IFERROR(INDEX('Watershed plans'!$F$12:$F$15,MATCH(23,'Watershed plans'!$S$12:$S$15,0)),"") | C28: =IFERROR(INDEX('Watershed plans'!$B$12:$B$15,MATCH(23,'Watershed plans'!$S$12:$S$15,0)),"") | D28: =IFERROR(INDEX('Watershed plans'!$J$12:$J$15,MATCH(23,'Watershed plans'!$S$12:$S$15,0)),"") | E28: =IFERROR(INDEX('Watershed plans'!$K$12:$K$15,MATCH(23,'Watershed plans'!$S$12:$S$15,0)),"") | F28: =IFERROR(INDEX('Watershed plans'!$I$12:$I$15,MATCH(23,'Watershed plans'!$S$12:$S$15,0)),"") | G28: =IFERROR(INDEX('Watershed plans'!$Y$12:$Y$15,MATCH(23,'Watershed plans'!$S$12:$S$15,0)),"") | H28: =IFERROR(INDEX('Watershed plans'!$X$12:$X$15,MATCH(23,'Watershed plans'!$S$12:$S$15,0)),"")
A29: 24 | B29: =IFERROR(INDEX('Watershed plans'!$F$12:$F$15,MATCH(24,'Watershed plans'!$S$12:$S$15,0)),"") | C29: =IFERROR(INDEX('Watershed plans'!$B$12:$B$15,MATCH(24,'Watershed plans'!$S$12:$S$15,0)),"") | D29: =IFERROR(INDEX('Watershed plans'!$J$12:$J$15,MATCH(24,'Watershed plans'!$S$12:$S$15,0)),"") | E29: =IFERROR(INDEX('Watershed plans'!$K$12:$K$15,MATCH(24,'Watershed plans'!$S$12:$S$15,0)),"") | F29: =IFERROR(INDEX('Watershed plans'!$I$12:$I$15,MATCH(24,'Watershed plans'!$S$12:$S$15,0)),"") | G29: =IFERROR(INDEX('Watershed plans'!$Y$12:$Y$15,MATCH(24,'Watershed plans'!$S$12:$S$15,0)),"") | H29: =IFERROR(INDEX('Watershed plans'!$X$12:$X$15,MATCH(24,'Watershed plans'!$S$12:$S$15,0)),"")
A30: 25 | B30: =IFERROR(INDEX('Watershed plans'!$F$12:$F$15,MATCH(25,'Watershed plans'!$S$12:$S$15,0)),"") | C30: =IFERROR(INDEX('Watershed plans'!$B$12:$B$15,MATCH(25,'Watershed plans'!$S$12:$S$15,0)),"") | D30: =IFERROR(INDEX('Watershed plans'!$J$12:$J$15,MATCH(25,'Watershed plans'!$S$12:$S$15,0)),"") | E30: =IFERROR(INDEX('Watershed plans'!$K$12:$K$15,MATCH(25,'Watershed plans'!$S$12:$S$15,0)),"") | F30: =IFERROR(INDEX('Watershed plans'!$I$12:$I$15,MATCH(25,'Watershed plans'!$S$12:$S$15,0)),"") | G30: =IFERROR(INDEX('Watershed plans'!$Y$12:$Y$15,MATCH(25,'Watershed plans'!$S$12:$S$15,0)),"") | H30: =IFERROR(INDEX('Watershed plans'!$X$12:$X$15,MATCH(25,'Watershed plans'!$S$12:$S$15,0)),"")
A31: 26 | B31: =IFERROR(INDEX('Watershed plans'!$F$12:$F$15,MATCH(26,'Watershed plans'!$S$12:$S$15,0)),"") | C31: =IFERROR(INDEX('Watershed plans'!$B$12:$B$15,MATCH(26,'Watershed plans'!$S$12:$S$15,0)),"") | D31: =IFERROR(INDEX('Watershed plans'!$J$12:$J$15,MATCH(26,'Watershed plans'!$S$12:$S$15,0)),"") | E31: =IFERROR(INDEX('Watershed plans'!$K$12:$K$15,MATCH(26,'Watershed plans'!$S$12:$S$15,0)),"") | F31: =IFERROR(INDEX('Watershed plans'!$I$12:$I$15,MATCH(26,'Watershed plans'!$S$12:$S$15,0)),"") | G31: =IFERROR(INDEX('Watershed plans'!$Y$12:$Y$15,MATCH(26,'Watershed plans'!$S$12:$S$15,0)),"") | H31: =IFERROR(INDEX('Watershed plans'!$X$12:$X$15,MATCH(26,'Watershed plans'!$S$12:$S$15,0)),"")
A32: 27 | B32: =IFERROR(INDEX('Watershed plans'!$F$12:$F$15,MATCH(27,'Watershed plans'!$S$12:$S$15,0)),"") | C32: =IFERROR(INDEX('Watershed plans'!$B$12:$B$15,MATCH(27,'Watershed plans'!$S$12:$S$15,0)),"") | D32: =IFERROR(INDEX('Watershed plans'!$J$12:$J$15,MATCH(27,'Watershed plans'!$S$12:$S$15,0)),"") | E32: =IFERROR(INDEX('Watershed plans'!$K$12:$K$15,MATCH(27,'Watershed plans'!$S$12:$S$15,0)),"") | F32: =IFERROR(INDEX('Watershed plans'!$I$12:$I$15,MATCH(27,'Watershed plans'!$S$12:$S$15,0)),"") | G32: =IFERROR(INDEX('Watershed plans'!$Y$12:$Y$15,MATCH(27,'Watershed plans'!$S$12:$S$15,0)),"") | H32: =IFERROR(INDEX('Watershed plans'!$X$12:$X$15,MATCH(27,'Watershed plans'!$S$12:$S$15,0)),"")
A33: 28 | B33: =IFERROR(INDEX('Watershed plans'!$F$12:$F$15,MATCH(28,'Watershed plans'!$S$12:$S$15,0)),"") | C33: =IFERROR(INDEX('Watershed plans'!$B$12:$B$15,MATCH(28,'Watershed plans'!$S$12:$S$15,0)),"") | D33: =IFERROR(INDEX('Watershed plans'!$J$12:$J$15,MATCH(28,'Watershed plans'!$S$12:$S$15,0)),"") | E33: =IFERROR(INDEX('Watershed plans'!$K$12:$K$15,MATCH(28,'Watershed plans'!$S$12:$S$15,0)),"") | F33: =IFERROR(INDEX('Watershed plans'!$I$12:$I$15,MATCH(28,'Watershed plans'!$S$12:$S$15,0)),"") | G33: =IFERROR(INDEX('Watershed plans'!$Y$12:$Y$15,MATCH(28,'Watershed plans'!$S$12:$S$15,0)),"") | H33: =IFERROR(INDEX('Watershed plans'!$X$12:$X$15,MATCH(28,'Watershed plans'!$S$12:$S$15,0)),"")
A34: 29 | B34: =IFERROR(INDEX('Watershed plans'!$F$12:$F$15,MATCH(29,'Watershed plans'!$S$12:$S$15,0)),"") | C34: =IFERROR(INDEX('Watershed plans'!$B$12:$B$15,MATCH(29,'Watershed plans'!$S$12:$S$15,0)),"") | D34: =IFERROR(INDEX('Watershed plans'!$J$12:$J$15,MATCH(29,'Watershed plans'!$S$12:$S$15,0)),"") | E34: =IFERROR(INDEX('Watershed plans'!$K$12:$K$15,MATCH(29,'Watershed plans'!$S$12:$S$15,0)),"") | F34: =IFERROR(INDEX('Watershed plans'!$I$12:$I$15,MATCH(29,'Watershed plans'!$S$12:$S$15,0)),"") | G34: =IFERROR(INDEX('Watershed plans'!$Y$12:$Y$15,MATCH(29,'Watershed plans'!$S$12:$S$15,0)),"") | H34: =IFERROR(INDEX('Watershed plans'!$X$12:$X$15,MATCH(29,'Watershed plans'!$S$12:$S$15,0)),"")
A35: 30 | B35: =IFERROR(INDEX('Watershed plans'!$F$12:$F$15,MATCH(30,'Watershed plans'!$S$12:$S$15,0)),"") | C35: =IFERROR(INDEX('Watershed plans'!$B$12:$B$15,MATCH(30,'Watershed plans'!$S$12:$S$15,0)),"") | D35: =IFERROR(INDEX('Watershed plans'!$J$12:$J$15,MATCH(30,'Watershed plans'!$S$12:$S$15,0)),"") | E35: =IFERROR(INDEX('Watershed plans'!$K$12:$K$15,MATCH(30,'Watershed plans'!$S$12:$S$15,0)),"") | F35: =IFERROR(INDEX('Watershed plans'!$I$12:$I$15,MATCH(30,'Watershed plans'!$S$12:$S$15,0)),"") | G35: =IFERROR(INDEX('Watershed plans'!$Y$12:$Y$15,MATCH(30,'Watershed plans'!$S$12:$S$15,0)),"") | H35: =IFERROR(INDEX('Watershed plans'!$X$12:$X$15,MATCH(30,'Watershed plans'!$S$12:$S$15,0)),"")
A36: 31 | B36: =IFERROR(INDEX('Watershed plans'!$F$12:$F$15,MATCH(31,'Watershed plans'!$S$12:$S$15,0)),"") | C36: =IFERROR(INDEX('Watershed plans'!$B$12:$B$15,MATCH(31,'Watershed plans'!$S$12:$S$15,0)),"") | D36: =IFERROR(INDEX('Watershed plans'!$J$12:$J$15,MATCH(31,'Watershed plans'!$S$12:$S$15,0)),"") | E36: =IFERROR(INDEX('Watershed plans'!$K$12:$K$15,MATCH(31,'Watershed plans'!$S$12:$S$15,0)),"") | F36: =IFERROR(INDEX('Watershed plans'!$I$12:$I$15,MATCH(31,'Watershed plans'!$S$12:$S$15,0)),"") | G36: =IFERROR(INDEX('Watershed plans'!$Y$12:$Y$15,MATCH(31,'Watershed plans'!$S$12:$S$15,0)),"") | H36: =IFERROR(INDEX('Watershed plans'!$X$12:$X$15,MATCH(31,'Watershed plans'!$S$12:$S$15,0)),"")
A37: 32 | B37: =IFERROR(INDEX('Watershed plans'!$F$12:$F$15,MATCH(32,'Watershed plans'!$S$12:$S$15,0)),"") | C37: =IFERROR(INDEX('Watershed plans'!$B$12:$B$15,MATCH(32,'Watershed plans'!$S$12:$S$15,0)),"") | D37: =IFERROR(INDEX('Watershed plans'!$J$12:$J$15,MATCH(32,'Watershed plans'!$S$12:$S$15,0)),"") | E37: =IFERROR(INDEX('Watershed plans'!$K$12:$K$15,MATCH(32,'Watershed plans'!$S$12:$S$15,0)),"") | F37: =IFERROR(INDEX('Watershed plans'!$I$12:$I$15,MATCH(32,'Watershed plans'!$S$12:$S$15,0)),"") | G37: =IFERROR(INDEX('Watershed plans'!$Y$12:$Y$15,MATCH(32,'Watershed plans'!$S$12:$S$15,0)),"") | H37: =IFERROR(INDEX('Watershed plans'!$X$12:$X$15,MATCH(32,'Watershed plans'!$S$12:$S$15,0)),"")
A38: 33 | B38: =IFERROR(INDEX('Watershed plans'!$F$12:$F$15,MATCH(33,'Watershed plans'!$S$12:$S$15,0)),"") | C38: =IFERROR(INDEX('Watershed plans'!$B$12:$B$15,MATCH(33,'Watershed plans'!$S$12:$S$15,0)),"") | D38: =IFERROR(INDEX('Watershed plans'!$J$12:$J$15,MATCH(33,'Watershed plans'!$S$12:$S$15,0)),"") | E38: =IFERROR(INDEX('Watershed plans'!$K$12:$K$15,MATCH(33,'Watershed plans'!$S$12:$S$15,0)),"") | F38: =IFERROR(INDEX('Watershed plans'!$I$12:$I$15,MATCH(33,'Watershed plans'!$S$12:$S$15,0)),"") | G38: =IFERROR(INDEX('Watershed plans'!$Y$12:$Y$15,MATCH(33,'Watershed plans'!$S$12:$S$15,0)),"") | H38: =IFERROR(INDEX('Watershed plans'!$X$12:$X$15,MATCH(33,'Watershed plans'!$S$12:$S$15,0)),"")
A39: 34 | B39: =IFERROR(INDEX('Watershed plans'!$F$12:$F$15,MATCH(34,'Watershed plans'!$S$12:$S$15,0)),"") | C39: =IFERROR(INDEX('Watershed plans'!$B$12:$B$15,MATCH(34,'Watershed plans'!$S$12:$S$15,0)),"") | D39: =IFERROR(INDEX('Watershed plans'!$J$12:$J$15,MATCH(34,'Watershed plans'!$S$12:$S$15,0)),"") | E39: =IFERROR(INDEX('Watershed plans'!$K$12:$K$15,MATCH(34,'Watershed plans'!$S$12:$S$15,0)),"") | F39: =IFERROR(INDEX('Watershed plans'!$I$12:$I$15,MATCH(34,'Watershed plans'!$S$12:$S$15,0)),"") | G39: =IFERROR(INDEX('Watershed plans'!$Y$12:$Y$15,MATCH(34,'Watershed plans'!$S$12:$S$15,0)),"") | H39: =IFERROR(INDEX('Watershed plans'!$X$12:$X$15,MATCH(34,'Watershed plans'!$S$12:$S$15,0)),"")
A40: 35 | B40: =IFERROR(INDEX('Watershed plans'!$F$12:$F$15,MATCH(35,'Watershed plans'!$S$12:$S$15,0)),"") | C40: =IFERROR(INDEX('Watershed plans'!$B$12:$B$15,MATCH(35,'Watershed plans'!$S$12:$S$15,0)),"") | D40: =IFERROR(INDEX('Watershed plans'!$J$12:$J$15,MATCH(35,'Watershed plans'!$S$12:$S$15,0)),"") | E40: =IFERROR(INDEX('Watershed plans'!$K$12:$K$15,MATCH(35,'Watershed plans'!$S$12:$S$15,0)),"") | F40: =IFERROR(INDEX('Watershed plans'!$I$12:$I$15,MATCH(35,'Watershed plans'!$S$12:$S$15,0)),"") | G40: =IFERROR(INDEX('Watershed plans'!$Y$12:$Y$15,MATCH(35,'Watershed plans'!$S$12:$S$15,0)),"") | H40: =IFERROR(INDEX('Watershed plans'!$X$12:$X$15,MATCH(35,'Watershed plans'!$S$12:$S$15,0)),"")
A41: 36 | B41: =IFERROR(INDEX('Watershed plans'!$F$12:$F$15,MATCH(36,'Watershed plans'!$S$12:$S$15,0)),"") | C41: =IFERROR(INDEX('Watershed plans'!$B$12:$B$15,MATCH(36,'Watershed plans'!$S$12:$S$15,0)),"") | D41: =IFERROR(INDEX('Watershed plans'!$J$12:$J$15,MATCH(36,'Watershed plans'!$S$12:$S$15,0)),"") | E41: =IFERROR(INDEX('Watershed plans'!$K$12:$K$15,MATCH(36,'Watershed plans'!$S$12:$S$15,0)),"") | F41: =IFERROR(INDEX('Watershed plans'!$I$12:$I$15,MATCH(36,'Watershed plans'!$S$12:$S$15,0)),"") | G41: =IFERROR(INDEX('Watershed plans'!$Y$12:$Y$15,MATCH(36,'Watershed plans'!$S$12:$S$15,0)),"") | H41: =IFERROR(INDEX('Watershed plans'!$X$12:$X$15,MATCH(36,'Watershed plans'!$S$12:$S$15,0)),"")
A42: 37 | B42: =IFERROR(INDEX('Watershed plans'!$F$12:$F$15,MATCH(37,'Watershed plans'!$S$12:$S$15,0)),"") | C42: =IFERROR(INDEX('Watershed plans'!$B$12:$B$15,MATCH(37,'Watershed plans'!$S$12:$S$15,0)),"") | D42: =IFERROR(INDEX('Watershed plans'!$J$12:$J$15,MATCH(37,'Watershed plans'!$S$12:$S$15,0)),"") | E42: =IFERROR(INDEX('Watershed plans'!$K$12:$K$15,MATCH(37,'Watershed plans'!$S$12:$S$15,0)),"") | F42: =IFERROR(INDEX('Watershed plans'!$I$12:$I$15,MATCH(37,'Watershed plans'!$S$12:$S$15,0)),"") | G42: =IFERROR(INDEX('Watershed plans'!$Y$12:$Y$15,MATCH(37,'Watershed plans'!$S$12:$S$15,0)),"") | H42: =IFERROR(INDEX('Watershed plans'!$X$12:$X$15,MATCH(37,'Watershed plans'!$S$12:$S$15,0)),"")
A43: 38 | B43: =IFERROR(INDEX('Watershed plans'!$F$12:$F$15,MATCH(38,'Watershed plans'!$S$12:$S$15,0)),"") | C43: =IFERROR(INDEX('Watershed plans'!$B$12:$B$15,MATCH(38,'Watershed plans'!$S$12:$S$15,0)),"") | D43: =IFERROR(INDEX('Watershed plans'!$J$12:$J$15,MATCH(38,'Watershed plans'!$S$12:$S$15,0)),"") | E43: =IFERROR(INDEX('Watershed plans'!$K$12:$K$15,MATCH(38,'Watershed plans'!$S$12:$S$15,0)),"") | F43: =IFERROR(INDEX('Watershed plans'!$I$12:$I$15,MATCH(38,'Watershed plans'!$S$12:$S$15,0)),"") | G43: =IFERROR(INDEX('Watershed plans'!$Y$12:$Y$15,MATCH(38,'Watershed plans'!$S$12:$S$15,0)),"") | H43: =IFERROR(INDEX('Watershed plans'!$X$12:$X$15,MATCH(38,'Watershed plans'!$S$12:$S$15,0)),"")
A44: 39 | B44: =IFERROR(INDEX('Watershed plans'!$F$12:$F$15,MATCH(39,'Watershed plans'!$S$12:$S$15,0)),"") | C44: =IFERROR(INDEX('Watershed plans'!$B$12:$B$15,MATCH(39,'Watershed plans'!$S$12:$S$15,0)),"") | D44: =IFERROR(INDEX('Watershed plans'!$J$12:$J$15,MATCH(39,'Watershed plans'!$S$12:$S$15,0)),"") | E44: =IFERROR(INDEX('Watershed plans'!$K$12:$K$15,MATCH(39,'Watershed plans'!$S$12:$S$15,0)),"") | F44: =IFERROR(INDEX('Watershed plans'!$I$12:$I$15,MATCH(39,'Watershed plans'!$S$12:$S$15,0)),"") | G44: =IFERROR(INDEX('Watershed plans'!$Y$12:$Y$15,MATCH(39,'Watershed plans'!$S$12:$S$15,0)),"") | H44: =IFERROR(INDEX('Watershed plans'!$X$12:$X$15,MATCH(39,'Watershed plans'!$S$12:$S$15,0)),"")
A45: 40 | B45: =IFERROR(INDEX('Watershed plans'!$F$12:$F$15,MATCH(40,'Watershed plans'!$S$12:$S$15,0)),"") | C45: =IFERROR(INDEX('Watershed plans'!$B$12:$B$15,MATCH(40,'Watershed plans'!$S$12:$S$15,0)),"") | D45: =IFERROR(INDEX('Watershed plans'!$J$12:$J$15,MATCH(40,'Watershed plans'!$S$12:$S$15,0)),"") | E45: =IFERROR(INDEX('Watershed plans'!$K$12:$K$15,MATCH(40,'Watershed plans'!$S$12:$S$15,0)),"") | F45: =IFERROR(INDEX('Watershed plans'!$I$12:$I$15,MATCH(40,'Watershed plans'!$S$12:$S$15,0)),"") | G45: =IFERROR(INDEX('Watershed plans'!$Y$12:$Y$15,MATCH(40,'Watershed plans'!$S$12:$S$15,0)),"") | H45: =IFERROR(INDEX('Watershed plans'!$X$12:$X$15,MATCH(40,'Watershed plans'!$S$12:$S$15,0)),"")
A48: Final array (in order of output) and 'Is it worth it?'
A49: Order | B49: Plan number | C49: Plan | D49: Lift (AAHU) | E49: Average annual cost | F49: Construction cost | G49: Unit cost | H49: Added output | I49: Added cost | J49: Added cost per unit | K49: Worth it? | L49: Why
A50: 1 | B50: =IFERROR(INDEX('Watershed plans'!$F$12:$F$15,MATCH(1,'Watershed plans'!$AA$12:$AA$15,0)),"") -> 1 | C50: =IFERROR(INDEX('Watershed plans'!$B$12:$B$15,MATCH(1,'Watershed plans'!$AA$12:$AA$15,0)),"") -> No Action | D50: =IFERROR(INDEX('Watershed plans'!$J$12:$J$15,MATCH(1,'Watershed plans'!$AA$12:$AA$15,0)),"") -> 0 | E50: =IFERROR(INDEX('Watershed plans'!$K$12:$K$15,MATCH(1,'Watershed plans'!$AA$12:$AA$15,0)),"") -> 0 | F50: =IFERROR(INDEX('Watershed plans'!$I$12:$I$15,MATCH(1,'Watershed plans'!$AA$12:$AA$15,0)),"") -> 0 | G50: =IFERROR(INDEX('Watershed plans'!$Y$12:$Y$15,MATCH(1,'Watershed plans'!$AA$12:$AA$15,0)),"") -> n/a
A51: 2 | B51: =IFERROR(INDEX('Watershed plans'!$F$12:$F$15,MATCH(2,'Watershed plans'!$AA$12:$AA$15,0)),"") -> 2 | C51: =IFERROR(INDEX('Watershed plans'!$B$12:$B$15,MATCH(2,'Watershed plans'!$AA$12:$AA$15,0)),"") -> A | D51: =IFERROR(INDEX('Watershed plans'!$J$12:$J$15,MATCH(2,'Watershed plans'!$AA$12:$AA$15,0)),"") -> 6.208 | E51: =IFERROR(INDEX('Watershed plans'!$K$12:$K$15,MATCH(2,'Watershed plans'!$AA$12:$AA$15,0)),"") -> 18711.72 | F51: =IFERROR(INDEX('Watershed plans'!$I$12:$I$15,MATCH(2,'Watershed plans'!$AA$12:$AA$15,0)),"") -> 400000 | G51: =IFERROR(INDEX('Watershed plans'!$Y$12:$Y$15,MATCH(2,'Watershed plans'!$AA$12:$AA$15,0)),"") -> 3014.1302 | H51: =IF(ISNUMBER(D51),D51-D50,"") -> 6.208 | I51: =IF(ISNUMBER(E51),E51-E50,"") -> 18711.72 | J51: =IF(AND(ISNUMBER(H51),H51<>0),I51/H51,"") -> 3014.1302
A52: 3 | B52: =IFERROR(INDEX('Watershed plans'!$F$12:$F$15,MATCH(3,'Watershed plans'!$AA$12:$AA$15,0)),"") | C52: =IFERROR(INDEX('Watershed plans'!$B$12:$B$15,MATCH(3,'Watershed plans'!$AA$12:$AA$15,0)),"") | D52: =IFERROR(INDEX('Watershed plans'!$J$12:$J$15,MATCH(3,'Watershed plans'!$AA$12:$AA$15,0)),"") | E52: =IFERROR(INDEX('Watershed plans'!$K$12:$K$15,MATCH(3,'Watershed plans'!$AA$12:$AA$15,0)),"") | F52: =IFERROR(INDEX('Watershed plans'!$I$12:$I$15,MATCH(3,'Watershed plans'!$AA$12:$AA$15,0)),"") | G52: =IFERROR(INDEX('Watershed plans'!$Y$12:$Y$15,MATCH(3,'Watershed plans'!$AA$12:$AA$15,0)),"") | H52: =IF(ISNUMBER(D52),D52-D51,"") | I52: =IF(ISNUMBER(E52),E52-E51,"") | J52: =IF(AND(ISNUMBER(H52),H52<>0),I52/H52,"")
A53: 4 | B53: =IFERROR(INDEX('Watershed plans'!$F$12:$F$15,MATCH(4,'Watershed plans'!$AA$12:$AA$15,0)),"") | C53: =IFERROR(INDEX('Watershed plans'!$B$12:$B$15,MATCH(4,'Watershed plans'!$AA$12:$AA$15,0)),"") | D53: =IFERROR(INDEX('Watershed plans'!$J$12:$J$15,MATCH(4,'Watershed plans'!$AA$12:$AA$15,0)),"") | E53: =IFERROR(INDEX('Watershed plans'!$K$12:$K$15,MATCH(4,'Watershed plans'!$AA$12:$AA$15,0)),"") | F53: =IFERROR(INDEX('Watershed plans'!$I$12:$I$15,MATCH(4,'Watershed plans'!$AA$12:$AA$15,0)),"") | G53: =IFERROR(INDEX('Watershed plans'!$Y$12:$Y$15,MATCH(4,'Watershed plans'!$AA$12:$AA$15,0)),"") | H53: =IF(ISNUMBER(D53),D53-D52,"") | I53: =IF(ISNUMBER(E53),E53-E52,"") | J53: =IF(AND(ISNUMBER(H53),H53<>0),I53/H53,"")
A54: 5 | B54: =IFERROR(INDEX('Watershed plans'!$F$12:$F$15,MATCH(5,'Watershed plans'!$AA$12:$AA$15,0)),"") | C54: =IFERROR(INDEX('Watershed plans'!$B$12:$B$15,MATCH(5,'Watershed plans'!$AA$12:$AA$15,0)),"") | D54: =IFERROR(INDEX('Watershed plans'!$J$12:$J$15,MATCH(5,'Watershed plans'!$AA$12:$AA$15,0)),"") | E54: =IFERROR(INDEX('Watershed plans'!$K$12:$K$15,MATCH(5,'Watershed plans'!$AA$12:$AA$15,0)),"") | F54: =IFERROR(INDEX('Watershed plans'!$I$12:$I$15,MATCH(5,'Watershed plans'!$AA$12:$AA$15,0)),"") | G54: =IFERROR(INDEX('Watershed plans'!$Y$12:$Y$15,MATCH(5,'Watershed plans'!$AA$12:$AA$15,0)),"") | H54: =IF(ISNUMBER(D54),D54-D53,"") | I54: =IF(ISNUMBER(E54),E54-E53,"") | J54: =IF(AND(ISNUMBER(H54),H54<>0),I54/H54,"")
A55: 6 | B55: =IFERROR(INDEX('Watershed plans'!$F$12:$F$15,MATCH(6,'Watershed plans'!$AA$12:$AA$15,0)),"") | C55: =IFERROR(INDEX('Watershed plans'!$B$12:$B$15,MATCH(6,'Watershed plans'!$AA$12:$AA$15,0)),"") | D55: =IFERROR(INDEX('Watershed plans'!$J$12:$J$15,MATCH(6,'Watershed plans'!$AA$12:$AA$15,0)),"") | E55: =IFERROR(INDEX('Watershed plans'!$K$12:$K$15,MATCH(6,'Watershed plans'!$AA$12:$AA$15,0)),"") | F55: =IFERROR(INDEX('Watershed plans'!$I$12:$I$15,MATCH(6,'Watershed plans'!$AA$12:$AA$15,0)),"") | G55: =IFERROR(INDEX('Watershed plans'!$Y$12:$Y$15,MATCH(6,'Watershed plans'!$AA$12:$AA$15,0)),"") | H55: =IF(ISNUMBER(D55),D55-D54,"") | I55: =IF(ISNUMBER(E55),E55-E54,"") | J55: =IF(AND(ISNUMBER(H55),H55<>0),I55/H55,"")
A56: 7 | B56: =IFERROR(INDEX('Watershed plans'!$F$12:$F$15,MATCH(7,'Watershed plans'!$AA$12:$AA$15,0)),"") | C56: =IFERROR(INDEX('Watershed plans'!$B$12:$B$15,MATCH(7,'Watershed plans'!$AA$12:$AA$15,0)),"") | D56: =IFERROR(INDEX('Watershed plans'!$J$12:$J$15,MATCH(7,'Watershed plans'!$AA$12:$AA$15,0)),"") | E56: =IFERROR(INDEX('Watershed plans'!$K$12:$K$15,MATCH(7,'Watershed plans'!$AA$12:$AA$15,0)),"") | F56: =IFERROR(INDEX('Watershed plans'!$I$12:$I$15,MATCH(7,'Watershed plans'!$AA$12:$AA$15,0)),"") | G56: =IFERROR(INDEX('Watershed plans'!$Y$12:$Y$15,MATCH(7,'Watershed plans'!$AA$12:$AA$15,0)),"") | H56: =IF(ISNUMBER(D56),D56-D55,"") | I56: =IF(ISNUMBER(E56),E56-E55,"") | J56: =IF(AND(ISNUMBER(H56),H56<>0),I56/H56,"")
A57: 8 | B57: =IFERROR(INDEX('Watershed plans'!$F$12:$F$15,MATCH(8,'Watershed plans'!$AA$12:$AA$15,0)),"") | C57: =IFERROR(INDEX('Watershed plans'!$B$12:$B$15,MATCH(8,'Watershed plans'!$AA$12:$AA$15,0)),"") | D57: =IFERROR(INDEX('Watershed plans'!$J$12:$J$15,MATCH(8,'Watershed plans'!$AA$12:$AA$15,0)),"") | E57: =IFERROR(INDEX('Watershed plans'!$K$12:$K$15,MATCH(8,'Watershed plans'!$AA$12:$AA$15,0)),"") | F57: =IFERROR(INDEX('Watershed plans'!$I$12:$I$15,MATCH(8,'Watershed plans'!$AA$12:$AA$15,0)),"") | G57: =IFERROR(INDEX('Watershed plans'!$Y$12:$Y$15,MATCH(8,'Watershed plans'!$AA$12:$AA$15,0)),"") | H57: =IF(ISNUMBER(D57),D57-D56,"") | I57: =IF(ISNUMBER(E57),E57-E56,"") | J57: =IF(AND(ISNUMBER(H57),H57<>0),I57/H57,"")
A58: 9 | B58: =IFERROR(INDEX('Watershed plans'!$F$12:$F$15,MATCH(9,'Watershed plans'!$AA$12:$AA$15,0)),"") | C58: =IFERROR(INDEX('Watershed plans'!$B$12:$B$15,MATCH(9,'Watershed plans'!$AA$12:$AA$15,0)),"") | D58: =IFERROR(INDEX('Watershed plans'!$J$12:$J$15,MATCH(9,'Watershed plans'!$AA$12:$AA$15,0)),"") | E58: =IFERROR(INDEX('Watershed plans'!$K$12:$K$15,MATCH(9,'Watershed plans'!$AA$12:$AA$15,0)),"") | F58: =IFERROR(INDEX('Watershed plans'!$I$12:$I$15,MATCH(9,'Watershed plans'!$AA$12:$AA$15,0)),"") | G58: =IFERROR(INDEX('Watershed plans'!$Y$12:$Y$15,MATCH(9,'Watershed plans'!$AA$12:$AA$15,0)),"") | H58: =IF(ISNUMBER(D58),D58-D57,"") | I58: =IF(ISNUMBER(E58),E58-E57,"") | J58: =IF(AND(ISNUMBER(H58),H58<>0),I58/H58,"")
A59: 10 | B59: =IFERROR(INDEX('Watershed plans'!$F$12:$F$15,MATCH(10,'Watershed plans'!$AA$12:$AA$15,0)),"") | C59: =IFERROR(INDEX('Watershed plans'!$B$12:$B$15,MATCH(10,'Watershed plans'!$AA$12:$AA$15,0)),"") | D59: =IFERROR(INDEX('Watershed plans'!$J$12:$J$15,MATCH(10,'Watershed plans'!$AA$12:$AA$15,0)),"") | E59: =IFERROR(INDEX('Watershed plans'!$K$12:$K$15,MATCH(10,'Watershed plans'!$AA$12:$AA$15,0)),"") | F59: =IFERROR(INDEX('Watershed plans'!$I$12:$I$15,MATCH(10,'Watershed plans'!$AA$12:$AA$15,0)),"") | G59: =IFERROR(INDEX('Watershed plans'!$Y$12:$Y$15,MATCH(10,'Watershed plans'!$AA$12:$AA$15,0)),"") | H59: =IF(ISNUMBER(D59),D59-D58,"") | I59: =IF(ISNUMBER(E59),E59-E58,"") | J59: =IF(AND(ISNUMBER(H59),H59<>0),I59/H59,"")
A60: 11 | B60: =IFERROR(INDEX('Watershed plans'!$F$12:$F$15,MATCH(11,'Watershed plans'!$AA$12:$AA$15,0)),"") | C60: =IFERROR(INDEX('Watershed plans'!$B$12:$B$15,MATCH(11,'Watershed plans'!$AA$12:$AA$15,0)),"") | D60: =IFERROR(INDEX('Watershed plans'!$J$12:$J$15,MATCH(11,'Watershed plans'!$AA$12:$AA$15,0)),"") | E60: =IFERROR(INDEX('Watershed plans'!$K$12:$K$15,MATCH(11,'Watershed plans'!$AA$12:$AA$15,0)),"") | F60: =IFERROR(INDEX('Watershed plans'!$I$12:$I$15,MATCH(11,'Watershed plans'!$AA$12:$AA$15,0)),"") | G60: =IFERROR(INDEX('Watershed plans'!$Y$12:$Y$15,MATCH(11,'Watershed plans'!$AA$12:$AA$15,0)),"") | H60: =IF(ISNUMBER(D60),D60-D59,"") | I60: =IF(ISNUMBER(E60),E60-E59,"") | J60: =IF(AND(ISNUMBER(H60),H60<>0),I60/H60,"")
A61: 12 | B61: =IFERROR(INDEX('Watershed plans'!$F$12:$F$15,MATCH(12,'Watershed plans'!$AA$12:$AA$15,0)),"") | C61: =IFERROR(INDEX('Watershed plans'!$B$12:$B$15,MATCH(12,'Watershed plans'!$AA$12:$AA$15,0)),"") | D61: =IFERROR(INDEX('Watershed plans'!$J$12:$J$15,MATCH(12,'Watershed plans'!$AA$12:$AA$15,0)),"") | E61: =IFERROR(INDEX('Watershed plans'!$K$12:$K$15,MATCH(12,'Watershed plans'!$AA$12:$AA$15,0)),"") | F61: =IFERROR(INDEX('Watershed plans'!$I$12:$I$15,MATCH(12,'Watershed plans'!$AA$12:$AA$15,0)),"") | G61: =IFERROR(INDEX('Watershed plans'!$Y$12:$Y$15,MATCH(12,'Watershed plans'!$AA$12:$AA$15,0)),"") | H61: =IF(ISNUMBER(D61),D61-D60,"") | I61: =IF(ISNUMBER(E61),E61-E60,"") | J61: =IF(AND(ISNUMBER(H61),H61<>0),I61/H61,"")
A62: 13 | B62: =IFERROR(INDEX('Watershed plans'!$F$12:$F$15,MATCH(13,'Watershed plans'!$AA$12:$AA$15,0)),"") | C62: =IFERROR(INDEX('Watershed plans'!$B$12:$B$15,MATCH(13,'Watershed plans'!$AA$12:$AA$15,0)),"") | D62: =IFERROR(INDEX('Watershed plans'!$J$12:$J$15,MATCH(13,'Watershed plans'!$AA$12:$AA$15,0)),"") | E62: =IFERROR(INDEX('Watershed plans'!$K$12:$K$15,MATCH(13,'Watershed plans'!$AA$12:$AA$15,0)),"") | F62: =IFERROR(INDEX('Watershed plans'!$I$12:$I$15,MATCH(13,'Watershed plans'!$AA$12:$AA$15,0)),"") | G62: =IFERROR(INDEX('Watershed plans'!$Y$12:$Y$15,MATCH(13,'Watershed plans'!$AA$12:$AA$15,0)),"") | H62: =IF(ISNUMBER(D62),D62-D61,"") | I62: =IF(ISNUMBER(E62),E62-E61,"") | J62: =IF(AND(ISNUMBER(H62),H62<>0),I62/H62,"")
A63: 14 | B63: =IFERROR(INDEX('Watershed plans'!$F$12:$F$15,MATCH(14,'Watershed plans'!$AA$12:$AA$15,0)),"") | C63: =IFERROR(INDEX('Watershed plans'!$B$12:$B$15,MATCH(14,'Watershed plans'!$AA$12:$AA$15,0)),"") | D63: =IFERROR(INDEX('Watershed plans'!$J$12:$J$15,MATCH(14,'Watershed plans'!$AA$12:$AA$15,0)),"") | E63: =IFERROR(INDEX('Watershed plans'!$K$12:$K$15,MATCH(14,'Watershed plans'!$AA$12:$AA$15,0)),"") | F63: =IFERROR(INDEX('Watershed plans'!$I$12:$I$15,MATCH(14,'Watershed plans'!$AA$12:$AA$15,0)),"") | G63: =IFERROR(INDEX('Watershed plans'!$Y$12:$Y$15,MATCH(14,'Watershed plans'!$AA$12:$AA$15,0)),"") | H63: =IF(ISNUMBER(D63),D63-D62,"") | I63: =IF(ISNUMBER(E63),E63-E62,"") | J63: =IF(AND(ISNUMBER(H63),H63<>0),I63/H63,"")
A64: 15 | B64: =IFERROR(INDEX('Watershed plans'!$F$12:$F$15,MATCH(15,'Watershed plans'!$AA$12:$AA$15,0)),"") | C64: =IFERROR(INDEX('Watershed plans'!$B$12:$B$15,MATCH(15,'Watershed plans'!$AA$12:$AA$15,0)),"") | D64: =IFERROR(INDEX('Watershed plans'!$J$12:$J$15,MATCH(15,'Watershed plans'!$AA$12:$AA$15,0)),"") | E64: =IFERROR(INDEX('Watershed plans'!$K$12:$K$15,MATCH(15,'Watershed plans'!$AA$12:$AA$15,0)),"") | F64: =IFERROR(INDEX('Watershed plans'!$I$12:$I$15,MATCH(15,'Watershed plans'!$AA$12:$AA$15,0)),"") | G64: =IFERROR(INDEX('Watershed plans'!$Y$12:$Y$15,MATCH(15,'Watershed plans'!$AA$12:$AA$15,0)),"") | H64: =IF(ISNUMBER(D64),D64-D63,"") | I64: =IF(ISNUMBER(E64),E64-E63,"") | J64: =IF(AND(ISNUMBER(H64),H64<>0),I64/H64,"")
A65: 16 | B65: =IFERROR(INDEX('Watershed plans'!$F$12:$F$15,MATCH(16,'Watershed plans'!$AA$12:$AA$15,0)),"") | C65: =IFERROR(INDEX('Watershed plans'!$B$12:$B$15,MATCH(16,'Watershed plans'!$AA$12:$AA$15,0)),"") | D65: =IFERROR(INDEX('Watershed plans'!$J$12:$J$15,MATCH(16,'Watershed plans'!$AA$12:$AA$15,0)),"") | E65: =IFERROR(INDEX('Watershed plans'!$K$12:$K$15,MATCH(16,'Watershed plans'!$AA$12:$AA$15,0)),"") | F65: =IFERROR(INDEX('Watershed plans'!$I$12:$I$15,MATCH(16,'Watershed plans'!$AA$12:$AA$15,0)),"") | G65: =IFERROR(INDEX('Watershed plans'!$Y$12:$Y$15,MATCH(16,'Watershed plans'!$AA$12:$AA$15,0)),"") | H65: =IF(ISNUMBER(D65),D65-D64,"") | I65: =IF(ISNUMBER(E65),E65-E64,"") | J65: =IF(AND(ISNUMBER(H65),H65<>0),I65/H65,"")
A66: 17 | B66: =IFERROR(INDEX('Watershed plans'!$F$12:$F$15,MATCH(17,'Watershed plans'!$AA$12:$AA$15,0)),"") | C66: =IFERROR(INDEX('Watershed plans'!$B$12:$B$15,MATCH(17,'Watershed plans'!$AA$12:$AA$15,0)),"") | D66: =IFERROR(INDEX('Watershed plans'!$J$12:$J$15,MATCH(17,'Watershed plans'!$AA$12:$AA$15,0)),"") | E66: =IFERROR(INDEX('Watershed plans'!$K$12:$K$15,MATCH(17,'Watershed plans'!$AA$12:$AA$15,0)),"") | F66: =IFERROR(INDEX('Watershed plans'!$I$12:$I$15,MATCH(17,'Watershed plans'!$AA$12:$AA$15,0)),"") | G66: =IFERROR(INDEX('Watershed plans'!$Y$12:$Y$15,MATCH(17,'Watershed plans'!$AA$12:$AA$15,0)),"") | H66: =IF(ISNUMBER(D66),D66-D65,"") | I66: =IF(ISNUMBER(E66),E66-E65,"") | J66: =IF(AND(ISNUMBER(H66),H66<>0),I66/H66,"")
A67: 18 | B67: =IFERROR(INDEX('Watershed plans'!$F$12:$F$15,MATCH(18,'Watershed plans'!$AA$12:$AA$15,0)),"") | C67: =IFERROR(INDEX('Watershed plans'!$B$12:$B$15,MATCH(18,'Watershed plans'!$AA$12:$AA$15,0)),"") | D67: =IFERROR(INDEX('Watershed plans'!$J$12:$J$15,MATCH(18,'Watershed plans'!$AA$12:$AA$15,0)),"") | E67: =IFERROR(INDEX('Watershed plans'!$K$12:$K$15,MATCH(18,'Watershed plans'!$AA$12:$AA$15,0)),"") | F67: =IFERROR(INDEX('Watershed plans'!$I$12:$I$15,MATCH(18,'Watershed plans'!$AA$12:$AA$15,0)),"") | G67: =IFERROR(INDEX('Watershed plans'!$Y$12:$Y$15,MATCH(18,'Watershed plans'!$AA$12:$AA$15,0)),"") | H67: =IF(ISNUMBER(D67),D67-D66,"") | I67: =IF(ISNUMBER(E67),E67-E66,"") | J67: =IF(AND(ISNUMBER(H67),H67<>0),I67/H67,"")
A68: 19 | B68: =IFERROR(INDEX('Watershed plans'!$F$12:$F$15,MATCH(19,'Watershed plans'!$AA$12:$AA$15,0)),"") | C68: =IFERROR(INDEX('Watershed plans'!$B$12:$B$15,MATCH(19,'Watershed plans'!$AA$12:$AA$15,0)),"") | D68: =IFERROR(INDEX('Watershed plans'!$J$12:$J$15,MATCH(19,'Watershed plans'!$AA$12:$AA$15,0)),"") | E68: =IFERROR(INDEX('Watershed plans'!$K$12:$K$15,MATCH(19,'Watershed plans'!$AA$12:$AA$15,0)),"") | F68: =IFERROR(INDEX('Watershed plans'!$I$12:$I$15,MATCH(19,'Watershed plans'!$AA$12:$AA$15,0)),"") | G68: =IFERROR(INDEX('Watershed plans'!$Y$12:$Y$15,MATCH(19,'Watershed plans'!$AA$12:$AA$15,0)),"") | H68: =IF(ISNUMBER(D68),D68-D67,"") | I68: =IF(ISNUMBER(E68),E68-E67,"") | J68: =IF(AND(ISNUMBER(H68),H68<>0),I68/H68,"")
A69: 20 | B69: =IFERROR(INDEX('Watershed plans'!$F$12:$F$15,MATCH(20,'Watershed plans'!$AA$12:$AA$15,0)),"") | C69: =IFERROR(INDEX('Watershed plans'!$B$12:$B$15,MATCH(20,'Watershed plans'!$AA$12:$AA$15,0)),"") | D69: =IFERROR(INDEX('Watershed plans'!$J$12:$J$15,MATCH(20,'Watershed plans'!$AA$12:$AA$15,0)),"") | E69: =IFERROR(INDEX('Watershed plans'!$K$12:$K$15,MATCH(20,'Watershed plans'!$AA$12:$AA$15,0)),"") | F69: =IFERROR(INDEX('Watershed plans'!$I$12:$I$15,MATCH(20,'Watershed plans'!$AA$12:$AA$15,0)),"") | G69: =IFERROR(INDEX('Watershed plans'!$Y$12:$Y$15,MATCH(20,'Watershed plans'!$AA$12:$AA$15,0)),"") | H69: =IF(ISNUMBER(D69),D69-D68,"") | I69: =IF(ISNUMBER(E69),E69-E68,"") | J69: =IF(AND(ISNUMBER(H69),H69<>0),I69/H69,"")
A70: 21 | B70: =IFERROR(INDEX('Watershed plans'!$F$12:$F$15,MATCH(21,'Watershed plans'!$AA$12:$AA$15,0)),"") | C70: =IFERROR(INDEX('Watershed plans'!$B$12:$B$15,MATCH(21,'Watershed plans'!$AA$12:$AA$15,0)),"") | D70: =IFERROR(INDEX('Watershed plans'!$J$12:$J$15,MATCH(21,'Watershed plans'!$AA$12:$AA$15,0)),"") | E70: =IFERROR(INDEX('Watershed plans'!$K$12:$K$15,MATCH(21,'Watershed plans'!$AA$12:$AA$15,0)),"") | F70: =IFERROR(INDEX('Watershed plans'!$I$12:$I$15,MATCH(21,'Watershed plans'!$AA$12:$AA$15,0)),"") | G70: =IFERROR(INDEX('Watershed plans'!$Y$12:$Y$15,MATCH(21,'Watershed plans'!$AA$12:$AA$15,0)),"") | H70: =IF(ISNUMBER(D70),D70-D69,"") | I70: =IF(ISNUMBER(E70),E70-E69,"") | J70: =IF(AND(ISNUMBER(H70),H70<>0),I70/H70,"")
A71: 22 | B71: =IFERROR(INDEX('Watershed plans'!$F$12:$F$15,MATCH(22,'Watershed plans'!$AA$12:$AA$15,0)),"") | C71: =IFERROR(INDEX('Watershed plans'!$B$12:$B$15,MATCH(22,'Watershed plans'!$AA$12:$AA$15,0)),"") | D71: =IFERROR(INDEX('Watershed plans'!$J$12:$J$15,MATCH(22,'Watershed plans'!$AA$12:$AA$15,0)),"") | E71: =IFERROR(INDEX('Watershed plans'!$K$12:$K$15,MATCH(22,'Watershed plans'!$AA$12:$AA$15,0)),"") | F71: =IFERROR(INDEX('Watershed plans'!$I$12:$I$15,MATCH(22,'Watershed plans'!$AA$12:$AA$15,0)),"") | G71: =IFERROR(INDEX('Watershed plans'!$Y$12:$Y$15,MATCH(22,'Watershed plans'!$AA$12:$AA$15,0)),"") | H71: =IF(ISNUMBER(D71),D71-D70,"") | I71: =IF(ISNUMBER(E71),E71-E70,"") | J71: =IF(AND(ISNUMBER(H71),H71<>0),I71/H71,"")
A72: 23 | B72: =IFERROR(INDEX('Watershed plans'!$F$12:$F$15,MATCH(23,'Watershed plans'!$AA$12:$AA$15,0)),"") | C72: =IFERROR(INDEX('Watershed plans'!$B$12:$B$15,MATCH(23,'Watershed plans'!$AA$12:$AA$15,0)),"") | D72: =IFERROR(INDEX('Watershed plans'!$J$12:$J$15,MATCH(23,'Watershed plans'!$AA$12:$AA$15,0)),"") | E72: =IFERROR(INDEX('Watershed plans'!$K$12:$K$15,MATCH(23,'Watershed plans'!$AA$12:$AA$15,0)),"") | F72: =IFERROR(INDEX('Watershed plans'!$I$12:$I$15,MATCH(23,'Watershed plans'!$AA$12:$AA$15,0)),"") | G72: =IFERROR(INDEX('Watershed plans'!$Y$12:$Y$15,MATCH(23,'Watershed plans'!$AA$12:$AA$15,0)),"") | H72: =IF(ISNUMBER(D72),D72-D71,"") | I72: =IF(ISNUMBER(E72),E72-E71,"") | J72: =IF(AND(ISNUMBER(H72),H72<>0),I72/H72,"")
A73: 24 | B73: =IFERROR(INDEX('Watershed plans'!$F$12:$F$15,MATCH(24,'Watershed plans'!$AA$12:$AA$15,0)),"") | C73: =IFERROR(INDEX('Watershed plans'!$B$12:$B$15,MATCH(24,'Watershed plans'!$AA$12:$AA$15,0)),"") | D73: =IFERROR(INDEX('Watershed plans'!$J$12:$J$15,MATCH(24,'Watershed plans'!$AA$12:$AA$15,0)),"") | E73: =IFERROR(INDEX('Watershed plans'!$K$12:$K$15,MATCH(24,'Watershed plans'!$AA$12:$AA$15,0)),"") | F73: =IFERROR(INDEX('Watershed plans'!$I$12:$I$15,MATCH(24,'Watershed plans'!$AA$12:$AA$15,0)),"") | G73: =IFERROR(INDEX('Watershed plans'!$Y$12:$Y$15,MATCH(24,'Watershed plans'!$AA$12:$AA$15,0)),"") | H73: =IF(ISNUMBER(D73),D73-D72,"") | I73: =IF(ISNUMBER(E73),E73-E72,"") | J73: =IF(AND(ISNUMBER(H73),H73<>0),I73/H73,"")
A74: 25 | B74: =IFERROR(INDEX('Watershed plans'!$F$12:$F$15,MATCH(25,'Watershed plans'!$AA$12:$AA$15,0)),"") | C74: =IFERROR(INDEX('Watershed plans'!$B$12:$B$15,MATCH(25,'Watershed plans'!$AA$12:$AA$15,0)),"") | D74: =IFERROR(INDEX('Watershed plans'!$J$12:$J$15,MATCH(25,'Watershed plans'!$AA$12:$AA$15,0)),"") | E74: =IFERROR(INDEX('Watershed plans'!$K$12:$K$15,MATCH(25,'Watershed plans'!$AA$12:$AA$15,0)),"") | F74: =IFERROR(INDEX('Watershed plans'!$I$12:$I$15,MATCH(25,'Watershed plans'!$AA$12:$AA$15,0)),"") | G74: =IFERROR(INDEX('Watershed plans'!$Y$12:$Y$15,MATCH(25,'Watershed plans'!$AA$12:$AA$15,0)),"") | H74: =IF(ISNUMBER(D74),D74-D73,"") | I74: =IF(ISNUMBER(E74),E74-E73,"") | J74: =IF(AND(ISNUMBER(H74),H74<>0),I74/H74,"")
A75: 26 | B75: =IFERROR(INDEX('Watershed plans'!$F$12:$F$15,MATCH(26,'Watershed plans'!$AA$12:$AA$15,0)),"") | C75: =IFERROR(INDEX('Watershed plans'!$B$12:$B$15,MATCH(26,'Watershed plans'!$AA$12:$AA$15,0)),"") | D75: =IFERROR(INDEX('Watershed plans'!$J$12:$J$15,MATCH(26,'Watershed plans'!$AA$12:$AA$15,0)),"") | E75: =IFERROR(INDEX('Watershed plans'!$K$12:$K$15,MATCH(26,'Watershed plans'!$AA$12:$AA$15,0)),"") | F75: =IFERROR(INDEX('Watershed plans'!$I$12:$I$15,MATCH(26,'Watershed plans'!$AA$12:$AA$15,0)),"") | G75: =IFERROR(INDEX('Watershed plans'!$Y$12:$Y$15,MATCH(26,'Watershed plans'!$AA$12:$AA$15,0)),"") | H75: =IF(ISNUMBER(D75),D75-D74,"") | I75: =IF(ISNUMBER(E75),E75-E74,"") | J75: =IF(AND(ISNUMBER(H75),H75<>0),I75/H75,"")
A76: 27 | B76: =IFERROR(INDEX('Watershed plans'!$F$12:$F$15,MATCH(27,'Watershed plans'!$AA$12:$AA$15,0)),"") | C76: =IFERROR(INDEX('Watershed plans'!$B$12:$B$15,MATCH(27,'Watershed plans'!$AA$12:$AA$15,0)),"") | D76: =IFERROR(INDEX('Watershed plans'!$J$12:$J$15,MATCH(27,'Watershed plans'!$AA$12:$AA$15,0)),"") | E76: =IFERROR(INDEX('Watershed plans'!$K$12:$K$15,MATCH(27,'Watershed plans'!$AA$12:$AA$15,0)),"") | F76: =IFERROR(INDEX('Watershed plans'!$I$12:$I$15,MATCH(27,'Watershed plans'!$AA$12:$AA$15,0)),"") | G76: =IFERROR(INDEX('Watershed plans'!$Y$12:$Y$15,MATCH(27,'Watershed plans'!$AA$12:$AA$15,0)),"") | H76: =IF(ISNUMBER(D76),D76-D75,"") | I76: =IF(ISNUMBER(E76),E76-E75,"") | J76: =IF(AND(ISNUMBER(H76),H76<>0),I76/H76,"")
A77: 28 | B77: =IFERROR(INDEX('Watershed plans'!$F$12:$F$15,MATCH(28,'Watershed plans'!$AA$12:$AA$15,0)),"") | C77: =IFERROR(INDEX('Watershed plans'!$B$12:$B$15,MATCH(28,'Watershed plans'!$AA$12:$AA$15,0)),"") | D77: =IFERROR(INDEX('Watershed plans'!$J$12:$J$15,MATCH(28,'Watershed plans'!$AA$12:$AA$15,0)),"") | E77: =IFERROR(INDEX('Watershed plans'!$K$12:$K$15,MATCH(28,'Watershed plans'!$AA$12:$AA$15,0)),"") | F77: =IFERROR(INDEX('Watershed plans'!$I$12:$I$15,MATCH(28,'Watershed plans'!$AA$12:$AA$15,0)),"") | G77: =IFERROR(INDEX('Watershed plans'!$Y$12:$Y$15,MATCH(28,'Watershed plans'!$AA$12:$AA$15,0)),"") | H77: =IF(ISNUMBER(D77),D77-D76,"") | I77: =IF(ISNUMBER(E77),E77-E76,"") | J77: =IF(AND(ISNUMBER(H77),H77<>0),I77/H77,"")
A78: 29 | B78: =IFERROR(INDEX('Watershed plans'!$F$12:$F$15,MATCH(29,'Watershed plans'!$AA$12:$AA$15,0)),"") | C78: =IFERROR(INDEX('Watershed plans'!$B$12:$B$15,MATCH(29,'Watershed plans'!$AA$12:$AA$15,0)),"") | D78: =IFERROR(INDEX('Watershed plans'!$J$12:$J$15,MATCH(29,'Watershed plans'!$AA$12:$AA$15,0)),"") | E78: =IFERROR(INDEX('Watershed plans'!$K$12:$K$15,MATCH(29,'Watershed plans'!$AA$12:$AA$15,0)),"") | F78: =IFERROR(INDEX('Watershed plans'!$I$12:$I$15,MATCH(29,'Watershed plans'!$AA$12:$AA$15,0)),"") | G78: =IFERROR(INDEX('Watershed plans'!$Y$12:$Y$15,MATCH(29,'Watershed plans'!$AA$12:$AA$15,0)),"") | H78: =IF(ISNUMBER(D78),D78-D77,"") | I78: =IF(ISNUMBER(E78),E78-E77,"") | J78: =IF(AND(ISNUMBER(H78),H78<>0),I78/H78,"")
A79: 30 | B79: =IFERROR(INDEX('Watershed plans'!$F$12:$F$15,MATCH(30,'Watershed plans'!$AA$12:$AA$15,0)),"") | C79: =IFERROR(INDEX('Watershed plans'!$B$12:$B$15,MATCH(30,'Watershed plans'!$AA$12:$AA$15,0)),"") | D79: =IFERROR(INDEX('Watershed plans'!$J$12:$J$15,MATCH(30,'Watershed plans'!$AA$12:$AA$15,0)),"") | E79: =IFERROR(INDEX('Watershed plans'!$K$12:$K$15,MATCH(30,'Watershed plans'!$AA$12:$AA$15,0)),"") | F79: =IFERROR(INDEX('Watershed plans'!$I$12:$I$15,MATCH(30,'Watershed plans'!$AA$12:$AA$15,0)),"") | G79: =IFERROR(INDEX('Watershed plans'!$Y$12:$Y$15,MATCH(30,'Watershed plans'!$AA$12:$AA$15,0)),"") | H79: =IF(ISNUMBER(D79),D79-D78,"") | I79: =IF(ISNUMBER(E79),E79-E78,"") | J79: =IF(AND(ISNUMBER(H79),H79<>0),I79/H79,"")
A80: 31 | B80: =IFERROR(INDEX('Watershed plans'!$F$12:$F$15,MATCH(31,'Watershed plans'!$AA$12:$AA$15,0)),"") | C80: =IFERROR(INDEX('Watershed plans'!$B$12:$B$15,MATCH(31,'Watershed plans'!$AA$12:$AA$15,0)),"") | D80: =IFERROR(INDEX('Watershed plans'!$J$12:$J$15,MATCH(31,'Watershed plans'!$AA$12:$AA$15,0)),"") | E80: =IFERROR(INDEX('Watershed plans'!$K$12:$K$15,MATCH(31,'Watershed plans'!$AA$12:$AA$15,0)),"") | F80: =IFERROR(INDEX('Watershed plans'!$I$12:$I$15,MATCH(31,'Watershed plans'!$AA$12:$AA$15,0)),"") | G80: =IFERROR(INDEX('Watershed plans'!$Y$12:$Y$15,MATCH(31,'Watershed plans'!$AA$12:$AA$15,0)),"") | H80: =IF(ISNUMBER(D80),D80-D79,"") | I80: =IF(ISNUMBER(E80),E80-E79,"") | J80: =IF(AND(ISNUMBER(H80),H80<>0),I80/H80,"")
A81: 32 | B81: =IFERROR(INDEX('Watershed plans'!$F$12:$F$15,MATCH(32,'Watershed plans'!$AA$12:$AA$15,0)),"") | C81: =IFERROR(INDEX('Watershed plans'!$B$12:$B$15,MATCH(32,'Watershed plans'!$AA$12:$AA$15,0)),"") | D81: =IFERROR(INDEX('Watershed plans'!$J$12:$J$15,MATCH(32,'Watershed plans'!$AA$12:$AA$15,0)),"") | E81: =IFERROR(INDEX('Watershed plans'!$K$12:$K$15,MATCH(32,'Watershed plans'!$AA$12:$AA$15,0)),"") | F81: =IFERROR(INDEX('Watershed plans'!$I$12:$I$15,MATCH(32,'Watershed plans'!$AA$12:$AA$15,0)),"") | G81: =IFERROR(INDEX('Watershed plans'!$Y$12:$Y$15,MATCH(32,'Watershed plans'!$AA$12:$AA$15,0)),"") | H81: =IF(ISNUMBER(D81),D81-D80,"") | I81: =IF(ISNUMBER(E81),E81-E80,"") | J81: =IF(AND(ISNUMBER(H81),H81<>0),I81/H81,"")
A82: 33 | B82: =IFERROR(INDEX('Watershed plans'!$F$12:$F$15,MATCH(33,'Watershed plans'!$AA$12:$AA$15,0)),"") | C82: =IFERROR(INDEX('Watershed plans'!$B$12:$B$15,MATCH(33,'Watershed plans'!$AA$12:$AA$15,0)),"") | D82: =IFERROR(INDEX('Watershed plans'!$J$12:$J$15,MATCH(33,'Watershed plans'!$AA$12:$AA$15,0)),"") | E82: =IFERROR(INDEX('Watershed plans'!$K$12:$K$15,MATCH(33,'Watershed plans'!$AA$12:$AA$15,0)),"") | F82: =IFERROR(INDEX('Watershed plans'!$I$12:$I$15,MATCH(33,'Watershed plans'!$AA$12:$AA$15,0)),"") | G82: =IFERROR(INDEX('Watershed plans'!$Y$12:$Y$15,MATCH(33,'Watershed plans'!$AA$12:$AA$15,0)),"") | H82: =IF(ISNUMBER(D82),D82-D81,"") | I82: =IF(ISNUMBER(E82),E82-E81,"") | J82: =IF(AND(ISNUMBER(H82),H82<>0),I82/H82,"")
A83: 34 | B83: =IFERROR(INDEX('Watershed plans'!$F$12:$F$15,MATCH(34,'Watershed plans'!$AA$12:$AA$15,0)),"") | C83: =IFERROR(INDEX('Watershed plans'!$B$12:$B$15,MATCH(34,'Watershed plans'!$AA$12:$AA$15,0)),"") | D83: =IFERROR(INDEX('Watershed plans'!$J$12:$J$15,MATCH(34,'Watershed plans'!$AA$12:$AA$15,0)),"") | E83: =IFERROR(INDEX('Watershed plans'!$K$12:$K$15,MATCH(34,'Watershed plans'!$AA$12:$AA$15,0)),"") | F83: =IFERROR(INDEX('Watershed plans'!$I$12:$I$15,MATCH(34,'Watershed plans'!$AA$12:$AA$15,0)),"") | G83: =IFERROR(INDEX('Watershed plans'!$Y$12:$Y$15,MATCH(34,'Watershed plans'!$AA$12:$AA$15,0)),"") | H83: =IF(ISNUMBER(D83),D83-D82,"") | I83: =IF(ISNUMBER(E83),E83-E82,"") | J83: =IF(AND(ISNUMBER(H83),H83<>0),I83/H83,"")
A84: 35 | B84: =IFERROR(INDEX('Watershed plans'!$F$12:$F$15,MATCH(35,'Watershed plans'!$AA$12:$AA$15,0)),"") | C84: =IFERROR(INDEX('Watershed plans'!$B$12:$B$15,MATCH(35,'Watershed plans'!$AA$12:$AA$15,0)),"") | D84: =IFERROR(INDEX('Watershed plans'!$J$12:$J$15,MATCH(35,'Watershed plans'!$AA$12:$AA$15,0)),"") | E84: =IFERROR(INDEX('Watershed plans'!$K$12:$K$15,MATCH(35,'Watershed plans'!$AA$12:$AA$15,0)),"") | F84: =IFERROR(INDEX('Watershed plans'!$I$12:$I$15,MATCH(35,'Watershed plans'!$AA$12:$AA$15,0)),"") | G84: =IFERROR(INDEX('Watershed plans'!$Y$12:$Y$15,MATCH(35,'Watershed plans'!$AA$12:$AA$15,0)),"") | H84: =IF(ISNUMBER(D84),D84-D83,"") | I84: =IF(ISNUMBER(E84),E84-E83,"") | J84: =IF(AND(ISNUMBER(H84),H84<>0),I84/H84,"")
A85: 36 | B85: =IFERROR(INDEX('Watershed plans'!$F$12:$F$15,MATCH(36,'Watershed plans'!$AA$12:$AA$15,0)),"") | C85: =IFERROR(INDEX('Watershed plans'!$B$12:$B$15,MATCH(36,'Watershed plans'!$AA$12:$AA$15,0)),"") | D85: =IFERROR(INDEX('Watershed plans'!$J$12:$J$15,MATCH(36,'Watershed plans'!$AA$12:$AA$15,0)),"") | E85: =IFERROR(INDEX('Watershed plans'!$K$12:$K$15,MATCH(36,'Watershed plans'!$AA$12:$AA$15,0)),"") | F85: =IFERROR(INDEX('Watershed plans'!$I$12:$I$15,MATCH(36,'Watershed plans'!$AA$12:$AA$15,0)),"") | G85: =IFERROR(INDEX('Watershed plans'!$Y$12:$Y$15,MATCH(36,'Watershed plans'!$AA$12:$AA$15,0)),"") | H85: =IF(ISNUMBER(D85),D85-D84,"") | I85: =IF(ISNUMBER(E85),E85-E84,"") | J85: =IF(AND(ISNUMBER(H85),H85<>0),I85/H85,"")
A86: 37 | B86: =IFERROR(INDEX('Watershed plans'!$F$12:$F$15,MATCH(37,'Watershed plans'!$AA$12:$AA$15,0)),"") | C86: =IFERROR(INDEX('Watershed plans'!$B$12:$B$15,MATCH(37,'Watershed plans'!$AA$12:$AA$15,0)),"") | D86: =IFERROR(INDEX('Watershed plans'!$J$12:$J$15,MATCH(37,'Watershed plans'!$AA$12:$AA$15,0)),"") | E86: =IFERROR(INDEX('Watershed plans'!$K$12:$K$15,MATCH(37,'Watershed plans'!$AA$12:$AA$15,0)),"") | F86: =IFERROR(INDEX('Watershed plans'!$I$12:$I$15,MATCH(37,'Watershed plans'!$AA$12:$AA$15,0)),"") | G86: =IFERROR(INDEX('Watershed plans'!$Y$12:$Y$15,MATCH(37,'Watershed plans'!$AA$12:$AA$15,0)),"") | H86: =IF(ISNUMBER(D86),D86-D85,"") | I86: =IF(ISNUMBER(E86),E86-E85,"") | J86: =IF(AND(ISNUMBER(H86),H86<>0),I86/H86,"")
A87: 38 | B87: =IFERROR(INDEX('Watershed plans'!$F$12:$F$15,MATCH(38,'Watershed plans'!$AA$12:$AA$15,0)),"") | C87: =IFERROR(INDEX('Watershed plans'!$B$12:$B$15,MATCH(38,'Watershed plans'!$AA$12:$AA$15,0)),"") | D87: =IFERROR(INDEX('Watershed plans'!$J$12:$J$15,MATCH(38,'Watershed plans'!$AA$12:$AA$15,0)),"") | E87: =IFERROR(INDEX('Watershed plans'!$K$12:$K$15,MATCH(38,'Watershed plans'!$AA$12:$AA$15,0)),"") | F87: =IFERROR(INDEX('Watershed plans'!$I$12:$I$15,MATCH(38,'Watershed plans'!$AA$12:$AA$15,0)),"") | G87: =IFERROR(INDEX('Watershed plans'!$Y$12:$Y$15,MATCH(38,'Watershed plans'!$AA$12:$AA$15,0)),"") | H87: =IF(ISNUMBER(D87),D87-D86,"") | I87: =IF(ISNUMBER(E87),E87-E86,"") | J87: =IF(AND(ISNUMBER(H87),H87<>0),I87/H87,"")
A88: 39 | B88: =IFERROR(INDEX('Watershed plans'!$F$12:$F$15,MATCH(39,'Watershed plans'!$AA$12:$AA$15,0)),"") | C88: =IFERROR(INDEX('Watershed plans'!$B$12:$B$15,MATCH(39,'Watershed plans'!$AA$12:$AA$15,0)),"") | D88: =IFERROR(INDEX('Watershed plans'!$J$12:$J$15,MATCH(39,'Watershed plans'!$AA$12:$AA$15,0)),"") | E88: =IFERROR(INDEX('Watershed plans'!$K$12:$K$15,MATCH(39,'Watershed plans'!$AA$12:$AA$15,0)),"") | F88: =IFERROR(INDEX('Watershed plans'!$I$12:$I$15,MATCH(39,'Watershed plans'!$AA$12:$AA$15,0)),"") | G88: =IFERROR(INDEX('Watershed plans'!$Y$12:$Y$15,MATCH(39,'Watershed plans'!$AA$12:$AA$15,0)),"") | H88: =IF(ISNUMBER(D88),D88-D87,"") | I88: =IF(ISNUMBER(E88),E88-E87,"") | J88: =IF(AND(ISNUMBER(H88),H88<>0),I88/H88,"")
A89: 40 | B89: =IFERROR(INDEX('Watershed plans'!$F$12:$F$15,MATCH(40,'Watershed plans'!$AA$12:$AA$15,0)),"") | C89: =IFERROR(INDEX('Watershed plans'!$B$12:$B$15,MATCH(40,'Watershed plans'!$AA$12:$AA$15,0)),"") | D89: =IFERROR(INDEX('Watershed plans'!$J$12:$J$15,MATCH(40,'Watershed plans'!$AA$12:$AA$15,0)),"") | E89: =IFERROR(INDEX('Watershed plans'!$K$12:$K$15,MATCH(40,'Watershed plans'!$AA$12:$AA$15,0)),"") | F89: =IFERROR(INDEX('Watershed plans'!$I$12:$I$15,MATCH(40,'Watershed plans'!$AA$12:$AA$15,0)),"") | G89: =IFERROR(INDEX('Watershed plans'!$Y$12:$Y$15,MATCH(40,'Watershed plans'!$AA$12:$AA$15,0)),"") | H89: =IF(ISNUMBER(D89),D89-D88,"") | I89: =IF(ISNUMBER(E89),E89-E88,"") | J89: =IF(AND(ISNUMBER(H89),H89<>0),I89/H89,"")
A92: Tentatively selected plan
A93: Plan number
A94: Plan | B94: =IFERROR(INDEX('Watershed plans'!$B$12:$B$15,MATCH($B$93,'Watershed plans'!$F$12:$F$15,0)),"n/a") -> n/a
A95: Lift (AAHU) | B95: =IFERROR(INDEX('Watershed plans'!$J$12:$J$15,MATCH($B$93,'Watershed plans'!$F$12:$F$15,0)),"n/a") -> n/a
A96: Average annual cost | B96: =IFERROR(INDEX('Watershed plans'!$K$12:$K$15,MATCH($B$93,'Watershed plans'!$F$12:$F$15,0)),"n/a") -> n/a
A97: Construction cost | B97: =IFERROR(INDEX('Watershed plans'!$I$12:$I$15,MATCH($B$93,'Watershed plans'!$F$12:$F$15,0)),"n/a") -> n/a
A98: Unit cost | B98: =IFERROR(INDEX('Watershed plans'!$Y$12:$Y$15,MATCH($B$93,'Watershed plans'!$F$12:$F$15,0)),"n/a") -> n/a
A99: In the final array | B99: =IFERROR(INDEX('Watershed plans'!$Z$12:$Z$15,MATCH($B$93,'Watershed plans'!$F$12:$F$15,0)),"n/a") -> n/a

Sheet IWR input
A1: IWR Planning Suite II input
A2: Paste-ready plan, output and cost columns for an independent re-run in IWR Planning Suite II (user-entered planning set; No Action is the first plan).
A4: Site planning sets
A5: Site | B5: Plan | C5: Output (AAHU above No Action) | D5: Cost (average annual, above No Action)
A6: A | B6: NA | C6: ='Site CE-ICA'!I6/10^in_out_dp -> 0 | D6: ='Site CE-ICA'!J6/10^in_cost_dp -> 0
A7: A | B7: A1 | C7: ='Site CE-ICA'!I7/10^in_out_dp -> 6.208 | D7: ='Site CE-ICA'!J7/10^in_cost_dp -> 18711.72
A8: A | B8: A2 | C8: ='Site CE-ICA'!I8/10^in_out_dp -> 3.085 | D8: ='Site CE-ICA'!J8/10^in_cost_dp -> 8420.27
A9: B | B9: NA | C9: ='Site CE-ICA'!I11/10^in_out_dp -> 0 | D9: ='Site CE-ICA'!J11/10^in_cost_dp -> 0
A10: B | B10: B1 | C10: ='Site CE-ICA'!I12/10^in_out_dp -> 5.93 | D10: ='Site CE-ICA'!J12/10^in_cost_dp -> 14033.79
A12: Watershed planning set (valid plans)
A13: Plan number | B13: Plan | C13: Output | D13: Cost
A14: ='Watershed plans'!F12 -> 1 | B14: ='Watershed plans'!B12 -> No Action | C14: =IF('Watershed plans'!C12=1,'Watershed plans'!J12,"") -> 0 | D14: =IF('Watershed plans'!C12=1,'Watershed plans'!K12,"") -> 0
A15: ='Watershed plans'!F13 | B15: ='Watershed plans'!B13 -> B | C15: =IF('Watershed plans'!C13=1,'Watershed plans'!J13,"") | D15: =IF('Watershed plans'!C13=1,'Watershed plans'!K13,"")
A16: ='Watershed plans'!F14 -> 2 | B16: ='Watershed plans'!B14 -> A | C16: =IF('Watershed plans'!C14=1,'Watershed plans'!J14,"") -> 6.208 | D16: =IF('Watershed plans'!C14=1,'Watershed plans'!K14,"") -> 18711.72
A17: ='Watershed plans'!F15 | B17: ='Watershed plans'!B15 -> A + B | C17: =IF('Watershed plans'!C15=1,'Watershed plans'!J15,"") | D17: =IF('Watershed plans'!C15=1,'Watershed plans'!K15,"")

Sheet Charts
A1: Charts: watershed cost-effectiveness and incremental cost
A2: Built from the watershed plans sheet; they update with the inputs.
A30: Other plans: lift | B30: Other plans: cost | C30: Frontier: lift | D30: Frontier: cost | E30: Best buys: lift | F30: Best buys: cost | G30: Step boxes: lift | H30: Step boxes: cost per unit | K30: (frontier order) | M30: TSP: lift | N30: TSP: cost
A31: =IF(AND('Watershed plans'!C12=1,'Watershed plans'!N12<>1),'Watershed plans'!J12,NA()) -> #N/A | B31: =IF(AND('Watershed plans'!C12=1,'Watershed plans'!N12<>1),'Watershed plans'!K12,NA()) -> #N/A | C31: =IFERROR(INDEX('Watershed plans'!$J$12:$J$15,MATCH(1,$K$31:$K$34,0)),NA()) -> 0 | D31: =IFERROR(INDEX('Watershed plans'!$K$12:$K$15,MATCH(1,$K$31:$K$34,0)),NA()) -> 0 | E31: =IFERROR(INDEX('Watershed plans'!$J$12:$J$15,MATCH(1,'Watershed plans'!$S$12:$S$15,0)),NA()) -> 0 | F31: =IFERROR(INDEX('Watershed plans'!$K$12:$K$15,MATCH(1,'Watershed plans'!$S$12:$S$15,0)),NA()) -> 0 | G31: =E31 -> 0 | H31: =IF(ISNUMBER(H32),0,NA()) -> 0 | K31: =IF('Watershed plans'!N12=1,1+SUMPRODUCT('Watershed plans'!$N$12:$N$15*(('Watershed plans'!$G$12:$G$15<'Watershed plans'!G12)+('Watershed plans'!$G$12:$G$15='Watershed plans'!G12)*('Watershed plans'!$A$12:$A$15<'Watershed plans'!A12))),0) -> 1 | M31: =IFERROR(INDEX('Watershed plans'!$J$12:$J$15,MATCH('Watershed summary'!$B$93,'Watershed plans'!$F$12:$F$15,0)),NA()) -> #N/A | N31: =IFERROR(INDEX('Watershed plans'!$K$12:$K$15,MATCH('Watershed summary'!$B$93,'Watershed plans'!$F$12:$F$15,0)),NA()) -> #N/A
A32: =IF(AND('Watershed plans'!C13=1,'Watershed plans'!N13<>1),'Watershed plans'!J13,NA()) -> #N/A | B32: =IF(AND('Watershed plans'!C13=1,'Watershed plans'!N13<>1),'Watershed plans'!K13,NA()) -> #N/A | C32: =IFERROR(INDEX('Watershed plans'!$J$12:$J$15,MATCH(2,$K$31:$K$34,0)),NA()) -> 6.208 | D32: =IFERROR(INDEX('Watershed plans'!$K$12:$K$15,MATCH(2,$K$31:$K$34,0)),NA()) -> 18711.72 | E32: =IFERROR(INDEX('Watershed plans'!$J$12:$J$15,MATCH(2,'Watershed plans'!$S$12:$S$15,0)),NA()) -> 6.208 | F32: =IFERROR(INDEX('Watershed plans'!$K$12:$K$15,MATCH(2,'Watershed plans'!$S$12:$S$15,0)),NA()) -> 18711.72 | G32: =E31 -> 0 | H32: =IFERROR(INDEX('Watershed plans'!$X$12:$X$15,MATCH(2,'Watershed plans'!$S$12:$S$15,0)),NA()) -> 3014.1302 | K32: =IF('Watershed plans'!N13=1,1+SUMPRODUCT('Watershed plans'!$N$12:$N$15*(('Watershed plans'!$G$12:$G$15<'Watershed plans'!G13)+('Watershed plans'!$G$12:$G$15='Watershed plans'!G13)*('Watershed plans'!$A$12:$A$15<'Watershed plans'!A13))),0) -> 0
A33: =IF(AND('Watershed plans'!C14=1,'Watershed plans'!N14<>1),'Watershed plans'!J14,NA()) -> #N/A | B33: =IF(AND('Watershed plans'!C14=1,'Watershed plans'!N14<>1),'Watershed plans'!K14,NA()) -> #N/A | C33: =IFERROR(INDEX('Watershed plans'!$J$12:$J$15,MATCH(3,$K$31:$K$34,0)),NA()) -> #N/A | D33: =IFERROR(INDEX('Watershed plans'!$K$12:$K$15,MATCH(3,$K$31:$K$34,0)),NA()) -> #N/A | E33: =IFERROR(INDEX('Watershed plans'!$J$12:$J$15,MATCH(3,'Watershed plans'!$S$12:$S$15,0)),NA()) -> #N/A | F33: =IFERROR(INDEX('Watershed plans'!$K$12:$K$15,MATCH(3,'Watershed plans'!$S$12:$S$15,0)),NA()) -> #N/A | G33: =E32 -> 6.208 | H33: =H32 -> 3014.1302 | K33: =IF('Watershed plans'!N14=1,1+SUMPRODUCT('Watershed plans'!$N$12:$N$15*(('Watershed plans'!$G$12:$G$15<'Watershed plans'!G14)+('Watershed plans'!$G$12:$G$15='Watershed plans'!G14)*('Watershed plans'!$A$12:$A$15<'Watershed plans'!A14))),0) -> 2
A34: =IF(AND('Watershed plans'!C15=1,'Watershed plans'!N15<>1),'Watershed plans'!J15,NA()) -> #N/A | B34: =IF(AND('Watershed plans'!C15=1,'Watershed plans'!N15<>1),'Watershed plans'!K15,NA()) -> #N/A | C34: =IFERROR(INDEX('Watershed plans'!$J$12:$J$15,MATCH(4,$K$31:$K$34,0)),NA()) -> #N/A | D34: =IFERROR(INDEX('Watershed plans'!$K$12:$K$15,MATCH(4,$K$31:$K$34,0)),NA()) -> #N/A | E34: =IFERROR(INDEX('Watershed plans'!$J$12:$J$15,MATCH(4,'Watershed plans'!$S$12:$S$15,0)),NA()) -> #N/A | F34: =IFERROR(INDEX('Watershed plans'!$K$12:$K$15,MATCH(4,'Watershed plans'!$S$12:$S$15,0)),NA()) -> #N/A | G34: =E32 -> 6.208 | H34: =IF(ISNUMBER(H32),0,NA()) -> 0 | K34: =IF('Watershed plans'!N15=1,1+SUMPRODUCT('Watershed plans'!$N$12:$N$15*(('Watershed plans'!$G$12:$G$15<'Watershed plans'!G15)+('Watershed plans'!$G$12:$G$15='Watershed plans'!G15)*('Watershed plans'!$A$12:$A$15<'Watershed plans'!A15))),0) -> 0
G35: =E32 -> 6.208 | H35: =IF(ISNUMBER(H36),0,NA()) -> #N/A
G36: =E32 -> 6.208 | H36: =IFERROR(INDEX('Watershed plans'!$X$12:$X$15,MATCH(3,'Watershed plans'!$S$12:$S$15,0)),NA()) -> #N/A
G37: =E33 -> #N/A | H37: =H36 -> #N/A
G38: =E33 -> #N/A | H38: =IF(ISNUMBER(H36),0,NA()) -> #N/A
G39: =E33 -> #N/A | H39: =IF(ISNUMBER(H40),0,NA()) -> #N/A
G40: =E33 -> #N/A | H40: =IFERROR(INDEX('Watershed plans'!$X$12:$X$15,MATCH(4,'Watershed plans'!$S$12:$S$15,0)),NA()) -> #N/A
G41: =E34 -> #N/A | H41: =H40 -> #N/A
G42: =E34 -> #N/A | H42: =IF(ISNUMBER(H40),0,NA()) -> #N/A

Sheet snap Parameters
B4: 0.03
B5: 50
B6: 12
B7: END
B8: END_OF_YEAR
B9: 2
B10: 3
B14: 0 | C14: 5 | D14: 50

Sheet snap Benefits
L6: 1 | M6: 1 | N6: 1
L7: 1 | M7: 4 | N7: 5
L8: 1 | M8: 2 | N8: 2.5
L9: 2 | M9: 2 | N9: 2
L10: 2 | M10: 5 | N10: 6
F11: 0.2 | G11: 0.2 | H11: 0.2 | I11: 3 | J11: 3 | K11: 3
F12: 0.2 | G12: 0.5 | H12: 0.7 | I12: 3 | J12: 3.5 | K12: 3.5
F13: 0.2 | G13: 0.6 | H13: 0.8 | I13: 3 | J13: 3 | K13: 3
F14: 0.4 | G14: 0.4 | H14: 0.4 | I14: 1 | J14: 1 | K14: 1
F15: 0.4 | G15: 0.4 | H15: 0.9 | I15: 1 | J15: 1 | K15: 2
O16: 0
O17: 1.5
O18: 0.5
O19: 0
O20: 2

Sheet snap Costs
D6: 0 | G6: 4
D7: 250000 | G7: 4
D8: 180000 | G8: 4
D9: 0 | G9: 4
D10: 300000 | G10: 4

Sheet snap Sites
C5: A1
C6: B1

Sheet snap Watershed plans
N12: 1 | R12: 1 | Z12: 1
N13: 0 | R13: 0 | Z13: 0
N14: 1 | R14: 1 | Z14: 1
N15: 1 | R15: 1 | Z15: 1

Sheet snap Watershed summary

Sheet snap Summary
G5: 0 | L5: 0
G6: 6.2075 | L6: 9752.3775
G7: 3.085 | L7: 7021.7118
G8: 0 | L8: 0
G9: 5.93 | L9: 11702.853

Sheet snap Site CE-ICA
L6: 1 | P6: 1
L7: 1 | P7: 1
L8: 1 | P8: 0
L11: 1 | P11: 1
L12: 1 | P12: 1

Sheet manifest
A1: ceica-calculator | B1: 2
A2: project | B2: 1 | C2: {"benefits":{"modules":[{"id":"hab","method":"HU","name":"Habitat","quantity_units":""},{"id":"rip","method":"INDEX_X_QUANTITY","name":"Riparian","quantity_units":"acres"},{"id":"wet","method":"AAHU","name":"Wetland","quantity_units":""}],"staf_mapping":"A","target_years":[0.0,5.0,50.0]},"cost_categories":[{"id":"construction","idc_applies":true,"name":"Construction"},{"id":"monitoring","idc_applies":false,"name":"Monitoring"},{"id":"adaptive_management","idc_applies":false,"name":"Adaptive management"}],"decisions":{"sites":{},"watershed":{"basis":null,"final_array":{},"steps":{},"tsp":null,"tsp_plan_type":"National Ecosystem Restoration (NER) plan","tsp_rationale":""}},"description":"","labels":{"annual_output_name":"Average annual habitat units","annual_output_short":"AAHU","lift_name":"Ecological lift","output_name":"Habitat units","output_short":"HU"},"name":"Mixed test","project_id":"golden-mixed","provenance":{},"report":{"contents":"FULL","date":"","prepared_by":"","status":"DRAFT","title":""},"schema_version":"ceica-project/3","settings":{"aahu_method":"TRAPEZOID","cost_decimals":2,"discount_rate":0.03,"idc_method":"END","idc_periods_per_year":12,"output_decimals":3,"period_of_analysis":50,"price_level":"","recurring_timing":"END_OF_YEAR"},"sites":[{"alternatives":[{"costs":{"annual_override":null,"construction_months":4.0,"first_costs":{"construction":0.0},"recurring":[]},"description":"","id":"NA","is_no_action":true,"name":"","outputs":[{"aahu":null,"module_id":"hab","quantity":[],"scores":{},"values":[1.0,1.0,1.0]},{"aahu":null,"module_id":"rip","quantity":[3.0,3.0,3.0],"scores":{},"values":[0.2,0.2,0.2]},{"aahu":0.0,"module_id":"wet","quantity":[],"scores":{},"values":[]}]},{"costs":{"annual_override":null,"construction_months":4.0,"first_costs":{"construction":250000.0},"recurring":[]},"description":"","id":"A1","is_no_action":false,"name":"","outputs":[{"aahu":null,"module_id":"hab","quantity":[],"scores":{},"values":[1.0,4.0,5.0]},{"aahu":null,"module_id":"rip","quantity":[3.0,3.5,3.5],"scores":{},"values":[0.2,0.5,0.7]},{"aahu":1.5,"module_id":"wet","quantity":[],"scores":{},"values":[]}]},{"costs":{"annual_override":null,"construction_months":4.0,"first_costs":{"construction":180000.0},"recurring":[]},"description":"","id":"A2","is_no_action":false,"name":"","outputs":[{"aahu":null,"module_id":"hab","quantity":[],"scores":{},"values":[1.0,2.0,2.5]},{"aahu":null,"module_id":"rip","quantity":[3.0,3.0,3.0],"scores":{},"values":[0.2,0.6,0.8]},{"aahu":0.5,"module_id":"wet","quantity":[],"scores":{},"values":[]}]}],"description":"","id":"A","name":"","staf_not_assessed":{},"staf_source":{}},{"alternatives":[{"costs":{"annual_override":null,"construction_months":4.0,"first_costs":{"construction":0.0},"recurring":[]},"description":"","id":"NA","is_no_action":true,"name":"","outputs":[{"aahu":null,"module_id":"hab","quantity":[],"scores":{},"values":[2.0,2.0,2.0]},{"aahu":null,"module_id":"rip","quantity":[1.0,1.0,1.0],"scores":{},"values":[0.4,0.4,0.4]},{"aahu":0.0,"module_id":"wet","quantity":[],"scores":{},"values":[]}]},{"costs":{"annual_override":null,"construction_months":4.0,"first_costs":{"construction":300000.0},"recurring":[]},"description":"","id":"B1","is_no_action":false,"name":"","outputs":[{"aahu":null,"module_id":"hab","quantity":[],"scores":{},"values":[2.0,5.0,6.0]},{"aahu":null,"module_id":"rip","quantity":[1.0,1.0,2.0],"scores":{},"values":[0.4,0.4,0.9]},{"aahu":2.0,"module_id":"wet","quantity":[],"scores":{},"values":[]}]}],"description":"","id":"B","name":"","staf_not_assessed":{},"staf_source":{}}],"watershed":{"carried":{},"mode":"RECOMMENDED","rules":[]}}
A3: meta | B3: 1 | C3: {"appVersion":"0.1.0","engineVersion":"1","format":"ceica-calculator","formatVersion":2,"layout":[{"cell":"B4","kind":"number","path":["settings","discount_rate"],"sheet":"Parameters"},{"cell":"B5","kind":"number","path":["settings","period_of_analysis"],"sheet":"Parameters"},{"cell":"B6","kind":"number","path":["settings","idc_periods_per_year"],"sheet":"Parameters"},{"cell":"B7","kind":"text","path":["settings","idc_method"],"sheet":"Parameters"},{"cell":"B8","kind":"text","path":["settings","recurring_timing"],"sheet":"Parameters"},{"cell":"B9","kind":"number","path":["settings","cost_decimals"],"sheet":"Parameters"},{"cell":"B10","kind":"number","path":["settings","output_decimals"],"sheet":"Parameters"},{"cell":"B14","kind":"number","path":["benefits","target_years",0],"sheet":"Parameters"},{"cell":"C14","kind":"number","path":["benefits","target_years",1],"sheet":"Parameters"},{"cell":"D14","kind":"number","path":["benefits","target_years",2],"sheet":"Parameters"},{"cell":"L6","kind":"optional","path":["sites",0,"alternatives",0,"outputs",{"module_id":"hab"},"values",0],"sheet":"Benefits"},{"cell":"M6","kind":"optional","path":["sites",0,"alternatives",0,"outputs",{"module_id":"hab"},"values",1],"sheet":"Benefits"},{"cell":"N6","kind":"optional","path":["sites",0,"alternatives",0,"outputs",{"module_id":"hab"},"values",2],"sheet":"Benefits"},{"cell":"L7","kind":"optional","path":["sites",0,"alternatives",1,"outputs",{"module_id":"hab"},"values",0],"sheet":"Benefits"},{"cell":"M7","kind":"optional","path":["sites",0,"alternatives",1,"outputs",{"module_id":"hab"},"values",1],"sheet":"Benefits"},{"cell":"N7","kind":"optional","path":["sites",0,"alternatives",1,"outputs",{"module_id":"hab"},"values",2],"sheet":"Benefits"},{"cell":"L8","kind":"optional","path":["sites",0,"alternatives",2,"outputs",{"module_id":"hab"},"values",0],"sheet":"Benefits"},{"cell":"M8","kind":"optional","path":["sites",0,"alternatives",2,"outputs",{"module_id":"hab"},"values",1],"sheet":"Benefits"},{"cell":"N8","kind":"optional","path":["sites",0,"alternatives",2,"outputs",{"module_id":"hab"},"values",2],"sheet":"Benefits"},{"cell":"L9","kind":"optional","path":["sites",1,"alternatives",0,"outputs",{"module_id":"hab"},"values",0],"sheet":"Benefits"},{"cell":"M9","kind":"optional","path":["sites",1,"alternatives",0,"outputs",{"module_id":"hab"},"values",1],"sheet":"Benefits"},{"cell":"N9","kind":"optional","path":["sites",1,"alternatives",0,"outputs",{"module_id":"hab"},"values",2],"sheet":"Benefits"},{"cell":"L10","kind":"optional","path":["sites",1,"alternatives",1,"outputs",{"module_id":"hab"},"values",0],"sheet":"Benefits"},{"cell":"M10","kind":"optional","path":["sites",1,"alternatives",1,"outputs",{"module_id":"hab"},"values",1],"sheet":"Benefits"},{"cell":"N10","kind":"optional","path":["sites",1,"alternatives",1,"outputs",{"module_id":"hab"},"values",2],"sheet":"Benefits"},{"cell":"F11","kind":"optional","path":["sites",0,"alternatives",0,"outputs",{"module_id":"rip"},"values",0],"sheet":"Benefits"},{"cell":"I11","kind":"optional","path":["sites",0,"alternatives",0,"outputs",{"module_id":"rip"},"quantity",0],"sheet":"Benefits"},{"cell":"G11","kind":"optional","path":["sites",0,"alternatives",0,"outputs",{"module_id":"rip"},"values",1],"sheet":"Benefits"},{"cell":"J11","kind":"optional","path":["sites",0,"alternatives",0,"outputs",{"module_id":"rip"},"quantity",1],"sheet":"Benefits"},{"cell":"H11","kind":"optional","path":["sites",0,"alternatives",0,"outputs",{"module_id":"rip"},"values",2],"sheet":"Benefits"},{"cell":"K11","kind":"optional","path":["sites",0,"alternatives",0,"outputs",{"module_id":"rip"},"quantity",2],"sheet":"Benefits"},{"cell":"F12","kind":"optional","path":["sites",0,"alternatives",1,"outputs",{"module_id":"rip"},"values",0],"sheet":"Benefits"},{"cell":"I12","kind":"optional","path":["sites",0,"alternatives",1,"outputs",{"module_id":"rip"},"quantity",0],"sheet":"Benefits"},{"cell":"G12","kind":"optional","path":["sites",0,"alternatives",1,"outputs",{"module_id":"rip"},"values",1],"sheet":"Benefits"},{"cell":"J12","kind":"optional","path":["sites",0,"alternatives",1,"outputs",{"module_id":"rip"},"quantity",1],"sheet":"Benefits"},{"cell":"H12","kind":"optional","path":["sites",0,"alternatives",1,"outputs",{"module_id":"rip"},"values",2],"sheet":"Benefits"},{"cell":"K12","kind":"optional","path":["sites",0,"alternatives",1,"outputs",{"module_id":"rip"},"quantity",2],"sheet":"Benefits"},{"cell":"F13","kind":"optional","path":["sites",0,"alternatives",2,"outputs",{"module_id":"rip"},"values",0],"sheet":"Benefits"},{"cell":"I13","kind":"optional","path":["sites",0,"alternatives",2,"outputs",{"module_id":"rip"},"quantity",0],"sheet":"Benefits"},{"cell":"G13","kind":"optional","path":["sites",0,"alternatives",2,"outputs",{"module_id":"rip"},"values",1],"sheet":"Benefits"},{"cell":"J13","kind":"optional","path":["sites",0,"alternatives",2,"outputs",{"module_id":"rip"},"quantity",1],"sheet":"Benefits"},{"cell":"H13","kind":"optional","path":["sites",0,"alternatives",2,"outputs",{"module_id":"rip"},"values",2],"sheet":"Benefits"},{"cell":"K13","kind":"optional","path":["sites",0,"alternatives",2,"outputs",{"module_id":"rip"},"quantity",2],"sheet":"Benefits"},{"cell":"F14","kind":"optional","path":["sites",1,"alternatives",0,"outputs",{"module_id":"rip"},"values",0],"sheet":"Benefits"},{"cell":"I14","kind":"optional","path":["sites",1,"alternatives",0,"outputs",{"module_id":"rip"},"quantity",0],"sheet":"Benefits"},{"cell":"G14","kind":"optional","path":["sites",1,"alternatives",0,"outputs",{"module_id":"rip"},"values",1],"sheet":"Benefits"},{"cell":"J14","kind":"optional","path":["sites",1,"alternatives",0,"outputs",{"module_id":"rip"},"quantity",1],"sheet":"Benefits"},{"cell":"H14","kind":"optional","path":["sites",1,"alternatives",0,"outputs",{"module_id":"rip"},"values",2],"sheet":"Benefits"},{"cell":"K14","kind":"optional","path":["sites",1,"alternatives",0,"outputs",{"module_id":"rip"},"quantity",2],"sheet":"Benefits"},{"cell":"F15","kind":"optional","path":["sites",1,"alternatives",1,"outputs",{"module_id":"rip"},"values",0],"sheet":"Benefits"},{"cell":"I15","kind":"optional","path":["sites",1,"alternatives",1,"outputs",{"module_id":"rip"},"quantity",0],"sheet":"Benefits"},{"cell":"G15","kind":"optional","path":["sites",1,"alternatives",1,"outputs",{"module_id":"rip"},"values",1],"sheet":"Benefits"},{"cell":"J15","kind":"optional","path":["sites",1,"alternatives",1,"outputs",{"module_id":"rip"},"quantity",1],"sheet":"Benefits"},{"cell":"H15","kind":"optional","path":["sites",1,"alternatives",1,"outputs",{"module_id":"rip"},"values",2],"sheet":"Benefits"},{"cell":"K15","kind":"optional","path":["sites",1,"alternatives",1,"outputs",{"module_id":"rip"},"quantity",2],"sheet":"Benefits"},{"cell":"O16","kind":"optional","path":["sites",0,"alternatives",0,"outputs",{"module_id":"wet"},"aahu"],"sheet":"Benefits"},{"cell":"O17","kind":"optional","path":["sites",0,"alternatives",1,"outputs",{"module_id":"wet"},"aahu"],"sheet":"Benefits"},{"cell":"O18","kind":"optional","path":["sites",0,"alternatives",2,"outputs",{"module_id":"wet"},"aahu"],"sheet":"Benefits"},{"cell":"O19","kind":"optional","path":["sites",1,"alternatives",0,"outputs",{"module_id":"wet"},"aahu"],"sheet":"Benefits"},{"cell":"O20","kind":"optional","path":["sites",1,"alternatives",1,"outputs",{"module_id":"wet"},"aahu"],"sheet":"Benefits"},{"cell":"D6","kind":"number","path":["sites",0,"alternatives",0,"costs","first_costs","construction"],"sheet":"Costs"},{"cell":"E6","kind":"number","path":["sites",0,"alternatives",0,"costs","first_costs","monitoring"],"sheet":"Costs"},{"cell":"F6","kind":"number","path":["sites",0,"alternatives",0,"costs","first_costs","adaptive_management"],"sheet":"Costs"},{"cell":"G6","kind":"number","path":["sites",0,"alternatives",0,"costs","construction_months"],"sheet":"Costs"},{"cell":"L6","kind":"optional","path":["sites",0,"alternatives",0,"costs","annual_override"],"sheet":"Costs"},{"cell":"D7","kind":"number","path":["sites",0,"alternatives",1,"costs","first_costs","construction"],"sheet":"Costs"},{"cell":"E7","kind":"number","path":["sites",0,"alternatives",1,"costs","first_costs","monitoring"],"sheet":"Costs"},{"cell":"F7","kind":"number","path":["sites",0,"alternatives",1,"costs","first_costs","adaptive_management"],"sheet":"Costs"},{"cell":"G7","kind":"number","path":["sites",0,"alternatives",1,"costs","construction_months"],"sheet":"Costs"},{"cell":"L7","kind":"optional","path":["sites",0,"alternatives",1,"costs","annual_override"],"sheet":"Costs"},{"cell":"D8","kind":"number","path":["sites",0,"alternatives",2,"costs","first_costs","construction"],"sheet":"Costs"},{"cell":"E8","kind":"number","path":["sites",0,"alternatives",2,"costs","first_costs","monitoring"],"sheet":"Costs"},{"cell":"F8","kind":"number","path":["sites",0,"alternatives",2,"costs","first_costs","adaptive_management"],"sheet":"Costs"},{"cell":"G8","kind":"number","path":["sites",0,"alternatives",2,"costs","construction_months"],"sheet":"Costs"},{"cell":"L8","kind":"optional","path":["sites",0,"alternatives",2,"costs","annual_override"],"sheet":"Costs"},{"cell":"D9","kind":"number","path":["sites",1,"alternatives",0,"costs","first_costs","construction"],"sheet":"Costs"},{"cell":"E9","kind":"number","path":["sites",1,"alternatives",0,"costs","first_costs","monitoring"],"sheet":"Costs"},{"cell":"F9","kind":"number","path":["sites",1,"alternatives",0,"costs","first_costs","adaptive_management"],"sheet":"Costs"},{"cell":"G9","kind":"number","path":["sites",1,"alternatives",0,"costs","construction_months"],"sheet":"Costs"},{"cell":"L9","kind":"optional","path":["sites",1,"alternatives",0,"costs","annual_override"],"sheet":"Costs"},{"cell":"D10","kind":"number","path":["sites",1,"alternatives",1,"costs","first_costs","construction"],"sheet":"Costs"},{"cell":"E10","kind":"number","path":["sites",1,"alternatives",1,"costs","first_costs","monitoring"],"sheet":"Costs"},{"cell":"F10","kind":"number","path":["sites",1,"alternatives",1,"costs","first_costs","adaptive_management"],"sheet":"Costs"},{"cell":"G10","kind":"number","path":["sites",1,"alternatives",1,"costs","construction_months"],"sheet":"Costs"},{"cell":"L10","kind":"optional","path":["sites",1,"alternatives",1,"costs","annual_override"],"sheet":"Costs"},{"cell":"C5","exported":"A1","kind":"rec","path":["decisions","sites","A","recommended_alt_id"],"sheet":"Sites"},{"cell":"C6","exported":"B1","kind":"rec","path":["decisions","sites","B","recommended_alt_id"],"sheet":"Sites"},{"cell":"Z12","kind":"final","path":["@final",12],"sheet":"Watershed plans"},{"cell":"Z13","kind":"final","path":["@final",13],"sheet":"Watershed plans"},{"cell":"Z14","kind":"final","path":["@final",14],"sheet":"Watershed plans"},{"cell":"Z15","kind":"final","path":["@final",15],"sheet":"Watershed plans"},{"cell":"K50","kind":"text","path":["@worth",0],"sheet":"Watershed summary"},{"cell":"L50","kind":"text","path":["@why",0],"sheet":"Watershed summary"},{"cell":"K51","kind":"text","path":["@worth",1],"sheet":"Watershed summary"},{"cell":"L51","kind":"text","path":["@why",1],"sheet":"Watershed summary"},{"cell":"K52","kind":"text","path":["@worth",2],"sheet":"Watershed summary"},{"cell":"L52","kind":"text","path":["@why",2],"sheet":"Watershed summary"},{"cell":"K53","kind":"text","path":["@worth",3],"sheet":"Watershed summary"},{"cell":"L53","kind":"text","path":["@why",3],"sheet":"Watershed summary"},{"cell":"K54","kind":"text","path":["@worth",4],"sheet":"Watershed summary"},{"cell":"L54","kind":"text","path":["@why",4],"sheet":"Watershed summary"},{"cell":"K55","kind":"text","path":["@worth",5],"sheet":"Watershed summary"},{"cell":"L55","kind":"text","path":["@why",5],"sheet":"Watershed summary"},{"cell":"K56","kind":"text","path":["@worth",6],"sheet":"Watershed summary"},{"cell":"L56","kind":"text","path":["@why",6],"sheet":"Watershed summary"},{"cell":"K57","kind":"text","path":["@worth",7],"sheet":"Watershed summary"},{"cell":"L57","kind":"text","path":["@why",7],"sheet":"Watershed summary"},{"cell":"K58","kind":"text","path":["@worth",8],"sheet":"Watershed summary"},{"cell":"L58","kind":"text","path":["@why",8],"sheet":"Watershed summary"},{"cell":"K59","kind":"text","path":["@worth",9],"sheet":"Watershed summary"},{"cell":"L59","kind":"text","path":["@why",9],"sheet":"Watershed summary"},{"cell":"K60","kind":"text","path":["@worth",10],"sheet":"Watershed summary"},{"cell":"L60","kind":"text","path":["@why",10],"sheet":"Watershed summary"},{"cell":"K61","kind":"text","path":["@worth",11],"sheet":"Watershed summary"},{"cell":"L61","kind":"text","path":["@why",11],"sheet":"Watershed summary"},{"cell":"K62","kind":"text","path":["@worth",12],"sheet":"Watershed summary"},{"cell":"L62","kind":"text","path":["@why",12],"sheet":"Watershed summary"},{"cell":"K63","kind":"text","path":["@worth",13],"sheet":"Watershed summary"},{"cell":"L63","kind":"text","path":["@why",13],"sheet":"Watershed summary"},{"cell":"K64","kind":"text","path":["@worth",14],"sheet":"Watershed summary"},{"cell":"L64","kind":"text","path":["@why",14],"sheet":"Watershed summary"},{"cell":"K65","kind":"text","path":["@worth",15],"sheet":"Watershed summary"},{"cell":"L65","kind":"text","path":["@why",15],"sheet":"Watershed summary"},{"cell":"K66","kind":"text","path":["@worth",16],"sheet":"Watershed summary"},{"cell":"L66","kind":"text","path":["@why",16],"sheet":"Watershed summary"},{"cell":"K67","kind":"text","path":["@worth",17],"sheet":"Watershed summary"},{"cell":"L67","kind":"text","path":["@why",17],"sheet":"Watershed summary"},{"cell":"K68","kind":"text","path":["@worth",18],"sheet":"Watershed summary"},{"cell":"L68","kind":"text","path":["@why",18],"sheet":"Watershed summary"},{"cell":"K69","kind":"text","path":["@worth",19],"sheet":"Watershed summary"},{"cell":"L69","kind":"text","path":["@why",19],"sheet":"Watershed summary"},{"cell":"K70","kind":"text","path":["@worth",20],"sheet":"Watershed summary"},{"cell":"L70","kind":"text","path":["@why",20],"sheet":"Watershed summary"},{"cell":"K71","kind":"text","path":["@worth",21],"sheet":"Watershed summary"},{"cell":"L71","kind":"text","path":["@why",21],"sheet":"Watershed summary"},{"cell":"K72","kind":"text","path":["@worth",22],"sheet":"Watershed summary"},{"cell":"L72","kind":"text","path":["@why",22],"sheet":"Watershed summary"},{"cell":"K73","kind":"text","path":["@worth",23],"sheet":"Watershed summary"},{"cell":"L73","kind":"text","path":["@why",23],"sheet":"Watershed summary"},{"cell":"K74","kind":"text","path":["@worth",24],"sheet":"Watershed summary"},{"cell":"L74","kind":"text","path":["@why",24],"sheet":"Watershed summary"},{"cell":"K75","kind":"text","path":["@worth",25],"sheet":"Watershed summary"},{"cell":"L75","kind":"text","path":["@why",25],"sheet":"Watershed summary"},{"cell":"K76","kind":"text","path":["@worth",26],"sheet":"Watershed summary"},{"cell":"L76","kind":"text","path":["@why",26],"sheet":"Watershed summary"},{"cell":"K77","kind":"text","path":["@worth",27],"sheet":"Watershed summary"},{"cell":"L77","kind":"text","path":["@why",27],"sheet":"Watershed summary"},{"cell":"K78","kind":"text","path":["@worth",28],"sheet":"Watershed summary"},{"cell":"L78","kind":"text","path":["@why",28],"sheet":"Watershed summary"},{"cell":"K79","kind":"text","path":["@worth",29],"sheet":"Watershed summary"},{"cell":"L79","kind":"text","path":["@why",29],"sheet":"Watershed summary"},{"cell":"K80","kind":"text","path":["@worth",30],"sheet":"Watershed summary"},{"cell":"L80","kind":"text","path":["@why",30],"sheet":"Watershed summary"},{"cell":"K81","kind":"text","path":["@worth",31],"sheet":"Watershed summary"},{"cell":"L81","kind":"text","path":["@why",31],"sheet":"Watershed summary"},{"cell":"K82","kind":"text","path":["@worth",32],"sheet":"Watershed summary"},{"cell":"L82","kind":"text","path":["@why",32],"sheet":"Watershed summary"},{"cell":"K83","kind":"text","path":["@worth",33],"sheet":"Watershed summary"},{"cell":"L83","kind":"text","path":["@why",33],"sheet":"Watershed summary"},{"cell":"K84","kind":"text","path":["@worth",34],"sheet":"Watershed summary"},{"cell":"L84","kind":"text","path":["@why",34],"sheet":"Watershed summary"},{"cell":"K85","kind":"text","path":["@worth",35],"sheet":"Watershed summary"},{"cell":"L85","kind":"text","path":["@why",35],"sheet":"Watershed summary"},{"cell":"K86","kind":"text","path":["@worth",36],"sheet":"Watershed summary"},{"cell":"L86","kind":"text","path":["@why",36],"sheet":"Watershed summary"},{"cell":"K87","kind":"text","path":["@worth",37],"sheet":"Watershed summary"},{"cell":"L87","kind":"text","path":["@why",37],"sheet":"Watershed summary"},{"cell":"K88","kind":"text","path":["@worth",38],"sheet":"Watershed summary"},{"cell":"L88","kind":"text","path":["@why",38],"sheet":"Watershed summary"},{"cell":"K89","kind":"text","path":["@worth",39],"sheet":"Watershed summary"},{"cell":"L89","kind":"text","path":["@why",39],"sheet":"Watershed summary"},{"cell":"B93","kind":"tsp","path":["@tsp"],"sheet":"Watershed summary"}],"liveWatershed":true,"planBits":[4,5],"planRowKeys":{"12":"","13":"B=B1","14":"A=A1","15":"A=A1;B=B1"},"planSites":["A","B"],"projectDigest":"8030b2b0f57f","schemaVersion":3}
