Workbook
Name in_rate: Parameters!$B$4
Name in_poa: Parameters!$B$5
Name in_ppy: Parameters!$B$6
Name in_idc_method: Parameters!$B$7
Name in_timing: Parameters!$B$8
Name in_cost_dp: Parameters!$B$9
Name in_out_dp: Parameters!$B$10
Name calc_crf: Parameters!$B$11
Name out_status: 'Read me'!$B$10
Name out_changed: 'Read me'!$B$11
Name out_mismatch: 'Read me'!$B$12

Sheet Read me
A1: Mixed test: CE/ICA calculator
A2: Cost-effectiveness and incremental cost analysis, as live formulas.
A4: Study | B4: Mixed test
A5: Generated by | B5: CEICA 1.0.0 (engine 1)
A6: Project digest | B6: 89aea71be748
A7: Discount rate | B7: 3 percent
A8: Period of analysis | B8: 50 years
A10: Status | B10: =IF(B11=0,IF(B12=0,"Unchanged: matches the CEICA export","ERROR: results differ from the export although no input changed"),"Edited: "&B11&" input cells changed since the export")
A11: Inputs changed | B11: =(SUMPRODUCT(1*(Parameters!B4:B10<>'snap Parameters'!B4:B10))+SUMPRODUCT(1*(Parameters!B14:D14<>'snap Parameters'!B14:D14))+SUMPRODUCT(1*(Benefits!L6:N10<>'snap Benefits'!L6:N10))+SUMPRODUCT(1*(Benefits!F11:K15<>'snap Benefits'!F11:K15))+SUMPRODUCT(1*(Benefits!O16:O20<>'snap Benefits'!O16:O20))+SUMPRODUCT(1*(Costs!D6:G10<>'snap Costs'!D6:G10))+SUMPRODUCT(1*(Costs!L6:L10<>'snap Costs'!L6:L10))+SUMPRODUCT(1*(Sites!C5:C6<>'snap Sites'!C5:C6)))
A12: Results that differ from the export | B12: =(SUMPRODUCT(1*(ABS(Summary!G5:G9-'snap Summary'!G5:G9)>1e-06))+SUMPRODUCT(1*(ABS(Summary!L5:L9-'snap Summary'!L5:L9)>0.0001))+SUMPRODUCT(1*('Site CE-ICA'!L6:L8<>'snap Site CE-ICA'!L6:L8))+SUMPRODUCT(1*('Site CE-ICA'!P6:P8<>'snap Site CE-ICA'!P6:P8))+SUMPRODUCT(1*('Site CE-ICA'!L11:L12<>'snap Site CE-ICA'!L11:L12))+SUMPRODUCT(1*('Site CE-ICA'!P11:P12<>'snap Site CE-ICA'!P11:P12)))
A14: How to use
A15: - Orange cells are inputs; grey cells are formulas. Sheets are protected (password 'ceica') only to prevent accidental edits.
A16: - Change any orange cell: annualization, site CE/ICA, the watershed plans and the summary update. Changed inputs turn yellow.
A17: - To add sites, alternatives or years, make the change in CEICA and export again.
A18: - Import this workbook in CEICA to bring your changes back into the project.
A20: Legend
A21: Input
A22: Formula
A23: Changed since export

Sheet Parameters
A1: Parameters
A2: Economics and conventions. Orange cells are inputs.
A3: Parameter | B3: Value
A4: Discount rate | B4: 0.03
A5: Period of analysis (years) | B5: 50
A6: Interest during construction: periods per year | B6: 12
A7: Interest during construction: spending in each period (END, MIDDLE or START) | B7: END
A8: OMRRR discounting (END_OF_YEAR or MID_YEAR) | B8: END_OF_YEAR
A9: Cost decimals kept for CE/ICA | B9: 2
A10: Output decimals kept for CE/ICA | B10: 3
A11: Capital recovery factor | B11: =IF(in_rate=0,1/in_poa,in_rate*(1+in_rate)^in_poa/((1+in_rate)^in_poa-1))
A13: Target years | B13: Year 1 | C13: Year 2 | D13: Year 3
A14: Years (first to last) | B14: 0 | C14: 5 | D14: 50

Sheet Benefits
A1: Benefits: habitat units by module
A2: One row per module, site and alternative; the Summary adds the modules' averages. Habitat: habitat units entered at each target year; Riparian: index x quantity at each target year; Wetland: the average entered directly. Averages are the area under straight lines between target years.
A4: Key | B4: Site | C4: Alternative | D4: Module | E4: Method | F4: Index (0 to 1) | I4: Quantity | L4: Habitat units (HU) | O4: Average (AAHU)
F5: =Parameters!$B$14 | G5: =Parameters!$C$14 | H5: =Parameters!$D$14 | I5: =Parameters!$B$14 | J5: =Parameters!$C$14 | K5: =Parameters!$D$14 | L5: =Parameters!$B$14 | M5: =Parameters!$C$14 | N5: =Parameters!$D$14
A6: =B6&"|"&C6 | B6: A | C6: NA | D6: Habitat | E6: Habitat units | L6: 1 | M6: 1 | N6: 1 | O6: =SUMPRODUCT($M$5:$N$5-$L$5:$M$5,(M6:N6+L6:M6)/2)/($N$5-$L$5)
A7: =B7&"|"&C7 | B7: A | C7: A1 | D7: Habitat | E7: Habitat units | L7: 1 | M7: 4 | N7: 5 | O7: =SUMPRODUCT($M$5:$N$5-$L$5:$M$5,(M7:N7+L7:M7)/2)/($N$5-$L$5)
A8: =B8&"|"&C8 | B8: A | C8: A2 | D8: Habitat | E8: Habitat units | L8: 1 | M8: 2 | N8: 2.5 | O8: =SUMPRODUCT($M$5:$N$5-$L$5:$M$5,(M8:N8+L8:M8)/2)/($N$5-$L$5)
A9: =B9&"|"&C9 | B9: B | C9: NA | D9: Habitat | E9: Habitat units | L9: 2 | M9: 2 | N9: 2 | O9: =SUMPRODUCT($M$5:$N$5-$L$5:$M$5,(M9:N9+L9:M9)/2)/($N$5-$L$5)
A10: =B10&"|"&C10 | B10: B | C10: B1 | D10: Habitat | E10: Habitat units | L10: 2 | M10: 5 | N10: 6 | O10: =SUMPRODUCT($M$5:$N$5-$L$5:$M$5,(M10:N10+L10:M10)/2)/($N$5-$L$5)
A11: =B11&"|"&C11 | B11: A | C11: NA | D11: Riparian | E11: Index x quantity | F11: 0.2 | G11: 0.2 | H11: 0.2 | I11: 3 | J11: 3 | K11: 3 | L11: =F11*I11 | M11: =G11*J11 | N11: =H11*K11 | O11: =SUMPRODUCT($M$5:$N$5-$L$5:$M$5,(M11:N11+L11:M11)/2)/($N$5-$L$5)
A12: =B12&"|"&C12 | B12: A | C12: A1 | D12: Riparian | E12: Index x quantity | F12: 0.2 | G12: 0.5 | H12: 0.7 | I12: 3 | J12: 3.5 | K12: 3.5 | L12: =F12*I12 | M12: =G12*J12 | N12: =H12*K12 | O12: =SUMPRODUCT($M$5:$N$5-$L$5:$M$5,(M12:N12+L12:M12)/2)/($N$5-$L$5)
A13: =B13&"|"&C13 | B13: A | C13: A2 | D13: Riparian | E13: Index x quantity | F13: 0.2 | G13: 0.6 | H13: 0.8 | I13: 3 | J13: 3 | K13: 3 | L13: =F13*I13 | M13: =G13*J13 | N13: =H13*K13 | O13: =SUMPRODUCT($M$5:$N$5-$L$5:$M$5,(M13:N13+L13:M13)/2)/($N$5-$L$5)
A14: =B14&"|"&C14 | B14: B | C14: NA | D14: Riparian | E14: Index x quantity | F14: 0.4 | G14: 0.4 | H14: 0.4 | I14: 1 | J14: 1 | K14: 1 | L14: =F14*I14 | M14: =G14*J14 | N14: =H14*K14 | O14: =SUMPRODUCT($M$5:$N$5-$L$5:$M$5,(M14:N14+L14:M14)/2)/($N$5-$L$5)
A15: =B15&"|"&C15 | B15: B | C15: B1 | D15: Riparian | E15: Index x quantity | F15: 0.4 | G15: 0.4 | H15: 0.9 | I15: 1 | J15: 1 | K15: 2 | L15: =F15*I15 | M15: =G15*J15 | N15: =H15*K15 | O15: =SUMPRODUCT($M$5:$N$5-$L$5:$M$5,(M15:N15+L15:M15)/2)/($N$5-$L$5)
A16: =B16&"|"&C16 | B16: A | C16: NA | D16: Wetland | E16: Average annual value | O16: 0
A17: =B17&"|"&C17 | B17: A | C17: A1 | D17: Wetland | E17: Average annual value | O17: 1.5
A18: =B18&"|"&C18 | B18: A | C18: A2 | D18: Wetland | E18: Average annual value | O18: 0.5
A19: =B19&"|"&C19 | B19: B | C19: NA | D19: Wetland | E19: Average annual value | O19: 0
A20: =B20&"|"&C20 | B20: B | C20: B1 | D20: Wetland | E20: Average annual value | O20: 2

Sheet Costs
A1: Costs: first costs, interest during construction and OMRRR
A2: First costs are base-year lump sums. Interest during construction accrues on the categories marked *, spent evenly over the construction months.
N3: Average annual cost by part
A4: Key | B4: Site | C4: Alternative | D4: Construction * | E4: Monitoring | F4: Adaptive management | G4: Construction months | H4: IDC base | I4: Interest during construction | J4: OMRRR present value | K4: Total present value | L4: Average annual cost entered | M4: Average annual cost | N4: Construction | O4: Monitoring | P4: Adaptive management | Q4: Interest during construction | R4: OMRRR
D5: construction | E5: monitoring | F5: adaptive_management
A6: =B6&"|"&C6 | B6: A | C6: NA | D6: 0 | G6: 4 | H6: =D6 | I6: =IF(OR(G6=0,in_rate=0,H6=0),0,H6/G6*(IF(in_idc_method="START",1+((1+in_rate)^(1/in_ppy)-1),IF(in_idc_method="MIDDLE",1+((1+in_rate)^(1/in_ppy)-1)/2,1))*((1+in_rate)^(G6/in_ppy)-1)/((1+in_rate)^(1/in_ppy)-1)-G6)) | J6: =SUMIFS(OMRRR!$S$5:$S$5,OMRRR!$A$5:$A$5,A6) | K6: =SUM(D6:F6)+I6+J6 | M6: =IF(ISNUMBER(L6),L6,calc_crf*K6) | N6: =calc_crf*D6 | O6: =calc_crf*E6 | P6: =calc_crf*F6 | Q6: =calc_crf*I6 | R6: =calc_crf*J6
A7: =B7&"|"&C7 | B7: A | C7: A1 | D7: lots | G7: 4 | H7: =D7 | I7: =IF(OR(G7=0,in_rate=0,H7=0),0,H7/G7*(IF(in_idc_method="START",1+((1+in_rate)^(1/in_ppy)-1),IF(in_idc_method="MIDDLE",1+((1+in_rate)^(1/in_ppy)-1)/2,1))*((1+in_rate)^(G7/in_ppy)-1)/((1+in_rate)^(1/in_ppy)-1)-G7)) | J7: =SUMIFS(OMRRR!$S$5:$S$5,OMRRR!$A$5:$A$5,A7) | K7: =SUM(D7:F7)+I7+J7 | M7: =IF(ISNUMBER(L7),L7,calc_crf*K7) | N7: =calc_crf*D7 | O7: =calc_crf*E7 | P7: =calc_crf*F7 | Q7: =calc_crf*I7 | R7: =calc_crf*J7
A8: =B8&"|"&C8 | B8: A | C8: A2 | D8: 180000 | G8: 4 | H8: =D8 | I8: =IF(OR(G8=0,in_rate=0,H8=0),0,H8/G8*(IF(in_idc_method="START",1+((1+in_rate)^(1/in_ppy)-1),IF(in_idc_method="MIDDLE",1+((1+in_rate)^(1/in_ppy)-1)/2,1))*((1+in_rate)^(G8/in_ppy)-1)/((1+in_rate)^(1/in_ppy)-1)-G8)) | J8: =SUMIFS(OMRRR!$S$5:$S$5,OMRRR!$A$5:$A$5,A8) | K8: =SUM(D8:F8)+I8+J8 | M8: =IF(ISNUMBER(L8),L8,calc_crf*K8) | N8: =calc_crf*D8 | O8: =calc_crf*E8 | P8: =calc_crf*F8 | Q8: =calc_crf*I8 | R8: =calc_crf*J8
A9: =B9&"|"&C9 | B9: B | C9: NA | D9: 0 | G9: 4 | H9: =D9 | I9: =IF(OR(G9=0,in_rate=0,H9=0),0,H9/G9*(IF(in_idc_method="START",1+((1+in_rate)^(1/in_ppy)-1),IF(in_idc_method="MIDDLE",1+((1+in_rate)^(1/in_ppy)-1)/2,1))*((1+in_rate)^(G9/in_ppy)-1)/((1+in_rate)^(1/in_ppy)-1)-G9)) | J9: =SUMIFS(OMRRR!$S$5:$S$5,OMRRR!$A$5:$A$5,A9) | K9: =SUM(D9:F9)+I9+J9 | M9: =IF(ISNUMBER(L9),L9,calc_crf*K9) | N9: =calc_crf*D9 | O9: =calc_crf*E9 | P9: =calc_crf*F9 | Q9: =calc_crf*I9 | R9: =calc_crf*J9
A10: =B10&"|"&C10 | B10: B | C10: B1 | D10: 300000 | G10: 4 | H10: =D10 | I10: =IF(OR(G10=0,in_rate=0,H10=0),0,H10/G10*(IF(in_idc_method="START",1+((1+in_rate)^(1/in_ppy)-1),IF(in_idc_method="MIDDLE",1+((1+in_rate)^(1/in_ppy)-1)/2,1))*((1+in_rate)^(G10/in_ppy)-1)/((1+in_rate)^(1/in_ppy)-1)-G10)) | J10: =SUMIFS(OMRRR!$S$5:$S$5,OMRRR!$A$5:$A$5,A10) | K10: =SUM(D10:F10)+I10+J10 | M10: =IF(ISNUMBER(L10),L10,calc_crf*K10) | N10: =calc_crf*D10 | O10: =calc_crf*E10 | P10: =calc_crf*F10 | Q10: =calc_crf*I10 | R10: =calc_crf*J10

Sheet OMRRR
A1: OMRRR: recurring operation, maintenance, repair, replacement and rehabilitation
A2: Each item costs the amount per occurrence every N years from the first year to the last (blank: every N years through the period of analysis). Basis: FIXED amount, PERCENT of a first-cost category, or RATE x quantity.
A4: Key | B4: Site | C4: Alternative | D4: Item | E4: Basis | F4: Amount | G4: Percent | H4: Category | I4: Unit rate | J4: Quantity | K4: Every N years | L4: First year | M4: Last year | N4: Amount per occurrence | O4: First | P4: Last | Q4: Occurrences | R4: Present value, end of year | S4: Present value

Sheet Summary
A1: Summary of inputs to CE/ICA
A2: Lift is each alternative's AAHU above No Action; the CE/ICA cost is its average annual cost above No Action.
A4: Key | B4: Site | C4: Alternative | D4: Name | E4: No Action | F4: Outputs (AAHU) | G4: Lift (AAHU) | H4: Construction cost | I4: First costs | J4: Interest during construction | K4: OMRRR present value | L4: Average annual cost | M4: Cost above No Action | N4: Unit cost ($/AAHU)
A5: =B5&"|"&C5 | B5: A | C5: NA | D5: NA | E5: 1 | F5: =SUMIFS(Benefits!$O$6:$O$20,Benefits!$A$6:$A$20,A5) | G5: =F5-$F$5 | H5: =Costs!D6 | I5: =SUM(Costs!D6:F6) | J5: =Costs!I6 | K5: =Costs!J6 | L5: =Costs!M6 | M5: =L5-$L$5 | N5: =IF(G5>0,M5/G5,"n/a")
A6: =B6&"|"&C6 | B6: A | C6: A1 | D6: A1 | E6: 0 | F6: =SUMIFS(Benefits!$O$6:$O$20,Benefits!$A$6:$A$20,A6) | G6: =F6-$F$5 | H6: =Costs!D7 | I6: =SUM(Costs!D7:F7) | J6: =Costs!I7 | K6: =Costs!J7 | L6: =Costs!M7 | M6: =L6-$L$5 | N6: =IF(G6>0,M6/G6,"n/a")
A7: =B7&"|"&C7 | B7: A | C7: A2 | D7: A2 | E7: 0 | F7: =SUMIFS(Benefits!$O$6:$O$20,Benefits!$A$6:$A$20,A7) | G7: =F7-$F$5 | H7: =Costs!D8 | I7: =SUM(Costs!D8:F8) | J7: =Costs!I8 | K7: =Costs!J8 | L7: =Costs!M8 | M7: =L7-$L$5 | N7: =IF(G7>0,M7/G7,"n/a")
A8: =B8&"|"&C8 | B8: B | C8: NA | D8: NA | E8: 1 | F8: =SUMIFS(Benefits!$O$6:$O$20,Benefits!$A$6:$A$20,A8) | G8: =F8-$F$8 | H8: =Costs!D9 | I8: =SUM(Costs!D9:F9) | J8: =Costs!I9 | K8: =Costs!J9 | L8: =Costs!M9 | M8: =L8-$L$8 | N8: =IF(G8>0,M8/G8,"n/a")
A9: =B9&"|"&C9 | B9: B | C9: B1 | D9: B1 | E9: 0 | F9: =SUMIFS(Benefits!$O$6:$O$20,Benefits!$A$6:$A$20,A9) | G9: =F9-$F$8 | H9: =Costs!D10 | I9: =SUM(Costs!D10:F10) | J9: =Costs!I10 | K9: =Costs!J10 | L9: =Costs!M10 | M9: =L9-$L$8 | N9: =IF(G9>0,M9/G9,"n/a")

Sheet Site CE-ICA
A1: Site-by-site CE/ICA
A2: Cost-effective: no alternative gives the same output for less, or more output for no more. Best buy: on the lower hull from No Action (IWR Planning Suite II rules).
A4: Key | B4: Site | C4: Alternative | D4: Name | E4: No Action | F4: Ordinal | G4: Lift (AAHU) | H4: Cost above No Action | I4: Lift (scaled) | J4: Cost (scaled) | K4: Dominated by | L4: Cost-effective | M4: Candidate | N4: Slope in (max) | O4: Slope out (min) | P4: Best buy | Q4: Best-buy step | R4: Previous lift (scaled) | S4: Previous cost (scaled) | T4: Incremental output | U4: Incremental cost | V4: Incremental cost per unit | W4: Unit cost | X4: Recommended
B5: A
A6: =B6&"|"&C6 | B6: A | C6: NA | D6: NA | E6: 1 | F6: 1 | G6: =Summary!G5 | H6: =Summary!M5 | I6: =ROUND(G6*10^in_out_dp,0) | J6: =ROUND(H6*10^in_cost_dp,0) | K6: =SUMPRODUCT(($I$6:$I$8=I6)*($J$6:$J$8<J6)+($I$6:$I$8>I6)*($J$6:$J$8<=J6)) | L6: =IF(OR(E6=1,K6=0),1,0) | M6: =IF(AND(L6=1,E6=0,I6>0),1,0) | N6: =IF(M6=1,MAX(J6/I6,SUMPRODUCT(MAX(((J6-$J$6:$J$8)*($M$6:$M$8*($I$6:$I$8<I6)))/((I6-$I$6:$I$8)*($M$6:$M$8*($I$6:$I$8<I6))+1-($M$6:$M$8*($I$6:$I$8<I6)))-(1-($M$6:$M$8*($I$6:$I$8<I6)))*1E+300))),0) | O6: =IF(M6=1,SUMPRODUCT(MIN(((($J$6:$J$8-J6)*($M$6:$M$8*($I$6:$I$8>I6)))/(($I$6:$I$8-I6)*($M$6:$M$8*($I$6:$I$8>I6))+1-($M$6:$M$8*($I$6:$I$8>I6)))+(1-($M$6:$M$8*($I$6:$I$8>I6)))*1E+300))),0) | P6: =IF(E6=1,1,IF(AND(M6=1,N6<=O6),1,0)) | Q6: =IF(P6=1,1+SUMPRODUCT($P$6:$P$8*(($I$6:$I$8<I6)+($I$6:$I$8=I6)*($F$6:$F$8<F6))),0) | R6: =IF(Q6<=1,0,SUMPRODUCT(($Q$6:$Q$8=Q6-1)*$I$6:$I$8)) | S6: =IF(Q6<=1,0,SUMPRODUCT(($Q$6:$Q$8=Q6-1)*$J$6:$J$8)) | T6: =IF(Q6=0,"",(I6-R6)/10^in_out_dp) | U6: =IF(Q6=0,"",(J6-S6)/10^in_cost_dp) | V6: =IF(Q6=0,"",IF(I6=R6,0,U6/T6)) | W6: =IF(I6>0,(J6/10^in_cost_dp)/(I6/10^in_out_dp),"n/a") | X6: =IF(Sites!$C$5=C6,1,0)
A7: =B7&"|"&C7 | B7: A | C7: A1 | D7: A1 | E7: 0 | F7: 2 | G7: =Summary!G6 | H7: =Summary!M6 | I7: =ROUND(G7*10^in_out_dp,0) | J7: =ROUND(H7*10^in_cost_dp,0) | K7: =SUMPRODUCT(($I$6:$I$8=I7)*($J$6:$J$8<J7)+($I$6:$I$8>I7)*($J$6:$J$8<=J7)) | L7: =IF(OR(E7=1,K7=0),1,0) | M7: =IF(AND(L7=1,E7=0,I7>0),1,0) | N7: =IF(M7=1,MAX(J7/I7,SUMPRODUCT(MAX(((J7-$J$6:$J$8)*($M$6:$M$8*($I$6:$I$8<I7)))/((I7-$I$6:$I$8)*($M$6:$M$8*($I$6:$I$8<I7))+1-($M$6:$M$8*($I$6:$I$8<I7)))-(1-($M$6:$M$8*($I$6:$I$8<I7)))*1E+300))),0) | O7: =IF(M7=1,SUMPRODUCT(MIN(((($J$6:$J$8-J7)*($M$6:$M$8*($I$6:$I$8>I7)))/(($I$6:$I$8-I7)*($M$6:$M$8*($I$6:$I$8>I7))+1-($M$6:$M$8*($I$6:$I$8>I7)))+(1-($M$6:$M$8*($I$6:$I$8>I7)))*1E+300))),0) | P7: =IF(E7=1,1,IF(AND(M7=1,N7<=O7),1,0)) | Q7: =IF(P7=1,1+SUMPRODUCT($P$6:$P$8*(($I$6:$I$8<I7)+($I$6:$I$8=I7)*($F$6:$F$8<F7))),0) | R7: =IF(Q7<=1,0,SUMPRODUCT(($Q$6:$Q$8=Q7-1)*$I$6:$I$8)) | S7: =IF(Q7<=1,0,SUMPRODUCT(($Q$6:$Q$8=Q7-1)*$J$6:$J$8)) | T7: =IF(Q7=0,"",(I7-R7)/10^in_out_dp) | U7: =IF(Q7=0,"",(J7-S7)/10^in_cost_dp) | V7: =IF(Q7=0,"",IF(I7=R7,0,U7/T7)) | W7: =IF(I7>0,(J7/10^in_cost_dp)/(I7/10^in_out_dp),"n/a") | X7: =IF(Sites!$C$5=C7,1,0)
A8: =B8&"|"&C8 | B8: A | C8: A2 | D8: A2 | E8: 0 | F8: 3 | G8: =Summary!G7 | H8: =Summary!M7 | I8: =ROUND(G8*10^in_out_dp,0) | J8: =ROUND(H8*10^in_cost_dp,0) | K8: =SUMPRODUCT(($I$6:$I$8=I8)*($J$6:$J$8<J8)+($I$6:$I$8>I8)*($J$6:$J$8<=J8)) | L8: =IF(OR(E8=1,K8=0),1,0) | M8: =IF(AND(L8=1,E8=0,I8>0),1,0) | N8: =IF(M8=1,MAX(J8/I8,SUMPRODUCT(MAX(((J8-$J$6:$J$8)*($M$6:$M$8*($I$6:$I$8<I8)))/((I8-$I$6:$I$8)*($M$6:$M$8*($I$6:$I$8<I8))+1-($M$6:$M$8*($I$6:$I$8<I8)))-(1-($M$6:$M$8*($I$6:$I$8<I8)))*1E+300))),0) | O8: =IF(M8=1,SUMPRODUCT(MIN(((($J$6:$J$8-J8)*($M$6:$M$8*($I$6:$I$8>I8)))/(($I$6:$I$8-I8)*($M$6:$M$8*($I$6:$I$8>I8))+1-($M$6:$M$8*($I$6:$I$8>I8)))+(1-($M$6:$M$8*($I$6:$I$8>I8)))*1E+300))),0) | P8: =IF(E8=1,1,IF(AND(M8=1,N8<=O8),1,0)) | Q8: =IF(P8=1,1+SUMPRODUCT($P$6:$P$8*(($I$6:$I$8<I8)+($I$6:$I$8=I8)*($F$6:$F$8<F8))),0) | R8: =IF(Q8<=1,0,SUMPRODUCT(($Q$6:$Q$8=Q8-1)*$I$6:$I$8)) | S8: =IF(Q8<=1,0,SUMPRODUCT(($Q$6:$Q$8=Q8-1)*$J$6:$J$8)) | T8: =IF(Q8=0,"",(I8-R8)/10^in_out_dp) | U8: =IF(Q8=0,"",(J8-S8)/10^in_cost_dp) | V8: =IF(Q8=0,"",IF(I8=R8,0,U8/T8)) | W8: =IF(I8>0,(J8/10^in_cost_dp)/(I8/10^in_out_dp),"n/a") | X8: =IF(Sites!$C$5=C8,1,0)
B10: B
A11: =B11&"|"&C11 | B11: B | C11: NA | D11: NA | E11: 1 | F11: 1 | G11: =Summary!G8 | H11: =Summary!M8 | I11: =ROUND(G11*10^in_out_dp,0) | J11: =ROUND(H11*10^in_cost_dp,0) | K11: =SUMPRODUCT(($I$11:$I$12=I11)*($J$11:$J$12<J11)+($I$11:$I$12>I11)*($J$11:$J$12<=J11)) | L11: =IF(OR(E11=1,K11=0),1,0) | M11: =IF(AND(L11=1,E11=0,I11>0),1,0) | N11: =IF(M11=1,MAX(J11/I11,SUMPRODUCT(MAX(((J11-$J$11:$J$12)*($M$11:$M$12*($I$11:$I$12<I11)))/((I11-$I$11:$I$12)*($M$11:$M$12*($I$11:$I$12<I11))+1-($M$11:$M$12*($I$11:$I$12<I11)))-(1-($M$11:$M$12*($I$11:$I$12<I11)))*1E+300))),0) | O11: =IF(M11=1,SUMPRODUCT(MIN(((($J$11:$J$12-J11)*($M$11:$M$12*($I$11:$I$12>I11)))/(($I$11:$I$12-I11)*($M$11:$M$12*($I$11:$I$12>I11))+1-($M$11:$M$12*($I$11:$I$12>I11)))+(1-($M$11:$M$12*($I$11:$I$12>I11)))*1E+300))),0) | P11: =IF(E11=1,1,IF(AND(M11=1,N11<=O11),1,0)) | Q11: =IF(P11=1,1+SUMPRODUCT($P$11:$P$12*(($I$11:$I$12<I11)+($I$11:$I$12=I11)*($F$11:$F$12<F11))),0) | R11: =IF(Q11<=1,0,SUMPRODUCT(($Q$11:$Q$12=Q11-1)*$I$11:$I$12)) | S11: =IF(Q11<=1,0,SUMPRODUCT(($Q$11:$Q$12=Q11-1)*$J$11:$J$12)) | T11: =IF(Q11=0,"",(I11-R11)/10^in_out_dp) | U11: =IF(Q11=0,"",(J11-S11)/10^in_cost_dp) | V11: =IF(Q11=0,"",IF(I11=R11,0,U11/T11)) | W11: =IF(I11>0,(J11/10^in_cost_dp)/(I11/10^in_out_dp),"n/a") | X11: =IF(Sites!$C$6=C11,1,0)
A12: =B12&"|"&C12 | B12: B | C12: B1 | D12: B1 | E12: 0 | F12: 2 | G12: =Summary!G9 | H12: =Summary!M9 | I12: =ROUND(G12*10^in_out_dp,0) | J12: =ROUND(H12*10^in_cost_dp,0) | K12: =SUMPRODUCT(($I$11:$I$12=I12)*($J$11:$J$12<J12)+($I$11:$I$12>I12)*($J$11:$J$12<=J12)) | L12: =IF(OR(E12=1,K12=0),1,0) | M12: =IF(AND(L12=1,E12=0,I12>0),1,0) | N12: =IF(M12=1,MAX(J12/I12,SUMPRODUCT(MAX(((J12-$J$11:$J$12)*($M$11:$M$12*($I$11:$I$12<I12)))/((I12-$I$11:$I$12)*($M$11:$M$12*($I$11:$I$12<I12))+1-($M$11:$M$12*($I$11:$I$12<I12)))-(1-($M$11:$M$12*($I$11:$I$12<I12)))*1E+300))),0) | O12: =IF(M12=1,SUMPRODUCT(MIN(((($J$11:$J$12-J12)*($M$11:$M$12*($I$11:$I$12>I12)))/(($I$11:$I$12-I12)*($M$11:$M$12*($I$11:$I$12>I12))+1-($M$11:$M$12*($I$11:$I$12>I12)))+(1-($M$11:$M$12*($I$11:$I$12>I12)))*1E+300))),0) | P12: =IF(E12=1,1,IF(AND(M12=1,N12<=O12),1,0)) | Q12: =IF(P12=1,1+SUMPRODUCT($P$11:$P$12*(($I$11:$I$12<I12)+($I$11:$I$12=I12)*($F$11:$F$12<F12))),0) | R12: =IF(Q12<=1,0,SUMPRODUCT(($Q$11:$Q$12=Q12-1)*$I$11:$I$12)) | S12: =IF(Q12<=1,0,SUMPRODUCT(($Q$11:$Q$12=Q12-1)*$J$11:$J$12)) | T12: =IF(Q12=0,"",(I12-R12)/10^in_out_dp) | U12: =IF(Q12=0,"",(J12-S12)/10^in_cost_dp) | V12: =IF(Q12=0,"",IF(I12=R12,0,U12/T12)) | W12: =IF(I12>0,(J12/10^in_cost_dp)/(I12/10^in_out_dp),"n/a") | X12: =IF(Sites!$C$6=C12,1,0)

Sheet Sites
A1: Sites: the alternative carried to the watershed plans
A2: Choose each site's recommended alternative. No Action leaves the site out of every watershed plan.
A4: Site | B4: Name | C4: Recommended alternative | D4: No Action | E4: Carried | F4: Lift (AAHU) | G4: Cost above No Action | H4: Construction cost | I4: Lift (scaled) | J4: Cost (scaled) | K4: Cost-effective | L4: Best buy | M4: Decided by
A5: A | C5: A1 | D5: NA | E5: =IF(C5<>D5,1,0) | F5: =IFERROR(INDEX('Site CE-ICA'!$G$5:$G$12,MATCH(A5&"|"&C5,'Site CE-ICA'!$A$5:$A$12,0)),0) | G5: =IFERROR(INDEX('Site CE-ICA'!$H$5:$H$12,MATCH(A5&"|"&C5,'Site CE-ICA'!$A$5:$A$12,0)),0) | H5: =IFERROR(INDEX(Summary!$H$5:$H$7,MATCH(C5,Summary!$C$5:$C$7,0)),0) | I5: =IF(E5=1,IFERROR(INDEX('Site CE-ICA'!$I$5:$I$12,MATCH(A5&"|"&C5,'Site CE-ICA'!$A$5:$A$12,0)),0),0) | J5: =IF(E5=1,IFERROR(INDEX('Site CE-ICA'!$J$5:$J$12,MATCH(A5&"|"&C5,'Site CE-ICA'!$A$5:$A$12,0)),0),0) | K5: =IFERROR(INDEX('Site CE-ICA'!$L$5:$L$12,MATCH(A5&"|"&C5,'Site CE-ICA'!$A$5:$A$12,0)),0) | L5: =IFERROR(INDEX('Site CE-ICA'!$P$5:$P$12,MATCH(A5&"|"&C5,'Site CE-ICA'!$A$5:$A$12,0)),0) | M5: Suggested
A6: B | C6: B1 | D6: NA | E6: =IF(C6<>D6,1,0) | F6: =IFERROR(INDEX('Site CE-ICA'!$G$5:$G$12,MATCH(A6&"|"&C6,'Site CE-ICA'!$A$5:$A$12,0)),0) | G6: =IFERROR(INDEX('Site CE-ICA'!$H$5:$H$12,MATCH(A6&"|"&C6,'Site CE-ICA'!$A$5:$A$12,0)),0) | H6: =IFERROR(INDEX(Summary!$H$8:$H$9,MATCH(C6,Summary!$C$8:$C$9,0)),0) | I6: =IF(E6=1,IFERROR(INDEX('Site CE-ICA'!$I$5:$I$12,MATCH(A6&"|"&C6,'Site CE-ICA'!$A$5:$A$12,0)),0),0) | J6: =IF(E6=1,IFERROR(INDEX('Site CE-ICA'!$J$5:$J$12,MATCH(A6&"|"&C6,'Site CE-ICA'!$A$5:$A$12,0)),0),0) | K6: =IFERROR(INDEX('Site CE-ICA'!$L$5:$L$12,MATCH(A6&"|"&C6,'Site CE-ICA'!$A$5:$A$12,0)),0) | L6: =IFERROR(INDEX('Site CE-ICA'!$P$5:$P$12,MATCH(A6&"|"&C6,'Site CE-ICA'!$A$5:$A$12,0)),0) | M6: Suggested

Sheet Watershed plans
A1: Watershed plans (values from the app)
A2: This study uses several alternatives per site, so the plan table holds the app's values rather than formulas. Site sheets stay live.
A4: Plan number | B4: Plan | C4: Lift (AAHU) | D4: Average annual cost | E4: Construction cost | F4: Unit cost | G4: Cost-effective | H4: Best buy | I4: Best-buy step | J4: Incremental cost per unit | K4: Final array
A5: 1 | B5: No Action | C5: 0 | D5: 0 | E5: 0 | F5: n/a | G5: 1 | H5: 1 | I5: 0 | K5: 1
A6: 5 | B6: A (A2) | C6: 3.085 | D6: 7021.71 | E6: 180000 | F6: 2276.081 | G6: 1 | H6: 0 | K6: 0
A7: 2 | B7: B (B1) | C7: 5.93 | D7: 11702.85 | E7: 300000 | F7: 1973.4992 | G7: 0 | H7: 0 | K7: 0
A8: 3 | B8: A (A1) | C8: 6.208 | D8: 9752.38 | E8: 250000 | F8: 1570.9375 | G8: 1 | H8: 1 | I8: 1 | J8: 1570.9375 | K8: 1

Sheet Watershed summary
A1: Watershed summary: best buys, final array and the tentatively selected plan
A2: Tables read the watershed plans sheet. Choose the TSP from the final array.
A4: See the Watershed plans sheet (values from the app).

Sheet IWR input
A1: IWR Planning Suite II input
A2: Paste-ready plan, output and cost columns for an independent re-run in IWR Planning Suite II (user-entered planning set; No Action is the first plan).
A4: Site planning sets
A5: Site | B5: Plan | C5: Output (AAHU above No Action) | D5: Cost (average annual, above No Action)
A6: A | B6: NA | C6: ='Site CE-ICA'!I6/10^in_out_dp | D6: ='Site CE-ICA'!J6/10^in_cost_dp
A7: A | B7: A1 | C7: ='Site CE-ICA'!I7/10^in_out_dp | D7: ='Site CE-ICA'!J7/10^in_cost_dp
A8: A | B8: A2 | C8: ='Site CE-ICA'!I8/10^in_out_dp | D8: ='Site CE-ICA'!J8/10^in_cost_dp
A9: B | B9: NA | C9: ='Site CE-ICA'!I11/10^in_out_dp | D9: ='Site CE-ICA'!J11/10^in_cost_dp
A10: B | B10: B1 | C10: ='Site CE-ICA'!I12/10^in_out_dp | D10: ='Site CE-ICA'!J12/10^in_cost_dp

Sheet snap Parameters
B4: 0.03
B5: 50
B6: 12
B7: END
B8: END_OF_YEAR
B9: 2
B10: 3
B14: 0 | C14: 5 | D14: 50

Sheet snap Benefits
L6: 1 | M6: 1 | N6: 1
L7: 1 | M7: 4 | N7: 5
L8: 1 | M8: 2 | N8: 2.5
L9: 2 | M9: 2 | N9: 2
L10: 2 | M10: 5 | N10: 6
F11: 0.2 | G11: 0.2 | H11: 0.2 | I11: 3 | J11: 3 | K11: 3
F12: 0.2 | G12: 0.5 | H12: 0.7 | I12: 3 | J12: 3.5 | K12: 3.5
F13: 0.2 | G13: 0.6 | H13: 0.8 | I13: 3 | J13: 3 | K13: 3
F14: 0.4 | G14: 0.4 | H14: 0.4 | I14: 1 | J14: 1 | K14: 1
F15: 0.4 | G15: 0.4 | H15: 0.9 | I15: 1 | J15: 1 | K15: 2
O16: 0
O17: 1.5
O18: 0.5
O19: 0
O20: 2

Sheet snap Costs
D6: 0 | G6: 4
D7: 250000 | G7: 4
D8: 180000 | G8: 4
D9: 0 | G9: 4
D10: 300000 | G10: 4

Sheet snap Sites
C5: A1
C6: B1

Sheet snap Summary
G5: 0 | L5: 0
G6: 6.2075 | L6: 9752.3775
G7: 3.085 | L7: 7021.7118
G8: 0 | L8: 0
G9: 5.93 | L9: 11702.853

Sheet snap Site CE-ICA
L6: 1 | P6: 1
L7: 1 | P7: 1
L8: 1 | P8: 0
L11: 1 | P11: 1
L12: 1 | P12: 1

Sheet manifest
A1: ceica-calculator | B1: 2
A2: project | B2: 1 | C2: {"benefits":{"modules":[{"id":"hab","method":"HU","name":"Habitat","quantity_units":""},{"id":"rip","method":"INDEX_X_QUANTITY","name":"Riparian","quantity_units":"acres"},{"id":"wet","method":"AAHU","name":"Wetland","quantity_units":""}],"staf_mapping":"A","target_years":[0.0,5.0,50.0]},"cost_categories":[{"id":"construction","idc_applies":true,"name":"Construction"},{"id":"monitoring","idc_applies":false,"name":"Monitoring"},{"id":"adaptive_management","idc_applies":false,"name":"Adaptive management"}],"decisions":{"sites":{},"watershed":{"basis":null,"final_array":{},"steps":{},"tsp":null,"tsp_plan_type":"National Ecosystem Restoration (NER) plan","tsp_rationale":""}},"description":"","labels":{"annual_output_name":"Average annual habitat units","annual_output_short":"AAHU","lift_name":"Ecological lift","output_name":"Habitat units","output_short":"HU"},"name":"Mixed test","project_id":"golden-rules","provenance":{},"report":{"contents":"FULL","date":"","prepared_by":"","status":"DRAFT","title":""},"schema_version":"ceica-project/3","settings":{"aahu_method":"TRAPEZOID","cost_decimals":2,"discount_rate":0.03,"idc_method":"END","idc_periods_per_year":12,"output_decimals":3,"period_of_analysis":50,"price_level":"","recurring_timing":"END_OF_YEAR"},"sites":[{"alternatives":[{"costs":{"annual_override":null,"construction_months":4.0,"first_costs":{"construction":0.0},"recurring":[]},"description":"","id":"NA","is_no_action":true,"name":"","outputs":[{"aahu":null,"module_id":"hab","quantity":[],"scores":{},"values":[1.0,1.0,1.0]},{"aahu":null,"module_id":"rip","quantity":[3.0,3.0,3.0],"scores":{},"values":[0.2,0.2,0.2]},{"aahu":0.0,"module_id":"wet","quantity":[],"scores":{},"values":[]}]},{"costs":{"annual_override":null,"construction_months":4.0,"first_costs":{"construction":250000.0},"recurring":[]},"description":"","id":"A1","is_no_action":false,"name":"","outputs":[{"aahu":null,"module_id":"hab","quantity":[],"scores":{},"values":[1.0,4.0,5.0]},{"aahu":null,"module_id":"rip","quantity":[3.0,3.5,3.5],"scores":{},"values":[0.2,0.5,0.7]},{"aahu":1.5,"module_id":"wet","quantity":[],"scores":{},"values":[]}]},{"costs":{"annual_override":null,"construction_months":4.0,"first_costs":{"construction":180000.0},"recurring":[]},"description":"","id":"A2","is_no_action":false,"name":"","outputs":[{"aahu":null,"module_id":"hab","quantity":[],"scores":{},"values":[1.0,2.0,2.5]},{"aahu":null,"module_id":"rip","quantity":[3.0,3.0,3.0],"scores":{},"values":[0.2,0.6,0.8]},{"aahu":0.5,"module_id":"wet","quantity":[],"scores":{},"values":[]}]}],"description":"","id":"A","name":"","staf_not_assessed":{},"staf_source":{}},{"alternatives":[{"costs":{"annual_override":null,"construction_months":4.0,"first_costs":{"construction":0.0},"recurring":[]},"description":"","id":"NA","is_no_action":true,"name":"","outputs":[{"aahu":null,"module_id":"hab","quantity":[],"scores":{},"values":[2.0,2.0,2.0]},{"aahu":null,"module_id":"rip","quantity":[1.0,1.0,1.0],"scores":{},"values":[0.4,0.4,0.4]},{"aahu":0.0,"module_id":"wet","quantity":[],"scores":{},"values":[]}]},{"costs":{"annual_override":null,"construction_months":4.0,"first_costs":{"construction":300000.0},"recurring":[]},"description":"","id":"B1","is_no_action":false,"name":"","outputs":[{"aahu":null,"module_id":"hab","quantity":[],"scores":{},"values":[2.0,5.0,6.0]},{"aahu":null,"module_id":"rip","quantity":[1.0,1.0,2.0],"scores":{},"values":[0.4,0.4,0.9]},{"aahu":2.0,"module_id":"wet","quantity":[],"scores":{},"values":[]}]}],"description":"","id":"B","name":"","staf_not_assessed":{},"staf_source":{}}],"watershed":{"carried":{"A":["A1","A2"],"B":["B1"]},"mode":"MULTI","rules":[{"kind":"NOT_COMBINABLE","site_id":"A","with_sites":["B"]}]}}
A3: meta | B3: 1 | C3: {"appVersion":"1.0.0","engineVersion":"1","format":"ceica-calculator","formatVersion":2,"layout":[{"cell":"B4","kind":"number","path":["settings","discount_rate"],"sheet":"Parameters"},{"cell":"B5","kind":"number","path":["settings","period_of_analysis"],"sheet":"Parameters"},{"cell":"B6","kind":"number","path":["settings","idc_periods_per_year"],"sheet":"Parameters"},{"cell":"B7","kind":"text","path":["settings","idc_method"],"sheet":"Parameters"},{"cell":"B8","kind":"text","path":["settings","recurring_timing"],"sheet":"Parameters"},{"cell":"B9","kind":"number","path":["settings","cost_decimals"],"sheet":"Parameters"},{"cell":"B10","kind":"number","path":["settings","output_decimals"],"sheet":"Parameters"},{"cell":"B14","kind":"number","path":["benefits","target_years",0],"sheet":"Parameters"},{"cell":"C14","kind":"number","path":["benefits","target_years",1],"sheet":"Parameters"},{"cell":"D14","kind":"number","path":["benefits","target_years",2],"sheet":"Parameters"},{"cell":"L6","kind":"optional","path":["sites",0,"alternatives",0,"outputs",{"module_id":"hab"},"values",0],"sheet":"Benefits"},{"cell":"M6","kind":"optional","path":["sites",0,"alternatives",0,"outputs",{"module_id":"hab"},"values",1],"sheet":"Benefits"},{"cell":"N6","kind":"optional","path":["sites",0,"alternatives",0,"outputs",{"module_id":"hab"},"values",2],"sheet":"Benefits"},{"cell":"L7","kind":"optional","path":["sites",0,"alternatives",1,"outputs",{"module_id":"hab"},"values",0],"sheet":"Benefits"},{"cell":"M7","kind":"optional","path":["sites",0,"alternatives",1,"outputs",{"module_id":"hab"},"values",1],"sheet":"Benefits"},{"cell":"N7","kind":"optional","path":["sites",0,"alternatives",1,"outputs",{"module_id":"hab"},"values",2],"sheet":"Benefits"},{"cell":"L8","kind":"optional","path":["sites",0,"alternatives",2,"outputs",{"module_id":"hab"},"values",0],"sheet":"Benefits"},{"cell":"M8","kind":"optional","path":["sites",0,"alternatives",2,"outputs",{"module_id":"hab"},"values",1],"sheet":"Benefits"},{"cell":"N8","kind":"optional","path":["sites",0,"alternatives",2,"outputs",{"module_id":"hab"},"values",2],"sheet":"Benefits"},{"cell":"L9","kind":"optional","path":["sites",1,"alternatives",0,"outputs",{"module_id":"hab"},"values",0],"sheet":"Benefits"},{"cell":"M9","kind":"optional","path":["sites",1,"alternatives",0,"outputs",{"module_id":"hab"},"values",1],"sheet":"Benefits"},{"cell":"N9","kind":"optional","path":["sites",1,"alternatives",0,"outputs",{"module_id":"hab"},"values",2],"sheet":"Benefits"},{"cell":"L10","kind":"optional","path":["sites",1,"alternatives",1,"outputs",{"module_id":"hab"},"values",0],"sheet":"Benefits"},{"cell":"M10","kind":"optional","path":["sites",1,"alternatives",1,"outputs",{"module_id":"hab"},"values",1],"sheet":"Benefits"},{"cell":"N10","kind":"optional","path":["sites",1,"alternatives",1,"outputs",{"module_id":"hab"},"values",2],"sheet":"Benefits"},{"cell":"F11","kind":"optional","path":["sites",0,"alternatives",0,"outputs",{"module_id":"rip"},"values",0],"sheet":"Benefits"},{"cell":"I11","kind":"optional","path":["sites",0,"alternatives",0,"outputs",{"module_id":"rip"},"quantity",0],"sheet":"Benefits"},{"cell":"G11","kind":"optional","path":["sites",0,"alternatives",0,"outputs",{"module_id":"rip"},"values",1],"sheet":"Benefits"},{"cell":"J11","kind":"optional","path":["sites",0,"alternatives",0,"outputs",{"module_id":"rip"},"quantity",1],"sheet":"Benefits"},{"cell":"H11","kind":"optional","path":["sites",0,"alternatives",0,"outputs",{"module_id":"rip"},"values",2],"sheet":"Benefits"},{"cell":"K11","kind":"optional","path":["sites",0,"alternatives",0,"outputs",{"module_id":"rip"},"quantity",2],"sheet":"Benefits"},{"cell":"F12","kind":"optional","path":["sites",0,"alternatives",1,"outputs",{"module_id":"rip"},"values",0],"sheet":"Benefits"},{"cell":"I12","kind":"optional","path":["sites",0,"alternatives",1,"outputs",{"module_id":"rip"},"quantity",0],"sheet":"Benefits"},{"cell":"G12","kind":"optional","path":["sites",0,"alternatives",1,"outputs",{"module_id":"rip"},"values",1],"sheet":"Benefits"},{"cell":"J12","kind":"optional","path":["sites",0,"alternatives",1,"outputs",{"module_id":"rip"},"quantity",1],"sheet":"Benefits"},{"cell":"H12","kind":"optional","path":["sites",0,"alternatives",1,"outputs",{"module_id":"rip"},"values",2],"sheet":"Benefits"},{"cell":"K12","kind":"optional","path":["sites",0,"alternatives",1,"outputs",{"module_id":"rip"},"quantity",2],"sheet":"Benefits"},{"cell":"F13","kind":"optional","path":["sites",0,"alternatives",2,"outputs",{"module_id":"rip"},"values",0],"sheet":"Benefits"},{"cell":"I13","kind":"optional","path":["sites",0,"alternatives",2,"outputs",{"module_id":"rip"},"quantity",0],"sheet":"Benefits"},{"cell":"G13","kind":"optional","path":["sites",0,"alternatives",2,"outputs",{"module_id":"rip"},"values",1],"sheet":"Benefits"},{"cell":"J13","kind":"optional","path":["sites",0,"alternatives",2,"outputs",{"module_id":"rip"},"quantity",1],"sheet":"Benefits"},{"cell":"H13","kind":"optional","path":["sites",0,"alternatives",2,"outputs",{"module_id":"rip"},"values",2],"sheet":"Benefits"},{"cell":"K13","kind":"optional","path":["sites",0,"alternatives",2,"outputs",{"module_id":"rip"},"quantity",2],"sheet":"Benefits"},{"cell":"F14","kind":"optional","path":["sites",1,"alternatives",0,"outputs",{"module_id":"rip"},"values",0],"sheet":"Benefits"},{"cell":"I14","kind":"optional","path":["sites",1,"alternatives",0,"outputs",{"module_id":"rip"},"quantity",0],"sheet":"Benefits"},{"cell":"G14","kind":"optional","path":["sites",1,"alternatives",0,"outputs",{"module_id":"rip"},"values",1],"sheet":"Benefits"},{"cell":"J14","kind":"optional","path":["sites",1,"alternatives",0,"outputs",{"module_id":"rip"},"quantity",1],"sheet":"Benefits"},{"cell":"H14","kind":"optional","path":["sites",1,"alternatives",0,"outputs",{"module_id":"rip"},"values",2],"sheet":"Benefits"},{"cell":"K14","kind":"optional","path":["sites",1,"alternatives",0,"outputs",{"module_id":"rip"},"quantity",2],"sheet":"Benefits"},{"cell":"F15","kind":"optional","path":["sites",1,"alternatives",1,"outputs",{"module_id":"rip"},"values",0],"sheet":"Benefits"},{"cell":"I15","kind":"optional","path":["sites",1,"alternatives",1,"outputs",{"module_id":"rip"},"quantity",0],"sheet":"Benefits"},{"cell":"G15","kind":"optional","path":["sites",1,"alternatives",1,"outputs",{"module_id":"rip"},"values",1],"sheet":"Benefits"},{"cell":"J15","kind":"optional","path":["sites",1,"alternatives",1,"outputs",{"module_id":"rip"},"quantity",1],"sheet":"Benefits"},{"cell":"H15","kind":"optional","path":["sites",1,"alternatives",1,"outputs",{"module_id":"rip"},"values",2],"sheet":"Benefits"},{"cell":"K15","kind":"optional","path":["sites",1,"alternatives",1,"outputs",{"module_id":"rip"},"quantity",2],"sheet":"Benefits"},{"cell":"O16","kind":"optional","path":["sites",0,"alternatives",0,"outputs",{"module_id":"wet"},"aahu"],"sheet":"Benefits"},{"cell":"O17","kind":"optional","path":["sites",0,"alternatives",1,"outputs",{"module_id":"wet"},"aahu"],"sheet":"Benefits"},{"cell":"O18","kind":"optional","path":["sites",0,"alternatives",2,"outputs",{"module_id":"wet"},"aahu"],"sheet":"Benefits"},{"cell":"O19","kind":"optional","path":["sites",1,"alternatives",0,"outputs",{"module_id":"wet"},"aahu"],"sheet":"Benefits"},{"cell":"O20","kind":"optional","path":["sites",1,"alternatives",1,"outputs",{"module_id":"wet"},"aahu"],"sheet":"Benefits"},{"cell":"D6","kind":"number","path":["sites",0,"alternatives",0,"costs","first_costs","construction"],"sheet":"Costs"},{"cell":"E6","kind":"number","path":["sites",0,"alternatives",0,"costs","first_costs","monitoring"],"sheet":"Costs"},{"cell":"F6","kind":"number","path":["sites",0,"alternatives",0,"costs","first_costs","adaptive_management"],"sheet":"Costs"},{"cell":"G6","kind":"number","path":["sites",0,"alternatives",0,"costs","construction_months"],"sheet":"Costs"},{"cell":"L6","kind":"optional","path":["sites",0,"alternatives",0,"costs","annual_override"],"sheet":"Costs"},{"cell":"D7","kind":"number","path":["sites",0,"alternatives",1,"costs","first_costs","construction"],"sheet":"Costs"},{"cell":"E7","kind":"number","path":["sites",0,"alternatives",1,"costs","first_costs","monitoring"],"sheet":"Costs"},{"cell":"F7","kind":"number","path":["sites",0,"alternatives",1,"costs","first_costs","adaptive_management"],"sheet":"Costs"},{"cell":"G7","kind":"number","path":["sites",0,"alternatives",1,"costs","construction_months"],"sheet":"Costs"},{"cell":"L7","kind":"optional","path":["sites",0,"alternatives",1,"costs","annual_override"],"sheet":"Costs"},{"cell":"D8","kind":"number","path":["sites",0,"alternatives",2,"costs","first_costs","construction"],"sheet":"Costs"},{"cell":"E8","kind":"number","path":["sites",0,"alternatives",2,"costs","first_costs","monitoring"],"sheet":"Costs"},{"cell":"F8","kind":"number","path":["sites",0,"alternatives",2,"costs","first_costs","adaptive_management"],"sheet":"Costs"},{"cell":"G8","kind":"number","path":["sites",0,"alternatives",2,"costs","construction_months"],"sheet":"Costs"},{"cell":"L8","kind":"optional","path":["sites",0,"alternatives",2,"costs","annual_override"],"sheet":"Costs"},{"cell":"D9","kind":"number","path":["sites",1,"alternatives",0,"costs","first_costs","construction"],"sheet":"Costs"},{"cell":"E9","kind":"number","path":["sites",1,"alternatives",0,"costs","first_costs","monitoring"],"sheet":"Costs"},{"cell":"F9","kind":"number","path":["sites",1,"alternatives",0,"costs","first_costs","adaptive_management"],"sheet":"Costs"},{"cell":"G9","kind":"number","path":["sites",1,"alternatives",0,"costs","construction_months"],"sheet":"Costs"},{"cell":"L9","kind":"optional","path":["sites",1,"alternatives",0,"costs","annual_override"],"sheet":"Costs"},{"cell":"D10","kind":"number","path":["sites",1,"alternatives",1,"costs","first_costs","construction"],"sheet":"Costs"},{"cell":"E10","kind":"number","path":["sites",1,"alternatives",1,"costs","first_costs","monitoring"],"sheet":"Costs"},{"cell":"F10","kind":"number","path":["sites",1,"alternatives",1,"costs","first_costs","adaptive_management"],"sheet":"Costs"},{"cell":"G10","kind":"number","path":["sites",1,"alternatives",1,"costs","construction_months"],"sheet":"Costs"},{"cell":"L10","kind":"optional","path":["sites",1,"alternatives",1,"costs","annual_override"],"sheet":"Costs"},{"cell":"C5","exported":"A1","kind":"rec","path":["decisions","sites","A","recommended_alt_id"],"sheet":"Sites"},{"cell":"C6","exported":"B1","kind":"rec","path":["decisions","sites","B","recommended_alt_id"],"sheet":"Sites"}],"liveWatershed":false,"planBits":[],"planRowKeys":{},"planSites":[],"projectDigest":"89aea71be748","schemaVersion":3}
