Workbook
Name in_rate: Parameters!$B$4
Name in_poa: Parameters!$B$5
Name in_ppy: Parameters!$B$6
Name in_idc_method: Parameters!$B$7
Name in_timing: Parameters!$B$8
Name in_cost_dp: Parameters!$B$9
Name in_out_dp: Parameters!$B$10
Name calc_crf: Parameters!$B$11
Name out_status: 'Read me'!$B$10
Name out_changed: 'Read me'!$B$11
Name out_mismatch: 'Read me'!$B$12

Sheet Read me
A1: Small test: CE/ICA calculator
A2: Cost-effectiveness and incremental cost analysis, as live formulas.
A4: Study | B4: Small test
A5: Generated by | B5: CEICA 0.1.0 (engine 1)
A6: Project digest | B6: f4d289ead17a
A7: Discount rate | B7: 3 percent
A8: Period of analysis | B8: 50 years
A10: Status | B10: =IF(B11=0,IF(B12=0,"Unchanged: matches the CEICA export","ERROR: results differ from the export although no input changed"),"Edited: "&B11&" input cells changed since the export")
A11: Inputs changed | B11: =(SUMPRODUCT(1*(Parameters!B4:B10<>'snap Parameters'!B4:B10))+SUMPRODUCT(1*(Parameters!B14:D14<>'snap Parameters'!B14:D14))+SUMPRODUCT(1*(Benefits!F6:H14<>'snap Benefits'!F6:H14))+SUMPRODUCT(1*(Costs!D6:G14<>'snap Costs'!D6:G14))+SUMPRODUCT(1*(Costs!L6:L14<>'snap Costs'!L6:L14))+SUMPRODUCT(1*(OMRRR!F5:M8<>'snap OMRRR'!F5:M8))+SUMPRODUCT(1*(Sites!C5:C7<>'snap Sites'!C5:C7))+SUMPRODUCT(1*('Watershed plans'!AA12:AA19<>'snap Watershed plans'!AA12:AA19))+SUMPRODUCT(1*('Watershed summary'!K50:L89<>'snap Watershed summary'!K50:L89))+SUMPRODUCT(1*('Watershed summary'!B93:B93<>'snap Watershed summary'!B93:B93)))
A12: Results that differ from the export | B12: =(SUMPRODUCT(1*(ABS(Summary!G5:G13-'snap Summary'!G5:G13)>1e-06))+SUMPRODUCT(1*(ABS(Summary!L5:L13-'snap Summary'!L5:L13)>0.0001))+SUMPRODUCT(1*('Site CE-ICA'!L6:L8<>'snap Site CE-ICA'!L6:L8))+SUMPRODUCT(1*('Site CE-ICA'!P6:P8<>'snap Site CE-ICA'!P6:P8))+SUMPRODUCT(1*('Site CE-ICA'!L11:L14<>'snap Site CE-ICA'!L11:L14))+SUMPRODUCT(1*('Site CE-ICA'!P11:P14<>'snap Site CE-ICA'!P11:P14))+SUMPRODUCT(1*('Site CE-ICA'!L17:L18<>'snap Site CE-ICA'!L17:L18))+SUMPRODUCT(1*('Site CE-ICA'!P17:P18<>'snap Site CE-ICA'!P17:P18))+SUMPRODUCT(1*('Watershed plans'!O12:O19<>'snap Watershed plans'!O12:O19))+SUMPRODUCT(1*('Watershed plans'!S12:S19<>'snap Watershed plans'!S12:S19)))
A14: How to use
A15: - Orange cells are inputs; grey cells are formulas. Sheets are protected (password 'ceica') only to prevent accidental edits.
A16: - Change any orange cell: annualization, site CE/ICA, the watershed plans and the summary update. Changed inputs turn yellow.
A17: - To add sites, alternatives or years, make the change in CEICA and export again.
A18: - Import this workbook in CEICA to bring your changes back into the project.
A20: Legend
A21: Input
A22: Formula
A23: Changed since export

Sheet Parameters
A1: Parameters
A2: Economics and conventions. Orange cells are inputs.
A3: Parameter | B3: Value
A4: Discount rate | B4: 0.03
A5: Period of analysis (years) | B5: 50
A6: Interest during construction: periods per year | B6: 12
A7: Interest during construction: spending in each period (END, MIDDLE or START) | B7: END
A8: OMRRR discounting (END_OF_YEAR or MID_YEAR) | B8: END_OF_YEAR
A9: Cost decimals kept for CE/ICA | B9: 2
A10: Output decimals kept for CE/ICA | B10: 3
A11: Capital recovery factor | B11: =IF(in_rate=0,1/in_poa,in_rate*(1+in_rate)^in_poa/((1+in_rate)^in_poa-1))
A13: Target years | B13: Year 1 | C13: Year 2 | D13: Year 3
A14: Years (first to last) | B14: 0 | C14: 5 | D14: 50

Sheet Benefits
A1: Benefits: habitat units by module
A2: One row per module, site and alternative; the Summary adds the modules' averages. Total: habitat units entered at each target year. Averages are the area under straight lines between target years.
A4: Key | B4: Site | C4: Alternative | D4: Module | E4: Method | F4: Habitat units (HU) | I4: Average (AAHU)
F5: =Parameters!$B$14 | G5: =Parameters!$C$14 | H5: =Parameters!$D$14
A6: =B6&"|"&C6 | B6: A | C6: NA | D6: Total | E6: Habitat units | F6: 1 | G6: 1 | H6: 1 | I6: =SUMPRODUCT($G$5:$H$5-$F$5:$G$5,(G6:H6+F6:G6)/2)/($H$5-$F$5)
A7: =B7&"|"&C7 | B7: A | C7: A1 | D7: Total | E7: Habitat units | F7: 1 | G7: 5 | H7: 6 | I7: =SUMPRODUCT($G$5:$H$5-$F$5:$G$5,(G7:H7+F7:G7)/2)/($H$5-$F$5)
A8: =B8&"|"&C8 | B8: A | C8: A2 | D8: Total | E8: Habitat units | F8: 1 | G8: 3 | H8: 3.5 | I8: =SUMPRODUCT($G$5:$H$5-$F$5:$G$5,(G8:H8+F8:G8)/2)/($H$5-$F$5)
A9: =B9&"|"&C9 | B9: B | C9: NA | D9: Total | E9: Habitat units | F9: 2 | G9: 2 | H9: 2 | I9: =SUMPRODUCT($G$5:$H$5-$F$5:$G$5,(G9:H9+F9:G9)/2)/($H$5-$F$5)
A10: =B10&"|"&C10 | B10: B | C10: B1 | D10: Total | E10: Habitat units | F10: 2 | G10: 4 | H10: 4 | I10: =SUMPRODUCT($G$5:$H$5-$F$5:$G$5,(G10:H10+F10:G10)/2)/($H$5-$F$5)
A11: =B11&"|"&C11 | B11: B | C11: B2 | D11: Total | E11: Habitat units | F11: 2 | G11: 4 | H11: 4 | I11: =SUMPRODUCT($G$5:$H$5-$F$5:$G$5,(G11:H11+F11:G11)/2)/($H$5-$F$5)
A12: =B12&"|"&C12 | B12: B | C12: B3 | D12: Total | E12: Habitat units | F12: 2 | G12: 6 | H12: 6 | I12: =SUMPRODUCT($G$5:$H$5-$F$5:$G$5,(G12:H12+F12:G12)/2)/($H$5-$F$5)
A13: =B13&"|"&C13 | B13: C | C13: NA | D13: Total | E13: Habitat units | F13: 0.5 | G13: 0.5 | H13: 0.5 | I13: =SUMPRODUCT($G$5:$H$5-$F$5:$G$5,(G13:H13+F13:G13)/2)/($H$5-$F$5)
A14: =B14&"|"&C14 | B14: C | C14: C1 | D14: Total | E14: Habitat units | F14: 0.5 | G14: 2 | H14: 2.5 | I14: =SUMPRODUCT($G$5:$H$5-$F$5:$G$5,(G14:H14+F14:G14)/2)/($H$5-$F$5)

Sheet Costs
A1: Costs: first costs, interest during construction and OMRRR
A2: First costs are base-year lump sums. Interest during construction accrues on the categories marked *, spent evenly over the construction months.
N3: Average annual cost by part
A4: Key | B4: Site | C4: Alternative | D4: Construction * | E4: Monitoring | F4: Adaptive management | G4: Construction months | H4: IDC base | I4: Interest during construction | J4: OMRRR present value | K4: Total present value | L4: Average annual cost entered | M4: Average annual cost | N4: Construction | O4: Monitoring | P4: Adaptive management | Q4: Interest during construction | R4: OMRRR
D5: construction | E5: monitoring | F5: adaptive_management
A6: =B6&"|"&C6 | B6: A | C6: NA | G6: 0 | H6: =D6 | I6: =IF(OR(G6=0,in_rate=0,H6=0),0,H6/G6*(IF(in_idc_method="START",1+((1+in_rate)^(1/in_ppy)-1),IF(in_idc_method="MIDDLE",1+((1+in_rate)^(1/in_ppy)-1)/2,1))*((1+in_rate)^(G6/in_ppy)-1)/((1+in_rate)^(1/in_ppy)-1)-G6)) | J6: =SUMIFS(OMRRR!$S$5:$S$8,OMRRR!$A$5:$A$8,A6) | K6: =SUM(D6:F6)+I6+J6 | M6: =IF(ISNUMBER(L6),L6,calc_crf*K6) | N6: =calc_crf*D6 | O6: =calc_crf*E6 | P6: =calc_crf*F6 | Q6: =calc_crf*I6 | R6: =calc_crf*J6
A7: =B7&"|"&C7 | B7: A | C7: A1 | D7: 300000 | E7: 20000 | G7: 6 | H7: =D7 | I7: =IF(OR(G7=0,in_rate=0,H7=0),0,H7/G7*(IF(in_idc_method="START",1+((1+in_rate)^(1/in_ppy)-1),IF(in_idc_method="MIDDLE",1+((1+in_rate)^(1/in_ppy)-1)/2,1))*((1+in_rate)^(G7/in_ppy)-1)/((1+in_rate)^(1/in_ppy)-1)-G7)) | J7: =SUMIFS(OMRRR!$S$5:$S$8,OMRRR!$A$5:$A$8,A7) | K7: =SUM(D7:F7)+I7+J7 | M7: =IF(ISNUMBER(L7),L7,calc_crf*K7) | N7: =calc_crf*D7 | O7: =calc_crf*E7 | P7: =calc_crf*F7 | Q7: =calc_crf*I7 | R7: =calc_crf*J7
A8: =B8&"|"&C8 | B8: A | C8: A2 | D8: 150000 | G8: 6 | H8: =D8 | I8: =IF(OR(G8=0,in_rate=0,H8=0),0,H8/G8*(IF(in_idc_method="START",1+((1+in_rate)^(1/in_ppy)-1),IF(in_idc_method="MIDDLE",1+((1+in_rate)^(1/in_ppy)-1)/2,1))*((1+in_rate)^(G8/in_ppy)-1)/((1+in_rate)^(1/in_ppy)-1)-G8)) | J8: =SUMIFS(OMRRR!$S$5:$S$8,OMRRR!$A$5:$A$8,A8) | K8: =SUM(D8:F8)+I8+J8 | M8: =IF(ISNUMBER(L8),L8,calc_crf*K8) | N8: =calc_crf*D8 | O8: =calc_crf*E8 | P8: =calc_crf*F8 | Q8: =calc_crf*I8 | R8: =calc_crf*J8
A9: =B9&"|"&C9 | B9: B | C9: NA | G9: 0 | H9: =D9 | I9: =IF(OR(G9=0,in_rate=0,H9=0),0,H9/G9*(IF(in_idc_method="START",1+((1+in_rate)^(1/in_ppy)-1),IF(in_idc_method="MIDDLE",1+((1+in_rate)^(1/in_ppy)-1)/2,1))*((1+in_rate)^(G9/in_ppy)-1)/((1+in_rate)^(1/in_ppy)-1)-G9)) | J9: =SUMIFS(OMRRR!$S$5:$S$8,OMRRR!$A$5:$A$8,A9) | K9: =SUM(D9:F9)+I9+J9 | M9: =IF(ISNUMBER(L9),L9,calc_crf*K9) | N9: =calc_crf*D9 | O9: =calc_crf*E9 | P9: =calc_crf*F9 | Q9: =calc_crf*I9 | R9: =calc_crf*J9
A10: =B10&"|"&C10 | B10: B | C10: B1 | D10: 100000 | G10: 3 | H10: =D10 | I10: =IF(OR(G10=0,in_rate=0,H10=0),0,H10/G10*(IF(in_idc_method="START",1+((1+in_rate)^(1/in_ppy)-1),IF(in_idc_method="MIDDLE",1+((1+in_rate)^(1/in_ppy)-1)/2,1))*((1+in_rate)^(G10/in_ppy)-1)/((1+in_rate)^(1/in_ppy)-1)-G10)) | J10: =SUMIFS(OMRRR!$S$5:$S$8,OMRRR!$A$5:$A$8,A10) | K10: =SUM(D10:F10)+I10+J10 | M10: =IF(ISNUMBER(L10),L10,calc_crf*K10) | N10: =calc_crf*D10 | O10: =calc_crf*E10 | P10: =calc_crf*F10 | Q10: =calc_crf*I10 | R10: =calc_crf*J10
A11: =B11&"|"&C11 | B11: B | C11: B2 | D11: 100000 | G11: 3 | H11: =D11 | I11: =IF(OR(G11=0,in_rate=0,H11=0),0,H11/G11*(IF(in_idc_method="START",1+((1+in_rate)^(1/in_ppy)-1),IF(in_idc_method="MIDDLE",1+((1+in_rate)^(1/in_ppy)-1)/2,1))*((1+in_rate)^(G11/in_ppy)-1)/((1+in_rate)^(1/in_ppy)-1)-G11)) | J11: =SUMIFS(OMRRR!$S$5:$S$8,OMRRR!$A$5:$A$8,A11) | K11: =SUM(D11:F11)+I11+J11 | M11: =IF(ISNUMBER(L11),L11,calc_crf*K11) | N11: =calc_crf*D11 | O11: =calc_crf*E11 | P11: =calc_crf*F11 | Q11: =calc_crf*I11 | R11: =calc_crf*J11
A12: =B12&"|"&C12 | B12: B | C12: B3 | D12: 200000 | G12: 3 | H12: =D12 | I12: =IF(OR(G12=0,in_rate=0,H12=0),0,H12/G12*(IF(in_idc_method="START",1+((1+in_rate)^(1/in_ppy)-1),IF(in_idc_method="MIDDLE",1+((1+in_rate)^(1/in_ppy)-1)/2,1))*((1+in_rate)^(G12/in_ppy)-1)/((1+in_rate)^(1/in_ppy)-1)-G12)) | J12: =SUMIFS(OMRRR!$S$5:$S$8,OMRRR!$A$5:$A$8,A12) | K12: =SUM(D12:F12)+I12+J12 | M12: =IF(ISNUMBER(L12),L12,calc_crf*K12) | N12: =calc_crf*D12 | O12: =calc_crf*E12 | P12: =calc_crf*F12 | Q12: =calc_crf*I12 | R12: =calc_crf*J12
A13: =B13&"|"&C13 | B13: C | C13: NA | G13: 0 | H13: =D13 | I13: =IF(OR(G13=0,in_rate=0,H13=0),0,H13/G13*(IF(in_idc_method="START",1+((1+in_rate)^(1/in_ppy)-1),IF(in_idc_method="MIDDLE",1+((1+in_rate)^(1/in_ppy)-1)/2,1))*((1+in_rate)^(G13/in_ppy)-1)/((1+in_rate)^(1/in_ppy)-1)-G13)) | J13: =SUMIFS(OMRRR!$S$5:$S$8,OMRRR!$A$5:$A$8,A13) | K13: =SUM(D13:F13)+I13+J13 | M13: =IF(ISNUMBER(L13),L13,calc_crf*K13) | N13: =calc_crf*D13 | O13: =calc_crf*E13 | P13: =calc_crf*F13 | Q13: =calc_crf*I13 | R13: =calc_crf*J13
A14: =B14&"|"&C14 | B14: C | C14: C1 | D14: 90000 | G14: 6 | H14: =D14 | I14: =IF(OR(G14=0,in_rate=0,H14=0),0,H14/G14*(IF(in_idc_method="START",1+((1+in_rate)^(1/in_ppy)-1),IF(in_idc_method="MIDDLE",1+((1+in_rate)^(1/in_ppy)-1)/2,1))*((1+in_rate)^(G14/in_ppy)-1)/((1+in_rate)^(1/in_ppy)-1)-G14)) | J14: =SUMIFS(OMRRR!$S$5:$S$8,OMRRR!$A$5:$A$8,A14) | K14: =SUM(D14:F14)+I14+J14 | M14: =IF(ISNUMBER(L14),L14,calc_crf*K14) | N14: =calc_crf*D14 | O14: =calc_crf*E14 | P14: =calc_crf*F14 | Q14: =calc_crf*I14 | R14: =calc_crf*J14

Sheet OMRRR
A1: OMRRR: recurring operation, maintenance, repair, replacement and rehabilitation
A2: Each item costs the amount per occurrence every N years from the first year to the last (blank: every N years through the period of analysis). Basis: FIXED amount, PERCENT of a first-cost category, or RATE x quantity.
A4: Key | B4: Site | C4: Alternative | D4: Item | E4: Basis | F4: Amount | G4: Percent | H4: Category | I4: Unit rate | J4: Quantity | K4: Every N years | L4: First year | M4: Last year | N4: Amount per occurrence | O4: First | P4: Last | Q4: Occurrences | R4: Present value, end of year | S4: Present value
A5: =B5&"|"&C5 | B5: A | C5: A1 | D5: Annual O&M | E5: FIXED | F5: 2500 | K5: 1 | N5: =IF(E5="FIXED",F5,IF(E5="PERCENT",G5*IFERROR(INDEX(Costs!$D$6:$F$14,MATCH(A5,Costs!$A$6:$A$14,0),MATCH(H5,Costs!$D$5:$F$5,0)),0),I5*J5)) | O5: =IF(ISNUMBER(L5),L5,K5) | P5: =IF(ISNUMBER(M5),MIN(M5,in_poa),in_poa) | Q5: =IF(P5<O5,0,INT((P5-O5)/K5)+1) | R5: =IF(Q5=0,0,IF(in_rate=0,N5*Q5,N5*(1+in_rate)^(-O5)*(1-(1+in_rate)^(-K5*Q5))/(1-(1+in_rate)^(-K5)))) | S5: =IF(in_timing="MID_YEAR",IF(O5=0,IF(Q5=0,0,N5+(R5-N5)*(1+in_rate)^0.5),R5*(1+in_rate)^0.5),R5)
A6: =B6&"|"&C6 | B6: A | C6: A2 | D6: Repair | E6: PERCENT | G6: 0.1 | H6: construction | K6: 20 | N6: =IF(E6="FIXED",F6,IF(E6="PERCENT",G6*IFERROR(INDEX(Costs!$D$6:$F$14,MATCH(A6,Costs!$A$6:$A$14,0),MATCH(H6,Costs!$D$5:$F$5,0)),0),I6*J6)) | O6: =IF(ISNUMBER(L6),L6,K6) | P6: =IF(ISNUMBER(M6),MIN(M6,in_poa),in_poa) | Q6: =IF(P6<O6,0,INT((P6-O6)/K6)+1) | R6: =IF(Q6=0,0,IF(in_rate=0,N6*Q6,N6*(1+in_rate)^(-O6)*(1-(1+in_rate)^(-K6*Q6))/(1-(1+in_rate)^(-K6)))) | S6: =IF(in_timing="MID_YEAR",IF(O6=0,IF(Q6=0,0,N6+(R6-N6)*(1+in_rate)^0.5),R6*(1+in_rate)^0.5),R6)
A7: =B7&"|"&C7 | B7: A | C7: A2 | D7: Inspection | E7: RATE | I7: 4 | J7: 1200 | K7: 2 | N7: =IF(E7="FIXED",F7,IF(E7="PERCENT",G7*IFERROR(INDEX(Costs!$D$6:$F$14,MATCH(A7,Costs!$A$6:$A$14,0),MATCH(H7,Costs!$D$5:$F$5,0)),0),I7*J7)) | O7: =IF(ISNUMBER(L7),L7,K7) | P7: =IF(ISNUMBER(M7),MIN(M7,in_poa),in_poa) | Q7: =IF(P7<O7,0,INT((P7-O7)/K7)+1) | R7: =IF(Q7=0,0,IF(in_rate=0,N7*Q7,N7*(1+in_rate)^(-O7)*(1-(1+in_rate)^(-K7*Q7))/(1-(1+in_rate)^(-K7)))) | S7: =IF(in_timing="MID_YEAR",IF(O7=0,IF(Q7=0,0,N7+(R7-N7)*(1+in_rate)^0.5),R7*(1+in_rate)^0.5),R7)
A8: =B8&"|"&C8 | B8: C | C8: C1 | D8: Annual O&M | E8: FIXED | F8: 2500 | K8: 1 | N8: =IF(E8="FIXED",F8,IF(E8="PERCENT",G8*IFERROR(INDEX(Costs!$D$6:$F$14,MATCH(A8,Costs!$A$6:$A$14,0),MATCH(H8,Costs!$D$5:$F$5,0)),0),I8*J8)) | O8: =IF(ISNUMBER(L8),L8,K8) | P8: =IF(ISNUMBER(M8),MIN(M8,in_poa),in_poa) | Q8: =IF(P8<O8,0,INT((P8-O8)/K8)+1) | R8: =IF(Q8=0,0,IF(in_rate=0,N8*Q8,N8*(1+in_rate)^(-O8)*(1-(1+in_rate)^(-K8*Q8))/(1-(1+in_rate)^(-K8)))) | S8: =IF(in_timing="MID_YEAR",IF(O8=0,IF(Q8=0,0,N8+(R8-N8)*(1+in_rate)^0.5),R8*(1+in_rate)^0.5),R8)

Sheet Summary
A1: Summary of inputs to CE/ICA
A2: Lift is each alternative's AAHU above No Action; the CE/ICA cost is its average annual cost above No Action.
A4: Key | B4: Site | C4: Alternative | D4: Name | E4: No Action | F4: Outputs (AAHU) | G4: Lift (AAHU) | H4: Construction cost | I4: First costs | J4: Interest during construction | K4: OMRRR present value | L4: Average annual cost | M4: Cost above No Action | N4: Unit cost ($/AAHU)
A5: =B5&"|"&C5 | B5: A | C5: NA | D5: NA | E5: 1 | F5: =SUMIFS(Benefits!$I$6:$I$14,Benefits!$A$6:$A$14,A5) | G5: =F5-$F$5 | H5: =Costs!D6 | I5: =SUM(Costs!D6:F6) | J5: =Costs!I6 | K5: =Costs!J6 | L5: =Costs!M6 | M5: =L5-$L$5 | N5: =IF(G5>0,M5/G5,"n/a")
A6: =B6&"|"&C6 | B6: A | C6: A1 | D6: A1 | E6: 0 | F6: =SUMIFS(Benefits!$I$6:$I$14,Benefits!$A$6:$A$14,A6) | G6: =F6-$F$5 | H6: =Costs!D7 | I6: =SUM(Costs!D7:F7) | J6: =Costs!I7 | K6: =Costs!J7 | L6: =Costs!M7 | M6: =L6-$L$5 | N6: =IF(G6>0,M6/G6,"n/a")
A7: =B7&"|"&C7 | B7: A | C7: A2 | D7: A2 | E7: 0 | F7: =SUMIFS(Benefits!$I$6:$I$14,Benefits!$A$6:$A$14,A7) | G7: =F7-$F$5 | H7: =Costs!D8 | I7: =SUM(Costs!D8:F8) | J7: =Costs!I8 | K7: =Costs!J8 | L7: =Costs!M8 | M7: =L7-$L$5 | N7: =IF(G7>0,M7/G7,"n/a")
A8: =B8&"|"&C8 | B8: B | C8: NA | D8: NA | E8: 1 | F8: =SUMIFS(Benefits!$I$6:$I$14,Benefits!$A$6:$A$14,A8) | G8: =F8-$F$8 | H8: =Costs!D9 | I8: =SUM(Costs!D9:F9) | J8: =Costs!I9 | K8: =Costs!J9 | L8: =Costs!M9 | M8: =L8-$L$8 | N8: =IF(G8>0,M8/G8,"n/a")
A9: =B9&"|"&C9 | B9: B | C9: B1 | D9: B1 | E9: 0 | F9: =SUMIFS(Benefits!$I$6:$I$14,Benefits!$A$6:$A$14,A9) | G9: =F9-$F$8 | H9: =Costs!D10 | I9: =SUM(Costs!D10:F10) | J9: =Costs!I10 | K9: =Costs!J10 | L9: =Costs!M10 | M9: =L9-$L$8 | N9: =IF(G9>0,M9/G9,"n/a")
A10: =B10&"|"&C10 | B10: B | C10: B2 | D10: B2 | E10: 0 | F10: =SUMIFS(Benefits!$I$6:$I$14,Benefits!$A$6:$A$14,A10) | G10: =F10-$F$8 | H10: =Costs!D11 | I10: =SUM(Costs!D11:F11) | J10: =Costs!I11 | K10: =Costs!J11 | L10: =Costs!M11 | M10: =L10-$L$8 | N10: =IF(G10>0,M10/G10,"n/a")
A11: =B11&"|"&C11 | B11: B | C11: B3 | D11: B3 | E11: 0 | F11: =SUMIFS(Benefits!$I$6:$I$14,Benefits!$A$6:$A$14,A11) | G11: =F11-$F$8 | H11: =Costs!D12 | I11: =SUM(Costs!D12:F12) | J11: =Costs!I12 | K11: =Costs!J12 | L11: =Costs!M12 | M11: =L11-$L$8 | N11: =IF(G11>0,M11/G11,"n/a")
A12: =B12&"|"&C12 | B12: C | C12: NA | D12: NA | E12: 1 | F12: =SUMIFS(Benefits!$I$6:$I$14,Benefits!$A$6:$A$14,A12) | G12: =F12-$F$12 | H12: =Costs!D13 | I12: =SUM(Costs!D13:F13) | J12: =Costs!I13 | K12: =Costs!J13 | L12: =Costs!M13 | M12: =L12-$L$12 | N12: =IF(G12>0,M12/G12,"n/a")
A13: =B13&"|"&C13 | B13: C | C13: C1 | D13: C1 | E13: 0 | F13: =SUMIFS(Benefits!$I$6:$I$14,Benefits!$A$6:$A$14,A13) | G13: =F13-$F$12 | H13: =Costs!D14 | I13: =SUM(Costs!D14:F14) | J13: =Costs!I14 | K13: =Costs!J14 | L13: =Costs!M14 | M13: =L13-$L$12 | N13: =IF(G13>0,M13/G13,"n/a")

Sheet Site CE-ICA
A1: Site-by-site CE/ICA
A2: Cost-effective: no alternative gives the same output for less, or more output for no more. Best buy: on the lower hull from No Action (IWR Planning Suite II rules).
A4: Key | B4: Site | C4: Alternative | D4: Name | E4: No Action | F4: Ordinal | G4: Lift (AAHU) | H4: Cost above No Action | I4: Lift (scaled) | J4: Cost (scaled) | K4: Dominated by | L4: Cost-effective | M4: Candidate | N4: Slope in (max) | O4: Slope out (min) | P4: Best buy | Q4: Best-buy step | R4: Previous lift (scaled) | S4: Previous cost (scaled) | T4: Incremental output | U4: Incremental cost | V4: Incremental cost per unit | W4: Unit cost | X4: Recommended
B5: A Upper
A6: =B6&"|"&C6 | B6: A | C6: NA | D6: NA | E6: 1 | F6: 1 | G6: =Summary!G5 | H6: =Summary!M5 | I6: =ROUND(G6*10^in_out_dp,0) | J6: =ROUND(H6*10^in_cost_dp,0) | K6: =SUMPRODUCT(($I$6:$I$8=I6)*($J$6:$J$8<J6)+($I$6:$I$8>I6)*($J$6:$J$8<=J6)) | L6: =IF(OR(E6=1,K6=0),1,0) | M6: =IF(AND(L6=1,E6=0,I6>0),1,0) | N6: =IF(M6=1,MAX(J6/I6,SUMPRODUCT(MAX(((J6-$J$6:$J$8)*($M$6:$M$8*($I$6:$I$8<I6)))/((I6-$I$6:$I$8)*($M$6:$M$8*($I$6:$I$8<I6))+1-($M$6:$M$8*($I$6:$I$8<I6)))-(1-($M$6:$M$8*($I$6:$I$8<I6)))*1E+300))),0) | O6: =IF(M6=1,SUMPRODUCT(MIN(((($J$6:$J$8-J6)*($M$6:$M$8*($I$6:$I$8>I6)))/(($I$6:$I$8-I6)*($M$6:$M$8*($I$6:$I$8>I6))+1-($M$6:$M$8*($I$6:$I$8>I6)))+(1-($M$6:$M$8*($I$6:$I$8>I6)))*1E+300))),0) | P6: =IF(E6=1,1,IF(AND(M6=1,N6<=O6),1,0)) | Q6: =IF(P6=1,1+SUMPRODUCT($P$6:$P$8*(($I$6:$I$8<I6)+($I$6:$I$8=I6)*($F$6:$F$8<F6))),0) | R6: =IF(Q6<=1,0,SUMPRODUCT(($Q$6:$Q$8=Q6-1)*$I$6:$I$8)) | S6: =IF(Q6<=1,0,SUMPRODUCT(($Q$6:$Q$8=Q6-1)*$J$6:$J$8)) | T6: =IF(Q6=0,"",(I6-R6)/10^in_out_dp) | U6: =IF(Q6=0,"",(J6-S6)/10^in_cost_dp) | V6: =IF(Q6=0,"",IF(I6=R6,0,U6/T6)) | W6: =IF(I6>0,(J6/10^in_cost_dp)/(I6/10^in_out_dp),"n/a") | X6: =IF(Sites!$C$5=C6,1,0)
A7: =B7&"|"&C7 | B7: A | C7: A1 | D7: A1 | E7: 0 | F7: 2 | G7: =Summary!G6 | H7: =Summary!M6 | I7: =ROUND(G7*10^in_out_dp,0) | J7: =ROUND(H7*10^in_cost_dp,0) | K7: =SUMPRODUCT(($I$6:$I$8=I7)*($J$6:$J$8<J7)+($I$6:$I$8>I7)*($J$6:$J$8<=J7)) | L7: =IF(OR(E7=1,K7=0),1,0) | M7: =IF(AND(L7=1,E7=0,I7>0),1,0) | N7: =IF(M7=1,MAX(J7/I7,SUMPRODUCT(MAX(((J7-$J$6:$J$8)*($M$6:$M$8*($I$6:$I$8<I7)))/((I7-$I$6:$I$8)*($M$6:$M$8*($I$6:$I$8<I7))+1-($M$6:$M$8*($I$6:$I$8<I7)))-(1-($M$6:$M$8*($I$6:$I$8<I7)))*1E+300))),0) | O7: =IF(M7=1,SUMPRODUCT(MIN(((($J$6:$J$8-J7)*($M$6:$M$8*($I$6:$I$8>I7)))/(($I$6:$I$8-I7)*($M$6:$M$8*($I$6:$I$8>I7))+1-($M$6:$M$8*($I$6:$I$8>I7)))+(1-($M$6:$M$8*($I$6:$I$8>I7)))*1E+300))),0) | P7: =IF(E7=1,1,IF(AND(M7=1,N7<=O7),1,0)) | Q7: =IF(P7=1,1+SUMPRODUCT($P$6:$P$8*(($I$6:$I$8<I7)+($I$6:$I$8=I7)*($F$6:$F$8<F7))),0) | R7: =IF(Q7<=1,0,SUMPRODUCT(($Q$6:$Q$8=Q7-1)*$I$6:$I$8)) | S7: =IF(Q7<=1,0,SUMPRODUCT(($Q$6:$Q$8=Q7-1)*$J$6:$J$8)) | T7: =IF(Q7=0,"",(I7-R7)/10^in_out_dp) | U7: =IF(Q7=0,"",(J7-S7)/10^in_cost_dp) | V7: =IF(Q7=0,"",IF(I7=R7,0,U7/T7)) | W7: =IF(I7>0,(J7/10^in_cost_dp)/(I7/10^in_out_dp),"n/a") | X7: =IF(Sites!$C$5=C7,1,0)
A8: =B8&"|"&C8 | B8: A | C8: A2 | D8: A2 | E8: 0 | F8: 3 | G8: =Summary!G7 | H8: =Summary!M7 | I8: =ROUND(G8*10^in_out_dp,0) | J8: =ROUND(H8*10^in_cost_dp,0) | K8: =SUMPRODUCT(($I$6:$I$8=I8)*($J$6:$J$8<J8)+($I$6:$I$8>I8)*($J$6:$J$8<=J8)) | L8: =IF(OR(E8=1,K8=0),1,0) | M8: =IF(AND(L8=1,E8=0,I8>0),1,0) | N8: =IF(M8=1,MAX(J8/I8,SUMPRODUCT(MAX(((J8-$J$6:$J$8)*($M$6:$M$8*($I$6:$I$8<I8)))/((I8-$I$6:$I$8)*($M$6:$M$8*($I$6:$I$8<I8))+1-($M$6:$M$8*($I$6:$I$8<I8)))-(1-($M$6:$M$8*($I$6:$I$8<I8)))*1E+300))),0) | O8: =IF(M8=1,SUMPRODUCT(MIN(((($J$6:$J$8-J8)*($M$6:$M$8*($I$6:$I$8>I8)))/(($I$6:$I$8-I8)*($M$6:$M$8*($I$6:$I$8>I8))+1-($M$6:$M$8*($I$6:$I$8>I8)))+(1-($M$6:$M$8*($I$6:$I$8>I8)))*1E+300))),0) | P8: =IF(E8=1,1,IF(AND(M8=1,N8<=O8),1,0)) | Q8: =IF(P8=1,1+SUMPRODUCT($P$6:$P$8*(($I$6:$I$8<I8)+($I$6:$I$8=I8)*($F$6:$F$8<F8))),0) | R8: =IF(Q8<=1,0,SUMPRODUCT(($Q$6:$Q$8=Q8-1)*$I$6:$I$8)) | S8: =IF(Q8<=1,0,SUMPRODUCT(($Q$6:$Q$8=Q8-1)*$J$6:$J$8)) | T8: =IF(Q8=0,"",(I8-R8)/10^in_out_dp) | U8: =IF(Q8=0,"",(J8-S8)/10^in_cost_dp) | V8: =IF(Q8=0,"",IF(I8=R8,0,U8/T8)) | W8: =IF(I8>0,(J8/10^in_cost_dp)/(I8/10^in_out_dp),"n/a") | X8: =IF(Sites!$C$5=C8,1,0)
B10: B Middle
A11: =B11&"|"&C11 | B11: B | C11: NA | D11: NA | E11: 1 | F11: 1 | G11: =Summary!G8 | H11: =Summary!M8 | I11: =ROUND(G11*10^in_out_dp,0) | J11: =ROUND(H11*10^in_cost_dp,0) | K11: =SUMPRODUCT(($I$11:$I$14=I11)*($J$11:$J$14<J11)+($I$11:$I$14>I11)*($J$11:$J$14<=J11)) | L11: =IF(OR(E11=1,K11=0),1,0) | M11: =IF(AND(L11=1,E11=0,I11>0),1,0) | N11: =IF(M11=1,MAX(J11/I11,SUMPRODUCT(MAX(((J11-$J$11:$J$14)*($M$11:$M$14*($I$11:$I$14<I11)))/((I11-$I$11:$I$14)*($M$11:$M$14*($I$11:$I$14<I11))+1-($M$11:$M$14*($I$11:$I$14<I11)))-(1-($M$11:$M$14*($I$11:$I$14<I11)))*1E+300))),0) | O11: =IF(M11=1,SUMPRODUCT(MIN(((($J$11:$J$14-J11)*($M$11:$M$14*($I$11:$I$14>I11)))/(($I$11:$I$14-I11)*($M$11:$M$14*($I$11:$I$14>I11))+1-($M$11:$M$14*($I$11:$I$14>I11)))+(1-($M$11:$M$14*($I$11:$I$14>I11)))*1E+300))),0) | P11: =IF(E11=1,1,IF(AND(M11=1,N11<=O11),1,0)) | Q11: =IF(P11=1,1+SUMPRODUCT($P$11:$P$14*(($I$11:$I$14<I11)+($I$11:$I$14=I11)*($F$11:$F$14<F11))),0) | R11: =IF(Q11<=1,0,SUMPRODUCT(($Q$11:$Q$14=Q11-1)*$I$11:$I$14)) | S11: =IF(Q11<=1,0,SUMPRODUCT(($Q$11:$Q$14=Q11-1)*$J$11:$J$14)) | T11: =IF(Q11=0,"",(I11-R11)/10^in_out_dp) | U11: =IF(Q11=0,"",(J11-S11)/10^in_cost_dp) | V11: =IF(Q11=0,"",IF(I11=R11,0,U11/T11)) | W11: =IF(I11>0,(J11/10^in_cost_dp)/(I11/10^in_out_dp),"n/a") | X11: =IF(Sites!$C$6=C11,1,0)
A12: =B12&"|"&C12 | B12: B | C12: B1 | D12: B1 | E12: 0 | F12: 2 | G12: =Summary!G9 | H12: =Summary!M9 | I12: =ROUND(G12*10^in_out_dp,0) | J12: =ROUND(H12*10^in_cost_dp,0) | K12: =SUMPRODUCT(($I$11:$I$14=I12)*($J$11:$J$14<J12)+($I$11:$I$14>I12)*($J$11:$J$14<=J12)) | L12: =IF(OR(E12=1,K12=0),1,0) | M12: =IF(AND(L12=1,E12=0,I12>0),1,0) | N12: =IF(M12=1,MAX(J12/I12,SUMPRODUCT(MAX(((J12-$J$11:$J$14)*($M$11:$M$14*($I$11:$I$14<I12)))/((I12-$I$11:$I$14)*($M$11:$M$14*($I$11:$I$14<I12))+1-($M$11:$M$14*($I$11:$I$14<I12)))-(1-($M$11:$M$14*($I$11:$I$14<I12)))*1E+300))),0) | O12: =IF(M12=1,SUMPRODUCT(MIN(((($J$11:$J$14-J12)*($M$11:$M$14*($I$11:$I$14>I12)))/(($I$11:$I$14-I12)*($M$11:$M$14*($I$11:$I$14>I12))+1-($M$11:$M$14*($I$11:$I$14>I12)))+(1-($M$11:$M$14*($I$11:$I$14>I12)))*1E+300))),0) | P12: =IF(E12=1,1,IF(AND(M12=1,N12<=O12),1,0)) | Q12: =IF(P12=1,1+SUMPRODUCT($P$11:$P$14*(($I$11:$I$14<I12)+($I$11:$I$14=I12)*($F$11:$F$14<F12))),0) | R12: =IF(Q12<=1,0,SUMPRODUCT(($Q$11:$Q$14=Q12-1)*$I$11:$I$14)) | S12: =IF(Q12<=1,0,SUMPRODUCT(($Q$11:$Q$14=Q12-1)*$J$11:$J$14)) | T12: =IF(Q12=0,"",(I12-R12)/10^in_out_dp) | U12: =IF(Q12=0,"",(J12-S12)/10^in_cost_dp) | V12: =IF(Q12=0,"",IF(I12=R12,0,U12/T12)) | W12: =IF(I12>0,(J12/10^in_cost_dp)/(I12/10^in_out_dp),"n/a") | X12: =IF(Sites!$C$6=C12,1,0)
A13: =B13&"|"&C13 | B13: B | C13: B2 | D13: B2 | E13: 0 | F13: 3 | G13: =Summary!G10 | H13: =Summary!M10 | I13: =ROUND(G13*10^in_out_dp,0) | J13: =ROUND(H13*10^in_cost_dp,0) | K13: =SUMPRODUCT(($I$11:$I$14=I13)*($J$11:$J$14<J13)+($I$11:$I$14>I13)*($J$11:$J$14<=J13)) | L13: =IF(OR(E13=1,K13=0),1,0) | M13: =IF(AND(L13=1,E13=0,I13>0),1,0) | N13: =IF(M13=1,MAX(J13/I13,SUMPRODUCT(MAX(((J13-$J$11:$J$14)*($M$11:$M$14*($I$11:$I$14<I13)))/((I13-$I$11:$I$14)*($M$11:$M$14*($I$11:$I$14<I13))+1-($M$11:$M$14*($I$11:$I$14<I13)))-(1-($M$11:$M$14*($I$11:$I$14<I13)))*1E+300))),0) | O13: =IF(M13=1,SUMPRODUCT(MIN(((($J$11:$J$14-J13)*($M$11:$M$14*($I$11:$I$14>I13)))/(($I$11:$I$14-I13)*($M$11:$M$14*($I$11:$I$14>I13))+1-($M$11:$M$14*($I$11:$I$14>I13)))+(1-($M$11:$M$14*($I$11:$I$14>I13)))*1E+300))),0) | P13: =IF(E13=1,1,IF(AND(M13=1,N13<=O13),1,0)) | Q13: =IF(P13=1,1+SUMPRODUCT($P$11:$P$14*(($I$11:$I$14<I13)+($I$11:$I$14=I13)*($F$11:$F$14<F13))),0) | R13: =IF(Q13<=1,0,SUMPRODUCT(($Q$11:$Q$14=Q13-1)*$I$11:$I$14)) | S13: =IF(Q13<=1,0,SUMPRODUCT(($Q$11:$Q$14=Q13-1)*$J$11:$J$14)) | T13: =IF(Q13=0,"",(I13-R13)/10^in_out_dp) | U13: =IF(Q13=0,"",(J13-S13)/10^in_cost_dp) | V13: =IF(Q13=0,"",IF(I13=R13,0,U13/T13)) | W13: =IF(I13>0,(J13/10^in_cost_dp)/(I13/10^in_out_dp),"n/a") | X13: =IF(Sites!$C$6=C13,1,0)
A14: =B14&"|"&C14 | B14: B | C14: B3 | D14: B3 | E14: 0 | F14: 4 | G14: =Summary!G11 | H14: =Summary!M11 | I14: =ROUND(G14*10^in_out_dp,0) | J14: =ROUND(H14*10^in_cost_dp,0) | K14: =SUMPRODUCT(($I$11:$I$14=I14)*($J$11:$J$14<J14)+($I$11:$I$14>I14)*($J$11:$J$14<=J14)) | L14: =IF(OR(E14=1,K14=0),1,0) | M14: =IF(AND(L14=1,E14=0,I14>0),1,0) | N14: =IF(M14=1,MAX(J14/I14,SUMPRODUCT(MAX(((J14-$J$11:$J$14)*($M$11:$M$14*($I$11:$I$14<I14)))/((I14-$I$11:$I$14)*($M$11:$M$14*($I$11:$I$14<I14))+1-($M$11:$M$14*($I$11:$I$14<I14)))-(1-($M$11:$M$14*($I$11:$I$14<I14)))*1E+300))),0) | O14: =IF(M14=1,SUMPRODUCT(MIN(((($J$11:$J$14-J14)*($M$11:$M$14*($I$11:$I$14>I14)))/(($I$11:$I$14-I14)*($M$11:$M$14*($I$11:$I$14>I14))+1-($M$11:$M$14*($I$11:$I$14>I14)))+(1-($M$11:$M$14*($I$11:$I$14>I14)))*1E+300))),0) | P14: =IF(E14=1,1,IF(AND(M14=1,N14<=O14),1,0)) | Q14: =IF(P14=1,1+SUMPRODUCT($P$11:$P$14*(($I$11:$I$14<I14)+($I$11:$I$14=I14)*($F$11:$F$14<F14))),0) | R14: =IF(Q14<=1,0,SUMPRODUCT(($Q$11:$Q$14=Q14-1)*$I$11:$I$14)) | S14: =IF(Q14<=1,0,SUMPRODUCT(($Q$11:$Q$14=Q14-1)*$J$11:$J$14)) | T14: =IF(Q14=0,"",(I14-R14)/10^in_out_dp) | U14: =IF(Q14=0,"",(J14-S14)/10^in_cost_dp) | V14: =IF(Q14=0,"",IF(I14=R14,0,U14/T14)) | W14: =IF(I14>0,(J14/10^in_cost_dp)/(I14/10^in_out_dp),"n/a") | X14: =IF(Sites!$C$6=C14,1,0)
B16: C Lower
A17: =B17&"|"&C17 | B17: C | C17: NA | D17: NA | E17: 1 | F17: 1 | G17: =Summary!G12 | H17: =Summary!M12 | I17: =ROUND(G17*10^in_out_dp,0) | J17: =ROUND(H17*10^in_cost_dp,0) | K17: =SUMPRODUCT(($I$17:$I$18=I17)*($J$17:$J$18<J17)+($I$17:$I$18>I17)*($J$17:$J$18<=J17)) | L17: =IF(OR(E17=1,K17=0),1,0) | M17: =IF(AND(L17=1,E17=0,I17>0),1,0) | N17: =IF(M17=1,MAX(J17/I17,SUMPRODUCT(MAX(((J17-$J$17:$J$18)*($M$17:$M$18*($I$17:$I$18<I17)))/((I17-$I$17:$I$18)*($M$17:$M$18*($I$17:$I$18<I17))+1-($M$17:$M$18*($I$17:$I$18<I17)))-(1-($M$17:$M$18*($I$17:$I$18<I17)))*1E+300))),0) | O17: =IF(M17=1,SUMPRODUCT(MIN(((($J$17:$J$18-J17)*($M$17:$M$18*($I$17:$I$18>I17)))/(($I$17:$I$18-I17)*($M$17:$M$18*($I$17:$I$18>I17))+1-($M$17:$M$18*($I$17:$I$18>I17)))+(1-($M$17:$M$18*($I$17:$I$18>I17)))*1E+300))),0) | P17: =IF(E17=1,1,IF(AND(M17=1,N17<=O17),1,0)) | Q17: =IF(P17=1,1+SUMPRODUCT($P$17:$P$18*(($I$17:$I$18<I17)+($I$17:$I$18=I17)*($F$17:$F$18<F17))),0) | R17: =IF(Q17<=1,0,SUMPRODUCT(($Q$17:$Q$18=Q17-1)*$I$17:$I$18)) | S17: =IF(Q17<=1,0,SUMPRODUCT(($Q$17:$Q$18=Q17-1)*$J$17:$J$18)) | T17: =IF(Q17=0,"",(I17-R17)/10^in_out_dp) | U17: =IF(Q17=0,"",(J17-S17)/10^in_cost_dp) | V17: =IF(Q17=0,"",IF(I17=R17,0,U17/T17)) | W17: =IF(I17>0,(J17/10^in_cost_dp)/(I17/10^in_out_dp),"n/a") | X17: =IF(Sites!$C$7=C17,1,0)
A18: =B18&"|"&C18 | B18: C | C18: C1 | D18: C1 | E18: 0 | F18: 2 | G18: =Summary!G13 | H18: =Summary!M13 | I18: =ROUND(G18*10^in_out_dp,0) | J18: =ROUND(H18*10^in_cost_dp,0) | K18: =SUMPRODUCT(($I$17:$I$18=I18)*($J$17:$J$18<J18)+($I$17:$I$18>I18)*($J$17:$J$18<=J18)) | L18: =IF(OR(E18=1,K18=0),1,0) | M18: =IF(AND(L18=1,E18=0,I18>0),1,0) | N18: =IF(M18=1,MAX(J18/I18,SUMPRODUCT(MAX(((J18-$J$17:$J$18)*($M$17:$M$18*($I$17:$I$18<I18)))/((I18-$I$17:$I$18)*($M$17:$M$18*($I$17:$I$18<I18))+1-($M$17:$M$18*($I$17:$I$18<I18)))-(1-($M$17:$M$18*($I$17:$I$18<I18)))*1E+300))),0) | O18: =IF(M18=1,SUMPRODUCT(MIN(((($J$17:$J$18-J18)*($M$17:$M$18*($I$17:$I$18>I18)))/(($I$17:$I$18-I18)*($M$17:$M$18*($I$17:$I$18>I18))+1-($M$17:$M$18*($I$17:$I$18>I18)))+(1-($M$17:$M$18*($I$17:$I$18>I18)))*1E+300))),0) | P18: =IF(E18=1,1,IF(AND(M18=1,N18<=O18),1,0)) | Q18: =IF(P18=1,1+SUMPRODUCT($P$17:$P$18*(($I$17:$I$18<I18)+($I$17:$I$18=I18)*($F$17:$F$18<F18))),0) | R18: =IF(Q18<=1,0,SUMPRODUCT(($Q$17:$Q$18=Q18-1)*$I$17:$I$18)) | S18: =IF(Q18<=1,0,SUMPRODUCT(($Q$17:$Q$18=Q18-1)*$J$17:$J$18)) | T18: =IF(Q18=0,"",(I18-R18)/10^in_out_dp) | U18: =IF(Q18=0,"",(J18-S18)/10^in_cost_dp) | V18: =IF(Q18=0,"",IF(I18=R18,0,U18/T18)) | W18: =IF(I18>0,(J18/10^in_cost_dp)/(I18/10^in_out_dp),"n/a") | X18: =IF(Sites!$C$7=C18,1,0)

Sheet Sites
A1: Sites: the alternative carried to the watershed plans
A2: Choose each site's recommended alternative. No Action leaves the site out of every watershed plan.
A4: Site | B4: Name | C4: Recommended alternative | D4: No Action | E4: Carried | F4: Lift (AAHU) | G4: Cost above No Action | H4: Construction cost | I4: Lift (scaled) | J4: Cost (scaled) | K4: Cost-effective | L4: Best buy | M4: Decided by
A5: A | B5: Upper | C5: A1 | D5: NA | E5: =IF(C5<>D5,1,0) | F5: =IFERROR(INDEX('Site CE-ICA'!$G$5:$G$18,MATCH(A5&"|"&C5,'Site CE-ICA'!$A$5:$A$18,0)),0) | G5: =IFERROR(INDEX('Site CE-ICA'!$H$5:$H$18,MATCH(A5&"|"&C5,'Site CE-ICA'!$A$5:$A$18,0)),0) | H5: =IFERROR(INDEX(Summary!$H$5:$H$7,MATCH(C5,Summary!$C$5:$C$7,0)),0) | I5: =IF(E5=1,IFERROR(INDEX('Site CE-ICA'!$I$5:$I$18,MATCH(A5&"|"&C5,'Site CE-ICA'!$A$5:$A$18,0)),0),0) | J5: =IF(E5=1,IFERROR(INDEX('Site CE-ICA'!$J$5:$J$18,MATCH(A5&"|"&C5,'Site CE-ICA'!$A$5:$A$18,0)),0),0) | K5: =IFERROR(INDEX('Site CE-ICA'!$L$5:$L$18,MATCH(A5&"|"&C5,'Site CE-ICA'!$A$5:$A$18,0)),0) | L5: =IFERROR(INDEX('Site CE-ICA'!$P$5:$P$18,MATCH(A5&"|"&C5,'Site CE-ICA'!$A$5:$A$18,0)),0) | M5: Suggested
A6: B | B6: Middle | C6: B3 | D6: NA | E6: =IF(C6<>D6,1,0) | F6: =IFERROR(INDEX('Site CE-ICA'!$G$5:$G$18,MATCH(A6&"|"&C6,'Site CE-ICA'!$A$5:$A$18,0)),0) | G6: =IFERROR(INDEX('Site CE-ICA'!$H$5:$H$18,MATCH(A6&"|"&C6,'Site CE-ICA'!$A$5:$A$18,0)),0) | H6: =IFERROR(INDEX(Summary!$H$8:$H$11,MATCH(C6,Summary!$C$8:$C$11,0)),0) | I6: =IF(E6=1,IFERROR(INDEX('Site CE-ICA'!$I$5:$I$18,MATCH(A6&"|"&C6,'Site CE-ICA'!$A$5:$A$18,0)),0),0) | J6: =IF(E6=1,IFERROR(INDEX('Site CE-ICA'!$J$5:$J$18,MATCH(A6&"|"&C6,'Site CE-ICA'!$A$5:$A$18,0)),0),0) | K6: =IFERROR(INDEX('Site CE-ICA'!$L$5:$L$18,MATCH(A6&"|"&C6,'Site CE-ICA'!$A$5:$A$18,0)),0) | L6: =IFERROR(INDEX('Site CE-ICA'!$P$5:$P$18,MATCH(A6&"|"&C6,'Site CE-ICA'!$A$5:$A$18,0)),0) | M6: Suggested
A7: C | B7: Lower | C7: C1 | D7: NA | E7: =IF(C7<>D7,1,0) | F7: =IFERROR(INDEX('Site CE-ICA'!$G$5:$G$18,MATCH(A7&"|"&C7,'Site CE-ICA'!$A$5:$A$18,0)),0) | G7: =IFERROR(INDEX('Site CE-ICA'!$H$5:$H$18,MATCH(A7&"|"&C7,'Site CE-ICA'!$A$5:$A$18,0)),0) | H7: =IFERROR(INDEX(Summary!$H$12:$H$13,MATCH(C7,Summary!$C$12:$C$13,0)),0) | I7: =IF(E7=1,IFERROR(INDEX('Site CE-ICA'!$I$5:$I$18,MATCH(A7&"|"&C7,'Site CE-ICA'!$A$5:$A$18,0)),0),0) | J7: =IF(E7=1,IFERROR(INDEX('Site CE-ICA'!$J$5:$J$18,MATCH(A7&"|"&C7,'Site CE-ICA'!$A$5:$A$18,0)),0),0) | K7: =IFERROR(INDEX('Site CE-ICA'!$L$5:$L$18,MATCH(A7&"|"&C7,'Site CE-ICA'!$A$5:$A$18,0)),0) | L7: =IFERROR(INDEX('Site CE-ICA'!$P$5:$P$18,MATCH(A7&"|"&C7,'Site CE-ICA'!$A$5:$A$18,0)),0) | M7: Suggested

Sheet Watershed plans
A1: Watershed plans: every combination of the recommended site actions
A2: 1 and 0 mark a site included or excluded. Rows that include a site whose recommendation is No Action are not valid plans.
C4: Site | D4: A | E4: B | F4: C
C5: Carried | D5: =Sites!E5 | E5: =Sites!E6 | F5: =Sites!E7
C6: Lift (scaled) | D6: =Sites!I5 | E6: =Sites!I6 | F6: =Sites!I7
C7: Cost (scaled) | D7: =Sites!J5 | E7: =Sites!J6 | F7: =Sites!J7
C8: Construction cost | D8: =Sites!H5 | E8: =Sites!H6 | F8: =Sites!H7
C9: Weight | D9: =IF(D5=1,2^SUM(E5:$F$5),0) | E9: =IF(E5=1,2^SUM(F5:$F$5),0) | F9: =IF(F5=1,1,0)
A11: Row | B11: Plan | C11: Valid | D11: A | E11: B | F11: C | G11: Plan number | H11: Lift (scaled) | I11: Cost (scaled) | J11: Construction cost | K11: Lift (AAHU) | L11: Average annual cost | M11: No Action | N11: Dominated by | O11: Cost-effective | P11: Candidate | Q11: Slope in (max) | R11: Slope out (min) | S11: Best buy | T11: Best-buy step | U11: Previous lift (scaled) | V11: Previous cost (scaled) | W11: Incremental output | X11: Incremental cost | Y11: Incremental cost per unit | Z11: Unit cost | AA11: Final array | AB11: Final array order
A12: 1 | B12: No Action | C12: =IF(SUMPRODUCT(D12:F12,1-$D$5:$F$5)=0,1,0) | D12: 0 | E12: 0 | F12: 0 | G12: =IF(C12=1,1+SUMPRODUCT(D12:F12,$D$9:$F$9),"") | H12: =SUMPRODUCT(D12:F12,$D$6:$F$6) | I12: =SUMPRODUCT(D12:F12,$D$7:$F$7) | J12: =SUMPRODUCT(D12:F12,$D$8:$F$8) | K12: =H12/10^in_out_dp | L12: =I12/10^in_cost_dp | M12: =IF(SUM(D12:F12)=0,1,0) | N12: =SUMPRODUCT($C$12:$C$19*(($H$12:$H$19=H12)*($I$12:$I$19<I12)+($H$12:$H$19>H12)*($I$12:$I$19<=I12))) | O12: =IF(C12=0,0,IF(OR(M12=1,N12=0),1,0)) | P12: =IF(AND(O12=1,M12=0,H12>0),1,0) | Q12: =IF(P12=1,MAX(I12/H12,SUMPRODUCT(MAX(((I12-$I$12:$I$19)*($P$12:$P$19*($H$12:$H$19<H12)))/((H12-$H$12:$H$19)*($P$12:$P$19*($H$12:$H$19<H12))+1-($P$12:$P$19*($H$12:$H$19<H12)))-(1-($P$12:$P$19*($H$12:$H$19<H12)))*1E+300))),0) | R12: =IF(P12=1,SUMPRODUCT(MIN(((($I$12:$I$19-I12)*($P$12:$P$19*($H$12:$H$19>H12)))/(($H$12:$H$19-H12)*($P$12:$P$19*($H$12:$H$19>H12))+1-($P$12:$P$19*($H$12:$H$19>H12)))+(1-($P$12:$P$19*($H$12:$H$19>H12)))*1E+300))),0) | S12: =IF(C12=0,0,IF(M12=1,1,IF(AND(P12=1,Q12<=R12),1,0))) | T12: =IF(S12=1,1+SUMPRODUCT($S$12:$S$19*(($H$12:$H$19<H12)+($H$12:$H$19=H12)*($A$12:$A$19<A12))),0) | U12: =IF(T12<=1,0,SUMPRODUCT(($T$12:$T$19=T12-1)*$H$12:$H$19)) | V12: =IF(T12<=1,0,SUMPRODUCT(($T$12:$T$19=T12-1)*$I$12:$I$19)) | W12: =IF(T12=0,"",(H12-U12)/10^in_out_dp) | X12: =IF(T12=0,"",(I12-V12)/10^in_cost_dp) | Y12: =IF(T12=0,"",IF(H12=U12,0,X12/W12)) | Z12: =IF(AND(C12=1,H12>0),L12/K12,"n/a") | AA12: 1 | AB12: =IF(AND(C12=1,AA12=1),1+SUMPRODUCT($C$12:$C$19*$AA$12:$AA$19*(($H$12:$H$19<H12)+($H$12:$H$19=H12)*($I$12:$I$19<I12)+($H$12:$H$19=H12)*($I$12:$I$19=I12)*($A$12:$A$19<A12))),0)
A13: 2 | B13: C | C13: =IF(SUMPRODUCT(D13:F13,1-$D$5:$F$5)=0,1,0) | D13: 0 | E13: 0 | F13: 1 | G13: =IF(C13=1,1+SUMPRODUCT(D13:F13,$D$9:$F$9),"") | H13: =SUMPRODUCT(D13:F13,$D$6:$F$6) | I13: =SUMPRODUCT(D13:F13,$D$7:$F$7) | J13: =SUMPRODUCT(D13:F13,$D$8:$F$8) | K13: =H13/10^in_out_dp | L13: =I13/10^in_cost_dp | M13: =IF(SUM(D13:F13)=0,1,0) | N13: =SUMPRODUCT($C$12:$C$19*(($H$12:$H$19=H13)*($I$12:$I$19<I13)+($H$12:$H$19>H13)*($I$12:$I$19<=I13))) | O13: =IF(C13=0,0,IF(OR(M13=1,N13=0),1,0)) | P13: =IF(AND(O13=1,M13=0,H13>0),1,0) | Q13: =IF(P13=1,MAX(I13/H13,SUMPRODUCT(MAX(((I13-$I$12:$I$19)*($P$12:$P$19*($H$12:$H$19<H13)))/((H13-$H$12:$H$19)*($P$12:$P$19*($H$12:$H$19<H13))+1-($P$12:$P$19*($H$12:$H$19<H13)))-(1-($P$12:$P$19*($H$12:$H$19<H13)))*1E+300))),0) | R13: =IF(P13=1,SUMPRODUCT(MIN(((($I$12:$I$19-I13)*($P$12:$P$19*($H$12:$H$19>H13)))/(($H$12:$H$19-H13)*($P$12:$P$19*($H$12:$H$19>H13))+1-($P$12:$P$19*($H$12:$H$19>H13)))+(1-($P$12:$P$19*($H$12:$H$19>H13)))*1E+300))),0) | S13: =IF(C13=0,0,IF(M13=1,1,IF(AND(P13=1,Q13<=R13),1,0))) | T13: =IF(S13=1,1+SUMPRODUCT($S$12:$S$19*(($H$12:$H$19<H13)+($H$12:$H$19=H13)*($A$12:$A$19<A13))),0) | U13: =IF(T13<=1,0,SUMPRODUCT(($T$12:$T$19=T13-1)*$H$12:$H$19)) | V13: =IF(T13<=1,0,SUMPRODUCT(($T$12:$T$19=T13-1)*$I$12:$I$19)) | W13: =IF(T13=0,"",(H13-U13)/10^in_out_dp) | X13: =IF(T13=0,"",(I13-V13)/10^in_cost_dp) | Y13: =IF(T13=0,"",IF(H13=U13,0,X13/W13)) | Z13: =IF(AND(C13=1,H13>0),L13/K13,"n/a") | AA13: 0 | AB13: =IF(AND(C13=1,AA13=1),1+SUMPRODUCT($C$12:$C$19*$AA$12:$AA$19*(($H$12:$H$19<H13)+($H$12:$H$19=H13)*($I$12:$I$19<I13)+($H$12:$H$19=H13)*($I$12:$I$19=I13)*($A$12:$A$19<A13))),0)
A14: 3 | B14: B | C14: =IF(SUMPRODUCT(D14:F14,1-$D$5:$F$5)=0,1,0) | D14: 0 | E14: 1 | F14: 0 | G14: =IF(C14=1,1+SUMPRODUCT(D14:F14,$D$9:$F$9),"") | H14: =SUMPRODUCT(D14:F14,$D$6:$F$6) | I14: =SUMPRODUCT(D14:F14,$D$7:$F$7) | J14: =SUMPRODUCT(D14:F14,$D$8:$F$8) | K14: =H14/10^in_out_dp | L14: =I14/10^in_cost_dp | M14: =IF(SUM(D14:F14)=0,1,0) | N14: =SUMPRODUCT($C$12:$C$19*(($H$12:$H$19=H14)*($I$12:$I$19<I14)+($H$12:$H$19>H14)*($I$12:$I$19<=I14))) | O14: =IF(C14=0,0,IF(OR(M14=1,N14=0),1,0)) | P14: =IF(AND(O14=1,M14=0,H14>0),1,0) | Q14: =IF(P14=1,MAX(I14/H14,SUMPRODUCT(MAX(((I14-$I$12:$I$19)*($P$12:$P$19*($H$12:$H$19<H14)))/((H14-$H$12:$H$19)*($P$12:$P$19*($H$12:$H$19<H14))+1-($P$12:$P$19*($H$12:$H$19<H14)))-(1-($P$12:$P$19*($H$12:$H$19<H14)))*1E+300))),0) | R14: =IF(P14=1,SUMPRODUCT(MIN(((($I$12:$I$19-I14)*($P$12:$P$19*($H$12:$H$19>H14)))/(($H$12:$H$19-H14)*($P$12:$P$19*($H$12:$H$19>H14))+1-($P$12:$P$19*($H$12:$H$19>H14)))+(1-($P$12:$P$19*($H$12:$H$19>H14)))*1E+300))),0) | S14: =IF(C14=0,0,IF(M14=1,1,IF(AND(P14=1,Q14<=R14),1,0))) | T14: =IF(S14=1,1+SUMPRODUCT($S$12:$S$19*(($H$12:$H$19<H14)+($H$12:$H$19=H14)*($A$12:$A$19<A14))),0) | U14: =IF(T14<=1,0,SUMPRODUCT(($T$12:$T$19=T14-1)*$H$12:$H$19)) | V14: =IF(T14<=1,0,SUMPRODUCT(($T$12:$T$19=T14-1)*$I$12:$I$19)) | W14: =IF(T14=0,"",(H14-U14)/10^in_out_dp) | X14: =IF(T14=0,"",(I14-V14)/10^in_cost_dp) | Y14: =IF(T14=0,"",IF(H14=U14,0,X14/W14)) | Z14: =IF(AND(C14=1,H14>0),L14/K14,"n/a") | AA14: 1 | AB14: =IF(AND(C14=1,AA14=1),1+SUMPRODUCT($C$12:$C$19*$AA$12:$AA$19*(($H$12:$H$19<H14)+($H$12:$H$19=H14)*($I$12:$I$19<I14)+($H$12:$H$19=H14)*($I$12:$I$19=I14)*($A$12:$A$19<A14))),0)
A15: 4 | B15: B + C | C15: =IF(SUMPRODUCT(D15:F15,1-$D$5:$F$5)=0,1,0) | D15: 0 | E15: 1 | F15: 1 | G15: =IF(C15=1,1+SUMPRODUCT(D15:F15,$D$9:$F$9),"") | H15: =SUMPRODUCT(D15:F15,$D$6:$F$6) | I15: =SUMPRODUCT(D15:F15,$D$7:$F$7) | J15: =SUMPRODUCT(D15:F15,$D$8:$F$8) | K15: =H15/10^in_out_dp | L15: =I15/10^in_cost_dp | M15: =IF(SUM(D15:F15)=0,1,0) | N15: =SUMPRODUCT($C$12:$C$19*(($H$12:$H$19=H15)*($I$12:$I$19<I15)+($H$12:$H$19>H15)*($I$12:$I$19<=I15))) | O15: =IF(C15=0,0,IF(OR(M15=1,N15=0),1,0)) | P15: =IF(AND(O15=1,M15=0,H15>0),1,0) | Q15: =IF(P15=1,MAX(I15/H15,SUMPRODUCT(MAX(((I15-$I$12:$I$19)*($P$12:$P$19*($H$12:$H$19<H15)))/((H15-$H$12:$H$19)*($P$12:$P$19*($H$12:$H$19<H15))+1-($P$12:$P$19*($H$12:$H$19<H15)))-(1-($P$12:$P$19*($H$12:$H$19<H15)))*1E+300))),0) | R15: =IF(P15=1,SUMPRODUCT(MIN(((($I$12:$I$19-I15)*($P$12:$P$19*($H$12:$H$19>H15)))/(($H$12:$H$19-H15)*($P$12:$P$19*($H$12:$H$19>H15))+1-($P$12:$P$19*($H$12:$H$19>H15)))+(1-($P$12:$P$19*($H$12:$H$19>H15)))*1E+300))),0) | S15: =IF(C15=0,0,IF(M15=1,1,IF(AND(P15=1,Q15<=R15),1,0))) | T15: =IF(S15=1,1+SUMPRODUCT($S$12:$S$19*(($H$12:$H$19<H15)+($H$12:$H$19=H15)*($A$12:$A$19<A15))),0) | U15: =IF(T15<=1,0,SUMPRODUCT(($T$12:$T$19=T15-1)*$H$12:$H$19)) | V15: =IF(T15<=1,0,SUMPRODUCT(($T$12:$T$19=T15-1)*$I$12:$I$19)) | W15: =IF(T15=0,"",(H15-U15)/10^in_out_dp) | X15: =IF(T15=0,"",(I15-V15)/10^in_cost_dp) | Y15: =IF(T15=0,"",IF(H15=U15,0,X15/W15)) | Z15: =IF(AND(C15=1,H15>0),L15/K15,"n/a") | AA15: 0 | AB15: =IF(AND(C15=1,AA15=1),1+SUMPRODUCT($C$12:$C$19*$AA$12:$AA$19*(($H$12:$H$19<H15)+($H$12:$H$19=H15)*($I$12:$I$19<I15)+($H$12:$H$19=H15)*($I$12:$I$19=I15)*($A$12:$A$19<A15))),0)
A16: 5 | B16: A | C16: =IF(SUMPRODUCT(D16:F16,1-$D$5:$F$5)=0,1,0) | D16: 1 | E16: 0 | F16: 0 | G16: =IF(C16=1,1+SUMPRODUCT(D16:F16,$D$9:$F$9),"") | H16: =SUMPRODUCT(D16:F16,$D$6:$F$6) | I16: =SUMPRODUCT(D16:F16,$D$7:$F$7) | J16: =SUMPRODUCT(D16:F16,$D$8:$F$8) | K16: =H16/10^in_out_dp | L16: =I16/10^in_cost_dp | M16: =IF(SUM(D16:F16)=0,1,0) | N16: =SUMPRODUCT($C$12:$C$19*(($H$12:$H$19=H16)*($I$12:$I$19<I16)+($H$12:$H$19>H16)*($I$12:$I$19<=I16))) | O16: =IF(C16=0,0,IF(OR(M16=1,N16=0),1,0)) | P16: =IF(AND(O16=1,M16=0,H16>0),1,0) | Q16: =IF(P16=1,MAX(I16/H16,SUMPRODUCT(MAX(((I16-$I$12:$I$19)*($P$12:$P$19*($H$12:$H$19<H16)))/((H16-$H$12:$H$19)*($P$12:$P$19*($H$12:$H$19<H16))+1-($P$12:$P$19*($H$12:$H$19<H16)))-(1-($P$12:$P$19*($H$12:$H$19<H16)))*1E+300))),0) | R16: =IF(P16=1,SUMPRODUCT(MIN(((($I$12:$I$19-I16)*($P$12:$P$19*($H$12:$H$19>H16)))/(($H$12:$H$19-H16)*($P$12:$P$19*($H$12:$H$19>H16))+1-($P$12:$P$19*($H$12:$H$19>H16)))+(1-($P$12:$P$19*($H$12:$H$19>H16)))*1E+300))),0) | S16: =IF(C16=0,0,IF(M16=1,1,IF(AND(P16=1,Q16<=R16),1,0))) | T16: =IF(S16=1,1+SUMPRODUCT($S$12:$S$19*(($H$12:$H$19<H16)+($H$12:$H$19=H16)*($A$12:$A$19<A16))),0) | U16: =IF(T16<=1,0,SUMPRODUCT(($T$12:$T$19=T16-1)*$H$12:$H$19)) | V16: =IF(T16<=1,0,SUMPRODUCT(($T$12:$T$19=T16-1)*$I$12:$I$19)) | W16: =IF(T16=0,"",(H16-U16)/10^in_out_dp) | X16: =IF(T16=0,"",(I16-V16)/10^in_cost_dp) | Y16: =IF(T16=0,"",IF(H16=U16,0,X16/W16)) | Z16: =IF(AND(C16=1,H16>0),L16/K16,"n/a") | AA16: 0 | AB16: =IF(AND(C16=1,AA16=1),1+SUMPRODUCT($C$12:$C$19*$AA$12:$AA$19*(($H$12:$H$19<H16)+($H$12:$H$19=H16)*($I$12:$I$19<I16)+($H$12:$H$19=H16)*($I$12:$I$19=I16)*($A$12:$A$19<A16))),0)
A17: 6 | B17: A + C | C17: =IF(SUMPRODUCT(D17:F17,1-$D$5:$F$5)=0,1,0) | D17: 1 | E17: 0 | F17: 1 | G17: =IF(C17=1,1+SUMPRODUCT(D17:F17,$D$9:$F$9),"") | H17: =SUMPRODUCT(D17:F17,$D$6:$F$6) | I17: =SUMPRODUCT(D17:F17,$D$7:$F$7) | J17: =SUMPRODUCT(D17:F17,$D$8:$F$8) | K17: =H17/10^in_out_dp | L17: =I17/10^in_cost_dp | M17: =IF(SUM(D17:F17)=0,1,0) | N17: =SUMPRODUCT($C$12:$C$19*(($H$12:$H$19=H17)*($I$12:$I$19<I17)+($H$12:$H$19>H17)*($I$12:$I$19<=I17))) | O17: =IF(C17=0,0,IF(OR(M17=1,N17=0),1,0)) | P17: =IF(AND(O17=1,M17=0,H17>0),1,0) | Q17: =IF(P17=1,MAX(I17/H17,SUMPRODUCT(MAX(((I17-$I$12:$I$19)*($P$12:$P$19*($H$12:$H$19<H17)))/((H17-$H$12:$H$19)*($P$12:$P$19*($H$12:$H$19<H17))+1-($P$12:$P$19*($H$12:$H$19<H17)))-(1-($P$12:$P$19*($H$12:$H$19<H17)))*1E+300))),0) | R17: =IF(P17=1,SUMPRODUCT(MIN(((($I$12:$I$19-I17)*($P$12:$P$19*($H$12:$H$19>H17)))/(($H$12:$H$19-H17)*($P$12:$P$19*($H$12:$H$19>H17))+1-($P$12:$P$19*($H$12:$H$19>H17)))+(1-($P$12:$P$19*($H$12:$H$19>H17)))*1E+300))),0) | S17: =IF(C17=0,0,IF(M17=1,1,IF(AND(P17=1,Q17<=R17),1,0))) | T17: =IF(S17=1,1+SUMPRODUCT($S$12:$S$19*(($H$12:$H$19<H17)+($H$12:$H$19=H17)*($A$12:$A$19<A17))),0) | U17: =IF(T17<=1,0,SUMPRODUCT(($T$12:$T$19=T17-1)*$H$12:$H$19)) | V17: =IF(T17<=1,0,SUMPRODUCT(($T$12:$T$19=T17-1)*$I$12:$I$19)) | W17: =IF(T17=0,"",(H17-U17)/10^in_out_dp) | X17: =IF(T17=0,"",(I17-V17)/10^in_cost_dp) | Y17: =IF(T17=0,"",IF(H17=U17,0,X17/W17)) | Z17: =IF(AND(C17=1,H17>0),L17/K17,"n/a") | AA17: 0 | AB17: =IF(AND(C17=1,AA17=1),1+SUMPRODUCT($C$12:$C$19*$AA$12:$AA$19*(($H$12:$H$19<H17)+($H$12:$H$19=H17)*($I$12:$I$19<I17)+($H$12:$H$19=H17)*($I$12:$I$19=I17)*($A$12:$A$19<A17))),0)
A18: 7 | B18: A + B | C18: =IF(SUMPRODUCT(D18:F18,1-$D$5:$F$5)=0,1,0) | D18: 1 | E18: 1 | F18: 0 | G18: =IF(C18=1,1+SUMPRODUCT(D18:F18,$D$9:$F$9),"") | H18: =SUMPRODUCT(D18:F18,$D$6:$F$6) | I18: =SUMPRODUCT(D18:F18,$D$7:$F$7) | J18: =SUMPRODUCT(D18:F18,$D$8:$F$8) | K18: =H18/10^in_out_dp | L18: =I18/10^in_cost_dp | M18: =IF(SUM(D18:F18)=0,1,0) | N18: =SUMPRODUCT($C$12:$C$19*(($H$12:$H$19=H18)*($I$12:$I$19<I18)+($H$12:$H$19>H18)*($I$12:$I$19<=I18))) | O18: =IF(C18=0,0,IF(OR(M18=1,N18=0),1,0)) | P18: =IF(AND(O18=1,M18=0,H18>0),1,0) | Q18: =IF(P18=1,MAX(I18/H18,SUMPRODUCT(MAX(((I18-$I$12:$I$19)*($P$12:$P$19*($H$12:$H$19<H18)))/((H18-$H$12:$H$19)*($P$12:$P$19*($H$12:$H$19<H18))+1-($P$12:$P$19*($H$12:$H$19<H18)))-(1-($P$12:$P$19*($H$12:$H$19<H18)))*1E+300))),0) | R18: =IF(P18=1,SUMPRODUCT(MIN(((($I$12:$I$19-I18)*($P$12:$P$19*($H$12:$H$19>H18)))/(($H$12:$H$19-H18)*($P$12:$P$19*($H$12:$H$19>H18))+1-($P$12:$P$19*($H$12:$H$19>H18)))+(1-($P$12:$P$19*($H$12:$H$19>H18)))*1E+300))),0) | S18: =IF(C18=0,0,IF(M18=1,1,IF(AND(P18=1,Q18<=R18),1,0))) | T18: =IF(S18=1,1+SUMPRODUCT($S$12:$S$19*(($H$12:$H$19<H18)+($H$12:$H$19=H18)*($A$12:$A$19<A18))),0) | U18: =IF(T18<=1,0,SUMPRODUCT(($T$12:$T$19=T18-1)*$H$12:$H$19)) | V18: =IF(T18<=1,0,SUMPRODUCT(($T$12:$T$19=T18-1)*$I$12:$I$19)) | W18: =IF(T18=0,"",(H18-U18)/10^in_out_dp) | X18: =IF(T18=0,"",(I18-V18)/10^in_cost_dp) | Y18: =IF(T18=0,"",IF(H18=U18,0,X18/W18)) | Z18: =IF(AND(C18=1,H18>0),L18/K18,"n/a") | AA18: 1 | AB18: =IF(AND(C18=1,AA18=1),1+SUMPRODUCT($C$12:$C$19*$AA$12:$AA$19*(($H$12:$H$19<H18)+($H$12:$H$19=H18)*($I$12:$I$19<I18)+($H$12:$H$19=H18)*($I$12:$I$19=I18)*($A$12:$A$19<A18))),0)
A19: 8 | B19: A + B + C | C19: =IF(SUMPRODUCT(D19:F19,1-$D$5:$F$5)=0,1,0) | D19: 1 | E19: 1 | F19: 1 | G19: =IF(C19=1,1+SUMPRODUCT(D19:F19,$D$9:$F$9),"") | H19: =SUMPRODUCT(D19:F19,$D$6:$F$6) | I19: =SUMPRODUCT(D19:F19,$D$7:$F$7) | J19: =SUMPRODUCT(D19:F19,$D$8:$F$8) | K19: =H19/10^in_out_dp | L19: =I19/10^in_cost_dp | M19: =IF(SUM(D19:F19)=0,1,0) | N19: =SUMPRODUCT($C$12:$C$19*(($H$12:$H$19=H19)*($I$12:$I$19<I19)+($H$12:$H$19>H19)*($I$12:$I$19<=I19))) | O19: =IF(C19=0,0,IF(OR(M19=1,N19=0),1,0)) | P19: =IF(AND(O19=1,M19=0,H19>0),1,0) | Q19: =IF(P19=1,MAX(I19/H19,SUMPRODUCT(MAX(((I19-$I$12:$I$19)*($P$12:$P$19*($H$12:$H$19<H19)))/((H19-$H$12:$H$19)*($P$12:$P$19*($H$12:$H$19<H19))+1-($P$12:$P$19*($H$12:$H$19<H19)))-(1-($P$12:$P$19*($H$12:$H$19<H19)))*1E+300))),0) | R19: =IF(P19=1,SUMPRODUCT(MIN(((($I$12:$I$19-I19)*($P$12:$P$19*($H$12:$H$19>H19)))/(($H$12:$H$19-H19)*($P$12:$P$19*($H$12:$H$19>H19))+1-($P$12:$P$19*($H$12:$H$19>H19)))+(1-($P$12:$P$19*($H$12:$H$19>H19)))*1E+300))),0) | S19: =IF(C19=0,0,IF(M19=1,1,IF(AND(P19=1,Q19<=R19),1,0))) | T19: =IF(S19=1,1+SUMPRODUCT($S$12:$S$19*(($H$12:$H$19<H19)+($H$12:$H$19=H19)*($A$12:$A$19<A19))),0) | U19: =IF(T19<=1,0,SUMPRODUCT(($T$12:$T$19=T19-1)*$H$12:$H$19)) | V19: =IF(T19<=1,0,SUMPRODUCT(($T$12:$T$19=T19-1)*$I$12:$I$19)) | W19: =IF(T19=0,"",(H19-U19)/10^in_out_dp) | X19: =IF(T19=0,"",(I19-V19)/10^in_cost_dp) | Y19: =IF(T19=0,"",IF(H19=U19,0,X19/W19)) | Z19: =IF(AND(C19=1,H19>0),L19/K19,"n/a") | AA19: 1 | AB19: =IF(AND(C19=1,AA19=1),1+SUMPRODUCT($C$12:$C$19*$AA$12:$AA$19*(($H$12:$H$19<H19)+($H$12:$H$19=H19)*($I$12:$I$19<I19)+($H$12:$H$19=H19)*($I$12:$I$19=I19)*($A$12:$A$19<A19))),0)

Sheet Watershed summary
A1: Watershed summary: best buys, final array and the tentatively selected plan
A2: Tables read the watershed plans sheet. Choose the TSP from the final array.
A4: Best buys
A5: Step | B5: Plan number | C5: Plan | D5: Lift (AAHU) | E5: Average annual cost | F5: Construction cost | G5: Unit cost | H5: Incremental cost per unit
A6: 1 | B6: =IFERROR(INDEX('Watershed plans'!$G$12:$G$19,MATCH(1,'Watershed plans'!$T$12:$T$19,0)),"") | C6: =IFERROR(INDEX('Watershed plans'!$B$12:$B$19,MATCH(1,'Watershed plans'!$T$12:$T$19,0)),"") | D6: =IFERROR(INDEX('Watershed plans'!$K$12:$K$19,MATCH(1,'Watershed plans'!$T$12:$T$19,0)),"") | E6: =IFERROR(INDEX('Watershed plans'!$L$12:$L$19,MATCH(1,'Watershed plans'!$T$12:$T$19,0)),"") | F6: =IFERROR(INDEX('Watershed plans'!$J$12:$J$19,MATCH(1,'Watershed plans'!$T$12:$T$19,0)),"") | G6: =IFERROR(INDEX('Watershed plans'!$Z$12:$Z$19,MATCH(1,'Watershed plans'!$T$12:$T$19,0)),"") | H6: =IFERROR(INDEX('Watershed plans'!$Y$12:$Y$19,MATCH(1,'Watershed plans'!$T$12:$T$19,0)),"")
A7: 2 | B7: =IFERROR(INDEX('Watershed plans'!$G$12:$G$19,MATCH(2,'Watershed plans'!$T$12:$T$19,0)),"") | C7: =IFERROR(INDEX('Watershed plans'!$B$12:$B$19,MATCH(2,'Watershed plans'!$T$12:$T$19,0)),"") | D7: =IFERROR(INDEX('Watershed plans'!$K$12:$K$19,MATCH(2,'Watershed plans'!$T$12:$T$19,0)),"") | E7: =IFERROR(INDEX('Watershed plans'!$L$12:$L$19,MATCH(2,'Watershed plans'!$T$12:$T$19,0)),"") | F7: =IFERROR(INDEX('Watershed plans'!$J$12:$J$19,MATCH(2,'Watershed plans'!$T$12:$T$19,0)),"") | G7: =IFERROR(INDEX('Watershed plans'!$Z$12:$Z$19,MATCH(2,'Watershed plans'!$T$12:$T$19,0)),"") | H7: =IFERROR(INDEX('Watershed plans'!$Y$12:$Y$19,MATCH(2,'Watershed plans'!$T$12:$T$19,0)),"")
A8: 3 | B8: =IFERROR(INDEX('Watershed plans'!$G$12:$G$19,MATCH(3,'Watershed plans'!$T$12:$T$19,0)),"") | C8: =IFERROR(INDEX('Watershed plans'!$B$12:$B$19,MATCH(3,'Watershed plans'!$T$12:$T$19,0)),"") | D8: =IFERROR(INDEX('Watershed plans'!$K$12:$K$19,MATCH(3,'Watershed plans'!$T$12:$T$19,0)),"") | E8: =IFERROR(INDEX('Watershed plans'!$L$12:$L$19,MATCH(3,'Watershed plans'!$T$12:$T$19,0)),"") | F8: =IFERROR(INDEX('Watershed plans'!$J$12:$J$19,MATCH(3,'Watershed plans'!$T$12:$T$19,0)),"") | G8: =IFERROR(INDEX('Watershed plans'!$Z$12:$Z$19,MATCH(3,'Watershed plans'!$T$12:$T$19,0)),"") | H8: =IFERROR(INDEX('Watershed plans'!$Y$12:$Y$19,MATCH(3,'Watershed plans'!$T$12:$T$19,0)),"")
A9: 4 | B9: =IFERROR(INDEX('Watershed plans'!$G$12:$G$19,MATCH(4,'Watershed plans'!$T$12:$T$19,0)),"") | C9: =IFERROR(INDEX('Watershed plans'!$B$12:$B$19,MATCH(4,'Watershed plans'!$T$12:$T$19,0)),"") | D9: =IFERROR(INDEX('Watershed plans'!$K$12:$K$19,MATCH(4,'Watershed plans'!$T$12:$T$19,0)),"") | E9: =IFERROR(INDEX('Watershed plans'!$L$12:$L$19,MATCH(4,'Watershed plans'!$T$12:$T$19,0)),"") | F9: =IFERROR(INDEX('Watershed plans'!$J$12:$J$19,MATCH(4,'Watershed plans'!$T$12:$T$19,0)),"") | G9: =IFERROR(INDEX('Watershed plans'!$Z$12:$Z$19,MATCH(4,'Watershed plans'!$T$12:$T$19,0)),"") | H9: =IFERROR(INDEX('Watershed plans'!$Y$12:$Y$19,MATCH(4,'Watershed plans'!$T$12:$T$19,0)),"")
A10: 5 | B10: =IFERROR(INDEX('Watershed plans'!$G$12:$G$19,MATCH(5,'Watershed plans'!$T$12:$T$19,0)),"") | C10: =IFERROR(INDEX('Watershed plans'!$B$12:$B$19,MATCH(5,'Watershed plans'!$T$12:$T$19,0)),"") | D10: =IFERROR(INDEX('Watershed plans'!$K$12:$K$19,MATCH(5,'Watershed plans'!$T$12:$T$19,0)),"") | E10: =IFERROR(INDEX('Watershed plans'!$L$12:$L$19,MATCH(5,'Watershed plans'!$T$12:$T$19,0)),"") | F10: =IFERROR(INDEX('Watershed plans'!$J$12:$J$19,MATCH(5,'Watershed plans'!$T$12:$T$19,0)),"") | G10: =IFERROR(INDEX('Watershed plans'!$Z$12:$Z$19,MATCH(5,'Watershed plans'!$T$12:$T$19,0)),"") | H10: =IFERROR(INDEX('Watershed plans'!$Y$12:$Y$19,MATCH(5,'Watershed plans'!$T$12:$T$19,0)),"")
A11: 6 | B11: =IFERROR(INDEX('Watershed plans'!$G$12:$G$19,MATCH(6,'Watershed plans'!$T$12:$T$19,0)),"") | C11: =IFERROR(INDEX('Watershed plans'!$B$12:$B$19,MATCH(6,'Watershed plans'!$T$12:$T$19,0)),"") | D11: =IFERROR(INDEX('Watershed plans'!$K$12:$K$19,MATCH(6,'Watershed plans'!$T$12:$T$19,0)),"") | E11: =IFERROR(INDEX('Watershed plans'!$L$12:$L$19,MATCH(6,'Watershed plans'!$T$12:$T$19,0)),"") | F11: =IFERROR(INDEX('Watershed plans'!$J$12:$J$19,MATCH(6,'Watershed plans'!$T$12:$T$19,0)),"") | G11: =IFERROR(INDEX('Watershed plans'!$Z$12:$Z$19,MATCH(6,'Watershed plans'!$T$12:$T$19,0)),"") | H11: =IFERROR(INDEX('Watershed plans'!$Y$12:$Y$19,MATCH(6,'Watershed plans'!$T$12:$T$19,0)),"")
A12: 7 | B12: =IFERROR(INDEX('Watershed plans'!$G$12:$G$19,MATCH(7,'Watershed plans'!$T$12:$T$19,0)),"") | C12: =IFERROR(INDEX('Watershed plans'!$B$12:$B$19,MATCH(7,'Watershed plans'!$T$12:$T$19,0)),"") | D12: =IFERROR(INDEX('Watershed plans'!$K$12:$K$19,MATCH(7,'Watershed plans'!$T$12:$T$19,0)),"") | E12: =IFERROR(INDEX('Watershed plans'!$L$12:$L$19,MATCH(7,'Watershed plans'!$T$12:$T$19,0)),"") | F12: =IFERROR(INDEX('Watershed plans'!$J$12:$J$19,MATCH(7,'Watershed plans'!$T$12:$T$19,0)),"") | G12: =IFERROR(INDEX('Watershed plans'!$Z$12:$Z$19,MATCH(7,'Watershed plans'!$T$12:$T$19,0)),"") | H12: =IFERROR(INDEX('Watershed plans'!$Y$12:$Y$19,MATCH(7,'Watershed plans'!$T$12:$T$19,0)),"")
A13: 8 | B13: =IFERROR(INDEX('Watershed plans'!$G$12:$G$19,MATCH(8,'Watershed plans'!$T$12:$T$19,0)),"") | C13: =IFERROR(INDEX('Watershed plans'!$B$12:$B$19,MATCH(8,'Watershed plans'!$T$12:$T$19,0)),"") | D13: =IFERROR(INDEX('Watershed plans'!$K$12:$K$19,MATCH(8,'Watershed plans'!$T$12:$T$19,0)),"") | E13: =IFERROR(INDEX('Watershed plans'!$L$12:$L$19,MATCH(8,'Watershed plans'!$T$12:$T$19,0)),"") | F13: =IFERROR(INDEX('Watershed plans'!$J$12:$J$19,MATCH(8,'Watershed plans'!$T$12:$T$19,0)),"") | G13: =IFERROR(INDEX('Watershed plans'!$Z$12:$Z$19,MATCH(8,'Watershed plans'!$T$12:$T$19,0)),"") | H13: =IFERROR(INDEX('Watershed plans'!$Y$12:$Y$19,MATCH(8,'Watershed plans'!$T$12:$T$19,0)),"")
A14: 9 | B14: =IFERROR(INDEX('Watershed plans'!$G$12:$G$19,MATCH(9,'Watershed plans'!$T$12:$T$19,0)),"") | C14: =IFERROR(INDEX('Watershed plans'!$B$12:$B$19,MATCH(9,'Watershed plans'!$T$12:$T$19,0)),"") | D14: =IFERROR(INDEX('Watershed plans'!$K$12:$K$19,MATCH(9,'Watershed plans'!$T$12:$T$19,0)),"") | E14: =IFERROR(INDEX('Watershed plans'!$L$12:$L$19,MATCH(9,'Watershed plans'!$T$12:$T$19,0)),"") | F14: =IFERROR(INDEX('Watershed plans'!$J$12:$J$19,MATCH(9,'Watershed plans'!$T$12:$T$19,0)),"") | G14: =IFERROR(INDEX('Watershed plans'!$Z$12:$Z$19,MATCH(9,'Watershed plans'!$T$12:$T$19,0)),"") | H14: =IFERROR(INDEX('Watershed plans'!$Y$12:$Y$19,MATCH(9,'Watershed plans'!$T$12:$T$19,0)),"")
A15: 10 | B15: =IFERROR(INDEX('Watershed plans'!$G$12:$G$19,MATCH(10,'Watershed plans'!$T$12:$T$19,0)),"") | C15: =IFERROR(INDEX('Watershed plans'!$B$12:$B$19,MATCH(10,'Watershed plans'!$T$12:$T$19,0)),"") | D15: =IFERROR(INDEX('Watershed plans'!$K$12:$K$19,MATCH(10,'Watershed plans'!$T$12:$T$19,0)),"") | E15: =IFERROR(INDEX('Watershed plans'!$L$12:$L$19,MATCH(10,'Watershed plans'!$T$12:$T$19,0)),"") | F15: =IFERROR(INDEX('Watershed plans'!$J$12:$J$19,MATCH(10,'Watershed plans'!$T$12:$T$19,0)),"") | G15: =IFERROR(INDEX('Watershed plans'!$Z$12:$Z$19,MATCH(10,'Watershed plans'!$T$12:$T$19,0)),"") | H15: =IFERROR(INDEX('Watershed plans'!$Y$12:$Y$19,MATCH(10,'Watershed plans'!$T$12:$T$19,0)),"")
A16: 11 | B16: =IFERROR(INDEX('Watershed plans'!$G$12:$G$19,MATCH(11,'Watershed plans'!$T$12:$T$19,0)),"") | C16: =IFERROR(INDEX('Watershed plans'!$B$12:$B$19,MATCH(11,'Watershed plans'!$T$12:$T$19,0)),"") | D16: =IFERROR(INDEX('Watershed plans'!$K$12:$K$19,MATCH(11,'Watershed plans'!$T$12:$T$19,0)),"") | E16: =IFERROR(INDEX('Watershed plans'!$L$12:$L$19,MATCH(11,'Watershed plans'!$T$12:$T$19,0)),"") | F16: =IFERROR(INDEX('Watershed plans'!$J$12:$J$19,MATCH(11,'Watershed plans'!$T$12:$T$19,0)),"") | G16: =IFERROR(INDEX('Watershed plans'!$Z$12:$Z$19,MATCH(11,'Watershed plans'!$T$12:$T$19,0)),"") | H16: =IFERROR(INDEX('Watershed plans'!$Y$12:$Y$19,MATCH(11,'Watershed plans'!$T$12:$T$19,0)),"")
A17: 12 | B17: =IFERROR(INDEX('Watershed plans'!$G$12:$G$19,MATCH(12,'Watershed plans'!$T$12:$T$19,0)),"") | C17: =IFERROR(INDEX('Watershed plans'!$B$12:$B$19,MATCH(12,'Watershed plans'!$T$12:$T$19,0)),"") | D17: =IFERROR(INDEX('Watershed plans'!$K$12:$K$19,MATCH(12,'Watershed plans'!$T$12:$T$19,0)),"") | E17: =IFERROR(INDEX('Watershed plans'!$L$12:$L$19,MATCH(12,'Watershed plans'!$T$12:$T$19,0)),"") | F17: =IFERROR(INDEX('Watershed plans'!$J$12:$J$19,MATCH(12,'Watershed plans'!$T$12:$T$19,0)),"") | G17: =IFERROR(INDEX('Watershed plans'!$Z$12:$Z$19,MATCH(12,'Watershed plans'!$T$12:$T$19,0)),"") | H17: =IFERROR(INDEX('Watershed plans'!$Y$12:$Y$19,MATCH(12,'Watershed plans'!$T$12:$T$19,0)),"")
A18: 13 | B18: =IFERROR(INDEX('Watershed plans'!$G$12:$G$19,MATCH(13,'Watershed plans'!$T$12:$T$19,0)),"") | C18: =IFERROR(INDEX('Watershed plans'!$B$12:$B$19,MATCH(13,'Watershed plans'!$T$12:$T$19,0)),"") | D18: =IFERROR(INDEX('Watershed plans'!$K$12:$K$19,MATCH(13,'Watershed plans'!$T$12:$T$19,0)),"") | E18: =IFERROR(INDEX('Watershed plans'!$L$12:$L$19,MATCH(13,'Watershed plans'!$T$12:$T$19,0)),"") | F18: =IFERROR(INDEX('Watershed plans'!$J$12:$J$19,MATCH(13,'Watershed plans'!$T$12:$T$19,0)),"") | G18: =IFERROR(INDEX('Watershed plans'!$Z$12:$Z$19,MATCH(13,'Watershed plans'!$T$12:$T$19,0)),"") | H18: =IFERROR(INDEX('Watershed plans'!$Y$12:$Y$19,MATCH(13,'Watershed plans'!$T$12:$T$19,0)),"")
A19: 14 | B19: =IFERROR(INDEX('Watershed plans'!$G$12:$G$19,MATCH(14,'Watershed plans'!$T$12:$T$19,0)),"") | C19: =IFERROR(INDEX('Watershed plans'!$B$12:$B$19,MATCH(14,'Watershed plans'!$T$12:$T$19,0)),"") | D19: =IFERROR(INDEX('Watershed plans'!$K$12:$K$19,MATCH(14,'Watershed plans'!$T$12:$T$19,0)),"") | E19: =IFERROR(INDEX('Watershed plans'!$L$12:$L$19,MATCH(14,'Watershed plans'!$T$12:$T$19,0)),"") | F19: =IFERROR(INDEX('Watershed plans'!$J$12:$J$19,MATCH(14,'Watershed plans'!$T$12:$T$19,0)),"") | G19: =IFERROR(INDEX('Watershed plans'!$Z$12:$Z$19,MATCH(14,'Watershed plans'!$T$12:$T$19,0)),"") | H19: =IFERROR(INDEX('Watershed plans'!$Y$12:$Y$19,MATCH(14,'Watershed plans'!$T$12:$T$19,0)),"")
A20: 15 | B20: =IFERROR(INDEX('Watershed plans'!$G$12:$G$19,MATCH(15,'Watershed plans'!$T$12:$T$19,0)),"") | C20: =IFERROR(INDEX('Watershed plans'!$B$12:$B$19,MATCH(15,'Watershed plans'!$T$12:$T$19,0)),"") | D20: =IFERROR(INDEX('Watershed plans'!$K$12:$K$19,MATCH(15,'Watershed plans'!$T$12:$T$19,0)),"") | E20: =IFERROR(INDEX('Watershed plans'!$L$12:$L$19,MATCH(15,'Watershed plans'!$T$12:$T$19,0)),"") | F20: =IFERROR(INDEX('Watershed plans'!$J$12:$J$19,MATCH(15,'Watershed plans'!$T$12:$T$19,0)),"") | G20: =IFERROR(INDEX('Watershed plans'!$Z$12:$Z$19,MATCH(15,'Watershed plans'!$T$12:$T$19,0)),"") | H20: =IFERROR(INDEX('Watershed plans'!$Y$12:$Y$19,MATCH(15,'Watershed plans'!$T$12:$T$19,0)),"")
A21: 16 | B21: =IFERROR(INDEX('Watershed plans'!$G$12:$G$19,MATCH(16,'Watershed plans'!$T$12:$T$19,0)),"") | C21: =IFERROR(INDEX('Watershed plans'!$B$12:$B$19,MATCH(16,'Watershed plans'!$T$12:$T$19,0)),"") | D21: =IFERROR(INDEX('Watershed plans'!$K$12:$K$19,MATCH(16,'Watershed plans'!$T$12:$T$19,0)),"") | E21: =IFERROR(INDEX('Watershed plans'!$L$12:$L$19,MATCH(16,'Watershed plans'!$T$12:$T$19,0)),"") | F21: =IFERROR(INDEX('Watershed plans'!$J$12:$J$19,MATCH(16,'Watershed plans'!$T$12:$T$19,0)),"") | G21: =IFERROR(INDEX('Watershed plans'!$Z$12:$Z$19,MATCH(16,'Watershed plans'!$T$12:$T$19,0)),"") | H21: =IFERROR(INDEX('Watershed plans'!$Y$12:$Y$19,MATCH(16,'Watershed plans'!$T$12:$T$19,0)),"")
A22: 17 | B22: =IFERROR(INDEX('Watershed plans'!$G$12:$G$19,MATCH(17,'Watershed plans'!$T$12:$T$19,0)),"") | C22: =IFERROR(INDEX('Watershed plans'!$B$12:$B$19,MATCH(17,'Watershed plans'!$T$12:$T$19,0)),"") | D22: =IFERROR(INDEX('Watershed plans'!$K$12:$K$19,MATCH(17,'Watershed plans'!$T$12:$T$19,0)),"") | E22: =IFERROR(INDEX('Watershed plans'!$L$12:$L$19,MATCH(17,'Watershed plans'!$T$12:$T$19,0)),"") | F22: =IFERROR(INDEX('Watershed plans'!$J$12:$J$19,MATCH(17,'Watershed plans'!$T$12:$T$19,0)),"") | G22: =IFERROR(INDEX('Watershed plans'!$Z$12:$Z$19,MATCH(17,'Watershed plans'!$T$12:$T$19,0)),"") | H22: =IFERROR(INDEX('Watershed plans'!$Y$12:$Y$19,MATCH(17,'Watershed plans'!$T$12:$T$19,0)),"")
A23: 18 | B23: =IFERROR(INDEX('Watershed plans'!$G$12:$G$19,MATCH(18,'Watershed plans'!$T$12:$T$19,0)),"") | C23: =IFERROR(INDEX('Watershed plans'!$B$12:$B$19,MATCH(18,'Watershed plans'!$T$12:$T$19,0)),"") | D23: =IFERROR(INDEX('Watershed plans'!$K$12:$K$19,MATCH(18,'Watershed plans'!$T$12:$T$19,0)),"") | E23: =IFERROR(INDEX('Watershed plans'!$L$12:$L$19,MATCH(18,'Watershed plans'!$T$12:$T$19,0)),"") | F23: =IFERROR(INDEX('Watershed plans'!$J$12:$J$19,MATCH(18,'Watershed plans'!$T$12:$T$19,0)),"") | G23: =IFERROR(INDEX('Watershed plans'!$Z$12:$Z$19,MATCH(18,'Watershed plans'!$T$12:$T$19,0)),"") | H23: =IFERROR(INDEX('Watershed plans'!$Y$12:$Y$19,MATCH(18,'Watershed plans'!$T$12:$T$19,0)),"")
A24: 19 | B24: =IFERROR(INDEX('Watershed plans'!$G$12:$G$19,MATCH(19,'Watershed plans'!$T$12:$T$19,0)),"") | C24: =IFERROR(INDEX('Watershed plans'!$B$12:$B$19,MATCH(19,'Watershed plans'!$T$12:$T$19,0)),"") | D24: =IFERROR(INDEX('Watershed plans'!$K$12:$K$19,MATCH(19,'Watershed plans'!$T$12:$T$19,0)),"") | E24: =IFERROR(INDEX('Watershed plans'!$L$12:$L$19,MATCH(19,'Watershed plans'!$T$12:$T$19,0)),"") | F24: =IFERROR(INDEX('Watershed plans'!$J$12:$J$19,MATCH(19,'Watershed plans'!$T$12:$T$19,0)),"") | G24: =IFERROR(INDEX('Watershed plans'!$Z$12:$Z$19,MATCH(19,'Watershed plans'!$T$12:$T$19,0)),"") | H24: =IFERROR(INDEX('Watershed plans'!$Y$12:$Y$19,MATCH(19,'Watershed plans'!$T$12:$T$19,0)),"")
A25: 20 | B25: =IFERROR(INDEX('Watershed plans'!$G$12:$G$19,MATCH(20,'Watershed plans'!$T$12:$T$19,0)),"") | C25: =IFERROR(INDEX('Watershed plans'!$B$12:$B$19,MATCH(20,'Watershed plans'!$T$12:$T$19,0)),"") | D25: =IFERROR(INDEX('Watershed plans'!$K$12:$K$19,MATCH(20,'Watershed plans'!$T$12:$T$19,0)),"") | E25: =IFERROR(INDEX('Watershed plans'!$L$12:$L$19,MATCH(20,'Watershed plans'!$T$12:$T$19,0)),"") | F25: =IFERROR(INDEX('Watershed plans'!$J$12:$J$19,MATCH(20,'Watershed plans'!$T$12:$T$19,0)),"") | G25: =IFERROR(INDEX('Watershed plans'!$Z$12:$Z$19,MATCH(20,'Watershed plans'!$T$12:$T$19,0)),"") | H25: =IFERROR(INDEX('Watershed plans'!$Y$12:$Y$19,MATCH(20,'Watershed plans'!$T$12:$T$19,0)),"")
A26: 21 | B26: =IFERROR(INDEX('Watershed plans'!$G$12:$G$19,MATCH(21,'Watershed plans'!$T$12:$T$19,0)),"") | C26: =IFERROR(INDEX('Watershed plans'!$B$12:$B$19,MATCH(21,'Watershed plans'!$T$12:$T$19,0)),"") | D26: =IFERROR(INDEX('Watershed plans'!$K$12:$K$19,MATCH(21,'Watershed plans'!$T$12:$T$19,0)),"") | E26: =IFERROR(INDEX('Watershed plans'!$L$12:$L$19,MATCH(21,'Watershed plans'!$T$12:$T$19,0)),"") | F26: =IFERROR(INDEX('Watershed plans'!$J$12:$J$19,MATCH(21,'Watershed plans'!$T$12:$T$19,0)),"") | G26: =IFERROR(INDEX('Watershed plans'!$Z$12:$Z$19,MATCH(21,'Watershed plans'!$T$12:$T$19,0)),"") | H26: =IFERROR(INDEX('Watershed plans'!$Y$12:$Y$19,MATCH(21,'Watershed plans'!$T$12:$T$19,0)),"")
A27: 22 | B27: =IFERROR(INDEX('Watershed plans'!$G$12:$G$19,MATCH(22,'Watershed plans'!$T$12:$T$19,0)),"") | C27: =IFERROR(INDEX('Watershed plans'!$B$12:$B$19,MATCH(22,'Watershed plans'!$T$12:$T$19,0)),"") | D27: =IFERROR(INDEX('Watershed plans'!$K$12:$K$19,MATCH(22,'Watershed plans'!$T$12:$T$19,0)),"") | E27: =IFERROR(INDEX('Watershed plans'!$L$12:$L$19,MATCH(22,'Watershed plans'!$T$12:$T$19,0)),"") | F27: =IFERROR(INDEX('Watershed plans'!$J$12:$J$19,MATCH(22,'Watershed plans'!$T$12:$T$19,0)),"") | G27: =IFERROR(INDEX('Watershed plans'!$Z$12:$Z$19,MATCH(22,'Watershed plans'!$T$12:$T$19,0)),"") | H27: =IFERROR(INDEX('Watershed plans'!$Y$12:$Y$19,MATCH(22,'Watershed plans'!$T$12:$T$19,0)),"")
A28: 23 | B28: =IFERROR(INDEX('Watershed plans'!$G$12:$G$19,MATCH(23,'Watershed plans'!$T$12:$T$19,0)),"") | C28: =IFERROR(INDEX('Watershed plans'!$B$12:$B$19,MATCH(23,'Watershed plans'!$T$12:$T$19,0)),"") | D28: =IFERROR(INDEX('Watershed plans'!$K$12:$K$19,MATCH(23,'Watershed plans'!$T$12:$T$19,0)),"") | E28: =IFERROR(INDEX('Watershed plans'!$L$12:$L$19,MATCH(23,'Watershed plans'!$T$12:$T$19,0)),"") | F28: =IFERROR(INDEX('Watershed plans'!$J$12:$J$19,MATCH(23,'Watershed plans'!$T$12:$T$19,0)),"") | G28: =IFERROR(INDEX('Watershed plans'!$Z$12:$Z$19,MATCH(23,'Watershed plans'!$T$12:$T$19,0)),"") | H28: =IFERROR(INDEX('Watershed plans'!$Y$12:$Y$19,MATCH(23,'Watershed plans'!$T$12:$T$19,0)),"")
A29: 24 | B29: =IFERROR(INDEX('Watershed plans'!$G$12:$G$19,MATCH(24,'Watershed plans'!$T$12:$T$19,0)),"") | C29: =IFERROR(INDEX('Watershed plans'!$B$12:$B$19,MATCH(24,'Watershed plans'!$T$12:$T$19,0)),"") | D29: =IFERROR(INDEX('Watershed plans'!$K$12:$K$19,MATCH(24,'Watershed plans'!$T$12:$T$19,0)),"") | E29: =IFERROR(INDEX('Watershed plans'!$L$12:$L$19,MATCH(24,'Watershed plans'!$T$12:$T$19,0)),"") | F29: =IFERROR(INDEX('Watershed plans'!$J$12:$J$19,MATCH(24,'Watershed plans'!$T$12:$T$19,0)),"") | G29: =IFERROR(INDEX('Watershed plans'!$Z$12:$Z$19,MATCH(24,'Watershed plans'!$T$12:$T$19,0)),"") | H29: =IFERROR(INDEX('Watershed plans'!$Y$12:$Y$19,MATCH(24,'Watershed plans'!$T$12:$T$19,0)),"")
A30: 25 | B30: =IFERROR(INDEX('Watershed plans'!$G$12:$G$19,MATCH(25,'Watershed plans'!$T$12:$T$19,0)),"") | C30: =IFERROR(INDEX('Watershed plans'!$B$12:$B$19,MATCH(25,'Watershed plans'!$T$12:$T$19,0)),"") | D30: =IFERROR(INDEX('Watershed plans'!$K$12:$K$19,MATCH(25,'Watershed plans'!$T$12:$T$19,0)),"") | E30: =IFERROR(INDEX('Watershed plans'!$L$12:$L$19,MATCH(25,'Watershed plans'!$T$12:$T$19,0)),"") | F30: =IFERROR(INDEX('Watershed plans'!$J$12:$J$19,MATCH(25,'Watershed plans'!$T$12:$T$19,0)),"") | G30: =IFERROR(INDEX('Watershed plans'!$Z$12:$Z$19,MATCH(25,'Watershed plans'!$T$12:$T$19,0)),"") | H30: =IFERROR(INDEX('Watershed plans'!$Y$12:$Y$19,MATCH(25,'Watershed plans'!$T$12:$T$19,0)),"")
A31: 26 | B31: =IFERROR(INDEX('Watershed plans'!$G$12:$G$19,MATCH(26,'Watershed plans'!$T$12:$T$19,0)),"") | C31: =IFERROR(INDEX('Watershed plans'!$B$12:$B$19,MATCH(26,'Watershed plans'!$T$12:$T$19,0)),"") | D31: =IFERROR(INDEX('Watershed plans'!$K$12:$K$19,MATCH(26,'Watershed plans'!$T$12:$T$19,0)),"") | E31: =IFERROR(INDEX('Watershed plans'!$L$12:$L$19,MATCH(26,'Watershed plans'!$T$12:$T$19,0)),"") | F31: =IFERROR(INDEX('Watershed plans'!$J$12:$J$19,MATCH(26,'Watershed plans'!$T$12:$T$19,0)),"") | G31: =IFERROR(INDEX('Watershed plans'!$Z$12:$Z$19,MATCH(26,'Watershed plans'!$T$12:$T$19,0)),"") | H31: =IFERROR(INDEX('Watershed plans'!$Y$12:$Y$19,MATCH(26,'Watershed plans'!$T$12:$T$19,0)),"")
A32: 27 | B32: =IFERROR(INDEX('Watershed plans'!$G$12:$G$19,MATCH(27,'Watershed plans'!$T$12:$T$19,0)),"") | C32: =IFERROR(INDEX('Watershed plans'!$B$12:$B$19,MATCH(27,'Watershed plans'!$T$12:$T$19,0)),"") | D32: =IFERROR(INDEX('Watershed plans'!$K$12:$K$19,MATCH(27,'Watershed plans'!$T$12:$T$19,0)),"") | E32: =IFERROR(INDEX('Watershed plans'!$L$12:$L$19,MATCH(27,'Watershed plans'!$T$12:$T$19,0)),"") | F32: =IFERROR(INDEX('Watershed plans'!$J$12:$J$19,MATCH(27,'Watershed plans'!$T$12:$T$19,0)),"") | G32: =IFERROR(INDEX('Watershed plans'!$Z$12:$Z$19,MATCH(27,'Watershed plans'!$T$12:$T$19,0)),"") | H32: =IFERROR(INDEX('Watershed plans'!$Y$12:$Y$19,MATCH(27,'Watershed plans'!$T$12:$T$19,0)),"")
A33: 28 | B33: =IFERROR(INDEX('Watershed plans'!$G$12:$G$19,MATCH(28,'Watershed plans'!$T$12:$T$19,0)),"") | C33: =IFERROR(INDEX('Watershed plans'!$B$12:$B$19,MATCH(28,'Watershed plans'!$T$12:$T$19,0)),"") | D33: =IFERROR(INDEX('Watershed plans'!$K$12:$K$19,MATCH(28,'Watershed plans'!$T$12:$T$19,0)),"") | E33: =IFERROR(INDEX('Watershed plans'!$L$12:$L$19,MATCH(28,'Watershed plans'!$T$12:$T$19,0)),"") | F33: =IFERROR(INDEX('Watershed plans'!$J$12:$J$19,MATCH(28,'Watershed plans'!$T$12:$T$19,0)),"") | G33: =IFERROR(INDEX('Watershed plans'!$Z$12:$Z$19,MATCH(28,'Watershed plans'!$T$12:$T$19,0)),"") | H33: =IFERROR(INDEX('Watershed plans'!$Y$12:$Y$19,MATCH(28,'Watershed plans'!$T$12:$T$19,0)),"")
A34: 29 | B34: =IFERROR(INDEX('Watershed plans'!$G$12:$G$19,MATCH(29,'Watershed plans'!$T$12:$T$19,0)),"") | C34: =IFERROR(INDEX('Watershed plans'!$B$12:$B$19,MATCH(29,'Watershed plans'!$T$12:$T$19,0)),"") | D34: =IFERROR(INDEX('Watershed plans'!$K$12:$K$19,MATCH(29,'Watershed plans'!$T$12:$T$19,0)),"") | E34: =IFERROR(INDEX('Watershed plans'!$L$12:$L$19,MATCH(29,'Watershed plans'!$T$12:$T$19,0)),"") | F34: =IFERROR(INDEX('Watershed plans'!$J$12:$J$19,MATCH(29,'Watershed plans'!$T$12:$T$19,0)),"") | G34: =IFERROR(INDEX('Watershed plans'!$Z$12:$Z$19,MATCH(29,'Watershed plans'!$T$12:$T$19,0)),"") | H34: =IFERROR(INDEX('Watershed plans'!$Y$12:$Y$19,MATCH(29,'Watershed plans'!$T$12:$T$19,0)),"")
A35: 30 | B35: =IFERROR(INDEX('Watershed plans'!$G$12:$G$19,MATCH(30,'Watershed plans'!$T$12:$T$19,0)),"") | C35: =IFERROR(INDEX('Watershed plans'!$B$12:$B$19,MATCH(30,'Watershed plans'!$T$12:$T$19,0)),"") | D35: =IFERROR(INDEX('Watershed plans'!$K$12:$K$19,MATCH(30,'Watershed plans'!$T$12:$T$19,0)),"") | E35: =IFERROR(INDEX('Watershed plans'!$L$12:$L$19,MATCH(30,'Watershed plans'!$T$12:$T$19,0)),"") | F35: =IFERROR(INDEX('Watershed plans'!$J$12:$J$19,MATCH(30,'Watershed plans'!$T$12:$T$19,0)),"") | G35: =IFERROR(INDEX('Watershed plans'!$Z$12:$Z$19,MATCH(30,'Watershed plans'!$T$12:$T$19,0)),"") | H35: =IFERROR(INDEX('Watershed plans'!$Y$12:$Y$19,MATCH(30,'Watershed plans'!$T$12:$T$19,0)),"")
A36: 31 | B36: =IFERROR(INDEX('Watershed plans'!$G$12:$G$19,MATCH(31,'Watershed plans'!$T$12:$T$19,0)),"") | C36: =IFERROR(INDEX('Watershed plans'!$B$12:$B$19,MATCH(31,'Watershed plans'!$T$12:$T$19,0)),"") | D36: =IFERROR(INDEX('Watershed plans'!$K$12:$K$19,MATCH(31,'Watershed plans'!$T$12:$T$19,0)),"") | E36: =IFERROR(INDEX('Watershed plans'!$L$12:$L$19,MATCH(31,'Watershed plans'!$T$12:$T$19,0)),"") | F36: =IFERROR(INDEX('Watershed plans'!$J$12:$J$19,MATCH(31,'Watershed plans'!$T$12:$T$19,0)),"") | G36: =IFERROR(INDEX('Watershed plans'!$Z$12:$Z$19,MATCH(31,'Watershed plans'!$T$12:$T$19,0)),"") | H36: =IFERROR(INDEX('Watershed plans'!$Y$12:$Y$19,MATCH(31,'Watershed plans'!$T$12:$T$19,0)),"")
A37: 32 | B37: =IFERROR(INDEX('Watershed plans'!$G$12:$G$19,MATCH(32,'Watershed plans'!$T$12:$T$19,0)),"") | C37: =IFERROR(INDEX('Watershed plans'!$B$12:$B$19,MATCH(32,'Watershed plans'!$T$12:$T$19,0)),"") | D37: =IFERROR(INDEX('Watershed plans'!$K$12:$K$19,MATCH(32,'Watershed plans'!$T$12:$T$19,0)),"") | E37: =IFERROR(INDEX('Watershed plans'!$L$12:$L$19,MATCH(32,'Watershed plans'!$T$12:$T$19,0)),"") | F37: =IFERROR(INDEX('Watershed plans'!$J$12:$J$19,MATCH(32,'Watershed plans'!$T$12:$T$19,0)),"") | G37: =IFERROR(INDEX('Watershed plans'!$Z$12:$Z$19,MATCH(32,'Watershed plans'!$T$12:$T$19,0)),"") | H37: =IFERROR(INDEX('Watershed plans'!$Y$12:$Y$19,MATCH(32,'Watershed plans'!$T$12:$T$19,0)),"")
A38: 33 | B38: =IFERROR(INDEX('Watershed plans'!$G$12:$G$19,MATCH(33,'Watershed plans'!$T$12:$T$19,0)),"") | C38: =IFERROR(INDEX('Watershed plans'!$B$12:$B$19,MATCH(33,'Watershed plans'!$T$12:$T$19,0)),"") | D38: =IFERROR(INDEX('Watershed plans'!$K$12:$K$19,MATCH(33,'Watershed plans'!$T$12:$T$19,0)),"") | E38: =IFERROR(INDEX('Watershed plans'!$L$12:$L$19,MATCH(33,'Watershed plans'!$T$12:$T$19,0)),"") | F38: =IFERROR(INDEX('Watershed plans'!$J$12:$J$19,MATCH(33,'Watershed plans'!$T$12:$T$19,0)),"") | G38: =IFERROR(INDEX('Watershed plans'!$Z$12:$Z$19,MATCH(33,'Watershed plans'!$T$12:$T$19,0)),"") | H38: =IFERROR(INDEX('Watershed plans'!$Y$12:$Y$19,MATCH(33,'Watershed plans'!$T$12:$T$19,0)),"")
A39: 34 | B39: =IFERROR(INDEX('Watershed plans'!$G$12:$G$19,MATCH(34,'Watershed plans'!$T$12:$T$19,0)),"") | C39: =IFERROR(INDEX('Watershed plans'!$B$12:$B$19,MATCH(34,'Watershed plans'!$T$12:$T$19,0)),"") | D39: =IFERROR(INDEX('Watershed plans'!$K$12:$K$19,MATCH(34,'Watershed plans'!$T$12:$T$19,0)),"") | E39: =IFERROR(INDEX('Watershed plans'!$L$12:$L$19,MATCH(34,'Watershed plans'!$T$12:$T$19,0)),"") | F39: =IFERROR(INDEX('Watershed plans'!$J$12:$J$19,MATCH(34,'Watershed plans'!$T$12:$T$19,0)),"") | G39: =IFERROR(INDEX('Watershed plans'!$Z$12:$Z$19,MATCH(34,'Watershed plans'!$T$12:$T$19,0)),"") | H39: =IFERROR(INDEX('Watershed plans'!$Y$12:$Y$19,MATCH(34,'Watershed plans'!$T$12:$T$19,0)),"")
A40: 35 | B40: =IFERROR(INDEX('Watershed plans'!$G$12:$G$19,MATCH(35,'Watershed plans'!$T$12:$T$19,0)),"") | C40: =IFERROR(INDEX('Watershed plans'!$B$12:$B$19,MATCH(35,'Watershed plans'!$T$12:$T$19,0)),"") | D40: =IFERROR(INDEX('Watershed plans'!$K$12:$K$19,MATCH(35,'Watershed plans'!$T$12:$T$19,0)),"") | E40: =IFERROR(INDEX('Watershed plans'!$L$12:$L$19,MATCH(35,'Watershed plans'!$T$12:$T$19,0)),"") | F40: =IFERROR(INDEX('Watershed plans'!$J$12:$J$19,MATCH(35,'Watershed plans'!$T$12:$T$19,0)),"") | G40: =IFERROR(INDEX('Watershed plans'!$Z$12:$Z$19,MATCH(35,'Watershed plans'!$T$12:$T$19,0)),"") | H40: =IFERROR(INDEX('Watershed plans'!$Y$12:$Y$19,MATCH(35,'Watershed plans'!$T$12:$T$19,0)),"")
A41: 36 | B41: =IFERROR(INDEX('Watershed plans'!$G$12:$G$19,MATCH(36,'Watershed plans'!$T$12:$T$19,0)),"") | C41: =IFERROR(INDEX('Watershed plans'!$B$12:$B$19,MATCH(36,'Watershed plans'!$T$12:$T$19,0)),"") | D41: =IFERROR(INDEX('Watershed plans'!$K$12:$K$19,MATCH(36,'Watershed plans'!$T$12:$T$19,0)),"") | E41: =IFERROR(INDEX('Watershed plans'!$L$12:$L$19,MATCH(36,'Watershed plans'!$T$12:$T$19,0)),"") | F41: =IFERROR(INDEX('Watershed plans'!$J$12:$J$19,MATCH(36,'Watershed plans'!$T$12:$T$19,0)),"") | G41: =IFERROR(INDEX('Watershed plans'!$Z$12:$Z$19,MATCH(36,'Watershed plans'!$T$12:$T$19,0)),"") | H41: =IFERROR(INDEX('Watershed plans'!$Y$12:$Y$19,MATCH(36,'Watershed plans'!$T$12:$T$19,0)),"")
A42: 37 | B42: =IFERROR(INDEX('Watershed plans'!$G$12:$G$19,MATCH(37,'Watershed plans'!$T$12:$T$19,0)),"") | C42: =IFERROR(INDEX('Watershed plans'!$B$12:$B$19,MATCH(37,'Watershed plans'!$T$12:$T$19,0)),"") | D42: =IFERROR(INDEX('Watershed plans'!$K$12:$K$19,MATCH(37,'Watershed plans'!$T$12:$T$19,0)),"") | E42: =IFERROR(INDEX('Watershed plans'!$L$12:$L$19,MATCH(37,'Watershed plans'!$T$12:$T$19,0)),"") | F42: =IFERROR(INDEX('Watershed plans'!$J$12:$J$19,MATCH(37,'Watershed plans'!$T$12:$T$19,0)),"") | G42: =IFERROR(INDEX('Watershed plans'!$Z$12:$Z$19,MATCH(37,'Watershed plans'!$T$12:$T$19,0)),"") | H42: =IFERROR(INDEX('Watershed plans'!$Y$12:$Y$19,MATCH(37,'Watershed plans'!$T$12:$T$19,0)),"")
A43: 38 | B43: =IFERROR(INDEX('Watershed plans'!$G$12:$G$19,MATCH(38,'Watershed plans'!$T$12:$T$19,0)),"") | C43: =IFERROR(INDEX('Watershed plans'!$B$12:$B$19,MATCH(38,'Watershed plans'!$T$12:$T$19,0)),"") | D43: =IFERROR(INDEX('Watershed plans'!$K$12:$K$19,MATCH(38,'Watershed plans'!$T$12:$T$19,0)),"") | E43: =IFERROR(INDEX('Watershed plans'!$L$12:$L$19,MATCH(38,'Watershed plans'!$T$12:$T$19,0)),"") | F43: =IFERROR(INDEX('Watershed plans'!$J$12:$J$19,MATCH(38,'Watershed plans'!$T$12:$T$19,0)),"") | G43: =IFERROR(INDEX('Watershed plans'!$Z$12:$Z$19,MATCH(38,'Watershed plans'!$T$12:$T$19,0)),"") | H43: =IFERROR(INDEX('Watershed plans'!$Y$12:$Y$19,MATCH(38,'Watershed plans'!$T$12:$T$19,0)),"")
A44: 39 | B44: =IFERROR(INDEX('Watershed plans'!$G$12:$G$19,MATCH(39,'Watershed plans'!$T$12:$T$19,0)),"") | C44: =IFERROR(INDEX('Watershed plans'!$B$12:$B$19,MATCH(39,'Watershed plans'!$T$12:$T$19,0)),"") | D44: =IFERROR(INDEX('Watershed plans'!$K$12:$K$19,MATCH(39,'Watershed plans'!$T$12:$T$19,0)),"") | E44: =IFERROR(INDEX('Watershed plans'!$L$12:$L$19,MATCH(39,'Watershed plans'!$T$12:$T$19,0)),"") | F44: =IFERROR(INDEX('Watershed plans'!$J$12:$J$19,MATCH(39,'Watershed plans'!$T$12:$T$19,0)),"") | G44: =IFERROR(INDEX('Watershed plans'!$Z$12:$Z$19,MATCH(39,'Watershed plans'!$T$12:$T$19,0)),"") | H44: =IFERROR(INDEX('Watershed plans'!$Y$12:$Y$19,MATCH(39,'Watershed plans'!$T$12:$T$19,0)),"")
A45: 40 | B45: =IFERROR(INDEX('Watershed plans'!$G$12:$G$19,MATCH(40,'Watershed plans'!$T$12:$T$19,0)),"") | C45: =IFERROR(INDEX('Watershed plans'!$B$12:$B$19,MATCH(40,'Watershed plans'!$T$12:$T$19,0)),"") | D45: =IFERROR(INDEX('Watershed plans'!$K$12:$K$19,MATCH(40,'Watershed plans'!$T$12:$T$19,0)),"") | E45: =IFERROR(INDEX('Watershed plans'!$L$12:$L$19,MATCH(40,'Watershed plans'!$T$12:$T$19,0)),"") | F45: =IFERROR(INDEX('Watershed plans'!$J$12:$J$19,MATCH(40,'Watershed plans'!$T$12:$T$19,0)),"") | G45: =IFERROR(INDEX('Watershed plans'!$Z$12:$Z$19,MATCH(40,'Watershed plans'!$T$12:$T$19,0)),"") | H45: =IFERROR(INDEX('Watershed plans'!$Y$12:$Y$19,MATCH(40,'Watershed plans'!$T$12:$T$19,0)),"")
A48: Final array (in order of output) and 'Is it worth it?'
A49: Order | B49: Plan number | C49: Plan | D49: Lift (AAHU) | E49: Average annual cost | F49: Construction cost | G49: Unit cost | H49: Added output | I49: Added cost | J49: Added cost per unit | K49: Worth it? | L49: Why
A50: 1 | B50: =IFERROR(INDEX('Watershed plans'!$G$12:$G$19,MATCH(1,'Watershed plans'!$AB$12:$AB$19,0)),"") | C50: =IFERROR(INDEX('Watershed plans'!$B$12:$B$19,MATCH(1,'Watershed plans'!$AB$12:$AB$19,0)),"") | D50: =IFERROR(INDEX('Watershed plans'!$K$12:$K$19,MATCH(1,'Watershed plans'!$AB$12:$AB$19,0)),"") | E50: =IFERROR(INDEX('Watershed plans'!$L$12:$L$19,MATCH(1,'Watershed plans'!$AB$12:$AB$19,0)),"") | F50: =IFERROR(INDEX('Watershed plans'!$J$12:$J$19,MATCH(1,'Watershed plans'!$AB$12:$AB$19,0)),"") | G50: =IFERROR(INDEX('Watershed plans'!$Z$12:$Z$19,MATCH(1,'Watershed plans'!$AB$12:$AB$19,0)),"")
A51: 2 | B51: =IFERROR(INDEX('Watershed plans'!$G$12:$G$19,MATCH(2,'Watershed plans'!$AB$12:$AB$19,0)),"") | C51: =IFERROR(INDEX('Watershed plans'!$B$12:$B$19,MATCH(2,'Watershed plans'!$AB$12:$AB$19,0)),"") | D51: =IFERROR(INDEX('Watershed plans'!$K$12:$K$19,MATCH(2,'Watershed plans'!$AB$12:$AB$19,0)),"") | E51: =IFERROR(INDEX('Watershed plans'!$L$12:$L$19,MATCH(2,'Watershed plans'!$AB$12:$AB$19,0)),"") | F51: =IFERROR(INDEX('Watershed plans'!$J$12:$J$19,MATCH(2,'Watershed plans'!$AB$12:$AB$19,0)),"") | G51: =IFERROR(INDEX('Watershed plans'!$Z$12:$Z$19,MATCH(2,'Watershed plans'!$AB$12:$AB$19,0)),"") | H51: =IF(ISNUMBER(D51),D51-D50,"") | I51: =IF(ISNUMBER(E51),E51-E50,"") | J51: =IF(AND(ISNUMBER(H51),H51<>0),I51/H51,"")
A52: 3 | B52: =IFERROR(INDEX('Watershed plans'!$G$12:$G$19,MATCH(3,'Watershed plans'!$AB$12:$AB$19,0)),"") | C52: =IFERROR(INDEX('Watershed plans'!$B$12:$B$19,MATCH(3,'Watershed plans'!$AB$12:$AB$19,0)),"") | D52: =IFERROR(INDEX('Watershed plans'!$K$12:$K$19,MATCH(3,'Watershed plans'!$AB$12:$AB$19,0)),"") | E52: =IFERROR(INDEX('Watershed plans'!$L$12:$L$19,MATCH(3,'Watershed plans'!$AB$12:$AB$19,0)),"") | F52: =IFERROR(INDEX('Watershed plans'!$J$12:$J$19,MATCH(3,'Watershed plans'!$AB$12:$AB$19,0)),"") | G52: =IFERROR(INDEX('Watershed plans'!$Z$12:$Z$19,MATCH(3,'Watershed plans'!$AB$12:$AB$19,0)),"") | H52: =IF(ISNUMBER(D52),D52-D51,"") | I52: =IF(ISNUMBER(E52),E52-E51,"") | J52: =IF(AND(ISNUMBER(H52),H52<>0),I52/H52,"")
A53: 4 | B53: =IFERROR(INDEX('Watershed plans'!$G$12:$G$19,MATCH(4,'Watershed plans'!$AB$12:$AB$19,0)),"") | C53: =IFERROR(INDEX('Watershed plans'!$B$12:$B$19,MATCH(4,'Watershed plans'!$AB$12:$AB$19,0)),"") | D53: =IFERROR(INDEX('Watershed plans'!$K$12:$K$19,MATCH(4,'Watershed plans'!$AB$12:$AB$19,0)),"") | E53: =IFERROR(INDEX('Watershed plans'!$L$12:$L$19,MATCH(4,'Watershed plans'!$AB$12:$AB$19,0)),"") | F53: =IFERROR(INDEX('Watershed plans'!$J$12:$J$19,MATCH(4,'Watershed plans'!$AB$12:$AB$19,0)),"") | G53: =IFERROR(INDEX('Watershed plans'!$Z$12:$Z$19,MATCH(4,'Watershed plans'!$AB$12:$AB$19,0)),"") | H53: =IF(ISNUMBER(D53),D53-D52,"") | I53: =IF(ISNUMBER(E53),E53-E52,"") | J53: =IF(AND(ISNUMBER(H53),H53<>0),I53/H53,"")
A54: 5 | B54: =IFERROR(INDEX('Watershed plans'!$G$12:$G$19,MATCH(5,'Watershed plans'!$AB$12:$AB$19,0)),"") | C54: =IFERROR(INDEX('Watershed plans'!$B$12:$B$19,MATCH(5,'Watershed plans'!$AB$12:$AB$19,0)),"") | D54: =IFERROR(INDEX('Watershed plans'!$K$12:$K$19,MATCH(5,'Watershed plans'!$AB$12:$AB$19,0)),"") | E54: =IFERROR(INDEX('Watershed plans'!$L$12:$L$19,MATCH(5,'Watershed plans'!$AB$12:$AB$19,0)),"") | F54: =IFERROR(INDEX('Watershed plans'!$J$12:$J$19,MATCH(5,'Watershed plans'!$AB$12:$AB$19,0)),"") | G54: =IFERROR(INDEX('Watershed plans'!$Z$12:$Z$19,MATCH(5,'Watershed plans'!$AB$12:$AB$19,0)),"") | H54: =IF(ISNUMBER(D54),D54-D53,"") | I54: =IF(ISNUMBER(E54),E54-E53,"") | J54: =IF(AND(ISNUMBER(H54),H54<>0),I54/H54,"")
A55: 6 | B55: =IFERROR(INDEX('Watershed plans'!$G$12:$G$19,MATCH(6,'Watershed plans'!$AB$12:$AB$19,0)),"") | C55: =IFERROR(INDEX('Watershed plans'!$B$12:$B$19,MATCH(6,'Watershed plans'!$AB$12:$AB$19,0)),"") | D55: =IFERROR(INDEX('Watershed plans'!$K$12:$K$19,MATCH(6,'Watershed plans'!$AB$12:$AB$19,0)),"") | E55: =IFERROR(INDEX('Watershed plans'!$L$12:$L$19,MATCH(6,'Watershed plans'!$AB$12:$AB$19,0)),"") | F55: =IFERROR(INDEX('Watershed plans'!$J$12:$J$19,MATCH(6,'Watershed plans'!$AB$12:$AB$19,0)),"") | G55: =IFERROR(INDEX('Watershed plans'!$Z$12:$Z$19,MATCH(6,'Watershed plans'!$AB$12:$AB$19,0)),"") | H55: =IF(ISNUMBER(D55),D55-D54,"") | I55: =IF(ISNUMBER(E55),E55-E54,"") | J55: =IF(AND(ISNUMBER(H55),H55<>0),I55/H55,"")
A56: 7 | B56: =IFERROR(INDEX('Watershed plans'!$G$12:$G$19,MATCH(7,'Watershed plans'!$AB$12:$AB$19,0)),"") | C56: =IFERROR(INDEX('Watershed plans'!$B$12:$B$19,MATCH(7,'Watershed plans'!$AB$12:$AB$19,0)),"") | D56: =IFERROR(INDEX('Watershed plans'!$K$12:$K$19,MATCH(7,'Watershed plans'!$AB$12:$AB$19,0)),"") | E56: =IFERROR(INDEX('Watershed plans'!$L$12:$L$19,MATCH(7,'Watershed plans'!$AB$12:$AB$19,0)),"") | F56: =IFERROR(INDEX('Watershed plans'!$J$12:$J$19,MATCH(7,'Watershed plans'!$AB$12:$AB$19,0)),"") | G56: =IFERROR(INDEX('Watershed plans'!$Z$12:$Z$19,MATCH(7,'Watershed plans'!$AB$12:$AB$19,0)),"") | H56: =IF(ISNUMBER(D56),D56-D55,"") | I56: =IF(ISNUMBER(E56),E56-E55,"") | J56: =IF(AND(ISNUMBER(H56),H56<>0),I56/H56,"")
A57: 8 | B57: =IFERROR(INDEX('Watershed plans'!$G$12:$G$19,MATCH(8,'Watershed plans'!$AB$12:$AB$19,0)),"") | C57: =IFERROR(INDEX('Watershed plans'!$B$12:$B$19,MATCH(8,'Watershed plans'!$AB$12:$AB$19,0)),"") | D57: =IFERROR(INDEX('Watershed plans'!$K$12:$K$19,MATCH(8,'Watershed plans'!$AB$12:$AB$19,0)),"") | E57: =IFERROR(INDEX('Watershed plans'!$L$12:$L$19,MATCH(8,'Watershed plans'!$AB$12:$AB$19,0)),"") | F57: =IFERROR(INDEX('Watershed plans'!$J$12:$J$19,MATCH(8,'Watershed plans'!$AB$12:$AB$19,0)),"") | G57: =IFERROR(INDEX('Watershed plans'!$Z$12:$Z$19,MATCH(8,'Watershed plans'!$AB$12:$AB$19,0)),"") | H57: =IF(ISNUMBER(D57),D57-D56,"") | I57: =IF(ISNUMBER(E57),E57-E56,"") | J57: =IF(AND(ISNUMBER(H57),H57<>0),I57/H57,"")
A58: 9 | B58: =IFERROR(INDEX('Watershed plans'!$G$12:$G$19,MATCH(9,'Watershed plans'!$AB$12:$AB$19,0)),"") | C58: =IFERROR(INDEX('Watershed plans'!$B$12:$B$19,MATCH(9,'Watershed plans'!$AB$12:$AB$19,0)),"") | D58: =IFERROR(INDEX('Watershed plans'!$K$12:$K$19,MATCH(9,'Watershed plans'!$AB$12:$AB$19,0)),"") | E58: =IFERROR(INDEX('Watershed plans'!$L$12:$L$19,MATCH(9,'Watershed plans'!$AB$12:$AB$19,0)),"") | F58: =IFERROR(INDEX('Watershed plans'!$J$12:$J$19,MATCH(9,'Watershed plans'!$AB$12:$AB$19,0)),"") | G58: =IFERROR(INDEX('Watershed plans'!$Z$12:$Z$19,MATCH(9,'Watershed plans'!$AB$12:$AB$19,0)),"") | H58: =IF(ISNUMBER(D58),D58-D57,"") | I58: =IF(ISNUMBER(E58),E58-E57,"") | J58: =IF(AND(ISNUMBER(H58),H58<>0),I58/H58,"")
A59: 10 | B59: =IFERROR(INDEX('Watershed plans'!$G$12:$G$19,MATCH(10,'Watershed plans'!$AB$12:$AB$19,0)),"") | C59: =IFERROR(INDEX('Watershed plans'!$B$12:$B$19,MATCH(10,'Watershed plans'!$AB$12:$AB$19,0)),"") | D59: =IFERROR(INDEX('Watershed plans'!$K$12:$K$19,MATCH(10,'Watershed plans'!$AB$12:$AB$19,0)),"") | E59: =IFERROR(INDEX('Watershed plans'!$L$12:$L$19,MATCH(10,'Watershed plans'!$AB$12:$AB$19,0)),"") | F59: =IFERROR(INDEX('Watershed plans'!$J$12:$J$19,MATCH(10,'Watershed plans'!$AB$12:$AB$19,0)),"") | G59: =IFERROR(INDEX('Watershed plans'!$Z$12:$Z$19,MATCH(10,'Watershed plans'!$AB$12:$AB$19,0)),"") | H59: =IF(ISNUMBER(D59),D59-D58,"") | I59: =IF(ISNUMBER(E59),E59-E58,"") | J59: =IF(AND(ISNUMBER(H59),H59<>0),I59/H59,"")
A60: 11 | B60: =IFERROR(INDEX('Watershed plans'!$G$12:$G$19,MATCH(11,'Watershed plans'!$AB$12:$AB$19,0)),"") | C60: =IFERROR(INDEX('Watershed plans'!$B$12:$B$19,MATCH(11,'Watershed plans'!$AB$12:$AB$19,0)),"") | D60: =IFERROR(INDEX('Watershed plans'!$K$12:$K$19,MATCH(11,'Watershed plans'!$AB$12:$AB$19,0)),"") | E60: =IFERROR(INDEX('Watershed plans'!$L$12:$L$19,MATCH(11,'Watershed plans'!$AB$12:$AB$19,0)),"") | F60: =IFERROR(INDEX('Watershed plans'!$J$12:$J$19,MATCH(11,'Watershed plans'!$AB$12:$AB$19,0)),"") | G60: =IFERROR(INDEX('Watershed plans'!$Z$12:$Z$19,MATCH(11,'Watershed plans'!$AB$12:$AB$19,0)),"") | H60: =IF(ISNUMBER(D60),D60-D59,"") | I60: =IF(ISNUMBER(E60),E60-E59,"") | J60: =IF(AND(ISNUMBER(H60),H60<>0),I60/H60,"")
A61: 12 | B61: =IFERROR(INDEX('Watershed plans'!$G$12:$G$19,MATCH(12,'Watershed plans'!$AB$12:$AB$19,0)),"") | C61: =IFERROR(INDEX('Watershed plans'!$B$12:$B$19,MATCH(12,'Watershed plans'!$AB$12:$AB$19,0)),"") | D61: =IFERROR(INDEX('Watershed plans'!$K$12:$K$19,MATCH(12,'Watershed plans'!$AB$12:$AB$19,0)),"") | E61: =IFERROR(INDEX('Watershed plans'!$L$12:$L$19,MATCH(12,'Watershed plans'!$AB$12:$AB$19,0)),"") | F61: =IFERROR(INDEX('Watershed plans'!$J$12:$J$19,MATCH(12,'Watershed plans'!$AB$12:$AB$19,0)),"") | G61: =IFERROR(INDEX('Watershed plans'!$Z$12:$Z$19,MATCH(12,'Watershed plans'!$AB$12:$AB$19,0)),"") | H61: =IF(ISNUMBER(D61),D61-D60,"") | I61: =IF(ISNUMBER(E61),E61-E60,"") | J61: =IF(AND(ISNUMBER(H61),H61<>0),I61/H61,"")
A62: 13 | B62: =IFERROR(INDEX('Watershed plans'!$G$12:$G$19,MATCH(13,'Watershed plans'!$AB$12:$AB$19,0)),"") | C62: =IFERROR(INDEX('Watershed plans'!$B$12:$B$19,MATCH(13,'Watershed plans'!$AB$12:$AB$19,0)),"") | D62: =IFERROR(INDEX('Watershed plans'!$K$12:$K$19,MATCH(13,'Watershed plans'!$AB$12:$AB$19,0)),"") | E62: =IFERROR(INDEX('Watershed plans'!$L$12:$L$19,MATCH(13,'Watershed plans'!$AB$12:$AB$19,0)),"") | F62: =IFERROR(INDEX('Watershed plans'!$J$12:$J$19,MATCH(13,'Watershed plans'!$AB$12:$AB$19,0)),"") | G62: =IFERROR(INDEX('Watershed plans'!$Z$12:$Z$19,MATCH(13,'Watershed plans'!$AB$12:$AB$19,0)),"") | H62: =IF(ISNUMBER(D62),D62-D61,"") | I62: =IF(ISNUMBER(E62),E62-E61,"") | J62: =IF(AND(ISNUMBER(H62),H62<>0),I62/H62,"")
A63: 14 | B63: =IFERROR(INDEX('Watershed plans'!$G$12:$G$19,MATCH(14,'Watershed plans'!$AB$12:$AB$19,0)),"") | C63: =IFERROR(INDEX('Watershed plans'!$B$12:$B$19,MATCH(14,'Watershed plans'!$AB$12:$AB$19,0)),"") | D63: =IFERROR(INDEX('Watershed plans'!$K$12:$K$19,MATCH(14,'Watershed plans'!$AB$12:$AB$19,0)),"") | E63: =IFERROR(INDEX('Watershed plans'!$L$12:$L$19,MATCH(14,'Watershed plans'!$AB$12:$AB$19,0)),"") | F63: =IFERROR(INDEX('Watershed plans'!$J$12:$J$19,MATCH(14,'Watershed plans'!$AB$12:$AB$19,0)),"") | G63: =IFERROR(INDEX('Watershed plans'!$Z$12:$Z$19,MATCH(14,'Watershed plans'!$AB$12:$AB$19,0)),"") | H63: =IF(ISNUMBER(D63),D63-D62,"") | I63: =IF(ISNUMBER(E63),E63-E62,"") | J63: =IF(AND(ISNUMBER(H63),H63<>0),I63/H63,"")
A64: 15 | B64: =IFERROR(INDEX('Watershed plans'!$G$12:$G$19,MATCH(15,'Watershed plans'!$AB$12:$AB$19,0)),"") | C64: =IFERROR(INDEX('Watershed plans'!$B$12:$B$19,MATCH(15,'Watershed plans'!$AB$12:$AB$19,0)),"") | D64: =IFERROR(INDEX('Watershed plans'!$K$12:$K$19,MATCH(15,'Watershed plans'!$AB$12:$AB$19,0)),"") | E64: =IFERROR(INDEX('Watershed plans'!$L$12:$L$19,MATCH(15,'Watershed plans'!$AB$12:$AB$19,0)),"") | F64: =IFERROR(INDEX('Watershed plans'!$J$12:$J$19,MATCH(15,'Watershed plans'!$AB$12:$AB$19,0)),"") | G64: =IFERROR(INDEX('Watershed plans'!$Z$12:$Z$19,MATCH(15,'Watershed plans'!$AB$12:$AB$19,0)),"") | H64: =IF(ISNUMBER(D64),D64-D63,"") | I64: =IF(ISNUMBER(E64),E64-E63,"") | J64: =IF(AND(ISNUMBER(H64),H64<>0),I64/H64,"")
A65: 16 | B65: =IFERROR(INDEX('Watershed plans'!$G$12:$G$19,MATCH(16,'Watershed plans'!$AB$12:$AB$19,0)),"") | C65: =IFERROR(INDEX('Watershed plans'!$B$12:$B$19,MATCH(16,'Watershed plans'!$AB$12:$AB$19,0)),"") | D65: =IFERROR(INDEX('Watershed plans'!$K$12:$K$19,MATCH(16,'Watershed plans'!$AB$12:$AB$19,0)),"") | E65: =IFERROR(INDEX('Watershed plans'!$L$12:$L$19,MATCH(16,'Watershed plans'!$AB$12:$AB$19,0)),"") | F65: =IFERROR(INDEX('Watershed plans'!$J$12:$J$19,MATCH(16,'Watershed plans'!$AB$12:$AB$19,0)),"") | G65: =IFERROR(INDEX('Watershed plans'!$Z$12:$Z$19,MATCH(16,'Watershed plans'!$AB$12:$AB$19,0)),"") | H65: =IF(ISNUMBER(D65),D65-D64,"") | I65: =IF(ISNUMBER(E65),E65-E64,"") | J65: =IF(AND(ISNUMBER(H65),H65<>0),I65/H65,"")
A66: 17 | B66: =IFERROR(INDEX('Watershed plans'!$G$12:$G$19,MATCH(17,'Watershed plans'!$AB$12:$AB$19,0)),"") | C66: =IFERROR(INDEX('Watershed plans'!$B$12:$B$19,MATCH(17,'Watershed plans'!$AB$12:$AB$19,0)),"") | D66: =IFERROR(INDEX('Watershed plans'!$K$12:$K$19,MATCH(17,'Watershed plans'!$AB$12:$AB$19,0)),"") | E66: =IFERROR(INDEX('Watershed plans'!$L$12:$L$19,MATCH(17,'Watershed plans'!$AB$12:$AB$19,0)),"") | F66: =IFERROR(INDEX('Watershed plans'!$J$12:$J$19,MATCH(17,'Watershed plans'!$AB$12:$AB$19,0)),"") | G66: =IFERROR(INDEX('Watershed plans'!$Z$12:$Z$19,MATCH(17,'Watershed plans'!$AB$12:$AB$19,0)),"") | H66: =IF(ISNUMBER(D66),D66-D65,"") | I66: =IF(ISNUMBER(E66),E66-E65,"") | J66: =IF(AND(ISNUMBER(H66),H66<>0),I66/H66,"")
A67: 18 | B67: =IFERROR(INDEX('Watershed plans'!$G$12:$G$19,MATCH(18,'Watershed plans'!$AB$12:$AB$19,0)),"") | C67: =IFERROR(INDEX('Watershed plans'!$B$12:$B$19,MATCH(18,'Watershed plans'!$AB$12:$AB$19,0)),"") | D67: =IFERROR(INDEX('Watershed plans'!$K$12:$K$19,MATCH(18,'Watershed plans'!$AB$12:$AB$19,0)),"") | E67: =IFERROR(INDEX('Watershed plans'!$L$12:$L$19,MATCH(18,'Watershed plans'!$AB$12:$AB$19,0)),"") | F67: =IFERROR(INDEX('Watershed plans'!$J$12:$J$19,MATCH(18,'Watershed plans'!$AB$12:$AB$19,0)),"") | G67: =IFERROR(INDEX('Watershed plans'!$Z$12:$Z$19,MATCH(18,'Watershed plans'!$AB$12:$AB$19,0)),"") | H67: =IF(ISNUMBER(D67),D67-D66,"") | I67: =IF(ISNUMBER(E67),E67-E66,"") | J67: =IF(AND(ISNUMBER(H67),H67<>0),I67/H67,"")
A68: 19 | B68: =IFERROR(INDEX('Watershed plans'!$G$12:$G$19,MATCH(19,'Watershed plans'!$AB$12:$AB$19,0)),"") | C68: =IFERROR(INDEX('Watershed plans'!$B$12:$B$19,MATCH(19,'Watershed plans'!$AB$12:$AB$19,0)),"") | D68: =IFERROR(INDEX('Watershed plans'!$K$12:$K$19,MATCH(19,'Watershed plans'!$AB$12:$AB$19,0)),"") | E68: =IFERROR(INDEX('Watershed plans'!$L$12:$L$19,MATCH(19,'Watershed plans'!$AB$12:$AB$19,0)),"") | F68: =IFERROR(INDEX('Watershed plans'!$J$12:$J$19,MATCH(19,'Watershed plans'!$AB$12:$AB$19,0)),"") | G68: =IFERROR(INDEX('Watershed plans'!$Z$12:$Z$19,MATCH(19,'Watershed plans'!$AB$12:$AB$19,0)),"") | H68: =IF(ISNUMBER(D68),D68-D67,"") | I68: =IF(ISNUMBER(E68),E68-E67,"") | J68: =IF(AND(ISNUMBER(H68),H68<>0),I68/H68,"")
A69: 20 | B69: =IFERROR(INDEX('Watershed plans'!$G$12:$G$19,MATCH(20,'Watershed plans'!$AB$12:$AB$19,0)),"") | C69: =IFERROR(INDEX('Watershed plans'!$B$12:$B$19,MATCH(20,'Watershed plans'!$AB$12:$AB$19,0)),"") | D69: =IFERROR(INDEX('Watershed plans'!$K$12:$K$19,MATCH(20,'Watershed plans'!$AB$12:$AB$19,0)),"") | E69: =IFERROR(INDEX('Watershed plans'!$L$12:$L$19,MATCH(20,'Watershed plans'!$AB$12:$AB$19,0)),"") | F69: =IFERROR(INDEX('Watershed plans'!$J$12:$J$19,MATCH(20,'Watershed plans'!$AB$12:$AB$19,0)),"") | G69: =IFERROR(INDEX('Watershed plans'!$Z$12:$Z$19,MATCH(20,'Watershed plans'!$AB$12:$AB$19,0)),"") | H69: =IF(ISNUMBER(D69),D69-D68,"") | I69: =IF(ISNUMBER(E69),E69-E68,"") | J69: =IF(AND(ISNUMBER(H69),H69<>0),I69/H69,"")
A70: 21 | B70: =IFERROR(INDEX('Watershed plans'!$G$12:$G$19,MATCH(21,'Watershed plans'!$AB$12:$AB$19,0)),"") | C70: =IFERROR(INDEX('Watershed plans'!$B$12:$B$19,MATCH(21,'Watershed plans'!$AB$12:$AB$19,0)),"") | D70: =IFERROR(INDEX('Watershed plans'!$K$12:$K$19,MATCH(21,'Watershed plans'!$AB$12:$AB$19,0)),"") | E70: =IFERROR(INDEX('Watershed plans'!$L$12:$L$19,MATCH(21,'Watershed plans'!$AB$12:$AB$19,0)),"") | F70: =IFERROR(INDEX('Watershed plans'!$J$12:$J$19,MATCH(21,'Watershed plans'!$AB$12:$AB$19,0)),"") | G70: =IFERROR(INDEX('Watershed plans'!$Z$12:$Z$19,MATCH(21,'Watershed plans'!$AB$12:$AB$19,0)),"") | H70: =IF(ISNUMBER(D70),D70-D69,"") | I70: =IF(ISNUMBER(E70),E70-E69,"") | J70: =IF(AND(ISNUMBER(H70),H70<>0),I70/H70,"")
A71: 22 | B71: =IFERROR(INDEX('Watershed plans'!$G$12:$G$19,MATCH(22,'Watershed plans'!$AB$12:$AB$19,0)),"") | C71: =IFERROR(INDEX('Watershed plans'!$B$12:$B$19,MATCH(22,'Watershed plans'!$AB$12:$AB$19,0)),"") | D71: =IFERROR(INDEX('Watershed plans'!$K$12:$K$19,MATCH(22,'Watershed plans'!$AB$12:$AB$19,0)),"") | E71: =IFERROR(INDEX('Watershed plans'!$L$12:$L$19,MATCH(22,'Watershed plans'!$AB$12:$AB$19,0)),"") | F71: =IFERROR(INDEX('Watershed plans'!$J$12:$J$19,MATCH(22,'Watershed plans'!$AB$12:$AB$19,0)),"") | G71: =IFERROR(INDEX('Watershed plans'!$Z$12:$Z$19,MATCH(22,'Watershed plans'!$AB$12:$AB$19,0)),"") | H71: =IF(ISNUMBER(D71),D71-D70,"") | I71: =IF(ISNUMBER(E71),E71-E70,"") | J71: =IF(AND(ISNUMBER(H71),H71<>0),I71/H71,"")
A72: 23 | B72: =IFERROR(INDEX('Watershed plans'!$G$12:$G$19,MATCH(23,'Watershed plans'!$AB$12:$AB$19,0)),"") | C72: =IFERROR(INDEX('Watershed plans'!$B$12:$B$19,MATCH(23,'Watershed plans'!$AB$12:$AB$19,0)),"") | D72: =IFERROR(INDEX('Watershed plans'!$K$12:$K$19,MATCH(23,'Watershed plans'!$AB$12:$AB$19,0)),"") | E72: =IFERROR(INDEX('Watershed plans'!$L$12:$L$19,MATCH(23,'Watershed plans'!$AB$12:$AB$19,0)),"") | F72: =IFERROR(INDEX('Watershed plans'!$J$12:$J$19,MATCH(23,'Watershed plans'!$AB$12:$AB$19,0)),"") | G72: =IFERROR(INDEX('Watershed plans'!$Z$12:$Z$19,MATCH(23,'Watershed plans'!$AB$12:$AB$19,0)),"") | H72: =IF(ISNUMBER(D72),D72-D71,"") | I72: =IF(ISNUMBER(E72),E72-E71,"") | J72: =IF(AND(ISNUMBER(H72),H72<>0),I72/H72,"")
A73: 24 | B73: =IFERROR(INDEX('Watershed plans'!$G$12:$G$19,MATCH(24,'Watershed plans'!$AB$12:$AB$19,0)),"") | C73: =IFERROR(INDEX('Watershed plans'!$B$12:$B$19,MATCH(24,'Watershed plans'!$AB$12:$AB$19,0)),"") | D73: =IFERROR(INDEX('Watershed plans'!$K$12:$K$19,MATCH(24,'Watershed plans'!$AB$12:$AB$19,0)),"") | E73: =IFERROR(INDEX('Watershed plans'!$L$12:$L$19,MATCH(24,'Watershed plans'!$AB$12:$AB$19,0)),"") | F73: =IFERROR(INDEX('Watershed plans'!$J$12:$J$19,MATCH(24,'Watershed plans'!$AB$12:$AB$19,0)),"") | G73: =IFERROR(INDEX('Watershed plans'!$Z$12:$Z$19,MATCH(24,'Watershed plans'!$AB$12:$AB$19,0)),"") | H73: =IF(ISNUMBER(D73),D73-D72,"") | I73: =IF(ISNUMBER(E73),E73-E72,"") | J73: =IF(AND(ISNUMBER(H73),H73<>0),I73/H73,"")
A74: 25 | B74: =IFERROR(INDEX('Watershed plans'!$G$12:$G$19,MATCH(25,'Watershed plans'!$AB$12:$AB$19,0)),"") | C74: =IFERROR(INDEX('Watershed plans'!$B$12:$B$19,MATCH(25,'Watershed plans'!$AB$12:$AB$19,0)),"") | D74: =IFERROR(INDEX('Watershed plans'!$K$12:$K$19,MATCH(25,'Watershed plans'!$AB$12:$AB$19,0)),"") | E74: =IFERROR(INDEX('Watershed plans'!$L$12:$L$19,MATCH(25,'Watershed plans'!$AB$12:$AB$19,0)),"") | F74: =IFERROR(INDEX('Watershed plans'!$J$12:$J$19,MATCH(25,'Watershed plans'!$AB$12:$AB$19,0)),"") | G74: =IFERROR(INDEX('Watershed plans'!$Z$12:$Z$19,MATCH(25,'Watershed plans'!$AB$12:$AB$19,0)),"") | H74: =IF(ISNUMBER(D74),D74-D73,"") | I74: =IF(ISNUMBER(E74),E74-E73,"") | J74: =IF(AND(ISNUMBER(H74),H74<>0),I74/H74,"")
A75: 26 | B75: =IFERROR(INDEX('Watershed plans'!$G$12:$G$19,MATCH(26,'Watershed plans'!$AB$12:$AB$19,0)),"") | C75: =IFERROR(INDEX('Watershed plans'!$B$12:$B$19,MATCH(26,'Watershed plans'!$AB$12:$AB$19,0)),"") | D75: =IFERROR(INDEX('Watershed plans'!$K$12:$K$19,MATCH(26,'Watershed plans'!$AB$12:$AB$19,0)),"") | E75: =IFERROR(INDEX('Watershed plans'!$L$12:$L$19,MATCH(26,'Watershed plans'!$AB$12:$AB$19,0)),"") | F75: =IFERROR(INDEX('Watershed plans'!$J$12:$J$19,MATCH(26,'Watershed plans'!$AB$12:$AB$19,0)),"") | G75: =IFERROR(INDEX('Watershed plans'!$Z$12:$Z$19,MATCH(26,'Watershed plans'!$AB$12:$AB$19,0)),"") | H75: =IF(ISNUMBER(D75),D75-D74,"") | I75: =IF(ISNUMBER(E75),E75-E74,"") | J75: =IF(AND(ISNUMBER(H75),H75<>0),I75/H75,"")
A76: 27 | B76: =IFERROR(INDEX('Watershed plans'!$G$12:$G$19,MATCH(27,'Watershed plans'!$AB$12:$AB$19,0)),"") | C76: =IFERROR(INDEX('Watershed plans'!$B$12:$B$19,MATCH(27,'Watershed plans'!$AB$12:$AB$19,0)),"") | D76: =IFERROR(INDEX('Watershed plans'!$K$12:$K$19,MATCH(27,'Watershed plans'!$AB$12:$AB$19,0)),"") | E76: =IFERROR(INDEX('Watershed plans'!$L$12:$L$19,MATCH(27,'Watershed plans'!$AB$12:$AB$19,0)),"") | F76: =IFERROR(INDEX('Watershed plans'!$J$12:$J$19,MATCH(27,'Watershed plans'!$AB$12:$AB$19,0)),"") | G76: =IFERROR(INDEX('Watershed plans'!$Z$12:$Z$19,MATCH(27,'Watershed plans'!$AB$12:$AB$19,0)),"") | H76: =IF(ISNUMBER(D76),D76-D75,"") | I76: =IF(ISNUMBER(E76),E76-E75,"") | J76: =IF(AND(ISNUMBER(H76),H76<>0),I76/H76,"")
A77: 28 | B77: =IFERROR(INDEX('Watershed plans'!$G$12:$G$19,MATCH(28,'Watershed plans'!$AB$12:$AB$19,0)),"") | C77: =IFERROR(INDEX('Watershed plans'!$B$12:$B$19,MATCH(28,'Watershed plans'!$AB$12:$AB$19,0)),"") | D77: =IFERROR(INDEX('Watershed plans'!$K$12:$K$19,MATCH(28,'Watershed plans'!$AB$12:$AB$19,0)),"") | E77: =IFERROR(INDEX('Watershed plans'!$L$12:$L$19,MATCH(28,'Watershed plans'!$AB$12:$AB$19,0)),"") | F77: =IFERROR(INDEX('Watershed plans'!$J$12:$J$19,MATCH(28,'Watershed plans'!$AB$12:$AB$19,0)),"") | G77: =IFERROR(INDEX('Watershed plans'!$Z$12:$Z$19,MATCH(28,'Watershed plans'!$AB$12:$AB$19,0)),"") | H77: =IF(ISNUMBER(D77),D77-D76,"") | I77: =IF(ISNUMBER(E77),E77-E76,"") | J77: =IF(AND(ISNUMBER(H77),H77<>0),I77/H77,"")
A78: 29 | B78: =IFERROR(INDEX('Watershed plans'!$G$12:$G$19,MATCH(29,'Watershed plans'!$AB$12:$AB$19,0)),"") | C78: =IFERROR(INDEX('Watershed plans'!$B$12:$B$19,MATCH(29,'Watershed plans'!$AB$12:$AB$19,0)),"") | D78: =IFERROR(INDEX('Watershed plans'!$K$12:$K$19,MATCH(29,'Watershed plans'!$AB$12:$AB$19,0)),"") | E78: =IFERROR(INDEX('Watershed plans'!$L$12:$L$19,MATCH(29,'Watershed plans'!$AB$12:$AB$19,0)),"") | F78: =IFERROR(INDEX('Watershed plans'!$J$12:$J$19,MATCH(29,'Watershed plans'!$AB$12:$AB$19,0)),"") | G78: =IFERROR(INDEX('Watershed plans'!$Z$12:$Z$19,MATCH(29,'Watershed plans'!$AB$12:$AB$19,0)),"") | H78: =IF(ISNUMBER(D78),D78-D77,"") | I78: =IF(ISNUMBER(E78),E78-E77,"") | J78: =IF(AND(ISNUMBER(H78),H78<>0),I78/H78,"")
A79: 30 | B79: =IFERROR(INDEX('Watershed plans'!$G$12:$G$19,MATCH(30,'Watershed plans'!$AB$12:$AB$19,0)),"") | C79: =IFERROR(INDEX('Watershed plans'!$B$12:$B$19,MATCH(30,'Watershed plans'!$AB$12:$AB$19,0)),"") | D79: =IFERROR(INDEX('Watershed plans'!$K$12:$K$19,MATCH(30,'Watershed plans'!$AB$12:$AB$19,0)),"") | E79: =IFERROR(INDEX('Watershed plans'!$L$12:$L$19,MATCH(30,'Watershed plans'!$AB$12:$AB$19,0)),"") | F79: =IFERROR(INDEX('Watershed plans'!$J$12:$J$19,MATCH(30,'Watershed plans'!$AB$12:$AB$19,0)),"") | G79: =IFERROR(INDEX('Watershed plans'!$Z$12:$Z$19,MATCH(30,'Watershed plans'!$AB$12:$AB$19,0)),"") | H79: =IF(ISNUMBER(D79),D79-D78,"") | I79: =IF(ISNUMBER(E79),E79-E78,"") | J79: =IF(AND(ISNUMBER(H79),H79<>0),I79/H79,"")
A80: 31 | B80: =IFERROR(INDEX('Watershed plans'!$G$12:$G$19,MATCH(31,'Watershed plans'!$AB$12:$AB$19,0)),"") | C80: =IFERROR(INDEX('Watershed plans'!$B$12:$B$19,MATCH(31,'Watershed plans'!$AB$12:$AB$19,0)),"") | D80: =IFERROR(INDEX('Watershed plans'!$K$12:$K$19,MATCH(31,'Watershed plans'!$AB$12:$AB$19,0)),"") | E80: =IFERROR(INDEX('Watershed plans'!$L$12:$L$19,MATCH(31,'Watershed plans'!$AB$12:$AB$19,0)),"") | F80: =IFERROR(INDEX('Watershed plans'!$J$12:$J$19,MATCH(31,'Watershed plans'!$AB$12:$AB$19,0)),"") | G80: =IFERROR(INDEX('Watershed plans'!$Z$12:$Z$19,MATCH(31,'Watershed plans'!$AB$12:$AB$19,0)),"") | H80: =IF(ISNUMBER(D80),D80-D79,"") | I80: =IF(ISNUMBER(E80),E80-E79,"") | J80: =IF(AND(ISNUMBER(H80),H80<>0),I80/H80,"")
A81: 32 | B81: =IFERROR(INDEX('Watershed plans'!$G$12:$G$19,MATCH(32,'Watershed plans'!$AB$12:$AB$19,0)),"") | C81: =IFERROR(INDEX('Watershed plans'!$B$12:$B$19,MATCH(32,'Watershed plans'!$AB$12:$AB$19,0)),"") | D81: =IFERROR(INDEX('Watershed plans'!$K$12:$K$19,MATCH(32,'Watershed plans'!$AB$12:$AB$19,0)),"") | E81: =IFERROR(INDEX('Watershed plans'!$L$12:$L$19,MATCH(32,'Watershed plans'!$AB$12:$AB$19,0)),"") | F81: =IFERROR(INDEX('Watershed plans'!$J$12:$J$19,MATCH(32,'Watershed plans'!$AB$12:$AB$19,0)),"") | G81: =IFERROR(INDEX('Watershed plans'!$Z$12:$Z$19,MATCH(32,'Watershed plans'!$AB$12:$AB$19,0)),"") | H81: =IF(ISNUMBER(D81),D81-D80,"") | I81: =IF(ISNUMBER(E81),E81-E80,"") | J81: =IF(AND(ISNUMBER(H81),H81<>0),I81/H81,"")
A82: 33 | B82: =IFERROR(INDEX('Watershed plans'!$G$12:$G$19,MATCH(33,'Watershed plans'!$AB$12:$AB$19,0)),"") | C82: =IFERROR(INDEX('Watershed plans'!$B$12:$B$19,MATCH(33,'Watershed plans'!$AB$12:$AB$19,0)),"") | D82: =IFERROR(INDEX('Watershed plans'!$K$12:$K$19,MATCH(33,'Watershed plans'!$AB$12:$AB$19,0)),"") | E82: =IFERROR(INDEX('Watershed plans'!$L$12:$L$19,MATCH(33,'Watershed plans'!$AB$12:$AB$19,0)),"") | F82: =IFERROR(INDEX('Watershed plans'!$J$12:$J$19,MATCH(33,'Watershed plans'!$AB$12:$AB$19,0)),"") | G82: =IFERROR(INDEX('Watershed plans'!$Z$12:$Z$19,MATCH(33,'Watershed plans'!$AB$12:$AB$19,0)),"") | H82: =IF(ISNUMBER(D82),D82-D81,"") | I82: =IF(ISNUMBER(E82),E82-E81,"") | J82: =IF(AND(ISNUMBER(H82),H82<>0),I82/H82,"")
A83: 34 | B83: =IFERROR(INDEX('Watershed plans'!$G$12:$G$19,MATCH(34,'Watershed plans'!$AB$12:$AB$19,0)),"") | C83: =IFERROR(INDEX('Watershed plans'!$B$12:$B$19,MATCH(34,'Watershed plans'!$AB$12:$AB$19,0)),"") | D83: =IFERROR(INDEX('Watershed plans'!$K$12:$K$19,MATCH(34,'Watershed plans'!$AB$12:$AB$19,0)),"") | E83: =IFERROR(INDEX('Watershed plans'!$L$12:$L$19,MATCH(34,'Watershed plans'!$AB$12:$AB$19,0)),"") | F83: =IFERROR(INDEX('Watershed plans'!$J$12:$J$19,MATCH(34,'Watershed plans'!$AB$12:$AB$19,0)),"") | G83: =IFERROR(INDEX('Watershed plans'!$Z$12:$Z$19,MATCH(34,'Watershed plans'!$AB$12:$AB$19,0)),"") | H83: =IF(ISNUMBER(D83),D83-D82,"") | I83: =IF(ISNUMBER(E83),E83-E82,"") | J83: =IF(AND(ISNUMBER(H83),H83<>0),I83/H83,"")
A84: 35 | B84: =IFERROR(INDEX('Watershed plans'!$G$12:$G$19,MATCH(35,'Watershed plans'!$AB$12:$AB$19,0)),"") | C84: =IFERROR(INDEX('Watershed plans'!$B$12:$B$19,MATCH(35,'Watershed plans'!$AB$12:$AB$19,0)),"") | D84: =IFERROR(INDEX('Watershed plans'!$K$12:$K$19,MATCH(35,'Watershed plans'!$AB$12:$AB$19,0)),"") | E84: =IFERROR(INDEX('Watershed plans'!$L$12:$L$19,MATCH(35,'Watershed plans'!$AB$12:$AB$19,0)),"") | F84: =IFERROR(INDEX('Watershed plans'!$J$12:$J$19,MATCH(35,'Watershed plans'!$AB$12:$AB$19,0)),"") | G84: =IFERROR(INDEX('Watershed plans'!$Z$12:$Z$19,MATCH(35,'Watershed plans'!$AB$12:$AB$19,0)),"") | H84: =IF(ISNUMBER(D84),D84-D83,"") | I84: =IF(ISNUMBER(E84),E84-E83,"") | J84: =IF(AND(ISNUMBER(H84),H84<>0),I84/H84,"")
A85: 36 | B85: =IFERROR(INDEX('Watershed plans'!$G$12:$G$19,MATCH(36,'Watershed plans'!$AB$12:$AB$19,0)),"") | C85: =IFERROR(INDEX('Watershed plans'!$B$12:$B$19,MATCH(36,'Watershed plans'!$AB$12:$AB$19,0)),"") | D85: =IFERROR(INDEX('Watershed plans'!$K$12:$K$19,MATCH(36,'Watershed plans'!$AB$12:$AB$19,0)),"") | E85: =IFERROR(INDEX('Watershed plans'!$L$12:$L$19,MATCH(36,'Watershed plans'!$AB$12:$AB$19,0)),"") | F85: =IFERROR(INDEX('Watershed plans'!$J$12:$J$19,MATCH(36,'Watershed plans'!$AB$12:$AB$19,0)),"") | G85: =IFERROR(INDEX('Watershed plans'!$Z$12:$Z$19,MATCH(36,'Watershed plans'!$AB$12:$AB$19,0)),"") | H85: =IF(ISNUMBER(D85),D85-D84,"") | I85: =IF(ISNUMBER(E85),E85-E84,"") | J85: =IF(AND(ISNUMBER(H85),H85<>0),I85/H85,"")
A86: 37 | B86: =IFERROR(INDEX('Watershed plans'!$G$12:$G$19,MATCH(37,'Watershed plans'!$AB$12:$AB$19,0)),"") | C86: =IFERROR(INDEX('Watershed plans'!$B$12:$B$19,MATCH(37,'Watershed plans'!$AB$12:$AB$19,0)),"") | D86: =IFERROR(INDEX('Watershed plans'!$K$12:$K$19,MATCH(37,'Watershed plans'!$AB$12:$AB$19,0)),"") | E86: =IFERROR(INDEX('Watershed plans'!$L$12:$L$19,MATCH(37,'Watershed plans'!$AB$12:$AB$19,0)),"") | F86: =IFERROR(INDEX('Watershed plans'!$J$12:$J$19,MATCH(37,'Watershed plans'!$AB$12:$AB$19,0)),"") | G86: =IFERROR(INDEX('Watershed plans'!$Z$12:$Z$19,MATCH(37,'Watershed plans'!$AB$12:$AB$19,0)),"") | H86: =IF(ISNUMBER(D86),D86-D85,"") | I86: =IF(ISNUMBER(E86),E86-E85,"") | J86: =IF(AND(ISNUMBER(H86),H86<>0),I86/H86,"")
A87: 38 | B87: =IFERROR(INDEX('Watershed plans'!$G$12:$G$19,MATCH(38,'Watershed plans'!$AB$12:$AB$19,0)),"") | C87: =IFERROR(INDEX('Watershed plans'!$B$12:$B$19,MATCH(38,'Watershed plans'!$AB$12:$AB$19,0)),"") | D87: =IFERROR(INDEX('Watershed plans'!$K$12:$K$19,MATCH(38,'Watershed plans'!$AB$12:$AB$19,0)),"") | E87: =IFERROR(INDEX('Watershed plans'!$L$12:$L$19,MATCH(38,'Watershed plans'!$AB$12:$AB$19,0)),"") | F87: =IFERROR(INDEX('Watershed plans'!$J$12:$J$19,MATCH(38,'Watershed plans'!$AB$12:$AB$19,0)),"") | G87: =IFERROR(INDEX('Watershed plans'!$Z$12:$Z$19,MATCH(38,'Watershed plans'!$AB$12:$AB$19,0)),"") | H87: =IF(ISNUMBER(D87),D87-D86,"") | I87: =IF(ISNUMBER(E87),E87-E86,"") | J87: =IF(AND(ISNUMBER(H87),H87<>0),I87/H87,"")
A88: 39 | B88: =IFERROR(INDEX('Watershed plans'!$G$12:$G$19,MATCH(39,'Watershed plans'!$AB$12:$AB$19,0)),"") | C88: =IFERROR(INDEX('Watershed plans'!$B$12:$B$19,MATCH(39,'Watershed plans'!$AB$12:$AB$19,0)),"") | D88: =IFERROR(INDEX('Watershed plans'!$K$12:$K$19,MATCH(39,'Watershed plans'!$AB$12:$AB$19,0)),"") | E88: =IFERROR(INDEX('Watershed plans'!$L$12:$L$19,MATCH(39,'Watershed plans'!$AB$12:$AB$19,0)),"") | F88: =IFERROR(INDEX('Watershed plans'!$J$12:$J$19,MATCH(39,'Watershed plans'!$AB$12:$AB$19,0)),"") | G88: =IFERROR(INDEX('Watershed plans'!$Z$12:$Z$19,MATCH(39,'Watershed plans'!$AB$12:$AB$19,0)),"") | H88: =IF(ISNUMBER(D88),D88-D87,"") | I88: =IF(ISNUMBER(E88),E88-E87,"") | J88: =IF(AND(ISNUMBER(H88),H88<>0),I88/H88,"")
A89: 40 | B89: =IFERROR(INDEX('Watershed plans'!$G$12:$G$19,MATCH(40,'Watershed plans'!$AB$12:$AB$19,0)),"") | C89: =IFERROR(INDEX('Watershed plans'!$B$12:$B$19,MATCH(40,'Watershed plans'!$AB$12:$AB$19,0)),"") | D89: =IFERROR(INDEX('Watershed plans'!$K$12:$K$19,MATCH(40,'Watershed plans'!$AB$12:$AB$19,0)),"") | E89: =IFERROR(INDEX('Watershed plans'!$L$12:$L$19,MATCH(40,'Watershed plans'!$AB$12:$AB$19,0)),"") | F89: =IFERROR(INDEX('Watershed plans'!$J$12:$J$19,MATCH(40,'Watershed plans'!$AB$12:$AB$19,0)),"") | G89: =IFERROR(INDEX('Watershed plans'!$Z$12:$Z$19,MATCH(40,'Watershed plans'!$AB$12:$AB$19,0)),"") | H89: =IF(ISNUMBER(D89),D89-D88,"") | I89: =IF(ISNUMBER(E89),E89-E88,"") | J89: =IF(AND(ISNUMBER(H89),H89<>0),I89/H89,"")
A92: Tentatively selected plan
A93: Plan number
A94: Plan | B94: =IFERROR(INDEX('Watershed plans'!$B$12:$B$19,MATCH($B$93,'Watershed plans'!$G$12:$G$19,0)),"n/a")
A95: Lift (AAHU) | B95: =IFERROR(INDEX('Watershed plans'!$K$12:$K$19,MATCH($B$93,'Watershed plans'!$G$12:$G$19,0)),"n/a")
A96: Average annual cost | B96: =IFERROR(INDEX('Watershed plans'!$L$12:$L$19,MATCH($B$93,'Watershed plans'!$G$12:$G$19,0)),"n/a")
A97: Construction cost | B97: =IFERROR(INDEX('Watershed plans'!$J$12:$J$19,MATCH($B$93,'Watershed plans'!$G$12:$G$19,0)),"n/a")
A98: Unit cost | B98: =IFERROR(INDEX('Watershed plans'!$Z$12:$Z$19,MATCH($B$93,'Watershed plans'!$G$12:$G$19,0)),"n/a")
A99: In the final array | B99: =IFERROR(INDEX('Watershed plans'!$AA$12:$AA$19,MATCH($B$93,'Watershed plans'!$G$12:$G$19,0)),"n/a")

Sheet IWR input
A1: IWR Planning Suite II input
A2: Paste-ready plan, output and cost columns for an independent re-run in IWR Planning Suite II (user-entered planning set; No Action is the first plan).
A4: Site planning sets
A5: Site | B5: Plan | C5: Output (AAHU above No Action) | D5: Cost (average annual, above No Action)
A6: A | B6: NA | C6: ='Site CE-ICA'!I6/10^in_out_dp | D6: ='Site CE-ICA'!J6/10^in_cost_dp
A7: A | B7: A1 | C7: ='Site CE-ICA'!I7/10^in_out_dp | D7: ='Site CE-ICA'!J7/10^in_cost_dp
A8: A | B8: A2 | C8: ='Site CE-ICA'!I8/10^in_out_dp | D8: ='Site CE-ICA'!J8/10^in_cost_dp
A9: B | B9: NA | C9: ='Site CE-ICA'!I11/10^in_out_dp | D9: ='Site CE-ICA'!J11/10^in_cost_dp
A10: B | B10: B1 | C10: ='Site CE-ICA'!I12/10^in_out_dp | D10: ='Site CE-ICA'!J12/10^in_cost_dp
A11: B | B11: B2 | C11: ='Site CE-ICA'!I13/10^in_out_dp | D11: ='Site CE-ICA'!J13/10^in_cost_dp
A12: B | B12: B3 | C12: ='Site CE-ICA'!I14/10^in_out_dp | D12: ='Site CE-ICA'!J14/10^in_cost_dp
A13: C | B13: NA | C13: ='Site CE-ICA'!I17/10^in_out_dp | D13: ='Site CE-ICA'!J17/10^in_cost_dp
A14: C | B14: C1 | C14: ='Site CE-ICA'!I18/10^in_out_dp | D14: ='Site CE-ICA'!J18/10^in_cost_dp
A16: Watershed planning set (valid plans)
A17: Plan number | B17: Plan | C17: Output | D17: Cost
A18: ='Watershed plans'!G12 | B18: ='Watershed plans'!B12 | C18: =IF('Watershed plans'!C12=1,'Watershed plans'!K12,"") | D18: =IF('Watershed plans'!C12=1,'Watershed plans'!L12,"")
A19: ='Watershed plans'!G13 | B19: ='Watershed plans'!B13 | C19: =IF('Watershed plans'!C13=1,'Watershed plans'!K13,"") | D19: =IF('Watershed plans'!C13=1,'Watershed plans'!L13,"")
A20: ='Watershed plans'!G14 | B20: ='Watershed plans'!B14 | C20: =IF('Watershed plans'!C14=1,'Watershed plans'!K14,"") | D20: =IF('Watershed plans'!C14=1,'Watershed plans'!L14,"")
A21: ='Watershed plans'!G15 | B21: ='Watershed plans'!B15 | C21: =IF('Watershed plans'!C15=1,'Watershed plans'!K15,"") | D21: =IF('Watershed plans'!C15=1,'Watershed plans'!L15,"")
A22: ='Watershed plans'!G16 | B22: ='Watershed plans'!B16 | C22: =IF('Watershed plans'!C16=1,'Watershed plans'!K16,"") | D22: =IF('Watershed plans'!C16=1,'Watershed plans'!L16,"")
A23: ='Watershed plans'!G17 | B23: ='Watershed plans'!B17 | C23: =IF('Watershed plans'!C17=1,'Watershed plans'!K17,"") | D23: =IF('Watershed plans'!C17=1,'Watershed plans'!L17,"")
A24: ='Watershed plans'!G18 | B24: ='Watershed plans'!B18 | C24: =IF('Watershed plans'!C18=1,'Watershed plans'!K18,"") | D24: =IF('Watershed plans'!C18=1,'Watershed plans'!L18,"")
A25: ='Watershed plans'!G19 | B25: ='Watershed plans'!B19 | C25: =IF('Watershed plans'!C19=1,'Watershed plans'!K19,"") | D25: =IF('Watershed plans'!C19=1,'Watershed plans'!L19,"")

Sheet Charts
A1: Charts: watershed cost-effectiveness and incremental cost
A2: Built from the watershed plans sheet; they update with the inputs.
A30: All plans: lift | B30: All plans: cost | C30: Frontier: lift | D30: Frontier: cost | E30: Best buys: lift | F30: Best buys: cost | G30: Steps: output | H30: Steps: incremental cost | K30: (frontier order)
A31: =IF('Watershed plans'!C12=1,'Watershed plans'!K12,NA()) | B31: =IF('Watershed plans'!C12=1,'Watershed plans'!L12,NA()) | C31: =IFERROR(INDEX('Watershed plans'!$K$12:$K$19,MATCH(1,$K$31:$K$38,0)),NA()) | D31: =IFERROR(INDEX('Watershed plans'!$L$12:$L$19,MATCH(1,$K$31:$K$38,0)),NA()) | E31: =IFERROR(INDEX('Watershed plans'!$K$12:$K$19,MATCH(1,'Watershed plans'!$T$12:$T$19,0)),NA()) | F31: =IFERROR(INDEX('Watershed plans'!$L$12:$L$19,MATCH(1,'Watershed plans'!$T$12:$T$19,0)),NA()) | G31: =E31 | H31: =IFERROR(INDEX('Watershed plans'!$Y$12:$Y$19,MATCH(2,'Watershed plans'!$T$12:$T$19,0)),NA()) | K31: =IF('Watershed plans'!O12=1,1+SUMPRODUCT('Watershed plans'!$O$12:$O$19*(('Watershed plans'!$H$12:$H$19<'Watershed plans'!H12)+('Watershed plans'!$H$12:$H$19='Watershed plans'!H12)*('Watershed plans'!$A$12:$A$19<'Watershed plans'!A12))),0)
A32: =IF('Watershed plans'!C13=1,'Watershed plans'!K13,NA()) | B32: =IF('Watershed plans'!C13=1,'Watershed plans'!L13,NA()) | C32: =IFERROR(INDEX('Watershed plans'!$K$12:$K$19,MATCH(2,$K$31:$K$38,0)),NA()) | D32: =IFERROR(INDEX('Watershed plans'!$L$12:$L$19,MATCH(2,$K$31:$K$38,0)),NA()) | E32: =IFERROR(INDEX('Watershed plans'!$K$12:$K$19,MATCH(2,'Watershed plans'!$T$12:$T$19,0)),NA()) | F32: =IFERROR(INDEX('Watershed plans'!$L$12:$L$19,MATCH(2,'Watershed plans'!$T$12:$T$19,0)),NA()) | G32: =E32 | H32: =IFERROR(INDEX('Watershed plans'!$Y$12:$Y$19,MATCH(2,'Watershed plans'!$T$12:$T$19,0)),NA()) | K32: =IF('Watershed plans'!O13=1,1+SUMPRODUCT('Watershed plans'!$O$12:$O$19*(('Watershed plans'!$H$12:$H$19<'Watershed plans'!H13)+('Watershed plans'!$H$12:$H$19='Watershed plans'!H13)*('Watershed plans'!$A$12:$A$19<'Watershed plans'!A13))),0)
A33: =IF('Watershed plans'!C14=1,'Watershed plans'!K14,NA()) | B33: =IF('Watershed plans'!C14=1,'Watershed plans'!L14,NA()) | C33: =IFERROR(INDEX('Watershed plans'!$K$12:$K$19,MATCH(3,$K$31:$K$38,0)),NA()) | D33: =IFERROR(INDEX('Watershed plans'!$L$12:$L$19,MATCH(3,$K$31:$K$38,0)),NA()) | E33: =IFERROR(INDEX('Watershed plans'!$K$12:$K$19,MATCH(3,'Watershed plans'!$T$12:$T$19,0)),NA()) | F33: =IFERROR(INDEX('Watershed plans'!$L$12:$L$19,MATCH(3,'Watershed plans'!$T$12:$T$19,0)),NA()) | G33: =NA() | H33: =NA() | K33: =IF('Watershed plans'!O14=1,1+SUMPRODUCT('Watershed plans'!$O$12:$O$19*(('Watershed plans'!$H$12:$H$19<'Watershed plans'!H14)+('Watershed plans'!$H$12:$H$19='Watershed plans'!H14)*('Watershed plans'!$A$12:$A$19<'Watershed plans'!A14))),0)
A34: =IF('Watershed plans'!C15=1,'Watershed plans'!K15,NA()) | B34: =IF('Watershed plans'!C15=1,'Watershed plans'!L15,NA()) | C34: =IFERROR(INDEX('Watershed plans'!$K$12:$K$19,MATCH(4,$K$31:$K$38,0)),NA()) | D34: =IFERROR(INDEX('Watershed plans'!$L$12:$L$19,MATCH(4,$K$31:$K$38,0)),NA()) | E34: =IFERROR(INDEX('Watershed plans'!$K$12:$K$19,MATCH(4,'Watershed plans'!$T$12:$T$19,0)),NA()) | F34: =IFERROR(INDEX('Watershed plans'!$L$12:$L$19,MATCH(4,'Watershed plans'!$T$12:$T$19,0)),NA()) | G34: =E32 | H34: =IFERROR(INDEX('Watershed plans'!$Y$12:$Y$19,MATCH(3,'Watershed plans'!$T$12:$T$19,0)),NA()) | K34: =IF('Watershed plans'!O15=1,1+SUMPRODUCT('Watershed plans'!$O$12:$O$19*(('Watershed plans'!$H$12:$H$19<'Watershed plans'!H15)+('Watershed plans'!$H$12:$H$19='Watershed plans'!H15)*('Watershed plans'!$A$12:$A$19<'Watershed plans'!A15))),0)
A35: =IF('Watershed plans'!C16=1,'Watershed plans'!K16,NA()) | B35: =IF('Watershed plans'!C16=1,'Watershed plans'!L16,NA()) | C35: =IFERROR(INDEX('Watershed plans'!$K$12:$K$19,MATCH(5,$K$31:$K$38,0)),NA()) | D35: =IFERROR(INDEX('Watershed plans'!$L$12:$L$19,MATCH(5,$K$31:$K$38,0)),NA()) | E35: =IFERROR(INDEX('Watershed plans'!$K$12:$K$19,MATCH(5,'Watershed plans'!$T$12:$T$19,0)),NA()) | F35: =IFERROR(INDEX('Watershed plans'!$L$12:$L$19,MATCH(5,'Watershed plans'!$T$12:$T$19,0)),NA()) | G35: =E33 | H35: =IFERROR(INDEX('Watershed plans'!$Y$12:$Y$19,MATCH(3,'Watershed plans'!$T$12:$T$19,0)),NA()) | K35: =IF('Watershed plans'!O16=1,1+SUMPRODUCT('Watershed plans'!$O$12:$O$19*(('Watershed plans'!$H$12:$H$19<'Watershed plans'!H16)+('Watershed plans'!$H$12:$H$19='Watershed plans'!H16)*('Watershed plans'!$A$12:$A$19<'Watershed plans'!A16))),0)
A36: =IF('Watershed plans'!C17=1,'Watershed plans'!K17,NA()) | B36: =IF('Watershed plans'!C17=1,'Watershed plans'!L17,NA()) | C36: =IFERROR(INDEX('Watershed plans'!$K$12:$K$19,MATCH(6,$K$31:$K$38,0)),NA()) | D36: =IFERROR(INDEX('Watershed plans'!$L$12:$L$19,MATCH(6,$K$31:$K$38,0)),NA()) | E36: =IFERROR(INDEX('Watershed plans'!$K$12:$K$19,MATCH(6,'Watershed plans'!$T$12:$T$19,0)),NA()) | F36: =IFERROR(INDEX('Watershed plans'!$L$12:$L$19,MATCH(6,'Watershed plans'!$T$12:$T$19,0)),NA()) | G36: =NA() | H36: =NA() | K36: =IF('Watershed plans'!O17=1,1+SUMPRODUCT('Watershed plans'!$O$12:$O$19*(('Watershed plans'!$H$12:$H$19<'Watershed plans'!H17)+('Watershed plans'!$H$12:$H$19='Watershed plans'!H17)*('Watershed plans'!$A$12:$A$19<'Watershed plans'!A17))),0)
A37: =IF('Watershed plans'!C18=1,'Watershed plans'!K18,NA()) | B37: =IF('Watershed plans'!C18=1,'Watershed plans'!L18,NA()) | C37: =IFERROR(INDEX('Watershed plans'!$K$12:$K$19,MATCH(7,$K$31:$K$38,0)),NA()) | D37: =IFERROR(INDEX('Watershed plans'!$L$12:$L$19,MATCH(7,$K$31:$K$38,0)),NA()) | E37: =IFERROR(INDEX('Watershed plans'!$K$12:$K$19,MATCH(7,'Watershed plans'!$T$12:$T$19,0)),NA()) | F37: =IFERROR(INDEX('Watershed plans'!$L$12:$L$19,MATCH(7,'Watershed plans'!$T$12:$T$19,0)),NA()) | G37: =E33 | H37: =IFERROR(INDEX('Watershed plans'!$Y$12:$Y$19,MATCH(4,'Watershed plans'!$T$12:$T$19,0)),NA()) | K37: =IF('Watershed plans'!O18=1,1+SUMPRODUCT('Watershed plans'!$O$12:$O$19*(('Watershed plans'!$H$12:$H$19<'Watershed plans'!H18)+('Watershed plans'!$H$12:$H$19='Watershed plans'!H18)*('Watershed plans'!$A$12:$A$19<'Watershed plans'!A18))),0)
A38: =IF('Watershed plans'!C19=1,'Watershed plans'!K19,NA()) | B38: =IF('Watershed plans'!C19=1,'Watershed plans'!L19,NA()) | C38: =IFERROR(INDEX('Watershed plans'!$K$12:$K$19,MATCH(8,$K$31:$K$38,0)),NA()) | D38: =IFERROR(INDEX('Watershed plans'!$L$12:$L$19,MATCH(8,$K$31:$K$38,0)),NA()) | E38: =IFERROR(INDEX('Watershed plans'!$K$12:$K$19,MATCH(8,'Watershed plans'!$T$12:$T$19,0)),NA()) | F38: =IFERROR(INDEX('Watershed plans'!$L$12:$L$19,MATCH(8,'Watershed plans'!$T$12:$T$19,0)),NA()) | G38: =E34 | H38: =IFERROR(INDEX('Watershed plans'!$Y$12:$Y$19,MATCH(4,'Watershed plans'!$T$12:$T$19,0)),NA()) | K38: =IF('Watershed plans'!O19=1,1+SUMPRODUCT('Watershed plans'!$O$12:$O$19*(('Watershed plans'!$H$12:$H$19<'Watershed plans'!H19)+('Watershed plans'!$H$12:$H$19='Watershed plans'!H19)*('Watershed plans'!$A$12:$A$19<'Watershed plans'!A19))),0)
G39: =NA() | H39: =NA()
G40: =E34 | H40: =IFERROR(INDEX('Watershed plans'!$Y$12:$Y$19,MATCH(5,'Watershed plans'!$T$12:$T$19,0)),NA())
G41: =E35 | H41: =IFERROR(INDEX('Watershed plans'!$Y$12:$Y$19,MATCH(5,'Watershed plans'!$T$12:$T$19,0)),NA())
G42: =NA() | H42: =NA()
G43: =E35 | H43: =IFERROR(INDEX('Watershed plans'!$Y$12:$Y$19,MATCH(6,'Watershed plans'!$T$12:$T$19,0)),NA())
G44: =E36 | H44: =IFERROR(INDEX('Watershed plans'!$Y$12:$Y$19,MATCH(6,'Watershed plans'!$T$12:$T$19,0)),NA())
G45: =NA() | H45: =NA()
G46: =E36 | H46: =IFERROR(INDEX('Watershed plans'!$Y$12:$Y$19,MATCH(7,'Watershed plans'!$T$12:$T$19,0)),NA())
G47: =E37 | H47: =IFERROR(INDEX('Watershed plans'!$Y$12:$Y$19,MATCH(7,'Watershed plans'!$T$12:$T$19,0)),NA())
G48: =NA() | H48: =NA()
G49: =E37 | H49: =IFERROR(INDEX('Watershed plans'!$Y$12:$Y$19,MATCH(8,'Watershed plans'!$T$12:$T$19,0)),NA())
G50: =E38 | H50: =IFERROR(INDEX('Watershed plans'!$Y$12:$Y$19,MATCH(8,'Watershed plans'!$T$12:$T$19,0)),NA())
G51: =NA() | H51: =NA()

Sheet snap Parameters
B4: 0.03
B5: 50
B6: 12
B7: END
B8: END_OF_YEAR
B9: 2
B10: 3
B14: 0 | C14: 5 | D14: 50

Sheet snap Benefits
F6: 1 | G6: 1 | H6: 1
F7: 1 | G7: 5 | H7: 6
F8: 1 | G8: 3 | H8: 3.5
F9: 2 | G9: 2 | H9: 2
F10: 2 | G10: 4 | H10: 4
F11: 2 | G11: 4 | H11: 4
F12: 2 | G12: 6 | H12: 6
F13: 0.5 | G13: 0.5 | H13: 0.5
F14: 0.5 | G14: 2 | H14: 2.5

Sheet snap Costs
G6: 0
D7: 300000 | E7: 20000 | G7: 6
D8: 150000 | G8: 6
G9: 0
D10: 100000 | G10: 3
D11: 100000 | G11: 3
D12: 200000 | G12: 3
G13: 0
D14: 90000 | G14: 6

Sheet snap OMRRR
F5: 2500 | K5: 1
G6: 0.1 | H6: construction | K6: 20
I7: 4 | J7: 1200 | K7: 2
F8: 2500 | K8: 1

Sheet snap Sites
C5: A1
C6: B3
C7: C1

Sheet snap Watershed plans
O12: 1 | S12: 1 | AA12: 1
O13: 1 | S13: 0 | AA13: 0
O14: 1 | S14: 1 | AA14: 1
O15: 1 | S15: 0 | AA15: 0
O16: 0 | S16: 0 | AA16: 0
O17: 1 | S17: 0 | AA17: 0
O18: 1 | S18: 1 | AA18: 1
O19: 1 | S19: 1 | AA19: 1

Sheet snap Watershed summary

Sheet snap Summary
G5: 0 | L5: 0
G6: 4.25 | L6: 15009.085
G7: 2.125 | L7: 8731.9199
G8: 0 | L8: 0
G9: 1.9 | L9: 3896.1426
G10: 1.9 | L10: 3896.1426
G11: 3.8 | L11: 7792.2852
G12: 0 | L12: 0
G13: 1.65 | L13: 6019.5324

Sheet snap Site CE-ICA
L6: 1 | P6: 1
L7: 1 | P7: 1
L8: 1 | P8: 0
L11: 1 | P11: 1
L12: 1 | P12: 1
L13: 1 | P13: 1
L14: 1 | P14: 1
L17: 1 | P17: 1
L18: 1 | P18: 1

Sheet manifest
A1: ceica-calculator | B1: 2
A2: project | B2: 1 | C2: {"benefits":{"modules":[{"id":"total","method":"HU","name":"Total","quantity_units":""}],"staf_mapping":"A","target_years":[0.0,5.0,50.0]},"cost_categories":[{"id":"construction","idc_applies":true,"name":"Construction"},{"id":"monitoring","idc_applies":false,"name":"Monitoring"},{"id":"adaptive_management","idc_applies":false,"name":"Adaptive management"}],"decisions":{"sites":{},"watershed":{"basis":null,"final_array":{},"steps":{},"tsp":null,"tsp_plan_type":"National Ecosystem Restoration (NER) plan","tsp_rationale":""}},"description":"","district":"Mobile District","labels":{"annual_output_name":"Average annual habitat units","annual_output_short":"AAHU","lift_name":"Ecological lift","output_name":"Habitat units","output_short":"HU"},"name":"Small test","prepared_by":"A. Planner","project_id":"349e805601964609a2385ab7f162db4a","provenance":{},"report":{"contents":"FULL","date":"","prepared_by":"","status":"DRAFT","title":""},"schema_version":"ceica-project/2","settings":{"aahu_method":"TRAPEZOID","cost_decimals":2,"discount_rate":0.03,"idc_method":"END","idc_periods_per_year":12,"output_decimals":3,"period_of_analysis":50,"price_level":"","recurring_timing":"END_OF_YEAR"},"sites":[{"alternatives":[{"costs":{"annual_override":null,"construction_months":0.0,"first_costs":{},"recurring":[]},"description":"","id":"NA","is_no_action":true,"name":"NA","outputs":[{"aahu":null,"module_id":"total","quantity":[],"scores":{},"values":[1.0,1.0,1.0]}]},{"costs":{"annual_override":null,"construction_months":6.0,"first_costs":{"construction":300000.0,"monitoring":20000.0},"recurring":[{"amount":2500.0,"basis":"FIXED","category_id":null,"every_years":1,"first_year":null,"id":"om","last_year":null,"name":"Annual O&M","percent":0.0,"quantity":0.0,"quantity_units":"","unit_rate":0.0}]},"description":"","id":"A1","is_no_action":false,"name":"A1","outputs":[{"aahu":null,"module_id":"total","quantity":[],"scores":{},"values":[1.0,5.0,6.0]}]},{"costs":{"annual_override":null,"construction_months":6.0,"first_costs":{"construction":150000.0},"recurring":[{"amount":0.0,"basis":"PCT_OF_CATEGORY","category_id":"construction","every_years":20,"first_year":null,"id":"rep","last_year":null,"name":"Repair","percent":0.1,"quantity":0.0,"quantity_units":"","unit_rate":0.0},{"amount":0.0,"basis":"RATE_X_QUANTITY","category_id":null,"every_years":2,"first_year":null,"id":"insp","last_year":null,"name":"Inspection","percent":0.0,"quantity":1200.0,"quantity_units":"","unit_rate":4.0}]},"description":"","id":"A2","is_no_action":false,"name":"A2","outputs":[{"aahu":null,"module_id":"total","quantity":[],"scores":{},"values":[1.0,3.0,3.5]}]}],"description":"","id":"A","name":"Upper","staf_not_assessed":{},"staf_source":{}},{"alternatives":[{"costs":{"annual_override":null,"construction_months":0.0,"first_costs":{},"recurring":[]},"description":"","id":"NA","is_no_action":true,"name":"NA","outputs":[{"aahu":null,"module_id":"total","quantity":[],"scores":{},"values":[2.0,2.0,2.0]}]},{"costs":{"annual_override":null,"construction_months":3.0,"first_costs":{"construction":100000.0},"recurring":[]},"description":"","id":"B1","is_no_action":false,"name":"B1","outputs":[{"aahu":null,"module_id":"total","quantity":[],"scores":{},"values":[2.0,4.0,4.0]}]},{"costs":{"annual_override":null,"construction_months":3.0,"first_costs":{"construction":100000.0},"recurring":[]},"description":"","id":"B2","is_no_action":false,"name":"B2","outputs":[{"aahu":null,"module_id":"total","quantity":[],"scores":{},"values":[2.0,4.0,4.0]}]},{"costs":{"annual_override":null,"construction_months":3.0,"first_costs":{"construction":200000.0},"recurring":[]},"description":"","id":"B3","is_no_action":false,"name":"B3","outputs":[{"aahu":null,"module_id":"total","quantity":[],"scores":{},"values":[2.0,6.0,6.0]}]}],"description":"","id":"B","name":"Middle","staf_not_assessed":{},"staf_source":{}},{"alternatives":[{"costs":{"annual_override":null,"construction_months":0.0,"first_costs":{},"recurring":[]},"description":"","id":"NA","is_no_action":true,"name":"NA","outputs":[{"aahu":null,"module_id":"total","quantity":[],"scores":{},"values":[0.5,0.5,0.5]}]},{"costs":{"annual_override":null,"construction_months":6.0,"first_costs":{"construction":90000.0},"recurring":[{"amount":2500.0,"basis":"FIXED","category_id":null,"every_years":1,"first_year":null,"id":"om","last_year":null,"name":"Annual O&M","percent":0.0,"quantity":0.0,"quantity_units":"","unit_rate":0.0}]},"description":"","id":"C1","is_no_action":false,"name":"C1","outputs":[{"aahu":null,"module_id":"total","quantity":[],"scores":{},"values":[0.5,2.0,2.5]}]}],"description":"","id":"C","name":"Lower","staf_not_assessed":{},"staf_source":{}}],"watershed":{"carried":{},"mode":"RECOMMENDED","rules":[]}}
A3: meta | B3: 1 | C3: {"appVersion":"0.1.0","engineVersion":"1","format":"ceica-calculator","formatVersion":2,"layout":[{"cell":"B4","kind":"number","path":["settings","discount_rate"],"sheet":"Parameters"},{"cell":"B5","kind":"number","path":["settings","period_of_analysis"],"sheet":"Parameters"},{"cell":"B6","kind":"number","path":["settings","idc_periods_per_year"],"sheet":"Parameters"},{"cell":"B7","kind":"text","path":["settings","idc_method"],"sheet":"Parameters"},{"cell":"B8","kind":"text","path":["settings","recurring_timing"],"sheet":"Parameters"},{"cell":"B9","kind":"number","path":["settings","cost_decimals"],"sheet":"Parameters"},{"cell":"B10","kind":"number","path":["settings","output_decimals"],"sheet":"Parameters"},{"cell":"B14","kind":"number","path":["benefits","target_years",0],"sheet":"Parameters"},{"cell":"C14","kind":"number","path":["benefits","target_years",1],"sheet":"Parameters"},{"cell":"D14","kind":"number","path":["benefits","target_years",2],"sheet":"Parameters"},{"cell":"F6","kind":"optional","path":["sites",0,"alternatives",0,"outputs",{"module_id":"total"},"values",0],"sheet":"Benefits"},{"cell":"G6","kind":"optional","path":["sites",0,"alternatives",0,"outputs",{"module_id":"total"},"values",1],"sheet":"Benefits"},{"cell":"H6","kind":"optional","path":["sites",0,"alternatives",0,"outputs",{"module_id":"total"},"values",2],"sheet":"Benefits"},{"cell":"F7","kind":"optional","path":["sites",0,"alternatives",1,"outputs",{"module_id":"total"},"values",0],"sheet":"Benefits"},{"cell":"G7","kind":"optional","path":["sites",0,"alternatives",1,"outputs",{"module_id":"total"},"values",1],"sheet":"Benefits"},{"cell":"H7","kind":"optional","path":["sites",0,"alternatives",1,"outputs",{"module_id":"total"},"values",2],"sheet":"Benefits"},{"cell":"F8","kind":"optional","path":["sites",0,"alternatives",2,"outputs",{"module_id":"total"},"values",0],"sheet":"Benefits"},{"cell":"G8","kind":"optional","path":["sites",0,"alternatives",2,"outputs",{"module_id":"total"},"values",1],"sheet":"Benefits"},{"cell":"H8","kind":"optional","path":["sites",0,"alternatives",2,"outputs",{"module_id":"total"},"values",2],"sheet":"Benefits"},{"cell":"F9","kind":"optional","path":["sites",1,"alternatives",0,"outputs",{"module_id":"total"},"values",0],"sheet":"Benefits"},{"cell":"G9","kind":"optional","path":["sites",1,"alternatives",0,"outputs",{"module_id":"total"},"values",1],"sheet":"Benefits"},{"cell":"H9","kind":"optional","path":["sites",1,"alternatives",0,"outputs",{"module_id":"total"},"values",2],"sheet":"Benefits"},{"cell":"F10","kind":"optional","path":["sites",1,"alternatives",1,"outputs",{"module_id":"total"},"values",0],"sheet":"Benefits"},{"cell":"G10","kind":"optional","path":["sites",1,"alternatives",1,"outputs",{"module_id":"total"},"values",1],"sheet":"Benefits"},{"cell":"H10","kind":"optional","path":["sites",1,"alternatives",1,"outputs",{"module_id":"total"},"values",2],"sheet":"Benefits"},{"cell":"F11","kind":"optional","path":["sites",1,"alternatives",2,"outputs",{"module_id":"total"},"values",0],"sheet":"Benefits"},{"cell":"G11","kind":"optional","path":["sites",1,"alternatives",2,"outputs",{"module_id":"total"},"values",1],"sheet":"Benefits"},{"cell":"H11","kind":"optional","path":["sites",1,"alternatives",2,"outputs",{"module_id":"total"},"values",2],"sheet":"Benefits"},{"cell":"F12","kind":"optional","path":["sites",1,"alternatives",3,"outputs",{"module_id":"total"},"values",0],"sheet":"Benefits"},{"cell":"G12","kind":"optional","path":["sites",1,"alternatives",3,"outputs",{"module_id":"total"},"values",1],"sheet":"Benefits"},{"cell":"H12","kind":"optional","path":["sites",1,"alternatives",3,"outputs",{"module_id":"total"},"values",2],"sheet":"Benefits"},{"cell":"F13","kind":"optional","path":["sites",2,"alternatives",0,"outputs",{"module_id":"total"},"values",0],"sheet":"Benefits"},{"cell":"G13","kind":"optional","path":["sites",2,"alternatives",0,"outputs",{"module_id":"total"},"values",1],"sheet":"Benefits"},{"cell":"H13","kind":"optional","path":["sites",2,"alternatives",0,"outputs",{"module_id":"total"},"values",2],"sheet":"Benefits"},{"cell":"F14","kind":"optional","path":["sites",2,"alternatives",1,"outputs",{"module_id":"total"},"values",0],"sheet":"Benefits"},{"cell":"G14","kind":"optional","path":["sites",2,"alternatives",1,"outputs",{"module_id":"total"},"values",1],"sheet":"Benefits"},{"cell":"H14","kind":"optional","path":["sites",2,"alternatives",1,"outputs",{"module_id":"total"},"values",2],"sheet":"Benefits"},{"cell":"D6","kind":"number","path":["sites",0,"alternatives",0,"costs","first_costs","construction"],"sheet":"Costs"},{"cell":"E6","kind":"number","path":["sites",0,"alternatives",0,"costs","first_costs","monitoring"],"sheet":"Costs"},{"cell":"F6","kind":"number","path":["sites",0,"alternatives",0,"costs","first_costs","adaptive_management"],"sheet":"Costs"},{"cell":"G6","kind":"number","path":["sites",0,"alternatives",0,"costs","construction_months"],"sheet":"Costs"},{"cell":"L6","kind":"optional","path":["sites",0,"alternatives",0,"costs","annual_override"],"sheet":"Costs"},{"cell":"D7","kind":"number","path":["sites",0,"alternatives",1,"costs","first_costs","construction"],"sheet":"Costs"},{"cell":"E7","kind":"number","path":["sites",0,"alternatives",1,"costs","first_costs","monitoring"],"sheet":"Costs"},{"cell":"F7","kind":"number","path":["sites",0,"alternatives",1,"costs","first_costs","adaptive_management"],"sheet":"Costs"},{"cell":"G7","kind":"number","path":["sites",0,"alternatives",1,"costs","construction_months"],"sheet":"Costs"},{"cell":"L7","kind":"optional","path":["sites",0,"alternatives",1,"costs","annual_override"],"sheet":"Costs"},{"cell":"D8","kind":"number","path":["sites",0,"alternatives",2,"costs","first_costs","construction"],"sheet":"Costs"},{"cell":"E8","kind":"number","path":["sites",0,"alternatives",2,"costs","first_costs","monitoring"],"sheet":"Costs"},{"cell":"F8","kind":"number","path":["sites",0,"alternatives",2,"costs","first_costs","adaptive_management"],"sheet":"Costs"},{"cell":"G8","kind":"number","path":["sites",0,"alternatives",2,"costs","construction_months"],"sheet":"Costs"},{"cell":"L8","kind":"optional","path":["sites",0,"alternatives",2,"costs","annual_override"],"sheet":"Costs"},{"cell":"D9","kind":"number","path":["sites",1,"alternatives",0,"costs","first_costs","construction"],"sheet":"Costs"},{"cell":"E9","kind":"number","path":["sites",1,"alternatives",0,"costs","first_costs","monitoring"],"sheet":"Costs"},{"cell":"F9","kind":"number","path":["sites",1,"alternatives",0,"costs","first_costs","adaptive_management"],"sheet":"Costs"},{"cell":"G9","kind":"number","path":["sites",1,"alternatives",0,"costs","construction_months"],"sheet":"Costs"},{"cell":"L9","kind":"optional","path":["sites",1,"alternatives",0,"costs","annual_override"],"sheet":"Costs"},{"cell":"D10","kind":"number","path":["sites",1,"alternatives",1,"costs","first_costs","construction"],"sheet":"Costs"},{"cell":"E10","kind":"number","path":["sites",1,"alternatives",1,"costs","first_costs","monitoring"],"sheet":"Costs"},{"cell":"F10","kind":"number","path":["sites",1,"alternatives",1,"costs","first_costs","adaptive_management"],"sheet":"Costs"},{"cell":"G10","kind":"number","path":["sites",1,"alternatives",1,"costs","construction_months"],"sheet":"Costs"},{"cell":"L10","kind":"optional","path":["sites",1,"alternatives",1,"costs","annual_override"],"sheet":"Costs"},{"cell":"D11","kind":"number","path":["sites",1,"alternatives",2,"costs","first_costs","construction"],"sheet":"Costs"},{"cell":"E11","kind":"number","path":["sites",1,"alternatives",2,"costs","first_costs","monitoring"],"sheet":"Costs"},{"cell":"F11","kind":"number","path":["sites",1,"alternatives",2,"costs","first_costs","adaptive_management"],"sheet":"Costs"},{"cell":"G11","kind":"number","path":["sites",1,"alternatives",2,"costs","construction_months"],"sheet":"Costs"},{"cell":"L11","kind":"optional","path":["sites",1,"alternatives",2,"costs","annual_override"],"sheet":"Costs"},{"cell":"D12","kind":"number","path":["sites",1,"alternatives",3,"costs","first_costs","construction"],"sheet":"Costs"},{"cell":"E12","kind":"number","path":["sites",1,"alternatives",3,"costs","first_costs","monitoring"],"sheet":"Costs"},{"cell":"F12","kind":"number","path":["sites",1,"alternatives",3,"costs","first_costs","adaptive_management"],"sheet":"Costs"},{"cell":"G12","kind":"number","path":["sites",1,"alternatives",3,"costs","construction_months"],"sheet":"Costs"},{"cell":"L12","kind":"optional","path":["sites",1,"alternatives",3,"costs","annual_override"],"sheet":"Costs"},{"cell":"D13","kind":"number","path":["sites",2,"alternatives",0,"costs","first_costs","construction"],"sheet":"Costs"},{"cell":"E13","kind":"number","path":["sites",2,"alternatives",0,"costs","first_costs","monitoring"],"sheet":"Costs"},{"cell":"F13","kind":"number","path":["sites",2,"alternatives",0,"costs","first_costs","adaptive_management"],"sheet":"Costs"},{"cell":"G13","kind":"number","path":["sites",2,"alternatives",0,"costs","construction_months"],"sheet":"Costs"},{"cell":"L13","kind":"optional","path":["sites",2,"alternatives",0,"costs","annual_override"],"sheet":"Costs"},{"cell":"D14","kind":"number","path":["sites",2,"alternatives",1,"costs","first_costs","construction"],"sheet":"Costs"},{"cell":"E14","kind":"number","path":["sites",2,"alternatives",1,"costs","first_costs","monitoring"],"sheet":"Costs"},{"cell":"F14","kind":"number","path":["sites",2,"alternatives",1,"costs","first_costs","adaptive_management"],"sheet":"Costs"},{"cell":"G14","kind":"number","path":["sites",2,"alternatives",1,"costs","construction_months"],"sheet":"Costs"},{"cell":"L14","kind":"optional","path":["sites",2,"alternatives",1,"costs","annual_override"],"sheet":"Costs"},{"cell":"F5","kind":"number","path":["sites",0,"alternatives",1,"costs","recurring",0,"amount"],"sheet":"OMRRR"},{"cell":"K5","kind":"int","path":["sites",0,"alternatives",1,"costs","recurring",0,"every_years"],"sheet":"OMRRR"},{"cell":"L5","kind":"optional_int","path":["sites",0,"alternatives",1,"costs","recurring",0,"first_year"],"sheet":"OMRRR"},{"cell":"M5","kind":"optional_int","path":["sites",0,"alternatives",1,"costs","recurring",0,"last_year"],"sheet":"OMRRR"},{"cell":"G6","kind":"number","path":["sites",0,"alternatives",2,"costs","recurring",0,"percent"],"sheet":"OMRRR"},{"cell":"K6","kind":"int","path":["sites",0,"alternatives",2,"costs","recurring",0,"every_years"],"sheet":"OMRRR"},{"cell":"L6","kind":"optional_int","path":["sites",0,"alternatives",2,"costs","recurring",0,"first_year"],"sheet":"OMRRR"},{"cell":"M6","kind":"optional_int","path":["sites",0,"alternatives",2,"costs","recurring",0,"last_year"],"sheet":"OMRRR"},{"cell":"I7","kind":"number","path":["sites",0,"alternatives",2,"costs","recurring",1,"unit_rate"],"sheet":"OMRRR"},{"cell":"J7","kind":"number","path":["sites",0,"alternatives",2,"costs","recurring",1,"quantity"],"sheet":"OMRRR"},{"cell":"K7","kind":"int","path":["sites",0,"alternatives",2,"costs","recurring",1,"every_years"],"sheet":"OMRRR"},{"cell":"L7","kind":"optional_int","path":["sites",0,"alternatives",2,"costs","recurring",1,"first_year"],"sheet":"OMRRR"},{"cell":"M7","kind":"optional_int","path":["sites",0,"alternatives",2,"costs","recurring",1,"last_year"],"sheet":"OMRRR"},{"cell":"F8","kind":"number","path":["sites",2,"alternatives",1,"costs","recurring",0,"amount"],"sheet":"OMRRR"},{"cell":"K8","kind":"int","path":["sites",2,"alternatives",1,"costs","recurring",0,"every_years"],"sheet":"OMRRR"},{"cell":"L8","kind":"optional_int","path":["sites",2,"alternatives",1,"costs","recurring",0,"first_year"],"sheet":"OMRRR"},{"cell":"M8","kind":"optional_int","path":["sites",2,"alternatives",1,"costs","recurring",0,"last_year"],"sheet":"OMRRR"},{"cell":"C5","exported":"A1","kind":"rec","path":["decisions","sites","A","recommended_alt_id"],"sheet":"Sites"},{"cell":"C6","exported":"B3","kind":"rec","path":["decisions","sites","B","recommended_alt_id"],"sheet":"Sites"},{"cell":"C7","exported":"C1","kind":"rec","path":["decisions","sites","C","recommended_alt_id"],"sheet":"Sites"},{"cell":"AA12","kind":"final","path":["@final",12],"sheet":"Watershed plans"},{"cell":"AA13","kind":"final","path":["@final",13],"sheet":"Watershed plans"},{"cell":"AA14","kind":"final","path":["@final",14],"sheet":"Watershed plans"},{"cell":"AA15","kind":"final","path":["@final",15],"sheet":"Watershed plans"},{"cell":"AA16","kind":"final","path":["@final",16],"sheet":"Watershed plans"},{"cell":"AA17","kind":"final","path":["@final",17],"sheet":"Watershed plans"},{"cell":"AA18","kind":"final","path":["@final",18],"sheet":"Watershed plans"},{"cell":"AA19","kind":"final","path":["@final",19],"sheet":"Watershed plans"},{"cell":"K50","kind":"text","path":["@worth",0],"sheet":"Watershed summary"},{"cell":"L50","kind":"text","path":["@why",0],"sheet":"Watershed summary"},{"cell":"K51","kind":"text","path":["@worth",1],"sheet":"Watershed summary"},{"cell":"L51","kind":"text","path":["@why",1],"sheet":"Watershed summary"},{"cell":"K52","kind":"text","path":["@worth",2],"sheet":"Watershed summary"},{"cell":"L52","kind":"text","path":["@why",2],"sheet":"Watershed summary"},{"cell":"K53","kind":"text","path":["@worth",3],"sheet":"Watershed summary"},{"cell":"L53","kind":"text","path":["@why",3],"sheet":"Watershed summary"},{"cell":"K54","kind":"text","path":["@worth",4],"sheet":"Watershed summary"},{"cell":"L54","kind":"text","path":["@why",4],"sheet":"Watershed summary"},{"cell":"K55","kind":"text","path":["@worth",5],"sheet":"Watershed summary"},{"cell":"L55","kind":"text","path":["@why",5],"sheet":"Watershed summary"},{"cell":"K56","kind":"text","path":["@worth",6],"sheet":"Watershed summary"},{"cell":"L56","kind":"text","path":["@why",6],"sheet":"Watershed summary"},{"cell":"K57","kind":"text","path":["@worth",7],"sheet":"Watershed summary"},{"cell":"L57","kind":"text","path":["@why",7],"sheet":"Watershed summary"},{"cell":"K58","kind":"text","path":["@worth",8],"sheet":"Watershed summary"},{"cell":"L58","kind":"text","path":["@why",8],"sheet":"Watershed summary"},{"cell":"K59","kind":"text","path":["@worth",9],"sheet":"Watershed summary"},{"cell":"L59","kind":"text","path":["@why",9],"sheet":"Watershed summary"},{"cell":"K60","kind":"text","path":["@worth",10],"sheet":"Watershed summary"},{"cell":"L60","kind":"text","path":["@why",10],"sheet":"Watershed summary"},{"cell":"K61","kind":"text","path":["@worth",11],"sheet":"Watershed summary"},{"cell":"L61","kind":"text","path":["@why",11],"sheet":"Watershed summary"},{"cell":"K62","kind":"text","path":["@worth",12],"sheet":"Watershed summary"},{"cell":"L62","kind":"text","path":["@why",12],"sheet":"Watershed summary"},{"cell":"K63","kind":"text","path":["@worth",13],"sheet":"Watershed summary"},{"cell":"L63","kind":"text","path":["@why",13],"sheet":"Watershed summary"},{"cell":"K64","kind":"text","path":["@worth",14],"sheet":"Watershed summary"},{"cell":"L64","kind":"text","path":["@why",14],"sheet":"Watershed summary"},{"cell":"K65","kind":"text","path":["@worth",15],"sheet":"Watershed summary"},{"cell":"L65","kind":"text","path":["@why",15],"sheet":"Watershed summary"},{"cell":"K66","kind":"text","path":["@worth",16],"sheet":"Watershed summary"},{"cell":"L66","kind":"text","path":["@why",16],"sheet":"Watershed summary"},{"cell":"K67","kind":"text","path":["@worth",17],"sheet":"Watershed summary"},{"cell":"L67","kind":"text","path":["@why",17],"sheet":"Watershed summary"},{"cell":"K68","kind":"text","path":["@worth",18],"sheet":"Watershed summary"},{"cell":"L68","kind":"text","path":["@why",18],"sheet":"Watershed summary"},{"cell":"K69","kind":"text","path":["@worth",19],"sheet":"Watershed summary"},{"cell":"L69","kind":"text","path":["@why",19],"sheet":"Watershed summary"},{"cell":"K70","kind":"text","path":["@worth",20],"sheet":"Watershed summary"},{"cell":"L70","kind":"text","path":["@why",20],"sheet":"Watershed summary"},{"cell":"K71","kind":"text","path":["@worth",21],"sheet":"Watershed summary"},{"cell":"L71","kind":"text","path":["@why",21],"sheet":"Watershed summary"},{"cell":"K72","kind":"text","path":["@worth",22],"sheet":"Watershed summary"},{"cell":"L72","kind":"text","path":["@why",22],"sheet":"Watershed summary"},{"cell":"K73","kind":"text","path":["@worth",23],"sheet":"Watershed summary"},{"cell":"L73","kind":"text","path":["@why",23],"sheet":"Watershed summary"},{"cell":"K74","kind":"text","path":["@worth",24],"sheet":"Watershed summary"},{"cell":"L74","kind":"text","path":["@why",24],"sheet":"Watershed summary"},{"cell":"K75","kind":"text","path":["@worth",25],"sheet":"Watershed summary"},{"cell":"L75","kind":"text","path":["@why",25],"sheet":"Watershed summary"},{"cell":"K76","kind":"text","path":["@worth",26],"sheet":"Watershed summary"},{"cell":"L76","kind":"text","path":["@why",26],"sheet":"Watershed summary"},{"cell":"K77","kind":"text","path":["@worth",27],"sheet":"Watershed summary"},{"cell":"L77","kind":"text","path":["@why",27],"sheet":"Watershed summary"},{"cell":"K78","kind":"text","path":["@worth",28],"sheet":"Watershed summary"},{"cell":"L78","kind":"text","path":["@why",28],"sheet":"Watershed summary"},{"cell":"K79","kind":"text","path":["@worth",29],"sheet":"Watershed summary"},{"cell":"L79","kind":"text","path":["@why",29],"sheet":"Watershed summary"},{"cell":"K80","kind":"text","path":["@worth",30],"sheet":"Watershed summary"},{"cell":"L80","kind":"text","path":["@why",30],"sheet":"Watershed summary"},{"cell":"K81","kind":"text","path":["@worth",31],"sheet":"Watershed summary"},{"cell":"L81","kind":"text","path":["@why",31],"sheet":"Watershed summary"},{"cell":"K82","kind":"text","path":["@worth",32],"sheet":"Watershed summary"},{"cell":"L82","kind":"text","path":["@why",32],"sheet":"Watershed summary"},{"cell":"K83","kind":"text","path":["@worth",33],"sheet":"Watershed summary"},{"cell":"L83","kind":"text","path":["@why",33],"sheet":"Watershed summary"},{"cell":"K84","kind":"text","path":["@worth",34],"sheet":"Watershed summary"},{"cell":"L84","kind":"text","path":["@why",34],"sheet":"Watershed summary"},{"cell":"K85","kind":"text","path":["@worth",35],"sheet":"Watershed summary"},{"cell":"L85","kind":"text","path":["@why",35],"sheet":"Watershed summary"},{"cell":"K86","kind":"text","path":["@worth",36],"sheet":"Watershed summary"},{"cell":"L86","kind":"text","path":["@why",36],"sheet":"Watershed summary"},{"cell":"K87","kind":"text","path":["@worth",37],"sheet":"Watershed summary"},{"cell":"L87","kind":"text","path":["@why",37],"sheet":"Watershed summary"},{"cell":"K88","kind":"text","path":["@worth",38],"sheet":"Watershed summary"},{"cell":"L88","kind":"text","path":["@why",38],"sheet":"Watershed summary"},{"cell":"K89","kind":"text","path":["@worth",39],"sheet":"Watershed summary"},{"cell":"L89","kind":"text","path":["@why",39],"sheet":"Watershed summary"},{"cell":"B93","kind":"tsp","path":["@tsp"],"sheet":"Watershed summary"}],"liveWatershed":true,"planBits":[4,6],"planRowKeys":{"12":"","13":"C=C1","14":"B=B3","15":"B=B3;C=C1","16":"A=A1","17":"A=A1;C=C1","18":"A=A1;B=B3","19":"A=A1;B=B3;C=C1"},"planSites":["A","B","C"],"projectDigest":"f4d289ead17a","schemaVersion":2}
